Workbook

Sheet Acumulado
A1: Sigmaseg S.A. de C.V. | B1: Anual P | C1: Anual R | D1: Anual D | E1: Ene P | F1: Enero | G1: Ene D | H1: Feb P | I1: Febrero | J1: Feb D | K1: Mar P | L1: Marzo | M1: Mar D | N1: Abr P | O1: Abril | P1: Abr D | Q1: May P | R1: Mayo | S1: May D | T1: Jun P | U1: Junio | V1: Jun D | W1: Jul P | X1: Julio | Y1: Jul D | Z1: Ago P | AA1: Agosto | AB1: Ago D | AC1: Sep P | AD1: Septiembre | AE1: Sep D | AF1: Oct P | AG1: Octubre | AH1: Oct D | AI1: Nov P | AJ1: Noviembre | AK1: Nov D | AL1: Dic P | AM1: Diciembre | AN1: Dic D
A3: Utilidad Bruta | B3: =B5-B10+B49-B54 -> 0 | C3: =C5-C10+C49-C54 -> 0 | D3: =C3-B3 -> 0 | E3: =E5-E10+E49-E54 -> 0 | F3: =F5-F10+F49-F54 -> 0 | G3: =F3-E3 -> 0 | H3: =H5-H10+H49-H54 -> 0 | I3: =I5-I10+I49-I54 -> 0 | J3: =I3-H3 -> 0 | K3: =K5-K10+K49-K54 -> 0 | L3: =L5-L10+L49-L54 -> 0 | M3: =L3-K3 -> 0 | N3: =N5-N10+N49-N54 -> 0 | O3: =O5-O10+O49-O54 -> 0 | P3: =O3-N3 -> 0 | Q3: =Q5-Q10+Q49-Q54 -> 0 | R3: =R5-R10+R49-R54 -> 0 | S3: =R3-Q3 -> 0 | T3: =T5-T10+T49-T54 -> 0 | U3: =U5-U10+U49-U54 -> 0 | V3: =U3-T3 -> 0 | W3: =W5-W10+W49-W54 -> 0 | X3: =X5-X10+X49-X54 -> 0 | Y3: =X3-W3 -> 0 | Z3: =Z5-Z10+Z49-Z54 -> 0 | AA3: =AA5-AA10+AA49-AA54 -> 0 | AB3: =AA3-Z3 -> 0 | AC3: =AC5-AC10+AC49-AC54 -> 0 | AD3: =AD5-AD10+AD49-AD54 -> 0 | AE3: =AD3-AC3 -> 0 | AF3: =AF5-AF10+AF49-AF54 -> 0 | AG3: =AG5-AG10+AG49-AG54 -> 0 | AH3: =AG3-AF3 -> 0 | AI3: =AI5-AI10+AI49-AI54 -> 0 | AJ3: =AJ5-AJ10+AJ49-AJ54 -> 0 | AK3: =AJ3-AI3 -> 0 | AL3: =AL5-AL10+AL49-AL54 -> 0 | AM3: =AM5-AM10+AM49-AM54 -> 0 | AN3: =AM3-AL3 -> 0
A5: Total de Ingresos | B5: =SUM(B6:B8) -> 0 | C5: =SUM(C6:C8) -> 0 | D5: =C5-B5 -> 0 | E5: =SUM(E6:E8) -> 0 | F5: =SUM(F6:F8) -> 0 | G5: =F5-E5 -> 0 | H5: =SUM(H6:H8) -> 0 | I5: =SUM(I6:I8) -> 0 | J5: =SUM(J6:J8) -> 0 | K5: =SUM(K6:K8) -> 0 | L5: =SUM(L6:L8) -> 0 | M5: =SUM(M6:M8) -> 0 | N5: =SUM(N6:N8) -> 0 | O5: =SUM(O6:O8) -> 0 | ... AN5: =SUM(AN6:AN8) -> 0
A6: A01 Seguridad | B6: =SUM(IF(MONTH(TODAY())>1,E6,0), IF(MONTH(TODAY())>2,H6,0), IF(MONTH(TODAY())>3,K6,0), IF(MONTH(TODAY())>4,N6,0), IF(MONTH(TODAY())>5,Q6,0), IF(MONTH(TODAY())>6,T6,0), IF(MONTH(TODAY())>7,W6,0), IF(MONTH(TODAY())>8,Z6,0), IF(MONTH(TODAY())>9,AC6,0), IF(MONTH(TODAY())>10,AF6,0), IF(MONTH(TODAY())>11,AI6,0), IF(MONTH(TODAY())>12,AL6,0)) -> 0 | C6: =SUM(IF(MONTH(TODAY())>1,F6,0), IF(MONTH(TODAY())>2,I6,0), IF(MONTH(TODAY())>3,L6,0), IF(MONTH(TODAY())>4,O6,0), IF(MONTH(TODAY())>5,R6,0), IF(MONTH(TODAY())>6,U6,0), IF(MONTH(TODAY())>7,X6,0), IF(MONTH(TODAY())>8,AA6,0), IF(MONTH(TODAY())>9,AD6,0), IF(MONTH(TODAY())>10,AG6,0), IF(MONTH(TODAY())>11,AJ6,0), IF(MONTH(TODAY())>12,AM6,0)) -> 0 | D6: =C6-B6 -> 0 | E6: {=IFERROR(SUMIF(Consolidado!$C$3:$C63, $A6, INDEX(Consolidado!$E$3:$P$100, , MATCH(E$1, Consolidado!$E$2:$P$2, 0))), "")} | F6: =IFERROR( LET( hoja, LEFT(F$1,3)&"R", fila, MATCH( RIGHT($A6, LEN($A6)-4), INDIRECT(hoja&"!$A:$A"), 0 ), columna, MATCH( "Totales", INDIRECT(hoja&"!$6:$6"), 0 ), valor, INDEX( INDIRECT(hoja&"!$A:$ZZ"), fila, columna ), IF(valor="-", "", valor) ), "") | G6: =F6-E6 -> 0 | H6: {=IFERROR(SUMIF(Consolidado!$C$3:$C63, $A6, INDEX(Consolidado!$E$3:$P$100, , MATCH(H$1, Consolidado!$E$2:$P$2, 0))), "")} | I6: =IFERROR( LET( hoja, LEFT(I$1,3)&"R", fila, MATCH( RIGHT($A6, LEN($A6)-4), INDIRECT(hoja&"!$A:$A"), 0 ), columna, MATCH( "Totales", INDIRECT(hoja&"!$6:$6"), 0 ), valor, INDEX( INDIRECT(hoja&"!$A:$ZZ"), fila, columna ), IF(valor="-", "", valor) ), "") | J6: =I6-H6 -> 0 | K6: {=IFERROR(SUMIF(Consolidado!$C$3:$C63, $A6, INDEX(Consolidado!$E$3:$P$100, , MATCH(K$1, Consolidado!$E$2:$P$2, 0))), "")} | L6: =IFERROR( LET( hoja, LEFT(L$1,3)&"R", fila, MATCH( RIGHT($A6, LEN($A6)-4), INDIRECT(hoja&"!$A:$A"), 0 ), columna, MATCH( "Totales", INDIRECT(hoja&"!$6:$6"), 0 ), valor, INDEX( INDIRECT(hoja&"!$A:$ZZ"), fila, columna ), IF(valor="-", "", valor) ), "") | M6: =L6-K6 -> 0 | N6: {=IFERROR(SUMIF(Consolidado!$C$3:$C63, $A6, INDEX(Consolidado!$E$3:$P$100, , MATCH(N$1, Consolidado!$E$2:$P$2, 0))), "")} | O6: =IFERROR( LET( hoja, LEFT(O$1,3)&"R", fila, MATCH( RIGHT($A6, LEN($A6)-4), INDIRECT(hoja&"!$A:$A"), 0 ), columna, MATCH( "Totales", INDIRECT(hoja&"!$6:$6"), 0 ), valor, INDEX( INDIRECT(hoja&"!$A:$ZZ"), fila, columna ), IF(valor="-", "", valor) ), "") | P6: =O6-N6 -> 0 | Q6: {=IFERROR(SUMIF(Consolidado!$C$3:$C63, $A6, INDEX(Consolidado!$E$3:$P$100, , MATCH(Q$1, Consolidado!$E$2:$P$2, 0))), "")} | R6: =IFERROR( LET( hoja, LEFT(R$1,3)&"R", fila, MATCH( RIGHT($A6, LEN($A6)-4), INDIRECT(hoja&"!$A:$A"), 0 ), columna, MATCH( "Totales", INDIRECT(hoja&"!$6:$6"), 0 ), valor, INDEX( INDIRECT(hoja&"!$A:$ZZ"), fila, columna ), IF(valor="-", "", valor) ), "") | S6: =R6-Q6 -> 0 | T6: {=IFERROR(SUMIF(Consolidado!$C$3:$C63, $A6, INDEX(Consolidado!$E$3:$P$100, , MATCH(T$1, Consolidado!$E$2:$P$2, 0))), "")} | U6: =IFERROR( LET( hoja, LEFT(U$1,3)&"R", fila, MATCH( RIGHT($A6, LEN($A6)-4), INDIRECT(hoja&"!$A:$A"), 0 ), columna, MATCH( "Totales", INDIRECT(hoja&"!$6:$6"), 0 ), valor, INDEX( INDIRECT(hoja&"!$A:$ZZ"), fila, columna ), IF(valor="-", "", valor) ), "") | V6: =U6-T6 -> 0 | W6: {=IFERROR(SUMIF(Consolidado!$C$3:$C63, $A6, INDEX(Consolidado!$E$3:$P$100, , MATCH(W$1, Consolidado!$E$2:$P$2, 0))), "")} | X6: =IFERROR( LET( hoja, LEFT(X$1,3)&"R", fila, MATCH( RIGHT($A6, LEN($A6)-4), INDIRECT(hoja&"!$A:$A"), 0 ), columna, MATCH( "Totales", INDIRECT(hoja&"!$6:$6"), 0 ), valor, INDEX( INDIRECT(hoja&"!$A:$ZZ"), fila, columna ), IF(valor="-", "", valor) ), "") | Y6: =X6-W6 -> 0 | Z6: {=IFERROR(SUMIF(Consolidado!$C$3:$C63, $A6, INDEX(Consolidado!$E$3:$P$100, , MATCH(Z$1, Consolidado!$E$2:$P$2, 0))), "")} | AA6: =IFERROR( LET( hoja, LEFT(AA$1,3)&"R", fila, MATCH( RIGHT($A6, LEN($A6)-4), INDIRECT(hoja&"!$A:$A"), 0 ), columna, MATCH( "Totales", INDIRECT(hoja&"!$6:$6"), 0 ), valor, INDEX( INDIRECT(hoja&"!$A:$ZZ"), fila, columna ), IF(valor="-", "", valor) ), "") | AB6: =AA6-Z6 -> 0 | AC6: {=IFERROR(SUMIF(Consolidado!$C$3:$C63, $A6, INDEX(Consolidado!$E$3:$P$100, , MATCH(AC$1, Consolidado!$E$2:$P$2, 0))), "")} | AD6: =IFERROR( LET( hoja, LEFT(AD$1,3)&"R", fila, MATCH( RIGHT($A6, LEN($A6)-4), INDIRECT(hoja&"!$A:$A"), 0 ), columna, MATCH( "Totales", INDIRECT(hoja&"!$6:$6"), 0 ), valor, INDEX( INDIRECT(hoja&"!$A:$ZZ"), fila, columna ), IF(valor="-", "", valor) ), "") | AE6: =AD6-AC6 -> 0 | AF6: {=IFERROR(SUMIF(Consolidado!$C$3:$C63, $A6, INDEX(Consolidado!$E$3:$P$100, , MATCH(AF$1, Consolidado!$E$2:$P$2, 0))), "")} | AG6: =IFERROR( LET( hoja, LEFT(AG$1,3)&"R", fila, MATCH( RIGHT($A6, LEN($A6)-4), INDIRECT(hoja&"!$A:$A"), 0 ), columna, MATCH( "Totales", INDIRECT(hoja&"!$6:$6"), 0 ), valor, INDEX( INDIRECT(hoja&"!$A:$ZZ"), fila, columna ), IF(valor="-", "", valor) ), "") | AH6: =AG6-AF6 -> 0 | AI6: {=IFERROR(SUMIF(Consolidado!$C$3:$C63, $A6, INDEX(Consolidado!$E$3:$P$100, , MATCH(AI$1, Consolidado!$E$2:$P$2, 0))), "")} | AJ6: =IFERROR( LET( hoja, LEFT(AJ$1,3)&"R", fila, MATCH( RIGHT($A6, LEN($A6)-4), INDIRECT(hoja&"!$A:$A"), 0 ), columna, MATCH( "Totales", INDIRECT(hoja&"!$6:$6"), 0 ), valor, INDEX( INDIRECT(hoja&"!$A:$ZZ"), fila, columna ), IF(valor="-", "", valor) ), "") | AK6: =AJ6-AI6 -> 0 | AL6: {=IFERROR(SUMIF(Consolidado!$C$3:$C63, $A6, INDEX(Consolidado!$E$3:$P$100, , MATCH(AL$1, Consolidado!$E$2:$P$2, 0))), "")} | AM6: =IFERROR( LET( hoja, LEFT(AM$1,3)&"R", fila, MATCH( RIGHT($A6, LEN($A6)-4), INDIRECT(hoja&"!$A:$A"), 0 ), columna, MATCH( "Totales", INDIRECT(hoja&"!$6:$6"), 0 ), valor, INDEX( INDIRECT(hoja&"!$A:$ZZ"), fila, columna ), IF(valor="-", "", valor) ), "") | AN6: =AM6-AL6 -> 0
A7: A02 Monitoreo | B7: =SUM(IF(MONTH(TODAY())>1,E7,0), IF(MONTH(TODAY())>2,H7,0), IF(MONTH(TODAY())>3,K7,0), IF(MONTH(TODAY())>4,N7,0), IF(MONTH(TODAY())>5,Q7,0), IF(MONTH(TODAY())>6,T7,0), IF(MONTH(TODAY())>7,W7,0), IF(MONTH(TODAY())>8,Z7,0), IF(MONTH(TODAY())>9,AC7,0), IF(MONTH(TODAY())>10,AF7,0), IF(MONTH(TODAY())>11,AI7,0), IF(MONTH(TODAY())>12,AL7,0)) -> 0 | C7: =SUM(IF(MONTH(TODAY())>1,F7,0), IF(MONTH(TODAY())>2,I7,0), IF(MONTH(TODAY())>3,L7,0), IF(MONTH(TODAY())>4,O7,0), IF(MONTH(TODAY())>5,R7,0), IF(MONTH(TODAY())>6,U7,0), IF(MONTH(TODAY())>7,X7,0), IF(MONTH(TODAY())>8,AA7,0), IF(MONTH(TODAY())>9,AD7,0), IF(MONTH(TODAY())>10,AG7,0), IF(MONTH(TODAY())>11,AJ7,0), IF(MONTH(TODAY())>12,AM7,0)) -> 0 | D7: =C7-B7 -> 0 | E7: {=IFERROR(SUMIF(Consolidado!$C$3:$C$100, $A7, INDEX(Consolidado!$E$3:$P$100, , MATCH(E$1, Consolidado!$E$2:$P$2, 0))), "")} | F7: =IFERROR( LET( hoja, LEFT(F$1,3)&"R", fila, MATCH( RIGHT($A7, LEN($A7)-4), INDIRECT(hoja&"!$A:$A"), 0 ), columna, MATCH( "Totales", INDIRECT(hoja&"!$6:$6"), 0 ), valor, INDEX( INDIRECT(hoja&"!$A:$ZZ"), fila, columna ), IF(valor="-", "", valor) ), "") | G7: =F7-E7 -> 0 | H7: {=IFERROR(SUMIF(Consolidado!$C$3:$C$100, $A7, INDEX(Consolidado!$E$3:$P$100, , MATCH(H$1, Consolidado!$E$2:$P$2, 0))), "")} | I7: =IFERROR( LET( hoja, LEFT(I$1,3)&"R", fila, MATCH( RIGHT($A7, LEN($A7)-4), INDIRECT(hoja&"!$A:$A"), 0 ), columna, MATCH( "Totales", INDIRECT(hoja&"!$6:$6"), 0 ), valor, INDEX( INDIRECT(hoja&"!$A:$ZZ"), fila, columna ), IF(valor="-", "", valor) ), "") | J7: =I7-H7 -> 0 | K7: {=IFERROR(SUMIF(Consolidado!$C$3:$C$100, $A7, INDEX(Consolidado!$E$3:$P$100, , MATCH(K$1, Consolidado!$E$2:$P$2, 0))), "")} | L7: =IFERROR( LET( hoja, LEFT(L$1,3)&"R", fila, MATCH( RIGHT($A7, LEN($A7)-4), INDIRECT(hoja&"!$A:$A"), 0 ), columna, MATCH( "Totales", INDIRECT(hoja&"!$6:$6"), 0 ), valor, INDEX( INDIRECT(hoja&"!$A:$ZZ"), fila, columna ), IF(valor="-", "", valor) ), "") | M7: =L7-K7 -> 0 | N7: {=IFERROR(SUMIF(Consolidado!$C$3:$C$100, $A7, INDEX(Consolidado!$E$3:$P$100, , MATCH(N$1, Consolidado!$E$2:$P$2, 0))), "")} | O7: =IFERROR( LET( hoja, LEFT(O$1,3)&"R", fila, MATCH( RIGHT($A7, LEN($A7)-4), INDIRECT(hoja&"!$A:$A"), 0 ), columna, MATCH( "Totales", INDIRECT(hoja&"!$6:$6"), 0 ), valor, INDEX( INDIRECT(hoja&"!$A:$ZZ"), fila, columna ), IF(valor="-", "", valor) ), "") | P7: =O7-N7 -> 0 | Q7: {=IFERROR(SUMIF(Consolidado!$C$3:$C$100, $A7, INDEX(Consolidado!$E$3:$P$100, , MATCH(Q$1, Consolidado!$E$2:$P$2, 0))), "")} | R7: =IFERROR( LET( hoja, LEFT(R$1,3)&"R", fila, MATCH( RIGHT($A7, LEN($A7)-4), INDIRECT(hoja&"!$A:$A"), 0 ), columna, MATCH( "Totales", INDIRECT(hoja&"!$6:$6"), 0 ), valor, INDEX( INDIRECT(hoja&"!$A:$ZZ"), fila, columna ), IF(valor="-", "", valor) ), "") | S7: =R7-Q7 -> 0 | T7: {=IFERROR(SUMIF(Consolidado!$C$3:$C$100, $A7, INDEX(Consolidado!$E$3:$P$100, , MATCH(T$1, Consolidado!$E$2:$P$2, 0))), "")} | U7: =IFERROR( LET( hoja, LEFT(U$1,3)&"R", fila, MATCH( RIGHT($A7, LEN($A7)-4), INDIRECT(hoja&"!$A:$A"), 0 ), columna, MATCH( "Totales", INDIRECT(hoja&"!$6:$6"), 0 ), valor, INDEX( INDIRECT(hoja&"!$A:$ZZ"), fila, columna ), IF(valor="-", "", valor) ), "") | V7: =U7-T7 -> 0 | W7: {=IFERROR(SUMIF(Consolidado!$C$3:$C$100, $A7, INDEX(Consolidado!$E$3:$P$100, , MATCH(W$1, Consolidado!$E$2:$P$2, 0))), "")} | X7: =IFERROR( LET( hoja, LEFT(X$1,3)&"R", fila, MATCH( RIGHT($A7, LEN($A7)-4), INDIRECT(hoja&"!$A:$A"), 0 ), columna, MATCH( "Totales", INDIRECT(hoja&"!$6:$6"), 0 ), valor, INDEX( INDIRECT(hoja&"!$A:$ZZ"), fila, columna ), IF(valor="-", "", valor) ), "") | Y7: =X7-W7 -> 0 | Z7: {=IFERROR(SUMIF(Consolidado!$C$3:$C$100, $A7, INDEX(Consolidado!$E$3:$P$100, , MATCH(Z$1, Consolidado!$E$2:$P$2, 0))), "")} | AA7: =IFERROR( LET( hoja, LEFT(AA$1,3)&"R", fila, MATCH( RIGHT($A7, LEN($A7)-4), INDIRECT(hoja&"!$A:$A"), 0 ), columna, MATCH( "Totales", INDIRECT(hoja&"!$6:$6"), 0 ), valor, INDEX( INDIRECT(hoja&"!$A:$ZZ"), fila, columna ), IF(valor="-", "", valor) ), "") | AB7: =AA7-Z7 -> 0 | AC7: {=IFERROR(SUMIF(Consolidado!$C$3:$C$100, $A7, INDEX(Consolidado!$E$3:$P$100, , MATCH(AC$1, Consolidado!$E$2:$P$2, 0))), "")} | AD7: =IFERROR( LET( hoja, LEFT(AD$1,3)&"R", fila, MATCH( RIGHT($A7, LEN($A7)-4), INDIRECT(hoja&"!$A:$A"), 0 ), columna, MATCH( "Totales", INDIRECT(hoja&"!$6:$6"), 0 ), valor, INDEX( INDIRECT(hoja&"!$A:$ZZ"), fila, columna ), IF(valor="-", "", valor) ), "") | AE7: =AD7-AC7 -> 0 | AF7: {=IFERROR(SUMIF(Consolidado!$C$3:$C$100, $A7, INDEX(Consolidado!$E$3:$P$100, , MATCH(AF$1, Consolidado!$E$2:$P$2, 0))), "")} | AG7: =IFERROR( LET( hoja, LEFT(AG$1,3)&"R", fila, MATCH( RIGHT($A7, LEN($A7)-4), INDIRECT(hoja&"!$A:$A"), 0 ), columna, MATCH( "Totales", INDIRECT(hoja&"!$6:$6"), 0 ), valor, INDEX( INDIRECT(hoja&"!$A:$ZZ"), fila, columna ), IF(valor="-", "", valor) ), "") | AH7: =AG7-AF7 -> 0 | AI7: {=IFERROR(SUMIF(Consolidado!$C$3:$C$100, $A7, INDEX(Consolidado!$E$3:$P$100, , MATCH(AI$1, Consolidado!$E$2:$P$2, 0))), "")} | AJ7: =IFERROR( LET( hoja, LEFT(AJ$1,3)&"R", fila, MATCH( RIGHT($A7, LEN($A7)-4), INDIRECT(hoja&"!$A:$A"), 0 ), columna, MATCH( "Totales", INDIRECT(hoja&"!$6:$6"), 0 ), valor, INDEX( INDIRECT(hoja&"!$A:$ZZ"), fila, columna ), IF(valor="-", "", valor) ), "") | AK7: =AJ7-AI7 -> 0 | AL7: {=IFERROR(SUMIF(Consolidado!$C$3:$C$100, $A7, INDEX(Consolidado!$E$3:$P$100, , MATCH(AL$1, Consolidado!$E$2:$P$2, 0))), "")} | AM7: =IFERROR( LET( hoja, LEFT(AM$1,3)&"R", fila, MATCH( RIGHT($A7, LEN($A7)-4), INDIRECT(hoja&"!$A:$A"), 0 ), columna, MATCH( "Totales", INDIRECT(hoja&"!$6:$6"), 0 ), valor, INDEX( INDIRECT(hoja&"!$A:$ZZ"), fila, columna ), IF(valor="-", "", valor) ), "") | AN7: =AM7-AL7 -> 0
B8: =SUM(IF(MONTH(TODAY())>1,E8,0), IF(MONTH(TODAY())>2,H8,0), IF(MONTH(TODAY())>3,K8,0), IF(MONTH(TODAY())>4,N8,0), IF(MONTH(TODAY())>5,Q8,0), IF(MONTH(TODAY())>6,T8,0), IF(MONTH(TODAY())>7,W8,0), IF(MONTH(TODAY())>8,Z8,0), IF(MONTH(TODAY())>9,AC8,0), IF(MONTH(TODAY())>10,AF8,0), IF(MONTH(TODAY())>11,AI8,0), IF(MONTH(TODAY())>12,AL8,0)) -> 0 | C8: =SUM(IF(MONTH(TODAY())>1,F8,0), IF(MONTH(TODAY())>2,I8,0), IF(MONTH(TODAY())>3,L8,0), IF(MONTH(TODAY())>4,O8,0), IF(MONTH(TODAY())>5,R8,0), IF(MONTH(TODAY())>6,U8,0), IF(MONTH(TODAY())>7,X8,0), IF(MONTH(TODAY())>8,AA8,0), IF(MONTH(TODAY())>9,AD8,0), IF(MONTH(TODAY())>10,AG8,0), IF(MONTH(TODAY())>11,AJ8,0), IF(MONTH(TODAY())>12,AM8,0)) -> 0 | D8: =C8-B8 -> 0 | E8: {=IFERROR(SUMIF(Consolidado!$C$3:$C$100, $A8, INDEX(Consolidado!$E$3:$P$100, , MATCH(E$1, Consolidado!$E$2:$P$2, 0))), "")} | F8: =IFERROR( LET( hoja, LEFT(F$1,3)&"R", fila, MATCH( RIGHT($A8, LEN($A8)-4), INDIRECT(hoja&"!$A:$A"), 0 ), columna, MATCH( "Totales", INDIRECT(hoja&"!$6:$6"), 0 ), valor, INDEX( INDIRECT(hoja&"!$A:$ZZ"), fila, columna ), IF(valor="-", "", valor) ), "") | G8: =F8-E8 -> 0 | H8: {=IFERROR(SUMIF(Consolidado!$C$3:$C$100, $A8, INDEX(Consolidado!$E$3:$P$100, , MATCH(H$1, Consolidado!$E$2:$P$2, 0))), "")} | I8: =IFERROR( LET( hoja, LEFT(I$1,3)&"R", fila, MATCH( RIGHT($A8, LEN($A8)-4), INDIRECT(hoja&"!$A:$A"), 0 ), columna, MATCH( "Totales", INDIRECT(hoja&"!$6:$6"), 0 ), valor, INDEX( INDIRECT(hoja&"!$A:$ZZ"), fila, columna ), IF(valor="-", "", valor) ), "") | J8: =I8-H8 -> 0 | K8: {=IFERROR(SUMIF(Consolidado!$C$3:$C$100, $A8, INDEX(Consolidado!$E$3:$P$100, , MATCH(K$1, Consolidado!$E$2:$P$2, 0))), "")} | L8: =IFERROR( LET( hoja, LEFT(L$1,3)&"R", fila, MATCH( RIGHT($A8, LEN($A8)-4), INDIRECT(hoja&"!$A:$A"), 0 ), columna, MATCH( "Totales", INDIRECT(hoja&"!$6:$6"), 0 ), valor, INDEX( INDIRECT(hoja&"!$A:$ZZ"), fila, columna ), IF(valor="-", "", valor) ), "") | M8: =L8-K8 -> 0 | N8: {=IFERROR(SUMIF(Consolidado!$C$3:$C$100, $A8, INDEX(Consolidado!$E$3:$P$100, , MATCH(N$1, Consolidado!$E$2:$P$2, 0))), "")} | O8: =IFERROR( LET( hoja, LEFT(O$1,3)&"R", fila, MATCH( RIGHT($A8, LEN($A8)-4), INDIRECT(hoja&"!$A:$A"), 0 ), columna, MATCH( "Totales", INDIRECT(hoja&"!$6:$6"), 0 ), valor, INDEX( INDIRECT(hoja&"!$A:$ZZ"), fila, columna ), IF(valor="-", "", valor) ), "") | P8: =O8-N8 -> 0 | Q8: {=IFERROR(SUMIF(Consolidado!$C$3:$C$100, $A8, INDEX(Consolidado!$E$3:$P$100, , MATCH(Q$1, Consolidado!$E$2:$P$2, 0))), "")} | R8: =IFERROR( LET( hoja, LEFT(R$1,3)&"R", fila, MATCH( RIGHT($A8, LEN($A8)-4), INDIRECT(hoja&"!$A:$A"), 0 ), columna, MATCH( "Totales", INDIRECT(hoja&"!$6:$6"), 0 ), valor, INDEX( INDIRECT(hoja&"!$A:$ZZ"), fila, columna ), IF(valor="-", "", valor) ), "") | S8: =R8-Q8 -> 0 | T8: {=IFERROR(SUMIF(Consolidado!$C$3:$C$100, $A8, INDEX(Consolidado!$E$3:$P$100, , MATCH(T$1, Consolidado!$E$2:$P$2, 0))), "")} | U8: =IFERROR( LET( hoja, LEFT(U$1,3)&"R", fila, MATCH( RIGHT($A8, LEN($A8)-4), INDIRECT(hoja&"!$A:$A"), 0 ), columna, MATCH( "Totales", INDIRECT(hoja&"!$6:$6"), 0 ), valor, INDEX( INDIRECT(hoja&"!$A:$ZZ"), fila, columna ), IF(valor="-", "", valor) ), "") | V8: =U8-T8 -> 0 | W8: {=IFERROR(SUMIF(Consolidado!$C$3:$C$100, $A8, INDEX(Consolidado!$E$3:$P$100, , MATCH(W$1, Consolidado!$E$2:$P$2, 0))), "")} | X8: =IFERROR( LET( hoja, LEFT(X$1,3)&"R", fila, MATCH( RIGHT($A8, LEN($A8)-4), INDIRECT(hoja&"!$A:$A"), 0 ), columna, MATCH( "Totales", INDIRECT(hoja&"!$6:$6"), 0 ), valor, INDEX( INDIRECT(hoja&"!$A:$ZZ"), fila, columna ), IF(valor="-", "", valor) ), "") | Y8: =X8-W8 -> 0 | Z8: {=IFERROR(SUMIF(Consolidado!$C$3:$C$100, $A8, INDEX(Consolidado!$E$3:$P$100, , MATCH(Z$1, Consolidado!$E$2:$P$2, 0))), "")} | AA8: =IFERROR( LET( hoja, LEFT(AA$1,3)&"R", fila, MATCH( RIGHT($A8, LEN($A8)-4), INDIRECT(hoja&"!$A:$A"), 0 ), columna, MATCH( "Totales", INDIRECT(hoja&"!$6:$6"), 0 ), valor, INDEX( INDIRECT(hoja&"!$A:$ZZ"), fila, columna ), IF(valor="-", "", valor) ), "") | AB8: =AA8-Z8 -> 0 | AC8: {=IFERROR(SUMIF(Consolidado!$C$3:$C$100, $A8, INDEX(Consolidado!$E$3:$P$100, , MATCH(AC$1, Consolidado!$E$2:$P$2, 0))), "")} | AD8: =IFERROR( LET( hoja, LEFT(AD$1,3)&"R", fila, MATCH( RIGHT($A8, LEN($A8)-4), INDIRECT(hoja&"!$A:$A"), 0 ), columna, MATCH( "Totales", INDIRECT(hoja&"!$6:$6"), 0 ), valor, INDEX( INDIRECT(hoja&"!$A:$ZZ"), fila, columna ), IF(valor="-", "", valor) ), "") | AE8: =AD8-AC8 -> 0 | AF8: {=IFERROR(SUMIF(Consolidado!$C$3:$C$100, $A8, INDEX(Consolidado!$E$3:$P$100, , MATCH(AF$1, Consolidado!$E$2:$P$2, 0))), "")} | AG8: =IFERROR( LET( hoja, LEFT(AG$1,3)&"R", fila, MATCH( RIGHT($A8, LEN($A8)-4), INDIRECT(hoja&"!$A:$A"), 0 ), columna, MATCH( "Totales", INDIRECT(hoja&"!$6:$6"), 0 ), valor, INDEX( INDIRECT(hoja&"!$A:$ZZ"), fila, columna ), IF(valor="-", "", valor) ), "") | AH8: =AG8-AF8 -> 0 | AI8: {=IFERROR(SUMIF(Consolidado!$C$3:$C$100, $A8, INDEX(Consolidado!$E$3:$P$100, , MATCH(AI$1, Consolidado!$E$2:$P$2, 0))), "")} | AJ8: =IFERROR( LET( hoja, LEFT(AJ$1,3)&"R", fila, MATCH( RIGHT($A8, LEN($A8)-4), INDIRECT(hoja&"!$A:$A"), 0 ), columna, MATCH( "Totales", INDIRECT(hoja&"!$6:$6"), 0 ), valor, INDEX( INDIRECT(hoja&"!$A:$ZZ"), fila, columna ), IF(valor="-", "", valor) ), "") | AK8: =AJ8-AI8 -> 0 | AL8: {=IFERROR(SUMIF(Consolidado!$C$3:$C$100, $A8, INDEX(Consolidado!$E$3:$P$100, , MATCH(AL$1, Consolidado!$E$2:$P$2, 0))), "")} | AM8: =IFERROR( LET( hoja, LEFT(AM$1,3)&"R", fila, MATCH( RIGHT($A8, LEN($A8)-4), INDIRECT(hoja&"!$A:$A"), 0 ), columna, MATCH( "Totales", INDIRECT(hoja&"!$6:$6"), 0 ), valor, INDEX( INDIRECT(hoja&"!$A:$ZZ"), fila, columna ), IF(valor="-", "", valor) ), "") | AN8: =AM8-AL8 -> 0
A10: Total de Egresos | B10: =SUM(B11:B47) -> 0 | C10: =SUM(C11:C47) -> 0 | D10: =C10-B10 -> 0 | E10: =SUM(E11:E47) -> 0 | F10: =SUM(F11:F47) -> 0 | G10: =F10-E10 -> 0 | H10: =SUM(H11:H47) -> 0 | I10: =SUM(I11:I47) -> 0 | J10: =SUM(J11:J47) -> 0 | K10: =SUM(K11:K47) -> 0 | L10: =SUM(L11:L47) -> 0 | M10: =SUM(M11:M47) -> 0 | N10: =SUM(N11:N47) -> 0 | O10: =SUM(O11:O47) -> 0 | ... AN10: =SUM(AN11:AN47) -> 0
A11: =Menus!B4 -> B01 Nomina | B11: =SUM(IF(MONTH(TODAY())>1,E11,0), IF(MONTH(TODAY())>2,H11,0), IF(MONTH(TODAY())>3,K11,0), IF(MONTH(TODAY())>4,N11,0), IF(MONTH(TODAY())>5,Q11,0), IF(MONTH(TODAY())>6,T11,0), IF(MONTH(TODAY())>7,W11,0), IF(MONTH(TODAY())>8,Z11,0), IF(MONTH(TODAY())>9,AC11,0), IF(MONTH(TODAY())>10,AF11,0), IF(MONTH(TODAY())>11,AI11,0), IF(MONTH(TODAY())>12,AL11,0)) -> 0 | C11: =SUM(IF(MONTH(TODAY())>1,F11,0), IF(MONTH(TODAY())>2,I11,0), IF(MONTH(TODAY())>3,L11,0), IF(MONTH(TODAY())>4,O11,0), IF(MONTH(TODAY())>5,R11,0), IF(MONTH(TODAY())>6,U11,0), IF(MONTH(TODAY())>7,X11,0), IF(MONTH(TODAY())>8,AA11,0), IF(MONTH(TODAY())>9,AD11,0), IF(MONTH(TODAY())>10,AG11,0), IF(MONTH(TODAY())>11,AJ11,0), IF(MONTH(TODAY())>12,AM11,0)) -> 0 | D11: =B11-C11 -> 0 | E11: {=IFERROR(SUMIF(Consolidado!$C$3:$C63, $A11, INDEX(Consolidado!$E$3:$P$100, , MATCH(E$1, Consolidado!$E$2:$P$2, 0))), "")} | F11: =IFERROR( LET( hoja, LEFT(F$1,3)&"R", fila, MATCH( RIGHT($A11, LEN($A11)-4), INDIRECT(hoja&"!$A:$A"), 0 ), columna, MATCH( "Totales", INDIRECT(hoja&"!$6:$6"), 0 ), valor, INDEX( INDIRECT(hoja&"!$A:$ZZ"), fila, columna ), IF(valor="-", "", valor) ), "") | G11: =E11-F11 -> 0 | H11: {=IFERROR(SUMIF(Consolidado!$C$3:$C63, $A11, INDEX(Consolidado!$E$3:$P$100, , MATCH(H$1, Consolidado!$E$2:$P$2, 0))), "")} | I11: =IFERROR( LET( hoja, LEFT(I$1,3)&"R", fila, MATCH( RIGHT($A11, LEN($A11)-4), INDIRECT(hoja&"!$A:$A"), 0 ), columna, MATCH( "Totales", INDIRECT(hoja&"!$6:$6"), 0 ), valor, INDEX( INDIRECT(hoja&"!$A:$ZZ"), fila, columna ), IF(valor="-", "", valor) ), "") | J11: =H11-I11 -> 0 | K11: {=IFERROR(SUMIF(Consolidado!$C$3:$C63, $A11, INDEX(Consolidado!$E$3:$P$100, , MATCH(K$1, Consolidado!$E$2:$P$2, 0))), "")} | L11: =IFERROR( LET( hoja, LEFT(L$1,3)&"R", fila, MATCH( RIGHT($A11, LEN($A11)-4), INDIRECT(hoja&"!$A:$A"), 0 ), columna, MATCH( "Totales", INDIRECT(hoja&"!$6:$6"), 0 ), valor, INDEX( INDIRECT(hoja&"!$A:$ZZ"), fila, columna ), IF(valor="-", "", valor) ), "") | M11: =K11-L11 -> 0 | N11: {=IFERROR(SUMIF(Consolidado!$C$3:$C63, $A11, INDEX(Consolidado!$E$3:$P$100, , MATCH(N$1, Consolidado!$E$2:$P$2, 0))), "")} | O11: =IFERROR( LET( hoja, LEFT(O$1,3)&"R", fila, MATCH( RIGHT($A11, LEN($A11)-4), INDIRECT(hoja&"!$A:$A"), 0 ), columna, MATCH( "Totales", INDIRECT(hoja&"!$6:$6"), 0 ), valor, INDEX( INDIRECT(hoja&"!$A:$ZZ"), fila, columna ), IF(valor="-", "", valor) ), "") | P11: =N11-O11 -> 0 | Q11: {=IFERROR(SUMIF(Consolidado!$C$3:$C63, $A11, INDEX(Consolidado!$E$3:$P$100, , MATCH(Q$1, Consolidado!$E$2:$P$2, 0))), "")} | R11: =IFERROR( LET( hoja, LEFT(R$1,3)&"R", fila, MATCH( RIGHT($A11, LEN($A11)-4), INDIRECT(hoja&"!$A:$A"), 0 ), columna, MATCH( "Totales", INDIRECT(hoja&"!$6:$6"), 0 ), valor, INDEX( INDIRECT(hoja&"!$A:$ZZ"), fila, columna ), IF(valor="-", "", valor) ), "") | S11: =Q11-R11 -> 0 | T11: {=IFERROR(SUMIF(Consolidado!$C$3:$C63, $A11, INDEX(Consolidado!$E$3:$P$100, , MATCH(T$1, Consolidado!$E$2:$P$2, 0))), "")} | U11: =IFERROR( LET( hoja, LEFT(U$1,3)&"R", fila, MATCH( RIGHT($A11, LEN($A11)-4), INDIRECT(hoja&"!$A:$A"), 0 ), columna, MATCH( "Totales", INDIRECT(hoja&"!$6:$6"), 0 ), valor, INDEX( INDIRECT(hoja&"!$A:$ZZ"), fila, columna ), IF(valor="-", "", valor) ), "") | V11: =T11-U11 -> 0 | W11: {=IFERROR(SUMIF(Consolidado!$C$3:$C63, $A11, INDEX(Consolidado!$E$3:$P$100, , MATCH(W$1, Consolidado!$E$2:$P$2, 0))), "")} | X11: =IFERROR( LET( hoja, LEFT(X$1,3)&"R", fila, MATCH( RIGHT($A11, LEN($A11)-4), INDIRECT(hoja&"!$A:$A"), 0 ), columna, MATCH( "Totales", INDIRECT(hoja&"!$6:$6"), 0 ), valor, INDEX( INDIRECT(hoja&"!$A:$ZZ"), fila, columna ), IF(valor="-", "", valor) ), "") | Y11: =W11-X11 -> 0 | Z11: {=IFERROR(SUMIF(Consolidado!$C$3:$C63, $A11, INDEX(Consolidado!$E$3:$P$100, , MATCH(Z$1, Consolidado!$E$2:$P$2, 0))), "")} | AA11: =IFERROR( LET( hoja, LEFT(AA$1,3)&"R", fila, MATCH( RIGHT($A11, LEN($A11)-4), INDIRECT(hoja&"!$A:$A"), 0 ), columna, MATCH( "Totales", INDIRECT(hoja&"!$6:$6"), 0 ), valor, INDEX( INDIRECT(hoja&"!$A:$ZZ"), fila, columna ), IF(valor="-", "", valor) ), "") | AB11: =Z11-AA11 -> 0 | AC11: {=IFERROR(SUMIF(Consolidado!$C$3:$C63, $A11, INDEX(Consolidado!$E$3:$P$100, , MATCH(AC$1, Consolidado!$E$2:$P$2, 0))), "")} | AD11: =IFERROR( LET( hoja, LEFT(AD$1,3)&"R", fila, MATCH( RIGHT($A11, LEN($A11)-4), INDIRECT(hoja&"!$A:$A"), 0 ), columna, MATCH( "Totales", INDIRECT(hoja&"!$6:$6"), 0 ), valor, INDEX( INDIRECT(hoja&"!$A:$ZZ"), fila, columna ), IF(valor="-", "", valor) ), "") | AE11: =AC11-AD11 -> 0 | AF11: {=IFERROR(SUMIF(Consolidado!$C$3:$C63, $A11, INDEX(Consolidado!$E$3:$P$100, , MATCH(AF$1, Consolidado!$E$2:$P$2, 0))), "")} | AG11: =IFERROR( LET( hoja, LEFT(AG$1,3)&"R", fila, MATCH( RIGHT($A11, LEN($A11)-4), INDIRECT(hoja&"!$A:$A"), 0 ), columna, MATCH( "Totales", INDIRECT(hoja&"!$6:$6"), 0 ), valor, INDEX( INDIRECT(hoja&"!$A:$ZZ"), fila, columna ), IF(valor="-", "", valor) ), "") | AH11: =AF11-AG11 -> 0 | AI11: {=IFERROR(SUMIF(Consolidado!$C$3:$C63, $A11, INDEX(Consolidado!$E$3:$P$100, , MATCH(AI$1, Consolidado!$E$2:$P$2, 0))), "")} | AJ11: =IFERROR( LET( hoja, LEFT(AJ$1,3)&"R", fila, MATCH( RIGHT($A11, LEN($A11)-4), INDIRECT(hoja&"!$A:$A"), 0 ), columna, MATCH( "Totales", INDIRECT(hoja&"!$6:$6"), 0 ), valor, INDEX( INDIRECT(hoja&"!$A:$ZZ"), fila, columna ), IF(valor="-", "", valor) ), "") | AK11: =AI11-AJ11 -> 0 | AL11: {=IFERROR(SUMIF(Consolidado!$C$3:$C63, $A11, INDEX(Consolidado!$E$3:$P$100, , MATCH(AL$1, Consolidado!$E$2:$P$2, 0))), "")} | AM11: =IFERROR( LET( hoja, LEFT(AM$1,3)&"R", fila, MATCH( RIGHT($A11, LEN($A11)-4), INDIRECT(hoja&"!$A:$A"), 0 ), columna, MATCH( "Totales", INDIRECT(hoja&"!$6:$6"), 0 ), valor, INDEX( INDIRECT(hoja&"!$A:$ZZ"), fila, columna ), IF(valor="-", "", valor) ), "") | AN11: =AL11-AM11 -> 0
A12: =Menus!B5 -> B02 Cuotas IMSS | B12: =SUM(IF(MONTH(TODAY())>1,E12,0), IF(MONTH(TODAY())>2,H12,0), IF(MONTH(TODAY())>3,K12,0), IF(MONTH(TODAY())>4,N12,0), IF(MONTH(TODAY())>5,Q12,0), IF(MONTH(TODAY())>6,T12,0), IF(MONTH(TODAY())>7,W12,0), IF(MONTH(TODAY())>8,Z12,0), IF(MONTH(TODAY())>9,AC12,0), IF(MONTH(TODAY())>10,AF12,0), IF(MONTH(TODAY())>11,AI12,0), IF(MONTH(TODAY())>12,AL12,0)) -> 0 | C12: =SUM(IF(MONTH(TODAY())>1,F12,0), IF(MONTH(TODAY())>2,I12,0), IF(MONTH(TODAY())>3,L12,0), IF(MONTH(TODAY())>4,O12,0), IF(MONTH(TODAY())>5,R12,0), IF(MONTH(TODAY())>6,U12,0), IF(MONTH(TODAY())>7,X12,0), IF(MONTH(TODAY())>8,AA12,0), IF(MONTH(TODAY())>9,AD12,0), IF(MONTH(TODAY())>10,AG12,0), IF(MONTH(TODAY())>11,AJ12,0), IF(MONTH(TODAY())>12,AM12,0)) -> 0 | D12: =B12-C12 -> 0 | E12: {=IFERROR(SUMIF(Consolidado!$C$3:$C63, $A12, INDEX(Consolidado!$E$3:$P$100, , MATCH(E$1, Consolidado!$E$2:$P$2, 0))), "")} | F12: =IFERROR( LET( hoja, LEFT(F$1,3)&"R", fila, MATCH( RIGHT($A12, LEN($A12)-4), INDIRECT(hoja&"!$A:$A"), 0 ), columna, MATCH( "Totales", INDIRECT(hoja&"!$6:$6"), 0 ), valor, INDEX( INDIRECT(hoja&"!$A:$ZZ"), fila, columna ), IF(valor="-", "", valor) ), "") | G12: =E12-F12 -> 0 | H12: {=IFERROR(SUMIF(Consolidado!$C$3:$C63, $A12, INDEX(Consolidado!$E$3:$P$100, , MATCH(H$1, Consolidado!$E$2:$P$2, 0))), "")} | I12: =IFERROR( LET( hoja, LEFT(I$1,3)&"R", fila, MATCH( RIGHT($A12, LEN($A12)-4), INDIRECT(hoja&"!$A:$A"), 0 ), columna, MATCH( "Totales", INDIRECT(hoja&"!$6:$6"), 0 ), valor, INDEX( INDIRECT(hoja&"!$A:$ZZ"), fila, columna ), IF(valor="-", "", valor) ), "") | J12: =H12-I12 -> 0 | K12: {=IFERROR(SUMIF(Consolidado!$C$3:$C63, $A12, INDEX(Consolidado!$E$3:$P$100, , MATCH(K$1, Consolidado!$E$2:$P$2, 0))), "")} | L12: =IFERROR( LET( hoja, LEFT(L$1,3)&"R", fila, MATCH( RIGHT($A12, LEN($A12)-4), INDIRECT(hoja&"!$A:$A"), 0 ), columna, MATCH( "Totales", INDIRECT(hoja&"!$6:$6"), 0 ), valor, INDEX( INDIRECT(hoja&"!$A:$ZZ"), fila, columna ), IF(valor="-", "", valor) ), "") | M12: =K12-L12 -> 0 | N12: {=IFERROR(SUMIF(Consolidado!$C$3:$C63, $A12, INDEX(Consolidado!$E$3:$P$100, , MATCH(N$1, Consolidado!$E$2:$P$2, 0))), "")} | O12: =IFERROR( LET( hoja, LEFT(O$1,3)&"R", fila, MATCH( RIGHT($A12, LEN($A12)-4), INDIRECT(hoja&"!$A:$A"), 0 ), columna, MATCH( "Totales", INDIRECT(hoja&"!$6:$6"), 0 ), valor, INDEX( INDIRECT(hoja&"!$A:$ZZ"), fila, columna ), IF(valor="-", "", valor) ), "") | P12: =N12-O12 -> 0 | Q12: {=IFERROR(SUMIF(Consolidado!$C$3:$C63, $A12, INDEX(Consolidado!$E$3:$P$100, , MATCH(Q$1, Consolidado!$E$2:$P$2, 0))), "")} | R12: =IFERROR( LET( hoja, LEFT(R$1,3)&"R", fila, MATCH( RIGHT($A12, LEN($A12)-4), INDIRECT(hoja&"!$A:$A"), 0 ), columna, MATCH( "Totales", INDIRECT(hoja&"!$6:$6"), 0 ), valor, INDEX( INDIRECT(hoja&"!$A:$ZZ"), fila, columna ), IF(valor="-", "", valor) ), "") | S12: =Q12-R12 -> 0 | T12: {=IFERROR(SUMIF(Consolidado!$C$3:$C63, $A12, INDEX(Consolidado!$E$3:$P$100, , MATCH(T$1, Consolidado!$E$2:$P$2, 0))), "")} | U12: =IFERROR( LET( hoja, LEFT(U$1,3)&"R", fila, MATCH( RIGHT($A12, LEN($A12)-4), INDIRECT(hoja&"!$A:$A"), 0 ), columna, MATCH( "Totales", INDIRECT(hoja&"!$6:$6"), 0 ), valor, INDEX( INDIRECT(hoja&"!$A:$ZZ"), fila, columna ), IF(valor="-", "", valor) ), "") | V12: =T12-U12 -> 0 | W12: {=IFERROR(SUMIF(Consolidado!$C$3:$C63, $A12, INDEX(Consolidado!$E$3:$P$100, , MATCH(W$1, Consolidado!$E$2:$P$2, 0))), "")} | X12: =IFERROR( LET( hoja, LEFT(X$1,3)&"R", fila, MATCH( RIGHT($A12, LEN($A12)-4), INDIRECT(hoja&"!$A:$A"), 0 ), columna, MATCH( "Totales", INDIRECT(hoja&"!$6:$6"), 0 ), valor, INDEX( INDIRECT(hoja&"!$A:$ZZ"), fila, columna ), IF(valor="-", "", valor) ), "") | Y12: =W12-X12 -> 0 | Z12: {=IFERROR(SUMIF(Consolidado!$C$3:$C63, $A12, INDEX(Consolidado!$E$3:$P$100, , MATCH(Z$1, Consolidado!$E$2:$P$2, 0))), "")} | AA12: =IFERROR( LET( hoja, LEFT(AA$1,3)&"R", fila, MATCH( RIGHT($A12, LEN($A12)-4), INDIRECT(hoja&"!$A:$A"), 0 ), columna, MATCH( "Totales", INDIRECT(hoja&"!$6:$6"), 0 ), valor, INDEX( INDIRECT(hoja&"!$A:$ZZ"), fila, columna ), IF(valor="-", "", valor) ), "") | AB12: =Z12-AA12 -> 0 | AC12: {=IFERROR(SUMIF(Consolidado!$C$3:$C63, $A12, INDEX(Consolidado!$E$3:$P$100, , MATCH(AC$1, Consolidado!$E$2:$P$2, 0))), "")} | AD12: =IFERROR( LET( hoja, LEFT(AD$1,3)&"R", fila, MATCH( RIGHT($A12, LEN($A12)-4), INDIRECT(hoja&"!$A:$A"), 0 ), columna, MATCH( "Totales", INDIRECT(hoja&"!$6:$6"), 0 ), valor, INDEX( INDIRECT(hoja&"!$A:$ZZ"), fila, columna ), IF(valor="-", "", valor) ), "") | AE12: =AC12-AD12 -> 0 | AF12: {=IFERROR(SUMIF(Consolidado!$C$3:$C63, $A12, INDEX(Consolidado!$E$3:$P$100, , MATCH(AF$1, Consolidado!$E$2:$P$2, 0))), "")} | AG12: =IFERROR( LET( hoja, LEFT(AG$1,3)&"R", fila, MATCH( RIGHT($A12, LEN($A12)-4), INDIRECT(hoja&"!$A:$A"), 0 ), columna, MATCH( "Totales", INDIRECT(hoja&"!$6:$6"), 0 ), valor, INDEX( INDIRECT(hoja&"!$A:$ZZ"), fila, columna ), IF(valor="-", "", valor) ), "") | AH12: =AF12-AG12 -> 0 | AI12: {=IFERROR(SUMIF(Consolidado!$C$3:$C63, $A12, INDEX(Consolidado!$E$3:$P$100, , MATCH(AI$1, Consolidado!$E$2:$P$2, 0))), "")} | AJ12: =IFERROR( LET( hoja, LEFT(AJ$1,3)&"R", fila, MATCH( RIGHT($A12, LEN($A12)-4), INDIRECT(hoja&"!$A:$A"), 0 ), columna, MATCH( "Totales", INDIRECT(hoja&"!$6:$6"), 0 ), valor, INDEX( INDIRECT(hoja&"!$A:$ZZ"), fila, columna ), IF(valor="-", "", valor) ), "") | AK12: =AI12-AJ12 -> 0 | AL12: {=IFERROR(SUMIF(Consolidado!$C$3:$C63, $A12, INDEX(Consolidado!$E$3:$P$100, , MATCH(AL$1, Consolidado!$E$2:$P$2, 0))), "")} | AM12: =IFERROR( LET( hoja, LEFT(AM$1,3)&"R", fila, MATCH( RIGHT($A12, LEN($A12)-4), INDIRECT(hoja&"!$A:$A"), 0 ), columna, MATCH( "Totales", INDIRECT(hoja&"!$6:$6"), 0 ), valor, INDEX( INDIRECT(hoja&"!$A:$ZZ"), fila, columna ), IF(valor="-", "", valor) ), "") | AN12: =AL12-AM12 -> 0
A13: =Menus!B6 -> B03 Cuotas AFORE | B13: =SUM(IF(MONTH(TODAY())>1,E13,0), IF(MONTH(TODAY())>2,H13,0), IF(MONTH(TODAY())>3,K13,0), IF(MONTH(TODAY())>4,N13,0), IF(MONTH(TODAY())>5,Q13,0), IF(MONTH(TODAY())>6,T13,0), IF(MONTH(TODAY())>7,W13,0), IF(MONTH(TODAY())>8,Z13,0), IF(MONTH(TODAY())>9,AC13,0), IF(MONTH(TODAY())>10,AF13,0), IF(MONTH(TODAY())>11,AI13,0), IF(MONTH(TODAY())>12,AL13,0)) -> 0 | C13: =SUM(IF(MONTH(TODAY())>1,F13,0), IF(MONTH(TODAY())>2,I13,0), IF(MONTH(TODAY())>3,L13,0), IF(MONTH(TODAY())>4,O13,0), IF(MONTH(TODAY())>5,R13,0), IF(MONTH(TODAY())>6,U13,0), IF(MONTH(TODAY())>7,X13,0), IF(MONTH(TODAY())>8,AA13,0), IF(MONTH(TODAY())>9,AD13,0), IF(MONTH(TODAY())>10,AG13,0), IF(MONTH(TODAY())>11,AJ13,0), IF(MONTH(TODAY())>12,AM13,0)) -> 0 | D13: =B13-C13 -> 0 | E13: {=IFERROR(SUMIF(Consolidado!$C$3:$C63, $A13, INDEX(Consolidado!$E$3:$P$100, , MATCH(E$1, Consolidado!$E$2:$P$2, 0))), "")} | F13: =IFERROR( LET( hoja, LEFT(F$1,3)&"R", fila, MATCH( RIGHT($A13, LEN($A13)-4), INDIRECT(hoja&"!$A:$A"), 0 ), columna, MATCH( "Totales", INDIRECT(hoja&"!$6:$6"), 0 ), valor, INDEX( INDIRECT(hoja&"!$A:$ZZ"), fila, columna ), IF(valor="-", "", valor) ), "") | G13: =E13-F13 -> 0 | H13: {=IFERROR(SUMIF(Consolidado!$C$3:$C63, $A13, INDEX(Consolidado!$E$3:$P$100, , MATCH(H$1, Consolidado!$E$2:$P$2, 0))), "")} | I13: =IFERROR( LET( hoja, LEFT(I$1,3)&"R", fila, MATCH( RIGHT($A13, LEN($A13)-4), INDIRECT(hoja&"!$A:$A"), 0 ), columna, MATCH( "Totales", INDIRECT(hoja&"!$6:$6"), 0 ), valor, INDEX( INDIRECT(hoja&"!$A:$ZZ"), fila, columna ), IF(valor="-", "", valor) ), "") | J13: =H13-I13 -> 0 | K13: {=IFERROR(SUMIF(Consolidado!$C$3:$C63, $A13, INDEX(Consolidado!$E$3:$P$100, , MATCH(K$1, Consolidado!$E$2:$P$2, 0))), "")} | L13: =IFERROR( LET( hoja, LEFT(L$1,3)&"R", fila, MATCH( RIGHT($A13, LEN($A13)-4), INDIRECT(hoja&"!$A:$A"), 0 ), columna, MATCH( "Totales", INDIRECT(hoja&"!$6:$6"), 0 ), valor, INDEX( INDIRECT(hoja&"!$A:$ZZ"), fila, columna ), IF(valor="-", "", valor) ), "") | M13: =K13-L13 -> 0 | N13: {=IFERROR(SUMIF(Consolidado!$C$3:$C63, $A13, INDEX(Consolidado!$E$3:$P$100, , MATCH(N$1, Consolidado!$E$2:$P$2, 0))), "")} | O13: =IFERROR( LET( hoja, LEFT(O$1,3)&"R", fila, MATCH( RIGHT($A13, LEN($A13)-4), INDIRECT(hoja&"!$A:$A"), 0 ), columna, MATCH( "Totales", INDIRECT(hoja&"!$6:$6"), 0 ), valor, INDEX( INDIRECT(hoja&"!$A:$ZZ"), fila, columna ), IF(valor="-", "", valor) ), "") | P13: =N13-O13 -> 0 | Q13: {=IFERROR(SUMIF(Consolidado!$C$3:$C63, $A13, INDEX(Consolidado!$E$3:$P$100, , MATCH(Q$1, Consolidado!$E$2:$P$2, 0))), "")} | R13: =IFERROR( LET( hoja, LEFT(R$1,3)&"R", fila, MATCH( RIGHT($A13, LEN($A13)-4), INDIRECT(hoja&"!$A:$A"), 0 ), columna, MATCH( "Totales", INDIRECT(hoja&"!$6:$6"), 0 ), valor, INDEX( INDIRECT(hoja&"!$A:$ZZ"), fila, columna ), IF(valor="-", "", valor) ), "") | S13: =Q13-R13 -> 0 | T13: {=IFERROR(SUMIF(Consolidado!$C$3:$C63, $A13, INDEX(Consolidado!$E$3:$P$100, , MATCH(T$1, Consolidado!$E$2:$P$2, 0))), "")} | U13: =IFERROR( LET( hoja, LEFT(U$1,3)&"R", fila, MATCH( RIGHT($A13, LEN($A13)-4), INDIRECT(hoja&"!$A:$A"), 0 ), columna, MATCH( "Totales", INDIRECT(hoja&"!$6:$6"), 0 ), valor, INDEX( INDIRECT(hoja&"!$A:$ZZ"), fila, columna ), IF(valor="-", "", valor) ), "") | V13: =T13-U13 -> 0 | W13: {=IFERROR(SUMIF(Consolidado!$C$3:$C63, $A13, INDEX(Consolidado!$E$3:$P$100, , MATCH(W$1, Consolidado!$E$2:$P$2, 0))), "")} | X13: =IFERROR( LET( hoja, LEFT(X$1,3)&"R", fila, MATCH( RIGHT($A13, LEN($A13)-4), INDIRECT(hoja&"!$A:$A"), 0 ), columna, MATCH( "Totales", INDIRECT(hoja&"!$6:$6"), 0 ), valor, INDEX( INDIRECT(hoja&"!$A:$ZZ"), fila, columna ), IF(valor="-", "", valor) ), "") | Y13: =W13-X13 -> 0 | Z13: {=IFERROR(SUMIF(Consolidado!$C$3:$C63, $A13, INDEX(Consolidado!$E$3:$P$100, , MATCH(Z$1, Consolidado!$E$2:$P$2, 0))), "")} | AA13: =IFERROR( LET( hoja, LEFT(AA$1,3)&"R", fila, MATCH( RIGHT($A13, LEN($A13)-4), INDIRECT(hoja&"!$A:$A"), 0 ), columna, MATCH( "Totales", INDIRECT(hoja&"!$6:$6"), 0 ), valor, INDEX( INDIRECT(hoja&"!$A:$ZZ"), fila, columna ), IF(valor="-", "", valor) ), "") | AB13: =Z13-AA13 -> 0 | AC13: {=IFERROR(SUMIF(Consolidado!$C$3:$C63, $A13, INDEX(Consolidado!$E$3:$P$100, , MATCH(AC$1, Consolidado!$E$2:$P$2, 0))), "")} | AD13: =IFERROR( LET( hoja, LEFT(AD$1,3)&"R", fila, MATCH( RIGHT($A13, LEN($A13)-4), INDIRECT(hoja&"!$A:$A"), 0 ), columna, MATCH( "Totales", INDIRECT(hoja&"!$6:$6"), 0 ), valor, INDEX( INDIRECT(hoja&"!$A:$ZZ"), fila, columna ), IF(valor="-", "", valor) ), "") | AE13: =AC13-AD13 -> 0 | AF13: {=IFERROR(SUMIF(Consolidado!$C$3:$C63, $A13, INDEX(Consolidado!$E$3:$P$100, , MATCH(AF$1, Consolidado!$E$2:$P$2, 0))), "")} | AG13: =IFERROR( LET( hoja, LEFT(AG$1,3)&"R", fila, MATCH( RIGHT($A13, LEN($A13)-4), INDIRECT(hoja&"!$A:$A"), 0 ), columna, MATCH( "Totales", INDIRECT(hoja&"!$6:$6"), 0 ), valor, INDEX( INDIRECT(hoja&"!$A:$ZZ"), fila, columna ), IF(valor="-", "", valor) ), "") | AH13: =AF13-AG13 -> 0 | AI13: {=IFERROR(SUMIF(Consolidado!$C$3:$C63, $A13, INDEX(Consolidado!$E$3:$P$100, , MATCH(AI$1, Consolidado!$E$2:$P$2, 0))), "")} | AJ13: =IFERROR( LET( hoja, LEFT(AJ$1,3)&"R", fila, MATCH( RIGHT($A13, LEN($A13)-4), INDIRECT(hoja&"!$A:$A"), 0 ), columna, MATCH( "Totales", INDIRECT(hoja&"!$6:$6"), 0 ), valor, INDEX( INDIRECT(hoja&"!$A:$ZZ"), fila, columna ), IF(valor="-", "", valor) ), "") | AK13: =AI13-AJ13 -> 0 | AL13: {=IFERROR(SUMIF(Consolidado!$C$3:$C63, $A13, INDEX(Consolidado!$E$3:$P$100, , MATCH(AL$1, Consolidado!$E$2:$P$2, 0))), "")} | AM13: =IFERROR( LET( hoja, LEFT(AM$1,3)&"R", fila, MATCH( RIGHT($A13, LEN($A13)-4), INDIRECT(hoja&"!$A:$A"), 0 ), columna, MATCH( "Totales", INDIRECT(hoja&"!$6:$6"), 0 ), valor, INDEX( INDIRECT(hoja&"!$A:$ZZ"), fila, columna ), IF(valor="-", "", valor) ), "") | AN13: =AL13-AM13 -> 0
A14: =Menus!B7 -> B04 Cuotas INFONAVIT | B14: =SUM(IF(MONTH(TODAY())>1,E14,0), IF(MONTH(TODAY())>2,H14,0), IF(MONTH(TODAY())>3,K14,0), IF(MONTH(TODAY())>4,N14,0), IF(MONTH(TODAY())>5,Q14,0), IF(MONTH(TODAY())>6,T14,0), IF(MONTH(TODAY())>7,W14,0), IF(MONTH(TODAY())>8,Z14,0), IF(MONTH(TODAY())>9,AC14,0), IF(MONTH(TODAY())>10,AF14,0), IF(MONTH(TODAY())>11,AI14,0), IF(MONTH(TODAY())>12,AL14,0)) -> 0 | C14: =SUM(IF(MONTH(TODAY())>1,F14,0), IF(MONTH(TODAY())>2,I14,0), IF(MONTH(TODAY())>3,L14,0), IF(MONTH(TODAY())>4,O14,0), IF(MONTH(TODAY())>5,R14,0), IF(MONTH(TODAY())>6,U14,0), IF(MONTH(TODAY())>7,X14,0), IF(MONTH(TODAY())>8,AA14,0), IF(MONTH(TODAY())>9,AD14,0), IF(MONTH(TODAY())>10,AG14,0), IF(MONTH(TODAY())>11,AJ14,0), IF(MONTH(TODAY())>12,AM14,0)) -> 0 | D14: =B14-C14 -> 0 | E14: {=IFERROR(SUMIF(Consolidado!$C$3:$C63, $A14, INDEX(Consolidado!$E$3:$P$100, , MATCH(E$1, Consolidado!$E$2:$P$2, 0))), "")} | F14: =IFERROR( LET( hoja, LEFT(F$1,3)&"R", fila, MATCH( RIGHT($A14, LEN($A14)-4), INDIRECT(hoja&"!$A:$A"), 0 ), columna, MATCH( "Totales", INDIRECT(hoja&"!$6:$6"), 0 ), valor, INDEX( INDIRECT(hoja&"!$A:$ZZ"), fila, columna ), IF(valor="-", "", valor) ), "") | G14: =E14-F14 -> 0 | H14: {=IFERROR(SUMIF(Consolidado!$C$3:$C63, $A14, INDEX(Consolidado!$E$3:$P$100, , MATCH(H$1, Consolidado!$E$2:$P$2, 0))), "")} | I14: =IFERROR( LET( hoja, LEFT(I$1,3)&"R", fila, MATCH( RIGHT($A14, LEN($A14)-4), INDIRECT(hoja&"!$A:$A"), 0 ), columna, MATCH( "Totales", INDIRECT(hoja&"!$6:$6"), 0 ), valor, INDEX( INDIRECT(hoja&"!$A:$ZZ"), fila, columna ), IF(valor="-", "", valor) ), "") | J14: =H14-I14 -> 0 | K14: {=IFERROR(SUMIF(Consolidado!$C$3:$C63, $A14, INDEX(Consolidado!$E$3:$P$100, , MATCH(K$1, Consolidado!$E$2:$P$2, 0))), "")} | L14: =IFERROR( LET( hoja, LEFT(L$1,3)&"R", fila, MATCH( RIGHT($A14, LEN($A14)-4), INDIRECT(hoja&"!$A:$A"), 0 ), columna, MATCH( "Totales", INDIRECT(hoja&"!$6:$6"), 0 ), valor, INDEX( INDIRECT(hoja&"!$A:$ZZ"), fila, columna ), IF(valor="-", "", valor) ), "") | M14: =K14-L14 -> 0 | N14: {=IFERROR(SUMIF(Consolidado!$C$3:$C63, $A14, INDEX(Consolidado!$E$3:$P$100, , MATCH(N$1, Consolidado!$E$2:$P$2, 0))), "")} | O14: =IFERROR( LET( hoja, LEFT(O$1,3)&"R", fila, MATCH( RIGHT($A14, LEN($A14)-4), INDIRECT(hoja&"!$A:$A"), 0 ), columna, MATCH( "Totales", INDIRECT(hoja&"!$6:$6"), 0 ), valor, INDEX( INDIRECT(hoja&"!$A:$ZZ"), fila, columna ), IF(valor="-", "", valor) ), "") | P14: =N14-O14 -> 0 | Q14: {=IFERROR(SUMIF(Consolidado!$C$3:$C63, $A14, INDEX(Consolidado!$E$3:$P$100, , MATCH(Q$1, Consolidado!$E$2:$P$2, 0))), "")} | R14: =IFERROR( LET( hoja, LEFT(R$1,3)&"R", fila, MATCH( RIGHT($A14, LEN($A14)-4), INDIRECT(hoja&"!$A:$A"), 0 ), columna, MATCH( "Totales", INDIRECT(hoja&"!$6:$6"), 0 ), valor, INDEX( INDIRECT(hoja&"!$A:$ZZ"), fila, columna ), IF(valor="-", "", valor) ), "") | S14: =Q14-R14 -> 0 | T14: {=IFERROR(SUMIF(Consolidado!$C$3:$C63, $A14, INDEX(Consolidado!$E$3:$P$100, , MATCH(T$1, Consolidado!$E$2:$P$2, 0))), "")} | U14: =IFERROR( LET( hoja, LEFT(U$1,3)&"R", fila, MATCH( RIGHT($A14, LEN($A14)-4), INDIRECT(hoja&"!$A:$A"), 0 ), columna, MATCH( "Totales", INDIRECT(hoja&"!$6:$6"), 0 ), valor, INDEX( INDIRECT(hoja&"!$A:$ZZ"), fila, columna ), IF(valor="-", "", valor) ), "") | V14: =T14-U14 -> 0 | W14: {=IFERROR(SUMIF(Consolidado!$C$3:$C63, $A14, INDEX(Consolidado!$E$3:$P$100, , MATCH(W$1, Consolidado!$E$2:$P$2, 0))), "")} | X14: =IFERROR( LET( hoja, LEFT(X$1,3)&"R", fila, MATCH( RIGHT($A14, LEN($A14)-4), INDIRECT(hoja&"!$A:$A"), 0 ), columna, MATCH( "Totales", INDIRECT(hoja&"!$6:$6"), 0 ), valor, INDEX( INDIRECT(hoja&"!$A:$ZZ"), fila, columna ), IF(valor="-", "", valor) ), "") | Y14: =W14-X14 -> 0 | Z14: {=IFERROR(SUMIF(Consolidado!$C$3:$C63, $A14, INDEX(Consolidado!$E$3:$P$100, , MATCH(Z$1, Consolidado!$E$2:$P$2, 0))), "")} | AA14: =IFERROR( LET( hoja, LEFT(AA$1,3)&"R", fila, MATCH( RIGHT($A14, LEN($A14)-4), INDIRECT(hoja&"!$A:$A"), 0 ), columna, MATCH( "Totales", INDIRECT(hoja&"!$6:$6"), 0 ), valor, INDEX( INDIRECT(hoja&"!$A:$ZZ"), fila, columna ), IF(valor="-", "", valor) ), "") | AB14: =Z14-AA14 -> 0 | AC14: {=IFERROR(SUMIF(Consolidado!$C$3:$C63, $A14, INDEX(Consolidado!$E$3:$P$100, , MATCH(AC$1, Consolidado!$E$2:$P$2, 0))), "")} | AD14: =IFERROR( LET( hoja, LEFT(AD$1,3)&"R", fila, MATCH( RIGHT($A14, LEN($A14)-4), INDIRECT(hoja&"!$A:$A"), 0 ), columna, MATCH( "Totales", INDIRECT(hoja&"!$6:$6"), 0 ), valor, INDEX( INDIRECT(hoja&"!$A:$ZZ"), fila, columna ), IF(valor="-", "", valor) ), "") | AE14: =AC14-AD14 -> 0 | AF14: {=IFERROR(SUMIF(Consolidado!$C$3:$C63, $A14, INDEX(Consolidado!$E$3:$P$100, , MATCH(AF$1, Consolidado!$E$2:$P$2, 0))), "")} | AG14: =IFERROR( LET( hoja, LEFT(AG$1,3)&"R", fila, MATCH( RIGHT($A14, LEN($A14)-4), INDIRECT(hoja&"!$A:$A"), 0 ), columna, MATCH( "Totales", INDIRECT(hoja&"!$6:$6"), 0 ), valor, INDEX( INDIRECT(hoja&"!$A:$ZZ"), fila, columna ), IF(valor="-", "", valor) ), "") | AH14: =AF14-AG14 -> 0 | AI14: {=IFERROR(SUMIF(Consolidado!$C$3:$C63, $A14, INDEX(Consolidado!$E$3:$P$100, , MATCH(AI$1, Consolidado!$E$2:$P$2, 0))), "")} | AJ14: =IFERROR( LET( hoja, LEFT(AJ$1,3)&"R", fila, MATCH( RIGHT($A14, LEN($A14)-4), INDIRECT(hoja&"!$A:$A"), 0 ), columna, MATCH( "Totales", INDIRECT(hoja&"!$6:$6"), 0 ), valor, INDEX( INDIRECT(hoja&"!$A:$ZZ"), fila, columna ), IF(valor="-", "", valor) ), "") | AK14: =AI14-AJ14 -> 0 | AL14: {=IFERROR(SUMIF(Consolidado!$C$3:$C63, $A14, INDEX(Consolidado!$E$3:$P$100, , MATCH(AL$1, Consolidado!$E$2:$P$2, 0))), "")} | AM14: =IFERROR( LET( hoja, LEFT(AM$1,3)&"R", fila, MATCH( RIGHT($A14, LEN($A14)-4), INDIRECT(hoja&"!$A:$A"), 0 ), columna, MATCH( "Totales", INDIRECT(hoja&"!$6:$6"), 0 ), valor, INDEX( INDIRECT(hoja&"!$A:$ZZ"), fila, columna ), IF(valor="-", "", valor) ), "") | AN14: =AL14-AM14 -> 0
A15: =Menus!B8 -> B05 2.5% sobre nomina | B15: =SUM(IF(MONTH(TODAY())>1,E15,0), IF(MONTH(TODAY())>2,H15,0), IF(MONTH(TODAY())>3,K15,0), IF(MONTH(TODAY())>4,N15,0), IF(MONTH(TODAY())>5,Q15,0), IF(MONTH(TODAY())>6,T15,0), IF(MONTH(TODAY())>7,W15,0), IF(MONTH(TODAY())>8,Z15,0), IF(MONTH(TODAY())>9,AC15,0), IF(MONTH(TODAY())>10,AF15,0), IF(MONTH(TODAY())>11,AI15,0), IF(MONTH(TODAY())>12,AL15,0)) -> 0 | C15: =SUM(IF(MONTH(TODAY())>1,F15,0), IF(MONTH(TODAY())>2,I15,0), IF(MONTH(TODAY())>3,L15,0), IF(MONTH(TODAY())>4,O15,0), IF(MONTH(TODAY())>5,R15,0), IF(MONTH(TODAY())>6,U15,0), IF(MONTH(TODAY())>7,X15,0), IF(MONTH(TODAY())>8,AA15,0), IF(MONTH(TODAY())>9,AD15,0), IF(MONTH(TODAY())>10,AG15,0), IF(MONTH(TODAY())>11,AJ15,0), IF(MONTH(TODAY())>12,AM15,0)) -> 0 | D15: =B15-C15 -> 0 | E15: {=IFERROR(SUMIF(Consolidado!$C$3:$C63, $A15, INDEX(Consolidado!$E$3:$P$100, , MATCH(E$1, Consolidado!$E$2:$P$2, 0))), "")} | F15: =IFERROR( LET( hoja, LEFT(F$1,3)&"R", fila, MATCH( RIGHT($A15, LEN($A15)-4), INDIRECT(hoja&"!$A:$A"), 0 ), columna, MATCH( "Totales", INDIRECT(hoja&"!$6:$6"), 0 ), valor, INDEX( INDIRECT(hoja&"!$A:$ZZ"), fila, columna ), IF(valor="-", "", valor) ), "") | G15: =E15-F15 -> 0 | H15: {=IFERROR(SUMIF(Consolidado!$C$3:$C63, $A15, INDEX(Consolidado!$E$3:$P$100, , MATCH(H$1, Consolidado!$E$2:$P$2, 0))), "")} | I15: =IFERROR( LET( hoja, LEFT(I$1,3)&"R", fila, MATCH( RIGHT($A15, LEN($A15)-4), INDIRECT(hoja&"!$A:$A"), 0 ), columna, MATCH( "Totales", INDIRECT(hoja&"!$6:$6"), 0 ), valor, INDEX( INDIRECT(hoja&"!$A:$ZZ"), fila, columna ), IF(valor="-", "", valor) ), "") | J15: =H15-I15 -> 0 | K15: {=IFERROR(SUMIF(Consolidado!$C$3:$C63, $A15, INDEX(Consolidado!$E$3:$P$100, , MATCH(K$1, Consolidado!$E$2:$P$2, 0))), "")} | L15: =IFERROR( LET( hoja, LEFT(L$1,3)&"R", fila, MATCH( RIGHT($A15, LEN($A15)-4), INDIRECT(hoja&"!$A:$A"), 0 ), columna, MATCH( "Totales", INDIRECT(hoja&"!$6:$6"), 0 ), valor, INDEX( INDIRECT(hoja&"!$A:$ZZ"), fila, columna ), IF(valor="-", "", valor) ), "") | M15: =K15-L15 -> 0 | N15: {=IFERROR(SUMIF(Consolidado!$C$3:$C63, $A15, INDEX(Consolidado!$E$3:$P$100, , MATCH(N$1, Consolidado!$E$2:$P$2, 0))), "")} | O15: =IFERROR( LET( hoja, LEFT(O$1,3)&"R", fila, MATCH( RIGHT($A15, LEN($A15)-4), INDIRECT(hoja&"!$A:$A"), 0 ), columna, MATCH( "Totales", INDIRECT(hoja&"!$6:$6"), 0 ), valor, INDEX( INDIRECT(hoja&"!$A:$ZZ"), fila, columna ), IF(valor="-", "", valor) ), "") | P15: =N15-O15 -> 0 | Q15: {=IFERROR(SUMIF(Consolidado!$C$3:$C63, $A15, INDEX(Consolidado!$E$3:$P$100, , MATCH(Q$1, Consolidado!$E$2:$P$2, 0))), "")} | R15: =IFERROR( LET( hoja, LEFT(R$1,3)&"R", fila, MATCH( RIGHT($A15, LEN($A15)-4), INDIRECT(hoja&"!$A:$A"), 0 ), columna, MATCH( "Totales", INDIRECT(hoja&"!$6:$6"), 0 ), valor, INDEX( INDIRECT(hoja&"!$A:$ZZ"), fila, columna ), IF(valor="-", "", valor) ), "") | S15: =Q15-R15 -> 0 | T15: {=IFERROR(SUMIF(Consolidado!$C$3:$C63, $A15, INDEX(Consolidado!$E$3:$P$100, , MATCH(T$1, Consolidado!$E$2:$P$2, 0))), "")} | U15: =IFERROR( LET( hoja, LEFT(U$1,3)&"R", fila, MATCH( RIGHT($A15, LEN($A15)-4), INDIRECT(hoja&"!$A:$A"), 0 ), columna, MATCH( "Totales", INDIRECT(hoja&"!$6:$6"), 0 ), valor, INDEX( INDIRECT(hoja&"!$A:$ZZ"), fila, columna ), IF(valor="-", "", valor) ), "") | V15: =T15-U15 -> 0 | W15: {=IFERROR(SUMIF(Consolidado!$C$3:$C63, $A15, INDEX(Consolidado!$E$3:$P$100, , MATCH(W$1, Consolidado!$E$2:$P$2, 0))), "")} | X15: =IFERROR( LET( hoja, LEFT(X$1,3)&"R", fila, MATCH( RIGHT($A15, LEN($A15)-4), INDIRECT(hoja&"!$A:$A"), 0 ), columna, MATCH( "Totales", INDIRECT(hoja&"!$6:$6"), 0 ), valor, INDEX( INDIRECT(hoja&"!$A:$ZZ"), fila, columna ), IF(valor="-", "", valor) ), "") | Y15: =W15-X15 -> 0 | Z15: {=IFERROR(SUMIF(Consolidado!$C$3:$C63, $A15, INDEX(Consolidado!$E$3:$P$100, , MATCH(Z$1, Consolidado!$E$2:$P$2, 0))), "")} | AA15: =IFERROR( LET( hoja, LEFT(AA$1,3)&"R", fila, MATCH( RIGHT($A15, LEN($A15)-4), INDIRECT(hoja&"!$A:$A"), 0 ), columna, MATCH( "Totales", INDIRECT(hoja&"!$6:$6"), 0 ), valor, INDEX( INDIRECT(hoja&"!$A:$ZZ"), fila, columna ), IF(valor="-", "", valor) ), "") | AB15: =Z15-AA15 -> 0 | AC15: {=IFERROR(SUMIF(Consolidado!$C$3:$C63, $A15, INDEX(Consolidado!$E$3:$P$100, , MATCH(AC$1, Consolidado!$E$2:$P$2, 0))), "")} | AD15: =IFERROR( LET( hoja, LEFT(AD$1,3)&"R", fila, MATCH( RIGHT($A15, LEN($A15)-4), INDIRECT(hoja&"!$A:$A"), 0 ), columna, MATCH( "Totales", INDIRECT(hoja&"!$6:$6"), 0 ), valor, INDEX( INDIRECT(hoja&"!$A:$ZZ"), fila, columna ), IF(valor="-", "", valor) ), "") | AE15: =AC15-AD15 -> 0 | AF15: {=IFERROR(SUMIF(Consolidado!$C$3:$C63, $A15, INDEX(Consolidado!$E$3:$P$100, , MATCH(AF$1, Consolidado!$E$2:$P$2, 0))), "")} | AG15: =IFERROR( LET( hoja, LEFT(AG$1,3)&"R", fila, MATCH( RIGHT($A15, LEN($A15)-4), INDIRECT(hoja&"!$A:$A"), 0 ), columna, MATCH( "Totales", INDIRECT(hoja&"!$6:$6"), 0 ), valor, INDEX( INDIRECT(hoja&"!$A:$ZZ"), fila, columna ), IF(valor="-", "", valor) ), "") | AH15: =AF15-AG15 -> 0 | AI15: {=IFERROR(SUMIF(Consolidado!$C$3:$C63, $A15, INDEX(Consolidado!$E$3:$P$100, , MATCH(AI$1, Consolidado!$E$2:$P$2, 0))), "")} | AJ15: =IFERROR( LET( hoja, LEFT(AJ$1,3)&"R", fila, MATCH( RIGHT($A15, LEN($A15)-4), INDIRECT(hoja&"!$A:$A"), 0 ), columna, MATCH( "Totales", INDIRECT(hoja&"!$6:$6"), 0 ), valor, INDEX( INDIRECT(hoja&"!$A:$ZZ"), fila, columna ), IF(valor="-", "", valor) ), "") | AK15: =AI15-AJ15 -> 0 | AL15: {=IFERROR(SUMIF(Consolidado!$C$3:$C63, $A15, INDEX(Consolidado!$E$3:$P$100, , MATCH(AL$1, Consolidado!$E$2:$P$2, 0))), "")} | AM15: =IFERROR( LET( hoja, LEFT(AM$1,3)&"R", fila, MATCH( RIGHT($A15, LEN($A15)-4), INDIRECT(hoja&"!$A:$A"), 0 ), columna, MATCH( "Totales", INDIRECT(hoja&"!$6:$6"), 0 ), valor, INDEX( INDIRECT(hoja&"!$A:$ZZ"), fila, columna ), IF(valor="-", "", valor) ), "") | AN15: =AL15-AM15 -> 0
A16: =Menus!B9 -> B06 Aguinaldo | B16: =SUM(IF(MONTH(TODAY())>1,E16,0), IF(MONTH(TODAY())>2,H16,0), IF(MONTH(TODAY())>3,K16,0), IF(MONTH(TODAY())>4,N16,0), IF(MONTH(TODAY())>5,Q16,0), IF(MONTH(TODAY())>6,T16,0), IF(MONTH(TODAY())>7,W16,0), IF(MONTH(TODAY())>8,Z16,0), IF(MONTH(TODAY())>9,AC16,0), IF(MONTH(TODAY())>10,AF16,0), IF(MONTH(TODAY())>11,AI16,0), IF(MONTH(TODAY())>12,AL16,0)) -> 0 | C16: =SUM(IF(MONTH(TODAY())>1,F16,0), IF(MONTH(TODAY())>2,I16,0), IF(MONTH(TODAY())>3,L16,0), IF(MONTH(TODAY())>4,O16,0), IF(MONTH(TODAY())>5,R16,0), IF(MONTH(TODAY())>6,U16,0), IF(MONTH(TODAY())>7,X16,0), IF(MONTH(TODAY())>8,AA16,0), IF(MONTH(TODAY())>9,AD16,0), IF(MONTH(TODAY())>10,AG16,0), IF(MONTH(TODAY())>11,AJ16,0), IF(MONTH(TODAY())>12,AM16,0)) -> 0 | D16: =B16-C16 -> 0 | E16: {=IFERROR(SUMIF(Consolidado!$C$3:$C63, $A16, INDEX(Consolidado!$E$3:$P$100, , MATCH(E$1, Consolidado!$E$2:$P$2, 0))), "")} | F16: =IFERROR( LET( hoja, LEFT(F$1,3)&"R", fila, MATCH( RIGHT($A16, LEN($A16)-4), INDIRECT(hoja&"!$A:$A"), 0 ), columna, MATCH( "Totales", INDIRECT(hoja&"!$6:$6"), 0 ), valor, INDEX( INDIRECT(hoja&"!$A:$ZZ"), fila, columna ), IF(valor="-", "", valor) ), "") | G16: =E16-F16 -> 0 | H16: {=IFERROR(SUMIF(Consolidado!$C$3:$C63, $A16, INDEX(Consolidado!$E$3:$P$100, , MATCH(H$1, Consolidado!$E$2:$P$2, 0))), "")} | I16: =IFERROR( LET( hoja, LEFT(I$1,3)&"R", fila, MATCH( RIGHT($A16, LEN($A16)-4), INDIRECT(hoja&"!$A:$A"), 0 ), columna, MATCH( "Totales", INDIRECT(hoja&"!$6:$6"), 0 ), valor, INDEX( INDIRECT(hoja&"!$A:$ZZ"), fila, columna ), IF(valor="-", "", valor) ), "") | J16: =H16-I16 -> 0 | K16: {=IFERROR(SUMIF(Consolidado!$C$3:$C63, $A16, INDEX(Consolidado!$E$3:$P$100, , MATCH(K$1, Consolidado!$E$2:$P$2, 0))), "")} | L16: =IFERROR( LET( hoja, LEFT(L$1,3)&"R", fila, MATCH( RIGHT($A16, LEN($A16)-4), INDIRECT(hoja&"!$A:$A"), 0 ), columna, MATCH( "Totales", INDIRECT(hoja&"!$6:$6"), 0 ), valor, INDEX( INDIRECT(hoja&"!$A:$ZZ"), fila, columna ), IF(valor="-", "", valor) ), "") | M16: =K16-L16 -> 0 | N16: {=IFERROR(SUMIF(Consolidado!$C$3:$C63, $A16, INDEX(Consolidado!$E$3:$P$100, , MATCH(N$1, Consolidado!$E$2:$P$2, 0))), "")} | O16: =IFERROR( LET( hoja, LEFT(O$1,3)&"R", fila, MATCH( RIGHT($A16, LEN($A16)-4), INDIRECT(hoja&"!$A:$A"), 0 ), columna, MATCH( "Totales", INDIRECT(hoja&"!$6:$6"), 0 ), valor, INDEX( INDIRECT(hoja&"!$A:$ZZ"), fila, columna ), IF(valor="-", "", valor) ), "") | P16: =N16-O16 -> 0 | Q16: {=IFERROR(SUMIF(Consolidado!$C$3:$C63, $A16, INDEX(Consolidado!$E$3:$P$100, , MATCH(Q$1, Consolidado!$E$2:$P$2, 0))), "")} | R16: =IFERROR( LET( hoja, LEFT(R$1,3)&"R", fila, MATCH( RIGHT($A16, LEN($A16)-4), INDIRECT(hoja&"!$A:$A"), 0 ), columna, MATCH( "Totales", INDIRECT(hoja&"!$6:$6"), 0 ), valor, INDEX( INDIRECT(hoja&"!$A:$ZZ"), fila, columna ), IF(valor="-", "", valor) ), "") | S16: =Q16-R16 -> 0 | T16: {=IFERROR(SUMIF(Consolidado!$C$3:$C63, $A16, INDEX(Consolidado!$E$3:$P$100, , MATCH(T$1, Consolidado!$E$2:$P$2, 0))), "")} | U16: =IFERROR( LET( hoja, LEFT(U$1,3)&"R", fila, MATCH( RIGHT($A16, LEN($A16)-4), INDIRECT(hoja&"!$A:$A"), 0 ), columna, MATCH( "Totales", INDIRECT(hoja&"!$6:$6"), 0 ), valor, INDEX( INDIRECT(hoja&"!$A:$ZZ"), fila, columna ), IF(valor="-", "", valor) ), "") | V16: =T16-U16 -> 0 | W16: {=IFERROR(SUMIF(Consolidado!$C$3:$C63, $A16, INDEX(Consolidado!$E$3:$P$100, , MATCH(W$1, Consolidado!$E$2:$P$2, 0))), "")} | X16: =IFERROR( LET( hoja, LEFT(X$1,3)&"R", fila, MATCH( RIGHT($A16, LEN($A16)-4), INDIRECT(hoja&"!$A:$A"), 0 ), columna, MATCH( "Totales", INDIRECT(hoja&"!$6:$6"), 0 ), valor, INDEX( INDIRECT(hoja&"!$A:$ZZ"), fila, columna ), IF(valor="-", "", valor) ), "") | Y16: =W16-X16 -> 0 | Z16: {=IFERROR(SUMIF(Consolidado!$C$3:$C63, $A16, INDEX(Consolidado!$E$3:$P$100, , MATCH(Z$1, Consolidado!$E$2:$P$2, 0))), "")} | AA16: =IFERROR( LET( hoja, LEFT(AA$1,3)&"R", fila, MATCH( RIGHT($A16, LEN($A16)-4), INDIRECT(hoja&"!$A:$A"), 0 ), columna, MATCH( "Totales", INDIRECT(hoja&"!$6:$6"), 0 ), valor, INDEX( INDIRECT(hoja&"!$A:$ZZ"), fila, columna ), IF(valor="-", "", valor) ), "") | AB16: =Z16-AA16 -> 0 | AC16: {=IFERROR(SUMIF(Consolidado!$C$3:$C63, $A16, INDEX(Consolidado!$E$3:$P$100, , MATCH(AC$1, Consolidado!$E$2:$P$2, 0))), "")} | AD16: =IFERROR( LET( hoja, LEFT(AD$1,3)&"R", fila, MATCH( RIGHT($A16, LEN($A16)-4), INDIRECT(hoja&"!$A:$A"), 0 ), columna, MATCH( "Totales", INDIRECT(hoja&"!$6:$6"), 0 ), valor, INDEX( INDIRECT(hoja&"!$A:$ZZ"), fila, columna ), IF(valor="-", "", valor) ), "") | AE16: =AC16-AD16 -> 0 | AF16: {=IFERROR(SUMIF(Consolidado!$C$3:$C63, $A16, INDEX(Consolidado!$E$3:$P$100, , MATCH(AF$1, Consolidado!$E$2:$P$2, 0))), "")} | AG16: =IFERROR( LET( hoja, LEFT(AG$1,3)&"R", fila, MATCH( RIGHT($A16, LEN($A16)-4), INDIRECT(hoja&"!$A:$A"), 0 ), columna, MATCH( "Totales", INDIRECT(hoja&"!$6:$6"), 0 ), valor, INDEX( INDIRECT(hoja&"!$A:$ZZ"), fila, columna ), IF(valor="-", "", valor) ), "") | AH16: =AF16-AG16 -> 0 | AI16: {=IFERROR(SUMIF(Consolidado!$C$3:$C63, $A16, INDEX(Consolidado!$E$3:$P$100, , MATCH(AI$1, Consolidado!$E$2:$P$2, 0))), "")} | AJ16: =IFERROR( LET( hoja, LEFT(AJ$1,3)&"R", fila, MATCH( RIGHT($A16, LEN($A16)-4), INDIRECT(hoja&"!$A:$A"), 0 ), columna, MATCH( "Totales", INDIRECT(hoja&"!$6:$6"), 0 ), valor, INDEX( INDIRECT(hoja&"!$A:$ZZ"), fila, columna ), IF(valor="-", "", valor) ), "") | AK16: =AI16-AJ16 -> 0 | AL16: {=IFERROR(SUMIF(Consolidado!$C$3:$C63, $A16, INDEX(Consolidado!$E$3:$P$100, , MATCH(AL$1, Consolidado!$E$2:$P$2, 0))), "")} | AM16: =IFERROR( LET( hoja, LEFT(AM$1,3)&"R", fila, MATCH( RIGHT($A16, LEN($A16)-4), INDIRECT(hoja&"!$A:$A"), 0 ), columna, MATCH( "Totales", INDIRECT(hoja&"!$6:$6"), 0 ), valor, INDEX( INDIRECT(hoja&"!$A:$ZZ"), fila, columna ), IF(valor="-", "", valor) ), "") | AN16: =AL16-AM16 -> 0
A17: =Menus!B10 -> B07 Comisiones Bancarias | B17: =SUM(IF(MONTH(TODAY())>1,E17,0), IF(MONTH(TODAY())>2,H17,0), IF(MONTH(TODAY())>3,K17,0), IF(MONTH(TODAY())>4,N17,0), IF(MONTH(TODAY())>5,Q17,0), IF(MONTH(TODAY())>6,T17,0), IF(MONTH(TODAY())>7,W17,0), IF(MONTH(TODAY())>8,Z17,0), IF(MONTH(TODAY())>9,AC17,0), IF(MONTH(TODAY())>10,AF17,0), IF(MONTH(TODAY())>11,AI17,0), IF(MONTH(TODAY())>12,AL17,0)) -> 0 | C17: =SUM(IF(MONTH(TODAY())>1,F17,0), IF(MONTH(TODAY())>2,I17,0), IF(MONTH(TODAY())>3,L17,0), IF(MONTH(TODAY())>4,O17,0), IF(MONTH(TODAY())>5,R17,0), IF(MONTH(TODAY())>6,U17,0), IF(MONTH(TODAY())>7,X17,0), IF(MONTH(TODAY())>8,AA17,0), IF(MONTH(TODAY())>9,AD17,0), IF(MONTH(TODAY())>10,AG17,0), IF(MONTH(TODAY())>11,AJ17,0), IF(MONTH(TODAY())>12,AM17,0)) -> 0 | D17: =B17-C17 -> 0 | E17: {=IFERROR(SUMIF(Consolidado!$C$3:$C63, $A17, INDEX(Consolidado!$E$3:$P$100, , MATCH(E$1, Consolidado!$E$2:$P$2, 0))), "")} | F17: =IFERROR( LET( hoja, LEFT(F$1,3)&"R", fila, MATCH( RIGHT($A17, LEN($A17)-4), INDIRECT(hoja&"!$A:$A"), 0 ), columna, MATCH( "Totales", INDIRECT(hoja&"!$6:$6"), 0 ), valor, INDEX( INDIRECT(hoja&"!$A:$ZZ"), fila, columna ), IF(valor="-", "", valor) ), "") | G17: =E17-F17 -> 0 | H17: {=IFERROR(SUMIF(Consolidado!$C$3:$C63, $A17, INDEX(Consolidado!$E$3:$P$100, , MATCH(H$1, Consolidado!$E$2:$P$2, 0))), "")} | I17: =IFERROR( LET( hoja, LEFT(I$1,3)&"R", fila, MATCH( RIGHT($A17, LEN($A17)-4), INDIRECT(hoja&"!$A:$A"), 0 ), columna, MATCH( "Totales", INDIRECT(hoja&"!$6:$6"), 0 ), valor, INDEX( INDIRECT(hoja&"!$A:$ZZ"), fila, columna ), IF(valor="-", "", valor) ), "") | J17: =H17-I17 -> 0 | K17: {=IFERROR(SUMIF(Consolidado!$C$3:$C63, $A17, INDEX(Consolidado!$E$3:$P$100, , MATCH(K$1, Consolidado!$E$2:$P$2, 0))), "")} | L17: =IFERROR( LET( hoja, LEFT(L$1,3)&"R", fila, MATCH( RIGHT($A17, LEN($A17)-4), INDIRECT(hoja&"!$A:$A"), 0 ), columna, MATCH( "Totales", INDIRECT(hoja&"!$6:$6"), 0 ), valor, INDEX( INDIRECT(hoja&"!$A:$ZZ"), fila, columna ), IF(valor="-", "", valor) ), "") | M17: =K17-L17 -> 0 | N17: {=IFERROR(SUMIF(Consolidado!$C$3:$C63, $A17, INDEX(Consolidado!$E$3:$P$100, , MATCH(N$1, Consolidado!$E$2:$P$2, 0))), "")} | O17: =IFERROR( LET( hoja, LEFT(O$1,3)&"R", fila, MATCH( RIGHT($A17, LEN($A17)-4), INDIRECT(hoja&"!$A:$A"), 0 ), columna, MATCH( "Totales", INDIRECT(hoja&"!$6:$6"), 0 ), valor, INDEX( INDIRECT(hoja&"!$A:$ZZ"), fila, columna ), IF(valor="-", "", valor) ), "") | P17: =N17-O17 -> 0 | Q17: {=IFERROR(SUMIF(Consolidado!$C$3:$C63, $A17, INDEX(Consolidado!$E$3:$P$100, , MATCH(Q$1, Consolidado!$E$2:$P$2, 0))), "")} | R17: =IFERROR( LET( hoja, LEFT(R$1,3)&"R", fila, MATCH( RIGHT($A17, LEN($A17)-4), INDIRECT(hoja&"!$A:$A"), 0 ), columna, MATCH( "Totales", INDIRECT(hoja&"!$6:$6"), 0 ), valor, INDEX( INDIRECT(hoja&"!$A:$ZZ"), fila, columna ), IF(valor="-", "", valor) ), "") | S17: =Q17-R17 -> 0 | T17: {=IFERROR(SUMIF(Consolidado!$C$3:$C63, $A17, INDEX(Consolidado!$E$3:$P$100, , MATCH(T$1, Consolidado!$E$2:$P$2, 0))), "")} | U17: =IFERROR( LET( hoja, LEFT(U$1,3)&"R", fila, MATCH( RIGHT($A17, LEN($A17)-4), INDIRECT(hoja&"!$A:$A"), 0 ), columna, MATCH( "Totales", INDIRECT(hoja&"!$6:$6"), 0 ), valor, INDEX( INDIRECT(hoja&"!$A:$ZZ"), fila, columna ), IF(valor="-", "", valor) ), "") | V17: =T17-U17 -> 0 | W17: {=IFERROR(SUMIF(Consolidado!$C$3:$C63, $A17, INDEX(Consolidado!$E$3:$P$100, , MATCH(W$1, Consolidado!$E$2:$P$2, 0))), "")} | X17: =IFERROR( LET( hoja, LEFT(X$1,3)&"R", fila, MATCH( RIGHT($A17, LEN($A17)-4), INDIRECT(hoja&"!$A:$A"), 0 ), columna, MATCH( "Totales", INDIRECT(hoja&"!$6:$6"), 0 ), valor, INDEX( INDIRECT(hoja&"!$A:$ZZ"), fila, columna ), IF(valor="-", "", valor) ), "") | Y17: =W17-X17 -> 0 | Z17: {=IFERROR(SUMIF(Consolidado!$C$3:$C63, $A17, INDEX(Consolidado!$E$3:$P$100, , MATCH(Z$1, Consolidado!$E$2:$P$2, 0))), "")} | AA17: =IFERROR( LET( hoja, LEFT(AA$1,3)&"R", fila, MATCH( RIGHT($A17, LEN($A17)-4), INDIRECT(hoja&"!$A:$A"), 0 ), columna, MATCH( "Totales", INDIRECT(hoja&"!$6:$6"), 0 ), valor, INDEX( INDIRECT(hoja&"!$A:$ZZ"), fila, columna ), IF(valor="-", "", valor) ), "") | AB17: =Z17-AA17 -> 0 | AC17: {=IFERROR(SUMIF(Consolidado!$C$3:$C63, $A17, INDEX(Consolidado!$E$3:$P$100, , MATCH(AC$1, Consolidado!$E$2:$P$2, 0))), "")} | AD17: =IFERROR( LET( hoja, LEFT(AD$1,3)&"R", fila, MATCH( RIGHT($A17, LEN($A17)-4), INDIRECT(hoja&"!$A:$A"), 0 ), columna, MATCH( "Totales", INDIRECT(hoja&"!$6:$6"), 0 ), valor, INDEX( INDIRECT(hoja&"!$A:$ZZ"), fila, columna ), IF(valor="-", "", valor) ), "") | AE17: =AC17-AD17 -> 0 | AF17: {=IFERROR(SUMIF(Consolidado!$C$3:$C63, $A17, INDEX(Consolidado!$E$3:$P$100, , MATCH(AF$1, Consolidado!$E$2:$P$2, 0))), "")} | AG17: =IFERROR( LET( hoja, LEFT(AG$1,3)&"R", fila, MATCH( RIGHT($A17, LEN($A17)-4), INDIRECT(hoja&"!$A:$A"), 0 ), columna, MATCH( "Totales", INDIRECT(hoja&"!$6:$6"), 0 ), valor, INDEX( INDIRECT(hoja&"!$A:$ZZ"), fila, columna ), IF(valor="-", "", valor) ), "") | AH17: =AF17-AG17 -> 0 | AI17: {=IFERROR(SUMIF(Consolidado!$C$3:$C63, $A17, INDEX(Consolidado!$E$3:$P$100, , MATCH(AI$1, Consolidado!$E$2:$P$2, 0))), "")} | AJ17: =IFERROR( LET( hoja, LEFT(AJ$1,3)&"R", fila, MATCH( RIGHT($A17, LEN($A17)-4), INDIRECT(hoja&"!$A:$A"), 0 ), columna, MATCH( "Totales", INDIRECT(hoja&"!$6:$6"), 0 ), valor, INDEX( INDIRECT(hoja&"!$A:$ZZ"), fila, columna ), IF(valor="-", "", valor) ), "") | AK17: =AI17-AJ17 -> 0 | AL17: {=IFERROR(SUMIF(Consolidado!$C$3:$C63, $A17, INDEX(Consolidado!$E$3:$P$100, , MATCH(AL$1, Consolidado!$E$2:$P$2, 0))), "")} | AM17: =IFERROR( LET( hoja, LEFT(AM$1,3)&"R", fila, MATCH( RIGHT($A17, LEN($A17)-4), INDIRECT(hoja&"!$A:$A"), 0 ), columna, MATCH( "Totales", INDIRECT(hoja&"!$6:$6"), 0 ), valor, INDEX( INDIRECT(hoja&"!$A:$ZZ"), fila, columna ), IF(valor="-", "", valor) ), "") | AN17: =AL17-AM17 -> 0
A18: =Menus!B11 -> B08 Licencias y permisos | B18: =SUM(IF(MONTH(TODAY())>1,E18,0), IF(MONTH(TODAY())>2,H18,0), IF(MONTH(TODAY())>3,K18,0), IF(MONTH(TODAY())>4,N18,0), IF(MONTH(TODAY())>5,Q18,0), IF(MONTH(TODAY())>6,T18,0), IF(MONTH(TODAY())>7,W18,0), IF(MONTH(TODAY())>8,Z18,0), IF(MONTH(TODAY())>9,AC18,0), IF(MONTH(TODAY())>10,AF18,0), IF(MONTH(TODAY())>11,AI18,0), IF(MONTH(TODAY())>12,AL18,0)) -> 0 | C18: =SUM(IF(MONTH(TODAY())>1,F18,0), IF(MONTH(TODAY())>2,I18,0), IF(MONTH(TODAY())>3,L18,0), IF(MONTH(TODAY())>4,O18,0), IF(MONTH(TODAY())>5,R18,0), IF(MONTH(TODAY())>6,U18,0), IF(MONTH(TODAY())>7,X18,0), IF(MONTH(TODAY())>8,AA18,0), IF(MONTH(TODAY())>9,AD18,0), IF(MONTH(TODAY())>10,AG18,0), IF(MONTH(TODAY())>11,AJ18,0), IF(MONTH(TODAY())>12,AM18,0)) -> 0 | D18: =B18-C18 -> 0 | E18: {=IFERROR(SUMIF(Consolidado!$C$3:$C63, $A18, INDEX(Consolidado!$E$3:$P$100, , MATCH(E$1, Consolidado!$E$2:$P$2, 0))), "")} | F18: =IFERROR( LET( hoja, LEFT(F$1,3)&"R", fila, MATCH( RIGHT($A18, LEN($A18)-4), INDIRECT(hoja&"!$A:$A"), 0 ), columna, MATCH( "Totales", INDIRECT(hoja&"!$6:$6"), 0 ), valor, INDEX( INDIRECT(hoja&"!$A:$ZZ"), fila, columna ), IF(valor="-", "", valor) ), "") | G18: =E18-F18 -> 0 | H18: {=IFERROR(SUMIF(Consolidado!$C$3:$C63, $A18, INDEX(Consolidado!$E$3:$P$100, , MATCH(H$1, Consolidado!$E$2:$P$2, 0))), "")} | I18: =IFERROR( LET( hoja, LEFT(I$1,3)&"R", fila, MATCH( RIGHT($A18, LEN($A18)-4), INDIRECT(hoja&"!$A:$A"), 0 ), columna, MATCH( "Totales", INDIRECT(hoja&"!$6:$6"), 0 ), valor, INDEX( INDIRECT(hoja&"!$A:$ZZ"), fila, columna ), IF(valor="-", "", valor) ), "") | J18: =H18-I18 -> 0 | K18: {=IFERROR(SUMIF(Consolidado!$C$3:$C63, $A18, INDEX(Consolidado!$E$3:$P$100, , MATCH(K$1, Consolidado!$E$2:$P$2, 0))), "")} | L18: =IFERROR( LET( hoja, LEFT(L$1,3)&"R", fila, MATCH( RIGHT($A18, LEN($A18)-4), INDIRECT(hoja&"!$A:$A"), 0 ), columna, MATCH( "Totales", INDIRECT(hoja&"!$6:$6"), 0 ), valor, INDEX( INDIRECT(hoja&"!$A:$ZZ"), fila, columna ), IF(valor="-", "", valor) ), "") | M18: =K18-L18 -> 0 | N18: {=IFERROR(SUMIF(Consolidado!$C$3:$C63, $A18, INDEX(Consolidado!$E$3:$P$100, , MATCH(N$1, Consolidado!$E$2:$P$2, 0))), "")} | O18: =IFERROR( LET( hoja, LEFT(O$1,3)&"R", fila, MATCH( RIGHT($A18, LEN($A18)-4), INDIRECT(hoja&"!$A:$A"), 0 ), columna, MATCH( "Totales", INDIRECT(hoja&"!$6:$6"), 0 ), valor, INDEX( INDIRECT(hoja&"!$A:$ZZ"), fila, columna ), IF(valor="-", "", valor) ), "") | P18: =N18-O18 -> 0 | Q18: {=IFERROR(SUMIF(Consolidado!$C$3:$C63, $A18, INDEX(Consolidado!$E$3:$P$100, , MATCH(Q$1, Consolidado!$E$2:$P$2, 0))), "")} | R18: =IFERROR( LET( hoja, LEFT(R$1,3)&"R", fila, MATCH( RIGHT($A18, LEN($A18)-4), INDIRECT(hoja&"!$A:$A"), 0 ), columna, MATCH( "Totales", INDIRECT(hoja&"!$6:$6"), 0 ), valor, INDEX( INDIRECT(hoja&"!$A:$ZZ"), fila, columna ), IF(valor="-", "", valor) ), "") | S18: =Q18-R18 -> 0 | T18: {=IFERROR(SUMIF(Consolidado!$C$3:$C63, $A18, INDEX(Consolidado!$E$3:$P$100, , MATCH(T$1, Consolidado!$E$2:$P$2, 0))), "")} | U18: =IFERROR( LET( hoja, LEFT(U$1,3)&"R", fila, MATCH( RIGHT($A18, LEN($A18)-4), INDIRECT(hoja&"!$A:$A"), 0 ), columna, MATCH( "Totales", INDIRECT(hoja&"!$6:$6"), 0 ), valor, INDEX( INDIRECT(hoja&"!$A:$ZZ"), fila, columna ), IF(valor="-", "", valor) ), "") | V18: =T18-U18 -> 0 | W18: {=IFERROR(SUMIF(Consolidado!$C$3:$C63, $A18, INDEX(Consolidado!$E$3:$P$100, , MATCH(W$1, Consolidado!$E$2:$P$2, 0))), "")} | X18: =IFERROR( LET( hoja, LEFT(X$1,3)&"R", fila, MATCH( RIGHT($A18, LEN($A18)-4), INDIRECT(hoja&"!$A:$A"), 0 ), columna, MATCH( "Totales", INDIRECT(hoja&"!$6:$6"), 0 ), valor, INDEX( INDIRECT(hoja&"!$A:$ZZ"), fila, columna ), IF(valor="-", "", valor) ), "") | Y18: =W18-X18 -> 0 | Z18: {=IFERROR(SUMIF(Consolidado!$C$3:$C63, $A18, INDEX(Consolidado!$E$3:$P$100, , MATCH(Z$1, Consolidado!$E$2:$P$2, 0))), "")} | AA18: =IFERROR( LET( hoja, LEFT(AA$1,3)&"R", fila, MATCH( RIGHT($A18, LEN($A18)-4), INDIRECT(hoja&"!$A:$A"), 0 ), columna, MATCH( "Totales", INDIRECT(hoja&"!$6:$6"), 0 ), valor, INDEX( INDIRECT(hoja&"!$A:$ZZ"), fila, columna ), IF(valor="-", "", valor) ), "") | AB18: =Z18-AA18 -> 0 | AC18: {=IFERROR(SUMIF(Consolidado!$C$3:$C63, $A18, INDEX(Consolidado!$E$3:$P$100, , MATCH(AC$1, Consolidado!$E$2:$P$2, 0))), "")} | AD18: =IFERROR( LET( hoja, LEFT(AD$1,3)&"R", fila, MATCH( RIGHT($A18, LEN($A18)-4), INDIRECT(hoja&"!$A:$A"), 0 ), columna, MATCH( "Totales", INDIRECT(hoja&"!$6:$6"), 0 ), valor, INDEX( INDIRECT(hoja&"!$A:$ZZ"), fila, columna ), IF(valor="-", "", valor) ), "") | AE18: =AC18-AD18 -> 0 | AF18: {=IFERROR(SUMIF(Consolidado!$C$3:$C63, $A18, INDEX(Consolidado!$E$3:$P$100, , MATCH(AF$1, Consolidado!$E$2:$P$2, 0))), "")} | AG18: =IFERROR( LET( hoja, LEFT(AG$1,3)&"R", fila, MATCH( RIGHT($A18, LEN($A18)-4), INDIRECT(hoja&"!$A:$A"), 0 ), columna, MATCH( "Totales", INDIRECT(hoja&"!$6:$6"), 0 ), valor, INDEX( INDIRECT(hoja&"!$A:$ZZ"), fila, columna ), IF(valor="-", "", valor) ), "") | AH18: =AF18-AG18 -> 0 | AI18: {=IFERROR(SUMIF(Consolidado!$C$3:$C63, $A18, INDEX(Consolidado!$E$3:$P$100, , MATCH(AI$1, Consolidado!$E$2:$P$2, 0))), "")} | AJ18: =IFERROR( LET( hoja, LEFT(AJ$1,3)&"R", fila, MATCH( RIGHT($A18, LEN($A18)-4), INDIRECT(hoja&"!$A:$A"), 0 ), columna, MATCH( "Totales", INDIRECT(hoja&"!$6:$6"), 0 ), valor, INDEX( INDIRECT(hoja&"!$A:$ZZ"), fila, columna ), IF(valor="-", "", valor) ), "") | AK18: =AI18-AJ18 -> 0 | AL18: {=IFERROR(SUMIF(Consolidado!$C$3:$C63, $A18, INDEX(Consolidado!$E$3:$P$100, , MATCH(AL$1, Consolidado!$E$2:$P$2, 0))), "")} | AM18: =IFERROR( LET( hoja, LEFT(AM$1,3)&"R", fila, MATCH( RIGHT($A18, LEN($A18)-4), INDIRECT(hoja&"!$A:$A"), 0 ), columna, MATCH( "Totales", INDIRECT(hoja&"!$6:$6"), 0 ), valor, INDEX( INDIRECT(hoja&"!$A:$ZZ"), fila, columna ), IF(valor="-", "", valor) ), "") | AN18: =AL18-AM18 -> 0
A19: =Menus!B12 -> B09 Uniformes | B19: =SUM(IF(MONTH(TODAY())>1,E19,0), IF(MONTH(TODAY())>2,H19,0), IF(MONTH(TODAY())>3,K19,0), IF(MONTH(TODAY())>4,N19,0), IF(MONTH(TODAY())>5,Q19,0), IF(MONTH(TODAY())>6,T19,0), IF(MONTH(TODAY())>7,W19,0), IF(MONTH(TODAY())>8,Z19,0), IF(MONTH(TODAY())>9,AC19,0), IF(MONTH(TODAY())>10,AF19,0), IF(MONTH(TODAY())>11,AI19,0), IF(MONTH(TODAY())>12,AL19,0)) -> 0 | C19: =SUM(IF(MONTH(TODAY())>1,F19,0), IF(MONTH(TODAY())>2,I19,0), IF(MONTH(TODAY())>3,L19,0), IF(MONTH(TODAY())>4,O19,0), IF(MONTH(TODAY())>5,R19,0), IF(MONTH(TODAY())>6,U19,0), IF(MONTH(TODAY())>7,X19,0), IF(MONTH(TODAY())>8,AA19,0), IF(MONTH(TODAY())>9,AD19,0), IF(MONTH(TODAY())>10,AG19,0), IF(MONTH(TODAY())>11,AJ19,0), IF(MONTH(TODAY())>12,AM19,0)) -> 0 | D19: =B19-C19 -> 0 | E19: {=IFERROR(SUMIF(Consolidado!$C$3:$C63, $A19, INDEX(Consolidado!$E$3:$P$100, , MATCH(E$1, Consolidado!$E$2:$P$2, 0))), "")} | F19: =IFERROR( LET( hoja, LEFT(F$1,3)&"R", fila, MATCH( RIGHT($A19, LEN($A19)-4), INDIRECT(hoja&"!$A:$A"), 0 ), columna, MATCH( "Totales", INDIRECT(hoja&"!$6:$6"), 0 ), valor, INDEX( INDIRECT(hoja&"!$A:$ZZ"), fila, columna ), IF(valor="-", "", valor) ), "") | G19: =E19-F19 -> 0 | H19: {=IFERROR(SUMIF(Consolidado!$C$3:$C63, $A19, INDEX(Consolidado!$E$3:$P$100, , MATCH(H$1, Consolidado!$E$2:$P$2, 0))), "")} | I19: =IFERROR( LET( hoja, LEFT(I$1,3)&"R", fila, MATCH( RIGHT($A19, LEN($A19)-4), INDIRECT(hoja&"!$A:$A"), 0 ), columna, MATCH( "Totales", INDIRECT(hoja&"!$6:$6"), 0 ), valor, INDEX( INDIRECT(hoja&"!$A:$ZZ"), fila, columna ), IF(valor="-", "", valor) ), "") | J19: =H19-I19 -> 0 | K19: {=IFERROR(SUMIF(Consolidado!$C$3:$C63, $A19, INDEX(Consolidado!$E$3:$P$100, , MATCH(K$1, Consolidado!$E$2:$P$2, 0))), "")} | L19: =IFERROR( LET( hoja, LEFT(L$1,3)&"R", fila, MATCH( RIGHT($A19, LEN($A19)-4), INDIRECT(hoja&"!$A:$A"), 0 ), columna, MATCH( "Totales", INDIRECT(hoja&"!$6:$6"), 0 ), valor, INDEX( INDIRECT(hoja&"!$A:$ZZ"), fila, columna ), IF(valor="-", "", valor) ), "") | M19: =K19-L19 -> 0 | N19: {=IFERROR(SUMIF(Consolidado!$C$3:$C63, $A19, INDEX(Consolidado!$E$3:$P$100, , MATCH(N$1, Consolidado!$E$2:$P$2, 0))), "")} | O19: =IFERROR( LET( hoja, LEFT(O$1,3)&"R", fila, MATCH( RIGHT($A19, LEN($A19)-4), INDIRECT(hoja&"!$A:$A"), 0 ), columna, MATCH( "Totales", INDIRECT(hoja&"!$6:$6"), 0 ), valor, INDEX( INDIRECT(hoja&"!$A:$ZZ"), fila, columna ), IF(valor="-", "", valor) ), "") | P19: =N19-O19 -> 0 | Q19: {=IFERROR(SUMIF(Consolidado!$C$3:$C63, $A19, INDEX(Consolidado!$E$3:$P$100, , MATCH(Q$1, Consolidado!$E$2:$P$2, 0))), "")} | R19: =IFERROR( LET( hoja, LEFT(R$1,3)&"R", fila, MATCH( RIGHT($A19, LEN($A19)-4), INDIRECT(hoja&"!$A:$A"), 0 ), columna, MATCH( "Totales", INDIRECT(hoja&"!$6:$6"), 0 ), valor, INDEX( INDIRECT(hoja&"!$A:$ZZ"), fila, columna ), IF(valor="-", "", valor) ), "") | S19: =Q19-R19 -> 0 | T19: {=IFERROR(SUMIF(Consolidado!$C$3:$C63, $A19, INDEX(Consolidado!$E$3:$P$100, , MATCH(T$1, Consolidado!$E$2:$P$2, 0))), "")} | U19: =IFERROR( LET( hoja, LEFT(U$1,3)&"R", fila, MATCH( RIGHT($A19, LEN($A19)-4), INDIRECT(hoja&"!$A:$A"), 0 ), columna, MATCH( "Totales", INDIRECT(hoja&"!$6:$6"), 0 ), valor, INDEX( INDIRECT(hoja&"!$A:$ZZ"), fila, columna ), IF(valor="-", "", valor) ), "") | V19: =T19-U19 -> 0 | W19: {=IFERROR(SUMIF(Consolidado!$C$3:$C63, $A19, INDEX(Consolidado!$E$3:$P$100, , MATCH(W$1, Consolidado!$E$2:$P$2, 0))), "")} | X19: =IFERROR( LET( hoja, LEFT(X$1,3)&"R", fila, MATCH( RIGHT($A19, LEN($A19)-4), INDIRECT(hoja&"!$A:$A"), 0 ), columna, MATCH( "Totales", INDIRECT(hoja&"!$6:$6"), 0 ), valor, INDEX( INDIRECT(hoja&"!$A:$ZZ"), fila, columna ), IF(valor="-", "", valor) ), "") | Y19: =W19-X19 -> 0 | Z19: {=IFERROR(SUMIF(Consolidado!$C$3:$C63, $A19, INDEX(Consolidado!$E$3:$P$100, , MATCH(Z$1, Consolidado!$E$2:$P$2, 0))), "")} | AA19: =IFERROR( LET( hoja, LEFT(AA$1,3)&"R", fila, MATCH( RIGHT($A19, LEN($A19)-4), INDIRECT(hoja&"!$A:$A"), 0 ), columna, MATCH( "Totales", INDIRECT(hoja&"!$6:$6"), 0 ), valor, INDEX( INDIRECT(hoja&"!$A:$ZZ"), fila, columna ), IF(valor="-", "", valor) ), "") | AB19: =Z19-AA19 -> 0 | AC19: {=IFERROR(SUMIF(Consolidado!$C$3:$C63, $A19, INDEX(Consolidado!$E$3:$P$100, , MATCH(AC$1, Consolidado!$E$2:$P$2, 0))), "")} | AD19: =IFERROR( LET( hoja, LEFT(AD$1,3)&"R", fila, MATCH( RIGHT($A19, LEN($A19)-4), INDIRECT(hoja&"!$A:$A"), 0 ), columna, MATCH( "Totales", INDIRECT(hoja&"!$6:$6"), 0 ), valor, INDEX( INDIRECT(hoja&"!$A:$ZZ"), fila, columna ), IF(valor="-", "", valor) ), "") | AE19: =AC19-AD19 -> 0 | AF19: {=IFERROR(SUMIF(Consolidado!$C$3:$C63, $A19, INDEX(Consolidado!$E$3:$P$100, , MATCH(AF$1, Consolidado!$E$2:$P$2, 0))), "")} | AG19: =IFERROR( LET( hoja, LEFT(AG$1,3)&"R", fila, MATCH( RIGHT($A19, LEN($A19)-4), INDIRECT(hoja&"!$A:$A"), 0 ), columna, MATCH( "Totales", INDIRECT(hoja&"!$6:$6"), 0 ), valor, INDEX( INDIRECT(hoja&"!$A:$ZZ"), fila, columna ), IF(valor="-", "", valor) ), "") | AH19: =AF19-AG19 -> 0 | AI19: {=IFERROR(SUMIF(Consolidado!$C$3:$C63, $A19, INDEX(Consolidado!$E$3:$P$100, , MATCH(AI$1, Consolidado!$E$2:$P$2, 0))), "")} | AJ19: =IFERROR( LET( hoja, LEFT(AJ$1,3)&"R", fila, MATCH( RIGHT($A19, LEN($A19)-4), INDIRECT(hoja&"!$A:$A"), 0 ), columna, MATCH( "Totales", INDIRECT(hoja&"!$6:$6"), 0 ), valor, INDEX( INDIRECT(hoja&"!$A:$ZZ"), fila, columna ), IF(valor="-", "", valor) ), "") | AK19: =AI19-AJ19 -> 0 | AL19: {=IFERROR(SUMIF(Consolidado!$C$3:$C63, $A19, INDEX(Consolidado!$E$3:$P$100, , MATCH(AL$1, Consolidado!$E$2:$P$2, 0))), "")} | AM19: =IFERROR( LET( hoja, LEFT(AM$1,3)&"R", fila, MATCH( RIGHT($A19, LEN($A19)-4), INDIRECT(hoja&"!$A:$A"), 0 ), columna, MATCH( "Totales", INDIRECT(hoja&"!$6:$6"), 0 ), valor, INDEX( INDIRECT(hoja&"!$A:$ZZ"), fila, columna ), IF(valor="-", "", valor) ), "") | AN19: =AL19-AM19 -> 0
A20: =Menus!B13 -> B10 Anuncios periódico | B20: =SUM(IF(MONTH(TODAY())>1,E20,0), IF(MONTH(TODAY())>2,H20,0), IF(MONTH(TODAY())>3,K20,0), IF(MONTH(TODAY())>4,N20,0), IF(MONTH(TODAY())>5,Q20,0), IF(MONTH(TODAY())>6,T20,0), IF(MONTH(TODAY())>7,W20,0), IF(MONTH(TODAY())>8,Z20,0), IF(MONTH(TODAY())>9,AC20,0), IF(MONTH(TODAY())>10,AF20,0), IF(MONTH(TODAY())>11,AI20,0), IF(MONTH(TODAY())>12,AL20,0)) -> 0 | C20: =SUM(IF(MONTH(TODAY())>1,F20,0), IF(MONTH(TODAY())>2,I20,0), IF(MONTH(TODAY())>3,L20,0), IF(MONTH(TODAY())>4,O20,0), IF(MONTH(TODAY())>5,R20,0), IF(MONTH(TODAY())>6,U20,0), IF(MONTH(TODAY())>7,X20,0), IF(MONTH(TODAY())>8,AA20,0), IF(MONTH(TODAY())>9,AD20,0), IF(MONTH(TODAY())>10,AG20,0), IF(MONTH(TODAY())>11,AJ20,0), IF(MONTH(TODAY())>12,AM20,0)) -> 0 | D20: =B20-C20 -> 0 | E20: {=IFERROR(SUMIF(Consolidado!$C$3:$C63, $A20, INDEX(Consolidado!$E$3:$P$100, , MATCH(E$1, Consolidado!$E$2:$P$2, 0))), "")} | F20: =IFERROR( LET( hoja, LEFT(F$1,3)&"R", fila, MATCH( RIGHT($A20, LEN($A20)-4), INDIRECT(hoja&"!$A:$A"), 0 ), columna, MATCH( "Totales", INDIRECT(hoja&"!$6:$6"), 0 ), valor, INDEX( INDIRECT(hoja&"!$A:$ZZ"), fila, columna ), IF(valor="-", "", valor) ), "") | G20: =E20-F20 -> 0 | H20: {=IFERROR(SUMIF(Consolidado!$C$3:$C63, $A20, INDEX(Consolidado!$E$3:$P$100, , MATCH(H$1, Consolidado!$E$2:$P$2, 0))), "")} | I20: =IFERROR( LET( hoja, LEFT(I$1,3)&"R", fila, MATCH( RIGHT($A20, LEN($A20)-4), INDIRECT(hoja&"!$A:$A"), 0 ), columna, MATCH( "Totales", INDIRECT(hoja&"!$6:$6"), 0 ), valor, INDEX( INDIRECT(hoja&"!$A:$ZZ"), fila, columna ), IF(valor="-", "", valor) ), "") | J20: =H20-I20 -> 0 | K20: {=IFERROR(SUMIF(Consolidado!$C$3:$C63, $A20, INDEX(Consolidado!$E$3:$P$100, , MATCH(K$1, Consolidado!$E$2:$P$2, 0))), "")} | L20: =IFERROR( LET( hoja, LEFT(L$1,3)&"R", fila, MATCH( RIGHT($A20, LEN($A20)-4), INDIRECT(hoja&"!$A:$A"), 0 ), columna, MATCH( "Totales", INDIRECT(hoja&"!$6:$6"), 0 ), valor, INDEX( INDIRECT(hoja&"!$A:$ZZ"), fila, columna ), IF(valor="-", "", valor) ), "") | M20: =K20-L20 -> 0 | N20: {=IFERROR(SUMIF(Consolidado!$C$3:$C63, $A20, INDEX(Consolidado!$E$3:$P$100, , MATCH(N$1, Consolidado!$E$2:$P$2, 0))), "")} | O20: =IFERROR( LET( hoja, LEFT(O$1,3)&"R", fila, MATCH( RIGHT($A20, LEN($A20)-4), INDIRECT(hoja&"!$A:$A"), 0 ), columna, MATCH( "Totales", INDIRECT(hoja&"!$6:$6"), 0 ), valor, INDEX( INDIRECT(hoja&"!$A:$ZZ"), fila, columna ), IF(valor="-", "", valor) ), "") | P20: =N20-O20 -> 0 | Q20: {=IFERROR(SUMIF(Consolidado!$C$3:$C63, $A20, INDEX(Consolidado!$E$3:$P$100, , MATCH(Q$1, Consolidado!$E$2:$P$2, 0))), "")} | R20: =IFERROR( LET( hoja, LEFT(R$1,3)&"R", fila, MATCH( RIGHT($A20, LEN($A20)-4), INDIRECT(hoja&"!$A:$A"), 0 ), columna, MATCH( "Totales", INDIRECT(hoja&"!$6:$6"), 0 ), valor, INDEX( INDIRECT(hoja&"!$A:$ZZ"), fila, columna ), IF(valor="-", "", valor) ), "") | S20: =Q20-R20 -> 0 | T20: {=IFERROR(SUMIF(Consolidado!$C$3:$C63, $A20, INDEX(Consolidado!$E$3:$P$100, , MATCH(T$1, Consolidado!$E$2:$P$2, 0))), "")} | U20: =IFERROR( LET( hoja, LEFT(U$1,3)&"R", fila, MATCH( RIGHT($A20, LEN($A20)-4), INDIRECT(hoja&"!$A:$A"), 0 ), columna, MATCH( "Totales", INDIRECT(hoja&"!$6:$6"), 0 ), valor, INDEX( INDIRECT(hoja&"!$A:$ZZ"), fila, columna ), IF(valor="-", "", valor) ), "") | V20: =T20-U20 -> 0 | W20: {=IFERROR(SUMIF(Consolidado!$C$3:$C63, $A20, INDEX(Consolidado!$E$3:$P$100, , MATCH(W$1, Consolidado!$E$2:$P$2, 0))), "")} | X20: =IFERROR( LET( hoja, LEFT(X$1,3)&"R", fila, MATCH( RIGHT($A20, LEN($A20)-4), INDIRECT(hoja&"!$A:$A"), 0 ), columna, MATCH( "Totales", INDIRECT(hoja&"!$6:$6"), 0 ), valor, INDEX( INDIRECT(hoja&"!$A:$ZZ"), fila, columna ), IF(valor="-", "", valor) ), "") | Y20: =W20-X20 -> 0 | Z20: {=IFERROR(SUMIF(Consolidado!$C$3:$C63, $A20, INDEX(Consolidado!$E$3:$P$100, , MATCH(Z$1, Consolidado!$E$2:$P$2, 0))), "")} | AA20: =IFERROR( LET( hoja, LEFT(AA$1,3)&"R", fila, MATCH( RIGHT($A20, LEN($A20)-4), INDIRECT(hoja&"!$A:$A"), 0 ), columna, MATCH( "Totales", INDIRECT(hoja&"!$6:$6"), 0 ), valor, INDEX( INDIRECT(hoja&"!$A:$ZZ"), fila, columna ), IF(valor="-", "", valor) ), "") | AB20: =Z20-AA20 -> 0 | AC20: {=IFERROR(SUMIF(Consolidado!$C$3:$C63, $A20, INDEX(Consolidado!$E$3:$P$100, , MATCH(AC$1, Consolidado!$E$2:$P$2, 0))), "")} | AD20: =IFERROR( LET( hoja, LEFT(AD$1,3)&"R", fila, MATCH( RIGHT($A20, LEN($A20)-4), INDIRECT(hoja&"!$A:$A"), 0 ), columna, MATCH( "Totales", INDIRECT(hoja&"!$6:$6"), 0 ), valor, INDEX( INDIRECT(hoja&"!$A:$ZZ"), fila, columna ), IF(valor="-", "", valor) ), "") | AE20: =AC20-AD20 -> 0 | AF20: {=IFERROR(SUMIF(Consolidado!$C$3:$C63, $A20, INDEX(Consolidado!$E$3:$P$100, , MATCH(AF$1, Consolidado!$E$2:$P$2, 0))), "")} | AG20: =IFERROR( LET( hoja, LEFT(AG$1,3)&"R", fila, MATCH( RIGHT($A20, LEN($A20)-4), INDIRECT(hoja&"!$A:$A"), 0 ), columna, MATCH( "Totales", INDIRECT(hoja&"!$6:$6"), 0 ), valor, INDEX( INDIRECT(hoja&"!$A:$ZZ"), fila, columna ), IF(valor="-", "", valor) ), "") | AH20: =AF20-AG20 -> 0 | AI20: {=IFERROR(SUMIF(Consolidado!$C$3:$C63, $A20, INDEX(Consolidado!$E$3:$P$100, , MATCH(AI$1, Consolidado!$E$2:$P$2, 0))), "")} | AJ20: =IFERROR( LET( hoja, LEFT(AJ$1,3)&"R", fila, MATCH( RIGHT($A20, LEN($A20)-4), INDIRECT(hoja&"!$A:$A"), 0 ), columna, MATCH( "Totales", INDIRECT(hoja&"!$6:$6"), 0 ), valor, INDEX( INDIRECT(hoja&"!$A:$ZZ"), fila, columna ), IF(valor="-", "", valor) ), "") | AK20: =AI20-AJ20 -> 0 | AL20: {=IFERROR(SUMIF(Consolidado!$C$3:$C63, $A20, INDEX(Consolidado!$E$3:$P$100, , MATCH(AL$1, Consolidado!$E$2:$P$2, 0))), "")} | AM20: =IFERROR( LET( hoja, LEFT(AM$1,3)&"R", fila, MATCH( RIGHT($A20, LEN($A20)-4), INDIRECT(hoja&"!$A:$A"), 0 ), columna, MATCH( "Totales", INDIRECT(hoja&"!$6:$6"), 0 ), valor, INDEX( INDIRECT(hoja&"!$A:$ZZ"), fila, columna ), IF(valor="-", "", valor) ), "") | AN20: =AL20-AM20 -> 0
A21: =Menus!B14 -> B11 Telefonía | B21: =SUM(IF(MONTH(TODAY())>1,E21,0), IF(MONTH(TODAY())>2,H21,0), IF(MONTH(TODAY())>3,K21,0), IF(MONTH(TODAY())>4,N21,0), IF(MONTH(TODAY())>5,Q21,0), IF(MONTH(TODAY())>6,T21,0), IF(MONTH(TODAY())>7,W21,0), IF(MONTH(TODAY())>8,Z21,0), IF(MONTH(TODAY())>9,AC21,0), IF(MONTH(TODAY())>10,AF21,0), IF(MONTH(TODAY())>11,AI21,0), IF(MONTH(TODAY())>12,AL21,0)) -> 0 | C21: =SUM(IF(MONTH(TODAY())>1,F21,0), IF(MONTH(TODAY())>2,I21,0), IF(MONTH(TODAY())>3,L21,0), IF(MONTH(TODAY())>4,O21,0), IF(MONTH(TODAY())>5,R21,0), IF(MONTH(TODAY())>6,U21,0), IF(MONTH(TODAY())>7,X21,0), IF(MONTH(TODAY())>8,AA21,0), IF(MONTH(TODAY())>9,AD21,0), IF(MONTH(TODAY())>10,AG21,0), IF(MONTH(TODAY())>11,AJ21,0), IF(MONTH(TODAY())>12,AM21,0)) -> 0 | D21: =B21-C21 -> 0 | E21: {=IFERROR(SUMIF(Consolidado!$C$3:$C63, $A21, INDEX(Consolidado!$E$3:$P$100, , MATCH(E$1, Consolidado!$E$2:$P$2, 0))), "")} | F21: =IFERROR( LET( hoja, LEFT(F$1,3)&"R", fila, MATCH( RIGHT($A21, LEN($A21)-4), INDIRECT(hoja&"!$A:$A"), 0 ), columna, MATCH( "Totales", INDIRECT(hoja&"!$6:$6"), 0 ), valor, INDEX( INDIRECT(hoja&"!$A:$ZZ"), fila, columna ), IF(valor="-", "", valor) ), "") | G21: =E21-F21 -> 0 | H21: {=IFERROR(SUMIF(Consolidado!$C$3:$C63, $A21, INDEX(Consolidado!$E$3:$P$100, , MATCH(H$1, Consolidado!$E$2:$P$2, 0))), "")} | I21: =IFERROR( LET( hoja, LEFT(I$1,3)&"R", fila, MATCH( RIGHT($A21, LEN($A21)-4), INDIRECT(hoja&"!$A:$A"), 0 ), columna, MATCH( "Totales", INDIRECT(hoja&"!$6:$6"), 0 ), valor, INDEX( INDIRECT(hoja&"!$A:$ZZ"), fila, columna ), IF(valor="-", "", valor) ), "") | J21: =H21-I21 -> 0 | K21: {=IFERROR(SUMIF(Consolidado!$C$3:$C63, $A21, INDEX(Consolidado!$E$3:$P$100, , MATCH(K$1, Consolidado!$E$2:$P$2, 0))), "")} | L21: =IFERROR( LET( hoja, LEFT(L$1,3)&"R", fila, MATCH( RIGHT($A21, LEN($A21)-4), INDIRECT(hoja&"!$A:$A"), 0 ), columna, MATCH( "Totales", INDIRECT(hoja&"!$6:$6"), 0 ), valor, INDEX( INDIRECT(hoja&"!$A:$ZZ"), fila, columna ), IF(valor="-", "", valor) ), "") | M21: =K21-L21 -> 0 | N21: {=IFERROR(SUMIF(Consolidado!$C$3:$C63, $A21, INDEX(Consolidado!$E$3:$P$100, , MATCH(N$1, Consolidado!$E$2:$P$2, 0))), "")} | O21: =IFERROR( LET( hoja, LEFT(O$1,3)&"R", fila, MATCH( RIGHT($A21, LEN($A21)-4), INDIRECT(hoja&"!$A:$A"), 0 ), columna, MATCH( "Totales", INDIRECT(hoja&"!$6:$6"), 0 ), valor, INDEX( INDIRECT(hoja&"!$A:$ZZ"), fila, columna ), IF(valor="-", "", valor) ), "") | P21: =N21-O21 -> 0 | Q21: {=IFERROR(SUMIF(Consolidado!$C$3:$C63, $A21, INDEX(Consolidado!$E$3:$P$100, , MATCH(Q$1, Consolidado!$E$2:$P$2, 0))), "")} | R21: =IFERROR( LET( hoja, LEFT(R$1,3)&"R", fila, MATCH( RIGHT($A21, LEN($A21)-4), INDIRECT(hoja&"!$A:$A"), 0 ), columna, MATCH( "Totales", INDIRECT(hoja&"!$6:$6"), 0 ), valor, INDEX( INDIRECT(hoja&"!$A:$ZZ"), fila, columna ), IF(valor="-", "", valor) ), "") | S21: =Q21-R21 -> 0 | T21: {=IFERROR(SUMIF(Consolidado!$C$3:$C63, $A21, INDEX(Consolidado!$E$3:$P$100, , MATCH(T$1, Consolidado!$E$2:$P$2, 0))), "")} | U21: =IFERROR( LET( hoja, LEFT(U$1,3)&"R", fila, MATCH( RIGHT($A21, LEN($A21)-4), INDIRECT(hoja&"!$A:$A"), 0 ), columna, MATCH( "Totales", INDIRECT(hoja&"!$6:$6"), 0 ), valor, INDEX( INDIRECT(hoja&"!$A:$ZZ"), fila, columna ), IF(valor="-", "", valor) ), "") | V21: =T21-U21 -> 0 | W21: {=IFERROR(SUMIF(Consolidado!$C$3:$C63, $A21, INDEX(Consolidado!$E$3:$P$100, , MATCH(W$1, Consolidado!$E$2:$P$2, 0))), "")} | X21: =IFERROR( LET( hoja, LEFT(X$1,3)&"R", fila, MATCH( RIGHT($A21, LEN($A21)-4), INDIRECT(hoja&"!$A:$A"), 0 ), columna, MATCH( "Totales", INDIRECT(hoja&"!$6:$6"), 0 ), valor, INDEX( INDIRECT(hoja&"!$A:$ZZ"), fila, columna ), IF(valor="-", "", valor) ), "") | Y21: =W21-X21 -> 0 | Z21: {=IFERROR(SUMIF(Consolidado!$C$3:$C63, $A21, INDEX(Consolidado!$E$3:$P$100, , MATCH(Z$1, Consolidado!$E$2:$P$2, 0))), "")} | AA21: =IFERROR( LET( hoja, LEFT(AA$1,3)&"R", fila, MATCH( RIGHT($A21, LEN($A21)-4), INDIRECT(hoja&"!$A:$A"), 0 ), columna, MATCH( "Totales", INDIRECT(hoja&"!$6:$6"), 0 ), valor, INDEX( INDIRECT(hoja&"!$A:$ZZ"), fila, columna ), IF(valor="-", "", valor) ), "") | AB21: =Z21-AA21 -> 0 | AC21: {=IFERROR(SUMIF(Consolidado!$C$3:$C63, $A21, INDEX(Consolidado!$E$3:$P$100, , MATCH(AC$1, Consolidado!$E$2:$P$2, 0))), "")} | AD21: =IFERROR( LET( hoja, LEFT(AD$1,3)&"R", fila, MATCH( RIGHT($A21, LEN($A21)-4), INDIRECT(hoja&"!$A:$A"), 0 ), columna, MATCH( "Totales", INDIRECT(hoja&"!$6:$6"), 0 ), valor, INDEX( INDIRECT(hoja&"!$A:$ZZ"), fila, columna ), IF(valor="-", "", valor) ), "") | AE21: =AC21-AD21 -> 0 | AF21: {=IFERROR(SUMIF(Consolidado!$C$3:$C63, $A21, INDEX(Consolidado!$E$3:$P$100, , MATCH(AF$1, Consolidado!$E$2:$P$2, 0))), "")} | AG21: =IFERROR( LET( hoja, LEFT(AG$1,3)&"R", fila, MATCH( RIGHT($A21, LEN($A21)-4), INDIRECT(hoja&"!$A:$A"), 0 ), columna, MATCH( "Totales", INDIRECT(hoja&"!$6:$6"), 0 ), valor, INDEX( INDIRECT(hoja&"!$A:$ZZ"), fila, columna ), IF(valor="-", "", valor) ), "") | AH21: =AF21-AG21 -> 0 | AI21: {=IFERROR(SUMIF(Consolidado!$C$3:$C63, $A21, INDEX(Consolidado!$E$3:$P$100, , MATCH(AI$1, Consolidado!$E$2:$P$2, 0))), "")} | AJ21: =IFERROR( LET( hoja, LEFT(AJ$1,3)&"R", fila, MATCH( RIGHT($A21, LEN($A21)-4), INDIRECT(hoja&"!$A:$A"), 0 ), columna, MATCH( "Totales", INDIRECT(hoja&"!$6:$6"), 0 ), valor, INDEX( INDIRECT(hoja&"!$A:$ZZ"), fila, columna ), IF(valor="-", "", valor) ), "") | AK21: =AI21-AJ21 -> 0 | AL21: {=IFERROR(SUMIF(Consolidado!$C$3:$C63, $A21, INDEX(Consolidado!$E$3:$P$100, , MATCH(AL$1, Consolidado!$E$2:$P$2, 0))), "")} | AM21: =IFERROR( LET( hoja, LEFT(AM$1,3)&"R", fila, MATCH( RIGHT($A21, LEN($A21)-4), INDIRECT(hoja&"!$A:$A"), 0 ), columna, MATCH( "Totales", INDIRECT(hoja&"!$6:$6"), 0 ), valor, INDEX( INDIRECT(hoja&"!$A:$ZZ"), fila, columna ), IF(valor="-", "", valor) ), "") | AN21: =AL21-AM21 -> 0
A22: =Menus!B15 -> B12 Papelería | B22: =SUM(IF(MONTH(TODAY())>1,E22,0), IF(MONTH(TODAY())>2,H22,0), IF(MONTH(TODAY())>3,K22,0), IF(MONTH(TODAY())>4,N22,0), IF(MONTH(TODAY())>5,Q22,0), IF(MONTH(TODAY())>6,T22,0), IF(MONTH(TODAY())>7,W22,0), IF(MONTH(TODAY())>8,Z22,0), IF(MONTH(TODAY())>9,AC22,0), IF(MONTH(TODAY())>10,AF22,0), IF(MONTH(TODAY())>11,AI22,0), IF(MONTH(TODAY())>12,AL22,0)) -> 0 | C22: =SUM(IF(MONTH(TODAY())>1,F22,0), IF(MONTH(TODAY())>2,I22,0), IF(MONTH(TODAY())>3,L22,0), IF(MONTH(TODAY())>4,O22,0), IF(MONTH(TODAY())>5,R22,0), IF(MONTH(TODAY())>6,U22,0), IF(MONTH(TODAY())>7,X22,0), IF(MONTH(TODAY())>8,AA22,0), IF(MONTH(TODAY())>9,AD22,0), IF(MONTH(TODAY())>10,AG22,0), IF(MONTH(TODAY())>11,AJ22,0), IF(MONTH(TODAY())>12,AM22,0)) -> 0 | D22: =B22-C22 -> 0 | E22: {=IFERROR(SUMIF(Consolidado!$C$3:$C63, $A22, INDEX(Consolidado!$E$3:$P$100, , MATCH(E$1, Consolidado!$E$2:$P$2, 0))), "")} | F22: =IFERROR( LET( hoja, LEFT(F$1,3)&"R", fila, MATCH( RIGHT($A22, LEN($A22)-4), INDIRECT(hoja&"!$A:$A"), 0 ), columna, MATCH( "Totales", INDIRECT(hoja&"!$6:$6"), 0 ), valor, INDEX( INDIRECT(hoja&"!$A:$ZZ"), fila, columna ), IF(valor="-", "", valor) ), "") | G22: =E22-F22 -> 0 | H22: {=IFERROR(SUMIF(Consolidado!$C$3:$C63, $A22, INDEX(Consolidado!$E$3:$P$100, , MATCH(H$1, Consolidado!$E$2:$P$2, 0))), "")} | I22: =IFERROR( LET( hoja, LEFT(I$1,3)&"R", fila, MATCH( RIGHT($A22, LEN($A22)-4), INDIRECT(hoja&"!$A:$A"), 0 ), columna, MATCH( "Totales", INDIRECT(hoja&"!$6:$6"), 0 ), valor, INDEX( INDIRECT(hoja&"!$A:$ZZ"), fila, columna ), IF(valor="-", "", valor) ), "") | J22: =H22-I22 -> 0 | K22: {=IFERROR(SUMIF(Consolidado!$C$3:$C63, $A22, INDEX(Consolidado!$E$3:$P$100, , MATCH(K$1, Consolidado!$E$2:$P$2, 0))), "")} | L22: =IFERROR( LET( hoja, LEFT(L$1,3)&"R", fila, MATCH( RIGHT($A22, LEN($A22)-4), INDIRECT(hoja&"!$A:$A"), 0 ), columna, MATCH( "Totales", INDIRECT(hoja&"!$6:$6"), 0 ), valor, INDEX( INDIRECT(hoja&"!$A:$ZZ"), fila, columna ), IF(valor="-", "", valor) ), "") | M22: =K22-L22 -> 0 | N22: {=IFERROR(SUMIF(Consolidado!$C$3:$C63, $A22, INDEX(Consolidado!$E$3:$P$100, , MATCH(N$1, Consolidado!$E$2:$P$2, 0))), "")} | O22: =IFERROR( LET( hoja, LEFT(O$1,3)&"R", fila, MATCH( RIGHT($A22, LEN($A22)-4), INDIRECT(hoja&"!$A:$A"), 0 ), columna, MATCH( "Totales", INDIRECT(hoja&"!$6:$6"), 0 ), valor, INDEX( INDIRECT(hoja&"!$A:$ZZ"), fila, columna ), IF(valor="-", "", valor) ), "") | P22: =N22-O22 -> 0 | Q22: {=IFERROR(SUMIF(Consolidado!$C$3:$C63, $A22, INDEX(Consolidado!$E$3:$P$100, , MATCH(Q$1, Consolidado!$E$2:$P$2, 0))), "")} | R22: =IFERROR( LET( hoja, LEFT(R$1,3)&"R", fila, MATCH( RIGHT($A22, LEN($A22)-4), INDIRECT(hoja&"!$A:$A"), 0 ), columna, MATCH( "Totales", INDIRECT(hoja&"!$6:$6"), 0 ), valor, INDEX( INDIRECT(hoja&"!$A:$ZZ"), fila, columna ), IF(valor="-", "", valor) ), "") | S22: =Q22-R22 -> 0 | T22: {=IFERROR(SUMIF(Consolidado!$C$3:$C63, $A22, INDEX(Consolidado!$E$3:$P$100, , MATCH(T$1, Consolidado!$E$2:$P$2, 0))), "")} | U22: =IFERROR( LET( hoja, LEFT(U$1,3)&"R", fila, MATCH( RIGHT($A22, LEN($A22)-4), INDIRECT(hoja&"!$A:$A"), 0 ), columna, MATCH( "Totales", INDIRECT(hoja&"!$6:$6"), 0 ), valor, INDEX( INDIRECT(hoja&"!$A:$ZZ"), fila, columna ), IF(valor="-", "", valor) ), "") | V22: =T22-U22 -> 0 | W22: {=IFERROR(SUMIF(Consolidado!$C$3:$C63, $A22, INDEX(Consolidado!$E$3:$P$100, , MATCH(W$1, Consolidado!$E$2:$P$2, 0))), "")} | X22: =IFERROR( LET( hoja, LEFT(X$1,3)&"R", fila, MATCH( RIGHT($A22, LEN($A22)-4), INDIRECT(hoja&"!$A:$A"), 0 ), columna, MATCH( "Totales", INDIRECT(hoja&"!$6:$6"), 0 ), valor, INDEX( INDIRECT(hoja&"!$A:$ZZ"), fila, columna ), IF(valor="-", "", valor) ), "") | Y22: =W22-X22 -> 0 | Z22: {=IFERROR(SUMIF(Consolidado!$C$3:$C63, $A22, INDEX(Consolidado!$E$3:$P$100, , MATCH(Z$1, Consolidado!$E$2:$P$2, 0))), "")} | AA22: =IFERROR( LET( hoja, LEFT(AA$1,3)&"R", fila, MATCH( RIGHT($A22, LEN($A22)-4), INDIRECT(hoja&"!$A:$A"), 0 ), columna, MATCH( "Totales", INDIRECT(hoja&"!$6:$6"), 0 ), valor, INDEX( INDIRECT(hoja&"!$A:$ZZ"), fila, columna ), IF(valor="-", "", valor) ), "") | AB22: =Z22-AA22 -> 0 | AC22: {=IFERROR(SUMIF(Consolidado!$C$3:$C63, $A22, INDEX(Consolidado!$E$3:$P$100, , MATCH(AC$1, Consolidado!$E$2:$P$2, 0))), "")} | AD22: =IFERROR( LET( hoja, LEFT(AD$1,3)&"R", fila, MATCH( RIGHT($A22, LEN($A22)-4), INDIRECT(hoja&"!$A:$A"), 0 ), columna, MATCH( "Totales", INDIRECT(hoja&"!$6:$6"), 0 ), valor, INDEX( INDIRECT(hoja&"!$A:$ZZ"), fila, columna ), IF(valor="-", "", valor) ), "") | AE22: =AC22-AD22 -> 0 | AF22: {=IFERROR(SUMIF(Consolidado!$C$3:$C63, $A22, INDEX(Consolidado!$E$3:$P$100, , MATCH(AF$1, Consolidado!$E$2:$P$2, 0))), "")} | AG22: =IFERROR( LET( hoja, LEFT(AG$1,3)&"R", fila, MATCH( RIGHT($A22, LEN($A22)-4), INDIRECT(hoja&"!$A:$A"), 0 ), columna, MATCH( "Totales", INDIRECT(hoja&"!$6:$6"), 0 ), valor, INDEX( INDIRECT(hoja&"!$A:$ZZ"), fila, columna ), IF(valor="-", "", valor) ), "") | AH22: =AF22-AG22 -> 0 | AI22: {=IFERROR(SUMIF(Consolidado!$C$3:$C63, $A22, INDEX(Consolidado!$E$3:$P$100, , MATCH(AI$1, Consolidado!$E$2:$P$2, 0))), "")} | AJ22: =IFERROR( LET( hoja, LEFT(AJ$1,3)&"R", fila, MATCH( RIGHT($A22, LEN($A22)-4), INDIRECT(hoja&"!$A:$A"), 0 ), columna, MATCH( "Totales", INDIRECT(hoja&"!$6:$6"), 0 ), valor, INDEX( INDIRECT(hoja&"!$A:$ZZ"), fila, columna ), IF(valor="-", "", valor) ), "") | AK22: =AI22-AJ22 -> 0 | AL22: {=IFERROR(SUMIF(Consolidado!$C$3:$C63, $A22, INDEX(Consolidado!$E$3:$P$100, , MATCH(AL$1, Consolidado!$E$2:$P$2, 0))), "")} | AM22: =IFERROR( LET( hoja, LEFT(AM$1,3)&"R", fila, MATCH( RIGHT($A22, LEN($A22)-4), INDIRECT(hoja&"!$A:$A"), 0 ), columna, MATCH( "Totales", INDIRECT(hoja&"!$6:$6"), 0 ), valor, INDEX( INDIRECT(hoja&"!$A:$ZZ"), fila, columna ), IF(valor="-", "", valor) ), "") | AN22: =AL22-AM22 -> 0
A23: =Menus!B16 -> B13 Honorarios | B23: =SUM(IF(MONTH(TODAY())>1,E23,0), IF(MONTH(TODAY())>2,H23,0), IF(MONTH(TODAY())>3,K23,0), IF(MONTH(TODAY())>4,N23,0), IF(MONTH(TODAY())>5,Q23,0), IF(MONTH(TODAY())>6,T23,0), IF(MONTH(TODAY())>7,W23,0), IF(MONTH(TODAY())>8,Z23,0), IF(MONTH(TODAY())>9,AC23,0), IF(MONTH(TODAY())>10,AF23,0), IF(MONTH(TODAY())>11,AI23,0), IF(MONTH(TODAY())>12,AL23,0)) -> 0 | C23: =SUM(IF(MONTH(TODAY())>1,F23,0), IF(MONTH(TODAY())>2,I23,0), IF(MONTH(TODAY())>3,L23,0), IF(MONTH(TODAY())>4,O23,0), IF(MONTH(TODAY())>5,R23,0), IF(MONTH(TODAY())>6,U23,0), IF(MONTH(TODAY())>7,X23,0), IF(MONTH(TODAY())>8,AA23,0), IF(MONTH(TODAY())>9,AD23,0), IF(MONTH(TODAY())>10,AG23,0), IF(MONTH(TODAY())>11,AJ23,0), IF(MONTH(TODAY())>12,AM23,0)) -> 0 | D23: =B23-C23 -> 0 | E23: {=IFERROR(SUMIF(Consolidado!$C$3:$C63, $A23, INDEX(Consolidado!$E$3:$P$100, , MATCH(E$1, Consolidado!$E$2:$P$2, 0))), "")} | F23: =IFERROR( LET( hoja, LEFT(F$1,3)&"R", fila, MATCH( RIGHT($A23, LEN($A23)-4), INDIRECT(hoja&"!$A:$A"), 0 ), columna, MATCH( "Totales", INDIRECT(hoja&"!$6:$6"), 0 ), valor, INDEX( INDIRECT(hoja&"!$A:$ZZ"), fila, columna ), IF(valor="-", "", valor) ), "") | G23: =E23-F23 -> 0 | H23: {=IFERROR(SUMIF(Consolidado!$C$3:$C63, $A23, INDEX(Consolidado!$E$3:$P$100, , MATCH(H$1, Consolidado!$E$2:$P$2, 0))), "")} | I23: =IFERROR( LET( hoja, LEFT(I$1,3)&"R", fila, MATCH( RIGHT($A23, LEN($A23)-4), INDIRECT(hoja&"!$A:$A"), 0 ), columna, MATCH( "Totales", INDIRECT(hoja&"!$6:$6"), 0 ), valor, INDEX( INDIRECT(hoja&"!$A:$ZZ"), fila, columna ), IF(valor="-", "", valor) ), "") | J23: =H23-I23 -> 0 | K23: {=IFERROR(SUMIF(Consolidado!$C$3:$C63, $A23, INDEX(Consolidado!$E$3:$P$100, , MATCH(K$1, Consolidado!$E$2:$P$2, 0))), "")} | L23: =IFERROR( LET( hoja, LEFT(L$1,3)&"R", fila, MATCH( RIGHT($A23, LEN($A23)-4), INDIRECT(hoja&"!$A:$A"), 0 ), columna, MATCH( "Totales", INDIRECT(hoja&"!$6:$6"), 0 ), valor, INDEX( INDIRECT(hoja&"!$A:$ZZ"), fila, columna ), IF(valor="-", "", valor) ), "") | M23: =K23-L23 -> 0 | N23: {=IFERROR(SUMIF(Consolidado!$C$3:$C63, $A23, INDEX(Consolidado!$E$3:$P$100, , MATCH(N$1, Consolidado!$E$2:$P$2, 0))), "")} | O23: =IFERROR( LET( hoja, LEFT(O$1,3)&"R", fila, MATCH( RIGHT($A23, LEN($A23)-4), INDIRECT(hoja&"!$A:$A"), 0 ), columna, MATCH( "Totales", INDIRECT(hoja&"!$6:$6"), 0 ), valor, INDEX( INDIRECT(hoja&"!$A:$ZZ"), fila, columna ), IF(valor="-", "", valor) ), "") | P23: =N23-O23 -> 0 | Q23: {=IFERROR(SUMIF(Consolidado!$C$3:$C63, $A23, INDEX(Consolidado!$E$3:$P$100, , MATCH(Q$1, Consolidado!$E$2:$P$2, 0))), "")} | R23: =IFERROR( LET( hoja, LEFT(R$1,3)&"R", fila, MATCH( RIGHT($A23, LEN($A23)-4), INDIRECT(hoja&"!$A:$A"), 0 ), columna, MATCH( "Totales", INDIRECT(hoja&"!$6:$6"), 0 ), valor, INDEX( INDIRECT(hoja&"!$A:$ZZ"), fila, columna ), IF(valor="-", "", valor) ), "") | S23: =Q23-R23 -> 0 | T23: {=IFERROR(SUMIF(Consolidado!$C$3:$C63, $A23, INDEX(Consolidado!$E$3:$P$100, , MATCH(T$1, Consolidado!$E$2:$P$2, 0))), "")} | U23: =IFERROR( LET( hoja, LEFT(U$1,3)&"R", fila, MATCH( RIGHT($A23, LEN($A23)-4), INDIRECT(hoja&"!$A:$A"), 0 ), columna, MATCH( "Totales", INDIRECT(hoja&"!$6:$6"), 0 ), valor, INDEX( INDIRECT(hoja&"!$A:$ZZ"), fila, columna ), IF(valor="-", "", valor) ), "") | V23: =T23-U23 -> 0 | W23: {=IFERROR(SUMIF(Consolidado!$C$3:$C63, $A23, INDEX(Consolidado!$E$3:$P$100, , MATCH(W$1, Consolidado!$E$2:$P$2, 0))), "")} | X23: =IFERROR( LET( hoja, LEFT(X$1,3)&"R", fila, MATCH( RIGHT($A23, LEN($A23)-4), INDIRECT(hoja&"!$A:$A"), 0 ), columna, MATCH( "Totales", INDIRECT(hoja&"!$6:$6"), 0 ), valor, INDEX( INDIRECT(hoja&"!$A:$ZZ"), fila, columna ), IF(valor="-", "", valor) ), "") | Y23: =W23-X23 -> 0 | Z23: {=IFERROR(SUMIF(Consolidado!$C$3:$C63, $A23, INDEX(Consolidado!$E$3:$P$100, , MATCH(Z$1, Consolidado!$E$2:$P$2, 0))), "")} | AA23: =IFERROR( LET( hoja, LEFT(AA$1,3)&"R", fila, MATCH( RIGHT($A23, LEN($A23)-4), INDIRECT(hoja&"!$A:$A"), 0 ), columna, MATCH( "Totales", INDIRECT(hoja&"!$6:$6"), 0 ), valor, INDEX( INDIRECT(hoja&"!$A:$ZZ"), fila, columna ), IF(valor="-", "", valor) ), "") | AB23: =Z23-AA23 -> 0 | AC23: {=IFERROR(SUMIF(Consolidado!$C$3:$C63, $A23, INDEX(Consolidado!$E$3:$P$100, , MATCH(AC$1, Consolidado!$E$2:$P$2, 0))), "")} | AD23: =IFERROR( LET( hoja, LEFT(AD$1,3)&"R", fila, MATCH( RIGHT($A23, LEN($A23)-4), INDIRECT(hoja&"!$A:$A"), 0 ), columna, MATCH( "Totales", INDIRECT(hoja&"!$6:$6"), 0 ), valor, INDEX( INDIRECT(hoja&"!$A:$ZZ"), fila, columna ), IF(valor="-", "", valor) ), "") | AE23: =AC23-AD23 -> 0 | AF23: {=IFERROR(SUMIF(Consolidado!$C$3:$C63, $A23, INDEX(Consolidado!$E$3:$P$100, , MATCH(AF$1, Consolidado!$E$2:$P$2, 0))), "")} | AG23: =IFERROR( LET( hoja, LEFT(AG$1,3)&"R", fila, MATCH( RIGHT($A23, LEN($A23)-4), INDIRECT(hoja&"!$A:$A"), 0 ), columna, MATCH( "Totales", INDIRECT(hoja&"!$6:$6"), 0 ), valor, INDEX( INDIRECT(hoja&"!$A:$ZZ"), fila, columna ), IF(valor="-", "", valor) ), "") | AH23: =AF23-AG23 -> 0 | AI23: {=IFERROR(SUMIF(Consolidado!$C$3:$C63, $A23, INDEX(Consolidado!$E$3:$P$100, , MATCH(AI$1, Consolidado!$E$2:$P$2, 0))), "")} | AJ23: =IFERROR( LET( hoja, LEFT(AJ$1,3)&"R", fila, MATCH( RIGHT($A23, LEN($A23)-4), INDIRECT(hoja&"!$A:$A"), 0 ), columna, MATCH( "Totales", INDIRECT(hoja&"!$6:$6"), 0 ), valor, INDEX( INDIRECT(hoja&"!$A:$ZZ"), fila, columna ), IF(valor="-", "", valor) ), "") | AK23: =AI23-AJ23 -> 0 | AL23: {=IFERROR(SUMIF(Consolidado!$C$3:$C63, $A23, INDEX(Consolidado!$E$3:$P$100, , MATCH(AL$1, Consolidado!$E$2:$P$2, 0))), "")} | AM23: =IFERROR( LET( hoja, LEFT(AM$1,3)&"R", fila, MATCH( RIGHT($A23, LEN($A23)-4), INDIRECT(hoja&"!$A:$A"), 0 ), columna, MATCH( "Totales", INDIRECT(hoja&"!$6:$6"), 0 ), valor, INDEX( INDIRECT(hoja&"!$A:$ZZ"), fila, columna ), IF(valor="-", "", valor) ), "") | AN23: =AL23-AM23 -> 0
A24: =Menus!B17 -> B14 Arrendamiento de inmuebles | B24: =SUM(IF(MONTH(TODAY())>1,E24,0), IF(MONTH(TODAY())>2,H24,0), IF(MONTH(TODAY())>3,K24,0), IF(MONTH(TODAY())>4,N24,0), IF(MONTH(TODAY())>5,Q24,0), IF(MONTH(TODAY())>6,T24,0), IF(MONTH(TODAY())>7,W24,0), IF(MONTH(TODAY())>8,Z24,0), IF(MONTH(TODAY())>9,AC24,0), IF(MONTH(TODAY())>10,AF24,0), IF(MONTH(TODAY())>11,AI24,0), IF(MONTH(TODAY())>12,AL24,0)) -> 0 | C24: =SUM(IF(MONTH(TODAY())>1,F24,0), IF(MONTH(TODAY())>2,I24,0), IF(MONTH(TODAY())>3,L24,0), IF(MONTH(TODAY())>4,O24,0), IF(MONTH(TODAY())>5,R24,0), IF(MONTH(TODAY())>6,U24,0), IF(MONTH(TODAY())>7,X24,0), IF(MONTH(TODAY())>8,AA24,0), IF(MONTH(TODAY())>9,AD24,0), IF(MONTH(TODAY())>10,AG24,0), IF(MONTH(TODAY())>11,AJ24,0), IF(MONTH(TODAY())>12,AM24,0)) -> 0 | D24: =B24-C24 -> 0 | E24: {=IFERROR(SUMIF(Consolidado!$C$3:$C63, $A24, INDEX(Consolidado!$E$3:$P$100, , MATCH(E$1, Consolidado!$E$2:$P$2, 0))), "")} | F24: =IFERROR( LET( hoja, LEFT(F$1,3)&"R", fila, MATCH( RIGHT($A24, LEN($A24)-4), INDIRECT(hoja&"!$A:$A"), 0 ), columna, MATCH( "Totales", INDIRECT(hoja&"!$6:$6"), 0 ), valor, INDEX( INDIRECT(hoja&"!$A:$ZZ"), fila, columna ), IF(valor="-", "", valor) ), "") | G24: =E24-F24 -> 0 | H24: {=IFERROR(SUMIF(Consolidado!$C$3:$C63, $A24, INDEX(Consolidado!$E$3:$P$100, , MATCH(H$1, Consolidado!$E$2:$P$2, 0))), "")} | I24: =IFERROR( LET( hoja, LEFT(I$1,3)&"R", fila, MATCH( RIGHT($A24, LEN($A24)-4), INDIRECT(hoja&"!$A:$A"), 0 ), columna, MATCH( "Totales", INDIRECT(hoja&"!$6:$6"), 0 ), valor, INDEX( INDIRECT(hoja&"!$A:$ZZ"), fila, columna ), IF(valor="-", "", valor) ), "") | J24: =H24-I24 -> 0 | K24: {=IFERROR(SUMIF(Consolidado!$C$3:$C63, $A24, INDEX(Consolidado!$E$3:$P$100, , MATCH(K$1, Consolidado!$E$2:$P$2, 0))), "")} | L24: =IFERROR( LET( hoja, LEFT(L$1,3)&"R", fila, MATCH( RIGHT($A24, LEN($A24)-4), INDIRECT(hoja&"!$A:$A"), 0 ), columna, MATCH( "Totales", INDIRECT(hoja&"!$6:$6"), 0 ), valor, INDEX( INDIRECT(hoja&"!$A:$ZZ"), fila, columna ), IF(valor="-", "", valor) ), "") | M24: =K24-L24 -> 0 | N24: {=IFERROR(SUMIF(Consolidado!$C$3:$C63, $A24, INDEX(Consolidado!$E$3:$P$100, , MATCH(N$1, Consolidado!$E$2:$P$2, 0))), "")} | O24: =IFERROR( LET( hoja, LEFT(O$1,3)&"R", fila, MATCH( RIGHT($A24, LEN($A24)-4), INDIRECT(hoja&"!$A:$A"), 0 ), columna, MATCH( "Totales", INDIRECT(hoja&"!$6:$6"), 0 ), valor, INDEX( INDIRECT(hoja&"!$A:$ZZ"), fila, columna ), IF(valor="-", "", valor) ), "") | P24: =N24-O24 -> 0 | Q24: {=IFERROR(SUMIF(Consolidado!$C$3:$C63, $A24, INDEX(Consolidado!$E$3:$P$100, , MATCH(Q$1, Consolidado!$E$2:$P$2, 0))), "")} | R24: =IFERROR( LET( hoja, LEFT(R$1,3)&"R", fila, MATCH( RIGHT($A24, LEN($A24)-4), INDIRECT(hoja&"!$A:$A"), 0 ), columna, MATCH( "Totales", INDIRECT(hoja&"!$6:$6"), 0 ), valor, INDEX( INDIRECT(hoja&"!$A:$ZZ"), fila, columna ), IF(valor="-", "", valor) ), "") | S24: =Q24-R24 -> 0 | T24: {=IFERROR(SUMIF(Consolidado!$C$3:$C63, $A24, INDEX(Consolidado!$E$3:$P$100, , MATCH(T$1, Consolidado!$E$2:$P$2, 0))), "")} | U24: =IFERROR( LET( hoja, LEFT(U$1,3)&"R", fila, MATCH( RIGHT($A24, LEN($A24)-4), INDIRECT(hoja&"!$A:$A"), 0 ), columna, MATCH( "Totales", INDIRECT(hoja&"!$6:$6"), 0 ), valor, INDEX( INDIRECT(hoja&"!$A:$ZZ"), fila, columna ), IF(valor="-", "", valor) ), "") | V24: =T24-U24 -> 0 | W24: {=IFERROR(SUMIF(Consolidado!$C$3:$C63, $A24, INDEX(Consolidado!$E$3:$P$100, , MATCH(W$1, Consolidado!$E$2:$P$2, 0))), "")} | X24: =IFERROR( LET( hoja, LEFT(X$1,3)&"R", fila, MATCH( RIGHT($A24, LEN($A24)-4), INDIRECT(hoja&"!$A:$A"), 0 ), columna, MATCH( "Totales", INDIRECT(hoja&"!$6:$6"), 0 ), valor, INDEX( INDIRECT(hoja&"!$A:$ZZ"), fila, columna ), IF(valor="-", "", valor) ), "") | Y24: =W24-X24 -> 0 | Z24: {=IFERROR(SUMIF(Consolidado!$C$3:$C63, $A24, INDEX(Consolidado!$E$3:$P$100, , MATCH(Z$1, Consolidado!$E$2:$P$2, 0))), "")} | AA24: =IFERROR( LET( hoja, LEFT(AA$1,3)&"R", fila, MATCH( RIGHT($A24, LEN($A24)-4), INDIRECT(hoja&"!$A:$A"), 0 ), columna, MATCH( "Totales", INDIRECT(hoja&"!$6:$6"), 0 ), valor, INDEX( INDIRECT(hoja&"!$A:$ZZ"), fila, columna ), IF(valor="-", "", valor) ), "") | AB24: =Z24-AA24 -> 0 | AC24: {=IFERROR(SUMIF(Consolidado!$C$3:$C63, $A24, INDEX(Consolidado!$E$3:$P$100, , MATCH(AC$1, Consolidado!$E$2:$P$2, 0))), "")} | AD24: =IFERROR( LET( hoja, LEFT(AD$1,3)&"R", fila, MATCH( RIGHT($A24, LEN($A24)-4), INDIRECT(hoja&"!$A:$A"), 0 ), columna, MATCH( "Totales", INDIRECT(hoja&"!$6:$6"), 0 ), valor, INDEX( INDIRECT(hoja&"!$A:$ZZ"), fila, columna ), IF(valor="-", "", valor) ), "") | AE24: =AC24-AD24 -> 0 | AF24: {=IFERROR(SUMIF(Consolidado!$C$3:$C63, $A24, INDEX(Consolidado!$E$3:$P$100, , MATCH(AF$1, Consolidado!$E$2:$P$2, 0))), "")} | AG24: =IFERROR( LET( hoja, LEFT(AG$1,3)&"R", fila, MATCH( RIGHT($A24, LEN($A24)-4), INDIRECT(hoja&"!$A:$A"), 0 ), columna, MATCH( "Totales", INDIRECT(hoja&"!$6:$6"), 0 ), valor, INDEX( INDIRECT(hoja&"!$A:$ZZ"), fila, columna ), IF(valor="-", "", valor) ), "") | AH24: =AF24-AG24 -> 0 | AI24: {=IFERROR(SUMIF(Consolidado!$C$3:$C63, $A24, INDEX(Consolidado!$E$3:$P$100, , MATCH(AI$1, Consolidado!$E$2:$P$2, 0))), "")} | AJ24: =IFERROR( LET( hoja, LEFT(AJ$1,3)&"R", fila, MATCH( RIGHT($A24, LEN($A24)-4), INDIRECT(hoja&"!$A:$A"), 0 ), columna, MATCH( "Totales", INDIRECT(hoja&"!$6:$6"), 0 ), valor, INDEX( INDIRECT(hoja&"!$A:$ZZ"), fila, columna ), IF(valor="-", "", valor) ), "") | AK24: =AI24-AJ24 -> 0 | AL24: {=IFERROR(SUMIF(Consolidado!$C$3:$C63, $A24, INDEX(Consolidado!$E$3:$P$100, , MATCH(AL$1, Consolidado!$E$2:$P$2, 0))), "")} | AM24: =IFERROR( LET( hoja, LEFT(AM$1,3)&"R", fila, MATCH( RIGHT($A24, LEN($A24)-4), INDIRECT(hoja&"!$A:$A"), 0 ), columna, MATCH( "Totales", INDIRECT(hoja&"!$6:$6"), 0 ), valor, INDEX( INDIRECT(hoja&"!$A:$ZZ"), fila, columna ), IF(valor="-", "", valor) ), "") | AN24: =AL24-AM24 -> 0
A25: =Menus!B18 -> B15 Mobiliario y equipo de oficina | B25: =SUM(IF(MONTH(TODAY())>1,E25,0), IF(MONTH(TODAY())>2,H25,0), IF(MONTH(TODAY())>3,K25,0), IF(MONTH(TODAY())>4,N25,0), IF(MONTH(TODAY())>5,Q25,0), IF(MONTH(TODAY())>6,T25,0), IF(MONTH(TODAY())>7,W25,0), IF(MONTH(TODAY())>8,Z25,0), IF(MONTH(TODAY())>9,AC25,0), IF(MONTH(TODAY())>10,AF25,0), IF(MONTH(TODAY())>11,AI25,0), IF(MONTH(TODAY())>12,AL25,0)) -> 0 | C25: =SUM(IF(MONTH(TODAY())>1,F25,0), IF(MONTH(TODAY())>2,I25,0), IF(MONTH(TODAY())>3,L25,0), IF(MONTH(TODAY())>4,O25,0), IF(MONTH(TODAY())>5,R25,0), IF(MONTH(TODAY())>6,U25,0), IF(MONTH(TODAY())>7,X25,0), IF(MONTH(TODAY())>8,AA25,0), IF(MONTH(TODAY())>9,AD25,0), IF(MONTH(TODAY())>10,AG25,0), IF(MONTH(TODAY())>11,AJ25,0), IF(MONTH(TODAY())>12,AM25,0)) -> 0 | D25: =B25-C25 -> 0 | E25: {=IFERROR(SUMIF(Consolidado!$C$3:$C63, $A25, INDEX(Consolidado!$E$3:$P$100, , MATCH(E$1, Consolidado!$E$2:$P$2, 0))), "")} | F25: =IFERROR( LET( hoja, LEFT(F$1,3)&"R", fila, MATCH( RIGHT($A25, LEN($A25)-4), INDIRECT(hoja&"!$A:$A"), 0 ), columna, MATCH( "Totales", INDIRECT(hoja&"!$6:$6"), 0 ), valor, INDEX( INDIRECT(hoja&"!$A:$ZZ"), fila, columna ), IF(valor="-", "", valor) ), "") | G25: =E25-F25 -> 0 | H25: {=IFERROR(SUMIF(Consolidado!$C$3:$C63, $A25, INDEX(Consolidado!$E$3:$P$100, , MATCH(H$1, Consolidado!$E$2:$P$2, 0))), "")} | I25: =IFERROR( LET( hoja, LEFT(I$1,3)&"R", fila, MATCH( RIGHT($A25, LEN($A25)-4), INDIRECT(hoja&"!$A:$A"), 0 ), columna, MATCH( "Totales", INDIRECT(hoja&"!$6:$6"), 0 ), valor, INDEX( INDIRECT(hoja&"!$A:$ZZ"), fila, columna ), IF(valor="-", "", valor) ), "") | J25: =H25-I25 -> 0 | K25: {=IFERROR(SUMIF(Consolidado!$C$3:$C63, $A25, INDEX(Consolidado!$E$3:$P$100, , MATCH(K$1, Consolidado!$E$2:$P$2, 0))), "")} | L25: =IFERROR( LET( hoja, LEFT(L$1,3)&"R", fila, MATCH( RIGHT($A25, LEN($A25)-4), INDIRECT(hoja&"!$A:$A"), 0 ), columna, MATCH( "Totales", INDIRECT(hoja&"!$6:$6"), 0 ), valor, INDEX( INDIRECT(hoja&"!$A:$ZZ"), fila, columna ), IF(valor="-", "", valor) ), "") | M25: =K25-L25 -> 0 | N25: {=IFERROR(SUMIF(Consolidado!$C$3:$C63, $A25, INDEX(Consolidado!$E$3:$P$100, , MATCH(N$1, Consolidado!$E$2:$P$2, 0))), "")} | O25: =IFERROR( LET( hoja, LEFT(O$1,3)&"R", fila, MATCH( RIGHT($A25, LEN($A25)-4), INDIRECT(hoja&"!$A:$A"), 0 ), columna, MATCH( "Totales", INDIRECT(hoja&"!$6:$6"), 0 ), valor, INDEX( INDIRECT(hoja&"!$A:$ZZ"), fila, columna ), IF(valor="-", "", valor) ), "") | P25: =N25-O25 -> 0 | Q25: {=IFERROR(SUMIF(Consolidado!$C$3:$C63, $A25, INDEX(Consolidado!$E$3:$P$100, , MATCH(Q$1, Consolidado!$E$2:$P$2, 0))), "")} | R25: =IFERROR( LET( hoja, LEFT(R$1,3)&"R", fila, MATCH( RIGHT($A25, LEN($A25)-4), INDIRECT(hoja&"!$A:$A"), 0 ), columna, MATCH( "Totales", INDIRECT(hoja&"!$6:$6"), 0 ), valor, INDEX( INDIRECT(hoja&"!$A:$ZZ"), fila, columna ), IF(valor="-", "", valor) ), "") | S25: =Q25-R25 -> 0 | T25: {=IFERROR(SUMIF(Consolidado!$C$3:$C63, $A25, INDEX(Consolidado!$E$3:$P$100, , MATCH(T$1, Consolidado!$E$2:$P$2, 0))), "")} | U25: =IFERROR( LET( hoja, LEFT(U$1,3)&"R", fila, MATCH( RIGHT($A25, LEN($A25)-4), INDIRECT(hoja&"!$A:$A"), 0 ), columna, MATCH( "Totales", INDIRECT(hoja&"!$6:$6"), 0 ), valor, INDEX( INDIRECT(hoja&"!$A:$ZZ"), fila, columna ), IF(valor="-", "", valor) ), "") | V25: =T25-U25 -> 0 | W25: {=IFERROR(SUMIF(Consolidado!$C$3:$C63, $A25, INDEX(Consolidado!$E$3:$P$100, , MATCH(W$1, Consolidado!$E$2:$P$2, 0))), "")} | X25: =IFERROR( LET( hoja, LEFT(X$1,3)&"R", fila, MATCH( RIGHT($A25, LEN($A25)-4), INDIRECT(hoja&"!$A:$A"), 0 ), columna, MATCH( "Totales", INDIRECT(hoja&"!$6:$6"), 0 ), valor, INDEX( INDIRECT(hoja&"!$A:$ZZ"), fila, columna ), IF(valor="-", "", valor) ), "") | Y25: =W25-X25 -> 0 | Z25: {=IFERROR(SUMIF(Consolidado!$C$3:$C63, $A25, INDEX(Consolidado!$E$3:$P$100, , MATCH(Z$1, Consolidado!$E$2:$P$2, 0))), "")} | AA25: =IFERROR( LET( hoja, LEFT(AA$1,3)&"R", fila, MATCH( RIGHT($A25, LEN($A25)-4), INDIRECT(hoja&"!$A:$A"), 0 ), columna, MATCH( "Totales", INDIRECT(hoja&"!$6:$6"), 0 ), valor, INDEX( INDIRECT(hoja&"!$A:$ZZ"), fila, columna ), IF(valor="-", "", valor) ), "") | AB25: =Z25-AA25 -> 0 | AC25: {=IFERROR(SUMIF(Consolidado!$C$3:$C63, $A25, INDEX(Consolidado!$E$3:$P$100, , MATCH(AC$1, Consolidado!$E$2:$P$2, 0))), "")} | AD25: =IFERROR( LET( hoja, LEFT(AD$1,3)&"R", fila, MATCH( RIGHT($A25, LEN($A25)-4), INDIRECT(hoja&"!$A:$A"), 0 ), columna, MATCH( "Totales", INDIRECT(hoja&"!$6:$6"), 0 ), valor, INDEX( INDIRECT(hoja&"!$A:$ZZ"), fila, columna ), IF(valor="-", "", valor) ), "") | AE25: =AC25-AD25 -> 0 | AF25: {=IFERROR(SUMIF(Consolidado!$C$3:$C63, $A25, INDEX(Consolidado!$E$3:$P$100, , MATCH(AF$1, Consolidado!$E$2:$P$2, 0))), "")} | AG25: =IFERROR( LET( hoja, LEFT(AG$1,3)&"R", fila, MATCH( RIGHT($A25, LEN($A25)-4), INDIRECT(hoja&"!$A:$A"), 0 ), columna, MATCH( "Totales", INDIRECT(hoja&"!$6:$6"), 0 ), valor, INDEX( INDIRECT(hoja&"!$A:$ZZ"), fila, columna ), IF(valor="-", "", valor) ), "") | AH25: =AF25-AG25 -> 0 | AI25: {=IFERROR(SUMIF(Consolidado!$C$3:$C63, $A25, INDEX(Consolidado!$E$3:$P$100, , MATCH(AI$1, Consolidado!$E$2:$P$2, 0))), "")} | AJ25: =IFERROR( LET( hoja, LEFT(AJ$1,3)&"R", fila, MATCH( RIGHT($A25, LEN($A25)-4), INDIRECT(hoja&"!$A:$A"), 0 ), columna, MATCH( "Totales", INDIRECT(hoja&"!$6:$6"), 0 ), valor, INDEX( INDIRECT(hoja&"!$A:$ZZ"), fila, columna ), IF(valor="-", "", valor) ), "") | AK25: =AI25-AJ25 -> 0 | AL25: {=IFERROR(SUMIF(Consolidado!$C$3:$C63, $A25, INDEX(Consolidado!$E$3:$P$100, , MATCH(AL$1, Consolidado!$E$2:$P$2, 0))), "")} | AM25: =IFERROR( LET( hoja, LEFT(AM$1,3)&"R", fila, MATCH( RIGHT($A25, LEN($A25)-4), INDIRECT(hoja&"!$A:$A"), 0 ), columna, MATCH( "Totales", INDIRECT(hoja&"!$6:$6"), 0 ), valor, INDEX( INDIRECT(hoja&"!$A:$ZZ"), fila, columna ), IF(valor="-", "", valor) ), "") | AN25: =AL25-AM25 -> 0
A26: =Menus!B19 -> B16 Fianzas y seguros | B26: =SUM(IF(MONTH(TODAY())>1,E26,0), IF(MONTH(TODAY())>2,H26,0), IF(MONTH(TODAY())>3,K26,0), IF(MONTH(TODAY())>4,N26,0), IF(MONTH(TODAY())>5,Q26,0), IF(MONTH(TODAY())>6,T26,0), IF(MONTH(TODAY())>7,W26,0), IF(MONTH(TODAY())>8,Z26,0), IF(MONTH(TODAY())>9,AC26,0), IF(MONTH(TODAY())>10,AF26,0), IF(MONTH(TODAY())>11,AI26,0), IF(MONTH(TODAY())>12,AL26,0)) -> 0 | C26: =SUM(IF(MONTH(TODAY())>1,F26,0), IF(MONTH(TODAY())>2,I26,0), IF(MONTH(TODAY())>3,L26,0), IF(MONTH(TODAY())>4,O26,0), IF(MONTH(TODAY())>5,R26,0), IF(MONTH(TODAY())>6,U26,0), IF(MONTH(TODAY())>7,X26,0), IF(MONTH(TODAY())>8,AA26,0), IF(MONTH(TODAY())>9,AD26,0), IF(MONTH(TODAY())>10,AG26,0), IF(MONTH(TODAY())>11,AJ26,0), IF(MONTH(TODAY())>12,AM26,0)) -> 0 | D26: =B26-C26 -> 0 | E26: {=IFERROR(SUMIF(Consolidado!$C$3:$C63, $A26, INDEX(Consolidado!$E$3:$P$100, , MATCH(E$1, Consolidado!$E$2:$P$2, 0))), "")} | F26: =IFERROR( LET( hoja, LEFT(F$1,3)&"R", fila, MATCH( RIGHT($A26, LEN($A26)-4), INDIRECT(hoja&"!$A:$A"), 0 ), columna, MATCH( "Totales", INDIRECT(hoja&"!$6:$6"), 0 ), valor, INDEX( INDIRECT(hoja&"!$A:$ZZ"), fila, columna ), IF(valor="-", "", valor) ), "") | G26: =E26-F26 -> 0 | H26: {=IFERROR(SUMIF(Consolidado!$C$3:$C63, $A26, INDEX(Consolidado!$E$3:$P$100, , MATCH(H$1, Consolidado!$E$2:$P$2, 0))), "")} | I26: =IFERROR( LET( hoja, LEFT(I$1,3)&"R", fila, MATCH( RIGHT($A26, LEN($A26)-4), INDIRECT(hoja&"!$A:$A"), 0 ), columna, MATCH( "Totales", INDIRECT(hoja&"!$6:$6"), 0 ), valor, INDEX( INDIRECT(hoja&"!$A:$ZZ"), fila, columna ), IF(valor="-", "", valor) ), "") | J26: =H26-I26 -> 0 | K26: {=IFERROR(SUMIF(Consolidado!$C$3:$C63, $A26, INDEX(Consolidado!$E$3:$P$100, , MATCH(K$1, Consolidado!$E$2:$P$2, 0))), "")} | L26: =IFERROR( LET( hoja, LEFT(L$1,3)&"R", fila, MATCH( RIGHT($A26, LEN($A26)-4), INDIRECT(hoja&"!$A:$A"), 0 ), columna, MATCH( "Totales", INDIRECT(hoja&"!$6:$6"), 0 ), valor, INDEX( INDIRECT(hoja&"!$A:$ZZ"), fila, columna ), IF(valor="-", "", valor) ), "") | M26: =K26-L26 -> 0 | N26: {=IFERROR(SUMIF(Consolidado!$C$3:$C63, $A26, INDEX(Consolidado!$E$3:$P$100, , MATCH(N$1, Consolidado!$E$2:$P$2, 0))), "")} | O26: =IFERROR( LET( hoja, LEFT(O$1,3)&"R", fila, MATCH( RIGHT($A26, LEN($A26)-4), INDIRECT(hoja&"!$A:$A"), 0 ), columna, MATCH( "Totales", INDIRECT(hoja&"!$6:$6"), 0 ), valor, INDEX( INDIRECT(hoja&"!$A:$ZZ"), fila, columna ), IF(valor="-", "", valor) ), "") | P26: =N26-O26 -> 0 | Q26: {=IFERROR(SUMIF(Consolidado!$C$3:$C63, $A26, INDEX(Consolidado!$E$3:$P$100, , MATCH(Q$1, Consolidado!$E$2:$P$2, 0))), "")} | R26: =IFERROR( LET( hoja, LEFT(R$1,3)&"R", fila, MATCH( RIGHT($A26, LEN($A26)-4), INDIRECT(hoja&"!$A:$A"), 0 ), columna, MATCH( "Totales", INDIRECT(hoja&"!$6:$6"), 0 ), valor, INDEX( INDIRECT(hoja&"!$A:$ZZ"), fila, columna ), IF(valor="-", "", valor) ), "") | S26: =Q26-R26 -> 0 | T26: {=IFERROR(SUMIF(Consolidado!$C$3:$C63, $A26, INDEX(Consolidado!$E$3:$P$100, , MATCH(T$1, Consolidado!$E$2:$P$2, 0))), "")} | U26: =IFERROR( LET( hoja, LEFT(U$1,3)&"R", fila, MATCH( RIGHT($A26, LEN($A26)-4), INDIRECT(hoja&"!$A:$A"), 0 ), columna, MATCH( "Totales", INDIRECT(hoja&"!$6:$6"), 0 ), valor, INDEX( INDIRECT(hoja&"!$A:$ZZ"), fila, columna ), IF(valor="-", "", valor) ), "") | V26: =T26-U26 -> 0 | W26: {=IFERROR(SUMIF(Consolidado!$C$3:$C63, $A26, INDEX(Consolidado!$E$3:$P$100, , MATCH(W$1, Consolidado!$E$2:$P$2, 0))), "")} | X26: =IFERROR( LET( hoja, LEFT(X$1,3)&"R", fila, MATCH( RIGHT($A26, LEN($A26)-4), INDIRECT(hoja&"!$A:$A"), 0 ), columna, MATCH( "Totales", INDIRECT(hoja&"!$6:$6"), 0 ), valor, INDEX( INDIRECT(hoja&"!$A:$ZZ"), fila, columna ), IF(valor="-", "", valor) ), "") | Y26: =W26-X26 -> 0 | Z26: {=IFERROR(SUMIF(Consolidado!$C$3:$C63, $A26, INDEX(Consolidado!$E$3:$P$100, , MATCH(Z$1, Consolidado!$E$2:$P$2, 0))), "")} | AA26: =IFERROR( LET( hoja, LEFT(AA$1,3)&"R", fila, MATCH( RIGHT($A26, LEN($A26)-4), INDIRECT(hoja&"!$A:$A"), 0 ), columna, MATCH( "Totales", INDIRECT(hoja&"!$6:$6"), 0 ), valor, INDEX( INDIRECT(hoja&"!$A:$ZZ"), fila, columna ), IF(valor="-", "", valor) ), "") | AB26: =Z26-AA26 -> 0 | AC26: {=IFERROR(SUMIF(Consolidado!$C$3:$C63, $A26, INDEX(Consolidado!$E$3:$P$100, , MATCH(AC$1, Consolidado!$E$2:$P$2, 0))), "")} | AD26: =IFERROR( LET( hoja, LEFT(AD$1,3)&"R", fila, MATCH( RIGHT($A26, LEN($A26)-4), INDIRECT(hoja&"!$A:$A"), 0 ), columna, MATCH( "Totales", INDIRECT(hoja&"!$6:$6"), 0 ), valor, INDEX( INDIRECT(hoja&"!$A:$ZZ"), fila, columna ), IF(valor="-", "", valor) ), "") | AE26: =AC26-AD26 -> 0 | AF26: {=IFERROR(SUMIF(Consolidado!$C$3:$C63, $A26, INDEX(Consolidado!$E$3:$P$100, , MATCH(AF$1, Consolidado!$E$2:$P$2, 0))), "")} | AG26: =IFERROR( LET( hoja, LEFT(AG$1,3)&"R", fila, MATCH( RIGHT($A26, LEN($A26)-4), INDIRECT(hoja&"!$A:$A"), 0 ), columna, MATCH( "Totales", INDIRECT(hoja&"!$6:$6"), 0 ), valor, INDEX( INDIRECT(hoja&"!$A:$ZZ"), fila, columna ), IF(valor="-", "", valor) ), "") | AH26: =AF26-AG26 -> 0 | AI26: {=IFERROR(SUMIF(Consolidado!$C$3:$C63, $A26, INDEX(Consolidado!$E$3:$P$100, , MATCH(AI$1, Consolidado!$E$2:$P$2, 0))), "")} | AJ26: =IFERROR( LET( hoja, LEFT(AJ$1,3)&"R", fila, MATCH( RIGHT($A26, LEN($A26)-4), INDIRECT(hoja&"!$A:$A"), 0 ), columna, MATCH( "Totales", INDIRECT(hoja&"!$6:$6"), 0 ), valor, INDEX( INDIRECT(hoja&"!$A:$ZZ"), fila, columna ), IF(valor="-", "", valor) ), "") | AK26: =AI26-AJ26 -> 0 | AL26: {=IFERROR(SUMIF(Consolidado!$C$3:$C63, $A26, INDEX(Consolidado!$E$3:$P$100, , MATCH(AL$1, Consolidado!$E$2:$P$2, 0))), "")} | AM26: =IFERROR( LET( hoja, LEFT(AM$1,3)&"R", fila, MATCH( RIGHT($A26, LEN($A26)-4), INDIRECT(hoja&"!$A:$A"), 0 ), columna, MATCH( "Totales", INDIRECT(hoja&"!$6:$6"), 0 ), valor, INDEX( INDIRECT(hoja&"!$A:$ZZ"), fila, columna ), IF(valor="-", "", valor) ), "") | AN26: =AL26-AM26 -> 0
A27: =Menus!B20 -> B17 Mantenimiento Plaza/Oficina | B27: =SUM(IF(MONTH(TODAY())>1,E27,0), IF(MONTH(TODAY())>2,H27,0), IF(MONTH(TODAY())>3,K27,0), IF(MONTH(TODAY())>4,N27,0), IF(MONTH(TODAY())>5,Q27,0), IF(MONTH(TODAY())>6,T27,0), IF(MONTH(TODAY())>7,W27,0), IF(MONTH(TODAY())>8,Z27,0), IF(MONTH(TODAY())>9,AC27,0), IF(MONTH(TODAY())>10,AF27,0), IF(MONTH(TODAY())>11,AI27,0), IF(MONTH(TODAY())>12,AL27,0)) -> 0 | C27: =SUM(IF(MONTH(TODAY())>1,F27,0), IF(MONTH(TODAY())>2,I27,0), IF(MONTH(TODAY())>3,L27,0), IF(MONTH(TODAY())>4,O27,0), IF(MONTH(TODAY())>5,R27,0), IF(MONTH(TODAY())>6,U27,0), IF(MONTH(TODAY())>7,X27,0), IF(MONTH(TODAY())>8,AA27,0), IF(MONTH(TODAY())>9,AD27,0), IF(MONTH(TODAY())>10,AG27,0), IF(MONTH(TODAY())>11,AJ27,0), IF(MONTH(TODAY())>12,AM27,0)) -> 0 | D27: =B27-C27 -> 0 | E27: {=IFERROR(SUMIF(Consolidado!$C$3:$C63, $A27, INDEX(Consolidado!$E$3:$P$100, , MATCH(E$1, Consolidado!$E$2:$P$2, 0))), "")} | F27: =IFERROR( LET( hoja, LEFT(F$1,3)&"R", fila, MATCH( RIGHT($A27, LEN($A27)-4), INDIRECT(hoja&"!$A:$A"), 0 ), columna, MATCH( "Totales", INDIRECT(hoja&"!$6:$6"), 0 ), valor, INDEX( INDIRECT(hoja&"!$A:$ZZ"), fila, columna ), IF(valor="-", "", valor) ), "") | G27: =E27-F27 -> 0 | H27: {=IFERROR(SUMIF(Consolidado!$C$3:$C63, $A27, INDEX(Consolidado!$E$3:$P$100, , MATCH(H$1, Consolidado!$E$2:$P$2, 0))), "")} | I27: =IFERROR( LET( hoja, LEFT(I$1,3)&"R", fila, MATCH( RIGHT($A27, LEN($A27)-4), INDIRECT(hoja&"!$A:$A"), 0 ), columna, MATCH( "Totales", INDIRECT(hoja&"!$6:$6"), 0 ), valor, INDEX( INDIRECT(hoja&"!$A:$ZZ"), fila, columna ), IF(valor="-", "", valor) ), "") | J27: =H27-I27 -> 0 | K27: {=IFERROR(SUMIF(Consolidado!$C$3:$C63, $A27, INDEX(Consolidado!$E$3:$P$100, , MATCH(K$1, Consolidado!$E$2:$P$2, 0))), "")} | L27: =IFERROR( LET( hoja, LEFT(L$1,3)&"R", fila, MATCH( RIGHT($A27, LEN($A27)-4), INDIRECT(hoja&"!$A:$A"), 0 ), columna, MATCH( "Totales", INDIRECT(hoja&"!$6:$6"), 0 ), valor, INDEX( INDIRECT(hoja&"!$A:$ZZ"), fila, columna ), IF(valor="-", "", valor) ), "") | M27: =K27-L27 -> 0 | N27: {=IFERROR(SUMIF(Consolidado!$C$3:$C63, $A27, INDEX(Consolidado!$E$3:$P$100, , MATCH(N$1, Consolidado!$E$2:$P$2, 0))), "")} | O27: =IFERROR( LET( hoja, LEFT(O$1,3)&"R", fila, MATCH( RIGHT($A27, LEN($A27)-4), INDIRECT(hoja&"!$A:$A"), 0 ), columna, MATCH( "Totales", INDIRECT(hoja&"!$6:$6"), 0 ), valor, INDEX( INDIRECT(hoja&"!$A:$ZZ"), fila, columna ), IF(valor="-", "", valor) ), "") | P27: =N27-O27 -> 0 | Q27: {=IFERROR(SUMIF(Consolidado!$C$3:$C63, $A27, INDEX(Consolidado!$E$3:$P$100, , MATCH(Q$1, Consolidado!$E$2:$P$2, 0))), "")} | R27: =IFERROR( LET( hoja, LEFT(R$1,3)&"R", fila, MATCH( RIGHT($A27, LEN($A27)-4), INDIRECT(hoja&"!$A:$A"), 0 ), columna, MATCH( "Totales", INDIRECT(hoja&"!$6:$6"), 0 ), valor, INDEX( INDIRECT(hoja&"!$A:$ZZ"), fila, columna ), IF(valor="-", "", valor) ), "") | S27: =Q27-R27 -> 0 | T27: {=IFERROR(SUMIF(Consolidado!$C$3:$C63, $A27, INDEX(Consolidado!$E$3:$P$100, , MATCH(T$1, Consolidado!$E$2:$P$2, 0))), "")} | U27: =IFERROR( LET( hoja, LEFT(U$1,3)&"R", fila, MATCH( RIGHT($A27, LEN($A27)-4), INDIRECT(hoja&"!$A:$A"), 0 ), columna, MATCH( "Totales", INDIRECT(hoja&"!$6:$6"), 0 ), valor, INDEX( INDIRECT(hoja&"!$A:$ZZ"), fila, columna ), IF(valor="-", "", valor) ), "") | V27: =T27-U27 -> 0 | W27: {=IFERROR(SUMIF(Consolidado!$C$3:$C63, $A27, INDEX(Consolidado!$E$3:$P$100, , MATCH(W$1, Consolidado!$E$2:$P$2, 0))), "")} | X27: =IFERROR( LET( hoja, LEFT(X$1,3)&"R", fila, MATCH( RIGHT($A27, LEN($A27)-4), INDIRECT(hoja&"!$A:$A"), 0 ), columna, MATCH( "Totales", INDIRECT(hoja&"!$6:$6"), 0 ), valor, INDEX( INDIRECT(hoja&"!$A:$ZZ"), fila, columna ), IF(valor="-", "", valor) ), "") | Y27: =W27-X27 -> 0 | Z27: {=IFERROR(SUMIF(Consolidado!$C$3:$C63, $A27, INDEX(Consolidado!$E$3:$P$100, , MATCH(Z$1, Consolidado!$E$2:$P$2, 0))), "")} | AA27: =IFERROR( LET( hoja, LEFT(AA$1,3)&"R", fila, MATCH( RIGHT($A27, LEN($A27)-4), INDIRECT(hoja&"!$A:$A"), 0 ), columna, MATCH( "Totales", INDIRECT(hoja&"!$6:$6"), 0 ), valor, INDEX( INDIRECT(hoja&"!$A:$ZZ"), fila, columna ), IF(valor="-", "", valor) ), "") | AB27: =Z27-AA27 -> 0 | AC27: {=IFERROR(SUMIF(Consolidado!$C$3:$C63, $A27, INDEX(Consolidado!$E$3:$P$100, , MATCH(AC$1, Consolidado!$E$2:$P$2, 0))), "")} | AD27: =IFERROR( LET( hoja, LEFT(AD$1,3)&"R", fila, MATCH( RIGHT($A27, LEN($A27)-4), INDIRECT(hoja&"!$A:$A"), 0 ), columna, MATCH( "Totales", INDIRECT(hoja&"!$6:$6"), 0 ), valor, INDEX( INDIRECT(hoja&"!$A:$ZZ"), fila, columna ), IF(valor="-", "", valor) ), "") | AE27: =AC27-AD27 -> 0 | AF27: {=IFERROR(SUMIF(Consolidado!$C$3:$C63, $A27, INDEX(Consolidado!$E$3:$P$100, , MATCH(AF$1, Consolidado!$E$2:$P$2, 0))), "")} | AG27: =IFERROR( LET( hoja, LEFT(AG$1,3)&"R", fila, MATCH( RIGHT($A27, LEN($A27)-4), INDIRECT(hoja&"!$A:$A"), 0 ), columna, MATCH( "Totales", INDIRECT(hoja&"!$6:$6"), 0 ), valor, INDEX( INDIRECT(hoja&"!$A:$ZZ"), fila, columna ), IF(valor="-", "", valor) ), "") | AH27: =AF27-AG27 -> 0 | AI27: {=IFERROR(SUMIF(Consolidado!$C$3:$C63, $A27, INDEX(Consolidado!$E$3:$P$100, , MATCH(AI$1, Consolidado!$E$2:$P$2, 0))), "")} | AJ27: =IFERROR( LET( hoja, LEFT(AJ$1,3)&"R", fila, MATCH( RIGHT($A27, LEN($A27)-4), INDIRECT(hoja&"!$A:$A"), 0 ), columna, MATCH( "Totales", INDIRECT(hoja&"!$6:$6"), 0 ), valor, INDEX( INDIRECT(hoja&"!$A:$ZZ"), fila, columna ), IF(valor="-", "", valor) ), "") | AK27: =AI27-AJ27 -> 0 | AL27: {=IFERROR(SUMIF(Consolidado!$C$3:$C63, $A27, INDEX(Consolidado!$E$3:$P$100, , MATCH(AL$1, Consolidado!$E$2:$P$2, 0))), "")} | AM27: =IFERROR( LET( hoja, LEFT(AM$1,3)&"R", fila, MATCH( RIGHT($A27, LEN($A27)-4), INDIRECT(hoja&"!$A:$A"), 0 ), columna, MATCH( "Totales", INDIRECT(hoja&"!$6:$6"), 0 ), valor, INDEX( INDIRECT(hoja&"!$A:$ZZ"), fila, columna ), IF(valor="-", "", valor) ), "") | AN27: =AL27-AM27 -> 0
A28: =Menus!B21 -> B18 Depreciación | B28: =SUM(IF(MONTH(TODAY())>1,E28,0), IF(MONTH(TODAY())>2,H28,0), IF(MONTH(TODAY())>3,K28,0), IF(MONTH(TODAY())>4,N28,0), IF(MONTH(TODAY())>5,Q28,0), IF(MONTH(TODAY())>6,T28,0), IF(MONTH(TODAY())>7,W28,0), IF(MONTH(TODAY())>8,Z28,0), IF(MONTH(TODAY())>9,AC28,0), IF(MONTH(TODAY())>10,AF28,0), IF(MONTH(TODAY())>11,AI28,0), IF(MONTH(TODAY())>12,AL28,0)) -> 0 | C28: =SUM(IF(MONTH(TODAY())>1,F28,0), IF(MONTH(TODAY())>2,I28,0), IF(MONTH(TODAY())>3,L28,0), IF(MONTH(TODAY())>4,O28,0), IF(MONTH(TODAY())>5,R28,0), IF(MONTH(TODAY())>6,U28,0), IF(MONTH(TODAY())>7,X28,0), IF(MONTH(TODAY())>8,AA28,0), IF(MONTH(TODAY())>9,AD28,0), IF(MONTH(TODAY())>10,AG28,0), IF(MONTH(TODAY())>11,AJ28,0), IF(MONTH(TODAY())>12,AM28,0)) -> 0 | D28: =B28-C28 -> 0 | E28: {=IFERROR(SUMIF(Consolidado!$C$3:$C63, $A28, INDEX(Consolidado!$E$3:$P$100, , MATCH(E$1, Consolidado!$E$2:$P$2, 0))), "")} | F28: =IFERROR( LET( hoja, LEFT(F$1,3)&"R", fila, MATCH( RIGHT($A28, LEN($A28)-4), INDIRECT(hoja&"!$A:$A"), 0 ), columna, MATCH( "Totales", INDIRECT(hoja&"!$6:$6"), 0 ), valor, INDEX( INDIRECT(hoja&"!$A:$ZZ"), fila, columna ), IF(valor="-", "", valor) ), "") | G28: =E28-F28 -> 0 | H28: {=IFERROR(SUMIF(Consolidado!$C$3:$C63, $A28, INDEX(Consolidado!$E$3:$P$100, , MATCH(H$1, Consolidado!$E$2:$P$2, 0))), "")} | I28: =IFERROR( LET( hoja, LEFT(I$1,3)&"R", fila, MATCH( RIGHT($A28, LEN($A28)-4), INDIRECT(hoja&"!$A:$A"), 0 ), columna, MATCH( "Totales", INDIRECT(hoja&"!$6:$6"), 0 ), valor, INDEX( INDIRECT(hoja&"!$A:$ZZ"), fila, columna ), IF(valor="-", "", valor) ), "") | J28: =H28-I28 -> 0 | K28: {=IFERROR(SUMIF(Consolidado!$C$3:$C63, $A28, INDEX(Consolidado!$E$3:$P$100, , MATCH(K$1, Consolidado!$E$2:$P$2, 0))), "")} | L28: =IFERROR( LET( hoja, LEFT(L$1,3)&"R", fila, MATCH( RIGHT($A28, LEN($A28)-4), INDIRECT(hoja&"!$A:$A"), 0 ), columna, MATCH( "Totales", INDIRECT(hoja&"!$6:$6"), 0 ), valor, INDEX( INDIRECT(hoja&"!$A:$ZZ"), fila, columna ), IF(valor="-", "", valor) ), "") | M28: =K28-L28 -> 0 | N28: {=IFERROR(SUMIF(Consolidado!$C$3:$C63, $A28, INDEX(Consolidado!$E$3:$P$100, , MATCH(N$1, Consolidado!$E$2:$P$2, 0))), "")} | O28: =IFERROR( LET( hoja, LEFT(O$1,3)&"R", fila, MATCH( RIGHT($A28, LEN($A28)-4), INDIRECT(hoja&"!$A:$A"), 0 ), columna, MATCH( "Totales", INDIRECT(hoja&"!$6:$6"), 0 ), valor, INDEX( INDIRECT(hoja&"!$A:$ZZ"), fila, columna ), IF(valor="-", "", valor) ), "") | P28: =N28-O28 -> 0 | Q28: {=IFERROR(SUMIF(Consolidado!$C$3:$C63, $A28, INDEX(Consolidado!$E$3:$P$100, , MATCH(Q$1, Consolidado!$E$2:$P$2, 0))), "")} | R28: =IFERROR( LET( hoja, LEFT(R$1,3)&"R", fila, MATCH( RIGHT($A28, LEN($A28)-4), INDIRECT(hoja&"!$A:$A"), 0 ), columna, MATCH( "Totales", INDIRECT(hoja&"!$6:$6"), 0 ), valor, INDEX( INDIRECT(hoja&"!$A:$ZZ"), fila, columna ), IF(valor="-", "", valor) ), "") | S28: =Q28-R28 -> 0 | T28: {=IFERROR(SUMIF(Consolidado!$C$3:$C63, $A28, INDEX(Consolidado!$E$3:$P$100, , MATCH(T$1, Consolidado!$E$2:$P$2, 0))), "")} | U28: =IFERROR( LET( hoja, LEFT(U$1,3)&"R", fila, MATCH( RIGHT($A28, LEN($A28)-4), INDIRECT(hoja&"!$A:$A"), 0 ), columna, MATCH( "Totales", INDIRECT(hoja&"!$6:$6"), 0 ), valor, INDEX( INDIRECT(hoja&"!$A:$ZZ"), fila, columna ), IF(valor="-", "", valor) ), "") | V28: =T28-U28 -> 0 | W28: {=IFERROR(SUMIF(Consolidado!$C$3:$C63, $A28, INDEX(Consolidado!$E$3:$P$100, , MATCH(W$1, Consolidado!$E$2:$P$2, 0))), "")} | X28: =IFERROR( LET( hoja, LEFT(X$1,3)&"R", fila, MATCH( RIGHT($A28, LEN($A28)-4), INDIRECT(hoja&"!$A:$A"), 0 ), columna, MATCH( "Totales", INDIRECT(hoja&"!$6:$6"), 0 ), valor, INDEX( INDIRECT(hoja&"!$A:$ZZ"), fila, columna ), IF(valor="-", "", valor) ), "") | Y28: =W28-X28 -> 0 | Z28: {=IFERROR(SUMIF(Consolidado!$C$3:$C63, $A28, INDEX(Consolidado!$E$3:$P$100, , MATCH(Z$1, Consolidado!$E$2:$P$2, 0))), "")} | AA28: =IFERROR( LET( hoja, LEFT(AA$1,3)&"R", fila, MATCH( RIGHT($A28, LEN($A28)-4), INDIRECT(hoja&"!$A:$A"), 0 ), columna, MATCH( "Totales", INDIRECT(hoja&"!$6:$6"), 0 ), valor, INDEX( INDIRECT(hoja&"!$A:$ZZ"), fila, columna ), IF(valor="-", "", valor) ), "") | AB28: =Z28-AA28 -> 0 | AC28: {=IFERROR(SUMIF(Consolidado!$C$3:$C63, $A28, INDEX(Consolidado!$E$3:$P$100, , MATCH(AC$1, Consolidado!$E$2:$P$2, 0))), "")} | AD28: =IFERROR( LET( hoja, LEFT(AD$1,3)&"R", fila, MATCH( RIGHT($A28, LEN($A28)-4), INDIRECT(hoja&"!$A:$A"), 0 ), columna, MATCH( "Totales", INDIRECT(hoja&"!$6:$6"), 0 ), valor, INDEX( INDIRECT(hoja&"!$A:$ZZ"), fila, columna ), IF(valor="-", "", valor) ), "") | AE28: =AC28-AD28 -> 0 | AF28: {=IFERROR(SUMIF(Consolidado!$C$3:$C63, $A28, INDEX(Consolidado!$E$3:$P$100, , MATCH(AF$1, Consolidado!$E$2:$P$2, 0))), "")} | AG28: =IFERROR( LET( hoja, LEFT(AG$1,3)&"R", fila, MATCH( RIGHT($A28, LEN($A28)-4), INDIRECT(hoja&"!$A:$A"), 0 ), columna, MATCH( "Totales", INDIRECT(hoja&"!$6:$6"), 0 ), valor, INDEX( INDIRECT(hoja&"!$A:$ZZ"), fila, columna ), IF(valor="-", "", valor) ), "") | AH28: =AF28-AG28 -> 0 | AI28: {=IFERROR(SUMIF(Consolidado!$C$3:$C63, $A28, INDEX(Consolidado!$E$3:$P$100, , MATCH(AI$1, Consolidado!$E$2:$P$2, 0))), "")} | AJ28: =IFERROR( LET( hoja, LEFT(AJ$1,3)&"R", fila, MATCH( RIGHT($A28, LEN($A28)-4), INDIRECT(hoja&"!$A:$A"), 0 ), columna, MATCH( "Totales", INDIRECT(hoja&"!$6:$6"), 0 ), valor, INDEX( INDIRECT(hoja&"!$A:$ZZ"), fila, columna ), IF(valor="-", "", valor) ), "") | AK28: =AI28-AJ28 -> 0 | AL28: {=IFERROR(SUMIF(Consolidado!$C$3:$C63, $A28, INDEX(Consolidado!$E$3:$P$100, , MATCH(AL$1, Consolidado!$E$2:$P$2, 0))), "")} | AM28: =IFERROR( LET( hoja, LEFT(AM$1,3)&"R", fila, MATCH( RIGHT($A28, LEN($A28)-4), INDIRECT(hoja&"!$A:$A"), 0 ), columna, MATCH( "Totales", INDIRECT(hoja&"!$6:$6"), 0 ), valor, INDEX( INDIRECT(hoja&"!$A:$ZZ"), fila, columna ), IF(valor="-", "", valor) ), "") | AN28: =AL28-AM28 -> 0
A29: =Menus!B22 -> B19 Comidas empleados | B29: =SUM(IF(MONTH(TODAY())>1,E29,0), IF(MONTH(TODAY())>2,H29,0), IF(MONTH(TODAY())>3,K29,0), IF(MONTH(TODAY())>4,N29,0), IF(MONTH(TODAY())>5,Q29,0), IF(MONTH(TODAY())>6,T29,0), IF(MONTH(TODAY())>7,W29,0), IF(MONTH(TODAY())>8,Z29,0), IF(MONTH(TODAY())>9,AC29,0), IF(MONTH(TODAY())>10,AF29,0), IF(MONTH(TODAY())>11,AI29,0), IF(MONTH(TODAY())>12,AL29,0)) -> 0 | C29: =SUM(IF(MONTH(TODAY())>1,F29,0), IF(MONTH(TODAY())>2,I29,0), IF(MONTH(TODAY())>3,L29,0), IF(MONTH(TODAY())>4,O29,0), IF(MONTH(TODAY())>5,R29,0), IF(MONTH(TODAY())>6,U29,0), IF(MONTH(TODAY())>7,X29,0), IF(MONTH(TODAY())>8,AA29,0), IF(MONTH(TODAY())>9,AD29,0), IF(MONTH(TODAY())>10,AG29,0), IF(MONTH(TODAY())>11,AJ29,0), IF(MONTH(TODAY())>12,AM29,0)) -> 0 | D29: =B29-C29 -> 0 | E29: {=IFERROR(SUMIF(Consolidado!$C$3:$C63, $A29, INDEX(Consolidado!$E$3:$P$100, , MATCH(E$1, Consolidado!$E$2:$P$2, 0))), "")} | F29: =IFERROR( LET( hoja, LEFT(F$1,3)&"R", fila, MATCH( RIGHT($A29, LEN($A29)-4), INDIRECT(hoja&"!$A:$A"), 0 ), columna, MATCH( "Totales", INDIRECT(hoja&"!$6:$6"), 0 ), valor, INDEX( INDIRECT(hoja&"!$A:$ZZ"), fila, columna ), IF(valor="-", "", valor) ), "") | G29: =E29-F29 -> 0 | H29: {=IFERROR(SUMIF(Consolidado!$C$3:$C63, $A29, INDEX(Consolidado!$E$3:$P$100, , MATCH(H$1, Consolidado!$E$2:$P$2, 0))), "")} | I29: =IFERROR( LET( hoja, LEFT(I$1,3)&"R", fila, MATCH( RIGHT($A29, LEN($A29)-4), INDIRECT(hoja&"!$A:$A"), 0 ), columna, MATCH( "Totales", INDIRECT(hoja&"!$6:$6"), 0 ), valor, INDEX( INDIRECT(hoja&"!$A:$ZZ"), fila, columna ), IF(valor="-", "", valor) ), "") | J29: =H29-I29 -> 0 | K29: {=IFERROR(SUMIF(Consolidado!$C$3:$C63, $A29, INDEX(Consolidado!$E$3:$P$100, , MATCH(K$1, Consolidado!$E$2:$P$2, 0))), "")} | L29: =IFERROR( LET( hoja, LEFT(L$1,3)&"R", fila, MATCH( RIGHT($A29, LEN($A29)-4), INDIRECT(hoja&"!$A:$A"), 0 ), columna, MATCH( "Totales", INDIRECT(hoja&"!$6:$6"), 0 ), valor, INDEX( INDIRECT(hoja&"!$A:$ZZ"), fila, columna ), IF(valor="-", "", valor) ), "") | M29: =K29-L29 -> 0 | N29: {=IFERROR(SUMIF(Consolidado!$C$3:$C63, $A29, INDEX(Consolidado!$E$3:$P$100, , MATCH(N$1, Consolidado!$E$2:$P$2, 0))), "")} | O29: =IFERROR( LET( hoja, LEFT(O$1,3)&"R", fila, MATCH( RIGHT($A29, LEN($A29)-4), INDIRECT(hoja&"!$A:$A"), 0 ), columna, MATCH( "Totales", INDIRECT(hoja&"!$6:$6"), 0 ), valor, INDEX( INDIRECT(hoja&"!$A:$ZZ"), fila, columna ), IF(valor="-", "", valor) ), "") | P29: =N29-O29 -> 0 | Q29: {=IFERROR(SUMIF(Consolidado!$C$3:$C63, $A29, INDEX(Consolidado!$E$3:$P$100, , MATCH(Q$1, Consolidado!$E$2:$P$2, 0))), "")} | R29: =IFERROR( LET( hoja, LEFT(R$1,3)&"R", fila, MATCH( RIGHT($A29, LEN($A29)-4), INDIRECT(hoja&"!$A:$A"), 0 ), columna, MATCH( "Totales", INDIRECT(hoja&"!$6:$6"), 0 ), valor, INDEX( INDIRECT(hoja&"!$A:$ZZ"), fila, columna ), IF(valor="-", "", valor) ), "") | S29: =Q29-R29 -> 0 | T29: {=IFERROR(SUMIF(Consolidado!$C$3:$C63, $A29, INDEX(Consolidado!$E$3:$P$100, , MATCH(T$1, Consolidado!$E$2:$P$2, 0))), "")} | U29: =IFERROR( LET( hoja, LEFT(U$1,3)&"R", fila, MATCH( RIGHT($A29, LEN($A29)-4), INDIRECT(hoja&"!$A:$A"), 0 ), columna, MATCH( "Totales", INDIRECT(hoja&"!$6:$6"), 0 ), valor, INDEX( INDIRECT(hoja&"!$A:$ZZ"), fila, columna ), IF(valor="-", "", valor) ), "") | V29: =T29-U29 -> 0 | W29: {=IFERROR(SUMIF(Consolidado!$C$3:$C63, $A29, INDEX(Consolidado!$E$3:$P$100, , MATCH(W$1, Consolidado!$E$2:$P$2, 0))), "")} | X29: =IFERROR( LET( hoja, LEFT(X$1,3)&"R", fila, MATCH( RIGHT($A29, LEN($A29)-4), INDIRECT(hoja&"!$A:$A"), 0 ), columna, MATCH( "Totales", INDIRECT(hoja&"!$6:$6"), 0 ), valor, INDEX( INDIRECT(hoja&"!$A:$ZZ"), fila, columna ), IF(valor="-", "", valor) ), "") | Y29: =W29-X29 -> 0 | Z29: {=IFERROR(SUMIF(Consolidado!$C$3:$C63, $A29, INDEX(Consolidado!$E$3:$P$100, , MATCH(Z$1, Consolidado!$E$2:$P$2, 0))), "")} | AA29: =IFERROR( LET( hoja, LEFT(AA$1,3)&"R", fila, MATCH( RIGHT($A29, LEN($A29)-4), INDIRECT(hoja&"!$A:$A"), 0 ), columna, MATCH( "Totales", INDIRECT(hoja&"!$6:$6"), 0 ), valor, INDEX( INDIRECT(hoja&"!$A:$ZZ"), fila, columna ), IF(valor="-", "", valor) ), "") | AB29: =Z29-AA29 -> 0 | AC29: {=IFERROR(SUMIF(Consolidado!$C$3:$C63, $A29, INDEX(Consolidado!$E$3:$P$100, , MATCH(AC$1, Consolidado!$E$2:$P$2, 0))), "")} | AD29: =IFERROR( LET( hoja, LEFT(AD$1,3)&"R", fila, MATCH( RIGHT($A29, LEN($A29)-4), INDIRECT(hoja&"!$A:$A"), 0 ), columna, MATCH( "Totales", INDIRECT(hoja&"!$6:$6"), 0 ), valor, INDEX( INDIRECT(hoja&"!$A:$ZZ"), fila, columna ), IF(valor="-", "", valor) ), "") | AE29: =AC29-AD29 -> 0 | AF29: {=IFERROR(SUMIF(Consolidado!$C$3:$C63, $A29, INDEX(Consolidado!$E$3:$P$100, , MATCH(AF$1, Consolidado!$E$2:$P$2, 0))), "")} | AG29: =IFERROR( LET( hoja, LEFT(AG$1,3)&"R", fila, MATCH( RIGHT($A29, LEN($A29)-4), INDIRECT(hoja&"!$A:$A"), 0 ), columna, MATCH( "Totales", INDIRECT(hoja&"!$6:$6"), 0 ), valor, INDEX( INDIRECT(hoja&"!$A:$ZZ"), fila, columna ), IF(valor="-", "", valor) ), "") | AH29: =AF29-AG29 -> 0 | AI29: {=IFERROR(SUMIF(Consolidado!$C$3:$C63, $A29, INDEX(Consolidado!$E$3:$P$100, , MATCH(AI$1, Consolidado!$E$2:$P$2, 0))), "")} | AJ29: =IFERROR( LET( hoja, LEFT(AJ$1,3)&"R", fila, MATCH( RIGHT($A29, LEN($A29)-4), INDIRECT(hoja&"!$A:$A"), 0 ), columna, MATCH( "Totales", INDIRECT(hoja&"!$6:$6"), 0 ), valor, INDEX( INDIRECT(hoja&"!$A:$ZZ"), fila, columna ), IF(valor="-", "", valor) ), "") | AK29: =AI29-AJ29 -> 0 | AL29: {=IFERROR(SUMIF(Consolidado!$C$3:$C63, $A29, INDEX(Consolidado!$E$3:$P$100, , MATCH(AL$1, Consolidado!$E$2:$P$2, 0))), "")} | AM29: =IFERROR( LET( hoja, LEFT(AM$1,3)&"R", fila, MATCH( RIGHT($A29, LEN($A29)-4), INDIRECT(hoja&"!$A:$A"), 0 ), columna, MATCH( "Totales", INDIRECT(hoja&"!$6:$6"), 0 ), valor, INDEX( INDIRECT(hoja&"!$A:$ZZ"), fila, columna ), IF(valor="-", "", valor) ), "") | AN29: =AL29-AM29 -> 0
A30: =Menus!B23 -> B20 Asesoría y gestoría | B30: =SUM(IF(MONTH(TODAY())>1,E30,0), IF(MONTH(TODAY())>2,H30,0), IF(MONTH(TODAY())>3,K30,0), IF(MONTH(TODAY())>4,N30,0), IF(MONTH(TODAY())>5,Q30,0), IF(MONTH(TODAY())>6,T30,0), IF(MONTH(TODAY())>7,W30,0), IF(MONTH(TODAY())>8,Z30,0), IF(MONTH(TODAY())>9,AC30,0), IF(MONTH(TODAY())>10,AF30,0), IF(MONTH(TODAY())>11,AI30,0), IF(MONTH(TODAY())>12,AL30,0)) -> 0 | C30: =SUM(IF(MONTH(TODAY())>1,F30,0), IF(MONTH(TODAY())>2,I30,0), IF(MONTH(TODAY())>3,L30,0), IF(MONTH(TODAY())>4,O30,0), IF(MONTH(TODAY())>5,R30,0), IF(MONTH(TODAY())>6,U30,0), IF(MONTH(TODAY())>7,X30,0), IF(MONTH(TODAY())>8,AA30,0), IF(MONTH(TODAY())>9,AD30,0), IF(MONTH(TODAY())>10,AG30,0), IF(MONTH(TODAY())>11,AJ30,0), IF(MONTH(TODAY())>12,AM30,0)) -> 0 | D30: =B30-C30 -> 0 | E30: {=IFERROR(SUMIF(Consolidado!$C$3:$C63, $A30, INDEX(Consolidado!$E$3:$P$100, , MATCH(E$1, Consolidado!$E$2:$P$2, 0))), "")} | F30: =IFERROR( LET( hoja, LEFT(F$1,3)&"R", fila, MATCH( RIGHT($A30, LEN($A30)-4), INDIRECT(hoja&"!$A:$A"), 0 ), columna, MATCH( "Totales", INDIRECT(hoja&"!$6:$6"), 0 ), valor, INDEX( INDIRECT(hoja&"!$A:$ZZ"), fila, columna ), IF(valor="-", "", valor) ), "") | G30: =E30-F30 -> 0 | H30: {=IFERROR(SUMIF(Consolidado!$C$3:$C63, $A30, INDEX(Consolidado!$E$3:$P$100, , MATCH(H$1, Consolidado!$E$2:$P$2, 0))), "")} | I30: =IFERROR( LET( hoja, LEFT(I$1,3)&"R", fila, MATCH( RIGHT($A30, LEN($A30)-4), INDIRECT(hoja&"!$A:$A"), 0 ), columna, MATCH( "Totales", INDIRECT(hoja&"!$6:$6"), 0 ), valor, INDEX( INDIRECT(hoja&"!$A:$ZZ"), fila, columna ), IF(valor="-", "", valor) ), "") | J30: =H30-I30 -> 0 | K30: {=IFERROR(SUMIF(Consolidado!$C$3:$C63, $A30, INDEX(Consolidado!$E$3:$P$100, , MATCH(K$1, Consolidado!$E$2:$P$2, 0))), "")} | L30: =IFERROR( LET( hoja, LEFT(L$1,3)&"R", fila, MATCH( RIGHT($A30, LEN($A30)-4), INDIRECT(hoja&"!$A:$A"), 0 ), columna, MATCH( "Totales", INDIRECT(hoja&"!$6:$6"), 0 ), valor, INDEX( INDIRECT(hoja&"!$A:$ZZ"), fila, columna ), IF(valor="-", "", valor) ), "") | M30: =K30-L30 -> 0 | N30: {=IFERROR(SUMIF(Consolidado!$C$3:$C63, $A30, INDEX(Consolidado!$E$3:$P$100, , MATCH(N$1, Consolidado!$E$2:$P$2, 0))), "")} | O30: =IFERROR( LET( hoja, LEFT(O$1,3)&"R", fila, MATCH( RIGHT($A30, LEN($A30)-4), INDIRECT(hoja&"!$A:$A"), 0 ), columna, MATCH( "Totales", INDIRECT(hoja&"!$6:$6"), 0 ), valor, INDEX( INDIRECT(hoja&"!$A:$ZZ"), fila, columna ), IF(valor="-", "", valor) ), "") | P30: =N30-O30 -> 0 | Q30: {=IFERROR(SUMIF(Consolidado!$C$3:$C63, $A30, INDEX(Consolidado!$E$3:$P$100, , MATCH(Q$1, Consolidado!$E$2:$P$2, 0))), "")} | R30: =IFERROR( LET( hoja, LEFT(R$1,3)&"R", fila, MATCH( RIGHT($A30, LEN($A30)-4), INDIRECT(hoja&"!$A:$A"), 0 ), columna, MATCH( "Totales", INDIRECT(hoja&"!$6:$6"), 0 ), valor, INDEX( INDIRECT(hoja&"!$A:$ZZ"), fila, columna ), IF(valor="-", "", valor) ), "") | S30: =Q30-R30 -> 0 | T30: {=IFERROR(SUMIF(Consolidado!$C$3:$C63, $A30, INDEX(Consolidado!$E$3:$P$100, , MATCH(T$1, Consolidado!$E$2:$P$2, 0))), "")} | U30: =IFERROR( LET( hoja, LEFT(U$1,3)&"R", fila, MATCH( RIGHT($A30, LEN($A30)-4), INDIRECT(hoja&"!$A:$A"), 0 ), columna, MATCH( "Totales", INDIRECT(hoja&"!$6:$6"), 0 ), valor, INDEX( INDIRECT(hoja&"!$A:$ZZ"), fila, columna ), IF(valor="-", "", valor) ), "") | V30: =T30-U30 -> 0 | W30: {=IFERROR(SUMIF(Consolidado!$C$3:$C63, $A30, INDEX(Consolidado!$E$3:$P$100, , MATCH(W$1, Consolidado!$E$2:$P$2, 0))), "")} | X30: =IFERROR( LET( hoja, LEFT(X$1,3)&"R", fila, MATCH( RIGHT($A30, LEN($A30)-4), INDIRECT(hoja&"!$A:$A"), 0 ), columna, MATCH( "Totales", INDIRECT(hoja&"!$6:$6"), 0 ), valor, INDEX( INDIRECT(hoja&"!$A:$ZZ"), fila, columna ), IF(valor="-", "", valor) ), "") | Y30: =W30-X30 -> 0 | Z30: {=IFERROR(SUMIF(Consolidado!$C$3:$C63, $A30, INDEX(Consolidado!$E$3:$P$100, , MATCH(Z$1, Consolidado!$E$2:$P$2, 0))), "")} | AA30: =IFERROR( LET( hoja, LEFT(AA$1,3)&"R", fila, MATCH( RIGHT($A30, LEN($A30)-4), INDIRECT(hoja&"!$A:$A"), 0 ), columna, MATCH( "Totales", INDIRECT(hoja&"!$6:$6"), 0 ), valor, INDEX( INDIRECT(hoja&"!$A:$ZZ"), fila, columna ), IF(valor="-", "", valor) ), "") | AB30: =Z30-AA30 -> 0 | AC30: {=IFERROR(SUMIF(Consolidado!$C$3:$C63, $A30, INDEX(Consolidado!$E$3:$P$100, , MATCH(AC$1, Consolidado!$E$2:$P$2, 0))), "")} | AD30: =IFERROR( LET( hoja, LEFT(AD$1,3)&"R", fila, MATCH( RIGHT($A30, LEN($A30)-4), INDIRECT(hoja&"!$A:$A"), 0 ), columna, MATCH( "Totales", INDIRECT(hoja&"!$6:$6"), 0 ), valor, INDEX( INDIRECT(hoja&"!$A:$ZZ"), fila, columna ), IF(valor="-", "", valor) ), "") | AE30: =AC30-AD30 -> 0 | AF30: {=IFERROR(SUMIF(Consolidado!$C$3:$C63, $A30, INDEX(Consolidado!$E$3:$P$100, , MATCH(AF$1, Consolidado!$E$2:$P$2, 0))), "")} | AG30: =IFERROR( LET( hoja, LEFT(AG$1,3)&"R", fila, MATCH( RIGHT($A30, LEN($A30)-4), INDIRECT(hoja&"!$A:$A"), 0 ), columna, MATCH( "Totales", INDIRECT(hoja&"!$6:$6"), 0 ), valor, INDEX( INDIRECT(hoja&"!$A:$ZZ"), fila, columna ), IF(valor="-", "", valor) ), "") | AH30: =AF30-AG30 -> 0 | AI30: {=IFERROR(SUMIF(Consolidado!$C$3:$C63, $A30, INDEX(Consolidado!$E$3:$P$100, , MATCH(AI$1, Consolidado!$E$2:$P$2, 0))), "")} | AJ30: =IFERROR( LET( hoja, LEFT(AJ$1,3)&"R", fila, MATCH( RIGHT($A30, LEN($A30)-4), INDIRECT(hoja&"!$A:$A"), 0 ), columna, MATCH( "Totales", INDIRECT(hoja&"!$6:$6"), 0 ), valor, INDEX( INDIRECT(hoja&"!$A:$ZZ"), fila, columna ), IF(valor="-", "", valor) ), "") | AK30: =AI30-AJ30 -> 0 | AL30: {=IFERROR(SUMIF(Consolidado!$C$3:$C63, $A30, INDEX(Consolidado!$E$3:$P$100, , MATCH(AL$1, Consolidado!$E$2:$P$2, 0))), "")} | AM30: =IFERROR( LET( hoja, LEFT(AM$1,3)&"R", fila, MATCH( RIGHT($A30, LEN($A30)-4), INDIRECT(hoja&"!$A:$A"), 0 ), columna, MATCH( "Totales", INDIRECT(hoja&"!$6:$6"), 0 ), valor, INDEX( INDIRECT(hoja&"!$A:$ZZ"), fila, columna ), IF(valor="-", "", valor) ), "") | AN30: =AL30-AM30 -> 0
A31: =Menus!B24 -> B21 Equipo de operación | B31: =SUM(IF(MONTH(TODAY())>1,E31,0), IF(MONTH(TODAY())>2,H31,0), IF(MONTH(TODAY())>3,K31,0), IF(MONTH(TODAY())>4,N31,0), IF(MONTH(TODAY())>5,Q31,0), IF(MONTH(TODAY())>6,T31,0), IF(MONTH(TODAY())>7,W31,0), IF(MONTH(TODAY())>8,Z31,0), IF(MONTH(TODAY())>9,AC31,0), IF(MONTH(TODAY())>10,AF31,0), IF(MONTH(TODAY())>11,AI31,0), IF(MONTH(TODAY())>12,AL31,0)) -> 0 | C31: =SUM(IF(MONTH(TODAY())>1,F31,0), IF(MONTH(TODAY())>2,I31,0), IF(MONTH(TODAY())>3,L31,0), IF(MONTH(TODAY())>4,O31,0), IF(MONTH(TODAY())>5,R31,0), IF(MONTH(TODAY())>6,U31,0), IF(MONTH(TODAY())>7,X31,0), IF(MONTH(TODAY())>8,AA31,0), IF(MONTH(TODAY())>9,AD31,0), IF(MONTH(TODAY())>10,AG31,0), IF(MONTH(TODAY())>11,AJ31,0), IF(MONTH(TODAY())>12,AM31,0)) -> 0 | D31: =B31-C31 -> 0 | E31: {=IFERROR(SUMIF(Consolidado!$C$3:$C63, $A31, INDEX(Consolidado!$E$3:$P$100, , MATCH(E$1, Consolidado!$E$2:$P$2, 0))), "")} | F31: =IFERROR( LET( hoja, LEFT(F$1,3)&"R", fila, MATCH( RIGHT($A31, LEN($A31)-4), INDIRECT(hoja&"!$A:$A"), 0 ), columna, MATCH( "Totales", INDIRECT(hoja&"!$6:$6"), 0 ), valor, INDEX( INDIRECT(hoja&"!$A:$ZZ"), fila, columna ), IF(valor="-", "", valor) ), "") | G31: =E31-F31 -> 0 | H31: {=IFERROR(SUMIF(Consolidado!$C$3:$C63, $A31, INDEX(Consolidado!$E$3:$P$100, , MATCH(H$1, Consolidado!$E$2:$P$2, 0))), "")} | I31: =IFERROR( LET( hoja, LEFT(I$1,3)&"R", fila, MATCH( RIGHT($A31, LEN($A31)-4), INDIRECT(hoja&"!$A:$A"), 0 ), columna, MATCH( "Totales", INDIRECT(hoja&"!$6:$6"), 0 ), valor, INDEX( INDIRECT(hoja&"!$A:$ZZ"), fila, columna ), IF(valor="-", "", valor) ), "") | J31: =H31-I31 -> 0 | K31: {=IFERROR(SUMIF(Consolidado!$C$3:$C63, $A31, INDEX(Consolidado!$E$3:$P$100, , MATCH(K$1, Consolidado!$E$2:$P$2, 0))), "")} | L31: =IFERROR( LET( hoja, LEFT(L$1,3)&"R", fila, MATCH( RIGHT($A31, LEN($A31)-4), INDIRECT(hoja&"!$A:$A"), 0 ), columna, MATCH( "Totales", INDIRECT(hoja&"!$6:$6"), 0 ), valor, INDEX( INDIRECT(hoja&"!$A:$ZZ"), fila, columna ), IF(valor="-", "", valor) ), "") | M31: =K31-L31 -> 0 | N31: {=IFERROR(SUMIF(Consolidado!$C$3:$C63, $A31, INDEX(Consolidado!$E$3:$P$100, , MATCH(N$1, Consolidado!$E$2:$P$2, 0))), "")} | O31: =IFERROR( LET( hoja, LEFT(O$1,3)&"R", fila, MATCH( RIGHT($A31, LEN($A31)-4), INDIRECT(hoja&"!$A:$A"), 0 ), columna, MATCH( "Totales", INDIRECT(hoja&"!$6:$6"), 0 ), valor, INDEX( INDIRECT(hoja&"!$A:$ZZ"), fila, columna ), IF(valor="-", "", valor) ), "") | P31: =N31-O31 -> 0 | Q31: {=IFERROR(SUMIF(Consolidado!$C$3:$C63, $A31, INDEX(Consolidado!$E$3:$P$100, , MATCH(Q$1, Consolidado!$E$2:$P$2, 0))), "")} | R31: =IFERROR( LET( hoja, LEFT(R$1,3)&"R", fila, MATCH( RIGHT($A31, LEN($A31)-4), INDIRECT(hoja&"!$A:$A"), 0 ), columna, MATCH( "Totales", INDIRECT(hoja&"!$6:$6"), 0 ), valor, INDEX( INDIRECT(hoja&"!$A:$ZZ"), fila, columna ), IF(valor="-", "", valor) ), "") | S31: =Q31-R31 -> 0 | T31: {=IFERROR(SUMIF(Consolidado!$C$3:$C63, $A31, INDEX(Consolidado!$E$3:$P$100, , MATCH(T$1, Consolidado!$E$2:$P$2, 0))), "")} | U31: =IFERROR( LET( hoja, LEFT(U$1,3)&"R", fila, MATCH( RIGHT($A31, LEN($A31)-4), INDIRECT(hoja&"!$A:$A"), 0 ), columna, MATCH( "Totales", INDIRECT(hoja&"!$6:$6"), 0 ), valor, INDEX( INDIRECT(hoja&"!$A:$ZZ"), fila, columna ), IF(valor="-", "", valor) ), "") | V31: =T31-U31 -> 0 | W31: {=IFERROR(SUMIF(Consolidado!$C$3:$C63, $A31, INDEX(Consolidado!$E$3:$P$100, , MATCH(W$1, Consolidado!$E$2:$P$2, 0))), "")} | X31: =IFERROR( LET( hoja, LEFT(X$1,3)&"R", fila, MATCH( RIGHT($A31, LEN($A31)-4), INDIRECT(hoja&"!$A:$A"), 0 ), columna, MATCH( "Totales", INDIRECT(hoja&"!$6:$6"), 0 ), valor, INDEX( INDIRECT(hoja&"!$A:$ZZ"), fila, columna ), IF(valor="-", "", valor) ), "") | Y31: =W31-X31 -> 0 | Z31: {=IFERROR(SUMIF(Consolidado!$C$3:$C63, $A31, INDEX(Consolidado!$E$3:$P$100, , MATCH(Z$1, Consolidado!$E$2:$P$2, 0))), "")} | AA31: =IFERROR( LET( hoja, LEFT(AA$1,3)&"R", fila, MATCH( RIGHT($A31, LEN($A31)-4), INDIRECT(hoja&"!$A:$A"), 0 ), columna, MATCH( "Totales", INDIRECT(hoja&"!$6:$6"), 0 ), valor, INDEX( INDIRECT(hoja&"!$A:$ZZ"), fila, columna ), IF(valor="-", "", valor) ), "") | AB31: =Z31-AA31 -> 0 | AC31: {=IFERROR(SUMIF(Consolidado!$C$3:$C63, $A31, INDEX(Consolidado!$E$3:$P$100, , MATCH(AC$1, Consolidado!$E$2:$P$2, 0))), "")} | AD31: =IFERROR( LET( hoja, LEFT(AD$1,3)&"R", fila, MATCH( RIGHT($A31, LEN($A31)-4), INDIRECT(hoja&"!$A:$A"), 0 ), columna, MATCH( "Totales", INDIRECT(hoja&"!$6:$6"), 0 ), valor, INDEX( INDIRECT(hoja&"!$A:$ZZ"), fila, columna ), IF(valor="-", "", valor) ), "") | AE31: =AC31-AD31 -> 0 | AF31: {=IFERROR(SUMIF(Consolidado!$C$3:$C63, $A31, INDEX(Consolidado!$E$3:$P$100, , MATCH(AF$1, Consolidado!$E$2:$P$2, 0))), "")} | AG31: =IFERROR( LET( hoja, LEFT(AG$1,3)&"R", fila, MATCH( RIGHT($A31, LEN($A31)-4), INDIRECT(hoja&"!$A:$A"), 0 ), columna, MATCH( "Totales", INDIRECT(hoja&"!$6:$6"), 0 ), valor, INDEX( INDIRECT(hoja&"!$A:$ZZ"), fila, columna ), IF(valor="-", "", valor) ), "") | AH31: =AF31-AG31 -> 0 | AI31: {=IFERROR(SUMIF(Consolidado!$C$3:$C63, $A31, INDEX(Consolidado!$E$3:$P$100, , MATCH(AI$1, Consolidado!$E$2:$P$2, 0))), "")} | AJ31: =IFERROR( LET( hoja, LEFT(AJ$1,3)&"R", fila, MATCH( RIGHT($A31, LEN($A31)-4), INDIRECT(hoja&"!$A:$A"), 0 ), columna, MATCH( "Totales", INDIRECT(hoja&"!$6:$6"), 0 ), valor, INDEX( INDIRECT(hoja&"!$A:$ZZ"), fila, columna ), IF(valor="-", "", valor) ), "") | AK31: =AI31-AJ31 -> 0 | AL31: {=IFERROR(SUMIF(Consolidado!$C$3:$C63, $A31, INDEX(Consolidado!$E$3:$P$100, , MATCH(AL$1, Consolidado!$E$2:$P$2, 0))), "")} | AM31: =IFERROR( LET( hoja, LEFT(AM$1,3)&"R", fila, MATCH( RIGHT($A31, LEN($A31)-4), INDIRECT(hoja&"!$A:$A"), 0 ), columna, MATCH( "Totales", INDIRECT(hoja&"!$6:$6"), 0 ), valor, INDEX( INDIRECT(hoja&"!$A:$ZZ"), fila, columna ), IF(valor="-", "", valor) ), "") | AN31: =AL31-AM31 -> 0
A32: =Menus!B25 -> B22 Equipo de capacitación | B32: =SUM(IF(MONTH(TODAY())>1,E32,0), IF(MONTH(TODAY())>2,H32,0), IF(MONTH(TODAY())>3,K32,0), IF(MONTH(TODAY())>4,N32,0), IF(MONTH(TODAY())>5,Q32,0), IF(MONTH(TODAY())>6,T32,0), IF(MONTH(TODAY())>7,W32,0), IF(MONTH(TODAY())>8,Z32,0), IF(MONTH(TODAY())>9,AC32,0), IF(MONTH(TODAY())>10,AF32,0), IF(MONTH(TODAY())>11,AI32,0), IF(MONTH(TODAY())>12,AL32,0)) -> 0 | C32: =SUM(IF(MONTH(TODAY())>1,F32,0), IF(MONTH(TODAY())>2,I32,0), IF(MONTH(TODAY())>3,L32,0), IF(MONTH(TODAY())>4,O32,0), IF(MONTH(TODAY())>5,R32,0), IF(MONTH(TODAY())>6,U32,0), IF(MONTH(TODAY())>7,X32,0), IF(MONTH(TODAY())>8,AA32,0), IF(MONTH(TODAY())>9,AD32,0), IF(MONTH(TODAY())>10,AG32,0), IF(MONTH(TODAY())>11,AJ32,0), IF(MONTH(TODAY())>12,AM32,0)) -> 0 | D32: =B32-C32 -> 0 | E32: {=IFERROR(SUMIF(Consolidado!$C$3:$C63, $A32, INDEX(Consolidado!$E$3:$P$100, , MATCH(E$1, Consolidado!$E$2:$P$2, 0))), "")} | F32: =IFERROR( LET( hoja, LEFT(F$1,3)&"R", fila, MATCH( RIGHT($A32, LEN($A32)-4), INDIRECT(hoja&"!$A:$A"), 0 ), columna, MATCH( "Totales", INDIRECT(hoja&"!$6:$6"), 0 ), valor, INDEX( INDIRECT(hoja&"!$A:$ZZ"), fila, columna ), IF(valor="-", "", valor) ), "") | G32: =E32-F32 -> 0 | H32: {=IFERROR(SUMIF(Consolidado!$C$3:$C63, $A32, INDEX(Consolidado!$E$3:$P$100, , MATCH(H$1, Consolidado!$E$2:$P$2, 0))), "")} | I32: =IFERROR( LET( hoja, LEFT(I$1,3)&"R", fila, MATCH( RIGHT($A32, LEN($A32)-4), INDIRECT(hoja&"!$A:$A"), 0 ), columna, MATCH( "Totales", INDIRECT(hoja&"!$6:$6"), 0 ), valor, INDEX( INDIRECT(hoja&"!$A:$ZZ"), fila, columna ), IF(valor="-", "", valor) ), "") | J32: =H32-I32 -> 0 | K32: {=IFERROR(SUMIF(Consolidado!$C$3:$C63, $A32, INDEX(Consolidado!$E$3:$P$100, , MATCH(K$1, Consolidado!$E$2:$P$2, 0))), "")} | L32: =IFERROR( LET( hoja, LEFT(L$1,3)&"R", fila, MATCH( RIGHT($A32, LEN($A32)-4), INDIRECT(hoja&"!$A:$A"), 0 ), columna, MATCH( "Totales", INDIRECT(hoja&"!$6:$6"), 0 ), valor, INDEX( INDIRECT(hoja&"!$A:$ZZ"), fila, columna ), IF(valor="-", "", valor) ), "") | M32: =K32-L32 -> 0 | N32: {=IFERROR(SUMIF(Consolidado!$C$3:$C63, $A32, INDEX(Consolidado!$E$3:$P$100, , MATCH(N$1, Consolidado!$E$2:$P$2, 0))), "")} | O32: =IFERROR( LET( hoja, LEFT(O$1,3)&"R", fila, MATCH( RIGHT($A32, LEN($A32)-4), INDIRECT(hoja&"!$A:$A"), 0 ), columna, MATCH( "Totales", INDIRECT(hoja&"!$6:$6"), 0 ), valor, INDEX( INDIRECT(hoja&"!$A:$ZZ"), fila, columna ), IF(valor="-", "", valor) ), "") | P32: =N32-O32 -> 0 | Q32: {=IFERROR(SUMIF(Consolidado!$C$3:$C63, $A32, INDEX(Consolidado!$E$3:$P$100, , MATCH(Q$1, Consolidado!$E$2:$P$2, 0))), "")} | R32: =IFERROR( LET( hoja, LEFT(R$1,3)&"R", fila, MATCH( RIGHT($A32, LEN($A32)-4), INDIRECT(hoja&"!$A:$A"), 0 ), columna, MATCH( "Totales", INDIRECT(hoja&"!$6:$6"), 0 ), valor, INDEX( INDIRECT(hoja&"!$A:$ZZ"), fila, columna ), IF(valor="-", "", valor) ), "") | S32: =Q32-R32 -> 0 | T32: {=IFERROR(SUMIF(Consolidado!$C$3:$C63, $A32, INDEX(Consolidado!$E$3:$P$100, , MATCH(T$1, Consolidado!$E$2:$P$2, 0))), "")} | U32: =IFERROR( LET( hoja, LEFT(U$1,3)&"R", fila, MATCH( RIGHT($A32, LEN($A32)-4), INDIRECT(hoja&"!$A:$A"), 0 ), columna, MATCH( "Totales", INDIRECT(hoja&"!$6:$6"), 0 ), valor, INDEX( INDIRECT(hoja&"!$A:$ZZ"), fila, columna ), IF(valor="-", "", valor) ), "") | V32: =T32-U32 -> 0 | W32: {=IFERROR(SUMIF(Consolidado!$C$3:$C63, $A32, INDEX(Consolidado!$E$3:$P$100, , MATCH(W$1, Consolidado!$E$2:$P$2, 0))), "")} | X32: =IFERROR( LET( hoja, LEFT(X$1,3)&"R", fila, MATCH( RIGHT($A32, LEN($A32)-4), INDIRECT(hoja&"!$A:$A"), 0 ), columna, MATCH( "Totales", INDIRECT(hoja&"!$6:$6"), 0 ), valor, INDEX( INDIRECT(hoja&"!$A:$ZZ"), fila, columna ), IF(valor="-", "", valor) ), "") | Y32: =W32-X32 -> 0 | Z32: {=IFERROR(SUMIF(Consolidado!$C$3:$C63, $A32, INDEX(Consolidado!$E$3:$P$100, , MATCH(Z$1, Consolidado!$E$2:$P$2, 0))), "")} | AA32: =IFERROR( LET( hoja, LEFT(AA$1,3)&"R", fila, MATCH( RIGHT($A32, LEN($A32)-4), INDIRECT(hoja&"!$A:$A"), 0 ), columna, MATCH( "Totales", INDIRECT(hoja&"!$6:$6"), 0 ), valor, INDEX( INDIRECT(hoja&"!$A:$ZZ"), fila, columna ), IF(valor="-", "", valor) ), "") | AB32: =Z32-AA32 -> 0 | AC32: {=IFERROR(SUMIF(Consolidado!$C$3:$C63, $A32, INDEX(Consolidado!$E$3:$P$100, , MATCH(AC$1, Consolidado!$E$2:$P$2, 0))), "")} | AD32: =IFERROR( LET( hoja, LEFT(AD$1,3)&"R", fila, MATCH( RIGHT($A32, LEN($A32)-4), INDIRECT(hoja&"!$A:$A"), 0 ), columna, MATCH( "Totales", INDIRECT(hoja&"!$6:$6"), 0 ), valor, INDEX( INDIRECT(hoja&"!$A:$ZZ"), fila, columna ), IF(valor="-", "", valor) ), "") | AE32: =AC32-AD32 -> 0 | AF32: {=IFERROR(SUMIF(Consolidado!$C$3:$C63, $A32, INDEX(Consolidado!$E$3:$P$100, , MATCH(AF$1, Consolidado!$E$2:$P$2, 0))), "")} | AG32: =IFERROR( LET( hoja, LEFT(AG$1,3)&"R", fila, MATCH( RIGHT($A32, LEN($A32)-4), INDIRECT(hoja&"!$A:$A"), 0 ), columna, MATCH( "Totales", INDIRECT(hoja&"!$6:$6"), 0 ), valor, INDEX( INDIRECT(hoja&"!$A:$ZZ"), fila, columna ), IF(valor="-", "", valor) ), "") | AH32: =AF32-AG32 -> 0 | AI32: {=IFERROR(SUMIF(Consolidado!$C$3:$C63, $A32, INDEX(Consolidado!$E$3:$P$100, , MATCH(AI$1, Consolidado!$E$2:$P$2, 0))), "")} | AJ32: =IFERROR( LET( hoja, LEFT(AJ$1,3)&"R", fila, MATCH( RIGHT($A32, LEN($A32)-4), INDIRECT(hoja&"!$A:$A"), 0 ), columna, MATCH( "Totales", INDIRECT(hoja&"!$6:$6"), 0 ), valor, INDEX( INDIRECT(hoja&"!$A:$ZZ"), fila, columna ), IF(valor="-", "", valor) ), "") | AK32: =AI32-AJ32 -> 0 | AL32: {=IFERROR(SUMIF(Consolidado!$C$3:$C63, $A32, INDEX(Consolidado!$E$3:$P$100, , MATCH(AL$1, Consolidado!$E$2:$P$2, 0))), "")} | AM32: =IFERROR( LET( hoja, LEFT(AM$1,3)&"R", fila, MATCH( RIGHT($A32, LEN($A32)-4), INDIRECT(hoja&"!$A:$A"), 0 ), columna, MATCH( "Totales", INDIRECT(hoja&"!$6:$6"), 0 ), valor, INDEX( INDIRECT(hoja&"!$A:$ZZ"), fila, columna ), IF(valor="-", "", valor) ), "") | AN32: =AL32-AM32 -> 0
A33: =Menus!B26 -> B23 Equipo Rondinero | B33: =SUM(IF(MONTH(TODAY())>1,E33,0), IF(MONTH(TODAY())>2,H33,0), IF(MONTH(TODAY())>3,K33,0), IF(MONTH(TODAY())>4,N33,0), IF(MONTH(TODAY())>5,Q33,0), IF(MONTH(TODAY())>6,T33,0), IF(MONTH(TODAY())>7,W33,0), IF(MONTH(TODAY())>8,Z33,0), IF(MONTH(TODAY())>9,AC33,0), IF(MONTH(TODAY())>10,AF33,0), IF(MONTH(TODAY())>11,AI33,0), IF(MONTH(TODAY())>12,AL33,0)) -> 0 | C33: =SUM(IF(MONTH(TODAY())>1,F33,0), IF(MONTH(TODAY())>2,I33,0), IF(MONTH(TODAY())>3,L33,0), IF(MONTH(TODAY())>4,O33,0), IF(MONTH(TODAY())>5,R33,0), IF(MONTH(TODAY())>6,U33,0), IF(MONTH(TODAY())>7,X33,0), IF(MONTH(TODAY())>8,AA33,0), IF(MONTH(TODAY())>9,AD33,0), IF(MONTH(TODAY())>10,AG33,0), IF(MONTH(TODAY())>11,AJ33,0), IF(MONTH(TODAY())>12,AM33,0)) -> 0 | D33: =B33-C33 -> 0 | E33: {=IFERROR(SUMIF(Consolidado!$C$3:$C63, $A33, INDEX(Consolidado!$E$3:$P$100, , MATCH(E$1, Consolidado!$E$2:$P$2, 0))), "")} | F33: =IFERROR( LET( hoja, LEFT(F$1,3)&"R", fila, MATCH( RIGHT($A33, LEN($A33)-4), INDIRECT(hoja&"!$A:$A"), 0 ), columna, MATCH( "Totales", INDIRECT(hoja&"!$6:$6"), 0 ), valor, INDEX( INDIRECT(hoja&"!$A:$ZZ"), fila, columna ), IF(valor="-", "", valor) ), "") | G33: =E33-F33 -> 0 | H33: {=IFERROR(SUMIF(Consolidado!$C$3:$C63, $A33, INDEX(Consolidado!$E$3:$P$100, , MATCH(H$1, Consolidado!$E$2:$P$2, 0))), "")} | I33: =IFERROR( LET( hoja, LEFT(I$1,3)&"R", fila, MATCH( RIGHT($A33, LEN($A33)-4), INDIRECT(hoja&"!$A:$A"), 0 ), columna, MATCH( "Totales", INDIRECT(hoja&"!$6:$6"), 0 ), valor, INDEX( INDIRECT(hoja&"!$A:$ZZ"), fila, columna ), IF(valor="-", "", valor) ), "") | J33: =H33-I33 -> 0 | K33: {=IFERROR(SUMIF(Consolidado!$C$3:$C63, $A33, INDEX(Consolidado!$E$3:$P$100, , MATCH(K$1, Consolidado!$E$2:$P$2, 0))), "")} | L33: =IFERROR( LET( hoja, LEFT(L$1,3)&"R", fila, MATCH( RIGHT($A33, LEN($A33)-4), INDIRECT(hoja&"!$A:$A"), 0 ), columna, MATCH( "Totales", INDIRECT(hoja&"!$6:$6"), 0 ), valor, INDEX( INDIRECT(hoja&"!$A:$ZZ"), fila, columna ), IF(valor="-", "", valor) ), "") | M33: =K33-L33 -> 0 | N33: {=IFERROR(SUMIF(Consolidado!$C$3:$C63, $A33, INDEX(Consolidado!$E$3:$P$100, , MATCH(N$1, Consolidado!$E$2:$P$2, 0))), "")} | O33: =IFERROR( LET( hoja, LEFT(O$1,3)&"R", fila, MATCH( RIGHT($A33, LEN($A33)-4), INDIRECT(hoja&"!$A:$A"), 0 ), columna, MATCH( "Totales", INDIRECT(hoja&"!$6:$6"), 0 ), valor, INDEX( INDIRECT(hoja&"!$A:$ZZ"), fila, columna ), IF(valor="-", "", valor) ), "") | P33: =N33-O33 -> 0 | Q33: {=IFERROR(SUMIF(Consolidado!$C$3:$C63, $A33, INDEX(Consolidado!$E$3:$P$100, , MATCH(Q$1, Consolidado!$E$2:$P$2, 0))), "")} | R33: =IFERROR( LET( hoja, LEFT(R$1,3)&"R", fila, MATCH( RIGHT($A33, LEN($A33)-4), INDIRECT(hoja&"!$A:$A"), 0 ), columna, MATCH( "Totales", INDIRECT(hoja&"!$6:$6"), 0 ), valor, INDEX( INDIRECT(hoja&"!$A:$ZZ"), fila, columna ), IF(valor="-", "", valor) ), "") | S33: =Q33-R33 -> 0 | T33: {=IFERROR(SUMIF(Consolidado!$C$3:$C63, $A33, INDEX(Consolidado!$E$3:$P$100, , MATCH(T$1, Consolidado!$E$2:$P$2, 0))), "")} | U33: =IFERROR( LET( hoja, LEFT(U$1,3)&"R", fila, MATCH( RIGHT($A33, LEN($A33)-4), INDIRECT(hoja&"!$A:$A"), 0 ), columna, MATCH( "Totales", INDIRECT(hoja&"!$6:$6"), 0 ), valor, INDEX( INDIRECT(hoja&"!$A:$ZZ"), fila, columna ), IF(valor="-", "", valor) ), "") | V33: =T33-U33 -> 0 | W33: {=IFERROR(SUMIF(Consolidado!$C$3:$C63, $A33, INDEX(Consolidado!$E$3:$P$100, , MATCH(W$1, Consolidado!$E$2:$P$2, 0))), "")} | X33: =IFERROR( LET( hoja, LEFT(X$1,3)&"R", fila, MATCH( RIGHT($A33, LEN($A33)-4), INDIRECT(hoja&"!$A:$A"), 0 ), columna, MATCH( "Totales", INDIRECT(hoja&"!$6:$6"), 0 ), valor, INDEX( INDIRECT(hoja&"!$A:$ZZ"), fila, columna ), IF(valor="-", "", valor) ), "") | Y33: =W33-X33 -> 0 | Z33: {=IFERROR(SUMIF(Consolidado!$C$3:$C63, $A33, INDEX(Consolidado!$E$3:$P$100, , MATCH(Z$1, Consolidado!$E$2:$P$2, 0))), "")} | AA33: =IFERROR( LET( hoja, LEFT(AA$1,3)&"R", fila, MATCH( RIGHT($A33, LEN($A33)-4), INDIRECT(hoja&"!$A:$A"), 0 ), columna, MATCH( "Totales", INDIRECT(hoja&"!$6:$6"), 0 ), valor, INDEX( INDIRECT(hoja&"!$A:$ZZ"), fila, columna ), IF(valor="-", "", valor) ), "") | AB33: =Z33-AA33 -> 0 | AC33: {=IFERROR(SUMIF(Consolidado!$C$3:$C63, $A33, INDEX(Consolidado!$E$3:$P$100, , MATCH(AC$1, Consolidado!$E$2:$P$2, 0))), "")} | AD33: =IFERROR( LET( hoja, LEFT(AD$1,3)&"R", fila, MATCH( RIGHT($A33, LEN($A33)-4), INDIRECT(hoja&"!$A:$A"), 0 ), columna, MATCH( "Totales", INDIRECT(hoja&"!$6:$6"), 0 ), valor, INDEX( INDIRECT(hoja&"!$A:$ZZ"), fila, columna ), IF(valor="-", "", valor) ), "") | AE33: =AC33-AD33 -> 0 | AF33: {=IFERROR(SUMIF(Consolidado!$C$3:$C63, $A33, INDEX(Consolidado!$E$3:$P$100, , MATCH(AF$1, Consolidado!$E$2:$P$2, 0))), "")} | AG33: =IFERROR( LET( hoja, LEFT(AG$1,3)&"R", fila, MATCH( RIGHT($A33, LEN($A33)-4), INDIRECT(hoja&"!$A:$A"), 0 ), columna, MATCH( "Totales", INDIRECT(hoja&"!$6:$6"), 0 ), valor, INDEX( INDIRECT(hoja&"!$A:$ZZ"), fila, columna ), IF(valor="-", "", valor) ), "") | AH33: =AF33-AG33 -> 0 | AI33: {=IFERROR(SUMIF(Consolidado!$C$3:$C63, $A33, INDEX(Consolidado!$E$3:$P$100, , MATCH(AI$1, Consolidado!$E$2:$P$2, 0))), "")} | AJ33: =IFERROR( LET( hoja, LEFT(AJ$1,3)&"R", fila, MATCH( RIGHT($A33, LEN($A33)-4), INDIRECT(hoja&"!$A:$A"), 0 ), columna, MATCH( "Totales", INDIRECT(hoja&"!$6:$6"), 0 ), valor, INDEX( INDIRECT(hoja&"!$A:$ZZ"), fila, columna ), IF(valor="-", "", valor) ), "") | AK33: =AI33-AJ33 -> 0 | AL33: {=IFERROR(SUMIF(Consolidado!$C$3:$C63, $A33, INDEX(Consolidado!$E$3:$P$100, , MATCH(AL$1, Consolidado!$E$2:$P$2, 0))), "")} | AM33: =IFERROR( LET( hoja, LEFT(AM$1,3)&"R", fila, MATCH( RIGHT($A33, LEN($A33)-4), INDIRECT(hoja&"!$A:$A"), 0 ), columna, MATCH( "Totales", INDIRECT(hoja&"!$6:$6"), 0 ), valor, INDEX( INDIRECT(hoja&"!$A:$ZZ"), fila, columna ), IF(valor="-", "", valor) ), "") | AN33: =AL33-AM33 -> 0
A34: =Menus!B27 -> B24 Equipo de seguridad | B34: =SUM(IF(MONTH(TODAY())>1,E34,0), IF(MONTH(TODAY())>2,H34,0), IF(MONTH(TODAY())>3,K34,0), IF(MONTH(TODAY())>4,N34,0), IF(MONTH(TODAY())>5,Q34,0), IF(MONTH(TODAY())>6,T34,0), IF(MONTH(TODAY())>7,W34,0), IF(MONTH(TODAY())>8,Z34,0), IF(MONTH(TODAY())>9,AC34,0), IF(MONTH(TODAY())>10,AF34,0), IF(MONTH(TODAY())>11,AI34,0), IF(MONTH(TODAY())>12,AL34,0)) -> 0 | C34: =SUM(IF(MONTH(TODAY())>1,F34,0), IF(MONTH(TODAY())>2,I34,0), IF(MONTH(TODAY())>3,L34,0), IF(MONTH(TODAY())>4,O34,0), IF(MONTH(TODAY())>5,R34,0), IF(MONTH(TODAY())>6,U34,0), IF(MONTH(TODAY())>7,X34,0), IF(MONTH(TODAY())>8,AA34,0), IF(MONTH(TODAY())>9,AD34,0), IF(MONTH(TODAY())>10,AG34,0), IF(MONTH(TODAY())>11,AJ34,0), IF(MONTH(TODAY())>12,AM34,0)) -> 0 | D34: =B34-C34 -> 0 | E34: {=IFERROR(SUMIF(Consolidado!$C$3:$C63, $A34, INDEX(Consolidado!$E$3:$P$100, , MATCH(E$1, Consolidado!$E$2:$P$2, 0))), "")} | F34: =IFERROR( LET( hoja, LEFT(F$1,3)&"R", fila, MATCH( RIGHT($A34, LEN($A34)-4), INDIRECT(hoja&"!$A:$A"), 0 ), columna, MATCH( "Totales", INDIRECT(hoja&"!$6:$6"), 0 ), valor, INDEX( INDIRECT(hoja&"!$A:$ZZ"), fila, columna ), IF(valor="-", "", valor) ), "") | G34: =E34-F34 -> 0 | H34: {=IFERROR(SUMIF(Consolidado!$C$3:$C63, $A34, INDEX(Consolidado!$E$3:$P$100, , MATCH(H$1, Consolidado!$E$2:$P$2, 0))), "")} | I34: =IFERROR( LET( hoja, LEFT(I$1,3)&"R", fila, MATCH( RIGHT($A34, LEN($A34)-4), INDIRECT(hoja&"!$A:$A"), 0 ), columna, MATCH( "Totales", INDIRECT(hoja&"!$6:$6"), 0 ), valor, INDEX( INDIRECT(hoja&"!$A:$ZZ"), fila, columna ), IF(valor="-", "", valor) ), "") | J34: =H34-I34 -> 0 | K34: {=IFERROR(SUMIF(Consolidado!$C$3:$C63, $A34, INDEX(Consolidado!$E$3:$P$100, , MATCH(K$1, Consolidado!$E$2:$P$2, 0))), "")} | L34: =IFERROR( LET( hoja, LEFT(L$1,3)&"R", fila, MATCH( RIGHT($A34, LEN($A34)-4), INDIRECT(hoja&"!$A:$A"), 0 ), columna, MATCH( "Totales", INDIRECT(hoja&"!$6:$6"), 0 ), valor, INDEX( INDIRECT(hoja&"!$A:$ZZ"), fila, columna ), IF(valor="-", "", valor) ), "") | M34: =K34-L34 -> 0 | N34: {=IFERROR(SUMIF(Consolidado!$C$3:$C63, $A34, INDEX(Consolidado!$E$3:$P$100, , MATCH(N$1, Consolidado!$E$2:$P$2, 0))), "")} | O34: =IFERROR( LET( hoja, LEFT(O$1,3)&"R", fila, MATCH( RIGHT($A34, LEN($A34)-4), INDIRECT(hoja&"!$A:$A"), 0 ), columna, MATCH( "Totales", INDIRECT(hoja&"!$6:$6"), 0 ), valor, INDEX( INDIRECT(hoja&"!$A:$ZZ"), fila, columna ), IF(valor="-", "", valor) ), "") | P34: =N34-O34 -> 0 | Q34: {=IFERROR(SUMIF(Consolidado!$C$3:$C63, $A34, INDEX(Consolidado!$E$3:$P$100, , MATCH(Q$1, Consolidado!$E$2:$P$2, 0))), "")} | R34: =IFERROR( LET( hoja, LEFT(R$1,3)&"R", fila, MATCH( RIGHT($A34, LEN($A34)-4), INDIRECT(hoja&"!$A:$A"), 0 ), columna, MATCH( "Totales", INDIRECT(hoja&"!$6:$6"), 0 ), valor, INDEX( INDIRECT(hoja&"!$A:$ZZ"), fila, columna ), IF(valor="-", "", valor) ), "") | S34: =Q34-R34 -> 0 | T34: {=IFERROR(SUMIF(Consolidado!$C$3:$C63, $A34, INDEX(Consolidado!$E$3:$P$100, , MATCH(T$1, Consolidado!$E$2:$P$2, 0))), "")} | U34: =IFERROR( LET( hoja, LEFT(U$1,3)&"R", fila, MATCH( RIGHT($A34, LEN($A34)-4), INDIRECT(hoja&"!$A:$A"), 0 ), columna, MATCH( "Totales", INDIRECT(hoja&"!$6:$6"), 0 ), valor, INDEX( INDIRECT(hoja&"!$A:$ZZ"), fila, columna ), IF(valor="-", "", valor) ), "") | V34: =T34-U34 -> 0 | W34: {=IFERROR(SUMIF(Consolidado!$C$3:$C63, $A34, INDEX(Consolidado!$E$3:$P$100, , MATCH(W$1, Consolidado!$E$2:$P$2, 0))), "")} | X34: =IFERROR( LET( hoja, LEFT(X$1,3)&"R", fila, MATCH( RIGHT($A34, LEN($A34)-4), INDIRECT(hoja&"!$A:$A"), 0 ), columna, MATCH( "Totales", INDIRECT(hoja&"!$6:$6"), 0 ), valor, INDEX( INDIRECT(hoja&"!$A:$ZZ"), fila, columna ), IF(valor="-", "", valor) ), "") | Y34: =W34-X34 -> 0 | Z34: {=IFERROR(SUMIF(Consolidado!$C$3:$C63, $A34, INDEX(Consolidado!$E$3:$P$100, , MATCH(Z$1, Consolidado!$E$2:$P$2, 0))), "")} | AA34: =IFERROR( LET( hoja, LEFT(AA$1,3)&"R", fila, MATCH( RIGHT($A34, LEN($A34)-4), INDIRECT(hoja&"!$A:$A"), 0 ), columna, MATCH( "Totales", INDIRECT(hoja&"!$6:$6"), 0 ), valor, INDEX( INDIRECT(hoja&"!$A:$ZZ"), fila, columna ), IF(valor="-", "", valor) ), "") | AB34: =Z34-AA34 -> 0 | AC34: {=IFERROR(SUMIF(Consolidado!$C$3:$C63, $A34, INDEX(Consolidado!$E$3:$P$100, , MATCH(AC$1, Consolidado!$E$2:$P$2, 0))), "")} | AD34: =IFERROR( LET( hoja, LEFT(AD$1,3)&"R", fila, MATCH( RIGHT($A34, LEN($A34)-4), INDIRECT(hoja&"!$A:$A"), 0 ), columna, MATCH( "Totales", INDIRECT(hoja&"!$6:$6"), 0 ), valor, INDEX( INDIRECT(hoja&"!$A:$ZZ"), fila, columna ), IF(valor="-", "", valor) ), "") | AE34: =AC34-AD34 -> 0 | AF34: {=IFERROR(SUMIF(Consolidado!$C$3:$C63, $A34, INDEX(Consolidado!$E$3:$P$100, , MATCH(AF$1, Consolidado!$E$2:$P$2, 0))), "")} | AG34: =IFERROR( LET( hoja, LEFT(AG$1,3)&"R", fila, MATCH( RIGHT($A34, LEN($A34)-4), INDIRECT(hoja&"!$A:$A"), 0 ), columna, MATCH( "Totales", INDIRECT(hoja&"!$6:$6"), 0 ), valor, INDEX( INDIRECT(hoja&"!$A:$ZZ"), fila, columna ), IF(valor="-", "", valor) ), "") | AH34: =AF34-AG34 -> 0 | AI34: {=IFERROR(SUMIF(Consolidado!$C$3:$C63, $A34, INDEX(Consolidado!$E$3:$P$100, , MATCH(AI$1, Consolidado!$E$2:$P$2, 0))), "")} | AJ34: =IFERROR( LET( hoja, LEFT(AJ$1,3)&"R", fila, MATCH( RIGHT($A34, LEN($A34)-4), INDIRECT(hoja&"!$A:$A"), 0 ), columna, MATCH( "Totales", INDIRECT(hoja&"!$6:$6"), 0 ), valor, INDEX( INDIRECT(hoja&"!$A:$ZZ"), fila, columna ), IF(valor="-", "", valor) ), "") | AK34: =AI34-AJ34 -> 0 | AL34: {=IFERROR(SUMIF(Consolidado!$C$3:$C63, $A34, INDEX(Consolidado!$E$3:$P$100, , MATCH(AL$1, Consolidado!$E$2:$P$2, 0))), "")} | AM34: =IFERROR( LET( hoja, LEFT(AM$1,3)&"R", fila, MATCH( RIGHT($A34, LEN($A34)-4), INDIRECT(hoja&"!$A:$A"), 0 ), columna, MATCH( "Totales", INDIRECT(hoja&"!$6:$6"), 0 ), valor, INDEX( INDIRECT(hoja&"!$A:$ZZ"), fila, columna ), IF(valor="-", "", valor) ), "") | AN34: =AL34-AM34 -> 0
A35: =Menus!B28 -> B25 Reparación equipo de operación | B35: =SUM(IF(MONTH(TODAY())>1,E35,0), IF(MONTH(TODAY())>2,H35,0), IF(MONTH(TODAY())>3,K35,0), IF(MONTH(TODAY())>4,N35,0), IF(MONTH(TODAY())>5,Q35,0), IF(MONTH(TODAY())>6,T35,0), IF(MONTH(TODAY())>7,W35,0), IF(MONTH(TODAY())>8,Z35,0), IF(MONTH(TODAY())>9,AC35,0), IF(MONTH(TODAY())>10,AF35,0), IF(MONTH(TODAY())>11,AI35,0), IF(MONTH(TODAY())>12,AL35,0)) -> 0 | C35: =SUM(IF(MONTH(TODAY())>1,F35,0), IF(MONTH(TODAY())>2,I35,0), IF(MONTH(TODAY())>3,L35,0), IF(MONTH(TODAY())>4,O35,0), IF(MONTH(TODAY())>5,R35,0), IF(MONTH(TODAY())>6,U35,0), IF(MONTH(TODAY())>7,X35,0), IF(MONTH(TODAY())>8,AA35,0), IF(MONTH(TODAY())>9,AD35,0), IF(MONTH(TODAY())>10,AG35,0), IF(MONTH(TODAY())>11,AJ35,0), IF(MONTH(TODAY())>12,AM35,0)) -> 0 | D35: =B35-C35 -> 0 | E35: {=IFERROR(SUMIF(Consolidado!$C$3:$C63, $A35, INDEX(Consolidado!$E$3:$P$100, , MATCH(E$1, Consolidado!$E$2:$P$2, 0))), "")} | F35: =IFERROR( LET( hoja, LEFT(F$1,3)&"R", fila, MATCH( RIGHT($A35, LEN($A35)-4), INDIRECT(hoja&"!$A:$A"), 0 ), columna, MATCH( "Totales", INDIRECT(hoja&"!$6:$6"), 0 ), valor, INDEX( INDIRECT(hoja&"!$A:$ZZ"), fila, columna ), IF(valor="-", "", valor) ), "") | G35: =E35-F35 -> 0 | H35: {=IFERROR(SUMIF(Consolidado!$C$3:$C63, $A35, INDEX(Consolidado!$E$3:$P$100, , MATCH(H$1, Consolidado!$E$2:$P$2, 0))), "")} | I35: =IFERROR( LET( hoja, LEFT(I$1,3)&"R", fila, MATCH( RIGHT($A35, LEN($A35)-4), INDIRECT(hoja&"!$A:$A"), 0 ), columna, MATCH( "Totales", INDIRECT(hoja&"!$6:$6"), 0 ), valor, INDEX( INDIRECT(hoja&"!$A:$ZZ"), fila, columna ), IF(valor="-", "", valor) ), "") | J35: =H35-I35 -> 0 | K35: {=IFERROR(SUMIF(Consolidado!$C$3:$C63, $A35, INDEX(Consolidado!$E$3:$P$100, , MATCH(K$1, Consolidado!$E$2:$P$2, 0))), "")} | L35: =IFERROR( LET( hoja, LEFT(L$1,3)&"R", fila, MATCH( RIGHT($A35, LEN($A35)-4), INDIRECT(hoja&"!$A:$A"), 0 ), columna, MATCH( "Totales", INDIRECT(hoja&"!$6:$6"), 0 ), valor, INDEX( INDIRECT(hoja&"!$A:$ZZ"), fila, columna ), IF(valor="-", "", valor) ), "") | M35: =K35-L35 -> 0 | N35: {=IFERROR(SUMIF(Consolidado!$C$3:$C63, $A35, INDEX(Consolidado!$E$3:$P$100, , MATCH(N$1, Consolidado!$E$2:$P$2, 0))), "")} | O35: =IFERROR( LET( hoja, LEFT(O$1,3)&"R", fila, MATCH( RIGHT($A35, LEN($A35)-4), INDIRECT(hoja&"!$A:$A"), 0 ), columna, MATCH( "Totales", INDIRECT(hoja&"!$6:$6"), 0 ), valor, INDEX( INDIRECT(hoja&"!$A:$ZZ"), fila, columna ), IF(valor="-", "", valor) ), "") | P35: =N35-O35 -> 0 | Q35: {=IFERROR(SUMIF(Consolidado!$C$3:$C63, $A35, INDEX(Consolidado!$E$3:$P$100, , MATCH(Q$1, Consolidado!$E$2:$P$2, 0))), "")} | R35: =IFERROR( LET( hoja, LEFT(R$1,3)&"R", fila, MATCH( RIGHT($A35, LEN($A35)-4), INDIRECT(hoja&"!$A:$A"), 0 ), columna, MATCH( "Totales", INDIRECT(hoja&"!$6:$6"), 0 ), valor, INDEX( INDIRECT(hoja&"!$A:$ZZ"), fila, columna ), IF(valor="-", "", valor) ), "") | S35: =Q35-R35 -> 0 | T35: {=IFERROR(SUMIF(Consolidado!$C$3:$C63, $A35, INDEX(Consolidado!$E$3:$P$100, , MATCH(T$1, Consolidado!$E$2:$P$2, 0))), "")} | U35: =IFERROR( LET( hoja, LEFT(U$1,3)&"R", fila, MATCH( RIGHT($A35, LEN($A35)-4), INDIRECT(hoja&"!$A:$A"), 0 ), columna, MATCH( "Totales", INDIRECT(hoja&"!$6:$6"), 0 ), valor, INDEX( INDIRECT(hoja&"!$A:$ZZ"), fila, columna ), IF(valor="-", "", valor) ), "") | V35: =T35-U35 -> 0 | W35: {=IFERROR(SUMIF(Consolidado!$C$3:$C63, $A35, INDEX(Consolidado!$E$3:$P$100, , MATCH(W$1, Consolidado!$E$2:$P$2, 0))), "")} | X35: =IFERROR( LET( hoja, LEFT(X$1,3)&"R", fila, MATCH( RIGHT($A35, LEN($A35)-4), INDIRECT(hoja&"!$A:$A"), 0 ), columna, MATCH( "Totales", INDIRECT(hoja&"!$6:$6"), 0 ), valor, INDEX( INDIRECT(hoja&"!$A:$ZZ"), fila, columna ), IF(valor="-", "", valor) ), "") | Y35: =W35-X35 -> 0 | Z35: {=IFERROR(SUMIF(Consolidado!$C$3:$C63, $A35, INDEX(Consolidado!$E$3:$P$100, , MATCH(Z$1, Consolidado!$E$2:$P$2, 0))), "")} | AA35: =IFERROR( LET( hoja, LEFT(AA$1,3)&"R", fila, MATCH( RIGHT($A35, LEN($A35)-4), INDIRECT(hoja&"!$A:$A"), 0 ), columna, MATCH( "Totales", INDIRECT(hoja&"!$6:$6"), 0 ), valor, INDEX( INDIRECT(hoja&"!$A:$ZZ"), fila, columna ), IF(valor="-", "", valor) ), "") | AB35: =Z35-AA35 -> 0 | AC35: {=IFERROR(SUMIF(Consolidado!$C$3:$C63, $A35, INDEX(Consolidado!$E$3:$P$100, , MATCH(AC$1, Consolidado!$E$2:$P$2, 0))), "")} | AD35: =IFERROR( LET( hoja, LEFT(AD$1,3)&"R", fila, MATCH( RIGHT($A35, LEN($A35)-4), INDIRECT(hoja&"!$A:$A"), 0 ), columna, MATCH( "Totales", INDIRECT(hoja&"!$6:$6"), 0 ), valor, INDEX( INDIRECT(hoja&"!$A:$ZZ"), fila, columna ), IF(valor="-", "", valor) ), "") | AE35: =AC35-AD35 -> 0 | AF35: {=IFERROR(SUMIF(Consolidado!$C$3:$C63, $A35, INDEX(Consolidado!$E$3:$P$100, , MATCH(AF$1, Consolidado!$E$2:$P$2, 0))), "")} | AG35: =IFERROR( LET( hoja, LEFT(AG$1,3)&"R", fila, MATCH( RIGHT($A35, LEN($A35)-4), INDIRECT(hoja&"!$A:$A"), 0 ), columna, MATCH( "Totales", INDIRECT(hoja&"!$6:$6"), 0 ), valor, INDEX( INDIRECT(hoja&"!$A:$ZZ"), fila, columna ), IF(valor="-", "", valor) ), "") | AH35: =AF35-AG35 -> 0 | AI35: {=IFERROR(SUMIF(Consolidado!$C$3:$C63, $A35, INDEX(Consolidado!$E$3:$P$100, , MATCH(AI$1, Consolidado!$E$2:$P$2, 0))), "")} | AJ35: =IFERROR( LET( hoja, LEFT(AJ$1,3)&"R", fila, MATCH( RIGHT($A35, LEN($A35)-4), INDIRECT(hoja&"!$A:$A"), 0 ), columna, MATCH( "Totales", INDIRECT(hoja&"!$6:$6"), 0 ), valor, INDEX( INDIRECT(hoja&"!$A:$ZZ"), fila, columna ), IF(valor="-", "", valor) ), "") | AK35: =AI35-AJ35 -> 0 | AL35: {=IFERROR(SUMIF(Consolidado!$C$3:$C63, $A35, INDEX(Consolidado!$E$3:$P$100, , MATCH(AL$1, Consolidado!$E$2:$P$2, 0))), "")} | AM35: =IFERROR( LET( hoja, LEFT(AM$1,3)&"R", fila, MATCH( RIGHT($A35, LEN($A35)-4), INDIRECT(hoja&"!$A:$A"), 0 ), columna, MATCH( "Totales", INDIRECT(hoja&"!$6:$6"), 0 ), valor, INDEX( INDIRECT(hoja&"!$A:$ZZ"), fila, columna ), IF(valor="-", "", valor) ), "") | AN35: =AL35-AM35 -> 0
A36: =Menus!B29 -> B26 Mantenimiento equipo de operación | B36: =SUM(IF(MONTH(TODAY())>1,E36,0), IF(MONTH(TODAY())>2,H36,0), IF(MONTH(TODAY())>3,K36,0), IF(MONTH(TODAY())>4,N36,0), IF(MONTH(TODAY())>5,Q36,0), IF(MONTH(TODAY())>6,T36,0), IF(MONTH(TODAY())>7,W36,0), IF(MONTH(TODAY())>8,Z36,0), IF(MONTH(TODAY())>9,AC36,0), IF(MONTH(TODAY())>10,AF36,0), IF(MONTH(TODAY())>11,AI36,0), IF(MONTH(TODAY())>12,AL36,0)) -> 0 | C36: =SUM(IF(MONTH(TODAY())>1,F36,0), IF(MONTH(TODAY())>2,I36,0), IF(MONTH(TODAY())>3,L36,0), IF(MONTH(TODAY())>4,O36,0), IF(MONTH(TODAY())>5,R36,0), IF(MONTH(TODAY())>6,U36,0), IF(MONTH(TODAY())>7,X36,0), IF(MONTH(TODAY())>8,AA36,0), IF(MONTH(TODAY())>9,AD36,0), IF(MONTH(TODAY())>10,AG36,0), IF(MONTH(TODAY())>11,AJ36,0), IF(MONTH(TODAY())>12,AM36,0)) -> 0 | D36: =B36-C36 -> 0 | E36: {=IFERROR(SUMIF(Consolidado!$C$3:$C63, $A36, INDEX(Consolidado!$E$3:$P$100, , MATCH(E$1, Consolidado!$E$2:$P$2, 0))), "")} | F36: =IFERROR( LET( hoja, LEFT(F$1,3)&"R", fila, MATCH( RIGHT($A36, LEN($A36)-4), INDIRECT(hoja&"!$A:$A"), 0 ), columna, MATCH( "Totales", INDIRECT(hoja&"!$6:$6"), 0 ), valor, INDEX( INDIRECT(hoja&"!$A:$ZZ"), fila, columna ), IF(valor="-", "", valor) ), "") | G36: =E36-F36 -> 0 | H36: {=IFERROR(SUMIF(Consolidado!$C$3:$C63, $A36, INDEX(Consolidado!$E$3:$P$100, , MATCH(H$1, Consolidado!$E$2:$P$2, 0))), "")} | I36: =IFERROR( LET( hoja, LEFT(I$1,3)&"R", fila, MATCH( RIGHT($A36, LEN($A36)-4), INDIRECT(hoja&"!$A:$A"), 0 ), columna, MATCH( "Totales", INDIRECT(hoja&"!$6:$6"), 0 ), valor, INDEX( INDIRECT(hoja&"!$A:$ZZ"), fila, columna ), IF(valor="-", "", valor) ), "") | J36: =H36-I36 -> 0 | K36: {=IFERROR(SUMIF(Consolidado!$C$3:$C63, $A36, INDEX(Consolidado!$E$3:$P$100, , MATCH(K$1, Consolidado!$E$2:$P$2, 0))), "")} | L36: =IFERROR( LET( hoja, LEFT(L$1,3)&"R", fila, MATCH( RIGHT($A36, LEN($A36)-4), INDIRECT(hoja&"!$A:$A"), 0 ), columna, MATCH( "Totales", INDIRECT(hoja&"!$6:$6"), 0 ), valor, INDEX( INDIRECT(hoja&"!$A:$ZZ"), fila, columna ), IF(valor="-", "", valor) ), "") | M36: =K36-L36 -> 0 | N36: {=IFERROR(SUMIF(Consolidado!$C$3:$C63, $A36, INDEX(Consolidado!$E$3:$P$100, , MATCH(N$1, Consolidado!$E$2:$P$2, 0))), "")} | O36: =IFERROR( LET( hoja, LEFT(O$1,3)&"R", fila, MATCH( RIGHT($A36, LEN($A36)-4), INDIRECT(hoja&"!$A:$A"), 0 ), columna, MATCH( "Totales", INDIRECT(hoja&"!$6:$6"), 0 ), valor, INDEX( INDIRECT(hoja&"!$A:$ZZ"), fila, columna ), IF(valor="-", "", valor) ), "") | P36: =N36-O36 -> 0 | Q36: {=IFERROR(SUMIF(Consolidado!$C$3:$C63, $A36, INDEX(Consolidado!$E$3:$P$100, , MATCH(Q$1, Consolidado!$E$2:$P$2, 0))), "")} | R36: =IFERROR( LET( hoja, LEFT(R$1,3)&"R", fila, MATCH( RIGHT($A36, LEN($A36)-4), INDIRECT(hoja&"!$A:$A"), 0 ), columna, MATCH( "Totales", INDIRECT(hoja&"!$6:$6"), 0 ), valor, INDEX( INDIRECT(hoja&"!$A:$ZZ"), fila, columna ), IF(valor="-", "", valor) ), "") | S36: =Q36-R36 -> 0 | T36: {=IFERROR(SUMIF(Consolidado!$C$3:$C63, $A36, INDEX(Consolidado!$E$3:$P$100, , MATCH(T$1, Consolidado!$E$2:$P$2, 0))), "")} | U36: =IFERROR( LET( hoja, LEFT(U$1,3)&"R", fila, MATCH( RIGHT($A36, LEN($A36)-4), INDIRECT(hoja&"!$A:$A"), 0 ), columna, MATCH( "Totales", INDIRECT(hoja&"!$6:$6"), 0 ), valor, INDEX( INDIRECT(hoja&"!$A:$ZZ"), fila, columna ), IF(valor="-", "", valor) ), "") | V36: =T36-U36 -> 0 | W36: {=IFERROR(SUMIF(Consolidado!$C$3:$C63, $A36, INDEX(Consolidado!$E$3:$P$100, , MATCH(W$1, Consolidado!$E$2:$P$2, 0))), "")} | X36: =IFERROR( LET( hoja, LEFT(X$1,3)&"R", fila, MATCH( RIGHT($A36, LEN($A36)-4), INDIRECT(hoja&"!$A:$A"), 0 ), columna, MATCH( "Totales", INDIRECT(hoja&"!$6:$6"), 0 ), valor, INDEX( INDIRECT(hoja&"!$A:$ZZ"), fila, columna ), IF(valor="-", "", valor) ), "") | Y36: =W36-X36 -> 0 | Z36: {=IFERROR(SUMIF(Consolidado!$C$3:$C63, $A36, INDEX(Consolidado!$E$3:$P$100, , MATCH(Z$1, Consolidado!$E$2:$P$2, 0))), "")} | AA36: =IFERROR( LET( hoja, LEFT(AA$1,3)&"R", fila, MATCH( RIGHT($A36, LEN($A36)-4), INDIRECT(hoja&"!$A:$A"), 0 ), columna, MATCH( "Totales", INDIRECT(hoja&"!$6:$6"), 0 ), valor, INDEX( INDIRECT(hoja&"!$A:$ZZ"), fila, columna ), IF(valor="-", "", valor) ), "") | AB36: =Z36-AA36 -> 0 | AC36: {=IFERROR(SUMIF(Consolidado!$C$3:$C63, $A36, INDEX(Consolidado!$E$3:$P$100, , MATCH(AC$1, Consolidado!$E$2:$P$2, 0))), "")} | AD36: =IFERROR( LET( hoja, LEFT(AD$1,3)&"R", fila, MATCH( RIGHT($A36, LEN($A36)-4), INDIRECT(hoja&"!$A:$A"), 0 ), columna, MATCH( "Totales", INDIRECT(hoja&"!$6:$6"), 0 ), valor, INDEX( INDIRECT(hoja&"!$A:$ZZ"), fila, columna ), IF(valor="-", "", valor) ), "") | AE36: =AC36-AD36 -> 0 | AF36: {=IFERROR(SUMIF(Consolidado!$C$3:$C63, $A36, INDEX(Consolidado!$E$3:$P$100, , MATCH(AF$1, Consolidado!$E$2:$P$2, 0))), "")} | AG36: =IFERROR( LET( hoja, LEFT(AG$1,3)&"R", fila, MATCH( RIGHT($A36, LEN($A36)-4), INDIRECT(hoja&"!$A:$A"), 0 ), columna, MATCH( "Totales", INDIRECT(hoja&"!$6:$6"), 0 ), valor, INDEX( INDIRECT(hoja&"!$A:$ZZ"), fila, columna ), IF(valor="-", "", valor) ), "") | AH36: =AF36-AG36 -> 0 | AI36: {=IFERROR(SUMIF(Consolidado!$C$3:$C63, $A36, INDEX(Consolidado!$E$3:$P$100, , MATCH(AI$1, Consolidado!$E$2:$P$2, 0))), "")} | AJ36: =IFERROR( LET( hoja, LEFT(AJ$1,3)&"R", fila, MATCH( RIGHT($A36, LEN($A36)-4), INDIRECT(hoja&"!$A:$A"), 0 ), columna, MATCH( "Totales", INDIRECT(hoja&"!$6:$6"), 0 ), valor, INDEX( INDIRECT(hoja&"!$A:$ZZ"), fila, columna ), IF(valor="-", "", valor) ), "") | AK36: =AI36-AJ36 -> 0 | AL36: {=IFERROR(SUMIF(Consolidado!$C$3:$C63, $A36, INDEX(Consolidado!$E$3:$P$100, , MATCH(AL$1, Consolidado!$E$2:$P$2, 0))), "")} | AM36: =IFERROR( LET( hoja, LEFT(AM$1,3)&"R", fila, MATCH( RIGHT($A36, LEN($A36)-4), INDIRECT(hoja&"!$A:$A"), 0 ), columna, MATCH( "Totales", INDIRECT(hoja&"!$6:$6"), 0 ), valor, INDEX( INDIRECT(hoja&"!$A:$ZZ"), fila, columna ), IF(valor="-", "", valor) ), "") | AN36: =AL36-AM36 -> 0
A37: =Menus!B30 -> B27 Publicidad | B37: =SUM(IF(MONTH(TODAY())>1,E37,0), IF(MONTH(TODAY())>2,H37,0), IF(MONTH(TODAY())>3,K37,0), IF(MONTH(TODAY())>4,N37,0), IF(MONTH(TODAY())>5,Q37,0), IF(MONTH(TODAY())>6,T37,0), IF(MONTH(TODAY())>7,W37,0), IF(MONTH(TODAY())>8,Z37,0), IF(MONTH(TODAY())>9,AC37,0), IF(MONTH(TODAY())>10,AF37,0), IF(MONTH(TODAY())>11,AI37,0), IF(MONTH(TODAY())>12,AL37,0)) -> 0 | C37: =SUM(IF(MONTH(TODAY())>1,F37,0), IF(MONTH(TODAY())>2,I37,0), IF(MONTH(TODAY())>3,L37,0), IF(MONTH(TODAY())>4,O37,0), IF(MONTH(TODAY())>5,R37,0), IF(MONTH(TODAY())>6,U37,0), IF(MONTH(TODAY())>7,X37,0), IF(MONTH(TODAY())>8,AA37,0), IF(MONTH(TODAY())>9,AD37,0), IF(MONTH(TODAY())>10,AG37,0), IF(MONTH(TODAY())>11,AJ37,0), IF(MONTH(TODAY())>12,AM37,0)) -> 0 | D37: =B37-C37 -> 0 | E37: {=IFERROR(SUMIF(Consolidado!$C$3:$C63, $A37, INDEX(Consolidado!$E$3:$P$100, , MATCH(E$1, Consolidado!$E$2:$P$2, 0))), "")} | F37: =IFERROR( LET( hoja, LEFT(F$1,3)&"R", fila, MATCH( RIGHT($A37, LEN($A37)-4), INDIRECT(hoja&"!$A:$A"), 0 ), columna, MATCH( "Totales", INDIRECT(hoja&"!$6:$6"), 0 ), valor, INDEX( INDIRECT(hoja&"!$A:$ZZ"), fila, columna ), IF(valor="-", "", valor) ), "") | G37: =E37-F37 -> 0 | H37: {=IFERROR(SUMIF(Consolidado!$C$3:$C63, $A37, INDEX(Consolidado!$E$3:$P$100, , MATCH(H$1, Consolidado!$E$2:$P$2, 0))), "")} | I37: =IFERROR( LET( hoja, LEFT(I$1,3)&"R", fila, MATCH( RIGHT($A37, LEN($A37)-4), INDIRECT(hoja&"!$A:$A"), 0 ), columna, MATCH( "Totales", INDIRECT(hoja&"!$6:$6"), 0 ), valor, INDEX( INDIRECT(hoja&"!$A:$ZZ"), fila, columna ), IF(valor="-", "", valor) ), "") | J37: =H37-I37 -> 0 | K37: {=IFERROR(SUMIF(Consolidado!$C$3:$C63, $A37, INDEX(Consolidado!$E$3:$P$100, , MATCH(K$1, Consolidado!$E$2:$P$2, 0))), "")} | L37: =IFERROR( LET( hoja, LEFT(L$1,3)&"R", fila, MATCH( RIGHT($A37, LEN($A37)-4), INDIRECT(hoja&"!$A:$A"), 0 ), columna, MATCH( "Totales", INDIRECT(hoja&"!$6:$6"), 0 ), valor, INDEX( INDIRECT(hoja&"!$A:$ZZ"), fila, columna ), IF(valor="-", "", valor) ), "") | M37: =K37-L37 -> 0 | N37: {=IFERROR(SUMIF(Consolidado!$C$3:$C63, $A37, INDEX(Consolidado!$E$3:$P$100, , MATCH(N$1, Consolidado!$E$2:$P$2, 0))), "")} | O37: =IFERROR( LET( hoja, LEFT(O$1,3)&"R", fila, MATCH( RIGHT($A37, LEN($A37)-4), INDIRECT(hoja&"!$A:$A"), 0 ), columna, MATCH( "Totales", INDIRECT(hoja&"!$6:$6"), 0 ), valor, INDEX( INDIRECT(hoja&"!$A:$ZZ"), fila, columna ), IF(valor="-", "", valor) ), "") | P37: =N37-O37 -> 0 | Q37: {=IFERROR(SUMIF(Consolidado!$C$3:$C63, $A37, INDEX(Consolidado!$E$3:$P$100, , MATCH(Q$1, Consolidado!$E$2:$P$2, 0))), "")} | R37: =IFERROR( LET( hoja, LEFT(R$1,3)&"R", fila, MATCH( RIGHT($A37, LEN($A37)-4), INDIRECT(hoja&"!$A:$A"), 0 ), columna, MATCH( "Totales", INDIRECT(hoja&"!$6:$6"), 0 ), valor, INDEX( INDIRECT(hoja&"!$A:$ZZ"), fila, columna ), IF(valor="-", "", valor) ), "") | S37: =Q37-R37 -> 0 | T37: {=IFERROR(SUMIF(Consolidado!$C$3:$C63, $A37, INDEX(Consolidado!$E$3:$P$100, , MATCH(T$1, Consolidado!$E$2:$P$2, 0))), "")} | U37: =IFERROR( LET( hoja, LEFT(U$1,3)&"R", fila, MATCH( RIGHT($A37, LEN($A37)-4), INDIRECT(hoja&"!$A:$A"), 0 ), columna, MATCH( "Totales", INDIRECT(hoja&"!$6:$6"), 0 ), valor, INDEX( INDIRECT(hoja&"!$A:$ZZ"), fila, columna ), IF(valor="-", "", valor) ), "") | V37: =T37-U37 -> 0 | W37: {=IFERROR(SUMIF(Consolidado!$C$3:$C63, $A37, INDEX(Consolidado!$E$3:$P$100, , MATCH(W$1, Consolidado!$E$2:$P$2, 0))), "")} | X37: =IFERROR( LET( hoja, LEFT(X$1,3)&"R", fila, MATCH( RIGHT($A37, LEN($A37)-4), INDIRECT(hoja&"!$A:$A"), 0 ), columna, MATCH( "Totales", INDIRECT(hoja&"!$6:$6"), 0 ), valor, INDEX( INDIRECT(hoja&"!$A:$ZZ"), fila, columna ), IF(valor="-", "", valor) ), "") | Y37: =W37-X37 -> 0 | Z37: {=IFERROR(SUMIF(Consolidado!$C$3:$C63, $A37, INDEX(Consolidado!$E$3:$P$100, , MATCH(Z$1, Consolidado!$E$2:$P$2, 0))), "")} | AA37: =IFERROR( LET( hoja, LEFT(AA$1,3)&"R", fila, MATCH( RIGHT($A37, LEN($A37)-4), INDIRECT(hoja&"!$A:$A"), 0 ), columna, MATCH( "Totales", INDIRECT(hoja&"!$6:$6"), 0 ), valor, INDEX( INDIRECT(hoja&"!$A:$ZZ"), fila, columna ), IF(valor="-", "", valor) ), "") | AB37: =Z37-AA37 -> 0 | AC37: {=IFERROR(SUMIF(Consolidado!$C$3:$C63, $A37, INDEX(Consolidado!$E$3:$P$100, , MATCH(AC$1, Consolidado!$E$2:$P$2, 0))), "")} | AD37: =IFERROR( LET( hoja, LEFT(AD$1,3)&"R", fila, MATCH( RIGHT($A37, LEN($A37)-4), INDIRECT(hoja&"!$A:$A"), 0 ), columna, MATCH( "Totales", INDIRECT(hoja&"!$6:$6"), 0 ), valor, INDEX( INDIRECT(hoja&"!$A:$ZZ"), fila, columna ), IF(valor="-", "", valor) ), "") | AE37: =AC37-AD37 -> 0 | AF37: {=IFERROR(SUMIF(Consolidado!$C$3:$C63, $A37, INDEX(Consolidado!$E$3:$P$100, , MATCH(AF$1, Consolidado!$E$2:$P$2, 0))), "")} | AG37: =IFERROR( LET( hoja, LEFT(AG$1,3)&"R", fila, MATCH( RIGHT($A37, LEN($A37)-4), INDIRECT(hoja&"!$A:$A"), 0 ), columna, MATCH( "Totales", INDIRECT(hoja&"!$6:$6"), 0 ), valor, INDEX( INDIRECT(hoja&"!$A:$ZZ"), fila, columna ), IF(valor="-", "", valor) ), "") | AH37: =AF37-AG37 -> 0 | AI37: {=IFERROR(SUMIF(Consolidado!$C$3:$C63, $A37, INDEX(Consolidado!$E$3:$P$100, , MATCH(AI$1, Consolidado!$E$2:$P$2, 0))), "")} | AJ37: =IFERROR( LET( hoja, LEFT(AJ$1,3)&"R", fila, MATCH( RIGHT($A37, LEN($A37)-4), INDIRECT(hoja&"!$A:$A"), 0 ), columna, MATCH( "Totales", INDIRECT(hoja&"!$6:$6"), 0 ), valor, INDEX( INDIRECT(hoja&"!$A:$ZZ"), fila, columna ), IF(valor="-", "", valor) ), "") | AK37: =AI37-AJ37 -> 0 | AL37: {=IFERROR(SUMIF(Consolidado!$C$3:$C63, $A37, INDEX(Consolidado!$E$3:$P$100, , MATCH(AL$1, Consolidado!$E$2:$P$2, 0))), "")} | AM37: =IFERROR( LET( hoja, LEFT(AM$1,3)&"R", fila, MATCH( RIGHT($A37, LEN($A37)-4), INDIRECT(hoja&"!$A:$A"), 0 ), columna, MATCH( "Totales", INDIRECT(hoja&"!$6:$6"), 0 ), valor, INDEX( INDIRECT(hoja&"!$A:$ZZ"), fila, columna ), IF(valor="-", "", valor) ), "") | AN37: =AL37-AM37 -> 0
A38: =Menus!B31 -> B28 Suministros de oficina | B38: =SUM(IF(MONTH(TODAY())>1,E38,0), IF(MONTH(TODAY())>2,H38,0), IF(MONTH(TODAY())>3,K38,0), IF(MONTH(TODAY())>4,N38,0), IF(MONTH(TODAY())>5,Q38,0), IF(MONTH(TODAY())>6,T38,0), IF(MONTH(TODAY())>7,W38,0), IF(MONTH(TODAY())>8,Z38,0), IF(MONTH(TODAY())>9,AC38,0), IF(MONTH(TODAY())>10,AF38,0), IF(MONTH(TODAY())>11,AI38,0), IF(MONTH(TODAY())>12,AL38,0)) -> 0 | C38: =SUM(IF(MONTH(TODAY())>1,F38,0), IF(MONTH(TODAY())>2,I38,0), IF(MONTH(TODAY())>3,L38,0), IF(MONTH(TODAY())>4,O38,0), IF(MONTH(TODAY())>5,R38,0), IF(MONTH(TODAY())>6,U38,0), IF(MONTH(TODAY())>7,X38,0), IF(MONTH(TODAY())>8,AA38,0), IF(MONTH(TODAY())>9,AD38,0), IF(MONTH(TODAY())>10,AG38,0), IF(MONTH(TODAY())>11,AJ38,0), IF(MONTH(TODAY())>12,AM38,0)) -> 0 | D38: =B38-C38 -> 0 | E38: {=IFERROR(SUMIF(Consolidado!$C$3:$C63, $A38, INDEX(Consolidado!$E$3:$P$100, , MATCH(E$1, Consolidado!$E$2:$P$2, 0))), "")} | F38: =IFERROR( LET( hoja, LEFT(F$1,3)&"R", fila, MATCH( RIGHT($A38, LEN($A38)-4), INDIRECT(hoja&"!$A:$A"), 0 ), columna, MATCH( "Totales", INDIRECT(hoja&"!$6:$6"), 0 ), valor, INDEX( INDIRECT(hoja&"!$A:$ZZ"), fila, columna ), IF(valor="-", "", valor) ), "") | G38: =E38-F38 -> 0 | H38: {=IFERROR(SUMIF(Consolidado!$C$3:$C63, $A38, INDEX(Consolidado!$E$3:$P$100, , MATCH(H$1, Consolidado!$E$2:$P$2, 0))), "")} | I38: =IFERROR( LET( hoja, LEFT(I$1,3)&"R", fila, MATCH( RIGHT($A38, LEN($A38)-4), INDIRECT(hoja&"!$A:$A"), 0 ), columna, MATCH( "Totales", INDIRECT(hoja&"!$6:$6"), 0 ), valor, INDEX( INDIRECT(hoja&"!$A:$ZZ"), fila, columna ), IF(valor="-", "", valor) ), "") | J38: =H38-I38 -> 0 | K38: {=IFERROR(SUMIF(Consolidado!$C$3:$C63, $A38, INDEX(Consolidado!$E$3:$P$100, , MATCH(K$1, Consolidado!$E$2:$P$2, 0))), "")} | L38: =IFERROR( LET( hoja, LEFT(L$1,3)&"R", fila, MATCH( RIGHT($A38, LEN($A38)-4), INDIRECT(hoja&"!$A:$A"), 0 ), columna, MATCH( "Totales", INDIRECT(hoja&"!$6:$6"), 0 ), valor, INDEX( INDIRECT(hoja&"!$A:$ZZ"), fila, columna ), IF(valor="-", "", valor) ), "") | M38: =K38-L38 -> 0 | N38: {=IFERROR(SUMIF(Consolidado!$C$3:$C63, $A38, INDEX(Consolidado!$E$3:$P$100, , MATCH(N$1, Consolidado!$E$2:$P$2, 0))), "")} | O38: =IFERROR( LET( hoja, LEFT(O$1,3)&"R", fila, MATCH( RIGHT($A38, LEN($A38)-4), INDIRECT(hoja&"!$A:$A"), 0 ), columna, MATCH( "Totales", INDIRECT(hoja&"!$6:$6"), 0 ), valor, INDEX( INDIRECT(hoja&"!$A:$ZZ"), fila, columna ), IF(valor="-", "", valor) ), "") | P38: =N38-O38 -> 0 | Q38: {=IFERROR(SUMIF(Consolidado!$C$3:$C63, $A38, INDEX(Consolidado!$E$3:$P$100, , MATCH(Q$1, Consolidado!$E$2:$P$2, 0))), "")} | R38: =IFERROR( LET( hoja, LEFT(R$1,3)&"R", fila, MATCH( RIGHT($A38, LEN($A38)-4), INDIRECT(hoja&"!$A:$A"), 0 ), columna, MATCH( "Totales", INDIRECT(hoja&"!$6:$6"), 0 ), valor, INDEX( INDIRECT(hoja&"!$A:$ZZ"), fila, columna ), IF(valor="-", "", valor) ), "") | S38: =Q38-R38 -> 0 | T38: {=IFERROR(SUMIF(Consolidado!$C$3:$C63, $A38, INDEX(Consolidado!$E$3:$P$100, , MATCH(T$1, Consolidado!$E$2:$P$2, 0))), "")} | U38: =IFERROR( LET( hoja, LEFT(U$1,3)&"R", fila, MATCH( RIGHT($A38, LEN($A38)-4), INDIRECT(hoja&"!$A:$A"), 0 ), columna, MATCH( "Totales", INDIRECT(hoja&"!$6:$6"), 0 ), valor, INDEX( INDIRECT(hoja&"!$A:$ZZ"), fila, columna ), IF(valor="-", "", valor) ), "") | V38: =T38-U38 -> 0 | W38: {=IFERROR(SUMIF(Consolidado!$C$3:$C63, $A38, INDEX(Consolidado!$E$3:$P$100, , MATCH(W$1, Consolidado!$E$2:$P$2, 0))), "")} | X38: =IFERROR( LET( hoja, LEFT(X$1,3)&"R", fila, MATCH( RIGHT($A38, LEN($A38)-4), INDIRECT(hoja&"!$A:$A"), 0 ), columna, MATCH( "Totales", INDIRECT(hoja&"!$6:$6"), 0 ), valor, INDEX( INDIRECT(hoja&"!$A:$ZZ"), fila, columna ), IF(valor="-", "", valor) ), "") | Y38: =W38-X38 -> 0 | Z38: {=IFERROR(SUMIF(Consolidado!$C$3:$C63, $A38, INDEX(Consolidado!$E$3:$P$100, , MATCH(Z$1, Consolidado!$E$2:$P$2, 0))), "")} | AA38: =IFERROR( LET( hoja, LEFT(AA$1,3)&"R", fila, MATCH( RIGHT($A38, LEN($A38)-4), INDIRECT(hoja&"!$A:$A"), 0 ), columna, MATCH( "Totales", INDIRECT(hoja&"!$6:$6"), 0 ), valor, INDEX( INDIRECT(hoja&"!$A:$ZZ"), fila, columna ), IF(valor="-", "", valor) ), "") | AB38: =Z38-AA38 -> 0 | AC38: {=IFERROR(SUMIF(Consolidado!$C$3:$C63, $A38, INDEX(Consolidado!$E$3:$P$100, , MATCH(AC$1, Consolidado!$E$2:$P$2, 0))), "")} | AD38: =IFERROR( LET( hoja, LEFT(AD$1,3)&"R", fila, MATCH( RIGHT($A38, LEN($A38)-4), INDIRECT(hoja&"!$A:$A"), 0 ), columna, MATCH( "Totales", INDIRECT(hoja&"!$6:$6"), 0 ), valor, INDEX( INDIRECT(hoja&"!$A:$ZZ"), fila, columna ), IF(valor="-", "", valor) ), "") | AE38: =AC38-AD38 -> 0 | AF38: {=IFERROR(SUMIF(Consolidado!$C$3:$C63, $A38, INDEX(Consolidado!$E$3:$P$100, , MATCH(AF$1, Consolidado!$E$2:$P$2, 0))), "")} | AG38: =IFERROR( LET( hoja, LEFT(AG$1,3)&"R", fila, MATCH( RIGHT($A38, LEN($A38)-4), INDIRECT(hoja&"!$A:$A"), 0 ), columna, MATCH( "Totales", INDIRECT(hoja&"!$6:$6"), 0 ), valor, INDEX( INDIRECT(hoja&"!$A:$ZZ"), fila, columna ), IF(valor="-", "", valor) ), "") | AH38: =AF38-AG38 -> 0 | AI38: {=IFERROR(SUMIF(Consolidado!$C$3:$C63, $A38, INDEX(Consolidado!$E$3:$P$100, , MATCH(AI$1, Consolidado!$E$2:$P$2, 0))), "")} | AJ38: =IFERROR( LET( hoja, LEFT(AJ$1,3)&"R", fila, MATCH( RIGHT($A38, LEN($A38)-4), INDIRECT(hoja&"!$A:$A"), 0 ), columna, MATCH( "Totales", INDIRECT(hoja&"!$6:$6"), 0 ), valor, INDEX( INDIRECT(hoja&"!$A:$ZZ"), fila, columna ), IF(valor="-", "", valor) ), "") | AK38: =AI38-AJ38 -> 0 | AL38: {=IFERROR(SUMIF(Consolidado!$C$3:$C63, $A38, INDEX(Consolidado!$E$3:$P$100, , MATCH(AL$1, Consolidado!$E$2:$P$2, 0))), "")} | AM38: =IFERROR( LET( hoja, LEFT(AM$1,3)&"R", fila, MATCH( RIGHT($A38, LEN($A38)-4), INDIRECT(hoja&"!$A:$A"), 0 ), columna, MATCH( "Totales", INDIRECT(hoja&"!$6:$6"), 0 ), valor, INDEX( INDIRECT(hoja&"!$A:$ZZ"), fila, columna ), IF(valor="-", "", valor) ), "") | AN38: =AL38-AM38 -> 0
A39: =Menus!B32 -> B29 Varios | B39: =SUM(IF(MONTH(TODAY())>1,E39,0), IF(MONTH(TODAY())>2,H39,0), IF(MONTH(TODAY())>3,K39,0), IF(MONTH(TODAY())>4,N39,0), IF(MONTH(TODAY())>5,Q39,0), IF(MONTH(TODAY())>6,T39,0), IF(MONTH(TODAY())>7,W39,0), IF(MONTH(TODAY())>8,Z39,0), IF(MONTH(TODAY())>9,AC39,0), IF(MONTH(TODAY())>10,AF39,0), IF(MONTH(TODAY())>11,AI39,0), IF(MONTH(TODAY())>12,AL39,0)) -> 0 | C39: =SUM(IF(MONTH(TODAY())>1,F39,0), IF(MONTH(TODAY())>2,I39,0), IF(MONTH(TODAY())>3,L39,0), IF(MONTH(TODAY())>4,O39,0), IF(MONTH(TODAY())>5,R39,0), IF(MONTH(TODAY())>6,U39,0), IF(MONTH(TODAY())>7,X39,0), IF(MONTH(TODAY())>8,AA39,0), IF(MONTH(TODAY())>9,AD39,0), IF(MONTH(TODAY())>10,AG39,0), IF(MONTH(TODAY())>11,AJ39,0), IF(MONTH(TODAY())>12,AM39,0)) -> 0 | D39: =B39-C39 -> 0 | E39: {=IFERROR(SUMIF(Consolidado!$C$3:$C63, $A39, INDEX(Consolidado!$E$3:$P$100, , MATCH(E$1, Consolidado!$E$2:$P$2, 0))), "")} | F39: =IFERROR( LET( hoja, LEFT(F$1,3)&"R", fila, MATCH( RIGHT($A39, LEN($A39)-4), INDIRECT(hoja&"!$A:$A"), 0 ), columna, MATCH( "Totales", INDIRECT(hoja&"!$6:$6"), 0 ), valor, INDEX( INDIRECT(hoja&"!$A:$ZZ"), fila, columna ), IF(valor="-", "", valor) ), "") | G39: =E39-F39 -> 0 | H39: {=IFERROR(SUMIF(Consolidado!$C$3:$C63, $A39, INDEX(Consolidado!$E$3:$P$100, , MATCH(H$1, Consolidado!$E$2:$P$2, 0))), "")} | I39: =IFERROR( LET( hoja, LEFT(I$1,3)&"R", fila, MATCH( RIGHT($A39, LEN($A39)-4), INDIRECT(hoja&"!$A:$A"), 0 ), columna, MATCH( "Totales", INDIRECT(hoja&"!$6:$6"), 0 ), valor, INDEX( INDIRECT(hoja&"!$A:$ZZ"), fila, columna ), IF(valor="-", "", valor) ), "") | J39: =H39-I39 -> 0 | K39: {=IFERROR(SUMIF(Consolidado!$C$3:$C63, $A39, INDEX(Consolidado!$E$3:$P$100, , MATCH(K$1, Consolidado!$E$2:$P$2, 0))), "")} | L39: =IFERROR( LET( hoja, LEFT(L$1,3)&"R", fila, MATCH( RIGHT($A39, LEN($A39)-4), INDIRECT(hoja&"!$A:$A"), 0 ), columna, MATCH( "Totales", INDIRECT(hoja&"!$6:$6"), 0 ), valor, INDEX( INDIRECT(hoja&"!$A:$ZZ"), fila, columna ), IF(valor="-", "", valor) ), "") | M39: =K39-L39 -> 0 | N39: {=IFERROR(SUMIF(Consolidado!$C$3:$C63, $A39, INDEX(Consolidado!$E$3:$P$100, , MATCH(N$1, Consolidado!$E$2:$P$2, 0))), "")} | O39: =IFERROR( LET( hoja, LEFT(O$1,3)&"R", fila, MATCH( RIGHT($A39, LEN($A39)-4), INDIRECT(hoja&"!$A:$A"), 0 ), columna, MATCH( "Totales", INDIRECT(hoja&"!$6:$6"), 0 ), valor, INDEX( INDIRECT(hoja&"!$A:$ZZ"), fila, columna ), IF(valor="-", "", valor) ), "") | P39: =N39-O39 -> 0 | Q39: {=IFERROR(SUMIF(Consolidado!$C$3:$C63, $A39, INDEX(Consolidado!$E$3:$P$100, , MATCH(Q$1, Consolidado!$E$2:$P$2, 0))), "")} | R39: =IFERROR( LET( hoja, LEFT(R$1,3)&"R", fila, MATCH( RIGHT($A39, LEN($A39)-4), INDIRECT(hoja&"!$A:$A"), 0 ), columna, MATCH( "Totales", INDIRECT(hoja&"!$6:$6"), 0 ), valor, INDEX( INDIRECT(hoja&"!$A:$ZZ"), fila, columna ), IF(valor="-", "", valor) ), "") | S39: =Q39-R39 -> 0 | T39: {=IFERROR(SUMIF(Consolidado!$C$3:$C63, $A39, INDEX(Consolidado!$E$3:$P$100, , MATCH(T$1, Consolidado!$E$2:$P$2, 0))), "")} | U39: =IFERROR( LET( hoja, LEFT(U$1,3)&"R", fila, MATCH( RIGHT($A39, LEN($A39)-4), INDIRECT(hoja&"!$A:$A"), 0 ), columna, MATCH( "Totales", INDIRECT(hoja&"!$6:$6"), 0 ), valor, INDEX( INDIRECT(hoja&"!$A:$ZZ"), fila, columna ), IF(valor="-", "", valor) ), "") | V39: =T39-U39 -> 0 | W39: {=IFERROR(SUMIF(Consolidado!$C$3:$C63, $A39, INDEX(Consolidado!$E$3:$P$100, , MATCH(W$1, Consolidado!$E$2:$P$2, 0))), "")} | X39: =IFERROR( LET( hoja, LEFT(X$1,3)&"R", fila, MATCH( RIGHT($A39, LEN($A39)-4), INDIRECT(hoja&"!$A:$A"), 0 ), columna, MATCH( "Totales", INDIRECT(hoja&"!$6:$6"), 0 ), valor, INDEX( INDIRECT(hoja&"!$A:$ZZ"), fila, columna ), IF(valor="-", "", valor) ), "") | Y39: =W39-X39 -> 0 | Z39: {=IFERROR(SUMIF(Consolidado!$C$3:$C63, $A39, INDEX(Consolidado!$E$3:$P$100, , MATCH(Z$1, Consolidado!$E$2:$P$2, 0))), "")} | AA39: =IFERROR( LET( hoja, LEFT(AA$1,3)&"R", fila, MATCH( RIGHT($A39, LEN($A39)-4), INDIRECT(hoja&"!$A:$A"), 0 ), columna, MATCH( "Totales", INDIRECT(hoja&"!$6:$6"), 0 ), valor, INDEX( INDIRECT(hoja&"!$A:$ZZ"), fila, columna ), IF(valor="-", "", valor) ), "") | AB39: =Z39-AA39 -> 0 | AC39: {=IFERROR(SUMIF(Consolidado!$C$3:$C63, $A39, INDEX(Consolidado!$E$3:$P$100, , MATCH(AC$1, Consolidado!$E$2:$P$2, 0))), "")} | AD39: =IFERROR( LET( hoja, LEFT(AD$1,3)&"R", fila, MATCH( RIGHT($A39, LEN($A39)-4), INDIRECT(hoja&"!$A:$A"), 0 ), columna, MATCH( "Totales", INDIRECT(hoja&"!$6:$6"), 0 ), valor, INDEX( INDIRECT(hoja&"!$A:$ZZ"), fila, columna ), IF(valor="-", "", valor) ), "") | AE39: =AC39-AD39 -> 0 | AF39: {=IFERROR(SUMIF(Consolidado!$C$3:$C63, $A39, INDEX(Consolidado!$E$3:$P$100, , MATCH(AF$1, Consolidado!$E$2:$P$2, 0))), "")} | AG39: =IFERROR( LET( hoja, LEFT(AG$1,3)&"R", fila, MATCH( RIGHT($A39, LEN($A39)-4), INDIRECT(hoja&"!$A:$A"), 0 ), columna, MATCH( "Totales", INDIRECT(hoja&"!$6:$6"), 0 ), valor, INDEX( INDIRECT(hoja&"!$A:$ZZ"), fila, columna ), IF(valor="-", "", valor) ), "") | AH39: =AF39-AG39 -> 0 | AI39: {=IFERROR(SUMIF(Consolidado!$C$3:$C63, $A39, INDEX(Consolidado!$E$3:$P$100, , MATCH(AI$1, Consolidado!$E$2:$P$2, 0))), "")} | AJ39: =IFERROR( LET( hoja, LEFT(AJ$1,3)&"R", fila, MATCH( RIGHT($A39, LEN($A39)-4), INDIRECT(hoja&"!$A:$A"), 0 ), columna, MATCH( "Totales", INDIRECT(hoja&"!$6:$6"), 0 ), valor, INDEX( INDIRECT(hoja&"!$A:$ZZ"), fila, columna ), IF(valor="-", "", valor) ), "") | AK39: =AI39-AJ39 -> 0 | AL39: {=IFERROR(SUMIF(Consolidado!$C$3:$C63, $A39, INDEX(Consolidado!$E$3:$P$100, , MATCH(AL$1, Consolidado!$E$2:$P$2, 0))), "")} | AM39: =IFERROR( LET( hoja, LEFT(AM$1,3)&"R", fila, MATCH( RIGHT($A39, LEN($A39)-4), INDIRECT(hoja&"!$A:$A"), 0 ), columna, MATCH( "Totales", INDIRECT(hoja&"!$6:$6"), 0 ), valor, INDEX( INDIRECT(hoja&"!$A:$ZZ"), fila, columna ), IF(valor="-", "", valor) ), "") | AN39: =AL39-AM39 -> 0
A40: =Menus!B33 -> B30 Artículos de Limpieza | B40: =SUM(IF(MONTH(TODAY())>1,E40,0), IF(MONTH(TODAY())>2,H40,0), IF(MONTH(TODAY())>3,K40,0), IF(MONTH(TODAY())>4,N40,0), IF(MONTH(TODAY())>5,Q40,0), IF(MONTH(TODAY())>6,T40,0), IF(MONTH(TODAY())>7,W40,0), IF(MONTH(TODAY())>8,Z40,0), IF(MONTH(TODAY())>9,AC40,0), IF(MONTH(TODAY())>10,AF40,0), IF(MONTH(TODAY())>11,AI40,0), IF(MONTH(TODAY())>12,AL40,0)) -> 0 | C40: =SUM(IF(MONTH(TODAY())>1,F40,0), IF(MONTH(TODAY())>2,I40,0), IF(MONTH(TODAY())>3,L40,0), IF(MONTH(TODAY())>4,O40,0), IF(MONTH(TODAY())>5,R40,0), IF(MONTH(TODAY())>6,U40,0), IF(MONTH(TODAY())>7,X40,0), IF(MONTH(TODAY())>8,AA40,0), IF(MONTH(TODAY())>9,AD40,0), IF(MONTH(TODAY())>10,AG40,0), IF(MONTH(TODAY())>11,AJ40,0), IF(MONTH(TODAY())>12,AM40,0)) -> 0 | D40: =B40-C40 -> 0 | E40: {=IFERROR(SUMIF(Consolidado!$C$3:$C63, $A40, INDEX(Consolidado!$E$3:$P$100, , MATCH(E$1, Consolidado!$E$2:$P$2, 0))), "")} | F40: =IFERROR( LET( hoja, LEFT(F$1,3)&"R", fila, MATCH( RIGHT($A40, LEN($A40)-4), INDIRECT(hoja&"!$A:$A"), 0 ), columna, MATCH( "Totales", INDIRECT(hoja&"!$6:$6"), 0 ), valor, INDEX( INDIRECT(hoja&"!$A:$ZZ"), fila, columna ), IF(valor="-", "", valor) ), "") | G40: =E40-F40 -> 0 | H40: {=IFERROR(SUMIF(Consolidado!$C$3:$C63, $A40, INDEX(Consolidado!$E$3:$P$100, , MATCH(H$1, Consolidado!$E$2:$P$2, 0))), "")} | I40: =IFERROR( LET( hoja, LEFT(I$1,3)&"R", fila, MATCH( RIGHT($A40, LEN($A40)-4), INDIRECT(hoja&"!$A:$A"), 0 ), columna, MATCH( "Totales", INDIRECT(hoja&"!$6:$6"), 0 ), valor, INDEX( INDIRECT(hoja&"!$A:$ZZ"), fila, columna ), IF(valor="-", "", valor) ), "") | J40: =H40-I40 -> 0 | K40: {=IFERROR(SUMIF(Consolidado!$C$3:$C63, $A40, INDEX(Consolidado!$E$3:$P$100, , MATCH(K$1, Consolidado!$E$2:$P$2, 0))), "")} | L40: =IFERROR( LET( hoja, LEFT(L$1,3)&"R", fila, MATCH( RIGHT($A40, LEN($A40)-4), INDIRECT(hoja&"!$A:$A"), 0 ), columna, MATCH( "Totales", INDIRECT(hoja&"!$6:$6"), 0 ), valor, INDEX( INDIRECT(hoja&"!$A:$ZZ"), fila, columna ), IF(valor="-", "", valor) ), "") | M40: =K40-L40 -> 0 | N40: {=IFERROR(SUMIF(Consolidado!$C$3:$C63, $A40, INDEX(Consolidado!$E$3:$P$100, , MATCH(N$1, Consolidado!$E$2:$P$2, 0))), "")} | O40: =IFERROR( LET( hoja, LEFT(O$1,3)&"R", fila, MATCH( RIGHT($A40, LEN($A40)-4), INDIRECT(hoja&"!$A:$A"), 0 ), columna, MATCH( "Totales", INDIRECT(hoja&"!$6:$6"), 0 ), valor, INDEX( INDIRECT(hoja&"!$A:$ZZ"), fila, columna ), IF(valor="-", "", valor) ), "") | P40: =N40-O40 -> 0 | Q40: {=IFERROR(SUMIF(Consolidado!$C$3:$C63, $A40, INDEX(Consolidado!$E$3:$P$100, , MATCH(Q$1, Consolidado!$E$2:$P$2, 0))), "")} | R40: =IFERROR( LET( hoja, LEFT(R$1,3)&"R", fila, MATCH( RIGHT($A40, LEN($A40)-4), INDIRECT(hoja&"!$A:$A"), 0 ), columna, MATCH( "Totales", INDIRECT(hoja&"!$6:$6"), 0 ), valor, INDEX( INDIRECT(hoja&"!$A:$ZZ"), fila, columna ), IF(valor="-", "", valor) ), "") | S40: =Q40-R40 -> 0 | T40: {=IFERROR(SUMIF(Consolidado!$C$3:$C63, $A40, INDEX(Consolidado!$E$3:$P$100, , MATCH(T$1, Consolidado!$E$2:$P$2, 0))), "")} | U40: =IFERROR( LET( hoja, LEFT(U$1,3)&"R", fila, MATCH( RIGHT($A40, LEN($A40)-4), INDIRECT(hoja&"!$A:$A"), 0 ), columna, MATCH( "Totales", INDIRECT(hoja&"!$6:$6"), 0 ), valor, INDEX( INDIRECT(hoja&"!$A:$ZZ"), fila, columna ), IF(valor="-", "", valor) ), "") | V40: =T40-U40 -> 0 | W40: {=IFERROR(SUMIF(Consolidado!$C$3:$C63, $A40, INDEX(Consolidado!$E$3:$P$100, , MATCH(W$1, Consolidado!$E$2:$P$2, 0))), "")} | X40: =IFERROR( LET( hoja, LEFT(X$1,3)&"R", fila, MATCH( RIGHT($A40, LEN($A40)-4), INDIRECT(hoja&"!$A:$A"), 0 ), columna, MATCH( "Totales", INDIRECT(hoja&"!$6:$6"), 0 ), valor, INDEX( INDIRECT(hoja&"!$A:$ZZ"), fila, columna ), IF(valor="-", "", valor) ), "") | Y40: =W40-X40 -> 0 | Z40: {=IFERROR(SUMIF(Consolidado!$C$3:$C63, $A40, INDEX(Consolidado!$E$3:$P$100, , MATCH(Z$1, Consolidado!$E$2:$P$2, 0))), "")} | AA40: =IFERROR( LET( hoja, LEFT(AA$1,3)&"R", fila, MATCH( RIGHT($A40, LEN($A40)-4), INDIRECT(hoja&"!$A:$A"), 0 ), columna, MATCH( "Totales", INDIRECT(hoja&"!$6:$6"), 0 ), valor, INDEX( INDIRECT(hoja&"!$A:$ZZ"), fila, columna ), IF(valor="-", "", valor) ), "") | AB40: =Z40-AA40 -> 0 | AC40: {=IFERROR(SUMIF(Consolidado!$C$3:$C63, $A40, INDEX(Consolidado!$E$3:$P$100, , MATCH(AC$1, Consolidado!$E$2:$P$2, 0))), "")} | AD40: =IFERROR( LET( hoja, LEFT(AD$1,3)&"R", fila, MATCH( RIGHT($A40, LEN($A40)-4), INDIRECT(hoja&"!$A:$A"), 0 ), columna, MATCH( "Totales", INDIRECT(hoja&"!$6:$6"), 0 ), valor, INDEX( INDIRECT(hoja&"!$A:$ZZ"), fila, columna ), IF(valor="-", "", valor) ), "") | AE40: =AC40-AD40 -> 0 | AF40: {=IFERROR(SUMIF(Consolidado!$C$3:$C63, $A40, INDEX(Consolidado!$E$3:$P$100, , MATCH(AF$1, Consolidado!$E$2:$P$2, 0))), "")} | AG40: =IFERROR( LET( hoja, LEFT(AG$1,3)&"R", fila, MATCH( RIGHT($A40, LEN($A40)-4), INDIRECT(hoja&"!$A:$A"), 0 ), columna, MATCH( "Totales", INDIRECT(hoja&"!$6:$6"), 0 ), valor, INDEX( INDIRECT(hoja&"!$A:$ZZ"), fila, columna ), IF(valor="-", "", valor) ), "") | AH40: =AF40-AG40 -> 0 | AI40: {=IFERROR(SUMIF(Consolidado!$C$3:$C63, $A40, INDEX(Consolidado!$E$3:$P$100, , MATCH(AI$1, Consolidado!$E$2:$P$2, 0))), "")} | AJ40: =IFERROR( LET( hoja, LEFT(AJ$1,3)&"R", fila, MATCH( RIGHT($A40, LEN($A40)-4), INDIRECT(hoja&"!$A:$A"), 0 ), columna, MATCH( "Totales", INDIRECT(hoja&"!$6:$6"), 0 ), valor, INDEX( INDIRECT(hoja&"!$A:$ZZ"), fila, columna ), IF(valor="-", "", valor) ), "") | AK40: =AI40-AJ40 -> 0 | AL40: {=IFERROR(SUMIF(Consolidado!$C$3:$C63, $A40, INDEX(Consolidado!$E$3:$P$100, , MATCH(AL$1, Consolidado!$E$2:$P$2, 0))), "")} | AM40: =IFERROR( LET( hoja, LEFT(AM$1,3)&"R", fila, MATCH( RIGHT($A40, LEN($A40)-4), INDIRECT(hoja&"!$A:$A"), 0 ), columna, MATCH( "Totales", INDIRECT(hoja&"!$6:$6"), 0 ), valor, INDEX( INDIRECT(hoja&"!$A:$ZZ"), fila, columna ), IF(valor="-", "", valor) ), "") | AN40: =AL40-AM40 -> 0
A41: =Menus!B34 -> B31 No deducibles | B41: =SUM(IF(MONTH(TODAY())>1,E41,0), IF(MONTH(TODAY())>2,H41,0), IF(MONTH(TODAY())>3,K41,0), IF(MONTH(TODAY())>4,N41,0), IF(MONTH(TODAY())>5,Q41,0), IF(MONTH(TODAY())>6,T41,0), IF(MONTH(TODAY())>7,W41,0), IF(MONTH(TODAY())>8,Z41,0), IF(MONTH(TODAY())>9,AC41,0), IF(MONTH(TODAY())>10,AF41,0), IF(MONTH(TODAY())>11,AI41,0), IF(MONTH(TODAY())>12,AL41,0)) -> 0 | C41: =SUM(IF(MONTH(TODAY())>1,F41,0), IF(MONTH(TODAY())>2,I41,0), IF(MONTH(TODAY())>3,L41,0), IF(MONTH(TODAY())>4,O41,0), IF(MONTH(TODAY())>5,R41,0), IF(MONTH(TODAY())>6,U41,0), IF(MONTH(TODAY())>7,X41,0), IF(MONTH(TODAY())>8,AA41,0), IF(MONTH(TODAY())>9,AD41,0), IF(MONTH(TODAY())>10,AG41,0), IF(MONTH(TODAY())>11,AJ41,0), IF(MONTH(TODAY())>12,AM41,0)) -> 0 | D41: =B41-C41 -> 0 | E41: {=IFERROR(SUMIF(Consolidado!$C$3:$C63, $A41, INDEX(Consolidado!$E$3:$P$100, , MATCH(E$1, Consolidado!$E$2:$P$2, 0))), "")} | F41: =IFERROR( LET( hoja, LEFT(F$1,3)&"R", fila, MATCH( RIGHT($A41, LEN($A41)-4), INDIRECT(hoja&"!$A:$A"), 0 ), columna, MATCH( "Totales", INDIRECT(hoja&"!$6:$6"), 0 ), valor, INDEX( INDIRECT(hoja&"!$A:$ZZ"), fila, columna ), IF(valor="-", "", valor) ), "") | G41: =E41-F41 -> 0 | H41: {=IFERROR(SUMIF(Consolidado!$C$3:$C63, $A41, INDEX(Consolidado!$E$3:$P$100, , MATCH(H$1, Consolidado!$E$2:$P$2, 0))), "")} | I41: =IFERROR( LET( hoja, LEFT(I$1,3)&"R", fila, MATCH( RIGHT($A41, LEN($A41)-4), INDIRECT(hoja&"!$A:$A"), 0 ), columna, MATCH( "Totales", INDIRECT(hoja&"!$6:$6"), 0 ), valor, INDEX( INDIRECT(hoja&"!$A:$ZZ"), fila, columna ), IF(valor="-", "", valor) ), "") | J41: =H41-I41 -> 0 | K41: {=IFERROR(SUMIF(Consolidado!$C$3:$C63, $A41, INDEX(Consolidado!$E$3:$P$100, , MATCH(K$1, Consolidado!$E$2:$P$2, 0))), "")} | L41: =IFERROR( LET( hoja, LEFT(L$1,3)&"R", fila, MATCH( RIGHT($A41, LEN($A41)-4), INDIRECT(hoja&"!$A:$A"), 0 ), columna, MATCH( "Totales", INDIRECT(hoja&"!$6:$6"), 0 ), valor, INDEX( INDIRECT(hoja&"!$A:$ZZ"), fila, columna ), IF(valor="-", "", valor) ), "") | M41: =K41-L41 -> 0 | N41: {=IFERROR(SUMIF(Consolidado!$C$3:$C63, $A41, INDEX(Consolidado!$E$3:$P$100, , MATCH(N$1, Consolidado!$E$2:$P$2, 0))), "")} | O41: =IFERROR( LET( hoja, LEFT(O$1,3)&"R", fila, MATCH( RIGHT($A41, LEN($A41)-4), INDIRECT(hoja&"!$A:$A"), 0 ), columna, MATCH( "Totales", INDIRECT(hoja&"!$6:$6"), 0 ), valor, INDEX( INDIRECT(hoja&"!$A:$ZZ"), fila, columna ), IF(valor="-", "", valor) ), "") | P41: =N41-O41 -> 0 | Q41: {=IFERROR(SUMIF(Consolidado!$C$3:$C63, $A41, INDEX(Consolidado!$E$3:$P$100, , MATCH(Q$1, Consolidado!$E$2:$P$2, 0))), "")} | R41: =IFERROR( LET( hoja, LEFT(R$1,3)&"R", fila, MATCH( RIGHT($A41, LEN($A41)-4), INDIRECT(hoja&"!$A:$A"), 0 ), columna, MATCH( "Totales", INDIRECT(hoja&"!$6:$6"), 0 ), valor, INDEX( INDIRECT(hoja&"!$A:$ZZ"), fila, columna ), IF(valor="-", "", valor) ), "") | S41: =Q41-R41 -> 0 | T41: {=IFERROR(SUMIF(Consolidado!$C$3:$C63, $A41, INDEX(Consolidado!$E$3:$P$100, , MATCH(T$1, Consolidado!$E$2:$P$2, 0))), "")} | U41: =IFERROR( LET( hoja, LEFT(U$1,3)&"R", fila, MATCH( RIGHT($A41, LEN($A41)-4), INDIRECT(hoja&"!$A:$A"), 0 ), columna, MATCH( "Totales", INDIRECT(hoja&"!$6:$6"), 0 ), valor, INDEX( INDIRECT(hoja&"!$A:$ZZ"), fila, columna ), IF(valor="-", "", valor) ), "") | V41: =T41-U41 -> 0 | W41: {=IFERROR(SUMIF(Consolidado!$C$3:$C63, $A41, INDEX(Consolidado!$E$3:$P$100, , MATCH(W$1, Consolidado!$E$2:$P$2, 0))), "")} | X41: =IFERROR( LET( hoja, LEFT(X$1,3)&"R", fila, MATCH( RIGHT($A41, LEN($A41)-4), INDIRECT(hoja&"!$A:$A"), 0 ), columna, MATCH( "Totales", INDIRECT(hoja&"!$6:$6"), 0 ), valor, INDEX( INDIRECT(hoja&"!$A:$ZZ"), fila, columna ), IF(valor="-", "", valor) ), "") | Y41: =W41-X41 -> 0 | Z41: {=IFERROR(SUMIF(Consolidado!$C$3:$C63, $A41, INDEX(Consolidado!$E$3:$P$100, , MATCH(Z$1, Consolidado!$E$2:$P$2, 0))), "")} | AA41: =IFERROR( LET( hoja, LEFT(AA$1,3)&"R", fila, MATCH( RIGHT($A41, LEN($A41)-4), INDIRECT(hoja&"!$A:$A"), 0 ), columna, MATCH( "Totales", INDIRECT(hoja&"!$6:$6"), 0 ), valor, INDEX( INDIRECT(hoja&"!$A:$ZZ"), fila, columna ), IF(valor="-", "", valor) ), "") | AB41: =Z41-AA41 -> 0 | AC41: {=IFERROR(SUMIF(Consolidado!$C$3:$C63, $A41, INDEX(Consolidado!$E$3:$P$100, , MATCH(AC$1, Consolidado!$E$2:$P$2, 0))), "")} | AD41: =IFERROR( LET( hoja, LEFT(AD$1,3)&"R", fila, MATCH( RIGHT($A41, LEN($A41)-4), INDIRECT(hoja&"!$A:$A"), 0 ), columna, MATCH( "Totales", INDIRECT(hoja&"!$6:$6"), 0 ), valor, INDEX( INDIRECT(hoja&"!$A:$ZZ"), fila, columna ), IF(valor="-", "", valor) ), "") | AE41: =AC41-AD41 -> 0 | AF41: {=IFERROR(SUMIF(Consolidado!$C$3:$C63, $A41, INDEX(Consolidado!$E$3:$P$100, , MATCH(AF$1, Consolidado!$E$2:$P$2, 0))), "")} | AG41: =IFERROR( LET( hoja, LEFT(AG$1,3)&"R", fila, MATCH( RIGHT($A41, LEN($A41)-4), INDIRECT(hoja&"!$A:$A"), 0 ), columna, MATCH( "Totales", INDIRECT(hoja&"!$6:$6"), 0 ), valor, INDEX( INDIRECT(hoja&"!$A:$ZZ"), fila, columna ), IF(valor="-", "", valor) ), "") | AH41: =AF41-AG41 -> 0 | AI41: {=IFERROR(SUMIF(Consolidado!$C$3:$C63, $A41, INDEX(Consolidado!$E$3:$P$100, , MATCH(AI$1, Consolidado!$E$2:$P$2, 0))), "")} | AJ41: =IFERROR( LET( hoja, LEFT(AJ$1,3)&"R", fila, MATCH( RIGHT($A41, LEN($A41)-4), INDIRECT(hoja&"!$A:$A"), 0 ), columna, MATCH( "Totales", INDIRECT(hoja&"!$6:$6"), 0 ), valor, INDEX( INDIRECT(hoja&"!$A:$ZZ"), fila, columna ), IF(valor="-", "", valor) ), "") | AK41: =AI41-AJ41 -> 0 | AL41: {=IFERROR(SUMIF(Consolidado!$C$3:$C63, $A41, INDEX(Consolidado!$E$3:$P$100, , MATCH(AL$1, Consolidado!$E$2:$P$2, 0))), "")} | AM41: =IFERROR( LET( hoja, LEFT(AM$1,3)&"R", fila, MATCH( RIGHT($A41, LEN($A41)-4), INDIRECT(hoja&"!$A:$A"), 0 ), columna, MATCH( "Totales", INDIRECT(hoja&"!$6:$6"), 0 ), valor, INDEX( INDIRECT(hoja&"!$A:$ZZ"), fila, columna ), IF(valor="-", "", valor) ), "") | AN41: =AL41-AM41 -> 0
