Workbook

Sheet Acumulado
A1: Sigmaseg S.A. de C.V. | B1: Anual R | C1: Enero | D1: Febrero | E1: Marzo | F1: Abril | G1: Mayo | H1: Junio | I1: Julio | J1: Agosto | K1: Septiembre | L1: Octubre | M1: Noviembre | N1: Diciembre
A3: Utilidad Bruta | B3: =B5-B10+B49-B54 -> 0 | C3: =C5-C10+C49-C54 -> 3185663.1 | D3: =D5-D10+D49-D54 -> 3145495.9 | E3: =E5-E10+E49-E54 -> 3195106.8 | F3: =F5-F10+F49-F54 -> 3039340 | G3: =G5-G10+G49-G54 -> 3048710.1 | H3: =H5-H10+H49-H54 -> 3046771.3 | I3: =I5-I10+I49-I54 -> 3012037.1 | ... N3: =N5-N10+N49-N54 -> 0
A5: Total de Ingresos | B5: =SUM(B6:B8) -> 0 | C5: =SUM(C6:C8) -> 3185663.1 | D5: =SUM(D6:D8) -> 3145495.9 | E5: =SUM(E6:E8) -> 3195106.8 | F5: =SUM(F6:F8) -> 3039340 | G5: =SUM(G6:G8) -> 3048710.1 | H5: =SUM(H6:H8) -> 3046771.3 | I5: =SUM(I6:I8) -> 3012037.1 | ... N5: =SUM(N6:N8) -> 0
A6: A01 Seguridad | B6: =SUM(IF(MONTH(TODAY())>1,C6,0), IF(MONTH(TODAY())>2,D6,0), IF(MONTH(TODAY())>3,E6,0), IF(MONTH(TODAY())>4,F6,0), IF(MONTH(TODAY())>5,G6,0), IF(MONTH(TODAY())>6,H6,0), IF(MONTH(TODAY())>7,I6,0), IF(MONTH(TODAY())>8,J6,0), IF(MONTH(TODAY())>9,K6,0), IF(MONTH(TODAY())>10,L6,0), IF(MONTH(TODAY())>11,M6,0), IF(MONTH(TODAY())>12,N6,0)) -> 0 | C6: =IFERROR( LET( hoja, LEFT(C$1,3)&"R", fila, MATCH( RIGHT($A6, LEN($A6)-4), INDIRECT(hoja&"!$A:$A"), 0 ), columna, MATCH( "Totales", INDIRECT(hoja&"!$6:$6"), 0 ), valor, INDEX( INDIRECT(hoja&"!$A:$ZZ"), fila, columna ), IF(valor="-", "", valor) ), "") -> 3185663.1 | D6: =IFERROR( LET( hoja, LEFT(D$1,3)&"R", fila, MATCH( RIGHT($A6, LEN($A6)-4), INDIRECT(hoja&"!$A:$A"), 0 ), columna, MATCH( "Totales", INDIRECT(hoja&"!$6:$6"), 0 ), valor, INDEX( INDIRECT(hoja&"!$A:$ZZ"), fila, columna ), IF(valor="-", "", valor) ), "") -> 3145495.9 | E6: =IFERROR( LET( hoja, LEFT(E$1,3)&"R", fila, MATCH( RIGHT($A6, LEN($A6)-4), INDIRECT(hoja&"!$A:$A"), 0 ), columna, MATCH( "Totales", INDIRECT(hoja&"!$6:$6"), 0 ), valor, INDEX( INDIRECT(hoja&"!$A:$ZZ"), fila, columna ), IF(valor="-", "", valor) ), "") -> 3173506.8 | F6: =IFERROR( LET( hoja, LEFT(F$1,3)&"R", fila, MATCH( RIGHT($A6, LEN($A6)-4), INDIRECT(hoja&"!$A:$A"), 0 ), columna, MATCH( "Totales", INDIRECT(hoja&"!$6:$6"), 0 ), valor, INDEX( INDIRECT(hoja&"!$A:$ZZ"), fila, columna ), IF(valor="-", "", valor) ), "") -> 3017740 | G6: =IFERROR( LET( hoja, LEFT(G$1,3)&"R", fila, MATCH( RIGHT($A6, LEN($A6)-4), INDIRECT(hoja&"!$A:$A"), 0 ), columna, MATCH( "Totales", INDIRECT(hoja&"!$6:$6"), 0 ), valor, INDEX( INDIRECT(hoja&"!$A:$ZZ"), fila, columna ), IF(valor="-", "", valor) ), "") -> 3027110.1 | H6: =IFERROR( LET( hoja, LEFT(H$1,3)&"R", fila, MATCH( RIGHT($A6, LEN($A6)-4), INDIRECT(hoja&"!$A:$A"), 0 ), columna, MATCH( "Totales", INDIRECT(hoja&"!$6:$6"), 0 ), valor, INDEX( INDIRECT(hoja&"!$A:$ZZ"), fila, columna ), IF(valor="-", "", valor) ), "") -> 3025171.3 | I6: =IFERROR( LET( hoja, LEFT(I$1,3)&"R", fila, MATCH( RIGHT($A6, LEN($A6)-4), INDIRECT(hoja&"!$A:$A"), 0 ), columna, MATCH( "Totales", INDIRECT(hoja&"!$6:$6"), 0 ), valor, INDEX( INDIRECT(hoja&"!$A:$ZZ"), fila, columna ), IF(valor="-", "", valor) ), "") -> 2990437.1 | J6: =IFERROR( LET( hoja, LEFT(J$1,3)&"R", fila, MATCH( RIGHT($A6, LEN($A6)-4), INDIRECT(hoja&"!$A:$A"), 0 ), columna, MATCH( "Totales", INDIRECT(hoja&"!$6:$6"), 0 ), valor, INDEX( INDIRECT(hoja&"!$A:$ZZ"), fila, columna ), IF(valor="-", "", valor) ), "") | ... N6: =IFERROR( LET( hoja, LEFT(N$1,3)&"R", fila, MATCH( RIGHT($A6, LEN($A6)-4), INDIRECT(hoja&"!$A:$A"), 0 ), columna, MATCH( "Totales", INDIRECT(hoja&"!$6:$6"), 0 ), valor, INDEX( INDIRECT(hoja&"!$A:$ZZ"), fila, columna ), IF(valor="-", "", valor) ), "")
A7: A02 Monitoreo | B7: =SUM(IF(MONTH(TODAY())>1,C7,0), IF(MONTH(TODAY())>2,D7,0), IF(MONTH(TODAY())>3,E7,0), IF(MONTH(TODAY())>4,F7,0), IF(MONTH(TODAY())>5,G7,0), IF(MONTH(TODAY())>6,H7,0), IF(MONTH(TODAY())>7,I7,0), IF(MONTH(TODAY())>8,J7,0), IF(MONTH(TODAY())>9,K7,0), IF(MONTH(TODAY())>10,L7,0), IF(MONTH(TODAY())>11,M7,0), IF(MONTH(TODAY())>12,N7,0)) -> 0 | C7: =IFERROR( LET( hoja, LEFT(C$1,3)&"R", fila, MATCH( RIGHT($A7, LEN($A7)-4), INDIRECT(hoja&"!$A:$A"), 0 ), columna, MATCH( "Totales", INDIRECT(hoja&"!$6:$6"), 0 ), valor, INDEX( INDIRECT(hoja&"!$A:$ZZ"), fila, columna ), IF(valor="-", "", valor) ), "") | D7: =IFERROR( LET( hoja, LEFT(D$1,3)&"R", fila, MATCH( RIGHT($A7, LEN($A7)-4), INDIRECT(hoja&"!$A:$A"), 0 ), columna, MATCH( "Totales", INDIRECT(hoja&"!$6:$6"), 0 ), valor, INDEX( INDIRECT(hoja&"!$A:$ZZ"), fila, columna ), IF(valor="-", "", valor) ), "") | E7: =IFERROR( LET( hoja, LEFT(E$1,3)&"R", fila, MATCH( RIGHT($A7, LEN($A7)-4), INDIRECT(hoja&"!$A:$A"), 0 ), columna, MATCH( "Totales", INDIRECT(hoja&"!$6:$6"), 0 ), valor, INDEX( INDIRECT(hoja&"!$A:$ZZ"), fila, columna ), IF(valor="-", "", valor) ), "") -> 21600 | F7: =IFERROR( LET( hoja, LEFT(F$1,3)&"R", fila, MATCH( RIGHT($A7, LEN($A7)-4), INDIRECT(hoja&"!$A:$A"), 0 ), columna, MATCH( "Totales", INDIRECT(hoja&"!$6:$6"), 0 ), valor, INDEX( INDIRECT(hoja&"!$A:$ZZ"), fila, columna ), IF(valor="-", "", valor) ), "") -> 21600 | G7: =IFERROR( LET( hoja, LEFT(G$1,3)&"R", fila, MATCH( RIGHT($A7, LEN($A7)-4), INDIRECT(hoja&"!$A:$A"), 0 ), columna, MATCH( "Totales", INDIRECT(hoja&"!$6:$6"), 0 ), valor, INDEX( INDIRECT(hoja&"!$A:$ZZ"), fila, columna ), IF(valor="-", "", valor) ), "") -> 21600 | H7: =IFERROR( LET( hoja, LEFT(H$1,3)&"R", fila, MATCH( RIGHT($A7, LEN($A7)-4), INDIRECT(hoja&"!$A:$A"), 0 ), columna, MATCH( "Totales", INDIRECT(hoja&"!$6:$6"), 0 ), valor, INDEX( INDIRECT(hoja&"!$A:$ZZ"), fila, columna ), IF(valor="-", "", valor) ), "") -> 21600 | I7: =IFERROR( LET( hoja, LEFT(I$1,3)&"R", fila, MATCH( RIGHT($A7, LEN($A7)-4), INDIRECT(hoja&"!$A:$A"), 0 ), columna, MATCH( "Totales", INDIRECT(hoja&"!$6:$6"), 0 ), valor, INDEX( INDIRECT(hoja&"!$A:$ZZ"), fila, columna ), IF(valor="-", "", valor) ), "") -> 21600 | J7: =IFERROR( LET( hoja, LEFT(J$1,3)&"R", fila, MATCH( RIGHT($A7, LEN($A7)-4), INDIRECT(hoja&"!$A:$A"), 0 ), columna, MATCH( "Totales", INDIRECT(hoja&"!$6:$6"), 0 ), valor, INDEX( INDIRECT(hoja&"!$A:$ZZ"), fila, columna ), IF(valor="-", "", valor) ), "") | ... N7: =IFERROR( LET( hoja, LEFT(N$1,3)&"R", fila, MATCH( RIGHT($A7, LEN($A7)-4), INDIRECT(hoja&"!$A:$A"), 0 ), columna, MATCH( "Totales", INDIRECT(hoja&"!$6:$6"), 0 ), valor, INDEX( INDIRECT(hoja&"!$A:$ZZ"), fila, columna ), IF(valor="-", "", valor) ), "")
B8: =SUM(IF(MONTH(TODAY())>1,C8,0), IF(MONTH(TODAY())>2,D8,0), IF(MONTH(TODAY())>3,E8,0), IF(MONTH(TODAY())>4,F8,0), IF(MONTH(TODAY())>5,G8,0), IF(MONTH(TODAY())>6,H8,0), IF(MONTH(TODAY())>7,I8,0), IF(MONTH(TODAY())>8,J8,0), IF(MONTH(TODAY())>9,K8,0), IF(MONTH(TODAY())>10,L8,0), IF(MONTH(TODAY())>11,M8,0), IF(MONTH(TODAY())>12,N8,0)) -> 0 | C8: =IFERROR( LET( hoja, LEFT(C$1,3)&"R", fila, MATCH( RIGHT($A8, LEN($A8)-4), INDIRECT(hoja&"!$A:$A"), 0 ), columna, MATCH( "Totales", INDIRECT(hoja&"!$6:$6"), 0 ), valor, INDEX( INDIRECT(hoja&"!$A:$ZZ"), fila, columna ), IF(valor="-", "", valor) ), "") | D8: =IFERROR( LET( hoja, LEFT(D$1,3)&"R", fila, MATCH( RIGHT($A8, LEN($A8)-4), INDIRECT(hoja&"!$A:$A"), 0 ), columna, MATCH( "Totales", INDIRECT(hoja&"!$6:$6"), 0 ), valor, INDEX( INDIRECT(hoja&"!$A:$ZZ"), fila, columna ), IF(valor="-", "", valor) ), "") | E8: =IFERROR( LET( hoja, LEFT(E$1,3)&"R", fila, MATCH( RIGHT($A8, LEN($A8)-4), INDIRECT(hoja&"!$A:$A"), 0 ), columna, MATCH( "Totales", INDIRECT(hoja&"!$6:$6"), 0 ), valor, INDEX( INDIRECT(hoja&"!$A:$ZZ"), fila, columna ), IF(valor="-", "", valor) ), "") | F8: =IFERROR( LET( hoja, LEFT(F$1,3)&"R", fila, MATCH( RIGHT($A8, LEN($A8)-4), INDIRECT(hoja&"!$A:$A"), 0 ), columna, MATCH( "Totales", INDIRECT(hoja&"!$6:$6"), 0 ), valor, INDEX( INDIRECT(hoja&"!$A:$ZZ"), fila, columna ), IF(valor="-", "", valor) ), "") | G8: =IFERROR( LET( hoja, LEFT(G$1,3)&"R", fila, MATCH( RIGHT($A8, LEN($A8)-4), INDIRECT(hoja&"!$A:$A"), 0 ), columna, MATCH( "Totales", INDIRECT(hoja&"!$6:$6"), 0 ), valor, INDEX( INDIRECT(hoja&"!$A:$ZZ"), fila, columna ), IF(valor="-", "", valor) ), "") | H8: =IFERROR( LET( hoja, LEFT(H$1,3)&"R", fila, MATCH( RIGHT($A8, LEN($A8)-4), INDIRECT(hoja&"!$A:$A"), 0 ), columna, MATCH( "Totales", INDIRECT(hoja&"!$6:$6"), 0 ), valor, INDEX( INDIRECT(hoja&"!$A:$ZZ"), fila, columna ), IF(valor="-", "", valor) ), "") | I8: =IFERROR( LET( hoja, LEFT(I$1,3)&"R", fila, MATCH( RIGHT($A8, LEN($A8)-4), INDIRECT(hoja&"!$A:$A"), 0 ), columna, MATCH( "Totales", INDIRECT(hoja&"!$6:$6"), 0 ), valor, INDEX( INDIRECT(hoja&"!$A:$ZZ"), fila, columna ), IF(valor="-", "", valor) ), "") | J8: =IFERROR( LET( hoja, LEFT(J$1,3)&"R", fila, MATCH( RIGHT($A8, LEN($A8)-4), INDIRECT(hoja&"!$A:$A"), 0 ), columna, MATCH( "Totales", INDIRECT(hoja&"!$6:$6"), 0 ), valor, INDEX( INDIRECT(hoja&"!$A:$ZZ"), fila, columna ), IF(valor="-", "", valor) ), "") | ... N8: =IFERROR( LET( hoja, LEFT(N$1,3)&"R", fila, MATCH( RIGHT($A8, LEN($A8)-4), INDIRECT(hoja&"!$A:$A"), 0 ), columna, MATCH( "Totales", INDIRECT(hoja&"!$6:$6"), 0 ), valor, INDEX( INDIRECT(hoja&"!$A:$ZZ"), fila, columna ), IF(valor="-", "", valor) ), "")
A10: Total de Egresos | B10: =SUM(B11:B47) -> 0 | C10: =SUM(C11:C47) -> 0 | D10: =SUM(D11:D47) -> 0 | E10: =SUM(E11:E47) -> 0 | F10: =SUM(F11:F47) -> 0 | G10: =SUM(G11:G47) -> 0 | H10: =SUM(H11:H47) -> 0 | I10: =SUM(I11:I47) -> 0 | ... N10: =SUM(N11:N47) -> 0
A11: =Menus!B4 | B11: =SUM(IF(MONTH(TODAY())>1,C11,0), IF(MONTH(TODAY())>2,D11,0), IF(MONTH(TODAY())>3,E11,0), IF(MONTH(TODAY())>4,F11,0), IF(MONTH(TODAY())>5,G11,0), IF(MONTH(TODAY())>6,H11,0), IF(MONTH(TODAY())>7,I11,0), IF(MONTH(TODAY())>8,J11,0), IF(MONTH(TODAY())>9,K11,0), IF(MONTH(TODAY())>10,L11,0), IF(MONTH(TODAY())>11,M11,0), IF(MONTH(TODAY())>12,N11,0)) -> 0 | C11: =IFERROR( LET( hoja, LEFT(C$1,3)&"R", fila, MATCH( RIGHT($A11, LEN($A11)-4), INDIRECT(hoja&"!$A:$A"), 0 ), columna, MATCH( "Totales", INDIRECT(hoja&"!$6:$6"), 0 ), valor, INDEX( INDIRECT(hoja&"!$A:$ZZ"), fila, columna ), IF(valor="-", "", valor) ), "") | D11: =IFERROR( LET( hoja, LEFT(D$1,3)&"R", fila, MATCH( RIGHT($A11, LEN($A11)-4), INDIRECT(hoja&"!$A:$A"), 0 ), columna, MATCH( "Totales", INDIRECT(hoja&"!$6:$6"), 0 ), valor, INDEX( INDIRECT(hoja&"!$A:$ZZ"), fila, columna ), IF(valor="-", "", valor) ), "") | E11: =IFERROR( LET( hoja, LEFT(E$1,3)&"R", fila, MATCH( RIGHT($A11, LEN($A11)-4), INDIRECT(hoja&"!$A:$A"), 0 ), columna, MATCH( "Totales", INDIRECT(hoja&"!$6:$6"), 0 ), valor, INDEX( INDIRECT(hoja&"!$A:$ZZ"), fila, columna ), IF(valor="-", "", valor) ), "") | F11: =IFERROR( LET( hoja, LEFT(F$1,3)&"R", fila, MATCH( RIGHT($A11, LEN($A11)-4), INDIRECT(hoja&"!$A:$A"), 0 ), columna, MATCH( "Totales", INDIRECT(hoja&"!$6:$6"), 0 ), valor, INDEX( INDIRECT(hoja&"!$A:$ZZ"), fila, columna ), IF(valor="-", "", valor) ), "") | G11: =IFERROR( LET( hoja, LEFT(G$1,3)&"R", fila, MATCH( RIGHT($A11, LEN($A11)-4), INDIRECT(hoja&"!$A:$A"), 0 ), columna, MATCH( "Totales", INDIRECT(hoja&"!$6:$6"), 0 ), valor, INDEX( INDIRECT(hoja&"!$A:$ZZ"), fila, columna ), IF(valor="-", "", valor) ), "") | H11: =IFERROR( LET( hoja, LEFT(H$1,3)&"R", fila, MATCH( RIGHT($A11, LEN($A11)-4), INDIRECT(hoja&"!$A:$A"), 0 ), columna, MATCH( "Totales", INDIRECT(hoja&"!$6:$6"), 0 ), valor, INDEX( INDIRECT(hoja&"!$A:$ZZ"), fila, columna ), IF(valor="-", "", valor) ), "") | I11: =IFERROR( LET( hoja, LEFT(I$1,3)&"R", fila, MATCH( RIGHT($A11, LEN($A11)-4), INDIRECT(hoja&"!$A:$A"), 0 ), columna, MATCH( "Totales", INDIRECT(hoja&"!$6:$6"), 0 ), valor, INDEX( INDIRECT(hoja&"!$A:$ZZ"), fila, columna ), IF(valor="-", "", valor) ), "") | J11: =IFERROR( LET( hoja, LEFT(J$1,3)&"R", fila, MATCH( RIGHT($A11, LEN($A11)-4), INDIRECT(hoja&"!$A:$A"), 0 ), columna, MATCH( "Totales", INDIRECT(hoja&"!$6:$6"), 0 ), valor, INDEX( INDIRECT(hoja&"!$A:$ZZ"), fila, columna ), IF(valor="-", "", valor) ), "") | ... N11: =IFERROR( LET( hoja, LEFT(N$1,3)&"R", fila, MATCH( RIGHT($A11, LEN($A11)-4), INDIRECT(hoja&"!$A:$A"), 0 ), columna, MATCH( "Totales", INDIRECT(hoja&"!$6:$6"), 0 ), valor, INDEX( INDIRECT(hoja&"!$A:$ZZ"), fila, columna ), IF(valor="-", "", valor) ), "")
A12: =Menus!B5 | B12: =SUM(IF(MONTH(TODAY())>1,C12,0), IF(MONTH(TODAY())>2,D12,0), IF(MONTH(TODAY())>3,E12,0), IF(MONTH(TODAY())>4,F12,0), IF(MONTH(TODAY())>5,G12,0), IF(MONTH(TODAY())>6,H12,0), IF(MONTH(TODAY())>7,I12,0), IF(MONTH(TODAY())>8,J12,0), IF(MONTH(TODAY())>9,K12,0), IF(MONTH(TODAY())>10,L12,0), IF(MONTH(TODAY())>11,M12,0), IF(MONTH(TODAY())>12,N12,0)) -> 0 | C12: =IFERROR( LET( hoja, LEFT(C$1,3)&"R", fila, MATCH( RIGHT($A12, LEN($A12)-4), INDIRECT(hoja&"!$A:$A"), 0 ), columna, MATCH( "Totales", INDIRECT(hoja&"!$6:$6"), 0 ), valor, INDEX( INDIRECT(hoja&"!$A:$ZZ"), fila, columna ), IF(valor="-", "", valor) ), "") | D12: =IFERROR( LET( hoja, LEFT(D$1,3)&"R", fila, MATCH( RIGHT($A12, LEN($A12)-4), INDIRECT(hoja&"!$A:$A"), 0 ), columna, MATCH( "Totales", INDIRECT(hoja&"!$6:$6"), 0 ), valor, INDEX( INDIRECT(hoja&"!$A:$ZZ"), fila, columna ), IF(valor="-", "", valor) ), "") | E12: =IFERROR( LET( hoja, LEFT(E$1,3)&"R", fila, MATCH( RIGHT($A12, LEN($A12)-4), INDIRECT(hoja&"!$A:$A"), 0 ), columna, MATCH( "Totales", INDIRECT(hoja&"!$6:$6"), 0 ), valor, INDEX( INDIRECT(hoja&"!$A:$ZZ"), fila, columna ), IF(valor="-", "", valor) ), "") | F12: =IFERROR( LET( hoja, LEFT(F$1,3)&"R", fila, MATCH( RIGHT($A12, LEN($A12)-4), INDIRECT(hoja&"!$A:$A"), 0 ), columna, MATCH( "Totales", INDIRECT(hoja&"!$6:$6"), 0 ), valor, INDEX( INDIRECT(hoja&"!$A:$ZZ"), fila, columna ), IF(valor="-", "", valor) ), "") | G12: =IFERROR( LET( hoja, LEFT(G$1,3)&"R", fila, MATCH( RIGHT($A12, LEN($A12)-4), INDIRECT(hoja&"!$A:$A"), 0 ), columna, MATCH( "Totales", INDIRECT(hoja&"!$6:$6"), 0 ), valor, INDEX( INDIRECT(hoja&"!$A:$ZZ"), fila, columna ), IF(valor="-", "", valor) ), "") | H12: =IFERROR( LET( hoja, LEFT(H$1,3)&"R", fila, MATCH( RIGHT($A12, LEN($A12)-4), INDIRECT(hoja&"!$A:$A"), 0 ), columna, MATCH( "Totales", INDIRECT(hoja&"!$6:$6"), 0 ), valor, INDEX( INDIRECT(hoja&"!$A:$ZZ"), fila, columna ), IF(valor="-", "", valor) ), "") | I12: =IFERROR( LET( hoja, LEFT(I$1,3)&"R", fila, MATCH( RIGHT($A12, LEN($A12)-4), INDIRECT(hoja&"!$A:$A"), 0 ), columna, MATCH( "Totales", INDIRECT(hoja&"!$6:$6"), 0 ), valor, INDEX( INDIRECT(hoja&"!$A:$ZZ"), fila, columna ), IF(valor="-", "", valor) ), "") | J12: =IFERROR( LET( hoja, LEFT(J$1,3)&"R", fila, MATCH( RIGHT($A12, LEN($A12)-4), INDIRECT(hoja&"!$A:$A"), 0 ), columna, MATCH( "Totales", INDIRECT(hoja&"!$6:$6"), 0 ), valor, INDEX( INDIRECT(hoja&"!$A:$ZZ"), fila, columna ), IF(valor="-", "", valor) ), "") | ... N12: =IFERROR( LET( hoja, LEFT(N$1,3)&"R", fila, MATCH( RIGHT($A12, LEN($A12)-4), INDIRECT(hoja&"!$A:$A"), 0 ), columna, MATCH( "Totales", INDIRECT(hoja&"!$6:$6"), 0 ), valor, INDEX( INDIRECT(hoja&"!$A:$ZZ"), fila, columna ), IF(valor="-", "", valor) ), "")
A13: =Menus!B6 | B13: =SUM(IF(MONTH(TODAY())>1,C13,0), IF(MONTH(TODAY())>2,D13,0), IF(MONTH(TODAY())>3,E13,0), IF(MONTH(TODAY())>4,F13,0), IF(MONTH(TODAY())>5,G13,0), IF(MONTH(TODAY())>6,H13,0), IF(MONTH(TODAY())>7,I13,0), IF(MONTH(TODAY())>8,J13,0), IF(MONTH(TODAY())>9,K13,0), IF(MONTH(TODAY())>10,L13,0), IF(MONTH(TODAY())>11,M13,0), IF(MONTH(TODAY())>12,N13,0)) -> 0 | C13: =IFERROR( LET( hoja, LEFT(C$1,3)&"R", fila, MATCH( RIGHT($A13, LEN($A13)-4), INDIRECT(hoja&"!$A:$A"), 0 ), columna, MATCH( "Totales", INDIRECT(hoja&"!$6:$6"), 0 ), valor, INDEX( INDIRECT(hoja&"!$A:$ZZ"), fila, columna ), IF(valor="-", "", valor) ), "") | D13: =IFERROR( LET( hoja, LEFT(D$1,3)&"R", fila, MATCH( RIGHT($A13, LEN($A13)-4), INDIRECT(hoja&"!$A:$A"), 0 ), columna, MATCH( "Totales", INDIRECT(hoja&"!$6:$6"), 0 ), valor, INDEX( INDIRECT(hoja&"!$A:$ZZ"), fila, columna ), IF(valor="-", "", valor) ), "") | E13: =IFERROR( LET( hoja, LEFT(E$1,3)&"R", fila, MATCH( RIGHT($A13, LEN($A13)-4), INDIRECT(hoja&"!$A:$A"), 0 ), columna, MATCH( "Totales", INDIRECT(hoja&"!$6:$6"), 0 ), valor, INDEX( INDIRECT(hoja&"!$A:$ZZ"), fila, columna ), IF(valor="-", "", valor) ), "") | F13: =IFERROR( LET( hoja, LEFT(F$1,3)&"R", fila, MATCH( RIGHT($A13, LEN($A13)-4), INDIRECT(hoja&"!$A:$A"), 0 ), columna, MATCH( "Totales", INDIRECT(hoja&"!$6:$6"), 0 ), valor, INDEX( INDIRECT(hoja&"!$A:$ZZ"), fila, columna ), IF(valor="-", "", valor) ), "") | G13: =IFERROR( LET( hoja, LEFT(G$1,3)&"R", fila, MATCH( RIGHT($A13, LEN($A13)-4), INDIRECT(hoja&"!$A:$A"), 0 ), columna, MATCH( "Totales", INDIRECT(hoja&"!$6:$6"), 0 ), valor, INDEX( INDIRECT(hoja&"!$A:$ZZ"), fila, columna ), IF(valor="-", "", valor) ), "") | H13: =IFERROR( LET( hoja, LEFT(H$1,3)&"R", fila, MATCH( RIGHT($A13, LEN($A13)-4), INDIRECT(hoja&"!$A:$A"), 0 ), columna, MATCH( "Totales", INDIRECT(hoja&"!$6:$6"), 0 ), valor, INDEX( INDIRECT(hoja&"!$A:$ZZ"), fila, columna ), IF(valor="-", "", valor) ), "") | I13: =IFERROR( LET( hoja, LEFT(I$1,3)&"R", fila, MATCH( RIGHT($A13, LEN($A13)-4), INDIRECT(hoja&"!$A:$A"), 0 ), columna, MATCH( "Totales", INDIRECT(hoja&"!$6:$6"), 0 ), valor, INDEX( INDIRECT(hoja&"!$A:$ZZ"), fila, columna ), IF(valor="-", "", valor) ), "") | J13: =IFERROR( LET( hoja, LEFT(J$1,3)&"R", fila, MATCH( RIGHT($A13, LEN($A13)-4), INDIRECT(hoja&"!$A:$A"), 0 ), columna, MATCH( "Totales", INDIRECT(hoja&"!$6:$6"), 0 ), valor, INDEX( INDIRECT(hoja&"!$A:$ZZ"), fila, columna ), IF(valor="-", "", valor) ), "") | ... N13: =IFERROR( LET( hoja, LEFT(N$1,3)&"R", fila, MATCH( RIGHT($A13, LEN($A13)-4), INDIRECT(hoja&"!$A:$A"), 0 ), columna, MATCH( "Totales", INDIRECT(hoja&"!$6:$6"), 0 ), valor, INDEX( INDIRECT(hoja&"!$A:$ZZ"), fila, columna ), IF(valor="-", "", valor) ), "")
A14: =Menus!B7 | B14: =SUM(IF(MONTH(TODAY())>1,C14,0), IF(MONTH(TODAY())>2,D14,0), IF(MONTH(TODAY())>3,E14,0), IF(MONTH(TODAY())>4,F14,0), IF(MONTH(TODAY())>5,G14,0), IF(MONTH(TODAY())>6,H14,0), IF(MONTH(TODAY())>7,I14,0), IF(MONTH(TODAY())>8,J14,0), IF(MONTH(TODAY())>9,K14,0), IF(MONTH(TODAY())>10,L14,0), IF(MONTH(TODAY())>11,M14,0), IF(MONTH(TODAY())>12,N14,0)) -> 0 | C14: =IFERROR( LET( hoja, LEFT(C$1,3)&"R", fila, MATCH( RIGHT($A14, LEN($A14)-4), INDIRECT(hoja&"!$A:$A"), 0 ), columna, MATCH( "Totales", INDIRECT(hoja&"!$6:$6"), 0 ), valor, INDEX( INDIRECT(hoja&"!$A:$ZZ"), fila, columna ), IF(valor="-", "", valor) ), "") | D14: =IFERROR( LET( hoja, LEFT(D$1,3)&"R", fila, MATCH( RIGHT($A14, LEN($A14)-4), INDIRECT(hoja&"!$A:$A"), 0 ), columna, MATCH( "Totales", INDIRECT(hoja&"!$6:$6"), 0 ), valor, INDEX( INDIRECT(hoja&"!$A:$ZZ"), fila, columna ), IF(valor="-", "", valor) ), "") | E14: =IFERROR( LET( hoja, LEFT(E$1,3)&"R", fila, MATCH( RIGHT($A14, LEN($A14)-4), INDIRECT(hoja&"!$A:$A"), 0 ), columna, MATCH( "Totales", INDIRECT(hoja&"!$6:$6"), 0 ), valor, INDEX( INDIRECT(hoja&"!$A:$ZZ"), fila, columna ), IF(valor="-", "", valor) ), "") | F14: =IFERROR( LET( hoja, LEFT(F$1,3)&"R", fila, MATCH( RIGHT($A14, LEN($A14)-4), INDIRECT(hoja&"!$A:$A"), 0 ), columna, MATCH( "Totales", INDIRECT(hoja&"!$6:$6"), 0 ), valor, INDEX( INDIRECT(hoja&"!$A:$ZZ"), fila, columna ), IF(valor="-", "", valor) ), "") | G14: =IFERROR( LET( hoja, LEFT(G$1,3)&"R", fila, MATCH( RIGHT($A14, LEN($A14)-4), INDIRECT(hoja&"!$A:$A"), 0 ), columna, MATCH( "Totales", INDIRECT(hoja&"!$6:$6"), 0 ), valor, INDEX( INDIRECT(hoja&"!$A:$ZZ"), fila, columna ), IF(valor="-", "", valor) ), "") | H14: =IFERROR( LET( hoja, LEFT(H$1,3)&"R", fila, MATCH( RIGHT($A14, LEN($A14)-4), INDIRECT(hoja&"!$A:$A"), 0 ), columna, MATCH( "Totales", INDIRECT(hoja&"!$6:$6"), 0 ), valor, INDEX( INDIRECT(hoja&"!$A:$ZZ"), fila, columna ), IF(valor="-", "", valor) ), "") | I14: =IFERROR( LET( hoja, LEFT(I$1,3)&"R", fila, MATCH( RIGHT($A14, LEN($A14)-4), INDIRECT(hoja&"!$A:$A"), 0 ), columna, MATCH( "Totales", INDIRECT(hoja&"!$6:$6"), 0 ), valor, INDEX( INDIRECT(hoja&"!$A:$ZZ"), fila, columna ), IF(valor="-", "", valor) ), "") | J14: =IFERROR( LET( hoja, LEFT(J$1,3)&"R", fila, MATCH( RIGHT($A14, LEN($A14)-4), INDIRECT(hoja&"!$A:$A"), 0 ), columna, MATCH( "Totales", INDIRECT(hoja&"!$6:$6"), 0 ), valor, INDEX( INDIRECT(hoja&"!$A:$ZZ"), fila, columna ), IF(valor="-", "", valor) ), "") | ... N14: =IFERROR( LET( hoja, LEFT(N$1,3)&"R", fila, MATCH( RIGHT($A14, LEN($A14)-4), INDIRECT(hoja&"!$A:$A"), 0 ), columna, MATCH( "Totales", INDIRECT(hoja&"!$6:$6"), 0 ), valor, INDEX( INDIRECT(hoja&"!$A:$ZZ"), fila, columna ), IF(valor="-", "", valor) ), "")
A15: =Menus!B8 | B15: =SUM(IF(MONTH(TODAY())>1,C15,0), IF(MONTH(TODAY())>2,D15,0), IF(MONTH(TODAY())>3,E15,0), IF(MONTH(TODAY())>4,F15,0), IF(MONTH(TODAY())>5,G15,0), IF(MONTH(TODAY())>6,H15,0), IF(MONTH(TODAY())>7,I15,0), IF(MONTH(TODAY())>8,J15,0), IF(MONTH(TODAY())>9,K15,0), IF(MONTH(TODAY())>10,L15,0), IF(MONTH(TODAY())>11,M15,0), IF(MONTH(TODAY())>12,N15,0)) -> 0 | C15: =IFERROR( LET( hoja, LEFT(C$1,3)&"R", fila, MATCH( RIGHT($A15, LEN($A15)-4), INDIRECT(hoja&"!$A:$A"), 0 ), columna, MATCH( "Totales", INDIRECT(hoja&"!$6:$6"), 0 ), valor, INDEX( INDIRECT(hoja&"!$A:$ZZ"), fila, columna ), IF(valor="-", "", valor) ), "") | D15: =IFERROR( LET( hoja, LEFT(D$1,3)&"R", fila, MATCH( RIGHT($A15, LEN($A15)-4), INDIRECT(hoja&"!$A:$A"), 0 ), columna, MATCH( "Totales", INDIRECT(hoja&"!$6:$6"), 0 ), valor, INDEX( INDIRECT(hoja&"!$A:$ZZ"), fila, columna ), IF(valor="-", "", valor) ), "") | E15: =IFERROR( LET( hoja, LEFT(E$1,3)&"R", fila, MATCH( RIGHT($A15, LEN($A15)-4), INDIRECT(hoja&"!$A:$A"), 0 ), columna, MATCH( "Totales", INDIRECT(hoja&"!$6:$6"), 0 ), valor, INDEX( INDIRECT(hoja&"!$A:$ZZ"), fila, columna ), IF(valor="-", "", valor) ), "") | F15: =IFERROR( LET( hoja, LEFT(F$1,3)&"R", fila, MATCH( RIGHT($A15, LEN($A15)-4), INDIRECT(hoja&"!$A:$A"), 0 ), columna, MATCH( "Totales", INDIRECT(hoja&"!$6:$6"), 0 ), valor, INDEX( INDIRECT(hoja&"!$A:$ZZ"), fila, columna ), IF(valor="-", "", valor) ), "") | G15: =IFERROR( LET( hoja, LEFT(G$1,3)&"R", fila, MATCH( RIGHT($A15, LEN($A15)-4), INDIRECT(hoja&"!$A:$A"), 0 ), columna, MATCH( "Totales", INDIRECT(hoja&"!$6:$6"), 0 ), valor, INDEX( INDIRECT(hoja&"!$A:$ZZ"), fila, columna ), IF(valor="-", "", valor) ), "") | H15: =IFERROR( LET( hoja, LEFT(H$1,3)&"R", fila, MATCH( RIGHT($A15, LEN($A15)-4), INDIRECT(hoja&"!$A:$A"), 0 ), columna, MATCH( "Totales", INDIRECT(hoja&"!$6:$6"), 0 ), valor, INDEX( INDIRECT(hoja&"!$A:$ZZ"), fila, columna ), IF(valor="-", "", valor) ), "") | I15: =IFERROR( LET( hoja, LEFT(I$1,3)&"R", fila, MATCH( RIGHT($A15, LEN($A15)-4), INDIRECT(hoja&"!$A:$A"), 0 ), columna, MATCH( "Totales", INDIRECT(hoja&"!$6:$6"), 0 ), valor, INDEX( INDIRECT(hoja&"!$A:$ZZ"), fila, columna ), IF(valor="-", "", valor) ), "") | J15: =IFERROR( LET( hoja, LEFT(J$1,3)&"R", fila, MATCH( RIGHT($A15, LEN($A15)-4), INDIRECT(hoja&"!$A:$A"), 0 ), columna, MATCH( "Totales", INDIRECT(hoja&"!$6:$6"), 0 ), valor, INDEX( INDIRECT(hoja&"!$A:$ZZ"), fila, columna ), IF(valor="-", "", valor) ), "") | ... N15: =IFERROR( LET( hoja, LEFT(N$1,3)&"R", fila, MATCH( RIGHT($A15, LEN($A15)-4), INDIRECT(hoja&"!$A:$A"), 0 ), columna, MATCH( "Totales", INDIRECT(hoja&"!$6:$6"), 0 ), valor, INDEX( INDIRECT(hoja&"!$A:$ZZ"), fila, columna ), IF(valor="-", "", valor) ), "")
A16: =Menus!B9 | B16: =SUM(IF(MONTH(TODAY())>1,C16,0), IF(MONTH(TODAY())>2,D16,0), IF(MONTH(TODAY())>3,E16,0), IF(MONTH(TODAY())>4,F16,0), IF(MONTH(TODAY())>5,G16,0), IF(MONTH(TODAY())>6,H16,0), IF(MONTH(TODAY())>7,I16,0), IF(MONTH(TODAY())>8,J16,0), IF(MONTH(TODAY())>9,K16,0), IF(MONTH(TODAY())>10,L16,0), IF(MONTH(TODAY())>11,M16,0), IF(MONTH(TODAY())>12,N16,0)) -> 0 | C16: =IFERROR( LET( hoja, LEFT(C$1,3)&"R", fila, MATCH( RIGHT($A16, LEN($A16)-4), INDIRECT(hoja&"!$A:$A"), 0 ), columna, MATCH( "Totales", INDIRECT(hoja&"!$6:$6"), 0 ), valor, INDEX( INDIRECT(hoja&"!$A:$ZZ"), fila, columna ), IF(valor="-", "", valor) ), "") | D16: =IFERROR( LET( hoja, LEFT(D$1,3)&"R", fila, MATCH( RIGHT($A16, LEN($A16)-4), INDIRECT(hoja&"!$A:$A"), 0 ), columna, MATCH( "Totales", INDIRECT(hoja&"!$6:$6"), 0 ), valor, INDEX( INDIRECT(hoja&"!$A:$ZZ"), fila, columna ), IF(valor="-", "", valor) ), "") | E16: =IFERROR( LET( hoja, LEFT(E$1,3)&"R", fila, MATCH( RIGHT($A16, LEN($A16)-4), INDIRECT(hoja&"!$A:$A"), 0 ), columna, MATCH( "Totales", INDIRECT(hoja&"!$6:$6"), 0 ), valor, INDEX( INDIRECT(hoja&"!$A:$ZZ"), fila, columna ), IF(valor="-", "", valor) ), "") | F16: =IFERROR( LET( hoja, LEFT(F$1,3)&"R", fila, MATCH( RIGHT($A16, LEN($A16)-4), INDIRECT(hoja&"!$A:$A"), 0 ), columna, MATCH( "Totales", INDIRECT(hoja&"!$6:$6"), 0 ), valor, INDEX( INDIRECT(hoja&"!$A:$ZZ"), fila, columna ), IF(valor="-", "", valor) ), "") | G16: =IFERROR( LET( hoja, LEFT(G$1,3)&"R", fila, MATCH( RIGHT($A16, LEN($A16)-4), INDIRECT(hoja&"!$A:$A"), 0 ), columna, MATCH( "Totales", INDIRECT(hoja&"!$6:$6"), 0 ), valor, INDEX( INDIRECT(hoja&"!$A:$ZZ"), fila, columna ), IF(valor="-", "", valor) ), "") | H16: =IFERROR( LET( hoja, LEFT(H$1,3)&"R", fila, MATCH( RIGHT($A16, LEN($A16)-4), INDIRECT(hoja&"!$A:$A"), 0 ), columna, MATCH( "Totales", INDIRECT(hoja&"!$6:$6"), 0 ), valor, INDEX( INDIRECT(hoja&"!$A:$ZZ"), fila, columna ), IF(valor="-", "", valor) ), "") | I16: =IFERROR( LET( hoja, LEFT(I$1,3)&"R", fila, MATCH( RIGHT($A16, LEN($A16)-4), INDIRECT(hoja&"!$A:$A"), 0 ), columna, MATCH( "Totales", INDIRECT(hoja&"!$6:$6"), 0 ), valor, INDEX( INDIRECT(hoja&"!$A:$ZZ"), fila, columna ), IF(valor="-", "", valor) ), "") | J16: =IFERROR( LET( hoja, LEFT(J$1,3)&"R", fila, MATCH( RIGHT($A16, LEN($A16)-4), INDIRECT(hoja&"!$A:$A"), 0 ), columna, MATCH( "Totales", INDIRECT(hoja&"!$6:$6"), 0 ), valor, INDEX( INDIRECT(hoja&"!$A:$ZZ"), fila, columna ), IF(valor="-", "", valor) ), "") | ... N16: =IFERROR( LET( hoja, LEFT(N$1,3)&"R", fila, MATCH( RIGHT($A16, LEN($A16)-4), INDIRECT(hoja&"!$A:$A"), 0 ), columna, MATCH( "Totales", INDIRECT(hoja&"!$6:$6"), 0 ), valor, INDEX( INDIRECT(hoja&"!$A:$ZZ"), fila, columna ), IF(valor="-", "", valor) ), "")
A17: =Menus!B10 | B17: =SUM(IF(MONTH(TODAY())>1,C17,0), IF(MONTH(TODAY())>2,D17,0), IF(MONTH(TODAY())>3,E17,0), IF(MONTH(TODAY())>4,F17,0), IF(MONTH(TODAY())>5,G17,0), IF(MONTH(TODAY())>6,H17,0), IF(MONTH(TODAY())>7,I17,0), IF(MONTH(TODAY())>8,J17,0), IF(MONTH(TODAY())>9,K17,0), IF(MONTH(TODAY())>10,L17,0), IF(MONTH(TODAY())>11,M17,0), IF(MONTH(TODAY())>12,N17,0)) -> 0 | C17: =IFERROR( LET( hoja, LEFT(C$1,3)&"R", fila, MATCH( RIGHT($A17, LEN($A17)-4), INDIRECT(hoja&"!$A:$A"), 0 ), columna, MATCH( "Totales", INDIRECT(hoja&"!$6:$6"), 0 ), valor, INDEX( INDIRECT(hoja&"!$A:$ZZ"), fila, columna ), IF(valor="-", "", valor) ), "") | D17: =IFERROR( LET( hoja, LEFT(D$1,3)&"R", fila, MATCH( RIGHT($A17, LEN($A17)-4), INDIRECT(hoja&"!$A:$A"), 0 ), columna, MATCH( "Totales", INDIRECT(hoja&"!$6:$6"), 0 ), valor, INDEX( INDIRECT(hoja&"!$A:$ZZ"), fila, columna ), IF(valor="-", "", valor) ), "") | E17: =IFERROR( LET( hoja, LEFT(E$1,3)&"R", fila, MATCH( RIGHT($A17, LEN($A17)-4), INDIRECT(hoja&"!$A:$A"), 0 ), columna, MATCH( "Totales", INDIRECT(hoja&"!$6:$6"), 0 ), valor, INDEX( INDIRECT(hoja&"!$A:$ZZ"), fila, columna ), IF(valor="-", "", valor) ), "") | F17: =IFERROR( LET( hoja, LEFT(F$1,3)&"R", fila, MATCH( RIGHT($A17, LEN($A17)-4), INDIRECT(hoja&"!$A:$A"), 0 ), columna, MATCH( "Totales", INDIRECT(hoja&"!$6:$6"), 0 ), valor, INDEX( INDIRECT(hoja&"!$A:$ZZ"), fila, columna ), IF(valor="-", "", valor) ), "") | G17: =IFERROR( LET( hoja, LEFT(G$1,3)&"R", fila, MATCH( RIGHT($A17, LEN($A17)-4), INDIRECT(hoja&"!$A:$A"), 0 ), columna, MATCH( "Totales", INDIRECT(hoja&"!$6:$6"), 0 ), valor, INDEX( INDIRECT(hoja&"!$A:$ZZ"), fila, columna ), IF(valor="-", "", valor) ), "") | H17: =IFERROR( LET( hoja, LEFT(H$1,3)&"R", fila, MATCH( RIGHT($A17, LEN($A17)-4), INDIRECT(hoja&"!$A:$A"), 0 ), columna, MATCH( "Totales", INDIRECT(hoja&"!$6:$6"), 0 ), valor, INDEX( INDIRECT(hoja&"!$A:$ZZ"), fila, columna ), IF(valor="-", "", valor) ), "") | I17: =IFERROR( LET( hoja, LEFT(I$1,3)&"R", fila, MATCH( RIGHT($A17, LEN($A17)-4), INDIRECT(hoja&"!$A:$A"), 0 ), columna, MATCH( "Totales", INDIRECT(hoja&"!$6:$6"), 0 ), valor, INDEX( INDIRECT(hoja&"!$A:$ZZ"), fila, columna ), IF(valor="-", "", valor) ), "") | J17: =IFERROR( LET( hoja, LEFT(J$1,3)&"R", fila, MATCH( RIGHT($A17, LEN($A17)-4), INDIRECT(hoja&"!$A:$A"), 0 ), columna, MATCH( "Totales", INDIRECT(hoja&"!$6:$6"), 0 ), valor, INDEX( INDIRECT(hoja&"!$A:$ZZ"), fila, columna ), IF(valor="-", "", valor) ), "") | ... N17: =IFERROR( LET( hoja, LEFT(N$1,3)&"R", fila, MATCH( RIGHT($A17, LEN($A17)-4), INDIRECT(hoja&"!$A:$A"), 0 ), columna, MATCH( "Totales", INDIRECT(hoja&"!$6:$6"), 0 ), valor, INDEX( INDIRECT(hoja&"!$A:$ZZ"), fila, columna ), IF(valor="-", "", valor) ), "")
A18: =Menus!B11 | B18: =SUM(IF(MONTH(TODAY())>1,C18,0), IF(MONTH(TODAY())>2,D18,0), IF(MONTH(TODAY())>3,E18,0), IF(MONTH(TODAY())>4,F18,0), IF(MONTH(TODAY())>5,G18,0), IF(MONTH(TODAY())>6,H18,0), IF(MONTH(TODAY())>7,I18,0), IF(MONTH(TODAY())>8,J18,0), IF(MONTH(TODAY())>9,K18,0), IF(MONTH(TODAY())>10,L18,0), IF(MONTH(TODAY())>11,M18,0), IF(MONTH(TODAY())>12,N18,0)) -> 0 | C18: =IFERROR( LET( hoja, LEFT(C$1,3)&"R", fila, MATCH( RIGHT($A18, LEN($A18)-4), INDIRECT(hoja&"!$A:$A"), 0 ), columna, MATCH( "Totales", INDIRECT(hoja&"!$6:$6"), 0 ), valor, INDEX( INDIRECT(hoja&"!$A:$ZZ"), fila, columna ), IF(valor="-", "", valor) ), "") | D18: =IFERROR( LET( hoja, LEFT(D$1,3)&"R", fila, MATCH( RIGHT($A18, LEN($A18)-4), INDIRECT(hoja&"!$A:$A"), 0 ), columna, MATCH( "Totales", INDIRECT(hoja&"!$6:$6"), 0 ), valor, INDEX( INDIRECT(hoja&"!$A:$ZZ"), fila, columna ), IF(valor="-", "", valor) ), "") | E18: =IFERROR( LET( hoja, LEFT(E$1,3)&"R", fila, MATCH( RIGHT($A18, LEN($A18)-4), INDIRECT(hoja&"!$A:$A"), 0 ), columna, MATCH( "Totales", INDIRECT(hoja&"!$6:$6"), 0 ), valor, INDEX( INDIRECT(hoja&"!$A:$ZZ"), fila, columna ), IF(valor="-", "", valor) ), "") | F18: =IFERROR( LET( hoja, LEFT(F$1,3)&"R", fila, MATCH( RIGHT($A18, LEN($A18)-4), INDIRECT(hoja&"!$A:$A"), 0 ), columna, MATCH( "Totales", INDIRECT(hoja&"!$6:$6"), 0 ), valor, INDEX( INDIRECT(hoja&"!$A:$ZZ"), fila, columna ), IF(valor="-", "", valor) ), "") | G18: =IFERROR( LET( hoja, LEFT(G$1,3)&"R", fila, MATCH( RIGHT($A18, LEN($A18)-4), INDIRECT(hoja&"!$A:$A"), 0 ), columna, MATCH( "Totales", INDIRECT(hoja&"!$6:$6"), 0 ), valor, INDEX( INDIRECT(hoja&"!$A:$ZZ"), fila, columna ), IF(valor="-", "", valor) ), "") | H18: =IFERROR( LET( hoja, LEFT(H$1,3)&"R", fila, MATCH( RIGHT($A18, LEN($A18)-4), INDIRECT(hoja&"!$A:$A"), 0 ), columna, MATCH( "Totales", INDIRECT(hoja&"!$6:$6"), 0 ), valor, INDEX( INDIRECT(hoja&"!$A:$ZZ"), fila, columna ), IF(valor="-", "", valor) ), "") | I18: =IFERROR( LET( hoja, LEFT(I$1,3)&"R", fila, MATCH( RIGHT($A18, LEN($A18)-4), INDIRECT(hoja&"!$A:$A"), 0 ), columna, MATCH( "Totales", INDIRECT(hoja&"!$6:$6"), 0 ), valor, INDEX( INDIRECT(hoja&"!$A:$ZZ"), fila, columna ), IF(valor="-", "", valor) ), "") | J18: =IFERROR( LET( hoja, LEFT(J$1,3)&"R", fila, MATCH( RIGHT($A18, LEN($A18)-4), INDIRECT(hoja&"!$A:$A"), 0 ), columna, MATCH( "Totales", INDIRECT(hoja&"!$6:$6"), 0 ), valor, INDEX( INDIRECT(hoja&"!$A:$ZZ"), fila, columna ), IF(valor="-", "", valor) ), "") | ... N18: =IFERROR( LET( hoja, LEFT(N$1,3)&"R", fila, MATCH( RIGHT($A18, LEN($A18)-4), INDIRECT(hoja&"!$A:$A"), 0 ), columna, MATCH( "Totales", INDIRECT(hoja&"!$6:$6"), 0 ), valor, INDEX( INDIRECT(hoja&"!$A:$ZZ"), fila, columna ), IF(valor="-", "", valor) ), "")
A19: =Menus!B12 | B19: =SUM(IF(MONTH(TODAY())>1,C19,0), IF(MONTH(TODAY())>2,D19,0), IF(MONTH(TODAY())>3,E19,0), IF(MONTH(TODAY())>4,F19,0), IF(MONTH(TODAY())>5,G19,0), IF(MONTH(TODAY())>6,H19,0), IF(MONTH(TODAY())>7,I19,0), IF(MONTH(TODAY())>8,J19,0), IF(MONTH(TODAY())>9,K19,0), IF(MONTH(TODAY())>10,L19,0), IF(MONTH(TODAY())>11,M19,0), IF(MONTH(TODAY())>12,N19,0)) -> 0 | C19: =IFERROR( LET( hoja, LEFT(C$1,3)&"R", fila, MATCH( RIGHT($A19, LEN($A19)-4), INDIRECT(hoja&"!$A:$A"), 0 ), columna, MATCH( "Totales", INDIRECT(hoja&"!$6:$6"), 0 ), valor, INDEX( INDIRECT(hoja&"!$A:$ZZ"), fila, columna ), IF(valor="-", "", valor) ), "") | D19: =IFERROR( LET( hoja, LEFT(D$1,3)&"R", fila, MATCH( RIGHT($A19, LEN($A19)-4), INDIRECT(hoja&"!$A:$A"), 0 ), columna, MATCH( "Totales", INDIRECT(hoja&"!$6:$6"), 0 ), valor, INDEX( INDIRECT(hoja&"!$A:$ZZ"), fila, columna ), IF(valor="-", "", valor) ), "") | E19: =IFERROR( LET( hoja, LEFT(E$1,3)&"R", fila, MATCH( RIGHT($A19, LEN($A19)-4), INDIRECT(hoja&"!$A:$A"), 0 ), columna, MATCH( "Totales", INDIRECT(hoja&"!$6:$6"), 0 ), valor, INDEX( INDIRECT(hoja&"!$A:$ZZ"), fila, columna ), IF(valor="-", "", valor) ), "") | F19: =IFERROR( LET( hoja, LEFT(F$1,3)&"R", fila, MATCH( RIGHT($A19, LEN($A19)-4), INDIRECT(hoja&"!$A:$A"), 0 ), columna, MATCH( "Totales", INDIRECT(hoja&"!$6:$6"), 0 ), valor, INDEX( INDIRECT(hoja&"!$A:$ZZ"), fila, columna ), IF(valor="-", "", valor) ), "") | G19: =IFERROR( LET( hoja, LEFT(G$1,3)&"R", fila, MATCH( RIGHT($A19, LEN($A19)-4), INDIRECT(hoja&"!$A:$A"), 0 ), columna, MATCH( "Totales", INDIRECT(hoja&"!$6:$6"), 0 ), valor, INDEX( INDIRECT(hoja&"!$A:$ZZ"), fila, columna ), IF(valor="-", "", valor) ), "") | H19: =IFERROR( LET( hoja, LEFT(H$1,3)&"R", fila, MATCH( RIGHT($A19, LEN($A19)-4), INDIRECT(hoja&"!$A:$A"), 0 ), columna, MATCH( "Totales", INDIRECT(hoja&"!$6:$6"), 0 ), valor, INDEX( INDIRECT(hoja&"!$A:$ZZ"), fila, columna ), IF(valor="-", "", valor) ), "") | I19: =IFERROR( LET( hoja, LEFT(I$1,3)&"R", fila, MATCH( RIGHT($A19, LEN($A19)-4), INDIRECT(hoja&"!$A:$A"), 0 ), columna, MATCH( "Totales", INDIRECT(hoja&"!$6:$6"), 0 ), valor, INDEX( INDIRECT(hoja&"!$A:$ZZ"), fila, columna ), IF(valor="-", "", valor) ), "") | J19: =IFERROR( LET( hoja, LEFT(J$1,3)&"R", fila, MATCH( RIGHT($A19, LEN($A19)-4), INDIRECT(hoja&"!$A:$A"), 0 ), columna, MATCH( "Totales", INDIRECT(hoja&"!$6:$6"), 0 ), valor, INDEX( INDIRECT(hoja&"!$A:$ZZ"), fila, columna ), IF(valor="-", "", valor) ), "") | ... N19: =IFERROR( LET( hoja, LEFT(N$1,3)&"R", fila, MATCH( RIGHT($A19, LEN($A19)-4), INDIRECT(hoja&"!$A:$A"), 0 ), columna, MATCH( "Totales", INDIRECT(hoja&"!$6:$6"), 0 ), valor, INDEX( INDIRECT(hoja&"!$A:$ZZ"), fila, columna ), IF(valor="-", "", valor) ), "")
A20: =Menus!B13 | B20: =SUM(IF(MONTH(TODAY())>1,C20,0), IF(MONTH(TODAY())>2,D20,0), IF(MONTH(TODAY())>3,E20,0), IF(MONTH(TODAY())>4,F20,0), IF(MONTH(TODAY())>5,G20,0), IF(MONTH(TODAY())>6,H20,0), IF(MONTH(TODAY())>7,I20,0), IF(MONTH(TODAY())>8,J20,0), IF(MONTH(TODAY())>9,K20,0), IF(MONTH(TODAY())>10,L20,0), IF(MONTH(TODAY())>11,M20,0), IF(MONTH(TODAY())>12,N20,0)) -> 0 | C20: =IFERROR( LET( hoja, LEFT(C$1,3)&"R", fila, MATCH( RIGHT($A20, LEN($A20)-4), INDIRECT(hoja&"!$A:$A"), 0 ), columna, MATCH( "Totales", INDIRECT(hoja&"!$6:$6"), 0 ), valor, INDEX( INDIRECT(hoja&"!$A:$ZZ"), fila, columna ), IF(valor="-", "", valor) ), "") | D20: =IFERROR( LET( hoja, LEFT(D$1,3)&"R", fila, MATCH( RIGHT($A20, LEN($A20)-4), INDIRECT(hoja&"!$A:$A"), 0 ), columna, MATCH( "Totales", INDIRECT(hoja&"!$6:$6"), 0 ), valor, INDEX( INDIRECT(hoja&"!$A:$ZZ"), fila, columna ), IF(valor="-", "", valor) ), "") | E20: =IFERROR( LET( hoja, LEFT(E$1,3)&"R", fila, MATCH( RIGHT($A20, LEN($A20)-4), INDIRECT(hoja&"!$A:$A"), 0 ), columna, MATCH( "Totales", INDIRECT(hoja&"!$6:$6"), 0 ), valor, INDEX( INDIRECT(hoja&"!$A:$ZZ"), fila, columna ), IF(valor="-", "", valor) ), "") | F20: =IFERROR( LET( hoja, LEFT(F$1,3)&"R", fila, MATCH( RIGHT($A20, LEN($A20)-4), INDIRECT(hoja&"!$A:$A"), 0 ), columna, MATCH( "Totales", INDIRECT(hoja&"!$6:$6"), 0 ), valor, INDEX( INDIRECT(hoja&"!$A:$ZZ"), fila, columna ), IF(valor="-", "", valor) ), "") | G20: =IFERROR( LET( hoja, LEFT(G$1,3)&"R", fila, MATCH( RIGHT($A20, LEN($A20)-4), INDIRECT(hoja&"!$A:$A"), 0 ), columna, MATCH( "Totales", INDIRECT(hoja&"!$6:$6"), 0 ), valor, INDEX( INDIRECT(hoja&"!$A:$ZZ"), fila, columna ), IF(valor="-", "", valor) ), "") | H20: =IFERROR( LET( hoja, LEFT(H$1,3)&"R", fila, MATCH( RIGHT($A20, LEN($A20)-4), INDIRECT(hoja&"!$A:$A"), 0 ), columna, MATCH( "Totales", INDIRECT(hoja&"!$6:$6"), 0 ), valor, INDEX( INDIRECT(hoja&"!$A:$ZZ"), fila, columna ), IF(valor="-", "", valor) ), "") | I20: =IFERROR( LET( hoja, LEFT(I$1,3)&"R", fila, MATCH( RIGHT($A20, LEN($A20)-4), INDIRECT(hoja&"!$A:$A"), 0 ), columna, MATCH( "Totales", INDIRECT(hoja&"!$6:$6"), 0 ), valor, INDEX( INDIRECT(hoja&"!$A:$ZZ"), fila, columna ), IF(valor="-", "", valor) ), "") | J20: =IFERROR( LET( hoja, LEFT(J$1,3)&"R", fila, MATCH( RIGHT($A20, LEN($A20)-4), INDIRECT(hoja&"!$A:$A"), 0 ), columna, MATCH( "Totales", INDIRECT(hoja&"!$6:$6"), 0 ), valor, INDEX( INDIRECT(hoja&"!$A:$ZZ"), fila, columna ), IF(valor="-", "", valor) ), "") | ... N20: =IFERROR( LET( hoja, LEFT(N$1,3)&"R", fila, MATCH( RIGHT($A20, LEN($A20)-4), INDIRECT(hoja&"!$A:$A"), 0 ), columna, MATCH( "Totales", INDIRECT(hoja&"!$6:$6"), 0 ), valor, INDEX( INDIRECT(hoja&"!$A:$ZZ"), fila, columna ), IF(valor="-", "", valor) ), "")
A21: =Menus!B14 | B21: =SUM(IF(MONTH(TODAY())>1,C21,0), IF(MONTH(TODAY())>2,D21,0), IF(MONTH(TODAY())>3,E21,0), IF(MONTH(TODAY())>4,F21,0), IF(MONTH(TODAY())>5,G21,0), IF(MONTH(TODAY())>6,H21,0), IF(MONTH(TODAY())>7,I21,0), IF(MONTH(TODAY())>8,J21,0), IF(MONTH(TODAY())>9,K21,0), IF(MONTH(TODAY())>10,L21,0), IF(MONTH(TODAY())>11,M21,0), IF(MONTH(TODAY())>12,N21,0)) -> 0 | C21: =IFERROR( LET( hoja, LEFT(C$1,3)&"R", fila, MATCH( RIGHT($A21, LEN($A21)-4), INDIRECT(hoja&"!$A:$A"), 0 ), columna, MATCH( "Totales", INDIRECT(hoja&"!$6:$6"), 0 ), valor, INDEX( INDIRECT(hoja&"!$A:$ZZ"), fila, columna ), IF(valor="-", "", valor) ), "") | D21: =IFERROR( LET( hoja, LEFT(D$1,3)&"R", fila, MATCH( RIGHT($A21, LEN($A21)-4), INDIRECT(hoja&"!$A:$A"), 0 ), columna, MATCH( "Totales", INDIRECT(hoja&"!$6:$6"), 0 ), valor, INDEX( INDIRECT(hoja&"!$A:$ZZ"), fila, columna ), IF(valor="-", "", valor) ), "") | E21: =IFERROR( LET( hoja, LEFT(E$1,3)&"R", fila, MATCH( RIGHT($A21, LEN($A21)-4), INDIRECT(hoja&"!$A:$A"), 0 ), columna, MATCH( "Totales", INDIRECT(hoja&"!$6:$6"), 0 ), valor, INDEX( INDIRECT(hoja&"!$A:$ZZ"), fila, columna ), IF(valor="-", "", valor) ), "") | F21: =IFERROR( LET( hoja, LEFT(F$1,3)&"R", fila, MATCH( RIGHT($A21, LEN($A21)-4), INDIRECT(hoja&"!$A:$A"), 0 ), columna, MATCH( "Totales", INDIRECT(hoja&"!$6:$6"), 0 ), valor, INDEX( INDIRECT(hoja&"!$A:$ZZ"), fila, columna ), IF(valor="-", "", valor) ), "") | G21: =IFERROR( LET( hoja, LEFT(G$1,3)&"R", fila, MATCH( RIGHT($A21, LEN($A21)-4), INDIRECT(hoja&"!$A:$A"), 0 ), columna, MATCH( "Totales", INDIRECT(hoja&"!$6:$6"), 0 ), valor, INDEX( INDIRECT(hoja&"!$A:$ZZ"), fila, columna ), IF(valor="-", "", valor) ), "") | H21: =IFERROR( LET( hoja, LEFT(H$1,3)&"R", fila, MATCH( RIGHT($A21, LEN($A21)-4), INDIRECT(hoja&"!$A:$A"), 0 ), columna, MATCH( "Totales", INDIRECT(hoja&"!$6:$6"), 0 ), valor, INDEX( INDIRECT(hoja&"!$A:$ZZ"), fila, columna ), IF(valor="-", "", valor) ), "") | I21: =IFERROR( LET( hoja, LEFT(I$1,3)&"R", fila, MATCH( RIGHT($A21, LEN($A21)-4), INDIRECT(hoja&"!$A:$A"), 0 ), columna, MATCH( "Totales", INDIRECT(hoja&"!$6:$6"), 0 ), valor, INDEX( INDIRECT(hoja&"!$A:$ZZ"), fila, columna ), IF(valor="-", "", valor) ), "") | J21: =IFERROR( LET( hoja, LEFT(J$1,3)&"R", fila, MATCH( RIGHT($A21, LEN($A21)-4), INDIRECT(hoja&"!$A:$A"), 0 ), columna, MATCH( "Totales", INDIRECT(hoja&"!$6:$6"), 0 ), valor, INDEX( INDIRECT(hoja&"!$A:$ZZ"), fila, columna ), IF(valor="-", "", valor) ), "") | ... N21: =IFERROR( LET( hoja, LEFT(N$1,3)&"R", fila, MATCH( RIGHT($A21, LEN($A21)-4), INDIRECT(hoja&"!$A:$A"), 0 ), columna, MATCH( "Totales", INDIRECT(hoja&"!$6:$6"), 0 ), valor, INDEX( INDIRECT(hoja&"!$A:$ZZ"), fila, columna ), IF(valor="-", "", valor) ), "")
A22: =Menus!B15 | B22: =SUM(IF(MONTH(TODAY())>1,C22,0), IF(MONTH(TODAY())>2,D22,0), IF(MONTH(TODAY())>3,E22,0), IF(MONTH(TODAY())>4,F22,0), IF(MONTH(TODAY())>5,G22,0), IF(MONTH(TODAY())>6,H22,0), IF(MONTH(TODAY())>7,I22,0), IF(MONTH(TODAY())>8,J22,0), IF(MONTH(TODAY())>9,K22,0), IF(MONTH(TODAY())>10,L22,0), IF(MONTH(TODAY())>11,M22,0), IF(MONTH(TODAY())>12,N22,0)) -> 0 | C22: =IFERROR( LET( hoja, LEFT(C$1,3)&"R", fila, MATCH( RIGHT($A22, LEN($A22)-4), INDIRECT(hoja&"!$A:$A"), 0 ), columna, MATCH( "Totales", INDIRECT(hoja&"!$6:$6"), 0 ), valor, INDEX( INDIRECT(hoja&"!$A:$ZZ"), fila, columna ), IF(valor="-", "", valor) ), "") | D22: =IFERROR( LET( hoja, LEFT(D$1,3)&"R", fila, MATCH( RIGHT($A22, LEN($A22)-4), INDIRECT(hoja&"!$A:$A"), 0 ), columna, MATCH( "Totales", INDIRECT(hoja&"!$6:$6"), 0 ), valor, INDEX( INDIRECT(hoja&"!$A:$ZZ"), fila, columna ), IF(valor="-", "", valor) ), "") | E22: =IFERROR( LET( hoja, LEFT(E$1,3)&"R", fila, MATCH( RIGHT($A22, LEN($A22)-4), INDIRECT(hoja&"!$A:$A"), 0 ), columna, MATCH( "Totales", INDIRECT(hoja&"!$6:$6"), 0 ), valor, INDEX( INDIRECT(hoja&"!$A:$ZZ"), fila, columna ), IF(valor="-", "", valor) ), "") | F22: =IFERROR( LET( hoja, LEFT(F$1,3)&"R", fila, MATCH( RIGHT($A22, LEN($A22)-4), INDIRECT(hoja&"!$A:$A"), 0 ), columna, MATCH( "Totales", INDIRECT(hoja&"!$6:$6"), 0 ), valor, INDEX( INDIRECT(hoja&"!$A:$ZZ"), fila, columna ), IF(valor="-", "", valor) ), "") | G22: =IFERROR( LET( hoja, LEFT(G$1,3)&"R", fila, MATCH( RIGHT($A22, LEN($A22)-4), INDIRECT(hoja&"!$A:$A"), 0 ), columna, MATCH( "Totales", INDIRECT(hoja&"!$6:$6"), 0 ), valor, INDEX( INDIRECT(hoja&"!$A:$ZZ"), fila, columna ), IF(valor="-", "", valor) ), "") | H22: =IFERROR( LET( hoja, LEFT(H$1,3)&"R", fila, MATCH( RIGHT($A22, LEN($A22)-4), INDIRECT(hoja&"!$A:$A"), 0 ), columna, MATCH( "Totales", INDIRECT(hoja&"!$6:$6"), 0 ), valor, INDEX( INDIRECT(hoja&"!$A:$ZZ"), fila, columna ), IF(valor="-", "", valor) ), "") | I22: =IFERROR( LET( hoja, LEFT(I$1,3)&"R", fila, MATCH( RIGHT($A22, LEN($A22)-4), INDIRECT(hoja&"!$A:$A"), 0 ), columna, MATCH( "Totales", INDIRECT(hoja&"!$6:$6"), 0 ), valor, INDEX( INDIRECT(hoja&"!$A:$ZZ"), fila, columna ), IF(valor="-", "", valor) ), "") | J22: =IFERROR( LET( hoja, LEFT(J$1,3)&"R", fila, MATCH( RIGHT($A22, LEN($A22)-4), INDIRECT(hoja&"!$A:$A"), 0 ), columna, MATCH( "Totales", INDIRECT(hoja&"!$6:$6"), 0 ), valor, INDEX( INDIRECT(hoja&"!$A:$ZZ"), fila, columna ), IF(valor="-", "", valor) ), "") | ... N22: =IFERROR( LET( hoja, LEFT(N$1,3)&"R", fila, MATCH( RIGHT($A22, LEN($A22)-4), INDIRECT(hoja&"!$A:$A"), 0 ), columna, MATCH( "Totales", INDIRECT(hoja&"!$6:$6"), 0 ), valor, INDEX( INDIRECT(hoja&"!$A:$ZZ"), fila, columna ), IF(valor="-", "", valor) ), "")
... A47: =Menus!B40 | B47: =SUM(IF(MONTH(TODAY())>1,C47,0), IF(MONTH(TODAY())>2,D47,0), IF(MONTH(TODAY())>3,E47,0), IF(MONTH(TODAY())>4,F47,0), IF(MONTH(TODAY())>5,G47,0), IF(MONTH(TODAY())>6,H47,0), IF(MONTH(TODAY())>7,I47,0), IF(MONTH(TODAY())>8,J47,0), IF(MONTH(TODAY())>9,K47,0), IF(MONTH(TODAY())>10,L47,0), IF(MONTH(TODAY())>11,M47,0), IF(MONTH(TODAY())>12,N47,0)) -> 0 | C47: =IFERROR( LET( hoja, LEFT(C$1,3)&"R", fila, MATCH( RIGHT($A47, LEN($A47)-4), INDIRECT(hoja&"!$A:$A"), 0 ), columna, MATCH( "Totales", INDIRECT(hoja&"!$6:$6"), 0 ), valor, INDEX( INDIRECT(hoja&"!$A:$ZZ"), fila, columna ), IF(valor="-", "", valor) ), "") | D47: =IFERROR( LET( hoja, LEFT(D$1,3)&"R", fila, MATCH( RIGHT($A47, LEN($A47)-4), INDIRECT(hoja&"!$A:$A"), 0 ), columna, MATCH( "Totales", INDIRECT(hoja&"!$6:$6"), 0 ), valor, INDEX( INDIRECT(hoja&"!$A:$ZZ"), fila, columna ), IF(valor="-", "", valor) ), "") | E47: =IFERROR( LET( hoja, LEFT(E$1,3)&"R", fila, MATCH( RIGHT($A47, LEN($A47)-4), INDIRECT(hoja&"!$A:$A"), 0 ), columna, MATCH( "Totales", INDIRECT(hoja&"!$6:$6"), 0 ), valor, INDEX( INDIRECT(hoja&"!$A:$ZZ"), fila, columna ), IF(valor="-", "", valor) ), "") | F47: =IFERROR( LET( hoja, LEFT(F$1,3)&"R", fila, MATCH( RIGHT($A47, LEN($A47)-4), INDIRECT(hoja&"!$A:$A"), 0 ), columna, MATCH( "Totales", INDIRECT(hoja&"!$6:$6"), 0 ), valor, INDEX( INDIRECT(hoja&"!$A:$ZZ"), fila, columna ), IF(valor="-", "", valor) ), "") | G47: =IFERROR( LET( hoja, LEFT(G$1,3)&"R", fila, MATCH( RIGHT($A47, LEN($A47)-4), INDIRECT(hoja&"!$A:$A"), 0 ), columna, MATCH( "Totales", INDIRECT(hoja&"!$6:$6"), 0 ), valor, INDEX( INDIRECT(hoja&"!$A:$ZZ"), fila, columna ), IF(valor="-", "", valor) ), "") | H47: =IFERROR( LET( hoja, LEFT(H$1,3)&"R", fila, MATCH( RIGHT($A47, LEN($A47)-4), INDIRECT(hoja&"!$A:$A"), 0 ), columna, MATCH( "Totales", INDIRECT(hoja&"!$6:$6"), 0 ), valor, INDEX( INDIRECT(hoja&"!$A:$ZZ"), fila, columna ), IF(valor="-", "", valor) ), "") | I47: =IFERROR( LET( hoja, LEFT(I$1,3)&"R", fila, MATCH( RIGHT($A47, LEN($A47)-4), INDIRECT(hoja&"!$A:$A"), 0 ), columna, MATCH( "Totales", INDIRECT(hoja&"!$6:$6"), 0 ), valor, INDEX( INDIRECT(hoja&"!$A:$ZZ"), fila, columna ), IF(valor="-", "", valor) ), "") | J47: =IFERROR( LET( hoja, LEFT(J$1,3)&"R", fila, MATCH( RIGHT($A47, LEN($A47)-4), INDIRECT(hoja&"!$A:$A"), 0 ), columna, MATCH( "Totales", INDIRECT(hoja&"!$6:$6"), 0 ), valor, INDEX( INDIRECT(hoja&"!$A:$ZZ"), fila, columna ), IF(valor="-", "", valor) ), "") | ... N47: =IFERROR( LET( hoja, LEFT(N$1,3)&"R", fila, MATCH( RIGHT($A47, LEN($A47)-4), INDIRECT(hoja&"!$A:$A"), 0 ), columna, MATCH( "Totales", INDIRECT(hoja&"!$6:$6"), 0 ), valor, INDEX( INDIRECT(hoja&"!$A:$ZZ"), fila, columna ), IF(valor="-", "", valor) ), "")
A49: Otros Ingresos | B49: =SUM(B50:B52) -> 0 | C49: =SUM(C50:C52) -> 0 | D49: =SUM(D50:D52) -> 0 | E49: =SUM(E50:E52) -> 0 | F49: =SUM(F50:F52) -> 0 | G49: =SUM(G50:G52) -> 0 | H49: =SUM(H50:H52) -> 0 | I49: =SUM(I50:I52) -> 0 | ... N49: =SUM(N50:N52) -> 0
A50: =Menus!Q2 | B50: =SUM(IF(MONTH(TODAY())>1,C50,0), IF(MONTH(TODAY())>2,D50,0), IF(MONTH(TODAY())>3,E50,0), IF(MONTH(TODAY())>4,F50,0), IF(MONTH(TODAY())>5,G50,0), IF(MONTH(TODAY())>6,H50,0), IF(MONTH(TODAY())>7,I50,0), IF(MONTH(TODAY())>8,J50,0), IF(MONTH(TODAY())>9,K50,0), IF(MONTH(TODAY())>10,L50,0), IF(MONTH(TODAY())>11,M50,0), IF(MONTH(TODAY())>12,N50,0)) -> 0 | C50: {=IFERROR(SUMIF(OtrosR!$C$3:$C$100, $A50, INDEX(OtrosR!$E$3:$P$100, , MATCH(C$1, OtrosR!$E$2:$P$2, 0))), "")} | D50: {=IFERROR(SUMIF(OtrosR!$C$3:$C$100, $A50, INDEX(OtrosR!$E$3:$P$100, , MATCH(D$1, OtrosR!$E$2:$P$2, 0))), "")} | E50: {=IFERROR(SUMIF(OtrosR!$C$3:$C$100, $A50, INDEX(OtrosR!$E$3:$P$100, , MATCH(E$1, OtrosR!$E$2:$P$2, 0))), "")} | F50: {=IFERROR(SUMIF(OtrosR!$C$3:$C$100, $A50, INDEX(OtrosR!$E$3:$P$100, , MATCH(F$1, OtrosR!$E$2:$P$2, 0))), "")} | G50: {=IFERROR(SUMIF(OtrosR!$C$3:$C$100, $A50, INDEX(OtrosR!$E$3:$P$100, , MATCH(G$1, OtrosR!$E$2:$P$2, 0))), "")} | H50: {=IFERROR(SUMIF(OtrosR!$C$3:$C$100, $A50, INDEX(OtrosR!$E$3:$P$100, , MATCH(H$1, OtrosR!$E$2:$P$2, 0))), "")} | I50: {=IFERROR(SUMIF(OtrosR!$C$3:$C$100, $A50, INDEX(OtrosR!$E$3:$P$100, , MATCH(I$1, OtrosR!$E$2:$P$2, 0))), "")} | J50: {=IFERROR(SUMIF(OtrosR!$C$3:$C$100, $A50, INDEX(OtrosR!$E$3:$P$100, , MATCH(J$1, OtrosR!$E$2:$P$2, 0))), "")} | ... N50: {=IFERROR(SUMIF(OtrosR!$C$3:$C$100, $A50, INDEX(OtrosR!$E$3:$P$100, , MATCH(N$1, OtrosR!$E$2:$P$2, 0))), "")}
B51: =SUM(IF(MONTH(TODAY())>1,C51,0), IF(MONTH(TODAY())>2,D51,0), IF(MONTH(TODAY())>3,E51,0), IF(MONTH(TODAY())>4,F51,0), IF(MONTH(TODAY())>5,G51,0), IF(MONTH(TODAY())>6,H51,0), IF(MONTH(TODAY())>7,I51,0), IF(MONTH(TODAY())>8,J51,0), IF(MONTH(TODAY())>9,K51,0), IF(MONTH(TODAY())>10,L51,0), IF(MONTH(TODAY())>11,M51,0), IF(MONTH(TODAY())>12,N51,0)) -> 0 | C51: {=IFERROR(SUMIF(OtrosR!$C$3:$C$100, $A51, INDEX(OtrosR!$E$3:$P$100, , MATCH(C$1, OtrosR!$E$2:$P$2, 0))), "")} | D51: {=IFERROR(SUMIF(OtrosR!$C$3:$C$100, $A51, INDEX(OtrosR!$E$3:$P$100, , MATCH(D$1, OtrosR!$E$2:$P$2, 0))), "")} | E51: {=IFERROR(SUMIF(OtrosR!$C$3:$C$100, $A51, INDEX(OtrosR!$E$3:$P$100, , MATCH(E$1, OtrosR!$E$2:$P$2, 0))), "")} | F51: {=IFERROR(SUMIF(OtrosR!$C$3:$C$100, $A51, INDEX(OtrosR!$E$3:$P$100, , MATCH(F$1, OtrosR!$E$2:$P$2, 0))), "")} | G51: {=IFERROR(SUMIF(OtrosR!$C$3:$C$100, $A51, INDEX(OtrosR!$E$3:$P$100, , MATCH(G$1, OtrosR!$E$2:$P$2, 0))), "")} | H51: {=IFERROR(SUMIF(OtrosR!$C$3:$C$100, $A51, INDEX(OtrosR!$E$3:$P$100, , MATCH(H$1, OtrosR!$E$2:$P$2, 0))), "")} | I51: {=IFERROR(SUMIF(OtrosR!$C$3:$C$100, $A51, INDEX(OtrosR!$E$3:$P$100, , MATCH(I$1, OtrosR!$E$2:$P$2, 0))), "")} | J51: {=IFERROR(SUMIF(OtrosR!$C$3:$C$100, $A51, INDEX(OtrosR!$E$3:$P$100, , MATCH(J$1, OtrosR!$E$2:$P$2, 0))), "")} | ... N51: {=IFERROR(SUMIF(OtrosR!$C$3:$C$100, $A51, INDEX(OtrosR!$E$3:$P$100, , MATCH(N$1, OtrosR!$E$2:$P$2, 0))), "")}
B52: =SUM(IF(MONTH(TODAY())>1,C52,0), IF(MONTH(TODAY())>2,D52,0), IF(MONTH(TODAY())>3,E52,0), IF(MONTH(TODAY())>4,F52,0), IF(MONTH(TODAY())>5,G52,0), IF(MONTH(TODAY())>6,H52,0), IF(MONTH(TODAY())>7,I52,0), IF(MONTH(TODAY())>8,J52,0), IF(MONTH(TODAY())>9,K52,0), IF(MONTH(TODAY())>10,L52,0), IF(MONTH(TODAY())>11,M52,0), IF(MONTH(TODAY())>12,N52,0)) -> 0 | C52: {=IFERROR(SUMIF(OtrosR!$C$3:$C$100, $A52, INDEX(OtrosR!$E$3:$P$100, , MATCH(C$1, OtrosR!$E$2:$P$2, 0))), "")} | D52: {=IFERROR(SUMIF(OtrosR!$C$3:$C$100, $A52, INDEX(OtrosR!$E$3:$P$100, , MATCH(D$1, OtrosR!$E$2:$P$2, 0))), "")} | E52: {=IFERROR(SUMIF(OtrosR!$C$3:$C$100, $A52, INDEX(OtrosR!$E$3:$P$100, , MATCH(E$1, OtrosR!$E$2:$P$2, 0))), "")} | F52: {=IFERROR(SUMIF(OtrosR!$C$3:$C$100, $A52, INDEX(OtrosR!$E$3:$P$100, , MATCH(F$1, OtrosR!$E$2:$P$2, 0))), "")} | G52: {=IFERROR(SUMIF(OtrosR!$C$3:$C$100, $A52, INDEX(OtrosR!$E$3:$P$100, , MATCH(G$1, OtrosR!$E$2:$P$2, 0))), "")} | H52: {=IFERROR(SUMIF(OtrosR!$C$3:$C$100, $A52, INDEX(OtrosR!$E$3:$P$100, , MATCH(H$1, OtrosR!$E$2:$P$2, 0))), "")} | I52: {=IFERROR(SUMIF(OtrosR!$C$3:$C$100, $A52, INDEX(OtrosR!$E$3:$P$100, , MATCH(I$1, OtrosR!$E$2:$P$2, 0))), "")} | J52: {=IFERROR(SUMIF(OtrosR!$C$3:$C$100, $A52, INDEX(OtrosR!$E$3:$P$100, , MATCH(J$1, OtrosR!$E$2:$P$2, 0))), "")} | ... N52: {=IFERROR(SUMIF(OtrosR!$C$3:$C$100, $A52, INDEX(OtrosR!$E$3:$P$100, , MATCH(N$1, OtrosR!$E$2:$P$2, 0))), "")}
A54: Otros Egresos | B54: =SUM(B55:B63) -> 0 | C54: =SUM(C55:C63) -> 0 | D54: =SUM(D55:D63) -> 0 | E54: =SUM(E55:E63) -> 0 | F54: =SUM(F55:F63) -> 0 | G54: =SUM(G55:G63) -> 0 | H54: =SUM(H55:H63) -> 0 | I54: =SUM(I55:I63) -> 0 | ... N54: =SUM(N55:N63) -> 0
A55: =Menus!Q3 | B55: =SUM(IF(MONTH(TODAY())>1,C55,0), IF(MONTH(TODAY())>2,D55,0), IF(MONTH(TODAY())>3,E55,0), IF(MONTH(TODAY())>4,F55,0), IF(MONTH(TODAY())>5,G55,0), IF(MONTH(TODAY())>6,H55,0), IF(MONTH(TODAY())>7,I55,0), IF(MONTH(TODAY())>8,J55,0), IF(MONTH(TODAY())>9,K55,0), IF(MONTH(TODAY())>10,L55,0), IF(MONTH(TODAY())>11,M55,0), IF(MONTH(TODAY())>12,N55,0)) -> 0 | C55: {=IFERROR(SUMIF(OtrosR!$C$3:$C$100, $A55, INDEX(OtrosR!$E$3:$P$100, , MATCH(C$1, OtrosR!$E$2:$P$2, 0))), "")} | D55: {=IFERROR(SUMIF(OtrosR!$C$3:$C$100, $A55, INDEX(OtrosR!$E$3:$P$100, , MATCH(D$1, OtrosR!$E$2:$P$2, 0))), "")} | E55: {=IFERROR(SUMIF(OtrosR!$C$3:$C$100, $A55, INDEX(OtrosR!$E$3:$P$100, , MATCH(E$1, OtrosR!$E$2:$P$2, 0))), "")} | F55: {=IFERROR(SUMIF(OtrosR!$C$3:$C$100, $A55, INDEX(OtrosR!$E$3:$P$100, , MATCH(F$1, OtrosR!$E$2:$P$2, 0))), "")} | G55: {=IFERROR(SUMIF(OtrosR!$C$3:$C$100, $A55, INDEX(OtrosR!$E$3:$P$100, , MATCH(G$1, OtrosR!$E$2:$P$2, 0))), "")} | H55: {=IFERROR(SUMIF(OtrosR!$C$3:$C$100, $A55, INDEX(OtrosR!$E$3:$P$100, , MATCH(H$1, OtrosR!$E$2:$P$2, 0))), "")} | I55: {=IFERROR(SUMIF(OtrosR!$C$3:$C$100, $A55, INDEX(OtrosR!$E$3:$P$100, , MATCH(I$1, OtrosR!$E$2:$P$2, 0))), "")} | J55: {=IFERROR(SUMIF(OtrosR!$C$3:$C$100, $A55, INDEX(OtrosR!$E$3:$P$100, , MATCH(J$1, OtrosR!$E$2:$P$2, 0))), "")} | ... N55: {=IFERROR(SUMIF(OtrosR!$C$3:$C$100, $A55, INDEX(OtrosR!$E$3:$P$100, , MATCH(N$1, OtrosR!$E$2:$P$2, 0))), "")}
A56: =Menus!Q4 | B56: =SUM(IF(MONTH(TODAY())>1,C56,0), IF(MONTH(TODAY())>2,D56,0), IF(MONTH(TODAY())>3,E56,0), IF(MONTH(TODAY())>4,F56,0), IF(MONTH(TODAY())>5,G56,0), IF(MONTH(TODAY())>6,H56,0), IF(MONTH(TODAY())>7,I56,0), IF(MONTH(TODAY())>8,J56,0), IF(MONTH(TODAY())>9,K56,0), IF(MONTH(TODAY())>10,L56,0), IF(MONTH(TODAY())>11,M56,0), IF(MONTH(TODAY())>12,N56,0)) -> 0 | C56: {=IFERROR(SUMIF(OtrosR!$C$3:$C$100, $A56, INDEX(OtrosR!$E$3:$P$100, , MATCH(C$1, OtrosR!$E$2:$P$2, 0))), "")} | D56: {=IFERROR(SUMIF(OtrosR!$C$3:$C$100, $A56, INDEX(OtrosR!$E$3:$P$100, , MATCH(D$1, OtrosR!$E$2:$P$2, 0))), "")} | E56: {=IFERROR(SUMIF(OtrosR!$C$3:$C$100, $A56, INDEX(OtrosR!$E$3:$P$100, , MATCH(E$1, OtrosR!$E$2:$P$2, 0))), "")} | F56: {=IFERROR(SUMIF(OtrosR!$C$3:$C$100, $A56, INDEX(OtrosR!$E$3:$P$100, , MATCH(F$1, OtrosR!$E$2:$P$2, 0))), "")} | G56: {=IFERROR(SUMIF(OtrosR!$C$3:$C$100, $A56, INDEX(OtrosR!$E$3:$P$100, , MATCH(G$1, OtrosR!$E$2:$P$2, 0))), "")} | H56: {=IFERROR(SUMIF(OtrosR!$C$3:$C$100, $A56, INDEX(OtrosR!$E$3:$P$100, , MATCH(H$1, OtrosR!$E$2:$P$2, 0))), "")} | I56: {=IFERROR(SUMIF(OtrosR!$C$3:$C$100, $A56, INDEX(OtrosR!$E$3:$P$100, , MATCH(I$1, OtrosR!$E$2:$P$2, 0))), "")} | J56: {=IFERROR(SUMIF(OtrosR!$C$3:$C$100, $A56, INDEX(OtrosR!$E$3:$P$100, , MATCH(J$1, OtrosR!$E$2:$P$2, 0))), "")} | ... N56: {=IFERROR(SUMIF(OtrosR!$C$3:$C$100, $A56, INDEX(OtrosR!$E$3:$P$100, , MATCH(N$1, OtrosR!$E$2:$P$2, 0))), "")}
A57: =Menus!Q5 | B57: =SUM(IF(MONTH(TODAY())>1,C57,0), IF(MONTH(TODAY())>2,D57,0), IF(MONTH(TODAY())>3,E57,0), IF(MONTH(TODAY())>4,F57,0), IF(MONTH(TODAY())>5,G57,0), IF(MONTH(TODAY())>6,H57,0), IF(MONTH(TODAY())>7,I57,0), IF(MONTH(TODAY())>8,J57,0), IF(MONTH(TODAY())>9,K57,0), IF(MONTH(TODAY())>10,L57,0), IF(MONTH(TODAY())>11,M57,0), IF(MONTH(TODAY())>12,N57,0)) -> 0 | C57: {=IFERROR(SUMIF(OtrosR!$C$3:$C$100, $A57, INDEX(OtrosR!$E$3:$P$100, , MATCH(C$1, OtrosR!$E$2:$P$2, 0))), "")} | D57: {=IFERROR(SUMIF(OtrosR!$C$3:$C$100, $A57, INDEX(OtrosR!$E$3:$P$100, , MATCH(D$1, OtrosR!$E$2:$P$2, 0))), "")} | E57: {=IFERROR(SUMIF(OtrosR!$C$3:$C$100, $A57, INDEX(OtrosR!$E$3:$P$100, , MATCH(E$1, OtrosR!$E$2:$P$2, 0))), "")} | F57: {=IFERROR(SUMIF(OtrosR!$C$3:$C$100, $A57, INDEX(OtrosR!$E$3:$P$100, , MATCH(F$1, OtrosR!$E$2:$P$2, 0))), "")} | G57: {=IFERROR(SUMIF(OtrosR!$C$3:$C$100, $A57, INDEX(OtrosR!$E$3:$P$100, , MATCH(G$1, OtrosR!$E$2:$P$2, 0))), "")} | H57: {=IFERROR(SUMIF(OtrosR!$C$3:$C$100, $A57, INDEX(OtrosR!$E$3:$P$100, , MATCH(H$1, OtrosR!$E$2:$P$2, 0))), "")} | I57: {=IFERROR(SUMIF(OtrosR!$C$3:$C$100, $A57, INDEX(OtrosR!$E$3:$P$100, , MATCH(I$1, OtrosR!$E$2:$P$2, 0))), "")} | J57: {=IFERROR(SUMIF(OtrosR!$C$3:$C$100, $A57, INDEX(OtrosR!$E$3:$P$100, , MATCH(J$1, OtrosR!$E$2:$P$2, 0))), "")} | ... N57: {=IFERROR(SUMIF(OtrosR!$C$3:$C$100, $A57, INDEX(OtrosR!$E$3:$P$100, , MATCH(N$1, OtrosR!$E$2:$P$2, 0))), "")}
A58: =Menus!Q6 | B58: =SUM(IF(MONTH(TODAY())>1,C58,0), IF(MONTH(TODAY())>2,D58,0), IF(MONTH(TODAY())>3,E58,0), IF(MONTH(TODAY())>4,F58,0), IF(MONTH(TODAY())>5,G58,0), IF(MONTH(TODAY())>6,H58,0), IF(MONTH(TODAY())>7,I58,0), IF(MONTH(TODAY())>8,J58,0), IF(MONTH(TODAY())>9,K58,0), IF(MONTH(TODAY())>10,L58,0), IF(MONTH(TODAY())>11,M58,0), IF(MONTH(TODAY())>12,N58,0)) -> 0 | C58: {=IFERROR(SUMIF(OtrosR!$C$3:$C$100, $A58, INDEX(OtrosR!$E$3:$P$100, , MATCH(C$1, OtrosR!$E$2:$P$2, 0))), "")} | D58: {=IFERROR(SUMIF(OtrosR!$C$3:$C$100, $A58, INDEX(OtrosR!$E$3:$P$100, , MATCH(D$1, OtrosR!$E$2:$P$2, 0))), "")} | E58: {=IFERROR(SUMIF(OtrosR!$C$3:$C$100, $A58, INDEX(OtrosR!$E$3:$P$100, , MATCH(E$1, OtrosR!$E$2:$P$2, 0))), "")} | F58: {=IFERROR(SUMIF(OtrosR!$C$3:$C$100, $A58, INDEX(OtrosR!$E$3:$P$100, , MATCH(F$1, OtrosR!$E$2:$P$2, 0))), "")} | G58: {=IFERROR(SUMIF(OtrosR!$C$3:$C$100, $A58, INDEX(OtrosR!$E$3:$P$100, , MATCH(G$1, OtrosR!$E$2:$P$2, 0))), "")} | H58: {=IFERROR(SUMIF(OtrosR!$C$3:$C$100, $A58, INDEX(OtrosR!$E$3:$P$100, , MATCH(H$1, OtrosR!$E$2:$P$2, 0))), "")} | I58: {=IFERROR(SUMIF(OtrosR!$C$3:$C$100, $A58, INDEX(OtrosR!$E$3:$P$100, , MATCH(I$1, OtrosR!$E$2:$P$2, 0))), "")} | J58: {=IFERROR(SUMIF(OtrosR!$C$3:$C$100, $A58, INDEX(OtrosR!$E$3:$P$100, , MATCH(J$1, OtrosR!$E$2:$P$2, 0))), "")} | ... N58: {=IFERROR(SUMIF(OtrosR!$C$3:$C$100, $A58, INDEX(OtrosR!$E$3:$P$100, , MATCH(N$1, OtrosR!$E$2:$P$2, 0))), "")}
A59: =Menus!Q7 | B59: =SUM(IF(MONTH(TODAY())>1,C59,0), IF(MONTH(TODAY())>2,D59,0), IF(MONTH(TODAY())>3,E59,0), IF(MONTH(TODAY())>4,F59,0), IF(MONTH(TODAY())>5,G59,0), IF(MONTH(TODAY())>6,H59,0), IF(MONTH(TODAY())>7,I59,0), IF(MONTH(TODAY())>8,J59,0), IF(MONTH(TODAY())>9,K59,0), IF(MONTH(TODAY())>10,L59,0), IF(MONTH(TODAY())>11,M59,0), IF(MONTH(TODAY())>12,N59,0)) -> 0 | C59: {=IFERROR(SUMIF(OtrosR!$C$3:$C$100, $A59, INDEX(OtrosR!$E$3:$P$100, , MATCH(C$1, OtrosR!$E$2:$P$2, 0))), "")} | D59: {=IFERROR(SUMIF(OtrosR!$C$3:$C$100, $A59, INDEX(OtrosR!$E$3:$P$100, , MATCH(D$1, OtrosR!$E$2:$P$2, 0))), "")} | E59: {=IFERROR(SUMIF(OtrosR!$C$3:$C$100, $A59, INDEX(OtrosR!$E$3:$P$100, , MATCH(E$1, OtrosR!$E$2:$P$2, 0))), "")} | F59: {=IFERROR(SUMIF(OtrosR!$C$3:$C$100, $A59, INDEX(OtrosR!$E$3:$P$100, , MATCH(F$1, OtrosR!$E$2:$P$2, 0))), "")} | G59: {=IFERROR(SUMIF(OtrosR!$C$3:$C$100, $A59, INDEX(OtrosR!$E$3:$P$100, , MATCH(G$1, OtrosR!$E$2:$P$2, 0))), "")} | H59: {=IFERROR(SUMIF(OtrosR!$C$3:$C$100, $A59, INDEX(OtrosR!$E$3:$P$100, , MATCH(H$1, OtrosR!$E$2:$P$2, 0))), "")} | I59: {=IFERROR(SUMIF(OtrosR!$C$3:$C$100, $A59, INDEX(OtrosR!$E$3:$P$100, , MATCH(I$1, OtrosR!$E$2:$P$2, 0))), "")} | J59: {=IFERROR(SUMIF(OtrosR!$C$3:$C$100, $A59, INDEX(OtrosR!$E$3:$P$100, , MATCH(J$1, OtrosR!$E$2:$P$2, 0))), "")} | ... N59: {=IFERROR(SUMIF(OtrosR!$C$3:$C$100, $A59, INDEX(OtrosR!$E$3:$P$100, , MATCH(N$1, OtrosR!$E$2:$P$2, 0))), "")}
A60: =Menus!Q8 | B60: =SUM(IF(MONTH(TODAY())>1,C60,0), IF(MONTH(TODAY())>2,D60,0), IF(MONTH(TODAY())>3,E60,0), IF(MONTH(TODAY())>4,F60,0), IF(MONTH(TODAY())>5,G60,0), IF(MONTH(TODAY())>6,H60,0), IF(MONTH(TODAY())>7,I60,0), IF(MONTH(TODAY())>8,J60,0), IF(MONTH(TODAY())>9,K60,0), IF(MONTH(TODAY())>10,L60,0), IF(MONTH(TODAY())>11,M60,0), IF(MONTH(TODAY())>12,N60,0)) -> 0 | C60: {=IFERROR(SUMIF(OtrosR!$C$3:$C$100, $A60, INDEX(OtrosR!$E$3:$P$100, , MATCH(C$1, OtrosR!$E$2:$P$2, 0))), "")} | D60: {=IFERROR(SUMIF(OtrosR!$C$3:$C$100, $A60, INDEX(OtrosR!$E$3:$P$100, , MATCH(D$1, OtrosR!$E$2:$P$2, 0))), "")} | E60: {=IFERROR(SUMIF(OtrosR!$C$3:$C$100, $A60, INDEX(OtrosR!$E$3:$P$100, , MATCH(E$1, OtrosR!$E$2:$P$2, 0))), "")} | F60: {=IFERROR(SUMIF(OtrosR!$C$3:$C$100, $A60, INDEX(OtrosR!$E$3:$P$100, , MATCH(F$1, OtrosR!$E$2:$P$2, 0))), "")} | G60: {=IFERROR(SUMIF(OtrosR!$C$3:$C$100, $A60, INDEX(OtrosR!$E$3:$P$100, , MATCH(G$1, OtrosR!$E$2:$P$2, 0))), "")} | H60: {=IFERROR(SUMIF(OtrosR!$C$3:$C$100, $A60, INDEX(OtrosR!$E$3:$P$100, , MATCH(H$1, OtrosR!$E$2:$P$2, 0))), "")} | I60: {=IFERROR(SUMIF(OtrosR!$C$3:$C$100, $A60, INDEX(OtrosR!$E$3:$P$100, , MATCH(I$1, OtrosR!$E$2:$P$2, 0))), "")} | J60: {=IFERROR(SUMIF(OtrosR!$C$3:$C$100, $A60, INDEX(OtrosR!$E$3:$P$100, , MATCH(J$1, OtrosR!$E$2:$P$2, 0))), "")} | ... N60: {=IFERROR(SUMIF(OtrosR!$C$3:$C$100, $A60, INDEX(OtrosR!$E$3:$P$100, , MATCH(N$1, OtrosR!$E$2:$P$2, 0))), "")}
A61: =Menus!Q9 | B61: =SUM(IF(MONTH(TODAY())>1,C61,0), IF(MONTH(TODAY())>2,D61,0), IF(MONTH(TODAY())>3,E61,0), IF(MONTH(TODAY())>4,F61,0), IF(MONTH(TODAY())>5,G61,0), IF(MONTH(TODAY())>6,H61,0), IF(MONTH(TODAY())>7,I61,0), IF(MONTH(TODAY())>8,J61,0), IF(MONTH(TODAY())>9,K61,0), IF(MONTH(TODAY())>10,L61,0), IF(MONTH(TODAY())>11,M61,0), IF(MONTH(TODAY())>12,N61,0)) -> 0 | C61: {=IFERROR(SUMIF(OtrosR!$C$3:$C$100, $A61, INDEX(OtrosR!$E$3:$P$100, , MATCH(C$1, OtrosR!$E$2:$P$2, 0))), "")} | D61: {=IFERROR(SUMIF(OtrosR!$C$3:$C$100, $A61, INDEX(OtrosR!$E$3:$P$100, , MATCH(D$1, OtrosR!$E$2:$P$2, 0))), "")} | E61: {=IFERROR(SUMIF(OtrosR!$C$3:$C$100, $A61, INDEX(OtrosR!$E$3:$P$100, , MATCH(E$1, OtrosR!$E$2:$P$2, 0))), "")} | F61: {=IFERROR(SUMIF(OtrosR!$C$3:$C$100, $A61, INDEX(OtrosR!$E$3:$P$100, , MATCH(F$1, OtrosR!$E$2:$P$2, 0))), "")} | G61: {=IFERROR(SUMIF(OtrosR!$C$3:$C$100, $A61, INDEX(OtrosR!$E$3:$P$100, , MATCH(G$1, OtrosR!$E$2:$P$2, 0))), "")} | H61: {=IFERROR(SUMIF(OtrosR!$C$3:$C$100, $A61, INDEX(OtrosR!$E$3:$P$100, , MATCH(H$1, OtrosR!$E$2:$P$2, 0))), "")} | I61: {=IFERROR(SUMIF(OtrosR!$C$3:$C$100, $A61, INDEX(OtrosR!$E$3:$P$100, , MATCH(I$1, OtrosR!$E$2:$P$2, 0))), "")} | J61: {=IFERROR(SUMIF(OtrosR!$C$3:$C$100, $A61, INDEX(OtrosR!$E$3:$P$100, , MATCH(J$1, OtrosR!$E$2:$P$2, 0))), "")} | ... N61: {=IFERROR(SUMIF(OtrosR!$C$3:$C$100, $A61, INDEX(OtrosR!$E$3:$P$100, , MATCH(N$1, OtrosR!$E$2:$P$2, 0))), "")}
A62: =Menus!Q10 | B62: =SUM(IF(MONTH(TODAY())>1,C62,0), IF(MONTH(TODAY())>2,D62,0), IF(MONTH(TODAY())>3,E62,0), IF(MONTH(TODAY())>4,F62,0), IF(MONTH(TODAY())>5,G62,0), IF(MONTH(TODAY())>6,H62,0), IF(MONTH(TODAY())>7,I62,0), IF(MONTH(TODAY())>8,J62,0), IF(MONTH(TODAY())>9,K62,0), IF(MONTH(TODAY())>10,L62,0), IF(MONTH(TODAY())>11,M62,0), IF(MONTH(TODAY())>12,N62,0)) -> 0 | C62: {=IFERROR(SUMIF(OtrosR!$C$3:$C$100, $A62, INDEX(OtrosR!$E$3:$P$100, , MATCH(C$1, OtrosR!$E$2:$P$2, 0))), "")} | D62: {=IFERROR(SUMIF(OtrosR!$C$3:$C$100, $A62, INDEX(OtrosR!$E$3:$P$100, , MATCH(D$1, OtrosR!$E$2:$P$2, 0))), "")} | E62: {=IFERROR(SUMIF(OtrosR!$C$3:$C$100, $A62, INDEX(OtrosR!$E$3:$P$100, , MATCH(E$1, OtrosR!$E$2:$P$2, 0))), "")} | F62: {=IFERROR(SUMIF(OtrosR!$C$3:$C$100, $A62, INDEX(OtrosR!$E$3:$P$100, , MATCH(F$1, OtrosR!$E$2:$P$2, 0))), "")} | G62: {=IFERROR(SUMIF(OtrosR!$C$3:$C$100, $A62, INDEX(OtrosR!$E$3:$P$100, , MATCH(G$1, OtrosR!$E$2:$P$2, 0))), "")} | H62: {=IFERROR(SUMIF(OtrosR!$C$3:$C$100, $A62, INDEX(OtrosR!$E$3:$P$100, , MATCH(H$1, OtrosR!$E$2:$P$2, 0))), "")} | I62: {=IFERROR(SUMIF(OtrosR!$C$3:$C$100, $A62, INDEX(OtrosR!$E$3:$P$100, , MATCH(I$1, OtrosR!$E$2:$P$2, 0))), "")} | J62: {=IFERROR(SUMIF(OtrosR!$C$3:$C$100, $A62, INDEX(OtrosR!$E$3:$P$100, , MATCH(J$1, OtrosR!$E$2:$P$2, 0))), "")} | ... N62: {=IFERROR(SUMIF(OtrosR!$C$3:$C$100, $A62, INDEX(OtrosR!$E$3:$P$100, , MATCH(N$1, OtrosR!$E$2:$P$2, 0))), "")}
A63: =Menus!Q11 | B63: =SUM(IF(MONTH(TODAY())>1,C63,0), IF(MONTH(TODAY())>2,D63,0), IF(MONTH(TODAY())>3,E63,0), IF(MONTH(TODAY())>4,F63,0), IF(MONTH(TODAY())>5,G63,0), IF(MONTH(TODAY())>6,H63,0), IF(MONTH(TODAY())>7,I63,0), IF(MONTH(TODAY())>8,J63,0), IF(MONTH(TODAY())>9,K63,0), IF(MONTH(TODAY())>10,L63,0), IF(MONTH(TODAY())>11,M63,0), IF(MONTH(TODAY())>12,N63,0)) -> 0 | C63: {=IFERROR(SUMIF(OtrosR!$C$3:$C$100, $A63, INDEX(OtrosR!$E$3:$P$100, , MATCH(C$1, OtrosR!$E$2:$P$2, 0))), "")} | D63: {=IFERROR(SUMIF(OtrosR!$C$3:$C$100, $A63, INDEX(OtrosR!$E$3:$P$100, , MATCH(D$1, OtrosR!$E$2:$P$2, 0))), "")} | E63: {=IFERROR(SUMIF(OtrosR!$C$3:$C$100, $A63, INDEX(OtrosR!$E$3:$P$100, , MATCH(E$1, OtrosR!$E$2:$P$2, 0))), "")} | F63: {=IFERROR(SUMIF(OtrosR!$C$3:$C$100, $A63, INDEX(OtrosR!$E$3:$P$100, , MATCH(F$1, OtrosR!$E$2:$P$2, 0))), "")} | G63: {=IFERROR(SUMIF(OtrosR!$C$3:$C$100, $A63, INDEX(OtrosR!$E$3:$P$100, , MATCH(G$1, OtrosR!$E$2:$P$2, 0))), "")} | H63: {=IFERROR(SUMIF(OtrosR!$C$3:$C$100, $A63, INDEX(OtrosR!$E$3:$P$100, , MATCH(H$1, OtrosR!$E$2:$P$2, 0))), "")} | I63: {=IFERROR(SUMIF(OtrosR!$C$3:$C$100, $A63, INDEX(OtrosR!$E$3:$P$100, , MATCH(I$1, OtrosR!$E$2:$P$2, 0))), "")} | J63: {=IFERROR(SUMIF(OtrosR!$C$3:$C$100, $A63, INDEX(OtrosR!$E$3:$P$100, , MATCH(J$1, OtrosR!$E$2:$P$2, 0))), "")} | ... N63: {=IFERROR(SUMIF(OtrosR!$C$3:$C$100, $A63, INDEX(OtrosR!$E$3:$P$100, , MATCH(N$1, OtrosR!$E$2:$P$2, 0))), "")}

Sheet Mensual
A1: =VLOOKUP(A2,Menus!E2:L13,5) -> #N/A | B1: =VLOOKUP(A2,Menus!E2:L13,6) -> #N/A | C1: (01) C. Polanco | D1: {=TRANSPOSE(Menus!A2:A65)}
A2: (07) Julio | B2: Total R | C2: =VLOOKUP(A2,Menus!E2:H13,3) -> #N/A | D2: =C2 -> #N/A | E2: =D2 -> #N/A | F2: =E2 -> #N/A | G2: =F2 -> #N/A | H2: =G2 -> #N/A | I2: =H2 -> #N/A | J2: =I2 -> #N/A | K2: =J2 -> #N/A | ... EP2: =EO2 -> #N/A
B3: =VLOOKUP(A2,Menus!E2:L13,7) -> #N/A | C3: =VLOOKUP(A2,Menus!E15:L26,7) -> #N/A
A4: Utilidad Bruta | B4: =B6-B11+B51-B56 -> #N/A | C4: =C6-C11+C51-C56 -> #N/A | D4: =D6-D11+D51-D56 -> #N/A | E4: =E6-E11+E51-E56 -> #N/A | F4: =F6-F11+F51-F56 -> #N/A | G4: =G6-G11+G51-G56 -> #N/A | H4: =H6-H11+H51-H56 -> #N/A | I4: =I6-I11+I51-I56 -> #N/A | ... AQ4: =AQ6-AQ11+AQ51-AQ56 -> #N/A | AR4: =AR6-AR11+AR56 -> #REF! | AS4: =AS6-AS11+AS56 -> #REF! | AT4: =AT6-AT11+AT56 -> #REF! | AU4: =AU6-AU11+AU56 -> #REF! | AV4: =AV6-AV11+AV56 -> #REF! | AW4: =AW6-AW11+AW56 -> #REF! | AX4: =AX6-AX11+AX56 -> #REF! | AY4: =AY6-AY11+AY56 -> #REF! | ... EP4: =EP6-EP11+EP56 -> #REF!
A5: =VLOOKUP(A2,Menus!E28:I39,2) -> #N/A | B5: =VLOOKUP(A2,Menus!E2:L13,8) -> #N/A
A6: Total de Ingresos | B6: =SUM(B7:B9) -> 0 | C6: =SUM(C7:C9) -> 0 | D6: =SUM(D7:D9) -> 0 | E6: =SUM(E7:E9) -> 0 | F6: =SUM(F7:F9) -> 0 | G6: =SUM(G7:G9) -> 0 | H6: =SUM(H7:H9) -> 0 | I6: =SUM(I7:I9) -> 0 | ... EP6: =SUM(EP7:EP9) -> 0
A7: A01 Seguridad | B7: =SUMIF($E$2:$EP$2, $C$2, D7:EP7 ) -> 0 | C7: =IFERROR( LET( resultado, INDEX( INDIRECT($B$1), MATCH(RIGHT($A7, LEN($A7)-4), INDIRECT($B$3), 0), MATCH(C$1, INDIRECT($B$5), 0) ), IF(resultado="-", "", resultado) ), "") | D7: =IFERROR( LET( resultado, INDEX( INDIRECT($B$1), MATCH(RIGHT($A7, LEN($A7)-4), INDIRECT($B$3), 0), MATCH(D$1, INDIRECT($B$5), 0) ), IF(resultado="-", "", resultado) ), "") | E7: =IFERROR( LET( resultado, INDEX( INDIRECT($B$1), MATCH(RIGHT($A7, LEN($A7)-4), INDIRECT($B$3), 0), MATCH(E$1, INDIRECT($B$5), 0) ), IF(resultado="-", "", resultado) ), "") | F7: =IFERROR( LET( resultado, INDEX( INDIRECT($B$1), MATCH(RIGHT($A7, LEN($A7)-4), INDIRECT($B$3), 0), MATCH(F$1, INDIRECT($B$5), 0) ), IF(resultado="-", "", resultado) ), "") | G7: =IFERROR( LET( resultado, INDEX( INDIRECT($B$1), MATCH(RIGHT($A7, LEN($A7)-4), INDIRECT($B$3), 0), MATCH(G$1, INDIRECT($B$5), 0) ), IF(resultado="-", "", resultado) ), "") | H7: =IFERROR( LET( resultado, INDEX( INDIRECT($B$1), MATCH(RIGHT($A7, LEN($A7)-4), INDIRECT($B$3), 0), MATCH(H$1, INDIRECT($B$5), 0) ), IF(resultado="-", "", resultado) ), "") | I7: =IFERROR( LET( resultado, INDEX( INDIRECT($B$1), MATCH(RIGHT($A7, LEN($A7)-4), INDIRECT($B$3), 0), MATCH(I$1, INDIRECT($B$5), 0) ), IF(resultado="-", "", resultado) ), "") | J7: =IFERROR( LET( resultado, INDEX( INDIRECT($B$1), MATCH(RIGHT($A7, LEN($A7)-4), INDIRECT($B$3), 0), MATCH(J$1, INDIRECT($B$5), 0) ), IF(resultado="-", "", resultado) ), "") | ... EP7: =IFERROR( LET( resultado, INDEX( INDIRECT($B$1), MATCH(RIGHT($A7, LEN($A7)-4), INDIRECT($B$3), 0), MATCH(EP$1, INDIRECT($B$5), 0) ), IF(resultado="-", "", resultado) ), "")
A8: A02 Monitoreo | B8: =SUMIF($E$2:$EP$2, $C$2, D8:EP8 ) -> 0 | C8: =IFERROR( LET( resultado, INDEX( INDIRECT($B$1), MATCH(RIGHT($A8, LEN($A8)-4), INDIRECT($B$3), 0), MATCH(C$1, INDIRECT($B$5), 0) ), IF(resultado="-", "", resultado) ), "") | D8: =IFERROR( LET( resultado, INDEX( INDIRECT($B$1), MATCH(RIGHT($A8, LEN($A8)-4), INDIRECT($B$3), 0), MATCH(D$1, INDIRECT($B$5), 0) ), IF(resultado="-", "", resultado) ), "") | E8: =IFERROR( LET( resultado, INDEX( INDIRECT($B$1), MATCH(RIGHT($A8, LEN($A8)-4), INDIRECT($B$3), 0), MATCH(E$1, INDIRECT($B$5), 0) ), IF(resultado="-", "", resultado) ), "") | F8: =IFERROR( LET( resultado, INDEX( INDIRECT($B$1), MATCH(RIGHT($A8, LEN($A8)-4), INDIRECT($B$3), 0), MATCH(F$1, INDIRECT($B$5), 0) ), IF(resultado="-", "", resultado) ), "") | G8: =IFERROR( LET( resultado, INDEX( INDIRECT($B$1), MATCH(RIGHT($A8, LEN($A8)-4), INDIRECT($B$3), 0), MATCH(G$1, INDIRECT($B$5), 0) ), IF(resultado="-", "", resultado) ), "") | H8: =IFERROR( LET( resultado, INDEX( INDIRECT($B$1), MATCH(RIGHT($A8, LEN($A8)-4), INDIRECT($B$3), 0), MATCH(H$1, INDIRECT($B$5), 0) ), IF(resultado="-", "", resultado) ), "") | I8: =IFERROR( LET( resultado, INDEX( INDIRECT($B$1), MATCH(RIGHT($A8, LEN($A8)-4), INDIRECT($B$3), 0), MATCH(I$1, INDIRECT($B$5), 0) ), IF(resultado="-", "", resultado) ), "") | J8: =IFERROR( LET( resultado, INDEX( INDIRECT($B$1), MATCH(RIGHT($A8, LEN($A8)-4), INDIRECT($B$3), 0), MATCH(J$1, INDIRECT($B$5), 0) ), IF(resultado="-", "", resultado) ), "") | ... EP8: =IFERROR( LET( resultado, INDEX( INDIRECT($B$1), MATCH(RIGHT($A8, LEN($A8)-4), INDIRECT($B$3), 0), MATCH(EP$1, INDIRECT($B$5), 0) ), IF(resultado="-", "", resultado) ), "")
B9: =SUMIF($D$2:$EP$2, $C$2, E9:EP9 ) -> 0 | C9: =IFERROR( LET( resultado, INDEX( INDIRECT($B$1), MATCH(RIGHT($A9, LEN($A9)-4), INDIRECT($B$3), 0), MATCH(C$1, INDIRECT($B$5), 0) ), IF(resultado="-", "", resultado) ), "") | D9: =IFERROR( LET( resultado, INDEX( INDIRECT($B$1), MATCH(RIGHT($A9, LEN($A9)-4), INDIRECT($B$3), 0), MATCH(D$1, INDIRECT($B$5), 0) ), IF(resultado="-", "", resultado) ), "") | E9: =IFERROR( LET( resultado, INDEX( INDIRECT($B$1), MATCH(RIGHT($A9, LEN($A9)-4), INDIRECT($B$3), 0), MATCH(E$1, INDIRECT($B$5), 0) ), IF(resultado="-", "", resultado) ), "") | F9: =IFERROR( LET( resultado, INDEX( INDIRECT($B$1), MATCH(RIGHT($A9, LEN($A9)-4), INDIRECT($B$3), 0), MATCH(F$1, INDIRECT($B$5), 0) ), IF(resultado="-", "", resultado) ), "") | G9: =IFERROR( LET( resultado, INDEX( INDIRECT($B$1), MATCH(RIGHT($A9, LEN($A9)-4), INDIRECT($B$3), 0), MATCH(G$1, INDIRECT($B$5), 0) ), IF(resultado="-", "", resultado) ), "") | H9: =IFERROR( LET( resultado, INDEX( INDIRECT($B$1), MATCH(RIGHT($A9, LEN($A9)-4), INDIRECT($B$3), 0), MATCH(H$1, INDIRECT($B$5), 0) ), IF(resultado="-", "", resultado) ), "") | I9: =IFERROR( LET( resultado, INDEX( INDIRECT($B$1), MATCH(RIGHT($A9, LEN($A9)-4), INDIRECT($B$3), 0), MATCH(I$1, INDIRECT($B$5), 0) ), IF(resultado="-", "", resultado) ), "") | J9: =IFERROR( LET( resultado, INDEX( INDIRECT($B$1), MATCH(RIGHT($A9, LEN($A9)-4), INDIRECT($B$3), 0), MATCH(J$1, INDIRECT($B$5), 0) ), IF(resultado="-", "", resultado) ), "") | ... EP9: =IFERROR( LET( resultado, INDEX( INDIRECT($B$1), MATCH(RIGHT($A9, LEN($A9)-4), INDIRECT($B$3), 0), MATCH(EP$1, INDIRECT($B$5), 0) ), IF(resultado="-", "", resultado) ), "")
A11: Total de Egresos | B11: =SUM(B12:B49) -> 0 | C11: =SUM(C12:C49) -> 0 | D11: =SUM(D12:D49) -> 0 | E11: =SUM(E12:E49) -> 0 | F11: =SUM(F12:F49) -> 0 | G11: =SUM(G12:G49) -> 0 | H11: =SUM(H12:H49) -> 0 | I11: =SUM(I12:I49) -> 0 | ... EP11: =SUM(EP12:EP49) -> 0
A12: =Menus!B4 | B12: =SUMIF($E$2:$EP$2, $C$2, D12:EP12 ) -> 0 | C12: =IFERROR( LET( resultado, INDEX( INDIRECT($B$1), MATCH(RIGHT($A12, LEN($A12)-4), INDIRECT($B$3), 0), MATCH(C$1, INDIRECT($B$5), 0) ), IF(resultado="-", "", resultado) ), "") | D12: =IFERROR( LET( resultado, INDEX( INDIRECT($B$1), MATCH(RIGHT($A12, LEN($A12)-4), INDIRECT($B$3), 0), MATCH(D$1, INDIRECT($B$5), 0) ), IF(resultado="-", "", resultado) ), "") | E12: =IFERROR( LET( resultado, INDEX( INDIRECT($B$1), MATCH(RIGHT($A12, LEN($A12)-4), INDIRECT($B$3), 0), MATCH(E$1, INDIRECT($B$5), 0) ), IF(resultado="-", "", resultado) ), "") | F12: =IFERROR( LET( resultado, INDEX( INDIRECT($B$1), MATCH(RIGHT($A12, LEN($A12)-4), INDIRECT($B$3), 0), MATCH(F$1, INDIRECT($B$5), 0) ), IF(resultado="-", "", resultado) ), "") | G12: =IFERROR( LET( resultado, INDEX( INDIRECT($B$1), MATCH(RIGHT($A12, LEN($A12)-4), INDIRECT($B$3), 0), MATCH(G$1, INDIRECT($B$5), 0) ), IF(resultado="-", "", resultado) ), "") | H12: =IFERROR( LET( resultado, INDEX( INDIRECT($B$1), MATCH(RIGHT($A12, LEN($A12)-4), INDIRECT($B$3), 0), MATCH(H$1, INDIRECT($B$5), 0) ), IF(resultado="-", "", resultado) ), "") | I12: =IFERROR( LET( resultado, INDEX( INDIRECT($B$1), MATCH(RIGHT($A12, LEN($A12)-4), INDIRECT($B$3), 0), MATCH(I$1, INDIRECT($B$5), 0) ), IF(resultado="-", "", resultado) ), "") | J12: =IFERROR( LET( resultado, INDEX( INDIRECT($B$1), MATCH(RIGHT($A12, LEN($A12)-4), INDIRECT($B$3), 0), MATCH(J$1, INDIRECT($B$5), 0) ), IF(resultado="-", "", resultado) ), "") | ... EP12: =IFERROR( LET( resultado, INDEX( INDIRECT($B$1), MATCH(RIGHT($A12, LEN($A12)-4), INDIRECT($B$3), 0), MATCH(EP$1, INDIRECT($B$5), 0) ), IF(resultado="-", "", resultado) ), "")
A13: =Menus!B5 | B13: =SUMIF($E$2:$EP$2, $C$2, D13:EP13 ) -> 0 | C13: =IFERROR( LET( resultado, INDEX( INDIRECT($B$1), MATCH(RIGHT($A13, LEN($A13)-4), INDIRECT($B$3), 0), MATCH(C$1, INDIRECT($B$5), 0) ), IF(resultado="-", "", resultado) ), "") | D13: =IFERROR( LET( resultado, INDEX( INDIRECT($B$1), MATCH(RIGHT($A13, LEN($A13)-4), INDIRECT($B$3), 0), MATCH(D$1, INDIRECT($B$5), 0) ), IF(resultado="-", "", resultado) ), "") | E13: =IFERROR( LET( resultado, INDEX( INDIRECT($B$1), MATCH(RIGHT($A13, LEN($A13)-4), INDIRECT($B$3), 0), MATCH(E$1, INDIRECT($B$5), 0) ), IF(resultado="-", "", resultado) ), "") | F13: =IFERROR( LET( resultado, INDEX( INDIRECT($B$1), MATCH(RIGHT($A13, LEN($A13)-4), INDIRECT($B$3), 0), MATCH(F$1, INDIRECT($B$5), 0) ), IF(resultado="-", "", resultado) ), "") | G13: =IFERROR( LET( resultado, INDEX( INDIRECT($B$1), MATCH(RIGHT($A13, LEN($A13)-4), INDIRECT($B$3), 0), MATCH(G$1, INDIRECT($B$5), 0) ), IF(resultado="-", "", resultado) ), "") | H13: =IFERROR( LET( resultado, INDEX( INDIRECT($B$1), MATCH(RIGHT($A13, LEN($A13)-4), INDIRECT($B$3), 0), MATCH(H$1, INDIRECT($B$5), 0) ), IF(resultado="-", "", resultado) ), "") | I13: =IFERROR( LET( resultado, INDEX( INDIRECT($B$1), MATCH(RIGHT($A13, LEN($A13)-4), INDIRECT($B$3), 0), MATCH(I$1, INDIRECT($B$5), 0) ), IF(resultado="-", "", resultado) ), "") | J13: =IFERROR( LET( resultado, INDEX( INDIRECT($B$1), MATCH(RIGHT($A13, LEN($A13)-4), INDIRECT($B$3), 0), MATCH(J$1, INDIRECT($B$5), 0) ), IF(resultado="-", "", resultado) ), "") | ... EP13: =IFERROR( LET( resultado, INDEX( INDIRECT($B$1), MATCH(RIGHT($A13, LEN($A13)-4), INDIRECT($B$3), 0), MATCH(EP$1, INDIRECT($B$5), 0) ), IF(resultado="-", "", resultado) ), "")
A14: =Menus!B6 | B14: =SUMIF($E$2:$EP$2, $C$2, D14:EP14 ) -> 0 | C14: =IFERROR( LET( resultado, INDEX( INDIRECT($B$1), MATCH(RIGHT($A14, LEN($A14)-4), INDIRECT($B$3), 0), MATCH(C$1, INDIRECT($B$5), 0) ), IF(resultado="-", "", resultado) ), "") | D14: =IFERROR( LET( resultado, INDEX( INDIRECT($B$1), MATCH(RIGHT($A14, LEN($A14)-4), INDIRECT($B$3), 0), MATCH(D$1, INDIRECT($B$5), 0) ), IF(resultado="-", "", resultado) ), "") | E14: =IFERROR( LET( resultado, INDEX( INDIRECT($B$1), MATCH(RIGHT($A14, LEN($A14)-4), INDIRECT($B$3), 0), MATCH(E$1, INDIRECT($B$5), 0) ), IF(resultado="-", "", resultado) ), "") | F14: =IFERROR( LET( resultado, INDEX( INDIRECT($B$1), MATCH(RIGHT($A14, LEN($A14)-4), INDIRECT($B$3), 0), MATCH(F$1, INDIRECT($B$5), 0) ), IF(resultado="-", "", resultado) ), "") | G14: =IFERROR( LET( resultado, INDEX( INDIRECT($B$1), MATCH(RIGHT($A14, LEN($A14)-4), INDIRECT($B$3), 0), MATCH(G$1, INDIRECT($B$5), 0) ), IF(resultado="-", "", resultado) ), "") | H14: =IFERROR( LET( resultado, INDEX( INDIRECT($B$1), MATCH(RIGHT($A14, LEN($A14)-4), INDIRECT($B$3), 0), MATCH(H$1, INDIRECT($B$5), 0) ), IF(resultado="-", "", resultado) ), "") | I14: =IFERROR( LET( resultado, INDEX( INDIRECT($B$1), MATCH(RIGHT($A14, LEN($A14)-4), INDIRECT($B$3), 0), MATCH(I$1, INDIRECT($B$5), 0) ), IF(resultado="-", "", resultado) ), "") | J14: =IFERROR( LET( resultado, INDEX( INDIRECT($B$1), MATCH(RIGHT($A14, LEN($A14)-4), INDIRECT($B$3), 0), MATCH(J$1, INDIRECT($B$5), 0) ), IF(resultado="-", "", resultado) ), "") | ... EP14: =IFERROR( LET( resultado, INDEX( INDIRECT($B$1), MATCH(RIGHT($A14, LEN($A14)-4), INDIRECT($B$3), 0), MATCH(EP$1, INDIRECT($B$5), 0) ), IF(resultado="-", "", resultado) ), "")
A15: =Menus!B7 | B15: =SUMIF($E$2:$EP$2, $C$2, D15:EP15 ) -> 0 | C15: =IFERROR( LET( resultado, INDEX( INDIRECT($B$1), MATCH(RIGHT($A15, LEN($A15)-4), INDIRECT($B$3), 0), MATCH(C$1, INDIRECT($B$5), 0) ), IF(resultado="-", "", resultado) ), "") | D15: =IFERROR( LET( resultado, INDEX( INDIRECT($B$1), MATCH(RIGHT($A15, LEN($A15)-4), INDIRECT($B$3), 0), MATCH(D$1, INDIRECT($B$5), 0) ), IF(resultado="-", "", resultado) ), "") | E15: =IFERROR( LET( resultado, INDEX( INDIRECT($B$1), MATCH(RIGHT($A15, LEN($A15)-4), INDIRECT($B$3), 0), MATCH(E$1, INDIRECT($B$5), 0) ), IF(resultado="-", "", resultado) ), "") | F15: =IFERROR( LET( resultado, INDEX( INDIRECT($B$1), MATCH(RIGHT($A15, LEN($A15)-4), INDIRECT($B$3), 0), MATCH(F$1, INDIRECT($B$5), 0) ), IF(resultado="-", "", resultado) ), "") | G15: =IFERROR( LET( resultado, INDEX( INDIRECT($B$1), MATCH(RIGHT($A15, LEN($A15)-4), INDIRECT($B$3), 0), MATCH(G$1, INDIRECT($B$5), 0) ), IF(resultado="-", "", resultado) ), "") | H15: =IFERROR( LET( resultado, INDEX( INDIRECT($B$1), MATCH(RIGHT($A15, LEN($A15)-4), INDIRECT($B$3), 0), MATCH(H$1, INDIRECT($B$5), 0) ), IF(resultado="-", "", resultado) ), "") | I15: =IFERROR( LET( resultado, INDEX( INDIRECT($B$1), MATCH(RIGHT($A15, LEN($A15)-4), INDIRECT($B$3), 0), MATCH(I$1, INDIRECT($B$5), 0) ), IF(resultado="-", "", resultado) ), "") | J15: =IFERROR( LET( resultado, INDEX( INDIRECT($B$1), MATCH(RIGHT($A15, LEN($A15)-4), INDIRECT($B$3), 0), MATCH(J$1, INDIRECT($B$5), 0) ), IF(resultado="-", "", resultado) ), "") | ... EP15: =IFERROR( LET( resultado, INDEX( INDIRECT($B$1), MATCH(RIGHT($A15, LEN($A15)-4), INDIRECT($B$3), 0), MATCH(EP$1, INDIRECT($B$5), 0) ), IF(resultado="-", "", resultado) ), "")
A16: =Menus!B8 | B16: =SUMIF($E$2:$EP$2, $C$2, D16:EP16 ) -> 0 | C16: =IFERROR( LET( resultado, INDEX( INDIRECT($B$1), MATCH(RIGHT($A16, LEN($A16)-4), INDIRECT($B$3), 0), MATCH(C$1, INDIRECT($B$5), 0) ), IF(resultado="-", "", resultado) ), "") | D16: =IFERROR( LET( resultado, INDEX( INDIRECT($B$1), MATCH(RIGHT($A16, LEN($A16)-4), INDIRECT($B$3), 0), MATCH(D$1, INDIRECT($B$5), 0) ), IF(resultado="-", "", resultado) ), "") | E16: =IFERROR( LET( resultado, INDEX( INDIRECT($B$1), MATCH(RIGHT($A16, LEN($A16)-4), INDIRECT($B$3), 0), MATCH(E$1, INDIRECT($B$5), 0) ), IF(resultado="-", "", resultado) ), "") | F16: =IFERROR( LET( resultado, INDEX( INDIRECT($B$1), MATCH(RIGHT($A16, LEN($A16)-4), INDIRECT($B$3), 0), MATCH(F$1, INDIRECT($B$5), 0) ), IF(resultado="-", "", resultado) ), "") | G16: =IFERROR( LET( resultado, INDEX( INDIRECT($B$1), MATCH(RIGHT($A16, LEN($A16)-4), INDIRECT($B$3), 0), MATCH(G$1, INDIRECT($B$5), 0) ), IF(resultado="-", "", resultado) ), "") | H16: =IFERROR( LET( resultado, INDEX( INDIRECT($B$1), MATCH(RIGHT($A16, LEN($A16)-4), INDIRECT($B$3), 0), MATCH(H$1, INDIRECT($B$5), 0) ), IF(resultado="-", "", resultado) ), "") | I16: =IFERROR( LET( resultado, INDEX( INDIRECT($B$1), MATCH(RIGHT($A16, LEN($A16)-4), INDIRECT($B$3), 0), MATCH(I$1, INDIRECT($B$5), 0) ), IF(resultado="-", "", resultado) ), "") | J16: =IFERROR( LET( resultado, INDEX( INDIRECT($B$1), MATCH(RIGHT($A16, LEN($A16)-4), INDIRECT($B$3), 0), MATCH(J$1, INDIRECT($B$5), 0) ), IF(resultado="-", "", resultado) ), "") | ... EP16: =IFERROR( LET( resultado, INDEX( INDIRECT($B$1), MATCH(RIGHT($A16, LEN($A16)-4), INDIRECT($B$3), 0), MATCH(EP$1, INDIRECT($B$5), 0) ), IF(resultado="-", "", resultado) ), "")
A17: =Menus!B9 | B17: =SUMIF($E$2:$EP$2, $C$2, D17:EP17 ) -> 0 | C17: =IFERROR( LET( resultado, INDEX( INDIRECT($B$1), MATCH(RIGHT($A17, LEN($A17)-4), INDIRECT($B$3), 0), MATCH(C$1, INDIRECT($B$5), 0) ), IF(resultado="-", "", resultado) ), "") | D17: =IFERROR( LET( resultado, INDEX( INDIRECT($B$1), MATCH(RIGHT($A17, LEN($A17)-4), INDIRECT($B$3), 0), MATCH(D$1, INDIRECT($B$5), 0) ), IF(resultado="-", "", resultado) ), "") | E17: =IFERROR( LET( resultado, INDEX( INDIRECT($B$1), MATCH(RIGHT($A17, LEN($A17)-4), INDIRECT($B$3), 0), MATCH(E$1, INDIRECT($B$5), 0) ), IF(resultado="-", "", resultado) ), "") | F17: =IFERROR( LET( resultado, INDEX( INDIRECT($B$1), MATCH(RIGHT($A17, LEN($A17)-4), INDIRECT($B$3), 0), MATCH(F$1, INDIRECT($B$5), 0) ), IF(resultado="-", "", resultado) ), "") | G17: =IFERROR( LET( resultado, INDEX( INDIRECT($B$1), MATCH(RIGHT($A17, LEN($A17)-4), INDIRECT($B$3), 0), MATCH(G$1, INDIRECT($B$5), 0) ), IF(resultado="-", "", resultado) ), "") | H17: =IFERROR( LET( resultado, INDEX( INDIRECT($B$1), MATCH(RIGHT($A17, LEN($A17)-4), INDIRECT($B$3), 0), MATCH(H$1, INDIRECT($B$5), 0) ), IF(resultado="-", "", resultado) ), "") | I17: =IFERROR( LET( resultado, INDEX( INDIRECT($B$1), MATCH(RIGHT($A17, LEN($A17)-4), INDIRECT($B$3), 0), MATCH(I$1, INDIRECT($B$5), 0) ), IF(resultado="-", "", resultado) ), "") | J17: =IFERROR( LET( resultado, INDEX( INDIRECT($B$1), MATCH(RIGHT($A17, LEN($A17)-4), INDIRECT($B$3), 0), MATCH(J$1, INDIRECT($B$5), 0) ), IF(resultado="-", "", resultado) ), "") | ... EP17: =IFERROR( LET( resultado, INDEX( INDIRECT($B$1), MATCH(RIGHT($A17, LEN($A17)-4), INDIRECT($B$3), 0), MATCH(EP$1, INDIRECT($B$5), 0) ), IF(resultado="-", "", resultado) ), "")
A18: =Menus!B10 | B18: =SUMIF($E$2:$EP$2, $C$2, D18:EP18 ) -> 0 | C18: =IFERROR( LET( resultado, INDEX( INDIRECT($B$1), MATCH(RIGHT($A18, LEN($A18)-4), INDIRECT($B$3), 0), MATCH(C$1, INDIRECT($B$5), 0) ), IF(resultado="-", "", resultado) ), "") | D18: =IFERROR( LET( resultado, INDEX( INDIRECT($B$1), MATCH(RIGHT($A18, LEN($A18)-4), INDIRECT($B$3), 0), MATCH(D$1, INDIRECT($B$5), 0) ), IF(resultado="-", "", resultado) ), "") | E18: =IFERROR( LET( resultado, INDEX( INDIRECT($B$1), MATCH(RIGHT($A18, LEN($A18)-4), INDIRECT($B$3), 0), MATCH(E$1, INDIRECT($B$5), 0) ), IF(resultado="-", "", resultado) ), "") | F18: =IFERROR( LET( resultado, INDEX( INDIRECT($B$1), MATCH(RIGHT($A18, LEN($A18)-4), INDIRECT($B$3), 0), MATCH(F$1, INDIRECT($B$5), 0) ), IF(resultado="-", "", resultado) ), "") | G18: =IFERROR( LET( resultado, INDEX( INDIRECT($B$1), MATCH(RIGHT($A18, LEN($A18)-4), INDIRECT($B$3), 0), MATCH(G$1, INDIRECT($B$5), 0) ), IF(resultado="-", "", resultado) ), "") | H18: =IFERROR( LET( resultado, INDEX( INDIRECT($B$1), MATCH(RIGHT($A18, LEN($A18)-4), INDIRECT($B$3), 0), MATCH(H$1, INDIRECT($B$5), 0) ), IF(resultado="-", "", resultado) ), "") | I18: =IFERROR( LET( resultado, INDEX( INDIRECT($B$1), MATCH(RIGHT($A18, LEN($A18)-4), INDIRECT($B$3), 0), MATCH(I$1, INDIRECT($B$5), 0) ), IF(resultado="-", "", resultado) ), "") | J18: =IFERROR( LET( resultado, INDEX( INDIRECT($B$1), MATCH(RIGHT($A18, LEN($A18)-4), INDIRECT($B$3), 0), MATCH(J$1, INDIRECT($B$5), 0) ), IF(resultado="-", "", resultado) ), "") | ... EP18: =IFERROR( LET( resultado, INDEX( INDIRECT($B$1), MATCH(RIGHT($A18, LEN($A18)-4), INDIRECT($B$3), 0), MATCH(EP$1, INDIRECT($B$5), 0) ), IF(resultado="-", "", resultado) ), "")
A19: =Menus!B11 | B19: =SUMIF($E$2:$EP$2, $C$2, D19:EP19 ) -> 0 | C19: =IFERROR( LET( resultado, INDEX( INDIRECT($B$1), MATCH(RIGHT($A19, LEN($A19)-4), INDIRECT($B$3), 0), MATCH(C$1, INDIRECT($B$5), 0) ), IF(resultado="-", "", resultado) ), "") | D19: =IFERROR( LET( resultado, INDEX( INDIRECT($B$1), MATCH(RIGHT($A19, LEN($A19)-4), INDIRECT($B$3), 0), MATCH(D$1, INDIRECT($B$5), 0) ), IF(resultado="-", "", resultado) ), "") | E19: =IFERROR( LET( resultado, INDEX( INDIRECT($B$1), MATCH(RIGHT($A19, LEN($A19)-4), INDIRECT($B$3), 0), MATCH(E$1, INDIRECT($B$5), 0) ), IF(resultado="-", "", resultado) ), "") | F19: =IFERROR( LET( resultado, INDEX( INDIRECT($B$1), MATCH(RIGHT($A19, LEN($A19)-4), INDIRECT($B$3), 0), MATCH(F$1, INDIRECT($B$5), 0) ), IF(resultado="-", "", resultado) ), "") | G19: =IFERROR( LET( resultado, INDEX( INDIRECT($B$1), MATCH(RIGHT($A19, LEN($A19)-4), INDIRECT($B$3), 0), MATCH(G$1, INDIRECT($B$5), 0) ), IF(resultado="-", "", resultado) ), "") | H19: =IFERROR( LET( resultado, INDEX( INDIRECT($B$1), MATCH(RIGHT($A19, LEN($A19)-4), INDIRECT($B$3), 0), MATCH(H$1, INDIRECT($B$5), 0) ), IF(resultado="-", "", resultado) ), "") | I19: =IFERROR( LET( resultado, INDEX( INDIRECT($B$1), MATCH(RIGHT($A19, LEN($A19)-4), INDIRECT($B$3), 0), MATCH(I$1, INDIRECT($B$5), 0) ), IF(resultado="-", "", resultado) ), "") | J19: =IFERROR( LET( resultado, INDEX( INDIRECT($B$1), MATCH(RIGHT($A19, LEN($A19)-4), INDIRECT($B$3), 0), MATCH(J$1, INDIRECT($B$5), 0) ), IF(resultado="-", "", resultado) ), "") | ... EP19: =IFERROR( LET( resultado, INDEX( INDIRECT($B$1), MATCH(RIGHT($A19, LEN($A19)-4), INDIRECT($B$3), 0), MATCH(EP$1, INDIRECT($B$5), 0) ), IF(resultado="-", "", resultado) ), "")
A20: =Menus!B12 | B20: =SUMIF($E$2:$EP$2, $C$2, D20:EP20 ) -> 0 | C20: =IFERROR( LET( resultado, INDEX( INDIRECT($B$1), MATCH(RIGHT($A20, LEN($A20)-4), INDIRECT($B$3), 0), MATCH(C$1, INDIRECT($B$5), 0) ), IF(resultado="-", "", resultado) ), "") | D20: =IFERROR( LET( resultado, INDEX( INDIRECT($B$1), MATCH(RIGHT($A20, LEN($A20)-4), INDIRECT($B$3), 0), MATCH(D$1, INDIRECT($B$5), 0) ), IF(resultado="-", "", resultado) ), "") | E20: =IFERROR( LET( resultado, INDEX( INDIRECT($B$1), MATCH(RIGHT($A20, LEN($A20)-4), INDIRECT($B$3), 0), MATCH(E$1, INDIRECT($B$5), 0) ), IF(resultado="-", "", resultado) ), "") | F20: =IFERROR( LET( resultado, INDEX( INDIRECT($B$1), MATCH(RIGHT($A20, LEN($A20)-4), INDIRECT($B$3), 0), MATCH(F$1, INDIRECT($B$5), 0) ), IF(resultado="-", "", resultado) ), "") | G20: =IFERROR( LET( resultado, INDEX( INDIRECT($B$1), MATCH(RIGHT($A20, LEN($A20)-4), INDIRECT($B$3), 0), MATCH(G$1, INDIRECT($B$5), 0) ), IF(resultado="-", "", resultado) ), "") | H20: =IFERROR( LET( resultado, INDEX( INDIRECT($B$1), MATCH(RIGHT($A20, LEN($A20)-4), INDIRECT($B$3), 0), MATCH(H$1, INDIRECT($B$5), 0) ), IF(resultado="-", "", resultado) ), "") | I20: =IFERROR( LET( resultado, INDEX( INDIRECT($B$1), MATCH(RIGHT($A20, LEN($A20)-4), INDIRECT($B$3), 0), MATCH(I$1, INDIRECT($B$5), 0) ), IF(resultado="-", "", resultado) ), "") | J20: =IFERROR( LET( resultado, INDEX( INDIRECT($B$1), MATCH(RIGHT($A20, LEN($A20)-4), INDIRECT($B$3), 0), MATCH(J$1, INDIRECT($B$5), 0) ), IF(resultado="-", "", resultado) ), "") | ... EP20: =IFERROR( LET( resultado, INDEX( INDIRECT($B$1), MATCH(RIGHT($A20, LEN($A20)-4), INDIRECT($B$3), 0), MATCH(EP$1, INDIRECT($B$5), 0) ), IF(resultado="-", "", resultado) ), "")
A21: =Menus!B13 | B21: =SUMIF($E$2:$EP$2, $C$2, D21:EP21 ) -> 0 | C21: =IFERROR( LET( resultado, INDEX( INDIRECT($B$1), MATCH(RIGHT($A21, LEN($A21)-4), INDIRECT($B$3), 0), MATCH(C$1, INDIRECT($B$5), 0) ), IF(resultado="-", "", resultado) ), "") | D21: =IFERROR( LET( resultado, INDEX( INDIRECT($B$1), MATCH(RIGHT($A21, LEN($A21)-4), INDIRECT($B$3), 0), MATCH(D$1, INDIRECT($B$5), 0) ), IF(resultado="-", "", resultado) ), "") | E21: =IFERROR( LET( resultado, INDEX( INDIRECT($B$1), MATCH(RIGHT($A21, LEN($A21)-4), INDIRECT($B$3), 0), MATCH(E$1, INDIRECT($B$5), 0) ), IF(resultado="-", "", resultado) ), "") | F21: =IFERROR( LET( resultado, INDEX( INDIRECT($B$1), MATCH(RIGHT($A21, LEN($A21)-4), INDIRECT($B$3), 0), MATCH(F$1, INDIRECT($B$5), 0) ), IF(resultado="-", "", resultado) ), "") | G21: =IFERROR( LET( resultado, INDEX( INDIRECT($B$1), MATCH(RIGHT($A21, LEN($A21)-4), INDIRECT($B$3), 0), MATCH(G$1, INDIRECT($B$5), 0) ), IF(resultado="-", "", resultado) ), "") | H21: =IFERROR( LET( resultado, INDEX( INDIRECT($B$1), MATCH(RIGHT($A21, LEN($A21)-4), INDIRECT($B$3), 0), MATCH(H$1, INDIRECT($B$5), 0) ), IF(resultado="-", "", resultado) ), "") | I21: =IFERROR( LET( resultado, INDEX( INDIRECT($B$1), MATCH(RIGHT($A21, LEN($A21)-4), INDIRECT($B$3), 0), MATCH(I$1, INDIRECT($B$5), 0) ), IF(resultado="-", "", resultado) ), "") | J21: =IFERROR( LET( resultado, INDEX( INDIRECT($B$1), MATCH(RIGHT($A21, LEN($A21)-4), INDIRECT($B$3), 0), MATCH(J$1, INDIRECT($B$5), 0) ), IF(resultado="-", "", resultado) ), "") | ... EP21: =IFERROR( LET( resultado, INDEX( INDIRECT($B$1), MATCH(RIGHT($A21, LEN($A21)-4), INDIRECT($B$3), 0), MATCH(EP$1, INDIRECT($B$5), 0) ), IF(resultado="-", "", resultado) ), "")
A22: =Menus!B14 | B22: =SUMIF($E$2:$EP$2, $C$2, D22:EP22 ) -> 0 | C22: =IFERROR( LET( resultado, INDEX( INDIRECT($B$1), MATCH(RIGHT($A22, LEN($A22)-4), INDIRECT($B$3), 0), MATCH(C$1, INDIRECT($B$5), 0) ), IF(resultado="-", "", resultado) ), "") | D22: =IFERROR( LET( resultado, INDEX( INDIRECT($B$1), MATCH(RIGHT($A22, LEN($A22)-4), INDIRECT($B$3), 0), MATCH(D$1, INDIRECT($B$5), 0) ), IF(resultado="-", "", resultado) ), "") | E22: =IFERROR( LET( resultado, INDEX( INDIRECT($B$1), MATCH(RIGHT($A22, LEN($A22)-4), INDIRECT($B$3), 0), MATCH(E$1, INDIRECT($B$5), 0) ), IF(resultado="-", "", resultado) ), "") | F22: =IFERROR( LET( resultado, INDEX( INDIRECT($B$1), MATCH(RIGHT($A22, LEN($A22)-4), INDIRECT($B$3), 0), MATCH(F$1, INDIRECT($B$5), 0) ), IF(resultado="-", "", resultado) ), "") | G22: =IFERROR( LET( resultado, INDEX( INDIRECT($B$1), MATCH(RIGHT($A22, LEN($A22)-4), INDIRECT($B$3), 0), MATCH(G$1, INDIRECT($B$5), 0) ), IF(resultado="-", "", resultado) ), "") | H22: =IFERROR( LET( resultado, INDEX( INDIRECT($B$1), MATCH(RIGHT($A22, LEN($A22)-4), INDIRECT($B$3), 0), MATCH(H$1, INDIRECT($B$5), 0) ), IF(resultado="-", "", resultado) ), "") | I22: =IFERROR( LET( resultado, INDEX( INDIRECT($B$1), MATCH(RIGHT($A22, LEN($A22)-4), INDIRECT($B$3), 0), MATCH(I$1, INDIRECT($B$5), 0) ), IF(resultado="-", "", resultado) ), "") | J22: =IFERROR( LET( resultado, INDEX( INDIRECT($B$1), MATCH(RIGHT($A22, LEN($A22)-4), INDIRECT($B$3), 0), MATCH(J$1, INDIRECT($B$5), 0) ), IF(resultado="-", "", resultado) ), "") | ... EP22: =IFERROR( LET( resultado, INDEX( INDIRECT($B$1), MATCH(RIGHT($A22, LEN($A22)-4), INDIRECT($B$3), 0), MATCH(EP$1, INDIRECT($B$5), 0) ), IF(resultado="-", "", resultado) ), "")
A23: =Menus!B15 | B23: =SUMIF($E$2:$EP$2, $C$2, D23:EP23 ) -> 0 | C23: =IFERROR( LET( resultado, INDEX( INDIRECT($B$1), MATCH(RIGHT($A23, LEN($A23)-4), INDIRECT($B$3), 0), MATCH(C$1, INDIRECT($B$5), 0) ), IF(resultado="-", "", resultado) ), "") | D23: =IFERROR( LET( resultado, INDEX( INDIRECT($B$1), MATCH(RIGHT($A23, LEN($A23)-4), INDIRECT($B$3), 0), MATCH(D$1, INDIRECT($B$5), 0) ), IF(resultado="-", "", resultado) ), "") | E23: =IFERROR( LET( resultado, INDEX( INDIRECT($B$1), MATCH(RIGHT($A23, LEN($A23)-4), INDIRECT($B$3), 0), MATCH(E$1, INDIRECT($B$5), 0) ), IF(resultado="-", "", resultado) ), "") | F23: =IFERROR( LET( resultado, INDEX( INDIRECT($B$1), MATCH(RIGHT($A23, LEN($A23)-4), INDIRECT($B$3), 0), MATCH(F$1, INDIRECT($B$5), 0) ), IF(resultado="-", "", resultado) ), "") | G23: =IFERROR( LET( resultado, INDEX( INDIRECT($B$1), MATCH(RIGHT($A23, LEN($A23)-4), INDIRECT($B$3), 0), MATCH(G$1, INDIRECT($B$5), 0) ), IF(resultado="-", "", resultado) ), "") | H23: =IFERROR( LET( resultado, INDEX( INDIRECT($B$1), MATCH(RIGHT($A23, LEN($A23)-4), INDIRECT($B$3), 0), MATCH(H$1, INDIRECT($B$5), 0) ), IF(resultado="-", "", resultado) ), "") | I23: =IFERROR( LET( resultado, INDEX( INDIRECT($B$1), MATCH(RIGHT($A23, LEN($A23)-4), INDIRECT($B$3), 0), MATCH(I$1, INDIRECT($B$5), 0) ), IF(resultado="-", "", resultado) ), "") | J23: =IFERROR( LET( resultado, INDEX( INDIRECT($B$1), MATCH(RIGHT($A23, LEN($A23)-4), INDIRECT($B$3), 0), MATCH(J$1, INDIRECT($B$5), 0) ), IF(resultado="-", "", resultado) ), "") | ... EP23: =IFERROR( LET( resultado, INDEX( INDIRECT($B$1), MATCH(RIGHT($A23, LEN($A23)-4), INDIRECT($B$3), 0), MATCH(EP$1, INDIRECT($B$5), 0) ), IF(resultado="-", "", resultado) ), "")
... A42: =Menus!B34 | B42: =SUMIF($E$2:$EP$2, $C$2, D42:EP42 ) -> 0 | C42: =IFERROR( LET( resultado, INDEX( INDIRECT($B$1), MATCH(RIGHT($A42, LEN($A42)-4), INDIRECT($B$3), 0), MATCH(C$1, INDIRECT($B$5), 0) ), IF(resultado="-", "", resultado) ), "") | D42: =IFERROR( LET( resultado, INDEX( INDIRECT($B$1), MATCH(RIGHT($A42, LEN($A42)-4), INDIRECT($B$3), 0), MATCH(D$1, INDIRECT($B$5), 0) ), IF(resultado="-", "", resultado) ), "") | E42: =IFERROR( LET( resultado, INDEX( INDIRECT($B$1), MATCH(RIGHT($A42, LEN($A42)-4), INDIRECT($B$3), 0), MATCH(E$1, INDIRECT($B$5), 0) ), IF(resultado="-", "", resultado) ), "") | F42: =IFERROR( LET( resultado, INDEX( INDIRECT($B$1), MATCH(RIGHT($A42, LEN($A42)-4), INDIRECT($B$3), 0), MATCH(F$1, INDIRECT($B$5), 0) ), IF(resultado="-", "", resultado) ), "") | G42: =IFERROR( LET( resultado, INDEX( INDIRECT($B$1), MATCH(RIGHT($A42, LEN($A42)-4), INDIRECT($B$3), 0), MATCH(G$1, INDIRECT($B$5), 0) ), IF(resultado="-", "", resultado) ), "") | H42: =IFERROR( LET( resultado, INDEX( INDIRECT($B$1), MATCH(RIGHT($A42, LEN($A42)-4), INDIRECT($B$3), 0), MATCH(H$1, INDIRECT($B$5), 0) ), IF(resultado="-", "", resultado) ), "") | I42: =IFERROR( LET( resultado, INDEX( INDIRECT($B$1), MATCH(RIGHT($A42, LEN($A42)-4), INDIRECT($B$3), 0), MATCH(I$1, INDIRECT($B$5), 0) ), IF(resultado="-", "", resultado) ), "") | J42: =IFERROR( LET( resultado, INDEX( INDIRECT($B$1), MATCH(RIGHT($A42, LEN($A42)-4), INDIRECT($B$3), 0), MATCH(J$1, INDIRECT($B$5), 0) ), IF(resultado="-", "", resultado) ), "") | ... EP42: =IFERROR( LET( resultado, INDEX( INDIRECT($B$1), MATCH(RIGHT($A42, LEN($A42)-4), INDIRECT($B$3), 0), MATCH(EP$1, INDIRECT($B$5), 0) ), IF(resultado="-", "", resultado) ), "")
A43: =Menus!B36 | B43: =SUMIF($E$2:$EP$2, $C$2, D43:EP43 ) -> 0 | C43: =IFERROR( LET( resultado, INDEX( INDIRECT($B$1), MATCH(RIGHT($A43, LEN($A43)-4), INDIRECT($B$3), 0), MATCH(C$1, INDIRECT($B$5), 0) ), IF(resultado="-", "", resultado) ), "") | D43: =IFERROR( LET( resultado, INDEX( INDIRECT($B$1), MATCH(RIGHT($A43, LEN($A43)-4), INDIRECT($B$3), 0), MATCH(D$1, INDIRECT($B$5), 0) ), IF(resultado="-", "", resultado) ), "") | E43: =IFERROR( LET( resultado, INDEX( INDIRECT($B$1), MATCH(RIGHT($A43, LEN($A43)-4), INDIRECT($B$3), 0), MATCH(E$1, INDIRECT($B$5), 0) ), IF(resultado="-", "", resultado) ), "") | F43: =IFERROR( LET( resultado, INDEX( INDIRECT($B$1), MATCH(RIGHT($A43, LEN($A43)-4), INDIRECT($B$3), 0), MATCH(F$1, INDIRECT($B$5), 0) ), IF(resultado="-", "", resultado) ), "") | G43: =IFERROR( LET( resultado, INDEX( INDIRECT($B$1), MATCH(RIGHT($A43, LEN($A43)-4), INDIRECT($B$3), 0), MATCH(G$1, INDIRECT($B$5), 0) ), IF(resultado="-", "", resultado) ), "") | H43: =IFERROR( LET( resultado, INDEX( INDIRECT($B$1), MATCH(RIGHT($A43, LEN($A43)-4), INDIRECT($B$3), 0), MATCH(H$1, INDIRECT($B$5), 0) ), IF(resultado="-", "", resultado) ), "") | I43: =IFERROR( LET( resultado, INDEX( INDIRECT($B$1), MATCH(RIGHT($A43, LEN($A43)-4), INDIRECT($B$3), 0), MATCH(I$1, INDIRECT($B$5), 0) ), IF(resultado="-", "", resultado) ), "") | J43: =IFERROR( LET( resultado, INDEX( INDIRECT($B$1), MATCH(RIGHT($A43, LEN($A43)-4), INDIRECT($B$3), 0), MATCH(J$1, INDIRECT($B$5), 0) ), IF(resultado="-", "", resultado) ), "") | ... EP43: =IFERROR( LET( resultado, INDEX( INDIRECT($B$1), MATCH(RIGHT($A43, LEN($A43)-4), INDIRECT($B$3), 0), MATCH(EP$1, INDIRECT($B$5), 0) ), IF(resultado="-", "", resultado) ), "")
A44: =Menus!B37 | B44: =SUMIF($E$2:$EP$2, $C$2, D44:EP44 ) -> 0 | C44: =IFERROR( LET( resultado, INDEX( INDIRECT($B$1), MATCH(RIGHT($A44, LEN($A44)-4), INDIRECT($B$3), 0), MATCH(C$1, INDIRECT($B$5), 0) ), IF(resultado="-", "", resultado) ), "") | D44: =IFERROR( LET( resultado, INDEX( INDIRECT($B$1), MATCH(RIGHT($A44, LEN($A44)-4), INDIRECT($B$3), 0), MATCH(D$1, INDIRECT($B$5), 0) ), IF(resultado="-", "", resultado) ), "") | E44: =IFERROR( LET( resultado, INDEX( INDIRECT($B$1), MATCH(RIGHT($A44, LEN($A44)-4), INDIRECT($B$3), 0), MATCH(E$1, INDIRECT($B$5), 0) ), IF(resultado="-", "", resultado) ), "") | F44: =IFERROR( LET( resultado, INDEX( INDIRECT($B$1), MATCH(RIGHT($A44, LEN($A44)-4), INDIRECT($B$3), 0), MATCH(F$1, INDIRECT($B$5), 0) ), IF(resultado="-", "", resultado) ), "") | G44: =IFERROR( LET( resultado, INDEX( INDIRECT($B$1), MATCH(RIGHT($A44, LEN($A44)-4), INDIRECT($B$3), 0), MATCH(G$1, INDIRECT($B$5), 0) ), IF(resultado="-", "", resultado) ), "") | H44: =IFERROR( LET( resultado, INDEX( INDIRECT($B$1), MATCH(RIGHT($A44, LEN($A44)-4), INDIRECT($B$3), 0), MATCH(H$1, INDIRECT($B$5), 0) ), IF(resultado="-", "", resultado) ), "") | I44: =IFERROR( LET( resultado, INDEX( INDIRECT($B$1), MATCH(RIGHT($A44, LEN($A44)-4), INDIRECT($B$3), 0), MATCH(I$1, INDIRECT($B$5), 0) ), IF(resultado="-", "", resultado) ), "") | J44: =IFERROR( LET( resultado, INDEX( INDIRECT($B$1), MATCH(RIGHT($A44, LEN($A44)-4), INDIRECT($B$3), 0), MATCH(J$1, INDIRECT($B$5), 0) ), IF(resultado="-", "", resultado) ), "") | ... EP44: =IFERROR( LET( resultado, INDEX( INDIRECT($B$1), MATCH(RIGHT($A44, LEN($A44)-4), INDIRECT($B$3), 0), MATCH(EP$1, INDIRECT($B$5), 0) ), IF(resultado="-", "", resultado) ), "")
A45: =Menus!B38 | B45: =SUMIF($E$2:$EP$2, $C$2, D45:EP45 ) -> 0 | C45: =IFERROR( LET( resultado, INDEX( INDIRECT($B$1), MATCH(RIGHT($A45, LEN($A45)-4), INDIRECT($B$3), 0), MATCH(C$1, INDIRECT($B$5), 0) ), IF(resultado="-", "", resultado) ), "") | D45: =IFERROR( LET( resultado, INDEX( INDIRECT($B$1), MATCH(RIGHT($A45, LEN($A45)-4), INDIRECT($B$3), 0), MATCH(D$1, INDIRECT($B$5), 0) ), IF(resultado="-", "", resultado) ), "") | E45: =IFERROR( LET( resultado, INDEX( INDIRECT($B$1), MATCH(RIGHT($A45, LEN($A45)-4), INDIRECT($B$3), 0), MATCH(E$1, INDIRECT($B$5), 0) ), IF(resultado="-", "", resultado) ), "") | F45: =IFERROR( LET( resultado, INDEX( INDIRECT($B$1), MATCH(RIGHT($A45, LEN($A45)-4), INDIRECT($B$3), 0), MATCH(F$1, INDIRECT($B$5), 0) ), IF(resultado="-", "", resultado) ), "") | G45: =IFERROR( LET( resultado, INDEX( INDIRECT($B$1), MATCH(RIGHT($A45, LEN($A45)-4), INDIRECT($B$3), 0), MATCH(G$1, INDIRECT($B$5), 0) ), IF(resultado="-", "", resultado) ), "") | H45: =IFERROR( LET( resultado, INDEX( INDIRECT($B$1), MATCH(RIGHT($A45, LEN($A45)-4), INDIRECT($B$3), 0), MATCH(H$1, INDIRECT($B$5), 0) ), IF(resultado="-", "", resultado) ), "") | I45: =IFERROR( LET( resultado, INDEX( INDIRECT($B$1), MATCH(RIGHT($A45, LEN($A45)-4), INDIRECT($B$3), 0), MATCH(I$1, INDIRECT($B$5), 0) ), IF(resultado="-", "", resultado) ), "") | J45: =IFERROR( LET( resultado, INDEX( INDIRECT($B$1), MATCH(RIGHT($A45, LEN($A45)-4), INDIRECT($B$3), 0), MATCH(J$1, INDIRECT($B$5), 0) ), IF(resultado="-", "", resultado) ), "") | ... EP45: =IFERROR( LET( resultado, INDEX( INDIRECT($B$1), MATCH(RIGHT($A45, LEN($A45)-4), INDIRECT($B$3), 0), MATCH(EP$1, INDIRECT($B$5), 0) ), IF(resultado="-", "", resultado) ), "")
A46: =Menus!B39 | B46: =SUMIF($E$2:$EP$2, $C$2, D46:EP46 ) -> 0 | C46: =IFERROR( LET( resultado, INDEX( INDIRECT($B$1), MATCH(RIGHT($A46, LEN($A46)-4), INDIRECT($B$3), 0), MATCH(C$1, INDIRECT($B$5), 0) ), IF(resultado="-", "", resultado) ), "") | D46: =IFERROR( LET( resultado, INDEX( INDIRECT($B$1), MATCH(RIGHT($A46, LEN($A46)-4), INDIRECT($B$3), 0), MATCH(D$1, INDIRECT($B$5), 0) ), IF(resultado="-", "", resultado) ), "") | E46: =IFERROR( LET( resultado, INDEX( INDIRECT($B$1), MATCH(RIGHT($A46, LEN($A46)-4), INDIRECT($B$3), 0), MATCH(E$1, INDIRECT($B$5), 0) ), IF(resultado="-", "", resultado) ), "") | F46: =IFERROR( LET( resultado, INDEX( INDIRECT($B$1), MATCH(RIGHT($A46, LEN($A46)-4), INDIRECT($B$3), 0), MATCH(F$1, INDIRECT($B$5), 0) ), IF(resultado="-", "", resultado) ), "") | G46: =IFERROR( LET( resultado, INDEX( INDIRECT($B$1), MATCH(RIGHT($A46, LEN($A46)-4), INDIRECT($B$3), 0), MATCH(G$1, INDIRECT($B$5), 0) ), IF(resultado="-", "", resultado) ), "") | H46: =IFERROR( LET( resultado, INDEX( INDIRECT($B$1), MATCH(RIGHT($A46, LEN($A46)-4), INDIRECT($B$3), 0), MATCH(H$1, INDIRECT($B$5), 0) ), IF(resultado="-", "", resultado) ), "") | I46: =IFERROR( LET( resultado, INDEX( INDIRECT($B$1), MATCH(RIGHT($A46, LEN($A46)-4), INDIRECT($B$3), 0), MATCH(I$1, INDIRECT($B$5), 0) ), IF(resultado="-", "", resultado) ), "") | J46: =IFERROR( LET( resultado, INDEX( INDIRECT($B$1), MATCH(RIGHT($A46, LEN($A46)-4), INDIRECT($B$3), 0), MATCH(J$1, INDIRECT($B$5), 0) ), IF(resultado="-", "", resultado) ), "") | ... EP46: =IFERROR( LET( resultado, INDEX( INDIRECT($B$1), MATCH(RIGHT($A46, LEN($A46)-4), INDIRECT($B$3), 0), MATCH(EP$1, INDIRECT($B$5), 0) ), IF(resultado="-", "", resultado) ), "")
A47: =Menus!B40 | B47: =SUMIF($E$2:$EP$2, $C$2, D47:EP47 ) -> 0 | C47: =IFERROR( LET( resultado, INDEX( INDIRECT($B$1), MATCH(RIGHT($A47, LEN($A47)-4), INDIRECT($B$3), 0), MATCH(C$1, INDIRECT($B$5), 0) ), IF(resultado="-", "", resultado) ), "") | D47: =IFERROR( LET( resultado, INDEX( INDIRECT($B$1), MATCH(RIGHT($A47, LEN($A47)-4), INDIRECT($B$3), 0), MATCH(D$1, INDIRECT($B$5), 0) ), IF(resultado="-", "", resultado) ), "") | E47: =IFERROR( LET( resultado, INDEX( INDIRECT($B$1), MATCH(RIGHT($A47, LEN($A47)-4), INDIRECT($B$3), 0), MATCH(E$1, INDIRECT($B$5), 0) ), IF(resultado="-", "", resultado) ), "") | F47: =IFERROR( LET( resultado, INDEX( INDIRECT($B$1), MATCH(RIGHT($A47, LEN($A47)-4), INDIRECT($B$3), 0), MATCH(F$1, INDIRECT($B$5), 0) ), IF(resultado="-", "", resultado) ), "") | G47: =IFERROR( LET( resultado, INDEX( INDIRECT($B$1), MATCH(RIGHT($A47, LEN($A47)-4), INDIRECT($B$3), 0), MATCH(G$1, INDIRECT($B$5), 0) ), IF(resultado="-", "", resultado) ), "") | H47: =IFERROR( LET( resultado, INDEX( INDIRECT($B$1), MATCH(RIGHT($A47, LEN($A47)-4), INDIRECT($B$3), 0), MATCH(H$1, INDIRECT($B$5), 0) ), IF(resultado="-", "", resultado) ), "") | I47: =IFERROR( LET( resultado, INDEX( INDIRECT($B$1), MATCH(RIGHT($A47, LEN($A47)-4), INDIRECT($B$3), 0), MATCH(I$1, INDIRECT($B$5), 0) ), IF(resultado="-", "", resultado) ), "") | J47: =IFERROR( LET( resultado, INDEX( INDIRECT($B$1), MATCH(RIGHT($A47, LEN($A47)-4), INDIRECT($B$3), 0), MATCH(J$1, INDIRECT($B$5), 0) ), IF(resultado="-", "", resultado) ), "") | ... EP47: =IFERROR( LET( resultado, INDEX( INDIRECT($B$1), MATCH(RIGHT($A47, LEN($A47)-4), INDIRECT($B$3), 0), MATCH(EP$1, INDIRECT($B$5), 0) ), IF(resultado="-", "", resultado) ), "")
A48: =Menus!B41 | B48: =SUMIF($E$2:$EP$2, $C$2, D48:EP48 ) -> 0 | C48: =IFERROR( LET( resultado, INDEX( INDIRECT($B$1), MATCH(RIGHT($A48, LEN($A48)-4), INDIRECT($B$3), 0), MATCH(C$1, INDIRECT($B$5), 0) ), IF(resultado="-", "", resultado) ), "") | D48: =IFERROR( LET( resultado, INDEX( INDIRECT($B$1), MATCH(RIGHT($A48, LEN($A48)-4), INDIRECT($B$3), 0), MATCH(D$1, INDIRECT($B$5), 0) ), IF(resultado="-", "", resultado) ), "") | E48: =IFERROR( LET( resultado, INDEX( INDIRECT($B$1), MATCH(RIGHT($A48, LEN($A48)-4), INDIRECT($B$3), 0), MATCH(E$1, INDIRECT($B$5), 0) ), IF(resultado="-", "", resultado) ), "") | F48: =IFERROR( LET( resultado, INDEX( INDIRECT($B$1), MATCH(RIGHT($A48, LEN($A48)-4), INDIRECT($B$3), 0), MATCH(F$1, INDIRECT($B$5), 0) ), IF(resultado="-", "", resultado) ), "") | G48: =IFERROR( LET( resultado, INDEX( INDIRECT($B$1), MATCH(RIGHT($A48, LEN($A48)-4), INDIRECT($B$3), 0), MATCH(G$1, INDIRECT($B$5), 0) ), IF(resultado="-", "", resultado) ), "") | H48: =IFERROR( LET( resultado, INDEX( INDIRECT($B$1), MATCH(RIGHT($A48, LEN($A48)-4), INDIRECT($B$3), 0), MATCH(H$1, INDIRECT($B$5), 0) ), IF(resultado="-", "", resultado) ), "") | I48: =IFERROR( LET( resultado, INDEX( INDIRECT($B$1), MATCH(RIGHT($A48, LEN($A48)-4), INDIRECT($B$3), 0), MATCH(I$1, INDIRECT($B$5), 0) ), IF(resultado="-", "", resultado) ), "") | J48: =IFERROR( LET( resultado, INDEX( INDIRECT($B$1), MATCH(RIGHT($A48, LEN($A48)-4), INDIRECT($B$3), 0), MATCH(J$1, INDIRECT($B$5), 0) ), IF(resultado="-", "", resultado) ), "") | ... EP48: =IFERROR( LET( resultado, INDEX( INDIRECT($B$1), MATCH(RIGHT($A48, LEN($A48)-4), INDIRECT($B$3), 0), MATCH(EP$1, INDIRECT($B$5), 0) ), IF(resultado="-", "", resultado) ), "")
A49: =Menus!B42 | B49: =SUMIF($E$2:$EP$2, $C$2, D49:EP49 ) -> 0 | C49: =IFERROR( LET( resultado, INDEX( INDIRECT($B$1), MATCH(RIGHT($A49, LEN($A49)-4), INDIRECT($B$3), 0), MATCH(C$1, INDIRECT($B$5), 0) ), IF(resultado="-", "", resultado) ), "") | D49: =IFERROR( LET( resultado, INDEX( INDIRECT($B$1), MATCH(RIGHT($A49, LEN($A49)-4), INDIRECT($B$3), 0), MATCH(D$1, INDIRECT($B$5), 0) ), IF(resultado="-", "", resultado) ), "") | E49: =IFERROR( LET( resultado, INDEX( INDIRECT($B$1), MATCH(RIGHT($A49, LEN($A49)-4), INDIRECT($B$3), 0), MATCH(E$1, INDIRECT($B$5), 0) ), IF(resultado="-", "", resultado) ), "") | F49: =IFERROR( LET( resultado, INDEX( INDIRECT($B$1), MATCH(RIGHT($A49, LEN($A49)-4), INDIRECT($B$3), 0), MATCH(F$1, INDIRECT($B$5), 0) ), IF(resultado="-", "", resultado) ), "") | G49: =IFERROR( LET( resultado, INDEX( INDIRECT($B$1), MATCH(RIGHT($A49, LEN($A49)-4), INDIRECT($B$3), 0), MATCH(G$1, INDIRECT($B$5), 0) ), IF(resultado="-", "", resultado) ), "") | H49: =IFERROR( LET( resultado, INDEX( INDIRECT($B$1), MATCH(RIGHT($A49, LEN($A49)-4), INDIRECT($B$3), 0), MATCH(H$1, INDIRECT($B$5), 0) ), IF(resultado="-", "", resultado) ), "") | I49: =IFERROR( LET( resultado, INDEX( INDIRECT($B$1), MATCH(RIGHT($A49, LEN($A49)-4), INDIRECT($B$3), 0), MATCH(I$1, INDIRECT($B$5), 0) ), IF(resultado="-", "", resultado) ), "") | J49: =IFERROR( LET( resultado, INDEX( INDIRECT($B$1), MATCH(RIGHT($A49, LEN($A49)-4), INDIRECT($B$3), 0), MATCH(J$1, INDIRECT($B$5), 0) ), IF(resultado="-", "", resultado) ), "") | ... EP49: =IFERROR( LET( resultado, INDEX( INDIRECT($B$1), MATCH(RIGHT($A49, LEN($A49)-4), INDIRECT($B$3), 0), MATCH(EP$1, INDIRECT($B$5), 0) ), IF(resultado="-", "", resultado) ), "")
A51: Otros Ingresos | B51: =SUM(B52:B54) -> #N/A | C51: =SUM(C52:C54) -> #N/A | D51: =SUM(D52:D54) -> #N/A | E51: =SUM(E52:E54) -> #N/A | F51: =SUM(F52:F54) -> #N/A | G51: =SUM(G52:G54) -> #N/A | H51: =SUM(H52:H54) -> #N/A | I51: =SUM(I52:I54) -> #N/A | ... AQ51: =SUM(AQ52:AQ54) -> #N/A
A52: =Menus!Q2 | B52: =SUMIF($E$2:$EP$2, $C$2, D52:EP52 ) -> #N/A | C52: {=SUM(SUMIFS(INDIRECT($A$5),OtrosR!$C$3:$C65,$A52,OtrosR!$B$3:$B65,C$1))} -> #N/A | D52: {=SUM(SUMIFS(INDIRECT($A$5),OtrosR!$C$3:$C65,$A52,OtrosR!$B$3:$B65,D$1))} -> #N/A | E52: {=SUM(SUMIFS(INDIRECT($A$5),OtrosR!$C$3:$C65,$A52,OtrosR!$B$3:$B65,E$1))} -> #N/A | F52: {=SUM(SUMIFS(INDIRECT($A$5),OtrosR!$C$3:$C65,$A52,OtrosR!$B$3:$B65,F$1))} -> #N/A | G52: {=SUM(SUMIFS(INDIRECT($A$5),OtrosR!$C$3:$C65,$A52,OtrosR!$B$3:$B65,G$1))} -> #N/A | H52: {=SUM(SUMIFS(INDIRECT($A$5),OtrosR!$C$3:$C65,$A52,OtrosR!$B$3:$B65,H$1))} -> #N/A | I52: {=SUM(SUMIFS(INDIRECT($A$5),OtrosR!$C$3:$C65,$A52,OtrosR!$B$3:$B65,I$1))} -> #N/A | J52: {=SUM(SUMIFS(INDIRECT($A$5),OtrosR!$C$3:$C65,$A52,OtrosR!$B$3:$B65,J$1))} -> #N/A | ... EP52: {=SUM(SUMIFS(INDIRECT($A$5),OtrosR!$C$3:$C65,$A52,OtrosR!$B$3:$B65,EP$1))} -> #N/A
B53: =SUMIF($E$2:$EP$2, $C$2, D53:EP53 ) -> #N/A | C53: {=SUM(SUMIFS(INDIRECT($A$5),OtrosR!$C$3:$C65,$A53,OtrosR!$B$3:$B65,C$1))} -> #N/A | D53: {=SUM(SUMIFS(INDIRECT($A$5),OtrosR!$C$3:$C65,$A53,OtrosR!$B$3:$B65,D$1))} -> #N/A | E53: {=SUM(SUMIFS(INDIRECT($A$5),OtrosR!$C$3:$C65,$A53,OtrosR!$B$3:$B65,E$1))} -> #N/A | F53: {=SUM(SUMIFS(INDIRECT($A$5),OtrosR!$C$3:$C65,$A53,OtrosR!$B$3:$B65,F$1))} -> #N/A | G53: {=SUM(SUMIFS(INDIRECT($A$5),OtrosR!$C$3:$C65,$A53,OtrosR!$B$3:$B65,G$1))} -> #N/A | H53: {=SUM(SUMIFS(INDIRECT($A$5),OtrosR!$C$3:$C65,$A53,OtrosR!$B$3:$B65,H$1))} -> #N/A | I53: {=SUM(SUMIFS(INDIRECT($A$5),OtrosR!$C$3:$C65,$A53,OtrosR!$B$3:$B65,I$1))} -> #N/A | J53: {=SUM(SUMIFS(INDIRECT($A$5),OtrosR!$C$3:$C65,$A53,OtrosR!$B$3:$B65,J$1))} -> #N/A | ... EP53: {=SUM(SUMIFS(INDIRECT($A$5),OtrosR!$C$3:$C65,$A53,OtrosR!$B$3:$B65,EP$1))} -> #N/A
B54: =SUMIF($E$2:$EP$2, $C$2, D54:EP54 ) -> #N/A | C54: {=SUM(SUMIFS(INDIRECT($A$5),OtrosR!$C$3:$C65,$A54,OtrosR!$B$3:$B65,C$1))} -> #N/A | D54: {=SUM(SUMIFS(INDIRECT($A$5),OtrosR!$C$3:$C65,$A54,OtrosR!$B$3:$B65,D$1))} -> #N/A | E54: {=SUM(SUMIFS(INDIRECT($A$5),OtrosR!$C$3:$C65,$A54,OtrosR!$B$3:$B65,E$1))} -> #N/A | F54: {=SUM(SUMIFS(INDIRECT($A$5),OtrosR!$C$3:$C65,$A54,OtrosR!$B$3:$B65,F$1))} -> #N/A | G54: {=SUM(SUMIFS(INDIRECT($A$5),OtrosR!$C$3:$C65,$A54,OtrosR!$B$3:$B65,G$1))} -> #N/A | H54: {=SUM(SUMIFS(INDIRECT($A$5),OtrosR!$C$3:$C65,$A54,OtrosR!$B$3:$B65,H$1))} -> #N/A | I54: {=SUM(SUMIFS(INDIRECT($A$5),OtrosR!$C$3:$C65,$A54,OtrosR!$B$3:$B65,I$1))} -> #N/A | J54: {=SUM(SUMIFS(INDIRECT($A$5),OtrosR!$C$3:$C65,$A54,OtrosR!$B$3:$B65,J$1))} -> #N/A | ... EP54: {=SUM(SUMIFS(INDIRECT($A$5),OtrosR!$C$3:$C65,$A54,OtrosR!$B$3:$B65,EP$1))} -> #N/A
A56: Otros Egresos | B56: =SUM(B57:B65) -> #N/A | C56: =SUM(C57:C65) -> #N/A | D56: =SUM(D57:D65) -> #N/A | E56: =SUM(E57:E65) -> #N/A | F56: =SUM(F57:F65) -> #N/A | G56: =SUM(G57:G65) -> #N/A | H56: =SUM(H57:H65) -> #N/A | I56: =SUM(I57:I65) -> #N/A | ... AQ56: =SUM(AQ57:AQ65) -> #N/A | AR56: =SUM(AR52:AR65) -> #REF! | AS56: =SUM(AS52:AS65) -> #REF! | AT56: =SUM(AT52:AT65) -> #REF! | AU56: =SUM(AU52:AU65) -> #REF! | AV56: =SUM(AV52:AV65) -> #REF! | AW56: =SUM(AW52:AW65) -> #REF! | AX56: =SUM(AX52:AX65) -> #REF! | AY56: =SUM(AY52:AY65) -> #REF! | ... EP56: =SUM(EP52:EP65) -> #REF!
A57: =Menus!Q3 | B57: =SUMIF($E$2:$EP$2, $C$2, D57:EP57 ) -> #N/A | C57: {=SUM(SUMIFS(INDIRECT($A$5),OtrosR!$C$3:$C65,$A57,OtrosR!$B$3:$B65,C$1))} -> #N/A | D57: {=SUM(SUMIFS(INDIRECT($A$5),OtrosR!$C$3:$C65,$A57,OtrosR!$B$3:$B65,D$1))} -> #N/A | E57: {=SUM(SUMIFS(INDIRECT($A$5),OtrosR!$C$3:$C65,$A57,OtrosR!$B$3:$B65,E$1))} -> #N/A | F57: {=SUM(SUMIFS(INDIRECT($A$5),OtrosR!$C$3:$C65,$A57,OtrosR!$B$3:$B65,F$1))} -> #N/A | G57: {=SUM(SUMIFS(INDIRECT($A$5),OtrosR!$C$3:$C65,$A57,OtrosR!$B$3:$B65,G$1))} -> #N/A | H57: {=SUM(SUMIFS(INDIRECT($A$5),OtrosR!$C$3:$C65,$A57,OtrosR!$B$3:$B65,H$1))} -> #N/A | I57: {=SUM(SUMIFS(INDIRECT($A$5),OtrosR!$C$3:$C65,$A57,OtrosR!$B$3:$B65,I$1))} -> #N/A | J57: {=SUM(SUMIFS(INDIRECT($A$5),OtrosR!$C$3:$C65,$A57,OtrosR!$B$3:$B65,J$1))} -> #N/A | ... EP57: {=SUM(SUMIFS(INDIRECT($A$5),OtrosR!$C$3:$C65,$A57,OtrosR!$B$3:$B65,EP$1))} -> #N/A
A58: =Menus!Q4 | B58: =SUMIF($E$2:$EP$2, $C$2, D58:EP58 ) -> #N/A | C58: {=SUM(SUMIFS(INDIRECT($A$5),OtrosR!$C$3:$C65,$A58,OtrosR!$B$3:$B65,C$1))} -> #N/A | D58: {=SUM(SUMIFS(INDIRECT($A$5),OtrosR!$C$3:$C65,$A58,OtrosR!$B$3:$B65,D$1))} -> #N/A | E58: {=SUM(SUMIFS(INDIRECT($A$5),OtrosR!$C$3:$C65,$A58,OtrosR!$B$3:$B65,E$1))} -> #N/A | F58: {=SUM(SUMIFS(INDIRECT($A$5),OtrosR!$C$3:$C65,$A58,OtrosR!$B$3:$B65,F$1))} -> #N/A | G58: {=SUM(SUMIFS(INDIRECT($A$5),OtrosR!$C$3:$C65,$A58,OtrosR!$B$3:$B65,G$1))} -> #N/A | H58: {=SUM(SUMIFS(INDIRECT($A$5),OtrosR!$C$3:$C65,$A58,OtrosR!$B$3:$B65,H$1))} -> #N/A | I58: {=SUM(SUMIFS(INDIRECT($A$5),OtrosR!$C$3:$C65,$A58,OtrosR!$B$3:$B65,I$1))} -> #N/A | J58: {=SUM(SUMIFS(INDIRECT($A$5),OtrosR!$C$3:$C65,$A58,OtrosR!$B$3:$B65,J$1))} -> #N/A | ... EP58: {=SUM(SUMIFS(INDIRECT($A$5),OtrosR!$C$3:$C65,$A58,OtrosR!$B$3:$B65,EP$1))} -> #N/A
A59: =Menus!Q5 | B59: =SUMIF($E$2:$EP$2, $C$2, D59:EP59 ) -> #N/A | C59: {=SUM(SUMIFS(INDIRECT($A$5),OtrosR!$C$3:$C65,$A59,OtrosR!$B$3:$B65,C$1))} -> #N/A | D59: {=SUM(SUMIFS(INDIRECT($A$5),OtrosR!$C$3:$C65,$A59,OtrosR!$B$3:$B65,D$1))} -> #N/A | E59: {=SUM(SUMIFS(INDIRECT($A$5),OtrosR!$C$3:$C65,$A59,OtrosR!$B$3:$B65,E$1))} -> #N/A | F59: {=SUM(SUMIFS(INDIRECT($A$5),OtrosR!$C$3:$C65,$A59,OtrosR!$B$3:$B65,F$1))} -> #N/A | G59: {=SUM(SUMIFS(INDIRECT($A$5),OtrosR!$C$3:$C65,$A59,OtrosR!$B$3:$B65,G$1))} -> #N/A | H59: {=SUM(SUMIFS(INDIRECT($A$5),OtrosR!$C$3:$C65,$A59,OtrosR!$B$3:$B65,H$1))} -> #N/A | I59: {=SUM(SUMIFS(INDIRECT($A$5),OtrosR!$C$3:$C65,$A59,OtrosR!$B$3:$B65,I$1))} -> #N/A | J59: {=SUM(SUMIFS(INDIRECT($A$5),OtrosR!$C$3:$C65,$A59,OtrosR!$B$3:$B65,J$1))} -> #N/A | ... EP59: {=SUM(SUMIFS(INDIRECT($A$5),OtrosR!$C$3:$C65,$A59,OtrosR!$B$3:$B65,EP$1))} -> #N/A
A60: =Menus!Q6 | B60: =SUMIF($E$2:$EP$2, $C$2, D60:EP60 ) -> #N/A | C60: {=SUM(SUMIFS(INDIRECT($A$5),OtrosR!$C$3:$C65,$A60,OtrosR!$B$3:$B65,C$1))} -> #N/A | D60: {=SUM(SUMIFS(INDIRECT($A$5),OtrosR!$C$3:$C65,$A60,OtrosR!$B$3:$B65,D$1))} -> #N/A | E60: {=SUM(SUMIFS(INDIRECT($A$5),OtrosR!$C$3:$C65,$A60,OtrosR!$B$3:$B65,E$1))} -> #N/A | F60: {=SUM(SUMIFS(INDIRECT($A$5),OtrosR!$C$3:$C65,$A60,OtrosR!$B$3:$B65,F$1))} -> #N/A | G60: {=SUM(SUMIFS(INDIRECT($A$5),OtrosR!$C$3:$C65,$A60,OtrosR!$B$3:$B65,G$1))} -> #N/A | H60: {=SUM(SUMIFS(INDIRECT($A$5),OtrosR!$C$3:$C65,$A60,OtrosR!$B$3:$B65,H$1))} -> #N/A | I60: {=SUM(SUMIFS(INDIRECT($A$5),OtrosR!$C$3:$C65,$A60,OtrosR!$B$3:$B65,I$1))} -> #N/A | J60: {=SUM(SUMIFS(INDIRECT($A$5),OtrosR!$C$3:$C65,$A60,OtrosR!$B$3:$B65,J$1))} -> #N/A | ... EP60: {=SUM(SUMIFS(INDIRECT($A$5),OtrosR!$C$3:$C65,$A60,OtrosR!$B$3:$B65,EP$1))} -> #N/A
A61: =Menus!Q7 | B61: =SUMIF($E$2:$EP$2, $C$2, D61:EP61 ) -> #N/A | C61: {=SUM(SUMIFS(INDIRECT($A$5),OtrosR!$C$3:$C65,$A61,OtrosR!$B$3:$B65,C$1))} -> #N/A | D61: {=SUM(SUMIFS(INDIRECT($A$5),OtrosR!$C$3:$C65,$A61,OtrosR!$B$3:$B65,D$1))} -> #N/A | E61: {=SUM(SUMIFS(INDIRECT($A$5),OtrosR!$C$3:$C65,$A61,OtrosR!$B$3:$B65,E$1))} -> #N/A | F61: {=SUM(SUMIFS(INDIRECT($A$5),OtrosR!$C$3:$C65,$A61,OtrosR!$B$3:$B65,F$1))} -> #N/A | G61: {=SUM(SUMIFS(INDIRECT($A$5),OtrosR!$C$3:$C65,$A61,OtrosR!$B$3:$B65,G$1))} -> #N/A | H61: {=SUM(SUMIFS(INDIRECT($A$5),OtrosR!$C$3:$C65,$A61,OtrosR!$B$3:$B65,H$1))} -> #N/A | I61: {=SUM(SUMIFS(INDIRECT($A$5),OtrosR!$C$3:$C65,$A61,OtrosR!$B$3:$B65,I$1))} -> #N/A | J61: {=SUM(SUMIFS(INDIRECT($A$5),OtrosR!$C$3:$C65,$A61,OtrosR!$B$3:$B65,J$1))} -> #N/A | ... EP61: {=SUM(SUMIFS(INDIRECT($A$5),OtrosR!$C$3:$C65,$A61,OtrosR!$B$3:$B65,EP$1))} -> #N/A
A62: =Menus!Q8 | B62: =SUMIF($E$2:$EP$2, $C$2, D62:EP62 ) -> #N/A | C62: {=SUM(SUMIFS(INDIRECT($A$5),OtrosR!$C$3:$C65,$A62,OtrosR!$B$3:$B65,C$1))} -> #N/A | D62: {=SUM(SUMIFS(INDIRECT($A$5),OtrosR!$C$3:$C65,$A62,OtrosR!$B$3:$B65,D$1))} -> #N/A | E62: {=SUM(SUMIFS(INDIRECT($A$5),OtrosR!$C$3:$C65,$A62,OtrosR!$B$3:$B65,E$1))} -> #N/A | F62: {=SUM(SUMIFS(INDIRECT($A$5),OtrosR!$C$3:$C65,$A62,OtrosR!$B$3:$B65,F$1))} -> #N/A | G62: {=SUM(SUMIFS(INDIRECT($A$5),OtrosR!$C$3:$C65,$A62,OtrosR!$B$3:$B65,G$1))} -> #N/A | H62: {=SUM(SUMIFS(INDIRECT($A$5),OtrosR!$C$3:$C65,$A62,OtrosR!$B$3:$B65,H$1))} -> #N/A | I62: {=SUM(SUMIFS(INDIRECT($A$5),OtrosR!$C$3:$C65,$A62,OtrosR!$B$3:$B65,I$1))} -> #N/A | J62: {=SUM(SUMIFS(INDIRECT($A$5),OtrosR!$C$3:$C65,$A62,OtrosR!$B$3:$B65,J$1))} -> #N/A | ... EP62: {=SUM(SUMIFS(INDIRECT($A$5),OtrosR!$C$3:$C65,$A62,OtrosR!$B$3:$B65,EP$1))} -> #N/A
A63: =Menus!Q9 | B63: =SUMIF($E$2:$EP$2, $C$2, D63:EP63 ) -> #N/A | C63: {=SUM(SUMIFS(INDIRECT($A$5),OtrosR!$C$3:$C65,$A63,OtrosR!$B$3:$B65,C$1))} -> #N/A | D63: {=SUM(SUMIFS(INDIRECT($A$5),OtrosR!$C$3:$C65,$A63,OtrosR!$B$3:$B65,D$1))} -> #N/A | E63: {=SUM(SUMIFS(INDIRECT($A$5),OtrosR!$C$3:$C65,$A63,OtrosR!$B$3:$B65,E$1))} -> #N/A | F63: {=SUM(SUMIFS(INDIRECT($A$5),OtrosR!$C$3:$C65,$A63,OtrosR!$B$3:$B65,F$1))} -> #N/A | G63: {=SUM(SUMIFS(INDIRECT($A$5),OtrosR!$C$3:$C65,$A63,OtrosR!$B$3:$B65,G$1))} -> #N/A | H63: {=SUM(SUMIFS(INDIRECT($A$5),OtrosR!$C$3:$C65,$A63,OtrosR!$B$3:$B65,H$1))} -> #N/A | I63: {=SUM(SUMIFS(INDIRECT($A$5),OtrosR!$C$3:$C65,$A63,OtrosR!$B$3:$B65,I$1))} -> #N/A | J63: {=SUM(SUMIFS(INDIRECT($A$5),OtrosR!$C$3:$C65,$A63,OtrosR!$B$3:$B65,J$1))} -> #N/A | ... EP63: {=SUM(SUMIFS(INDIRECT($A$5),OtrosR!$C$3:$C65,$A63,OtrosR!$B$3:$B65,EP$1))} -> #N/A
A64: =Menus!Q10 | B64: =SUMIF($E$2:$EP$2, $C$2, D64:EP64 ) -> #N/A | C64: {=SUM(SUMIFS(INDIRECT($A$5),OtrosR!$C$3:$C65,$A64,OtrosR!$B$3:$B65,C$1))} -> #N/A | D64: {=SUM(SUMIFS(INDIRECT($A$5),OtrosR!$C$3:$C65,$A64,OtrosR!$B$3:$B65,D$1))} -> #N/A | E64: {=SUM(SUMIFS(INDIRECT($A$5),OtrosR!$C$3:$C65,$A64,OtrosR!$B$3:$B65,E$1))} -> #N/A | F64: {=SUM(SUMIFS(INDIRECT($A$5),OtrosR!$C$3:$C65,$A64,OtrosR!$B$3:$B65,F$1))} -> #N/A | G64: {=SUM(SUMIFS(INDIRECT($A$5),OtrosR!$C$3:$C65,$A64,OtrosR!$B$3:$B65,G$1))} -> #N/A | H64: {=SUM(SUMIFS(INDIRECT($A$5),OtrosR!$C$3:$C65,$A64,OtrosR!$B$3:$B65,H$1))} -> #N/A | I64: {=SUM(SUMIFS(INDIRECT($A$5),OtrosR!$C$3:$C65,$A64,OtrosR!$B$3:$B65,I$1))} -> #N/A | J64: {=SUM(SUMIFS(INDIRECT($A$5),OtrosR!$C$3:$C65,$A64,OtrosR!$B$3:$B65,J$1))} -> #N/A | ... EP64: {=SUM(SUMIFS(INDIRECT($A$5),OtrosR!$C$3:$C65,$A64,OtrosR!$B$3:$B65,EP$1))} -> #N/A
A65: =Menus!Q11 | B65: =SUMIF($E$2:$EP$2, $C$2, D65:EP65 ) -> #N/A | C65: {=SUM(SUMIFS(INDIRECT($A$5),OtrosR!$C$3:$C65,$A65,OtrosR!$B$3:$B65,C$1))} -> #N/A | D65: {=SUM(SUMIFS(INDIRECT($A$5),OtrosR!$C$3:$C65,$A65,OtrosR!$B$3:$B65,D$1))} -> #N/A | E65: {=SUM(SUMIFS(INDIRECT($A$5),OtrosR!$C$3:$C65,$A65,OtrosR!$B$3:$B65,E$1))} -> #N/A | F65: {=SUM(SUMIFS(INDIRECT($A$5),OtrosR!$C$3:$C65,$A65,OtrosR!$B$3:$B65,F$1))} -> #N/A | G65: {=SUM(SUMIFS(INDIRECT($A$5),OtrosR!$C$3:$C65,$A65,OtrosR!$B$3:$B65,G$1))} -> #N/A | H65: {=SUM(SUMIFS(INDIRECT($A$5),OtrosR!$C$3:$C65,$A65,OtrosR!$B$3:$B65,H$1))} -> #N/A | I65: {=SUM(SUMIFS(INDIRECT($A$5),OtrosR!$C$3:$C65,$A65,OtrosR!$B$3:$B65,I$1))} -> #N/A | J65: {=SUM(SUMIFS(INDIRECT($A$5),OtrosR!$C$3:$C65,$A65,OtrosR!$B$3:$B65,J$1))} -> #N/A | ... EP65: {=SUM(SUMIFS(INDIRECT($A$5),OtrosR!$C$3:$C65,$A65,OtrosR!$B$3:$B65,EP$1))} -> #N/A

Sheet xProyecto
A1: (01) C. Polanco | B1: Anual R | C1: Enero | D1: Febrero | E1: Marzo | F1: Abril | G1: Mayo | H1: Junio | I1: Julio | J1: Agosto | K1: Septiembre | L1: Octubre | M1: Noviembre | N1: Diciembre
A3: Utilidad Bruta | B3: =B5-B10+B51-B56 -> 2191000 | C3: =C5-C10+C51-C56 -> 313000 | D3: =D5-D10+D51-D56 -> 313000 | E3: =E5-E10+E51-E56 -> 313000 | F3: =F5-F10+F51-F56 -> 313000 | G3: =G5-G10+G51-G56 -> 313000 | H3: =H5-H10+H51-H56 -> 313000 | I3: =I5-I10+I51-I56 -> 313000 | ... N3: =N5-N10+N51-N56 -> 0
A5: Total de Ingresos | B5: =SUM(B6:B8) -> 2191000 | C5: =SUM(C6:C8) -> 313000 | D5: =SUM(D6:D8) -> 313000 | E5: =SUM(E6:E8) -> 313000 | F5: =SUM(F6:F8) -> 313000 | G5: =SUM(G6:G8) -> 313000 | H5: =SUM(H6:H8) -> 313000 | I5: =SUM(I6:I8) -> 313000 | ... N5: =SUM(N6:N8) -> 0
A6: A01 Seguridad | B6: =C6+D6+E6+F6+G6+H6+I6+J6+K6+L6+M6+N6 -> 2191000 | C6: {=IFERROR( LET( valor, INDEX( EneR!$A$1:$AT$48, MATCH(RIGHT($A6, LEN($A6)-4), EneR!$A$1:$A1065, 0), MATCH($A$1, EneR!$A$6:N$6, 0) ), IF(valor = "-", "", valor) ), "")} -> 313000 | D6: {=IFERROR( LET( valor, INDEX( FebR!$A$1:$AT$51, MATCH(RIGHT($A6, LEN($A6)-4), FebR!$A$1:$A1065, 0), MATCH($A$1, FebR!$A$6:N$6, 0) ), IF(valor = "-", "", valor) ), "")} -> 313000 | E6: {=IFERROR( LET( valor, INDEX( MarR!$A$1:$AT$48, MATCH(RIGHT($A6, LEN($A6)-4), MarR!$A$1:$A1065, 0), MATCH($A$1, MarR!$A$6:N$6, 0) ), IF(valor = "-", "", valor) ), "")} -> 313000 | F6: {=IFERROR( LET( valor, INDEX( AbrR!$A$1:$AT$48, MATCH(RIGHT($A6, LEN($A6)-4), AbrR!$A$1:$A1065, 0), MATCH($A$1, AbrR!$A$6:N$6, 0) ), IF(valor = "-", "", valor) ), "")} -> 313000 | G6: {=IFERROR( LET( valor, INDEX( MayR!$A$1:$AT$48, MATCH(RIGHT($A6, LEN($A6)-4), MayR!$A$1:$A1065, 0), MATCH($A$1, MayR!$A$6:N$6, 0) ), IF(valor = "-", "", valor) ), "")} -> 313000 | H6: {=IFERROR( LET( valor, INDEX( JunR!$A$1:$AT$48, MATCH(RIGHT($A6, LEN($A6)-4), JunR!$A$1:$A1065, 0), MATCH($A$1, JunR!$A$6:N$6, 0) ), IF(valor = "-", "", valor) ), "")} -> 313000 | I6: {=IFERROR( LET( valor, INDEX( JulR!$A$1:$AT$48, MATCH(RIGHT($A6, LEN($A6)-4), JulR!$A$1:$A1065, 0), MATCH($A$1, JulR!$A$6:N$6, 0) ), IF(valor = "-", "", valor) ), "")} -> 313000 | J6: {=IFERROR( LET( valor, INDEX( AgoR!$A$1:$AT$60, MATCH(RIGHT($A6, LEN($A6)-4), AgoR!$A$1:$A1065, 0), MATCH($A$1, AgoR!$A$6:N$6, 0) ), IF(valor = "-", "", valor) ), "")} | K6: {=IFERROR( LET( valor, INDEX( SepR!$A$1:$AT$60, MATCH(RIGHT($A6, LEN($A6)-4), SepR!$A$1:$A1065, 0), MATCH($A$1, SepR!$A$6:N$6, 0) ), IF(valor = "-", "", valor) ), "")} | L6: {=IFERROR( LET( valor, INDEX( OctR!$A$1:$AT$60, MATCH(RIGHT($A6, LEN($A6)-4), OctR!$A$1:$A1065, 0), MATCH($A$1, OctR!$A$6:N$6, 0) ), IF(valor = "-", "", valor) ), "")} | M6: {=IFERROR( LET( valor, INDEX( NovR!$A$1:$AT$60, MATCH(RIGHT($A6, LEN($A6)-4), NovR!$A$1:$A1065, 0), MATCH($A$1, NovR!$A$6:N$6, 0) ), IF(valor = "-", "", valor) ), "")} | N6: {=IFERROR( LET( valor, INDEX( DicR!$A$1:$AT$60, MATCH(RIGHT($A6, LEN($A6)-4), DicR!$A$1:$A1065, 0), MATCH($A$1, DicR!$A$6:N$6, 0) ), IF(valor = "-", "", valor) ), "")}
A7: A02 Monitoreo | B7: =C7+D7+E7+F7+G7+H7+I7+J7+K7+L7+M7+N7 -> 0 | C7: {=IFERROR( LET( valor, INDEX( EneR!$A$1:$AT$48, MATCH(RIGHT($A7, LEN($A7)-4), EneR!$A$1:$A1065, 0), MATCH($A$1, EneR!$A$6:N$6, 0) ), IF(valor = "-", "", valor) ), "")} | D7: {=IFERROR( LET( valor, INDEX( FebR!$A$1:$AT$51, MATCH(RIGHT($A7, LEN($A7)-4), FebR!$A$1:$A1065, 0), MATCH($A$1, FebR!$A$6:N$6, 0) ), IF(valor = "-", "", valor) ), "")} | E7: {=IFERROR( LET( valor, INDEX( MarR!$A$1:$AT$48, MATCH(RIGHT($A7, LEN($A7)-4), MarR!$A$1:$A1065, 0), MATCH($A$1, MarR!$A$6:N$6, 0) ), IF(valor = "-", "", valor) ), "")} | F7: {=IFERROR( LET( valor, INDEX( AbrR!$A$1:$AT$48, MATCH(RIGHT($A7, LEN($A7)-4), AbrR!$A$1:$A1065, 0), MATCH($A$1, AbrR!$A$6:N$6, 0) ), IF(valor = "-", "", valor) ), "")} | G7: {=IFERROR( LET( valor, INDEX( MayR!$A$1:$AT$48, MATCH(RIGHT($A7, LEN($A7)-4), MayR!$A$1:$A1065, 0), MATCH($A$1, MayR!$A$6:N$6, 0) ), IF(valor = "-", "", valor) ), "")} | H7: {=IFERROR( LET( valor, INDEX( JunR!$A$1:$AT$48, MATCH(RIGHT($A7, LEN($A7)-4), JunR!$A$1:$A1065, 0), MATCH($A$1, JunR!$A$6:N$6, 0) ), IF(valor = "-", "", valor) ), "")} | I7: {=IFERROR( LET( valor, INDEX( JulR!$A$1:$AT$48, MATCH(RIGHT($A7, LEN($A7)-4), JulR!$A$1:$A1065, 0), MATCH($A$1, JulR!$A$6:N$6, 0) ), IF(valor = "-", "", valor) ), "")} | J7: {=IFERROR( LET( valor, INDEX( AgoR!$A$1:$AT$60, MATCH(RIGHT($A7, LEN($A7)-4), AgoR!$A$1:$A1065, 0), MATCH($A$1, AgoR!$A$6:N$6, 0) ), IF(valor = "-", "", valor) ), "")} | K7: {=IFERROR( LET( valor, INDEX( SepR!$A$1:$AT$60, MATCH(RIGHT($A7, LEN($A7)-4), SepR!$A$1:$A1065, 0), MATCH($A$1, SepR!$A$6:N$6, 0) ), IF(valor = "-", "", valor) ), "")} | L7: {=IFERROR( LET( valor, INDEX( OctR!$A$1:$AT$60, MATCH(RIGHT($A7, LEN($A7)-4), OctR!$A$1:$A1065, 0), MATCH($A$1, OctR!$A$6:N$6, 0) ), IF(valor = "-", "", valor) ), "")} | M7: {=IFERROR( LET( valor, INDEX( NovR!$A$1:$AT$60, MATCH(RIGHT($A7, LEN($A7)-4), NovR!$A$1:$A1065, 0), MATCH($A$1, NovR!$A$6:N$6, 0) ), IF(valor = "-", "", valor) ), "")} | N7: {=IFERROR( LET( valor, INDEX( DicR!$A$1:$AT$60, MATCH(RIGHT($A7, LEN($A7)-4), DicR!$A$1:$A1065, 0), MATCH($A$1, DicR!$A$6:N$6, 0) ), IF(valor = "-", "", valor) ), "")}
B8: =C8+D8+E8+F8+G8+H8+I8+J8+K8+L8+M8+N8 -> 0 | C8: {=IFERROR( LET( valor, INDEX( EneR!$A$1:$AT$48, MATCH(RIGHT($A8, LEN($A8)-4), EneR!$A$1:$A1065, 0), MATCH($A$1, EneR!$A$6:N$6, 0) ), IF(valor = "-", "", valor) ), "")} | D8: {=IFERROR( LET( valor, INDEX( FebR!$A$1:$AT$51, MATCH(RIGHT($A8, LEN($A8)-4), FebR!$A$1:$A1065, 0), MATCH($A$1, FebR!$A$6:N$6, 0) ), IF(valor = "-", "", valor) ), "")} | E8: {=IFERROR( LET( valor, INDEX( MarR!$A$1:$AT$48, MATCH(RIGHT($A8, LEN($A8)-4), MarR!$A$1:$A1065, 0), MATCH($A$1, MarR!$A$6:N$6, 0) ), IF(valor = "-", "", valor) ), "")} | F8: {=IFERROR( LET( valor, INDEX( AbrR!$A$1:$AT$48, MATCH(RIGHT($A8, LEN($A8)-4), AbrR!$A$1:$A1065, 0), MATCH($A$1, AbrR!$A$6:N$6, 0) ), IF(valor = "-", "", valor) ), "")} | G8: {=IFERROR( LET( valor, INDEX( MayR!$A$1:$AT$48, MATCH(RIGHT($A8, LEN($A8)-4), MayR!$A$1:$A1065, 0), MATCH($A$1, MayR!$A$6:N$6, 0) ), IF(valor = "-", "", valor) ), "")} | H8: {=IFERROR( LET( valor, INDEX( JunR!$A$1:$AT$48, MATCH(RIGHT($A8, LEN($A8)-4), JunR!$A$1:$A1065, 0), MATCH($A$1, JunR!$A$6:N$6, 0) ), IF(valor = "-", "", valor) ), "")} | I8: {=IFERROR( LET( valor, INDEX( JulR!$A$1:$AT$48, MATCH(RIGHT($A8, LEN($A8)-4), JulR!$A$1:$A1065, 0), MATCH($A$1, JulR!$A$6:N$6, 0) ), IF(valor = "-", "", valor) ), "")} | J8: {=IFERROR( LET( valor, INDEX( AgoR!$A$1:$AT$60, MATCH(RIGHT($A8, LEN($A8)-4), AgoR!$A$1:$A1065, 0), MATCH($A$1, AgoR!$A$6:N$6, 0) ), IF(valor = "-", "", valor) ), "")} | K8: {=IFERROR( LET( valor, INDEX( SepR!$A$1:$AT$60, MATCH(RIGHT($A8, LEN($A8)-4), SepR!$A$1:$A1065, 0), MATCH($A$1, SepR!$A$6:N$6, 0) ), IF(valor = "-", "", valor) ), "")} | L8: {=IFERROR( LET( valor, INDEX( OctR!$A$1:$AT$60, MATCH(RIGHT($A8, LEN($A8)-4), OctR!$A$1:$A1065, 0), MATCH($A$1, OctR!$A$6:N$6, 0) ), IF(valor = "-", "", valor) ), "")} | M8: {=IFERROR( LET( valor, INDEX( NovR!$A$1:$AT$60, MATCH(RIGHT($A8, LEN($A8)-4), NovR!$A$1:$A1065, 0), MATCH($A$1, NovR!$A$6:N$6, 0) ), IF(valor = "-", "", valor) ), "")} | N8: {=IFERROR( LET( valor, INDEX( DicR!$A$1:$AT$60, MATCH(RIGHT($A8, LEN($A8)-4), DicR!$A$1:$A1065, 0), MATCH($A$1, DicR!$A$6:N$6, 0) ), IF(valor = "-", "", valor) ), "")}
A10: Total de Egresos | B10: =SUM(B11:B49) -> 0 | C10: =SUM(C11:C49) -> 0 | D10: =SUM(D11:D49) -> 0 | E10: =SUM(E11:E49) -> 0 | F10: =SUM(F11:F49) -> 0 | G10: =SUM(G11:G49) -> 0 | H10: =SUM(H11:H49) -> 0 | I10: =SUM(I11:I49) -> 0 | ... N10: =SUM(N11:N49) -> 0
A11: =Menus!B4 | B11: =C11+D11+E11+F11+G11+H11+I11+J11+K11+L11+M11+N11 -> 0 | C11: {=IFERROR( LET( valor, INDEX( EneR!$A$1:$AT$48, MATCH(RIGHT($A11, LEN($A11)-4), EneR!$A$1:$A1065, 0), MATCH($A$1, EneR!$A$6:N$6, 0) ), IF(valor = "-", "", valor) ), "")} | D11: {=IFERROR( LET( valor, INDEX( FebR!$A$1:$AT$51, MATCH(RIGHT($A11, LEN($A11)-4), FebR!$A$1:$A1065, 0), MATCH($A$1, FebR!$A$6:N$6, 0) ), IF(valor = "-", "", valor) ), "")} | E11: {=IFERROR( LET( valor, INDEX( MarR!$A$1:$AT$48, MATCH(RIGHT($A11, LEN($A11)-4), MarR!$A$1:$A1065, 0), MATCH($A$1, MarR!$A$6:N$6, 0) ), IF(valor = "-", "", valor) ), "")} | F11: {=IFERROR( LET( valor, INDEX( AbrR!$A$1:$AT$48, MATCH(RIGHT($A11, LEN($A11)-4), AbrR!$A$1:$A1065, 0), MATCH($A$1, AbrR!$A$6:N$6, 0) ), IF(valor = "-", "", valor) ), "")} | G11: {=IFERROR( LET( valor, INDEX( MayR!$A$1:$AT$48, MATCH(RIGHT($A11, LEN($A11)-4), MayR!$A$1:$A1065, 0), MATCH($A$1, MayR!$A$6:N$6, 0) ), IF(valor = "-", "", valor) ), "")} | H11: {=IFERROR( LET( valor, INDEX( JunR!$A$1:$AT$48, MATCH(RIGHT($A11, LEN($A11)-4), JunR!$A$1:$A1065, 0), MATCH($A$1, JunR!$A$6:N$6, 0) ), IF(valor = "-", "", valor) ), "")} | I11: {=IFERROR( LET( valor, INDEX( JulR!$A$1:$AT$48, MATCH(RIGHT($A11, LEN($A11)-4), JulR!$A$1:$A1065, 0), MATCH($A$1, JulR!$A$6:N$6, 0) ), IF(valor = "-", "", valor) ), "")} | J11: {=IFERROR( LET( valor, INDEX( AgoR!$A$1:$AT$60, MATCH(RIGHT($A11, LEN($A11)-4), AgoR!$A$1:$A1065, 0), MATCH($A$1, AgoR!$A$6:N$6, 0) ), IF(valor = "-", "", valor) ), "")} | K11: {=IFERROR( LET( valor, INDEX( SepR!$A$1:$AT$60, MATCH(RIGHT($A11, LEN($A11)-4), SepR!$A$1:$A1065, 0), MATCH($A$1, SepR!$A$6:N$6, 0) ), IF(valor = "-", "", valor) ), "")} | L11: {=IFERROR( LET( valor, INDEX( OctR!$A$1:$AT$60, MATCH(RIGHT($A11, LEN($A11)-4), OctR!$A$1:$A1065, 0), MATCH($A$1, OctR!$A$6:N$6, 0) ), IF(valor = "-", "", valor) ), "")} | M11: {=IFERROR( LET( valor, INDEX( NovR!$A$1:$AT$60, MATCH(RIGHT($A11, LEN($A11)-4), NovR!$A$1:$A1065, 0), MATCH($A$1, NovR!$A$6:N$6, 0) ), IF(valor = "-", "", valor) ), "")} | N11: {=IFERROR( LET( valor, INDEX( DicR!$A$1:$AT$60, MATCH(RIGHT($A11, LEN($A11)-4), DicR!$A$1:$A1065, 0), MATCH($A$1, DicR!$A$6:N$6, 0) ), IF(valor = "-", "", valor) ), "")}
A12: =Menus!B5 | B12: =C12+D12+E12+F12+G12+H12+I12+J12+K12+L12+M12+N12 -> 0 | C12: {=IFERROR( LET( valor, INDEX( EneR!$A$1:$AT$48, MATCH(RIGHT($A12, LEN($A12)-4), EneR!$A$1:$A1065, 0), MATCH($A$1, EneR!$A$6:N$6, 0) ), IF(valor = "-", "", valor) ), "")} | D12: {=IFERROR( LET( valor, INDEX( FebR!$A$1:$AT$51, MATCH(RIGHT($A12, LEN($A12)-4), FebR!$A$1:$A1065, 0), MATCH($A$1, FebR!$A$6:N$6, 0) ), IF(valor = "-", "", valor) ), "")} | E12: {=IFERROR( LET( valor, INDEX( MarR!$A$1:$AT$48, MATCH(RIGHT($A12, LEN($A12)-4), MarR!$A$1:$A1065, 0), MATCH($A$1, MarR!$A$6:N$6, 0) ), IF(valor = "-", "", valor) ), "")} | F12: {=IFERROR( LET( valor, INDEX( AbrR!$A$1:$AT$48, MATCH(RIGHT($A12, LEN($A12)-4), AbrR!$A$1:$A1065, 0), MATCH($A$1, AbrR!$A$6:N$6, 0) ), IF(valor = "-", "", valor) ), "")} | G12: {=IFERROR( LET( valor, INDEX( MayR!$A$1:$AT$48, MATCH(RIGHT($A12, LEN($A12)-4), MayR!$A$1:$A1065, 0), MATCH($A$1, MayR!$A$6:N$6, 0) ), IF(valor = "-", "", valor) ), "")} | H12: {=IFERROR( LET( valor, INDEX( JunR!$A$1:$AT$48, MATCH(RIGHT($A12, LEN($A12)-4), JunR!$A$1:$A1065, 0), MATCH($A$1, JunR!$A$6:N$6, 0) ), IF(valor = "-", "", valor) ), "")} | I12: {=IFERROR( LET( valor, INDEX( JulR!$A$1:$AT$48, MATCH(RIGHT($A12, LEN($A12)-4), JulR!$A$1:$A1065, 0), MATCH($A$1, JulR!$A$6:N$6, 0) ), IF(valor = "-", "", valor) ), "")} | J12: {=IFERROR( LET( valor, INDEX( AgoR!$A$1:$AT$60, MATCH(RIGHT($A12, LEN($A12)-4), AgoR!$A$1:$A1065, 0), MATCH($A$1, AgoR!$A$6:N$6, 0) ), IF(valor = "-", "", valor) ), "")} | K12: {=IFERROR( LET( valor, INDEX( SepR!$A$1:$AT$60, MATCH(RIGHT($A12, LEN($A12)-4), SepR!$A$1:$A1065, 0), MATCH($A$1, SepR!$A$6:N$6, 0) ), IF(valor = "-", "", valor) ), "")} | L12: {=IFERROR( LET( valor, INDEX( OctR!$A$1:$AT$60, MATCH(RIGHT($A12, LEN($A12)-4), OctR!$A$1:$A1065, 0), MATCH($A$1, OctR!$A$6:N$6, 0) ), IF(valor = "-", "", valor) ), "")} | M12: {=IFERROR( LET( valor, INDEX( NovR!$A$1:$AT$60, MATCH(RIGHT($A12, LEN($A12)-4), NovR!$A$1:$A1065, 0), MATCH($A$1, NovR!$A$6:N$6, 0) ), IF(valor = "-", "", valor) ), "")} | N12: {=IFERROR( LET( valor, INDEX( DicR!$A$1:$AT$60, MATCH(RIGHT($A12, LEN($A12)-4), DicR!$A$1:$A1065, 0), MATCH($A$1, DicR!$A$6:N$6, 0) ), IF(valor = "-", "", valor) ), "")}
A13: =Menus!B6 | B13: =C13+D13+E13+F13+G13+H13+I13+J13+K13+L13+M13+N13 -> 0 | C13: {=IFERROR( LET( valor, INDEX( EneR!$A$1:$AT$48, MATCH(RIGHT($A13, LEN($A13)-4), EneR!$A$1:$A1065, 0), MATCH($A$1, EneR!$A$6:N$6, 0) ), IF(valor = "-", "", valor) ), "")} | D13: {=IFERROR( LET( valor, INDEX( FebR!$A$1:$AT$51, MATCH(RIGHT($A13, LEN($A13)-4), FebR!$A$1:$A1065, 0), MATCH($A$1, FebR!$A$6:N$6, 0) ), IF(valor = "-", "", valor) ), "")} | E13: {=IFERROR( LET( valor, INDEX( MarR!$A$1:$AT$48, MATCH(RIGHT($A13, LEN($A13)-4), MarR!$A$1:$A1065, 0), MATCH($A$1, MarR!$A$6:N$6, 0) ), IF(valor = "-", "", valor) ), "")} | F13: {=IFERROR( LET( valor, INDEX( AbrR!$A$1:$AT$48, MATCH(RIGHT($A13, LEN($A13)-4), AbrR!$A$1:$A1065, 0), MATCH($A$1, AbrR!$A$6:N$6, 0) ), IF(valor = "-", "", valor) ), "")} | G13: {=IFERROR( LET( valor, INDEX( MayR!$A$1:$AT$48, MATCH(RIGHT($A13, LEN($A13)-4), MayR!$A$1:$A1065, 0), MATCH($A$1, MayR!$A$6:N$6, 0) ), IF(valor = "-", "", valor) ), "")} | H13: {=IFERROR( LET( valor, INDEX( JunR!$A$1:$AT$48, MATCH(RIGHT($A13, LEN($A13)-4), JunR!$A$1:$A1065, 0), MATCH($A$1, JunR!$A$6:N$6, 0) ), IF(valor = "-", "", valor) ), "")} | I13: {=IFERROR( LET( valor, INDEX( JulR!$A$1:$AT$48, MATCH(RIGHT($A13, LEN($A13)-4), JulR!$A$1:$A1065, 0), MATCH($A$1, JulR!$A$6:N$6, 0) ), IF(valor = "-", "", valor) ), "")} | J13: {=IFERROR( LET( valor, INDEX( AgoR!$A$1:$AT$60, MATCH(RIGHT($A13, LEN($A13)-4), AgoR!$A$1:$A1065, 0), MATCH($A$1, AgoR!$A$6:N$6, 0) ), IF(valor = "-", "", valor) ), "")} | K13: {=IFERROR( LET( valor, INDEX( SepR!$A$1:$AT$60, MATCH(RIGHT($A13, LEN($A13)-4), SepR!$A$1:$A1065, 0), MATCH($A$1, SepR!$A$6:N$6, 0) ), IF(valor = "-", "", valor) ), "")} | L13: {=IFERROR( LET( valor, INDEX( OctR!$A$1:$AT$60, MATCH(RIGHT($A13, LEN($A13)-4), OctR!$A$1:$A1065, 0), MATCH($A$1, OctR!$A$6:N$6, 0) ), IF(valor = "-", "", valor) ), "")} | M13: {=IFERROR( LET( valor, INDEX( NovR!$A$1:$AT$60, MATCH(RIGHT($A13, LEN($A13)-4), NovR!$A$1:$A1065, 0), MATCH($A$1, NovR!$A$6:N$6, 0) ), IF(valor = "-", "", valor) ), "")} | N13: {=IFERROR( LET( valor, INDEX( DicR!$A$1:$AT$60, MATCH(RIGHT($A13, LEN($A13)-4), DicR!$A$1:$A1065, 0), MATCH($A$1, DicR!$A$6:N$6, 0) ), IF(valor = "-", "", valor) ), "")}
A14: =Menus!B7 | B14: =C14+D14+E14+F14+G14+H14+I14+J14+K14+L14+M14+N14 -> 0 | C14: {=IFERROR( LET( valor, INDEX( EneR!$A$1:$AT$48, MATCH(RIGHT($A14, LEN($A14)-4), EneR!$A$1:$A1065, 0), MATCH($A$1, EneR!$A$6:N$6, 0) ), IF(valor = "-", "", valor) ), "")} | D14: {=IFERROR( LET( valor, INDEX( FebR!$A$1:$AT$51, MATCH(RIGHT($A14, LEN($A14)-4), FebR!$A$1:$A1065, 0), MATCH($A$1, FebR!$A$6:N$6, 0) ), IF(valor = "-", "", valor) ), "")} | E14: {=IFERROR( LET( valor, INDEX( MarR!$A$1:$AT$48, MATCH(RIGHT($A14, LEN($A14)-4), MarR!$A$1:$A1065, 0), MATCH($A$1, MarR!$A$6:N$6, 0) ), IF(valor = "-", "", valor) ), "")} | F14: {=IFERROR( LET( valor, INDEX( AbrR!$A$1:$AT$48, MATCH(RIGHT($A14, LEN($A14)-4), AbrR!$A$1:$A1065, 0), MATCH($A$1, AbrR!$A$6:N$6, 0) ), IF(valor = "-", "", valor) ), "")} | G14: {=IFERROR( LET( valor, INDEX( MayR!$A$1:$AT$48, MATCH(RIGHT($A14, LEN($A14)-4), MayR!$A$1:$A1065, 0), MATCH($A$1, MayR!$A$6:N$6, 0) ), IF(valor = "-", "", valor) ), "")} | H14: {=IFERROR( LET( valor, INDEX( JunR!$A$1:$AT$48, MATCH(RIGHT($A14, LEN($A14)-4), JunR!$A$1:$A1065, 0), MATCH($A$1, JunR!$A$6:N$6, 0) ), IF(valor = "-", "", valor) ), "")} | I14: {=IFERROR( LET( valor, INDEX( JulR!$A$1:$AT$48, MATCH(RIGHT($A14, LEN($A14)-4), JulR!$A$1:$A1065, 0), MATCH($A$1, JulR!$A$6:N$6, 0) ), IF(valor = "-", "", valor) ), "")} | J14: {=IFERROR( LET( valor, INDEX( AgoR!$A$1:$AT$60, MATCH(RIGHT($A14, LEN($A14)-4), AgoR!$A$1:$A1065, 0), MATCH($A$1, AgoR!$A$6:N$6, 0) ), IF(valor = "-", "", valor) ), "")} | K14: {=IFERROR( LET( valor, INDEX( SepR!$A$1:$AT$60, MATCH(RIGHT($A14, LEN($A14)-4), SepR!$A$1:$A1065, 0), MATCH($A$1, SepR!$A$6:N$6, 0) ), IF(valor = "-", "", valor) ), "")} | L14: {=IFERROR( LET( valor, INDEX( OctR!$A$1:$AT$60, MATCH(RIGHT($A14, LEN($A14)-4), OctR!$A$1:$A1065, 0), MATCH($A$1, OctR!$A$6:N$6, 0) ), IF(valor = "-", "", valor) ), "")} | M14: {=IFERROR( LET( valor, INDEX( NovR!$A$1:$AT$60, MATCH(RIGHT($A14, LEN($A14)-4), NovR!$A$1:$A1065, 0), MATCH($A$1, NovR!$A$6:N$6, 0) ), IF(valor = "-", "", valor) ), "")} | N14: {=IFERROR( LET( valor, INDEX( DicR!$A$1:$AT$60, MATCH(RIGHT($A14, LEN($A14)-4), DicR!$A$1:$A1065, 0), MATCH($A$1, DicR!$A$6:N$6, 0) ), IF(valor = "-", "", valor) ), "")}
A15: =Menus!B8 | B15: =C15+D15+E15+F15+G15+H15+I15+J15+K15+L15+M15+N15 -> 0 | C15: {=IFERROR( LET( valor, INDEX( EneR!$A$1:$AT$48, MATCH(RIGHT($A15, LEN($A15)-4), EneR!$A$1:$A1065, 0), MATCH($A$1, EneR!$A$6:N$6, 0) ), IF(valor = "-", "", valor) ), "")} | D15: {=IFERROR( LET( valor, INDEX( FebR!$A$1:$AT$51, MATCH(RIGHT($A15, LEN($A15)-4), FebR!$A$1:$A1065, 0), MATCH($A$1, FebR!$A$6:N$6, 0) ), IF(valor = "-", "", valor) ), "")} | E15: {=IFERROR( LET( valor, INDEX( MarR!$A$1:$AT$48, MATCH(RIGHT($A15, LEN($A15)-4), MarR!$A$1:$A1065, 0), MATCH($A$1, MarR!$A$6:N$6, 0) ), IF(valor = "-", "", valor) ), "")} | F15: {=IFERROR( LET( valor, INDEX( AbrR!$A$1:$AT$48, MATCH(RIGHT($A15, LEN($A15)-4), AbrR!$A$1:$A1065, 0), MATCH($A$1, AbrR!$A$6:N$6, 0) ), IF(valor = "-", "", valor) ), "")} | G15: {=IFERROR( LET( valor, INDEX( MayR!$A$1:$AT$48, MATCH(RIGHT($A15, LEN($A15)-4), MayR!$A$1:$A1065, 0), MATCH($A$1, MayR!$A$6:N$6, 0) ), IF(valor = "-", "", valor) ), "")} | H15: {=IFERROR( LET( valor, INDEX( JunR!$A$1:$AT$48, MATCH(RIGHT($A15, LEN($A15)-4), JunR!$A$1:$A1065, 0), MATCH($A$1, JunR!$A$6:N$6, 0) ), IF(valor = "-", "", valor) ), "")} | I15: {=IFERROR( LET( valor, INDEX( JulR!$A$1:$AT$48, MATCH(RIGHT($A15, LEN($A15)-4), JulR!$A$1:$A1065, 0), MATCH($A$1, JulR!$A$6:N$6, 0) ), IF(valor = "-", "", valor) ), "")} | J15: {=IFERROR( LET( valor, INDEX( AgoR!$A$1:$AT$60, MATCH(RIGHT($A15, LEN($A15)-4), AgoR!$A$1:$A1065, 0), MATCH($A$1, AgoR!$A$6:N$6, 0) ), IF(valor = "-", "", valor) ), "")} | K15: {=IFERROR( LET( valor, INDEX( SepR!$A$1:$AT$60, MATCH(RIGHT($A15, LEN($A15)-4), SepR!$A$1:$A1065, 0), MATCH($A$1, SepR!$A$6:N$6, 0) ), IF(valor = "-", "", valor) ), "")} | L15: {=IFERROR( LET( valor, INDEX( OctR!$A$1:$AT$60, MATCH(RIGHT($A15, LEN($A15)-4), OctR!$A$1:$A1065, 0), MATCH($A$1, OctR!$A$6:N$6, 0) ), IF(valor = "-", "", valor) ), "")} | M15: {=IFERROR( LET( valor, INDEX( NovR!$A$1:$AT$60, MATCH(RIGHT($A15, LEN($A15)-4), NovR!$A$1:$A1065, 0), MATCH($A$1, NovR!$A$6:N$6, 0) ), IF(valor = "-", "", valor) ), "")} | N15: {=IFERROR( LET( valor, INDEX( DicR!$A$1:$AT$60, MATCH(RIGHT($A15, LEN($A15)-4), DicR!$A$1:$A1065, 0), MATCH($A$1, DicR!$A$6:N$6, 0) ), IF(valor = "-", "", valor) ), "")}
A16: =Menus!B9 | B16: =C16+D16+E16+F16+G16+H16+I16+J16+K16+L16+M16+N16 -> 0 | C16: {=IFERROR( LET( valor, INDEX( EneR!$A$1:$AT$48, MATCH(RIGHT($A16, LEN($A16)-4), EneR!$A$1:$A1065, 0), MATCH($A$1, EneR!$A$6:N$6, 0) ), IF(valor = "-", "", valor) ), "")} | D16: {=IFERROR( LET( valor, INDEX( FebR!$A$1:$AT$51, MATCH(RIGHT($A16, LEN($A16)-4), FebR!$A$1:$A1065, 0), MATCH($A$1, FebR!$A$6:N$6, 0) ), IF(valor = "-", "", valor) ), "")} | E16: {=IFERROR( LET( valor, INDEX( MarR!$A$1:$AT$48, MATCH(RIGHT($A16, LEN($A16)-4), MarR!$A$1:$A1065, 0), MATCH($A$1, MarR!$A$6:N$6, 0) ), IF(valor = "-", "", valor) ), "")} | F16: {=IFERROR( LET( valor, INDEX( AbrR!$A$1:$AT$48, MATCH(RIGHT($A16, LEN($A16)-4), AbrR!$A$1:$A1065, 0), MATCH($A$1, AbrR!$A$6:N$6, 0) ), IF(valor = "-", "", valor) ), "")} | G16: {=IFERROR( LET( valor, INDEX( MayR!$A$1:$AT$48, MATCH(RIGHT($A16, LEN($A16)-4), MayR!$A$1:$A1065, 0), MATCH($A$1, MayR!$A$6:N$6, 0) ), IF(valor = "-", "", valor) ), "")} | H16: {=IFERROR( LET( valor, INDEX( JunR!$A$1:$AT$48, MATCH(RIGHT($A16, LEN($A16)-4), JunR!$A$1:$A1065, 0), MATCH($A$1, JunR!$A$6:N$6, 0) ), IF(valor = "-", "", valor) ), "")} | I16: {=IFERROR( LET( valor, INDEX( JulR!$A$1:$AT$48, MATCH(RIGHT($A16, LEN($A16)-4), JulR!$A$1:$A1065, 0), MATCH($A$1, JulR!$A$6:N$6, 0) ), IF(valor = "-", "", valor) ), "")} | J16: {=IFERROR( LET( valor, INDEX( AgoR!$A$1:$AT$60, MATCH(RIGHT($A16, LEN($A16)-4), AgoR!$A$1:$A1065, 0), MATCH($A$1, AgoR!$A$6:N$6, 0) ), IF(valor = "-", "", valor) ), "")} | K16: {=IFERROR( LET( valor, INDEX( SepR!$A$1:$AT$60, MATCH(RIGHT($A16, LEN($A16)-4), SepR!$A$1:$A1065, 0), MATCH($A$1, SepR!$A$6:N$6, 0) ), IF(valor = "-", "", valor) ), "")} | L16: {=IFERROR( LET( valor, INDEX( OctR!$A$1:$AT$60, MATCH(RIGHT($A16, LEN($A16)-4), OctR!$A$1:$A1065, 0), MATCH($A$1, OctR!$A$6:N$6, 0) ), IF(valor = "-", "", valor) ), "")} | M16: {=IFERROR( LET( valor, INDEX( NovR!$A$1:$AT$60, MATCH(RIGHT($A16, LEN($A16)-4), NovR!$A$1:$A1065, 0), MATCH($A$1, NovR!$A$6:N$6, 0) ), IF(valor = "-", "", valor) ), "")} | N16: {=IFERROR( LET( valor, INDEX( DicR!$A$1:$AT$60, MATCH(RIGHT($A16, LEN($A16)-4), DicR!$A$1:$A1065, 0), MATCH($A$1, DicR!$A$6:N$6, 0) ), IF(valor = "-", "", valor) ), "")}
A17: =Menus!B10 | B17: =C17+D17+E17+F17+G17+H17+I17+J17+K17+L17+M17+N17 -> 0 | C17: {=IFERROR( LET( valor, INDEX( EneR!$A$1:$AT$48, MATCH(RIGHT($A17, LEN($A17)-4), EneR!$A$1:$A1065, 0), MATCH($A$1, EneR!$A$6:N$6, 0) ), IF(valor = "-", "", valor) ), "")} | D17: {=IFERROR( LET( valor, INDEX( FebR!$A$1:$AT$51, MATCH(RIGHT($A17, LEN($A17)-4), FebR!$A$1:$A1065, 0), MATCH($A$1, FebR!$A$6:N$6, 0) ), IF(valor = "-", "", valor) ), "")} | E17: {=IFERROR( LET( valor, INDEX( MarR!$A$1:$AT$48, MATCH(RIGHT($A17, LEN($A17)-4), MarR!$A$1:$A1065, 0), MATCH($A$1, MarR!$A$6:N$6, 0) ), IF(valor = "-", "", valor) ), "")} | F17: {=IFERROR( LET( valor, INDEX( AbrR!$A$1:$AT$48, MATCH(RIGHT($A17, LEN($A17)-4), AbrR!$A$1:$A1065, 0), MATCH($A$1, AbrR!$A$6:N$6, 0) ), IF(valor = "-", "", valor) ), "")} | G17: {=IFERROR( LET( valor, INDEX( MayR!$A$1:$AT$48, MATCH(RIGHT($A17, LEN($A17)-4), MayR!$A$1:$A1065, 0), MATCH($A$1, MayR!$A$6:N$6, 0) ), IF(valor = "-", "", valor) ), "")} | H17: {=IFERROR( LET( valor, INDEX( JunR!$A$1:$AT$48, MATCH(RIGHT($A17, LEN($A17)-4), JunR!$A$1:$A1065, 0), MATCH($A$1, JunR!$A$6:N$6, 0) ), IF(valor = "-", "", valor) ), "")} | I17: {=IFERROR( LET( valor, INDEX( JulR!$A$1:$AT$48, MATCH(RIGHT($A17, LEN($A17)-4), JulR!$A$1:$A1065, 0), MATCH($A$1, JulR!$A$6:N$6, 0) ), IF(valor = "-", "", valor) ), "")} | J17: {=IFERROR( LET( valor, INDEX( AgoR!$A$1:$AT$60, MATCH(RIGHT($A17, LEN($A17)-4), AgoR!$A$1:$A1065, 0), MATCH($A$1, AgoR!$A$6:N$6, 0) ), IF(valor = "-", "", valor) ), "")} | K17: {=IFERROR( LET( valor, INDEX( SepR!$A$1:$AT$60, MATCH(RIGHT($A17, LEN($A17)-4), SepR!$A$1:$A1065, 0), MATCH($A$1, SepR!$A$6:N$6, 0) ), IF(valor = "-", "", valor) ), "")} | L17: {=IFERROR( LET( valor, INDEX( OctR!$A$1:$AT$60, MATCH(RIGHT($A17, LEN($A17)-4), OctR!$A$1:$A1065, 0), MATCH($A$1, OctR!$A$6:N$6, 0) ), IF(valor = "-", "", valor) ), "")} | M17: {=IFERROR( LET( valor, INDEX( NovR!$A$1:$AT$60, MATCH(RIGHT($A17, LEN($A17)-4), NovR!$A$1:$A1065, 0), MATCH($A$1, NovR!$A$6:N$6, 0) ), IF(valor = "-", "", valor) ), "")} | N17: {=IFERROR( LET( valor, INDEX( DicR!$A$1:$AT$60, MATCH(RIGHT($A17, LEN($A17)-4), DicR!$A$1:$A1065, 0), MATCH($A$1, DicR!$A$6:N$6, 0) ), IF(valor = "-", "", valor) ), "")}
A18: =Menus!B11 | B18: =C18+D18+E18+F18+G18+H18+I18+J18+K18+L18+M18+N18 -> 0 | C18: {=IFERROR( LET( valor, INDEX( EneR!$A$1:$AT$48, MATCH(RIGHT($A18, LEN($A18)-4), EneR!$A$1:$A1065, 0), MATCH($A$1, EneR!$A$6:N$6, 0) ), IF(valor = "-", "", valor) ), "")} | D18: {=IFERROR( LET( valor, INDEX( FebR!$A$1:$AT$51, MATCH(RIGHT($A18, LEN($A18)-4), FebR!$A$1:$A1065, 0), MATCH($A$1, FebR!$A$6:N$6, 0) ), IF(valor = "-", "", valor) ), "")} | E18: {=IFERROR( LET( valor, INDEX( MarR!$A$1:$AT$48, MATCH(RIGHT($A18, LEN($A18)-4), MarR!$A$1:$A1065, 0), MATCH($A$1, MarR!$A$6:N$6, 0) ), IF(valor = "-", "", valor) ), "")} | F18: {=IFERROR( LET( valor, INDEX( AbrR!$A$1:$AT$48, MATCH(RIGHT($A18, LEN($A18)-4), AbrR!$A$1:$A1065, 0), MATCH($A$1, AbrR!$A$6:N$6, 0) ), IF(valor = "-", "", valor) ), "")} | G18: {=IFERROR( LET( valor, INDEX( MayR!$A$1:$AT$48, MATCH(RIGHT($A18, LEN($A18)-4), MayR!$A$1:$A1065, 0), MATCH($A$1, MayR!$A$6:N$6, 0) ), IF(valor = "-", "", valor) ), "")} | H18: {=IFERROR( LET( valor, INDEX( JunR!$A$1:$AT$48, MATCH(RIGHT($A18, LEN($A18)-4), JunR!$A$1:$A1065, 0), MATCH($A$1, JunR!$A$6:N$6, 0) ), IF(valor = "-", "", valor) ), "")} | I18: {=IFERROR( LET( valor, INDEX( JulR!$A$1:$AT$48, MATCH(RIGHT($A18, LEN($A18)-4), JulR!$A$1:$A1065, 0), MATCH($A$1, JulR!$A$6:N$6, 0) ), IF(valor = "-", "", valor) ), "")} | J18: {=IFERROR( LET( valor, INDEX( AgoR!$A$1:$AT$60, MATCH(RIGHT($A18, LEN($A18)-4), AgoR!$A$1:$A1065, 0), MATCH($A$1, AgoR!$A$6:N$6, 0) ), IF(valor = "-", "", valor) ), "")} | K18: {=IFERROR( LET( valor, INDEX( SepR!$A$1:$AT$60, MATCH(RIGHT($A18, LEN($A18)-4), SepR!$A$1:$A1065, 0), MATCH($A$1, SepR!$A$6:N$6, 0) ), IF(valor = "-", "", valor) ), "")} | L18: {=IFERROR( LET( valor, INDEX( OctR!$A$1:$AT$60, MATCH(RIGHT($A18, LEN($A18)-4), OctR!$A$1:$A1065, 0), MATCH($A$1, OctR!$A$6:N$6, 0) ), IF(valor = "-", "", valor) ), "")} | M18: {=IFERROR( LET( valor, INDEX( NovR!$A$1:$AT$60, MATCH(RIGHT($A18, LEN($A18)-4), NovR!$A$1:$A1065, 0), MATCH($A$1, NovR!$A$6:N$6, 0) ), IF(valor = "-", "", valor) ), "")} | N18: {=IFERROR( LET( valor, INDEX( DicR!$A$1:$AT$60, MATCH(RIGHT($A18, LEN($A18)-4), DicR!$A$1:$A1065, 0), MATCH($A$1, DicR!$A$6:N$6, 0) ), IF(valor = "-", "", valor) ), "")}
A19: =Menus!B12 | B19: =C19+D19+E19+F19+G19+H19+I19+J19+K19+L19+M19+N19 -> 0 | C19: {=IFERROR( LET( valor, INDEX( EneR!$A$1:$AT$48, MATCH(RIGHT($A19, LEN($A19)-4), EneR!$A$1:$A1065, 0), MATCH($A$1, EneR!$A$6:N$6, 0) ), IF(valor = "-", "", valor) ), "")} | D19: {=IFERROR( LET( valor, INDEX( FebR!$A$1:$AT$51, MATCH(RIGHT($A19, LEN($A19)-4), FebR!$A$1:$A1065, 0), MATCH($A$1, FebR!$A$6:N$6, 0) ), IF(valor = "-", "", valor) ), "")} | E19: {=IFERROR( LET( valor, INDEX( MarR!$A$1:$AT$48, MATCH(RIGHT($A19, LEN($A19)-4), MarR!$A$1:$A1065, 0), MATCH($A$1, MarR!$A$6:N$6, 0) ), IF(valor = "-", "", valor) ), "")} | F19: {=IFERROR( LET( valor, INDEX( AbrR!$A$1:$AT$48, MATCH(RIGHT($A19, LEN($A19)-4), AbrR!$A$1:$A1065, 0), MATCH($A$1, AbrR!$A$6:N$6, 0) ), IF(valor = "-", "", valor) ), "")} | G19: {=IFERROR( LET( valor, INDEX( MayR!$A$1:$AT$48, MATCH(RIGHT($A19, LEN($A19)-4), MayR!$A$1:$A1065, 0), MATCH($A$1, MayR!$A$6:N$6, 0) ), IF(valor = "-", "", valor) ), "")} | H19: {=IFERROR( LET( valor, INDEX( JunR!$A$1:$AT$48, MATCH(RIGHT($A19, LEN($A19)-4), JunR!$A$1:$A1065, 0), MATCH($A$1, JunR!$A$6:N$6, 0) ), IF(valor = "-", "", valor) ), "")} | I19: {=IFERROR( LET( valor, INDEX( JulR!$A$1:$AT$48, MATCH(RIGHT($A19, LEN($A19)-4), JulR!$A$1:$A1065, 0), MATCH($A$1, JulR!$A$6:N$6, 0) ), IF(valor = "-", "", valor) ), "")} | J19: {=IFERROR( LET( valor, INDEX( AgoR!$A$1:$AT$60, MATCH(RIGHT($A19, LEN($A19)-4), AgoR!$A$1:$A1065, 0), MATCH($A$1, AgoR!$A$6:N$6, 0) ), IF(valor = "-", "", valor) ), "")} | K19: {=IFERROR( LET( valor, INDEX( SepR!$A$1:$AT$60, MATCH(RIGHT($A19, LEN($A19)-4), SepR!$A$1:$A1065, 0), MATCH($A$1, SepR!$A$6:N$6, 0) ), IF(valor = "-", "", valor) ), "")} | L19: {=IFERROR( LET( valor, INDEX( OctR!$A$1:$AT$60, MATCH(RIGHT($A19, LEN($A19)-4), OctR!$A$1:$A1065, 0), MATCH($A$1, OctR!$A$6:N$6, 0) ), IF(valor = "-", "", valor) ), "")} | M19: {=IFERROR( LET( valor, INDEX( NovR!$A$1:$AT$60, MATCH(RIGHT($A19, LEN($A19)-4), NovR!$A$1:$A1065, 0), MATCH($A$1, NovR!$A$6:N$6, 0) ), IF(valor = "-", "", valor) ), "")} | N19: {=IFERROR( LET( valor, INDEX( DicR!$A$1:$AT$60, MATCH(RIGHT($A19, LEN($A19)-4), DicR!$A$1:$A1065, 0), MATCH($A$1, DicR!$A$6:N$6, 0) ), IF(valor = "-", "", valor) ), "")}
A20: =Menus!B13 | B20: =C20+D20+E20+F20+G20+H20+I20+J20+K20+L20+M20+N20 -> 0 | C20: {=IFERROR( LET( valor, INDEX( EneR!$A$1:$AT$48, MATCH(RIGHT($A20, LEN($A20)-4), EneR!$A$1:$A1065, 0), MATCH($A$1, EneR!$A$6:N$6, 0) ), IF(valor = "-", "", valor) ), "")} | D20: {=IFERROR( LET( valor, INDEX( FebR!$A$1:$AT$51, MATCH(RIGHT($A20, LEN($A20)-4), FebR!$A$1:$A1065, 0), MATCH($A$1, FebR!$A$6:N$6, 0) ), IF(valor = "-", "", valor) ), "")} | E20: {=IFERROR( LET( valor, INDEX( MarR!$A$1:$AT$48, MATCH(RIGHT($A20, LEN($A20)-4), MarR!$A$1:$A1065, 0), MATCH($A$1, MarR!$A$6:N$6, 0) ), IF(valor = "-", "", valor) ), "")} | F20: {=IFERROR( LET( valor, INDEX( AbrR!$A$1:$AT$48, MATCH(RIGHT($A20, LEN($A20)-4), AbrR!$A$1:$A1065, 0), MATCH($A$1, AbrR!$A$6:N$6, 0) ), IF(valor = "-", "", valor) ), "")} | G20: {=IFERROR( LET( valor, INDEX( MayR!$A$1:$AT$48, MATCH(RIGHT($A20, LEN($A20)-4), MayR!$A$1:$A1065, 0), MATCH($A$1, MayR!$A$6:N$6, 0) ), IF(valor = "-", "", valor) ), "")} | H20: {=IFERROR( LET( valor, INDEX( JunR!$A$1:$AT$48, MATCH(RIGHT($A20, LEN($A20)-4), JunR!$A$1:$A1065, 0), MATCH($A$1, JunR!$A$6:N$6, 0) ), IF(valor = "-", "", valor) ), "")} | I20: {=IFERROR( LET( valor, INDEX( JulR!$A$1:$AT$48, MATCH(RIGHT($A20, LEN($A20)-4), JulR!$A$1:$A1065, 0), MATCH($A$1, JulR!$A$6:N$6, 0) ), IF(valor = "-", "", valor) ), "")} | J20: {=IFERROR( LET( valor, INDEX( AgoR!$A$1:$AT$60, MATCH(RIGHT($A20, LEN($A20)-4), AgoR!$A$1:$A1065, 0), MATCH($A$1, AgoR!$A$6:N$6, 0) ), IF(valor = "-", "", valor) ), "")} | K20: {=IFERROR( LET( valor, INDEX( SepR!$A$1:$AT$60, MATCH(RIGHT($A20, LEN($A20)-4), SepR!$A$1:$A1065, 0), MATCH($A$1, SepR!$A$6:N$6, 0) ), IF(valor = "-", "", valor) ), "")} | L20: {=IFERROR( LET( valor, INDEX( OctR!$A$1:$AT$60, MATCH(RIGHT($A20, LEN($A20)-4), OctR!$A$1:$A1065, 0), MATCH($A$1, OctR!$A$6:N$6, 0) ), IF(valor = "-", "", valor) ), "")} | M20: {=IFERROR( LET( valor, INDEX( NovR!$A$1:$AT$60, MATCH(RIGHT($A20, LEN($A20)-4), NovR!$A$1:$A1065, 0), MATCH($A$1, NovR!$A$6:N$6, 0) ), IF(valor = "-", "", valor) ), "")} | N20: {=IFERROR( LET( valor, INDEX( DicR!$A$1:$AT$60, MATCH(RIGHT($A20, LEN($A20)-4), DicR!$A$1:$A1065, 0), MATCH($A$1, DicR!$A$6:N$6, 0) ), IF(valor = "-", "", valor) ), "")}
A21: =Menus!B14 | B21: =C21+D21+E21+F21+G21+H21+I21+J21+K21+L21+M21+N21 -> 0 | C21: {=IFERROR( LET( valor, INDEX( EneR!$A$1:$AT$48, MATCH(RIGHT($A21, LEN($A21)-4), EneR!$A$1:$A1065, 0), MATCH($A$1, EneR!$A$6:N$6, 0) ), IF(valor = "-", "", valor) ), "")} | D21: {=IFERROR( LET( valor, INDEX( FebR!$A$1:$AT$51, MATCH(RIGHT($A21, LEN($A21)-4), FebR!$A$1:$A1065, 0), MATCH($A$1, FebR!$A$6:N$6, 0) ), IF(valor = "-", "", valor) ), "")} | E21: {=IFERROR( LET( valor, INDEX( MarR!$A$1:$AT$48, MATCH(RIGHT($A21, LEN($A21)-4), MarR!$A$1:$A1065, 0), MATCH($A$1, MarR!$A$6:N$6, 0) ), IF(valor = "-", "", valor) ), "")} | F21: {=IFERROR( LET( valor, INDEX( AbrR!$A$1:$AT$48, MATCH(RIGHT($A21, LEN($A21)-4), AbrR!$A$1:$A1065, 0), MATCH($A$1, AbrR!$A$6:N$6, 0) ), IF(valor = "-", "", valor) ), "")} | G21: {=IFERROR( LET( valor, INDEX( MayR!$A$1:$AT$48, MATCH(RIGHT($A21, LEN($A21)-4), MayR!$A$1:$A1065, 0), MATCH($A$1, MayR!$A$6:N$6, 0) ), IF(valor = "-", "", valor) ), "")} | H21: {=IFERROR( LET( valor, INDEX( JunR!$A$1:$AT$48, MATCH(RIGHT($A21, LEN($A21)-4), JunR!$A$1:$A1065, 0), MATCH($A$1, JunR!$A$6:N$6, 0) ), IF(valor = "-", "", valor) ), "")} | I21: {=IFERROR( LET( valor, INDEX( JulR!$A$1:$AT$48, MATCH(RIGHT($A21, LEN($A21)-4), JulR!$A$1:$A1065, 0), MATCH($A$1, JulR!$A$6:N$6, 0) ), IF(valor = "-", "", valor) ), "")} | J21: {=IFERROR( LET( valor, INDEX( AgoR!$A$1:$AT$60, MATCH(RIGHT($A21, LEN($A21)-4), AgoR!$A$1:$A1065, 0), MATCH($A$1, AgoR!$A$6:N$6, 0) ), IF(valor = "-", "", valor) ), "")} | K21: {=IFERROR( LET( valor, INDEX( SepR!$A$1:$AT$60, MATCH(RIGHT($A21, LEN($A21)-4), SepR!$A$1:$A1065, 0), MATCH($A$1, SepR!$A$6:N$6, 0) ), IF(valor = "-", "", valor) ), "")} | L21: {=IFERROR( LET( valor, INDEX( OctR!$A$1:$AT$60, MATCH(RIGHT($A21, LEN($A21)-4), OctR!$A$1:$A1065, 0), MATCH($A$1, OctR!$A$6:N$6, 0) ), IF(valor = "-", "", valor) ), "")} | M21: {=IFERROR( LET( valor, INDEX( NovR!$A$1:$AT$60, MATCH(RIGHT($A21, LEN($A21)-4), NovR!$A$1:$A1065, 0), MATCH($A$1, NovR!$A$6:N$6, 0) ), IF(valor = "-", "", valor) ), "")} | N21: {=IFERROR( LET( valor, INDEX( DicR!$A$1:$AT$60, MATCH(RIGHT($A21, LEN($A21)-4), DicR!$A$1:$A1065, 0), MATCH($A$1, DicR!$A$6:N$6, 0) ), IF(valor = "-", "", valor) ), "")}
A22: =Menus!B15 | B22: =C22+D22+E22+F22+G22+H22+I22+J22+K22+L22+M22+N22 -> 0 | C22: {=IFERROR( LET( valor, INDEX( EneR!$A$1:$AT$48, MATCH(RIGHT($A22, LEN($A22)-4), EneR!$A$1:$A1065, 0), MATCH($A$1, EneR!$A$6:N$6, 0) ), IF(valor = "-", "", valor) ), "")} | D22: {=IFERROR( LET( valor, INDEX( FebR!$A$1:$AT$51, MATCH(RIGHT($A22, LEN($A22)-4), FebR!$A$1:$A1065, 0), MATCH($A$1, FebR!$A$6:N$6, 0) ), IF(valor = "-", "", valor) ), "")} | E22: {=IFERROR( LET( valor, INDEX( MarR!$A$1:$AT$48, MATCH(RIGHT($A22, LEN($A22)-4), MarR!$A$1:$A1065, 0), MATCH($A$1, MarR!$A$6:N$6, 0) ), IF(valor = "-", "", valor) ), "")} | F22: {=IFERROR( LET( valor, INDEX( AbrR!$A$1:$AT$48, MATCH(RIGHT($A22, LEN($A22)-4), AbrR!$A$1:$A1065, 0), MATCH($A$1, AbrR!$A$6:N$6, 0) ), IF(valor = "-", "", valor) ), "")} | G22: {=IFERROR( LET( valor, INDEX( MayR!$A$1:$AT$48, MATCH(RIGHT($A22, LEN($A22)-4), MayR!$A$1:$A1065, 0), MATCH($A$1, MayR!$A$6:N$6, 0) ), IF(valor = "-", "", valor) ), "")} | H22: {=IFERROR( LET( valor, INDEX( JunR!$A$1:$AT$48, MATCH(RIGHT($A22, LEN($A22)-4), JunR!$A$1:$A1065, 0), MATCH($A$1, JunR!$A$6:N$6, 0) ), IF(valor = "-", "", valor) ), "")} | I22: {=IFERROR( LET( valor, INDEX( JulR!$A$1:$AT$48, MATCH(RIGHT($A22, LEN($A22)-4), JulR!$A$1:$A1065, 0), MATCH($A$1, JulR!$A$6:N$6, 0) ), IF(valor = "-", "", valor) ), "")} | J22: {=IFERROR( LET( valor, INDEX( AgoR!$A$1:$AT$60, MATCH(RIGHT($A22, LEN($A22)-4), AgoR!$A$1:$A1065, 0), MATCH($A$1, AgoR!$A$6:N$6, 0) ), IF(valor = "-", "", valor) ), "")} | K22: {=IFERROR( LET( valor, INDEX( SepR!$A$1:$AT$60, MATCH(RIGHT($A22, LEN($A22)-4), SepR!$A$1:$A1065, 0), MATCH($A$1, SepR!$A$6:N$6, 0) ), IF(valor = "-", "", valor) ), "")} | L22: {=IFERROR( LET( valor, INDEX( OctR!$A$1:$AT$60, MATCH(RIGHT($A22, LEN($A22)-4), OctR!$A$1:$A1065, 0), MATCH($A$1, OctR!$A$6:N$6, 0) ), IF(valor = "-", "", valor) ), "")} | M22: {=IFERROR( LET( valor, INDEX( NovR!$A$1:$AT$60, MATCH(RIGHT($A22, LEN($A22)-4), NovR!$A$1:$A1065, 0), MATCH($A$1, NovR!$A$6:N$6, 0) ), IF(valor = "-", "", valor) ), "")} | N22: {=IFERROR( LET( valor, INDEX( DicR!$A$1:$AT$60, MATCH(RIGHT($A22, LEN($A22)-4), DicR!$A$1:$A1065, 0), MATCH($A$1, DicR!$A$6:N$6, 0) ), IF(valor = "-", "", valor) ), "")}
A23: =Menus!B16 | B23: =C23+D23+E23+F23+G23+H23+I23+J23+K23+L23+M23+N23 -> 0 | C23: {=IFERROR( LET( valor, INDEX( EneR!$A$1:$AT$48, MATCH(RIGHT($A23, LEN($A23)-4), EneR!$A$1:$A1065, 0), MATCH($A$1, EneR!$A$6:N$6, 0) ), IF(valor = "-", "", valor) ), "")} | D23: {=IFERROR( LET( valor, INDEX( FebR!$A$1:$AT$51, MATCH(RIGHT($A23, LEN($A23)-4), FebR!$A$1:$A1065, 0), MATCH($A$1, FebR!$A$6:N$6, 0) ), IF(valor = "-", "", valor) ), "")} | E23: {=IFERROR( LET( valor, INDEX( MarR!$A$1:$AT$48, MATCH(RIGHT($A23, LEN($A23)-4), MarR!$A$1:$A1065, 0), MATCH($A$1, MarR!$A$6:N$6, 0) ), IF(valor = "-", "", valor) ), "")} | F23: {=IFERROR( LET( valor, INDEX( AbrR!$A$1:$AT$48, MATCH(RIGHT($A23, LEN($A23)-4), AbrR!$A$1:$A1065, 0), MATCH($A$1, AbrR!$A$6:N$6, 0) ), IF(valor = "-", "", valor) ), "")} | G23: {=IFERROR( LET( valor, INDEX( MayR!$A$1:$AT$48, MATCH(RIGHT($A23, LEN($A23)-4), MayR!$A$1:$A1065, 0), MATCH($A$1, MayR!$A$6:N$6, 0) ), IF(valor = "-", "", valor) ), "")} | H23: {=IFERROR( LET( valor, INDEX( JunR!$A$1:$AT$48, MATCH(RIGHT($A23, LEN($A23)-4), JunR!$A$1:$A1065, 0), MATCH($A$1, JunR!$A$6:N$6, 0) ), IF(valor = "-", "", valor) ), "")} | I23: {=IFERROR( LET( valor, INDEX( JulR!$A$1:$AT$48, MATCH(RIGHT($A23, LEN($A23)-4), JulR!$A$1:$A1065, 0), MATCH($A$1, JulR!$A$6:N$6, 0) ), IF(valor = "-", "", valor) ), "")} | J23: {=IFERROR( LET( valor, INDEX( AgoR!$A$1:$AT$60, MATCH(RIGHT($A23, LEN($A23)-4), AgoR!$A$1:$A1065, 0), MATCH($A$1, AgoR!$A$6:N$6, 0) ), IF(valor = "-", "", valor) ), "")} | K23: {=IFERROR( LET( valor, INDEX( SepR!$A$1:$AT$60, MATCH(RIGHT($A23, LEN($A23)-4), SepR!$A$1:$A1065, 0), MATCH($A$1, SepR!$A$6:N$6, 0) ), IF(valor = "-", "", valor) ), "")} | L23: {=IFERROR( LET( valor, INDEX( OctR!$A$1:$AT$60, MATCH(RIGHT($A23, LEN($A23)-4), OctR!$A$1:$A1065, 0), MATCH($A$1, OctR!$A$6:N$6, 0) ), IF(valor = "-", "", valor) ), "")} | M23: {=IFERROR( LET( valor, INDEX( NovR!$A$1:$AT$60, MATCH(RIGHT($A23, LEN($A23)-4), NovR!$A$1:$A1065, 0), MATCH($A$1, NovR!$A$6:N$6, 0) ), IF(valor = "-", "", valor) ), "")} | N23: {=IFERROR( LET( valor, INDEX( DicR!$A$1:$AT$60, MATCH(RIGHT($A23, LEN($A23)-4), DicR!$A$1:$A1065, 0), MATCH($A$1, DicR!$A$6:N$6, 0) ), IF(valor = "-", "", valor) ), "")}
A24: =Menus!B17 | B24: =C24+D24+E24+F24+G24+H24+I24+J24+K24+L24+M24+N24 -> 0 | C24: {=IFERROR( LET( valor, INDEX( EneR!$A$1:$AT$48, MATCH(RIGHT($A24, LEN($A24)-4), EneR!$A$1:$A1065, 0), MATCH($A$1, EneR!$A$6:N$6, 0) ), IF(valor = "-", "", valor) ), "")} | D24: {=IFERROR( LET( valor, INDEX( FebR!$A$1:$AT$51, MATCH(RIGHT($A24, LEN($A24)-4), FebR!$A$1:$A1065, 0), MATCH($A$1, FebR!$A$6:N$6, 0) ), IF(valor = "-", "", valor) ), "")} | E24: {=IFERROR( LET( valor, INDEX( MarR!$A$1:$AT$48, MATCH(RIGHT($A24, LEN($A24)-4), MarR!$A$1:$A1065, 0), MATCH($A$1, MarR!$A$6:N$6, 0) ), IF(valor = "-", "", valor) ), "")} | F24: {=IFERROR( LET( valor, INDEX( AbrR!$A$1:$AT$48, MATCH(RIGHT($A24, LEN($A24)-4), AbrR!$A$1:$A1065, 0), MATCH($A$1, AbrR!$A$6:N$6, 0) ), IF(valor = "-", "", valor) ), "")} | G24: {=IFERROR( LET( valor, INDEX( MayR!$A$1:$AT$48, MATCH(RIGHT($A24, LEN($A24)-4), MayR!$A$1:$A1065, 0), MATCH($A$1, MayR!$A$6:N$6, 0) ), IF(valor = "-", "", valor) ), "")} | H24: {=IFERROR( LET( valor, INDEX( JunR!$A$1:$AT$48, MATCH(RIGHT($A24, LEN($A24)-4), JunR!$A$1:$A1065, 0), MATCH($A$1, JunR!$A$6:N$6, 0) ), IF(valor = "-", "", valor) ), "")} | I24: {=IFERROR( LET( valor, INDEX( JulR!$A$1:$AT$48, MATCH(RIGHT($A24, LEN($A24)-4), JulR!$A$1:$A1065, 0), MATCH($A$1, JulR!$A$6:N$6, 0) ), IF(valor = "-", "", valor) ), "")} | J24: {=IFERROR( LET( valor, INDEX( AgoR!$A$1:$AT$60, MATCH(RIGHT($A24, LEN($A24)-4), AgoR!$A$1:$A1065, 0), MATCH($A$1, AgoR!$A$6:N$6, 0) ), IF(valor = "-", "", valor) ), "")} | K24: {=IFERROR( LET( valor, INDEX( SepR!$A$1:$AT$60, MATCH(RIGHT($A24, LEN($A24)-4), SepR!$A$1:$A1065, 0), MATCH($A$1, SepR!$A$6:N$6, 0) ), IF(valor = "-", "", valor) ), "")} | L24: {=IFERROR( LET( valor, INDEX( OctR!$A$1:$AT$60, MATCH(RIGHT($A24, LEN($A24)-4), OctR!$A$1:$A1065, 0), MATCH($A$1, OctR!$A$6:N$6, 0) ), IF(valor = "-", "", valor) ), "")} | M24: {=IFERROR( LET( valor, INDEX( NovR!$A$1:$AT$60, MATCH(RIGHT($A24, LEN($A24)-4), NovR!$A$1:$A1065, 0), MATCH($A$1, NovR!$A$6:N$6, 0) ), IF(valor = "-", "", valor) ), "")} | N24: {=IFERROR( LET( valor, INDEX( DicR!$A$1:$AT$60, MATCH(RIGHT($A24, LEN($A24)-4), DicR!$A$1:$A1065, 0), MATCH($A$1, DicR!$A$6:N$6, 0) ), IF(valor = "-", "", valor) ), "")}
A25: =Menus!B18 | B25: =C25+D25+E25+F25+G25+H25+I25+J25+K25+L25+M25+N25 -> 0 | C25: {=IFERROR( LET( valor, INDEX( EneR!$A$1:$AT$48, MATCH(RIGHT($A25, LEN($A25)-4), EneR!$A$1:$A1065, 0), MATCH($A$1, EneR!$A$6:N$6, 0) ), IF(valor = "-", "", valor) ), "")} | D25: {=IFERROR( LET( valor, INDEX( FebR!$A$1:$AT$51, MATCH(RIGHT($A25, LEN($A25)-4), FebR!$A$1:$A1065, 0), MATCH($A$1, FebR!$A$6:N$6, 0) ), IF(valor = "-", "", valor) ), "")} | E25: {=IFERROR( LET( valor, INDEX( MarR!$A$1:$AT$48, MATCH(RIGHT($A25, LEN($A25)-4), MarR!$A$1:$A1065, 0), MATCH($A$1, MarR!$A$6:N$6, 0) ), IF(valor = "-", "", valor) ), "")} | F25: {=IFERROR( LET( valor, INDEX( AbrR!$A$1:$AT$48, MATCH(RIGHT($A25, LEN($A25)-4), AbrR!$A$1:$A1065, 0), MATCH($A$1, AbrR!$A$6:N$6, 0) ), IF(valor = "-", "", valor) ), "")} | G25: {=IFERROR( LET( valor, INDEX( MayR!$A$1:$AT$48, MATCH(RIGHT($A25, LEN($A25)-4), MayR!$A$1:$A1065, 0), MATCH($A$1, MayR!$A$6:N$6, 0) ), IF(valor = "-", "", valor) ), "")} | H25: {=IFERROR( LET( valor, INDEX( JunR!$A$1:$AT$48, MATCH(RIGHT($A25, LEN($A25)-4), JunR!$A$1:$A1065, 0), MATCH($A$1, JunR!$A$6:N$6, 0) ), IF(valor = "-", "", valor) ), "")} | I25: {=IFERROR( LET( valor, INDEX( JulR!$A$1:$AT$48, MATCH(RIGHT($A25, LEN($A25)-4), JulR!$A$1:$A1065, 0), MATCH($A$1, JulR!$A$6:N$6, 0) ), IF(valor = "-", "", valor) ), "")} | J25: {=IFERROR( LET( valor, INDEX( AgoR!$A$1:$AT$60, MATCH(RIGHT($A25, LEN($A25)-4), AgoR!$A$1:$A1065, 0), MATCH($A$1, AgoR!$A$6:N$6, 0) ), IF(valor = "-", "", valor) ), "")} | K25: {=IFERROR( LET( valor, INDEX( SepR!$A$1:$AT$60, MATCH(RIGHT($A25, LEN($A25)-4), SepR!$A$1:$A1065, 0), MATCH($A$1, SepR!$A$6:N$6, 0) ), IF(valor = "-", "", valor) ), "")} | L25: {=IFERROR( LET( valor, INDEX( OctR!$A$1:$AT$60, MATCH(RIGHT($A25, LEN($A25)-4), OctR!$A$1:$A1065, 0), MATCH($A$1, OctR!$A$6:N$6, 0) ), IF(valor = "-", "", valor) ), "")} | M25: {=IFERROR( LET( valor, INDEX( NovR!$A$1:$AT$60, MATCH(RIGHT($A25, LEN($A25)-4), NovR!$A$1:$A1065, 0), MATCH($A$1, NovR!$A$6:N$6, 0) ), IF(valor = "-", "", valor) ), "")} | N25: {=IFERROR( LET( valor, INDEX( DicR!$A$1:$AT$60, MATCH(RIGHT($A25, LEN($A25)-4), DicR!$A$1:$A1065, 0), MATCH($A$1, DicR!$A$6:N$6, 0) ), IF(valor = "-", "", valor) ), "")}
A26: =Menus!B19 | B26: =C26+D26+E26+F26+G26+H26+I26+J26+K26+L26+M26+N26 -> 0 | C26: {=IFERROR( LET( valor, INDEX( EneR!$A$1:$AT$48, MATCH(RIGHT($A26, LEN($A26)-4), EneR!$A$1:$A1065, 0), MATCH($A$1, EneR!$A$6:N$6, 0) ), IF(valor = "-", "", valor) ), "")} | D26: {=IFERROR( LET( valor, INDEX( FebR!$A$1:$AT$51, MATCH(RIGHT($A26, LEN($A26)-4), FebR!$A$1:$A1065, 0), MATCH($A$1, FebR!$A$6:N$6, 0) ), IF(valor = "-", "", valor) ), "")} | E26: {=IFERROR( LET( valor, INDEX( MarR!$A$1:$AT$48, MATCH(RIGHT($A26, LEN($A26)-4), MarR!$A$1:$A1065, 0), MATCH($A$1, MarR!$A$6:N$6, 0) ), IF(valor = "-", "", valor) ), "")} | F26: {=IFERROR( LET( valor, INDEX( AbrR!$A$1:$AT$48, MATCH(RIGHT($A26, LEN($A26)-4), AbrR!$A$1:$A1065, 0), MATCH($A$1, AbrR!$A$6:N$6, 0) ), IF(valor = "-", "", valor) ), "")} | G26: {=IFERROR( LET( valor, INDEX( MayR!$A$1:$AT$48, MATCH(RIGHT($A26, LEN($A26)-4), MayR!$A$1:$A1065, 0), MATCH($A$1, MayR!$A$6:N$6, 0) ), IF(valor = "-", "", valor) ), "")} | H26: {=IFERROR( LET( valor, INDEX( JunR!$A$1:$AT$48, MATCH(RIGHT($A26, LEN($A26)-4), JunR!$A$1:$A1065, 0), MATCH($A$1, JunR!$A$6:N$6, 0) ), IF(valor = "-", "", valor) ), "")} | I26: {=IFERROR( LET( valor, INDEX( JulR!$A$1:$AT$48, MATCH(RIGHT($A26, LEN($A26)-4), JulR!$A$1:$A1065, 0), MATCH($A$1, JulR!$A$6:N$6, 0) ), IF(valor = "-", "", valor) ), "")} | J26: {=IFERROR( LET( valor, INDEX( AgoR!$A$1:$AT$60, MATCH(RIGHT($A26, LEN($A26)-4), AgoR!$A$1:$A1065, 0), MATCH($A$1, AgoR!$A$6:N$6, 0) ), IF(valor = "-", "", valor) ), "")} | K26: {=IFERROR( LET( valor, INDEX( SepR!$A$1:$AT$60, MATCH(RIGHT($A26, LEN($A26)-4), SepR!$A$1:$A1065, 0), MATCH($A$1, SepR!$A$6:N$6, 0) ), IF(valor = "-", "", valor) ), "")} | L26: {=IFERROR( LET( valor, INDEX( OctR!$A$1:$AT$60, MATCH(RIGHT($A26, LEN($A26)-4), OctR!$A$1:$A1065, 0), MATCH($A$1, OctR!$A$6:N$6, 0) ), IF(valor = "-", "", valor) ), "")} | M26: {=IFERROR( LET( valor, INDEX( NovR!$A$1:$AT$60, MATCH(RIGHT($A26, LEN($A26)-4), NovR!$A$1:$A1065, 0), MATCH($A$1, NovR!$A$6:N$6, 0) ), IF(valor = "-", "", valor) ), "")} | N26: {=IFERROR( LET( valor, INDEX( DicR!$A$1:$AT$60, MATCH(RIGHT($A26, LEN($A26)-4), DicR!$A$1:$A1065, 0), MATCH($A$1, DicR!$A$6:N$6, 0) ), IF(valor = "-", "", valor) ), "")}
A27: =Menus!B20 | B27: =C27+D27+E27+F27+G27+H27+I27+J27+K27+L27+M27+N27 -> 0 | C27: {=IFERROR( LET( valor, INDEX( EneR!$A$1:$AT$48, MATCH(RIGHT($A27, LEN($A27)-4), EneR!$A$1:$A1065, 0), MATCH($A$1, EneR!$A$6:N$6, 0) ), IF(valor = "-", "", valor) ), "")} | D27: {=IFERROR( LET( valor, INDEX( FebR!$A$1:$AT$51, MATCH(RIGHT($A27, LEN($A27)-4), FebR!$A$1:$A1065, 0), MATCH($A$1, FebR!$A$6:N$6, 0) ), IF(valor = "-", "", valor) ), "")} | E27: {=IFERROR( LET( valor, INDEX( MarR!$A$1:$AT$48, MATCH(RIGHT($A27, LEN($A27)-4), MarR!$A$1:$A1065, 0), MATCH($A$1, MarR!$A$6:N$6, 0) ), IF(valor = "-", "", valor) ), "")} | F27: {=IFERROR( LET( valor, INDEX( AbrR!$A$1:$AT$48, MATCH(RIGHT($A27, LEN($A27)-4), AbrR!$A$1:$A1065, 0), MATCH($A$1, AbrR!$A$6:N$6, 0) ), IF(valor = "-", "", valor) ), "")} | G27: {=IFERROR( LET( valor, INDEX( MayR!$A$1:$AT$48, MATCH(RIGHT($A27, LEN($A27)-4), MayR!$A$1:$A1065, 0), MATCH($A$1, MayR!$A$6:N$6, 0) ), IF(valor = "-", "", valor) ), "")} | H27: {=IFERROR( LET( valor, INDEX( JunR!$A$1:$AT$48, MATCH(RIGHT($A27, LEN($A27)-4), JunR!$A$1:$A1065, 0), MATCH($A$1, JunR!$A$6:N$6, 0) ), IF(valor = "-", "", valor) ), "")} | I27: {=IFERROR( LET( valor, INDEX( JulR!$A$1:$AT$48, MATCH(RIGHT($A27, LEN($A27)-4), JulR!$A$1:$A1065, 0), MATCH($A$1, JulR!$A$6:N$6, 0) ), IF(valor = "-", "", valor) ), "")} | J27: {=IFERROR( LET( valor, INDEX( AgoR!$A$1:$AT$60, MATCH(RIGHT($A27, LEN($A27)-4), AgoR!$A$1:$A1065, 0), MATCH($A$1, AgoR!$A$6:N$6, 0) ), IF(valor = "-", "", valor) ), "")} | K27: {=IFERROR( LET( valor, INDEX( SepR!$A$1:$AT$60, MATCH(RIGHT($A27, LEN($A27)-4), SepR!$A$1:$A1065, 0), MATCH($A$1, SepR!$A$6:N$6, 0) ), IF(valor = "-", "", valor) ), "")} | L27: {=IFERROR( LET( valor, INDEX( OctR!$A$1:$AT$60, MATCH(RIGHT($A27, LEN($A27)-4), OctR!$A$1:$A1065, 0), MATCH($A$1, OctR!$A$6:N$6, 0) ), IF(valor = "-", "", valor) ), "")} | M27: {=IFERROR( LET( valor, INDEX( NovR!$A$1:$AT$60, MATCH(RIGHT($A27, LEN($A27)-4), NovR!$A$1:$A1065, 0), MATCH($A$1, NovR!$A$6:N$6, 0) ), IF(valor = "-", "", valor) ), "")} | N27: {=IFERROR( LET( valor, INDEX( DicR!$A$1:$AT$60, MATCH(RIGHT($A27, LEN($A27)-4), DicR!$A$1:$A1065, 0), MATCH($A$1, DicR!$A$6:N$6, 0) ), IF(valor = "-", "", valor) ), "")}
A28: =Menus!B21 | B28: =C28+D28+E28+F28+G28+H28+I28+J28+K28+L28+M28+N28 -> 0 | C28: {=IFERROR( LET( valor, INDEX( EneR!$A$1:$AT$48, MATCH(RIGHT($A28, LEN($A28)-4), EneR!$A$1:$A1065, 0), MATCH($A$1, EneR!$A$6:N$6, 0) ), IF(valor = "-", "", valor) ), "")} | D28: {=IFERROR( LET( valor, INDEX( FebR!$A$1:$AT$51, MATCH(RIGHT($A28, LEN($A28)-4), FebR!$A$1:$A1065, 0), MATCH($A$1, FebR!$A$6:N$6, 0) ), IF(valor = "-", "", valor) ), "")} | E28: {=IFERROR( LET( valor, INDEX( MarR!$A$1:$AT$48, MATCH(RIGHT($A28, LEN($A28)-4), MarR!$A$1:$A1065, 0), MATCH($A$1, MarR!$A$6:N$6, 0) ), IF(valor = "-", "", valor) ), "")} | F28: {=IFERROR( LET( valor, INDEX( AbrR!$A$1:$AT$48, MATCH(RIGHT($A28, LEN($A28)-4), AbrR!$A$1:$A1065, 0), MATCH($A$1, AbrR!$A$6:N$6, 0) ), IF(valor = "-", "", valor) ), "")} | G28: {=IFERROR( LET( valor, INDEX( MayR!$A$1:$AT$48, MATCH(RIGHT($A28, LEN($A28)-4), MayR!$A$1:$A1065, 0), MATCH($A$1, MayR!$A$6:N$6, 0) ), IF(valor = "-", "", valor) ), "")} | H28: {=IFERROR( LET( valor, INDEX( JunR!$A$1:$AT$48, MATCH(RIGHT($A28, LEN($A28)-4), JunR!$A$1:$A1065, 0), MATCH($A$1, JunR!$A$6:N$6, 0) ), IF(valor = "-", "", valor) ), "")} | I28: {=IFERROR( LET( valor, INDEX( JulR!$A$1:$AT$48, MATCH(RIGHT($A28, LEN($A28)-4), JulR!$A$1:$A1065, 0), MATCH($A$1, JulR!$A$6:N$6, 0) ), IF(valor = "-", "", valor) ), "")} | J28: {=IFERROR( LET( valor, INDEX( AgoR!$A$1:$AT$60, MATCH(RIGHT($A28, LEN($A28)-4), AgoR!$A$1:$A1065, 0), MATCH($A$1, AgoR!$A$6:N$6, 0) ), IF(valor = "-", "", valor) ), "")} | K28: {=IFERROR( LET( valor, INDEX( SepR!$A$1:$AT$60, MATCH(RIGHT($A28, LEN($A28)-4), SepR!$A$1:$A1065, 0), MATCH($A$1, SepR!$A$6:N$6, 0) ), IF(valor = "-", "", valor) ), "")} | L28: {=IFERROR( LET( valor, INDEX( OctR!$A$1:$AT$60, MATCH(RIGHT($A28, LEN($A28)-4), OctR!$A$1:$A1065, 0), MATCH($A$1, OctR!$A$6:N$6, 0) ), IF(valor = "-", "", valor) ), "")} | M28: {=IFERROR( LET( valor, INDEX( NovR!$A$1:$AT$60, MATCH(RIGHT($A28, LEN($A28)-4), NovR!$A$1:$A1065, 0), MATCH($A$1, NovR!$A$6:N$6, 0) ), IF(valor = "-", "", valor) ), "")} | N28: {=IFERROR( LET( valor, INDEX( DicR!$A$1:$AT$60, MATCH(RIGHT($A28, LEN($A28)-4), DicR!$A$1:$A1065, 0), MATCH($A$1, DicR!$A$6:N$6, 0) ), IF(valor = "-", "", valor) ), "")}
A29: =Menus!B22 | B29: =C29+D29+E29+F29+G29+H29+I29+J29+K29+L29+M29+N29 -> 0 | C29: {=IFERROR( LET( valor, INDEX( EneR!$A$1:$AT$48, MATCH(RIGHT($A29, LEN($A29)-4), EneR!$A$1:$A1065, 0), MATCH($A$1, EneR!$A$6:N$6, 0) ), IF(valor = "-", "", valor) ), "")} | D29: {=IFERROR( LET( valor, INDEX( FebR!$A$1:$AT$51, MATCH(RIGHT($A29, LEN($A29)-4), FebR!$A$1:$A1065, 0), MATCH($A$1, FebR!$A$6:N$6, 0) ), IF(valor = "-", "", valor) ), "")} | E29: {=IFERROR( LET( valor, INDEX( MarR!$A$1:$AT$48, MATCH(RIGHT($A29, LEN($A29)-4), MarR!$A$1:$A1065, 0), MATCH($A$1, MarR!$A$6:N$6, 0) ), IF(valor = "-", "", valor) ), "")} | F29: {=IFERROR( LET( valor, INDEX( AbrR!$A$1:$AT$48, MATCH(RIGHT($A29, LEN($A29)-4), AbrR!$A$1:$A1065, 0), MATCH($A$1, AbrR!$A$6:N$6, 0) ), IF(valor = "-", "", valor) ), "")} | G29: {=IFERROR( LET( valor, INDEX( MayR!$A$1:$AT$48, MATCH(RIGHT($A29, LEN($A29)-4), MayR!$A$1:$A1065, 0), MATCH($A$1, MayR!$A$6:N$6, 0) ), IF(valor = "-", "", valor) ), "")} | H29: {=IFERROR( LET( valor, INDEX( JunR!$A$1:$AT$48, MATCH(RIGHT($A29, LEN($A29)-4), JunR!$A$1:$A1065, 0), MATCH($A$1, JunR!$A$6:N$6, 0) ), IF(valor = "-", "", valor) ), "")} | I29: {=IFERROR( LET( valor, INDEX( JulR!$A$1:$AT$48, MATCH(RIGHT($A29, LEN($A29)-4), JulR!$A$1:$A1065, 0), MATCH($A$1, JulR!$A$6:N$6, 0) ), IF(valor = "-", "", valor) ), "")} | J29: {=IFERROR( LET( valor, INDEX( AgoR!$A$1:$AT$60, MATCH(RIGHT($A29, LEN($A29)-4), AgoR!$A$1:$A1065, 0), MATCH($A$1, AgoR!$A$6:N$6, 0) ), IF(valor = "-", "", valor) ), "")} | K29: {=IFERROR( LET( valor, INDEX( SepR!$A$1:$AT$60, MATCH(RIGHT($A29, LEN($A29)-4), SepR!$A$1:$A1065, 0), MATCH($A$1, SepR!$A$6:N$6, 0) ), IF(valor = "-", "", valor) ), "")} | L29: {=IFERROR( LET( valor, INDEX( OctR!$A$1:$AT$60, MATCH(RIGHT($A29, LEN($A29)-4), OctR!$A$1:$A1065, 0), MATCH($A$1, OctR!$A$6:N$6, 0) ), IF(valor = "-", "", valor) ), "")} | M29: {=IFERROR( LET( valor, INDEX( NovR!$A$1:$AT$60, MATCH(RIGHT($A29, LEN($A29)-4), NovR!$A$1:$A1065, 0), MATCH($A$1, NovR!$A$6:N$6, 0) ), IF(valor = "-", "", valor) ), "")} | N29: {=IFERROR( LET( valor, INDEX( DicR!$A$1:$AT$60, MATCH(RIGHT($A29, LEN($A29)-4), DicR!$A$1:$A1065, 0), MATCH($A$1, DicR!$A$6:N$6, 0) ), IF(valor = "-", "", valor) ), "")}
A30: =Menus!B23 | B30: =C30+D30+E30+F30+G30+H30+I30+J30+K30+L30+M30+N30 -> 0 | C30: {=IFERROR( LET( valor, INDEX( EneR!$A$1:$AT$48, MATCH(RIGHT($A30, LEN($A30)-4), EneR!$A$1:$A1065, 0), MATCH($A$1, EneR!$A$6:N$6, 0) ), IF(valor = "-", "", valor) ), "")} | D30: {=IFERROR( LET( valor, INDEX( FebR!$A$1:$AT$51, MATCH(RIGHT($A30, LEN($A30)-4), FebR!$A$1:$A1065, 0), MATCH($A$1, FebR!$A$6:N$6, 0) ), IF(valor = "-", "", valor) ), "")} | E30: {=IFERROR( LET( valor, INDEX( MarR!$A$1:$AT$48, MATCH(RIGHT($A30, LEN($A30)-4), MarR!$A$1:$A1065, 0), MATCH($A$1, MarR!$A$6:N$6, 0) ), IF(valor = "-", "", valor) ), "")} | F30: {=IFERROR( LET( valor, INDEX( AbrR!$A$1:$AT$48, MATCH(RIGHT($A30, LEN($A30)-4), AbrR!$A$1:$A1065, 0), MATCH($A$1, AbrR!$A$6:N$6, 0) ), IF(valor = "-", "", valor) ), "")} | G30: {=IFERROR( LET( valor, INDEX( MayR!$A$1:$AT$48, MATCH(RIGHT($A30, LEN($A30)-4), MayR!$A$1:$A1065, 0), MATCH($A$1, MayR!$A$6:N$6, 0) ), IF(valor = "-", "", valor) ), "")} | H30: {=IFERROR( LET( valor, INDEX( JunR!$A$1:$AT$48, MATCH(RIGHT($A30, LEN($A30)-4), JunR!$A$1:$A1065, 0), MATCH($A$1, JunR!$A$6:N$6, 0) ), IF(valor = "-", "", valor) ), "")} | I30: {=IFERROR( LET( valor, INDEX( JulR!$A$1:$AT$48, MATCH(RIGHT($A30, LEN($A30)-4), JulR!$A$1:$A1065, 0), MATCH($A$1, JulR!$A$6:N$6, 0) ), IF(valor = "-", "", valor) ), "")} | J30: {=IFERROR( LET( valor, INDEX( AgoR!$A$1:$AT$60, MATCH(RIGHT($A30, LEN($A30)-4), AgoR!$A$1:$A1065, 0), MATCH($A$1, AgoR!$A$6:N$6, 0) ), IF(valor = "-", "", valor) ), "")} | K30: {=IFERROR( LET( valor, INDEX( SepR!$A$1:$AT$60, MATCH(RIGHT($A30, LEN($A30)-4), SepR!$A$1:$A1065, 0), MATCH($A$1, SepR!$A$6:N$6, 0) ), IF(valor = "-", "", valor) ), "")} | L30: {=IFERROR( LET( valor, INDEX( OctR!$A$1:$AT$60, MATCH(RIGHT($A30, LEN($A30)-4), OctR!$A$1:$A1065, 0), MATCH($A$1, OctR!$A$6:N$6, 0) ), IF(valor = "-", "", valor) ), "")} | M30: {=IFERROR( LET( valor, INDEX( NovR!$A$1:$AT$60, MATCH(RIGHT($A30, LEN($A30)-4), NovR!$A$1:$A1065, 0), MATCH($A$1, NovR!$A$6:N$6, 0) ), IF(valor = "-", "", valor) ), "")} | N30: {=IFERROR( LET( valor, INDEX( DicR!$A$1:$AT$60, MATCH(RIGHT($A30, LEN($A30)-4), DicR!$A$1:$A1065, 0), MATCH($A$1, DicR!$A$6:N$6, 0) ), IF(valor = "-", "", valor) ), "")}
A31: =Menus!B24 | B31: =C31+D31+E31+F31+G31+H31+I31+J31+K31+L31+M31+N31 -> 0 | C31: {=IFERROR( LET( valor, INDEX( EneR!$A$1:$AT$48, MATCH(RIGHT($A31, LEN($A31)-4), EneR!$A$1:$A1065, 0), MATCH($A$1, EneR!$A$6:N$6, 0) ), IF(valor = "-", "", valor) ), "")} | D31: {=IFERROR( LET( valor, INDEX( FebR!$A$1:$AT$51, MATCH(RIGHT($A31, LEN($A31)-4), FebR!$A$1:$A1065, 0), MATCH($A$1, FebR!$A$6:N$6, 0) ), IF(valor = "-", "", valor) ), "")} | E31: {=IFERROR( LET( valor, INDEX( MarR!$A$1:$AT$48, MATCH(RIGHT($A31, LEN($A31)-4), MarR!$A$1:$A1065, 0), MATCH($A$1, MarR!$A$6:N$6, 0) ), IF(valor = "-", "", valor) ), "")} | F31: {=IFERROR( LET( valor, INDEX( AbrR!$A$1:$AT$48, MATCH(RIGHT($A31, LEN($A31)-4), AbrR!$A$1:$A1065, 0), MATCH($A$1, AbrR!$A$6:N$6, 0) ), IF(valor = "-", "", valor) ), "")} | G31: {=IFERROR( LET( valor, INDEX( MayR!$A$1:$AT$48, MATCH(RIGHT($A31, LEN($A31)-4), MayR!$A$1:$A1065, 0), MATCH($A$1, MayR!$A$6:N$6, 0) ), IF(valor = "-", "", valor) ), "")} | H31: {=IFERROR( LET( valor, INDEX( JunR!$A$1:$AT$48, MATCH(RIGHT($A31, LEN($A31)-4), JunR!$A$1:$A1065, 0), MATCH($A$1, JunR!$A$6:N$6, 0) ), IF(valor = "-", "", valor) ), "")} | I31: {=IFERROR( LET( valor, INDEX( JulR!$A$1:$AT$48, MATCH(RIGHT($A31, LEN($A31)-4), JulR!$A$1:$A1065, 0), MATCH($A$1, JulR!$A$6:N$6, 0) ), IF(valor = "-", "", valor) ), "")} | J31: {=IFERROR( LET( valor, INDEX( AgoR!$A$1:$AT$60, MATCH(RIGHT($A31, LEN($A31)-4), AgoR!$A$1:$A1065, 0), MATCH($A$1, AgoR!$A$6:N$6, 0) ), IF(valor = "-", "", valor) ), "")} | K31: {=IFERROR( LET( valor, INDEX( SepR!$A$1:$AT$60, MATCH(RIGHT($A31, LEN($A31)-4), SepR!$A$1:$A1065, 0), MATCH($A$1, SepR!$A$6:N$6, 0) ), IF(valor = "-", "", valor) ), "")} | L31: {=IFERROR( LET( valor, INDEX( OctR!$A$1:$AT$60, MATCH(RIGHT($A31, LEN($A31)-4), OctR!$A$1:$A1065, 0), MATCH($A$1, OctR!$A$6:N$6, 0) ), IF(valor = "-", "", valor) ), "")} | M31: {=IFERROR( LET( valor, INDEX( NovR!$A$1:$AT$60, MATCH(RIGHT($A31, LEN($A31)-4), NovR!$A$1:$A1065, 0), MATCH($A$1, NovR!$A$6:N$6, 0) ), IF(valor = "-", "", valor) ), "")} | N31: {=IFERROR( LET( valor, INDEX( DicR!$A$1:$AT$60, MATCH(RIGHT($A31, LEN($A31)-4), DicR!$A$1:$A1065, 0), MATCH($A$1, DicR!$A$6:N$6, 0) ), IF(valor = "-", "", valor) ), "")}
A32: =Menus!B25 | B32: =C32+D32+E32+F32+G32+H32+I32+J32+K32+L32+M32+N32 -> 0 | C32: {=IFERROR( LET( valor, INDEX( EneR!$A$1:$AT$48, MATCH(RIGHT($A32, LEN($A32)-4), EneR!$A$1:$A1065, 0), MATCH($A$1, EneR!$A$6:N$6, 0) ), IF(valor = "-", "", valor) ), "")} | D32: {=IFERROR( LET( valor, INDEX( FebR!$A$1:$AT$51, MATCH(RIGHT($A32, LEN($A32)-4), FebR!$A$1:$A1065, 0), MATCH($A$1, FebR!$A$6:N$6, 0) ), IF(valor = "-", "", valor) ), "")} | E32: {=IFERROR( LET( valor, INDEX( MarR!$A$1:$AT$48, MATCH(RIGHT($A32, LEN($A32)-4), MarR!$A$1:$A1065, 0), MATCH($A$1, MarR!$A$6:N$6, 0) ), IF(valor = "-", "", valor) ), "")} | F32: {=IFERROR( LET( valor, INDEX( AbrR!$A$1:$AT$48, MATCH(RIGHT($A32, LEN($A32)-4), AbrR!$A$1:$A1065, 0), MATCH($A$1, AbrR!$A$6:N$6, 0) ), IF(valor = "-", "", valor) ), "")} | G32: {=IFERROR( LET( valor, INDEX( MayR!$A$1:$AT$48, MATCH(RIGHT($A32, LEN($A32)-4), MayR!$A$1:$A1065, 0), MATCH($A$1, MayR!$A$6:N$6, 0) ), IF(valor = "-", "", valor) ), "")} | H32: {=IFERROR( LET( valor, INDEX( JunR!$A$1:$AT$48, MATCH(RIGHT($A32, LEN($A32)-4), JunR!$A$1:$A1065, 0), MATCH($A$1, JunR!$A$6:N$6, 0) ), IF(valor = "-", "", valor) ), "")} | I32: {=IFERROR( LET( valor, INDEX( JulR!$A$1:$AT$48, MATCH(RIGHT($A32, LEN($A32)-4), JulR!$A$1:$A1065, 0), MATCH($A$1, JulR!$A$6:N$6, 0) ), IF(valor = "-", "", valor) ), "")} | J32: {=IFERROR( LET( valor, INDEX( AgoR!$A$1:$AT$60, MATCH(RIGHT($A32, LEN($A32)-4), AgoR!$A$1:$A1065, 0), MATCH($A$1, AgoR!$A$6:N$6, 0) ), IF(valor = "-", "", valor) ), "")} | K32: {=IFERROR( LET( valor, INDEX( SepR!$A$1:$AT$60, MATCH(RIGHT($A32, LEN($A32)-4), SepR!$A$1:$A1065, 0), MATCH($A$1, SepR!$A$6:N$6, 0) ), IF(valor = "-", "", valor) ), "")} | L32: {=IFERROR( LET( valor, INDEX( OctR!$A$1:$AT$60, MATCH(RIGHT($A32, LEN($A32)-4), OctR!$A$1:$A1065, 0), MATCH($A$1, OctR!$A$6:N$6, 0) ), IF(valor = "-", "", valor) ), "")} | M32: {=IFERROR( LET( valor, INDEX( NovR!$A$1:$AT$60, MATCH(RIGHT($A32, LEN($A32)-4), NovR!$A$1:$A1065, 0), MATCH($A$1, NovR!$A$6:N$6, 0) ), IF(valor = "-", "", valor) ), "")} | N32: {=IFERROR( LET( valor, INDEX( DicR!$A$1:$AT$60, MATCH(RIGHT($A32, LEN($A32)-4), DicR!$A$1:$A1065, 0), MATCH($A$1, DicR!$A$6:N$6, 0) ), IF(valor = "-", "", valor) ), "")}
A33: =Menus!B26 | B33: =C33+D33+E33+F33+G33+H33+I33+J33+K33+L33+M33+N33 -> 0 | C33: {=IFERROR( LET( valor, INDEX( EneR!$A$1:$AT$48, MATCH(RIGHT($A33, LEN($A33)-4), EneR!$A$1:$A1065, 0), MATCH($A$1, EneR!$A$6:N$6, 0) ), IF(valor = "-", "", valor) ), "")} | D33: {=IFERROR( LET( valor, INDEX( FebR!$A$1:$AT$51, MATCH(RIGHT($A33, LEN($A33)-4), FebR!$A$1:$A1065, 0), MATCH($A$1, FebR!$A$6:N$6, 0) ), IF(valor = "-", "", valor) ), "")} | E33: {=IFERROR( LET( valor, INDEX( MarR!$A$1:$AT$48, MATCH(RIGHT($A33, LEN($A33)-4), MarR!$A$1:$A1065, 0), MATCH($A$1, MarR!$A$6:N$6, 0) ), IF(valor = "-", "", valor) ), "")} | F33: {=IFERROR( LET( valor, INDEX( AbrR!$A$1:$AT$48, MATCH(RIGHT($A33, LEN($A33)-4), AbrR!$A$1:$A1065, 0), MATCH($A$1, AbrR!$A$6:N$6, 0) ), IF(valor = "-", "", valor) ), "")} | G33: {=IFERROR( LET( valor, INDEX( MayR!$A$1:$AT$48, MATCH(RIGHT($A33, LEN($A33)-4), MayR!$A$1:$A1065, 0), MATCH($A$1, MayR!$A$6:N$6, 0) ), IF(valor = "-", "", valor) ), "")} | H33: {=IFERROR( LET( valor, INDEX( JunR!$A$1:$AT$48, MATCH(RIGHT($A33, LEN($A33)-4), JunR!$A$1:$A1065, 0), MATCH($A$1, JunR!$A$6:N$6, 0) ), IF(valor = "-", "", valor) ), "")} | I33: {=IFERROR( LET( valor, INDEX( JulR!$A$1:$AT$48, MATCH(RIGHT($A33, LEN($A33)-4), JulR!$A$1:$A1065, 0), MATCH($A$1, JulR!$A$6:N$6, 0) ), IF(valor = "-", "", valor) ), "")} | J33: {=IFERROR( LET( valor, INDEX( AgoR!$A$1:$AT$60, MATCH(RIGHT($A33, LEN($A33)-4), AgoR!$A$1:$A1065, 0), MATCH($A$1, AgoR!$A$6:N$6, 0) ), IF(valor = "-", "", valor) ), "")} | K33: {=IFERROR( LET( valor, INDEX( SepR!$A$1:$AT$60, MATCH(RIGHT($A33, LEN($A33)-4), SepR!$A$1:$A1065, 0), MATCH($A$1, SepR!$A$6:N$6, 0) ), IF(valor = "-", "", valor) ), "")} | L33: {=IFERROR( LET( valor, INDEX( OctR!$A$1:$AT$60, MATCH(RIGHT($A33, LEN($A33)-4), OctR!$A$1:$A1065, 0), MATCH($A$1, OctR!$A$6:N$6, 0) ), IF(valor = "-", "", valor) ), "")} | M33: {=IFERROR( LET( valor, INDEX( NovR!$A$1:$AT$60, MATCH(RIGHT($A33, LEN($A33)-4), NovR!$A$1:$A1065, 0), MATCH($A$1, NovR!$A$6:N$6, 0) ), IF(valor = "-", "", valor) ), "")} | N33: {=IFERROR( LET( valor, INDEX( DicR!$A$1:$AT$60, MATCH(RIGHT($A33, LEN($A33)-4), DicR!$A$1:$A1065, 0), MATCH($A$1, DicR!$A$6:N$6, 0) ), IF(valor = "-", "", valor) ), "")}
A34: =Menus!B27 | B34: =C34+D34+E34+F34+G34+H34+I34+J34+K34+L34+M34+N34 -> 0 | C34: {=IFERROR( LET( valor, INDEX( EneR!$A$1:$AT$48, MATCH(RIGHT($A34, LEN($A34)-4), EneR!$A$1:$A1065, 0), MATCH($A$1, EneR!$A$6:N$6, 0) ), IF(valor = "-", "", valor) ), "")} | D34: {=IFERROR( LET( valor, INDEX( FebR!$A$1:$AT$51, MATCH(RIGHT($A34, LEN($A34)-4), FebR!$A$1:$A1065, 0), MATCH($A$1, FebR!$A$6:N$6, 0) ), IF(valor = "-", "", valor) ), "")} | E34: {=IFERROR( LET( valor, INDEX( MarR!$A$1:$AT$48, MATCH(RIGHT($A34, LEN($A34)-4), MarR!$A$1:$A1065, 0), MATCH($A$1, MarR!$A$6:N$6, 0) ), IF(valor = "-", "", valor) ), "")} | F34: {=IFERROR( LET( valor, INDEX( AbrR!$A$1:$AT$48, MATCH(RIGHT($A34, LEN($A34)-4), AbrR!$A$1:$A1065, 0), MATCH($A$1, AbrR!$A$6:N$6, 0) ), IF(valor = "-", "", valor) ), "")} | G34: {=IFERROR( LET( valor, INDEX( MayR!$A$1:$AT$48, MATCH(RIGHT($A34, LEN($A34)-4), MayR!$A$1:$A1065, 0), MATCH($A$1, MayR!$A$6:N$6, 0) ), IF(valor = "-", "", valor) ), "")} | H34: {=IFERROR( LET( valor, INDEX( JunR!$A$1:$AT$48, MATCH(RIGHT($A34, LEN($A34)-4), JunR!$A$1:$A1065, 0), MATCH($A$1, JunR!$A$6:N$6, 0) ), IF(valor = "-", "", valor) ), "")} | I34: {=IFERROR( LET( valor, INDEX( JulR!$A$1:$AT$48, MATCH(RIGHT($A34, LEN($A34)-4), JulR!$A$1:$A1065, 0), MATCH($A$1, JulR!$A$6:N$6, 0) ), IF(valor = "-", "", valor) ), "")} | J34: {=IFERROR( LET( valor, INDEX( AgoR!$A$1:$AT$60, MATCH(RIGHT($A34, LEN($A34)-4), AgoR!$A$1:$A1065, 0), MATCH($A$1, AgoR!$A$6:N$6, 0) ), IF(valor = "-", "", valor) ), "")} | K34: {=IFERROR( LET( valor, INDEX( SepR!$A$1:$AT$60, MATCH(RIGHT($A34, LEN($A34)-4), SepR!$A$1:$A1065, 0), MATCH($A$1, SepR!$A$6:N$6, 0) ), IF(valor = "-", "", valor) ), "")} | L34: {=IFERROR( LET( valor, INDEX( OctR!$A$1:$AT$60, MATCH(RIGHT($A34, LEN($A34)-4), OctR!$A$1:$A1065, 0), MATCH($A$1, OctR!$A$6:N$6, 0) ), IF(valor = "-", "", valor) ), "")} | M34: {=IFERROR( LET( valor, INDEX( NovR!$A$1:$AT$60, MATCH(RIGHT($A34, LEN($A34)-4), NovR!$A$1:$A1065, 0), MATCH($A$1, NovR!$A$6:N$6, 0) ), IF(valor = "-", "", valor) ), "")} | N34: {=IFERROR( LET( valor, INDEX( DicR!$A$1:$AT$60, MATCH(RIGHT($A34, LEN($A34)-4), DicR!$A$1:$A1065, 0), MATCH($A$1, DicR!$A$6:N$6, 0) ), IF(valor = "-", "", valor) ), "")}
A35: =Menus!B28 | B35: =C35+D35+E35+F35+G35+H35+I35+J35+K35+L35+M35+N35 -> 0 | C35: {=IFERROR( LET( valor, INDEX( EneR!$A$1:$AT$48, MATCH(RIGHT($A35, LEN($A35)-4), EneR!$A$1:$A1065, 0), MATCH($A$1, EneR!$A$6:N$6, 0) ), IF(valor = "-", "", valor) ), "")} | D35: {=IFERROR( LET( valor, INDEX( FebR!$A$1:$AT$51, MATCH(RIGHT($A35, LEN($A35)-4), FebR!$A$1:$A1065, 0), MATCH($A$1, FebR!$A$6:N$6, 0) ), IF(valor = "-", "", valor) ), "")} | E35: {=IFERROR( LET( valor, INDEX( MarR!$A$1:$AT$48, MATCH(RIGHT($A35, LEN($A35)-4), MarR!$A$1:$A1065, 0), MATCH($A$1, MarR!$A$6:N$6, 0) ), IF(valor = "-", "", valor) ), "")} | F35: {=IFERROR( LET( valor, INDEX( AbrR!$A$1:$AT$48, MATCH(RIGHT($A35, LEN($A35)-4), AbrR!$A$1:$A1065, 0), MATCH($A$1, AbrR!$A$6:N$6, 0) ), IF(valor = "-", "", valor) ), "")} | G35: {=IFERROR( LET( valor, INDEX( MayR!$A$1:$AT$48, MATCH(RIGHT($A35, LEN($A35)-4), MayR!$A$1:$A1065, 0), MATCH($A$1, MayR!$A$6:N$6, 0) ), IF(valor = "-", "", valor) ), "")} | H35: {=IFERROR( LET( valor, INDEX( JunR!$A$1:$AT$48, MATCH(RIGHT($A35, LEN($A35)-4), JunR!$A$1:$A1065, 0), MATCH($A$1, JunR!$A$6:N$6, 0) ), IF(valor = "-", "", valor) ), "")} | I35: {=IFERROR( LET( valor, INDEX( JulR!$A$1:$AT$48, MATCH(RIGHT($A35, LEN($A35)-4), JulR!$A$1:$A1065, 0), MATCH($A$1, JulR!$A$6:N$6, 0) ), IF(valor = "-", "", valor) ), "")} | J35: {=IFERROR( LET( valor, INDEX( AgoR!$A$1:$AT$60, MATCH(RIGHT($A35, LEN($A35)-4), AgoR!$A$1:$A1065, 0), MATCH($A$1, AgoR!$A$6:N$6, 0) ), IF(valor = "-", "", valor) ), "")} | K35: {=IFERROR( LET( valor, INDEX( SepR!$A$1:$AT$60, MATCH(RIGHT($A35, LEN($A35)-4), SepR!$A$1:$A1065, 0), MATCH($A$1, SepR!$A$6:N$6, 0) ), IF(valor = "-", "", valor) ), "")} | L35: {=IFERROR( LET( valor, INDEX( OctR!$A$1:$AT$60, MATCH(RIGHT($A35, LEN($A35)-4), OctR!$A$1:$A1065, 0), MATCH($A$1, OctR!$A$6:N$6, 0) ), IF(valor = "-", "", valor) ), "")} | M35: {=IFERROR( LET( valor, INDEX( NovR!$A$1:$AT$60, MATCH(RIGHT($A35, LEN($A35)-4), NovR!$A$1:$A1065, 0), MATCH($A$1, NovR!$A$6:N$6, 0) ), IF(valor = "-", "", valor) ), "")} | N35: {=IFERROR( LET( valor, INDEX( DicR!$A$1:$AT$60, MATCH(RIGHT($A35, LEN($A35)-4), DicR!$A$1:$A1065, 0), MATCH($A$1, DicR!$A$6:N$6, 0) ), IF(valor = "-", "", valor) ), "")}
A36: =Menus!B29 | B36: =C36+D36+E36+F36+G36+H36+I36+J36+K36+L36+M36+N36 -> 0 | C36: {=IFERROR( LET( valor, INDEX( EneR!$A$1:$AT$48, MATCH(RIGHT($A36, LEN($A36)-4), EneR!$A$1:$A1065, 0), MATCH($A$1, EneR!$A$6:N$6, 0) ), IF(valor = "-", "", valor) ), "")} | D36: {=IFERROR( LET( valor, INDEX( FebR!$A$1:$AT$51, MATCH(RIGHT($A36, LEN($A36)-4), FebR!$A$1:$A1065, 0), MATCH($A$1, FebR!$A$6:N$6, 0) ), IF(valor = "-", "", valor) ), "")} | E36: {=IFERROR( LET( valor, INDEX( MarR!$A$1:$AT$48, MATCH(RIGHT($A36, LEN($A36)-4), MarR!$A$1:$A1065, 0), MATCH($A$1, MarR!$A$6:N$6, 0) ), IF(valor = "-", "", valor) ), "")} | F36: {=IFERROR( LET( valor, INDEX( AbrR!$A$1:$AT$48, MATCH(RIGHT($A36, LEN($A36)-4), AbrR!$A$1:$A1065, 0), MATCH($A$1, AbrR!$A$6:N$6, 0) ), IF(valor = "-", "", valor) ), "")} | G36: {=IFERROR( LET( valor, INDEX( MayR!$A$1:$AT$48, MATCH(RIGHT($A36, LEN($A36)-4), MayR!$A$1:$A1065, 0), MATCH($A$1, MayR!$A$6:N$6, 0) ), IF(valor = "-", "", valor) ), "")} | H36: {=IFERROR( LET( valor, INDEX( JunR!$A$1:$AT$48, MATCH(RIGHT($A36, LEN($A36)-4), JunR!$A$1:$A1065, 0), MATCH($A$1, JunR!$A$6:N$6, 0) ), IF(valor = "-", "", valor) ), "")} | I36: {=IFERROR( LET( valor, INDEX( JulR!$A$1:$AT$48, MATCH(RIGHT($A36, LEN($A36)-4), JulR!$A$1:$A1065, 0), MATCH($A$1, JulR!$A$6:N$6, 0) ), IF(valor = "-", "", valor) ), "")} | J36: {=IFERROR( LET( valor, INDEX( AgoR!$A$1:$AT$60, MATCH(RIGHT($A36, LEN($A36)-4), AgoR!$A$1:$A1065, 0), MATCH($A$1, AgoR!$A$6:N$6, 0) ), IF(valor = "-", "", valor) ), "")} | K36: {=IFERROR( LET( valor, INDEX( SepR!$A$1:$AT$60, MATCH(RIGHT($A36, LEN($A36)-4), SepR!$A$1:$A1065, 0), MATCH($A$1, SepR!$A$6:N$6, 0) ), IF(valor = "-", "", valor) ), "")} | L36: {=IFERROR( LET( valor, INDEX( OctR!$A$1:$AT$60, MATCH(RIGHT($A36, LEN($A36)-4), OctR!$A$1:$A1065, 0), MATCH($A$1, OctR!$A$6:N$6, 0) ), IF(valor = "-", "", valor) ), "")} | M36: {=IFERROR( LET( valor, INDEX( NovR!$A$1:$AT$60, MATCH(RIGHT($A36, LEN($A36)-4), NovR!$A$1:$A1065, 0), MATCH($A$1, NovR!$A$6:N$6, 0) ), IF(valor = "-", "", valor) ), "")} | N36: {=IFERROR( LET( valor, INDEX( DicR!$A$1:$AT$60, MATCH(RIGHT($A36, LEN($A36)-4), DicR!$A$1:$A1065, 0), MATCH($A$1, DicR!$A$6:N$6, 0) ), IF(valor = "-", "", valor) ), "")}
A37: =Menus!B30 | B37: =C37+D37+E37+F37+G37+H37+I37+J37+K37+L37+M37+N37 -> 0 | C37: {=IFERROR( LET( valor, INDEX( EneR!$A$1:$AT$48, MATCH(RIGHT($A37, LEN($A37)-4), EneR!$A$1:$A1065, 0), MATCH($A$1, EneR!$A$6:N$6, 0) ), IF(valor = "-", "", valor) ), "")} | D37: {=IFERROR( LET( valor, INDEX( FebR!$A$1:$AT$51, MATCH(RIGHT($A37, LEN($A37)-4), FebR!$A$1:$A1065, 0), MATCH($A$1, FebR!$A$6:N$6, 0) ), IF(valor = "-", "", valor) ), "")} | E37: {=IFERROR( LET( valor, INDEX( MarR!$A$1:$AT$48, MATCH(RIGHT($A37, LEN($A37)-4), MarR!$A$1:$A1065, 0), MATCH($A$1, MarR!$A$6:N$6, 0) ), IF(valor = "-", "", valor) ), "")} | F37: {=IFERROR( LET( valor, INDEX( AbrR!$A$1:$AT$48, MATCH(RIGHT($A37, LEN($A37)-4), AbrR!$A$1:$A1065, 0), MATCH($A$1, AbrR!$A$6:N$6, 0) ), IF(valor = "-", "", valor) ), "")} | G37: {=IFERROR( LET( valor, INDEX( MayR!$A$1:$AT$48, MATCH(RIGHT($A37, LEN($A37)-4), MayR!$A$1:$A1065, 0), MATCH($A$1, MayR!$A$6:N$6, 0) ), IF(valor = "-", "", valor) ), "")} | H37: {=IFERROR( LET( valor, INDEX( JunR!$A$1:$AT$48, MATCH(RIGHT($A37, LEN($A37)-4), JunR!$A$1:$A1065, 0), MATCH($A$1, JunR!$A$6:N$6, 0) ), IF(valor = "-", "", valor) ), "")} | I37: {=IFERROR( LET( valor, INDEX( JulR!$A$1:$AT$48, MATCH(RIGHT($A37, LEN($A37)-4), JulR!$A$1:$A1065, 0), MATCH($A$1, JulR!$A$6:N$6, 0) ), IF(valor = "-", "", valor) ), "")} | J37: {=IFERROR( LET( valor, INDEX( AgoR!$A$1:$AT$60, MATCH(RIGHT($A37, LEN($A37)-4), AgoR!$A$1:$A1065, 0), MATCH($A$1, AgoR!$A$6:N$6, 0) ), IF(valor = "-", "", valor) ), "")} | K37: {=IFERROR( LET( valor, INDEX( SepR!$A$1:$AT$60, MATCH(RIGHT($A37, LEN($A37)-4), SepR!$A$1:$A1065, 0), MATCH($A$1, SepR!$A$6:N$6, 0) ), IF(valor = "-", "", valor) ), "")} | L37: {=IFERROR( LET( valor, INDEX( OctR!$A$1:$AT$60, MATCH(RIGHT($A37, LEN($A37)-4), OctR!$A$1:$A1065, 0), MATCH($A$1, OctR!$A$6:N$6, 0) ), IF(valor = "-", "", valor) ), "")} | M37: {=IFERROR( LET( valor, INDEX( NovR!$A$1:$AT$60, MATCH(RIGHT($A37, LEN($A37)-4), NovR!$A$1:$A1065, 0), MATCH($A$1, NovR!$A$6:N$6, 0) ), IF(valor = "-", "", valor) ), "")} | N37: {=IFERROR( LET( valor, INDEX( DicR!$A$1:$AT$60, MATCH(RIGHT($A37, LEN($A37)-4), DicR!$A$1:$A1065, 0), MATCH($A$1, DicR!$A$6:N$6, 0) ), IF(valor = "-", "", valor) ), "")}
A38: =Menus!B31 | B38: =C38+D38+E38+F38+G38+H38+I38+J38+K38+L38+M38+N38 -> 0 | C38: {=IFERROR( LET( valor, INDEX( EneR!$A$1:$AT$48, MATCH(RIGHT($A38, LEN($A38)-4), EneR!$A$1:$A1065, 0), MATCH($A$1, EneR!$A$6:N$6, 0) ), IF(valor = "-", "", valor) ), "")} | D38: {=IFERROR( LET( valor, INDEX( FebR!$A$1:$AT$51, MATCH(RIGHT($A38, LEN($A38)-4), FebR!$A$1:$A1065, 0), MATCH($A$1, FebR!$A$6:N$6, 0) ), IF(valor = "-", "", valor) ), "")} | E38: {=IFERROR( LET( valor, INDEX( MarR!$A$1:$AT$48, MATCH(RIGHT($A38, LEN($A38)-4), MarR!$A$1:$A1065, 0), MATCH($A$1, MarR!$A$6:N$6, 0) ), IF(valor = "-", "", valor) ), "")} | F38: {=IFERROR( LET( valor, INDEX( AbrR!$A$1:$AT$48, MATCH(RIGHT($A38, LEN($A38)-4), AbrR!$A$1:$A1065, 0), MATCH($A$1, AbrR!$A$6:N$6, 0) ), IF(valor = "-", "", valor) ), "")} | G38: {=IFERROR( LET( valor, INDEX( MayR!$A$1:$AT$48, MATCH(RIGHT($A38, LEN($A38)-4), MayR!$A$1:$A1065, 0), MATCH($A$1, MayR!$A$6:N$6, 0) ), IF(valor = "-", "", valor) ), "")} | H38: {=IFERROR( LET( valor, INDEX( JunR!$A$1:$AT$48, MATCH(RIGHT($A38, LEN($A38)-4), JunR!$A$1:$A1065, 0), MATCH($A$1, JunR!$A$6:N$6, 0) ), IF(valor = "-", "", valor) ), "")} | I38: {=IFERROR( LET( valor, INDEX( JulR!$A$1:$AT$48, MATCH(RIGHT($A38, LEN($A38)-4), JulR!$A$1:$A1065, 0), MATCH($A$1, JulR!$A$6:N$6, 0) ), IF(valor = "-", "", valor) ), "")} | J38: {=IFERROR( LET( valor, INDEX( AgoR!$A$1:$AT$60, MATCH(RIGHT($A38, LEN($A38)-4), AgoR!$A$1:$A1065, 0), MATCH($A$1, AgoR!$A$6:N$6, 0) ), IF(valor = "-", "", valor) ), "")} | K38: {=IFERROR( LET( valor, INDEX( SepR!$A$1:$AT$60, MATCH(RIGHT($A38, LEN($A38)-4), SepR!$A$1:$A1065, 0), MATCH($A$1, SepR!$A$6:N$6, 0) ), IF(valor = "-", "", valor) ), "")} | L38: {=IFERROR( LET( valor, INDEX( OctR!$A$1:$AT$60, MATCH(RIGHT($A38, LEN($A38)-4), OctR!$A$1:$A1065, 0), MATCH($A$1, OctR!$A$6:N$6, 0) ), IF(valor = "-", "", valor) ), "")} | M38: {=IFERROR( LET( valor, INDEX( NovR!$A$1:$AT$60, MATCH(RIGHT($A38, LEN($A38)-4), NovR!$A$1:$A1065, 0), MATCH($A$1, NovR!$A$6:N$6, 0) ), IF(valor = "-", "", valor) ), "")} | N38: {=IFERROR( LET( valor, INDEX( DicR!$A$1:$AT$60, MATCH(RIGHT($A38, LEN($A38)-4), DicR!$A$1:$A1065, 0), MATCH($A$1, DicR!$A$6:N$6, 0) ), IF(valor = "-", "", valor) ), "")}
A39: =Menus!B32 | B39: =C39+D39+E39+F39+G39+H39+I39+J39+K39+L39+M39+N39 -> 0 | C39: {=IFERROR( LET( valor, INDEX( EneR!$A$1:$AT$48, MATCH(RIGHT($A39, LEN($A39)-4), EneR!$A$1:$A1065, 0), MATCH($A$1, EneR!$A$6:N$6, 0) ), IF(valor = "-", "", valor) ), "")} | D39: {=IFERROR( LET( valor, INDEX( FebR!$A$1:$AT$51, MATCH(RIGHT($A39, LEN($A39)-4), FebR!$A$1:$A1065, 0), MATCH($A$1, FebR!$A$6:N$6, 0) ), IF(valor = "-", "", valor) ), "")} | E39: {=IFERROR( LET( valor, INDEX( MarR!$A$1:$AT$48, MATCH(RIGHT($A39, LEN($A39)-4), MarR!$A$1:$A1065, 0), MATCH($A$1, MarR!$A$6:N$6, 0) ), IF(valor = "-", "", valor) ), "")} | F39: {=IFERROR( LET( valor, INDEX( AbrR!$A$1:$AT$48, MATCH(RIGHT($A39, LEN($A39)-4), AbrR!$A$1:$A1065, 0), MATCH($A$1, AbrR!$A$6:N$6, 0) ), IF(valor = "-", "", valor) ), "")} | G39: {=IFERROR( LET( valor, INDEX( MayR!$A$1:$AT$48, MATCH(RIGHT($A39, LEN($A39)-4), MayR!$A$1:$A1065, 0), MATCH($A$1, MayR!$A$6:N$6, 0) ), IF(valor = "-", "", valor) ), "")} | H39: {=IFERROR( LET( valor, INDEX( JunR!$A$1:$AT$48, MATCH(RIGHT($A39, LEN($A39)-4), JunR!$A$1:$A1065, 0), MATCH($A$1, JunR!$A$6:N$6, 0) ), IF(valor = "-", "", valor) ), "")} | I39: {=IFERROR( LET( valor, INDEX( JulR!$A$1:$AT$48, MATCH(RIGHT($A39, LEN($A39)-4), JulR!$A$1:$A1065, 0), MATCH($A$1, JulR!$A$6:N$6, 0) ), IF(valor = "-", "", valor) ), "")} | J39: {=IFERROR( LET( valor, INDEX( AgoR!$A$1:$AT$60, MATCH(RIGHT($A39, LEN($A39)-4), AgoR!$A$1:$A1065, 0), MATCH($A$1, AgoR!$A$6:N$6, 0) ), IF(valor = "-", "", valor) ), "")} | K39: {=IFERROR( LET( valor, INDEX( SepR!$A$1:$AT$60, MATCH(RIGHT($A39, LEN($A39)-4), SepR!$A$1:$A1065, 0), MATCH($A$1, SepR!$A$6:N$6, 0) ), IF(valor = "-", "", valor) ), "")} | L39: {=IFERROR( LET( valor, INDEX( OctR!$A$1:$AT$60, MATCH(RIGHT($A39, LEN($A39)-4), OctR!$A$1:$A1065, 0), MATCH($A$1, OctR!$A$6:N$6, 0) ), IF(valor = "-", "", valor) ), "")} | M39: {=IFERROR( LET( valor, INDEX( NovR!$A$1:$AT$60, MATCH(RIGHT($A39, LEN($A39)-4), NovR!$A$1:$A1065, 0), MATCH($A$1, NovR!$A$6:N$6, 0) ), IF(valor = "-", "", valor) ), "")} | N39: {=IFERROR( LET( valor, INDEX( DicR!$A$1:$AT$60, MATCH(RIGHT($A39, LEN($A39)-4), DicR!$A$1:$A1065, 0), MATCH($A$1, DicR!$A$6:N$6, 0) ), IF(valor = "-", "", valor) ), "")}
A40: =Menus!B33 | B40: =C40+D40+E40+F40+G40+H40+I40+J40+K40+L40+M40+N40 -> 0 | C40: {=IFERROR( LET( valor, INDEX( EneR!$A$1:$AT$48, MATCH(RIGHT($A40, LEN($A40)-4), EneR!$A$1:$A1065, 0), MATCH($A$1, EneR!$A$6:N$6, 0) ), IF(valor = "-", "", valor) ), "")} | D40: {=IFERROR( LET( valor, INDEX( FebR!$A$1:$AT$51, MATCH(RIGHT($A40, LEN($A40)-4), FebR!$A$1:$A1065, 0), MATCH($A$1, FebR!$A$6:N$6, 0) ), IF(valor = "-", "", valor) ), "")} | E40: {=IFERROR( LET( valor, INDEX( MarR!$A$1:$AT$48, MATCH(RIGHT($A40, LEN($A40)-4), MarR!$A$1:$A1065, 0), MATCH($A$1, MarR!$A$6:N$6, 0) ), IF(valor = "-", "", valor) ), "")} | F40: {=IFERROR( LET( valor, INDEX( AbrR!$A$1:$AT$48, MATCH(RIGHT($A40, LEN($A40)-4), AbrR!$A$1:$A1065, 0), MATCH($A$1, AbrR!$A$6:N$6, 0) ), IF(valor = "-", "", valor) ), "")} | G40: {=IFERROR( LET( valor, INDEX( MayR!$A$1:$AT$48, MATCH(RIGHT($A40, LEN($A40)-4), MayR!$A$1:$A1065, 0), MATCH($A$1, MayR!$A$6:N$6, 0) ), IF(valor = "-", "", valor) ), "")} | H40: {=IFERROR( LET( valor, INDEX( JunR!$A$1:$AT$48, MATCH(RIGHT($A40, LEN($A40)-4), JunR!$A$1:$A1065, 0), MATCH($A$1, JunR!$A$6:N$6, 0) ), IF(valor = "-", "", valor) ), "")} | I40: {=IFERROR( LET( valor, INDEX( JulR!$A$1:$AT$48, MATCH(RIGHT($A40, LEN($A40)-4), JulR!$A$1:$A1065, 0), MATCH($A$1, JulR!$A$6:N$6, 0) ), IF(valor = "-", "", valor) ), "")} | J40: {=IFERROR( LET( valor, INDEX( AgoR!$A$1:$AT$60, MATCH(RIGHT($A40, LEN($A40)-4), AgoR!$A$1:$A1065, 0), MATCH($A$1, AgoR!$A$6:N$6, 0) ), IF(valor = "-", "", valor) ), "")} | K40: {=IFERROR( LET( valor, INDEX( SepR!$A$1:$AT$60, MATCH(RIGHT($A40, LEN($A40)-4), SepR!$A$1:$A1065, 0), MATCH($A$1, SepR!$A$6:N$6, 0) ), IF(valor = "-", "", valor) ), "")} | L40: {=IFERROR( LET( valor, INDEX( OctR!$A$1:$AT$60, MATCH(RIGHT($A40, LEN($A40)-4), OctR!$A$1:$A1065, 0), MATCH($A$1, OctR!$A$6:N$6, 0) ), IF(valor = "-", "", valor) ), "")} | M40: {=IFERROR( LET( valor, INDEX( NovR!$A$1:$AT$60, MATCH(RIGHT($A40, LEN($A40)-4), NovR!$A$1:$A1065, 0), MATCH($A$1, NovR!$A$6:N$6, 0) ), IF(valor = "-", "", valor) ), "")} | N40: {=IFERROR( LET( valor, INDEX( DicR!$A$1:$AT$60, MATCH(RIGHT($A40, LEN($A40)-4), DicR!$A$1:$A1065, 0), MATCH($A$1, DicR!$A$6:N$6, 0) ), IF(valor = "-", "", valor) ), "")}
A41: =Menus!B34 | B41: =C41+D41+E41+F41+G41+H41+I41+J41+K41+L41+M41+N41 -> 0 | C41: {=IFERROR( LET( valor, INDEX( EneR!$A$1:$AT$48, MATCH(RIGHT($A41, LEN($A41)-4), EneR!$A$1:$A1065, 0), MATCH($A$1, EneR!$A$6:N$6, 0) ), IF(valor = "-", "", valor) ), "")} | D41: {=IFERROR( LET( valor, INDEX( FebR!$A$1:$AT$51, MATCH(RIGHT($A41, LEN($A41)-4), FebR!$A$1:$A1065, 0), MATCH($A$1, FebR!$A$6:N$6, 0) ), IF(valor = "-", "", valor) ), "")} | E41: {=IFERROR( LET( valor, INDEX( MarR!$A$1:$AT$48, MATCH(RIGHT($A41, LEN($A41)-4), MarR!$A$1:$A1065, 0), MATCH($A$1, MarR!$A$6:N$6, 0) ), IF(valor = "-", "", valor) ), "")} | F41: {=IFERROR( LET( valor, INDEX( AbrR!$A$1:$AT$48, MATCH(RIGHT($A41, LEN($A41)-4), AbrR!$A$1:$A1065, 0), MATCH($A$1, AbrR!$A$6:N$6, 0) ), IF(valor = "-", "", valor) ), "")} | G41: {=IFERROR( LET( valor, INDEX( MayR!$A$1:$AT$48, MATCH(RIGHT($A41, LEN($A41)-4), MayR!$A$1:$A1065, 0), MATCH($A$1, MayR!$A$6:N$6, 0) ), IF(valor = "-", "", valor) ), "")} | H41: {=IFERROR( LET( valor, INDEX( JunR!$A$1:$AT$48, MATCH(RIGHT($A41, LEN($A41)-4), JunR!$A$1:$A1065, 0), MATCH($A$1, JunR!$A$6:N$6, 0) ), IF(valor = "-", "", valor) ), "")} | I41: {=IFERROR( LET( valor, INDEX( JulR!$A$1:$AT$48, MATCH(RIGHT($A41, LEN($A41)-4), JulR!$A$1:$A1065, 0), MATCH($A$1, JulR!$A$6:N$6, 0) ), IF(valor = "-", "", valor) ), "")} | J41: {=IFERROR( LET( valor, INDEX( AgoR!$A$1:$AT$60, MATCH(RIGHT($A41, LEN($A41)-4), AgoR!$A$1:$A1065, 0), MATCH($A$1, AgoR!$A$6:N$6, 0) ), IF(valor = "-", "", valor) ), "")} | K41: {=IFERROR( LET( valor, INDEX( SepR!$A$1:$AT$60, MATCH(RIGHT($A41, LEN($A41)-4), SepR!$A$1:$A1065, 0), MATCH($A$1, SepR!$A$6:N$6, 0) ), IF(valor = "-", "", valor) ), "")} | L41: {=IFERROR( LET( valor, INDEX( OctR!$A$1:$AT$60, MATCH(RIGHT($A41, LEN($A41)-4), OctR!$A$1:$A1065, 0), MATCH($A$1, OctR!$A$6:N$6, 0) ), IF(valor = "-", "", valor) ), "")} | M41: {=IFERROR( LET( valor, INDEX( NovR!$A$1:$AT$60, MATCH(RIGHT($A41, LEN($A41)-4), NovR!$A$1:$A1065, 0), MATCH($A$1, NovR!$A$6:N$6, 0) ), IF(valor = "-", "", valor) ), "")} | N41: {=IFERROR( LET( valor, INDEX( DicR!$A$1:$AT$60, MATCH(RIGHT($A41, LEN($A41)-4), DicR!$A$1:$A1065, 0), MATCH($A$1, DicR!$A$6:N$6, 0) ), IF(valor = "-", "", valor) ), "")}
A42: =Menus!B35 | B42: =C42+D42+E42+F42+G42+H42+I42+J42+K42+L42+M42+N42 -> 0 | C42: {=IFERROR( LET( valor, INDEX( EneR!$A$1:$AT$48, MATCH(RIGHT($A42, LEN($A42)-4), EneR!$A$1:$A1065, 0), MATCH($A$1, EneR!$A$6:N$6, 0) ), IF(valor = "-", "", valor) ), "")} | D42: {=IFERROR( LET( valor, INDEX( FebR!$A$1:$AT$51, MATCH(RIGHT($A42, LEN($A42)-4), FebR!$A$1:$A1065, 0), MATCH($A$1, FebR!$A$6:N$6, 0) ), IF(valor = "-", "", valor) ), "")} | E42: {=IFERROR( LET( valor, INDEX( MarR!$A$1:$AT$48, MATCH(RIGHT($A42, LEN($A42)-4), MarR!$A$1:$A1065, 0), MATCH($A$1, MarR!$A$6:N$6, 0) ), IF(valor = "-", "", valor) ), "")} | F42: {=IFERROR( LET( valor, INDEX( AbrR!$A$1:$AT$48, MATCH(RIGHT($A42, LEN($A42)-4), AbrR!$A$1:$A1065, 0), MATCH($A$1, AbrR!$A$6:N$6, 0) ), IF(valor = "-", "", valor) ), "")} | G42: {=IFERROR( LET( valor, INDEX( MayR!$A$1:$AT$48, MATCH(RIGHT($A42, LEN($A42)-4), MayR!$A$1:$A1065, 0), MATCH($A$1, MayR!$A$6:N$6, 0) ), IF(valor = "-", "", valor) ), "")} | H42: {=IFERROR( LET( valor, INDEX( JunR!$A$1:$AT$48, MATCH(RIGHT($A42, LEN($A42)-4), JunR!$A$1:$A1065, 0), MATCH($A$1, JunR!$A$6:N$6, 0) ), IF(valor = "-", "", valor) ), "")} | I42: {=IFERROR( LET( valor, INDEX( JulR!$A$1:$AT$48, MATCH(RIGHT($A42, LEN($A42)-4), JulR!$A$1:$A1065, 0), MATCH($A$1, JulR!$A$6:N$6, 0) ), IF(valor = "-", "", valor) ), "")} | J42: {=IFERROR( LET( valor, INDEX( AgoR!$A$1:$AT$60, MATCH(RIGHT($A42, LEN($A42)-4), AgoR!$A$1:$A1065, 0), MATCH($A$1, AgoR!$A$6:N$6, 0) ), IF(valor = "-", "", valor) ), "")} | K42: {=IFERROR( LET( valor, INDEX( SepR!$A$1:$AT$60, MATCH(RIGHT($A42, LEN($A42)-4), SepR!$A$1:$A1065, 0), MATCH($A$1, SepR!$A$6:N$6, 0) ), IF(valor = "-", "", valor) ), "")} | L42: {=IFERROR( LET( valor, INDEX( OctR!$A$1:$AT$60, MATCH(RIGHT($A42, LEN($A42)-4), OctR!$A$1:$A1065, 0), MATCH($A$1, OctR!$A$6:N$6, 0) ), IF(valor = "-", "", valor) ), "")} | M42: {=IFERROR( LET( valor, INDEX( NovR!$A$1:$AT$60, MATCH(RIGHT($A42, LEN($A42)-4), NovR!$A$1:$A1065, 0), MATCH($A$1, NovR!$A$6:N$6, 0) ), IF(valor = "-", "", valor) ), "")} | N42: {=IFERROR( LET( valor, INDEX( DicR!$A$1:$AT$60, MATCH(RIGHT($A42, LEN($A42)-4), DicR!$A$1:$A1065, 0), MATCH($A$1, DicR!$A$6:N$6, 0) ), IF(valor = "-", "", valor) ), "")}
A43: =Menus!B36 | B43: =C43+D43+E43+F43+G43+H43+I43+J43+K43+L43+M43+N43 -> 0 | C43: {=IFERROR( LET( valor, INDEX( EneR!$A$1:$AT$48, MATCH(RIGHT($A43, LEN($A43)-4), EneR!$A$1:$A1065, 0), MATCH($A$1, EneR!$A$6:N$6, 0) ), IF(valor = "-", "", valor) ), "")} | D43: {=IFERROR( LET( valor, INDEX( FebR!$A$1:$AT$51, MATCH(RIGHT($A43, LEN($A43)-4), FebR!$A$1:$A1065, 0), MATCH($A$1, FebR!$A$6:N$6, 0) ), IF(valor = "-", "", valor) ), "")} | E43: {=IFERROR( LET( valor, INDEX( MarR!$A$1:$AT$48, MATCH(RIGHT($A43, LEN($A43)-4), MarR!$A$1:$A1065, 0), MATCH($A$1, MarR!$A$6:N$6, 0) ), IF(valor = "-", "", valor) ), "")} | F43: {=IFERROR( LET( valor, INDEX( AbrR!$A$1:$AT$48, MATCH(RIGHT($A43, LEN($A43)-4), AbrR!$A$1:$A1065, 0), MATCH($A$1, AbrR!$A$6:N$6, 0) ), IF(valor = "-", "", valor) ), "")} | G43: {=IFERROR( LET( valor, INDEX( MayR!$A$1:$AT$48, MATCH(RIGHT($A43, LEN($A43)-4), MayR!$A$1:$A1065, 0), MATCH($A$1, MayR!$A$6:N$6, 0) ), IF(valor = "-", "", valor) ), "")} | H43: {=IFERROR( LET( valor, INDEX( JunR!$A$1:$AT$48, MATCH(RIGHT($A43, LEN($A43)-4), JunR!$A$1:$A1065, 0), MATCH($A$1, JunR!$A$6:N$6, 0) ), IF(valor = "-", "", valor) ), "")} | I43: {=IFERROR( LET( valor, INDEX( JulR!$A$1:$AT$48, MATCH(RIGHT($A43, LEN($A43)-4), JulR!$A$1:$A1065, 0), MATCH($A$1, JulR!$A$6:N$6, 0) ), IF(valor = "-", "", valor) ), "")} | J43: {=IFERROR( LET( valor, INDEX( AgoR!$A$1:$AT$60, MATCH(RIGHT($A43, LEN($A43)-4), AgoR!$A$1:$A1065, 0), MATCH($A$1, AgoR!$A$6:N$6, 0) ), IF(valor = "-", "", valor) ), "")} | K43: {=IFERROR( LET( valor, INDEX( SepR!$A$1:$AT$60, MATCH(RIGHT($A43, LEN($A43)-4), SepR!$A$1:$A1065, 0), MATCH($A$1, SepR!$A$6:N$6, 0) ), IF(valor = "-", "", valor) ), "")} | L43: {=IFERROR( LET( valor, INDEX( OctR!$A$1:$AT$60, MATCH(RIGHT($A43, LEN($A43)-4), OctR!$A$1:$A1065, 0), MATCH($A$1, OctR!$A$6:N$6, 0) ), IF(valor = "-", "", valor) ), "")} | M43: {=IFERROR( LET( valor, INDEX( NovR!$A$1:$AT$60, MATCH(RIGHT($A43, LEN($A43)-4), NovR!$A$1:$A1065, 0), MATCH($A$1, NovR!$A$6:N$6, 0) ), IF(valor = "-", "", valor) ), "")} | N43: {=IFERROR( LET( valor, INDEX( DicR!$A$1:$AT$60, MATCH(RIGHT($A43, LEN($A43)-4), DicR!$A$1:$A1065, 0), MATCH($A$1, DicR!$A$6:N$6, 0) ), IF(valor = "-", "", valor) ), "")}
A44: =Menus!B37 | B44: =C44+D44+E44+F44+G44+H44+I44+J44+K44+L44+M44+N44 -> 0 | C44: {=IFERROR( LET( valor, INDEX( EneR!$A$1:$AT$48, MATCH(RIGHT($A44, LEN($A44)-4), EneR!$A$1:$A1065, 0), MATCH($A$1, EneR!$A$6:N$6, 0) ), IF(valor = "-", "", valor) ), "")} | D44: {=IFERROR( LET( valor, INDEX( FebR!$A$1:$AT$51, MATCH(RIGHT($A44, LEN($A44)-4), FebR!$A$1:$A1065, 0), MATCH($A$1, FebR!$A$6:N$6, 0) ), IF(valor = "-", "", valor) ), "")} | E44: {=IFERROR( LET( valor, INDEX( MarR!$A$1:$AT$48, MATCH(RIGHT($A44, LEN($A44)-4), MarR!$A$1:$A1065, 0), MATCH($A$1, MarR!$A$6:N$6, 0) ), IF(valor = "-", "", valor) ), "")} | F44: {=IFERROR( LET( valor, INDEX( AbrR!$A$1:$AT$48, MATCH(RIGHT($A44, LEN($A44)-4), AbrR!$A$1:$A1065, 0), MATCH($A$1, AbrR!$A$6:N$6, 0) ), IF(valor = "-", "", valor) ), "")} | G44: {=IFERROR( LET( valor, INDEX( MayR!$A$1:$AT$48, MATCH(RIGHT($A44, LEN($A44)-4), MayR!$A$1:$A1065, 0), MATCH($A$1, MayR!$A$6:N$6, 0) ), IF(valor = "-", "", valor) ), "")} | H44: {=IFERROR( LET( valor, INDEX( JunR!$A$1:$AT$48, MATCH(RIGHT($A44, LEN($A44)-4), JunR!$A$1:$A1065, 0), MATCH($A$1, JunR!$A$6:N$6, 0) ), IF(valor = "-", "", valor) ), "")} | I44: {=IFERROR( LET( valor, INDEX( JulR!$A$1:$AT$48, MATCH(RIGHT($A44, LEN($A44)-4), JulR!$A$1:$A1065, 0), MATCH($A$1, JulR!$A$6:N$6, 0) ), IF(valor = "-", "", valor) ), "")} | J44: {=IFERROR( LET( valor, INDEX( AgoR!$A$1:$AT$60, MATCH(RIGHT($A44, LEN($A44)-4), AgoR!$A$1:$A1065, 0), MATCH($A$1, AgoR!$A$6:N$6, 0) ), IF(valor = "-", "", valor) ), "")} | K44: {=IFERROR( LET( valor, INDEX( SepR!$A$1:$AT$60, MATCH(RIGHT($A44, LEN($A44)-4), SepR!$A$1:$A1065, 0), MATCH($A$1, SepR!$A$6:N$6, 0) ), IF(valor = "-", "", valor) ), "")} | L44: {=IFERROR( LET( valor, INDEX( OctR!$A$1:$AT$60, MATCH(RIGHT($A44, LEN($A44)-4), OctR!$A$1:$A1065, 0), MATCH($A$1, OctR!$A$6:N$6, 0) ), IF(valor = "-", "", valor) ), "")} | M44: {=IFERROR( LET( valor, INDEX( NovR!$A$1:$AT$60, MATCH(RIGHT($A44, LEN($A44)-4), NovR!$A$1:$A1065, 0), MATCH($A$1, NovR!$A$6:N$6, 0) ), IF(valor = "-", "", valor) ), "")} | N44: {=IFERROR( LET( valor, INDEX( DicR!$A$1:$AT$60, MATCH(RIGHT($A44, LEN($A44)-4), DicR!$A$1:$A1065, 0), MATCH($A$1, DicR!$A$6:N$6, 0) ), IF(valor = "-", "", valor) ), "")}
A45: =Menus!B38 | B45: =C45+D45+E45+F45+G45+H45+I45+J45+K45+L45+M45+N45 -> 0 | C45: {=IFERROR( LET( valor, INDEX( EneR!$A$1:$AT$48, MATCH(RIGHT($A45, LEN($A45)-4), EneR!$A$1:$A1065, 0), MATCH($A$1, EneR!$A$6:N$6, 0) ), IF(valor = "-", "", valor) ), "")} | D45: {=IFERROR( LET( valor, INDEX( FebR!$A$1:$AT$51, MATCH(RIGHT($A45, LEN($A45)-4), FebR!$A$1:$A1065, 0), MATCH($A$1, FebR!$A$6:N$6, 0) ), IF(valor = "-", "", valor) ), "")} | E45: {=IFERROR( LET( valor, INDEX( MarR!$A$1:$AT$48, MATCH(RIGHT($A45, LEN($A45)-4), MarR!$A$1:$A1065, 0), MATCH($A$1, MarR!$A$6:N$6, 0) ), IF(valor = "-", "", valor) ), "")} | F45: {=IFERROR( LET( valor, INDEX( AbrR!$A$1:$AT$48, MATCH(RIGHT($A45, LEN($A45)-4), AbrR!$A$1:$A1065, 0), MATCH($A$1, AbrR!$A$6:N$6, 0) ), IF(valor = "-", "", valor) ), "")} | G45: {=IFERROR( LET( valor, INDEX( MayR!$A$1:$AT$48, MATCH(RIGHT($A45, LEN($A45)-4), MayR!$A$1:$A1065, 0), MATCH($A$1, MayR!$A$6:N$6, 0) ), IF(valor = "-", "", valor) ), "")} | H45: {=IFERROR( LET( valor, INDEX( JunR!$A$1:$AT$48, MATCH(RIGHT($A45, LEN($A45)-4), JunR!$A$1:$A1065, 0), MATCH($A$1, JunR!$A$6:N$6, 0) ), IF(valor = "-", "", valor) ), "")} | I45: {=IFERROR( LET( valor, INDEX( JulR!$A$1:$AT$48, MATCH(RIGHT($A45, LEN($A45)-4), JulR!$A$1:$A1065, 0), MATCH($A$1, JulR!$A$6:N$6, 0) ), IF(valor = "-", "", valor) ), "")} | J45: {=IFERROR( LET( valor, INDEX( AgoR!$A$1:$AT$60, MATCH(RIGHT($A45, LEN($A45)-4), AgoR!$A$1:$A1065, 0), MATCH($A$1, AgoR!$A$6:N$6, 0) ), IF(valor = "-", "", valor) ), "")} | K45: {=IFERROR( LET( valor, INDEX( SepR!$A$1:$AT$60, MATCH(RIGHT($A45, LEN($A45)-4), SepR!$A$1:$A1065, 0), MATCH($A$1, SepR!$A$6:N$6, 0) ), IF(valor = "-", "", valor) ), "")} | L45: {=IFERROR( LET( valor, INDEX( OctR!$A$1:$AT$60, MATCH(RIGHT($A45, LEN($A45)-4), OctR!$A$1:$A1065, 0), MATCH($A$1, OctR!$A$6:N$6, 0) ), IF(valor = "-", "", valor) ), "")} | M45: {=IFERROR( LET( valor, INDEX( NovR!$A$1:$AT$60, MATCH(RIGHT($A45, LEN($A45)-4), NovR!$A$1:$A1065, 0), MATCH($A$1, NovR!$A$6:N$6, 0) ), IF(valor = "-", "", valor) ), "")} | N45: {=IFERROR( LET( valor, INDEX( DicR!$A$1:$AT$60, MATCH(RIGHT($A45, LEN($A45)-4), DicR!$A$1:$A1065, 0), MATCH($A$1, DicR!$A$6:N$6, 0) ), IF(valor = "-", "", valor) ), "")}
