Workbook

Sheet xProyecto
A1: Wepark S.A. de C.V. | B1: Total | C1: Interlomas | D1: {=TRANSPOSE(Menus!A2:A127)}
A3: Utilidad Wepark | B3: =SUM(D3:AZ3) -> 0 | C3: =C5-C36+C101 -> 0 | D3: =D5-D36+D105 -> 0 | E3: =E9-E40+E105 -> 0 | F3: =F9-F40+F105 -> 0 | G3: =G9-G40+G105 -> 0 | H3: =H9-H40+H105 -> 0 | I3: =I9-I40+I105 -> 0 | J3: =J9-J40+J105 -> 0 | K3: =K9-K40+K105 -> 0 | L3: =L9-L40+L105 -> 0 | ... AZ3: =AZ9-AZ40+AZ105 -> 0
A5: Honorario Wepark | B5: =SUM(D5:AZ5) -> 0 | C5: =IF(ISNA(VLOOKUP(C$1,Utilidades!$A$1:$B127,2,FALSE)),"",VLOOKUP(C$1,Utilidades!$A$1:$B127,2,FALSE)) | D5: =IF(ISNA(VLOOKUP(D$1,Utilidades!$A$1:$B127,2,FALSE)),"",VLOOKUP(D$1,Utilidades!$A$1:$B127,2,FALSE)) | E5: =IF(ISNA(VLOOKUP(E$1,Utilidades!$A$1:$B127,2,FALSE)),"",VLOOKUP(E$1,Utilidades!$A$1:$B127,2,FALSE)) | F5: =IF(ISNA(VLOOKUP(F$1,Utilidades!$A$1:$B127,2,FALSE)),"",VLOOKUP(F$1,Utilidades!$A$1:$B127,2,FALSE)) | G5: =IF(ISNA(VLOOKUP(G$1,Utilidades!$A$1:$B127,2,FALSE)),"",VLOOKUP(G$1,Utilidades!$A$1:$B127,2,FALSE)) | H5: =IF(ISNA(VLOOKUP(H$1,Utilidades!$A$1:$B127,2,FALSE)),"",VLOOKUP(H$1,Utilidades!$A$1:$B127,2,FALSE)) | I5: =IF(ISNA(VLOOKUP(I$1,Utilidades!$A$1:$B127,2,FALSE)),"",VLOOKUP(I$1,Utilidades!$A$1:$B127,2,FALSE)) | J5: =IF(ISNA(VLOOKUP(J$1,Utilidades!$A$1:$B127,2,FALSE)),"",VLOOKUP(J$1,Utilidades!$A$1:$B127,2,FALSE)) | ... AZ5: =IF(ISNA(VLOOKUP(AZ$1,Utilidades!$A$1:$B127,2,FALSE)),"",VLOOKUP(AZ$1,Utilidades!$A$1:$B127,2,FALSE))
A7: Utilidad Bruta | B7: =SUM(D7:AZ7) -> 0 | C7: =C9-C40+C105 -> 0 | D7: =D9-D40 -> 0 | E7: =E9-E40 -> 0 | F7: =F9-F40 -> 0 | G7: =G9-G40 -> 0 | H7: =H9-H40 -> 0 | I7: =I9-I40 -> 0 | J7: =J9-J40 -> 0 | K7: =K9-K40 -> 0 | ... AZ7: =AZ9-AZ40 -> 0
A9: Total de Ingresos | B9: =SUM(B10:B38) -> 0 | C9: =SUM(C10:C38) -> 0 | D9: =SUM(D10:D38) -> 0 | E9: =SUM(E10:E38) -> 0 | F9: =SUM(F10:F38) -> 0 | G9: =SUM(G10:G38) -> 0 | H9: =SUM(H10:H38) -> 0 | I9: =SUM(I10:I38) -> 0 | ... AY9: =SUM(AY10:AY38) -> 0
A10: =Menus!R2 | B10: =IFERROR(SUM(D10:AZ10),"") -> 0 | C10: =IFERROR(INDEX($D$1:$AQ127, MATCH($A10, $A$1:$A127, 0), MATCH(C$1, $D$1:AZ$1, 0)), "") | D10: {=SUM( IFERROR( VLOOKUP($A10, INDIRECT("EneR!$A$6:$ZZ$1048576"), MATCH(D$1, EneR!$6:$6, 0), FALSE), 0 ) + IFERROR( VLOOKUP($A10, INDIRECT("FebR!$A$6:$ZZ$1048576"), MATCH(D$1, FebR!$6:$6, 0), FALSE), 0 ) + IFERROR( VLOOKUP($A10, INDIRECT("MarR!$A$6:$ZZ$1048576"), MATCH(D$1, MarR!$6:$6, 0), FALSE), 0 ) + IFERROR( VLOOKUP($A10, INDIRECT("AbrR!$A$6:$ZZ$1048576"), MATCH(D$1, AbrR!$6:$6, 0), FALSE), 0 ) + IFERROR( VLOOKUP($A10, INDIRECT("MayR!$A$6:$ZZ$1048576"), MATCH(D$1, MayR!$6:$6, 0), FALSE), 0 ) + IFERROR( VLOOKUP($A10, INDIRECT("JunR!$A$6:$ZZ$1048576"), MATCH(D$1, JunR!$6:$6, 0), FALSE), 0 ) + IFERROR( VLOOKUP($A10, INDIRECT("JulR!$A$6:$ZZ$1048576"), MATCH(D$1, JulR!$6:$6, 0), FALSE), 0 ) + IFERROR( VLOOKUP($A10, INDIRECT("AgoR!$A$6:$ZZ$1048576"), MATCH(D$1, AgoR!$6:$6, 0), FALSE), 0 ) + IFERROR( VLOOKUP($A10, INDIRECT("SepR!$A$6:$ZZ$1048576"), MATCH(D$1, SepR!$6:$6, 0), FALSE), 0 ) + IFERROR( VLOOKUP($A10, INDIRECT("OctR!$A$6:$ZZ$1048576"), MATCH(D$1, OctR!$6:$6, 0), FALSE), 0 ) + IFERROR( VLOOKUP($A10, INDIRECT("NovR!$A$6:$ZZ$1048576"), MATCH(D$1, NovR!$6:$6, 0), FALSE), 0 ) + IFERROR( VLOOKUP($A10, INDIRECT("DicR!$A$6:$ZZ$1048576"), MATCH(D$1, DicR!$6:$6, 0), FALSE), 0 ) )} -> 0 | E10: {=SUM( IFERROR( VLOOKUP($A10, INDIRECT("EneR!$A$6:$ZZ$1048576"), MATCH(E$1, EneR!$6:$6, 0), FALSE), 0 ) + IFERROR( VLOOKUP($A10, INDIRECT("FebR!$A$6:$ZZ$1048576"), MATCH(E$1, FebR!$6:$6, 0), FALSE), 0 ) + IFERROR( VLOOKUP($A10, INDIRECT("MarR!$A$6:$ZZ$1048576"), MATCH(E$1, MarR!$6:$6, 0), FALSE), 0 ) + IFERROR( VLOOKUP($A10, INDIRECT("AbrR!$A$6:$ZZ$1048576"), MATCH(E$1, AbrR!$6:$6, 0), FALSE), 0 ) + IFERROR( VLOOKUP($A10, INDIRECT("MayR!$A$6:$ZZ$1048576"), MATCH(E$1, MayR!$6:$6, 0), FALSE), 0 ) + IFERROR( VLOOKUP($A10, INDIRECT("JunR!$A$6:$ZZ$1048576"), MATCH(E$1, JunR!$6:$6, 0), FALSE), 0 ) + IFERROR( VLOOKUP($A10, INDIRECT("JulR!$A$6:$ZZ$1048576"), MATCH(E$1, JulR!$6:$6, 0), FALSE), 0 ) + IFERROR( VLOOKUP($A10, INDIRECT("AgoR!$A$6:$ZZ$1048576"), MATCH(E$1, AgoR!$6:$6, 0), FALSE), 0 ) + IFERROR( VLOOKUP($A10, INDIRECT("SepR!$A$6:$ZZ$1048576"), MATCH(E$1, SepR!$6:$6, 0), FALSE), 0 ) + IFERROR( VLOOKUP($A10, INDIRECT("OctR!$A$6:$ZZ$1048576"), MATCH(E$1, OctR!$6:$6, 0), FALSE), 0 ) + IFERROR( VLOOKUP($A10, INDIRECT("NovR!$A$6:$ZZ$1048576"), MATCH(E$1, NovR!$6:$6, 0), FALSE), 0 ) + IFERROR( VLOOKUP($A10, INDIRECT("DicR!$A$6:$ZZ$1048576"), MATCH(E$1, DicR!$6:$6, 0), FALSE), 0 ) )} -> 0 | F10: {=SUM( IFERROR( VLOOKUP($A10, INDIRECT("EneR!$A$6:$ZZ$1048576"), MATCH(F$1, EneR!$6:$6, 0), FALSE), 0 ) + IFERROR( VLOOKUP($A10, INDIRECT("FebR!$A$6:$ZZ$1048576"), MATCH(F$1, FebR!$6:$6, 0), FALSE), 0 ) + IFERROR( VLOOKUP($A10, INDIRECT("MarR!$A$6:$ZZ$1048576"), MATCH(F$1, MarR!$6:$6, 0), FALSE), 0 ) + IFERROR( VLOOKUP($A10, INDIRECT("AbrR!$A$6:$ZZ$1048576"), MATCH(F$1, AbrR!$6:$6, 0), FALSE), 0 ) + IFERROR( VLOOKUP($A10, INDIRECT("MayR!$A$6:$ZZ$1048576"), MATCH(F$1, MayR!$6:$6, 0), FALSE), 0 ) + IFERROR( VLOOKUP($A10, INDIRECT("JunR!$A$6:$ZZ$1048576"), MATCH(F$1, JunR!$6:$6, 0), FALSE), 0 ) + IFERROR( VLOOKUP($A10, INDIRECT("JulR!$A$6:$ZZ$1048576"), MATCH(F$1, JulR!$6:$6, 0), FALSE), 0 ) + IFERROR( VLOOKUP($A10, INDIRECT("AgoR!$A$6:$ZZ$1048576"), MATCH(F$1, AgoR!$6:$6, 0), FALSE), 0 ) + IFERROR( VLOOKUP($A10, INDIRECT("SepR!$A$6:$ZZ$1048576"), MATCH(F$1, SepR!$6:$6, 0), FALSE), 0 ) + IFERROR( VLOOKUP($A10, INDIRECT("OctR!$A$6:$ZZ$1048576"), MATCH(F$1, OctR!$6:$6, 0), FALSE), 0 ) + IFERROR( VLOOKUP($A10, INDIRECT("NovR!$A$6:$ZZ$1048576"), MATCH(F$1, NovR!$6:$6, 0), FALSE), 0 ) + IFERROR( VLOOKUP($A10, INDIRECT("DicR!$A$6:$ZZ$1048576"), MATCH(F$1, DicR!$6:$6, 0), FALSE), 0 ) )} -> 0 | G10: {=SUM( IFERROR( VLOOKUP($A10, INDIRECT("EneR!$A$6:$ZZ$1048576"), MATCH(G$1, EneR!$6:$6, 0), FALSE), 0 ) + IFERROR( VLOOKUP($A10, INDIRECT("FebR!$A$6:$ZZ$1048576"), MATCH(G$1, FebR!$6:$6, 0), FALSE), 0 ) + IFERROR( VLOOKUP($A10, INDIRECT("MarR!$A$6:$ZZ$1048576"), MATCH(G$1, MarR!$6:$6, 0), FALSE), 0 ) + IFERROR( VLOOKUP($A10, INDIRECT("AbrR!$A$6:$ZZ$1048576"), MATCH(G$1, AbrR!$6:$6, 0), FALSE), 0 ) + IFERROR( VLOOKUP($A10, INDIRECT("MayR!$A$6:$ZZ$1048576"), MATCH(G$1, MayR!$6:$6, 0), FALSE), 0 ) + IFERROR( VLOOKUP($A10, INDIRECT("JunR!$A$6:$ZZ$1048576"), MATCH(G$1, JunR!$6:$6, 0), FALSE), 0 ) + IFERROR( VLOOKUP($A10, INDIRECT("JulR!$A$6:$ZZ$1048576"), MATCH(G$1, JulR!$6:$6, 0), FALSE), 0 ) + IFERROR( VLOOKUP($A10, INDIRECT("AgoR!$A$6:$ZZ$1048576"), MATCH(G$1, AgoR!$6:$6, 0), FALSE), 0 ) + IFERROR( VLOOKUP($A10, INDIRECT("SepR!$A$6:$ZZ$1048576"), MATCH(G$1, SepR!$6:$6, 0), FALSE), 0 ) + IFERROR( VLOOKUP($A10, INDIRECT("OctR!$A$6:$ZZ$1048576"), MATCH(G$1, OctR!$6:$6, 0), FALSE), 0 ) + IFERROR( VLOOKUP($A10, INDIRECT("NovR!$A$6:$ZZ$1048576"), MATCH(G$1, NovR!$6:$6, 0), FALSE), 0 ) + IFERROR( VLOOKUP($A10, INDIRECT("DicR!$A$6:$ZZ$1048576"), MATCH(G$1, DicR!$6:$6, 0), FALSE), 0 ) )} -> 0 | H10: {=SUM( IFERROR( VLOOKUP($A10, INDIRECT("EneR!$A$6:$ZZ$1048576"), MATCH(H$1, EneR!$6:$6, 0), FALSE), 0 ) + IFERROR( VLOOKUP($A10, INDIRECT("FebR!$A$6:$ZZ$1048576"), MATCH(H$1, FebR!$6:$6, 0), FALSE), 0 ) + IFERROR( VLOOKUP($A10, INDIRECT("MarR!$A$6:$ZZ$1048576"), MATCH(H$1, MarR!$6:$6, 0), FALSE), 0 ) + IFERROR( VLOOKUP($A10, INDIRECT("AbrR!$A$6:$ZZ$1048576"), MATCH(H$1, AbrR!$6:$6, 0), FALSE), 0 ) + IFERROR( VLOOKUP($A10, INDIRECT("MayR!$A$6:$ZZ$1048576"), MATCH(H$1, MayR!$6:$6, 0), FALSE), 0 ) + IFERROR( VLOOKUP($A10, INDIRECT("JunR!$A$6:$ZZ$1048576"), MATCH(H$1, JunR!$6:$6, 0), FALSE), 0 ) + IFERROR( VLOOKUP($A10, INDIRECT("JulR!$A$6:$ZZ$1048576"), MATCH(H$1, JulR!$6:$6, 0), FALSE), 0 ) + IFERROR( VLOOKUP($A10, INDIRECT("AgoR!$A$6:$ZZ$1048576"), MATCH(H$1, AgoR!$6:$6, 0), FALSE), 0 ) + IFERROR( VLOOKUP($A10, INDIRECT("SepR!$A$6:$ZZ$1048576"), MATCH(H$1, SepR!$6:$6, 0), FALSE), 0 ) + IFERROR( VLOOKUP($A10, INDIRECT("OctR!$A$6:$ZZ$1048576"), MATCH(H$1, OctR!$6:$6, 0), FALSE), 0 ) + IFERROR( VLOOKUP($A10, INDIRECT("NovR!$A$6:$ZZ$1048576"), MATCH(H$1, NovR!$6:$6, 0), FALSE), 0 ) + IFERROR( VLOOKUP($A10, INDIRECT("DicR!$A$6:$ZZ$1048576"), MATCH(H$1, DicR!$6:$6, 0), FALSE), 0 ) )} -> 0 | I10: {=SUM( IFERROR( VLOOKUP($A10, INDIRECT("EneR!$A$6:$ZZ$1048576"), MATCH(I$1, EneR!$6:$6, 0), FALSE), 0 ) + IFERROR( VLOOKUP($A10, INDIRECT("FebR!$A$6:$ZZ$1048576"), MATCH(I$1, FebR!$6:$6, 0), FALSE), 0 ) + IFERROR( VLOOKUP($A10, INDIRECT("MarR!$A$6:$ZZ$1048576"), MATCH(I$1, MarR!$6:$6, 0), FALSE), 0 ) + IFERROR( VLOOKUP($A10, INDIRECT("AbrR!$A$6:$ZZ$1048576"), MATCH(I$1, AbrR!$6:$6, 0), FALSE), 0 ) + IFERROR( VLOOKUP($A10, INDIRECT("MayR!$A$6:$ZZ$1048576"), MATCH(I$1, MayR!$6:$6, 0), FALSE), 0 ) + IFERROR( VLOOKUP($A10, INDIRECT("JunR!$A$6:$ZZ$1048576"), MATCH(I$1, JunR!$6:$6, 0), FALSE), 0 ) + IFERROR( VLOOKUP($A10, INDIRECT("JulR!$A$6:$ZZ$1048576"), MATCH(I$1, JulR!$6:$6, 0), FALSE), 0 ) + IFERROR( VLOOKUP($A10, INDIRECT("AgoR!$A$6:$ZZ$1048576"), MATCH(I$1, AgoR!$6:$6, 0), FALSE), 0 ) + IFERROR( VLOOKUP($A10, INDIRECT("SepR!$A$6:$ZZ$1048576"), MATCH(I$1, SepR!$6:$6, 0), FALSE), 0 ) + IFERROR( VLOOKUP($A10, INDIRECT("OctR!$A$6:$ZZ$1048576"), MATCH(I$1, OctR!$6:$6, 0), FALSE), 0 ) + IFERROR( VLOOKUP($A10, INDIRECT("NovR!$A$6:$ZZ$1048576"), MATCH(I$1, NovR!$6:$6, 0), FALSE), 0 ) + IFERROR( VLOOKUP($A10, INDIRECT("DicR!$A$6:$ZZ$1048576"), MATCH(I$1, DicR!$6:$6, 0), FALSE), 0 ) )} -> 0 | J10: {=SUM( IFERROR( VLOOKUP($A10, INDIRECT("EneR!$A$6:$ZZ$1048576"), MATCH(J$1, EneR!$6:$6, 0), FALSE), 0 ) + IFERROR( VLOOKUP($A10, INDIRECT("FebR!$A$6:$ZZ$1048576"), MATCH(J$1, FebR!$6:$6, 0), FALSE), 0 ) + IFERROR( VLOOKUP($A10, INDIRECT("MarR!$A$6:$ZZ$1048576"), MATCH(J$1, MarR!$6:$6, 0), FALSE), 0 ) + IFERROR( VLOOKUP($A10, INDIRECT("AbrR!$A$6:$ZZ$1048576"), MATCH(J$1, AbrR!$6:$6, 0), FALSE), 0 ) + IFERROR( VLOOKUP($A10, INDIRECT("MayR!$A$6:$ZZ$1048576"), MATCH(J$1, MayR!$6:$6, 0), FALSE), 0 ) + IFERROR( VLOOKUP($A10, INDIRECT("JunR!$A$6:$ZZ$1048576"), MATCH(J$1, JunR!$6:$6, 0), FALSE), 0 ) + IFERROR( VLOOKUP($A10, INDIRECT("JulR!$A$6:$ZZ$1048576"), MATCH(J$1, JulR!$6:$6, 0), FALSE), 0 ) + IFERROR( VLOOKUP($A10, INDIRECT("AgoR!$A$6:$ZZ$1048576"), MATCH(J$1, AgoR!$6:$6, 0), FALSE), 0 ) + IFERROR( VLOOKUP($A10, INDIRECT("SepR!$A$6:$ZZ$1048576"), MATCH(J$1, SepR!$6:$6, 0), FALSE), 0 ) + IFERROR( VLOOKUP($A10, INDIRECT("OctR!$A$6:$ZZ$1048576"), MATCH(J$1, OctR!$6:$6, 0), FALSE), 0 ) + IFERROR( VLOOKUP($A10, INDIRECT("NovR!$A$6:$ZZ$1048576"), MATCH(J$1, NovR!$6:$6, 0), FALSE), 0 ) + IFERROR( VLOOKUP($A10, INDIRECT("DicR!$A$6:$ZZ$1048576"), MATCH(J$1, DicR!$6:$6, 0), FALSE), 0 ) )} -> 0 | K10: {=SUM( IFERROR( VLOOKUP($A10, INDIRECT("EneR!$A$6:$ZZ$1048576"), MATCH(K$1, EneR!$6:$6, 0), FALSE), 0 ) + IFERROR( VLOOKUP($A10, INDIRECT("FebR!$A$6:$ZZ$1048576"), MATCH(K$1, FebR!$6:$6, 0), FALSE), 0 ) + IFERROR( VLOOKUP($A10, INDIRECT("MarR!$A$6:$ZZ$1048576"), MATCH(K$1, MarR!$6:$6, 0), FALSE), 0 ) + IFERROR( VLOOKUP($A10, INDIRECT("AbrR!$A$6:$ZZ$1048576"), MATCH(K$1, AbrR!$6:$6, 0), FALSE), 0 ) + IFERROR( VLOOKUP($A10, INDIRECT("MayR!$A$6:$ZZ$1048576"), MATCH(K$1, MayR!$6:$6, 0), FALSE), 0 ) + IFERROR( VLOOKUP($A10, INDIRECT("JunR!$A$6:$ZZ$1048576"), MATCH(K$1, JunR!$6:$6, 0), FALSE), 0 ) + IFERROR( VLOOKUP($A10, INDIRECT("JulR!$A$6:$ZZ$1048576"), MATCH(K$1, JulR!$6:$6, 0), FALSE), 0 ) + IFERROR( VLOOKUP($A10, INDIRECT("AgoR!$A$6:$ZZ$1048576"), MATCH(K$1, AgoR!$6:$6, 0), FALSE), 0 ) + IFERROR( VLOOKUP($A10, INDIRECT("SepR!$A$6:$ZZ$1048576"), MATCH(K$1, SepR!$6:$6, 0), FALSE), 0 ) + IFERROR( VLOOKUP($A10, INDIRECT("OctR!$A$6:$ZZ$1048576"), MATCH(K$1, OctR!$6:$6, 0), FALSE), 0 ) + IFERROR( VLOOKUP($A10, INDIRECT("NovR!$A$6:$ZZ$1048576"), MATCH(K$1, NovR!$6:$6, 0), FALSE), 0 ) + IFERROR( VLOOKUP($A10, INDIRECT("DicR!$A$6:$ZZ$1048576"), MATCH(K$1, DicR!$6:$6, 0), FALSE), 0 ) )} -> 0 | ... AY10: {=SUM( IFERROR( VLOOKUP($A10, INDIRECT("EneR!$A$6:$ZZ$1048576"), MATCH(AY$1, EneR!$6:$6, 0), FALSE), 0 ) + IFERROR( VLOOKUP($A10, INDIRECT("FebR!$A$6:$ZZ$1048576"), MATCH(AY$1, FebR!$6:$6, 0), FALSE), 0 ) + IFERROR( VLOOKUP($A10, INDIRECT("MarR!$A$6:$ZZ$1048576"), MATCH(AY$1, MarR!$6:$6, 0), FALSE), 0 ) + IFERROR( VLOOKUP($A10, INDIRECT("AbrR!$A$6:$ZZ$1048576"), MATCH(AY$1, AbrR!$6:$6, 0), FALSE), 0 ) + IFERROR( VLOOKUP($A10, INDIRECT("MayR!$A$6:$ZZ$1048576"), MATCH(AY$1, MayR!$6:$6, 0), FALSE), 0 ) + IFERROR( VLOOKUP($A10, INDIRECT("JunR!$A$6:$ZZ$1048576"), MATCH(AY$1, JunR!$6:$6, 0), FALSE), 0 ) + IFERROR( VLOOKUP($A10, INDIRECT("JulR!$A$6:$ZZ$1048576"), MATCH(AY$1, JulR!$6:$6, 0), FALSE), 0 ) + IFERROR( VLOOKUP($A10, INDIRECT("AgoR!$A$6:$ZZ$1048576"), MATCH(AY$1, AgoR!$6:$6, 0), FALSE), 0 ) + IFERROR( VLOOKUP($A10, INDIRECT("SepR!$A$6:$ZZ$1048576"), MATCH(AY$1, SepR!$6:$6, 0), FALSE), 0 ) + IFERROR( VLOOKUP($A10, INDIRECT("OctR!$A$6:$ZZ$1048576"), MATCH(AY$1, OctR!$6:$6, 0), FALSE), 0 ) + IFERROR( VLOOKUP($A10, INDIRECT("NovR!$A$6:$ZZ$1048576"), MATCH(AY$1, NovR!$6:$6, 0), FALSE), 0 ) + IFERROR( VLOOKUP($A10, INDIRECT("DicR!$A$6:$ZZ$1048576"), MATCH(AY$1, DicR!$6:$6, 0), FALSE), 0 ) )} -> 0
A11: =Menus!R3 | B11: =IFERROR(SUM(D11:AZ11),"") -> 0 | C11: =IFERROR(INDEX($D$1:$AQ128, MATCH($A11, $A$1:$A128, 0), MATCH(C$1, $D$1:AZ$1, 0)), "") | D11: {=SUM( IFERROR( VLOOKUP($A11, INDIRECT("EneR!$A$6:$ZZ$1048576"), MATCH(D$1, EneR!$6:$6, 0), FALSE), 0 ) + IFERROR( VLOOKUP($A11, INDIRECT("FebR!$A$6:$ZZ$1048576"), MATCH(D$1, FebR!$6:$6, 0), FALSE), 0 ) + IFERROR( VLOOKUP($A11, INDIRECT("MarR!$A$6:$ZZ$1048576"), MATCH(D$1, MarR!$6:$6, 0), FALSE), 0 ) + IFERROR( VLOOKUP($A11, INDIRECT("AbrR!$A$6:$ZZ$1048576"), MATCH(D$1, AbrR!$6:$6, 0), FALSE), 0 ) + IFERROR( VLOOKUP($A11, INDIRECT("MayR!$A$6:$ZZ$1048576"), MATCH(D$1, MayR!$6:$6, 0), FALSE), 0 ) + IFERROR( VLOOKUP($A11, INDIRECT("JunR!$A$6:$ZZ$1048576"), MATCH(D$1, JunR!$6:$6, 0), FALSE), 0 ) + IFERROR( VLOOKUP($A11, INDIRECT("JulR!$A$6:$ZZ$1048576"), MATCH(D$1, JulR!$6:$6, 0), FALSE), 0 ) + IFERROR( VLOOKUP($A11, INDIRECT("AgoR!$A$6:$ZZ$1048576"), MATCH(D$1, AgoR!$6:$6, 0), FALSE), 0 ) + IFERROR( VLOOKUP($A11, INDIRECT("SepR!$A$6:$ZZ$1048576"), MATCH(D$1, SepR!$6:$6, 0), FALSE), 0 ) + IFERROR( VLOOKUP($A11, INDIRECT("OctR!$A$6:$ZZ$1048576"), MATCH(D$1, OctR!$6:$6, 0), FALSE), 0 ) + IFERROR( VLOOKUP($A11, INDIRECT("NovR!$A$6:$ZZ$1048576"), MATCH(D$1, NovR!$6:$6, 0), FALSE), 0 ) + IFERROR( VLOOKUP($A11, INDIRECT("DicR!$A$6:$ZZ$1048576"), MATCH(D$1, DicR!$6:$6, 0), FALSE), 0 ) )} -> 0 | E11: {=SUM( IFERROR( VLOOKUP($A11, INDIRECT("EneR!$A$6:$ZZ$1048576"), MATCH(E$1, EneR!$6:$6, 0), FALSE), 0 ) + IFERROR( VLOOKUP($A11, INDIRECT("FebR!$A$6:$ZZ$1048576"), MATCH(E$1, FebR!$6:$6, 0), FALSE), 0 ) + IFERROR( VLOOKUP($A11, INDIRECT("MarR!$A$6:$ZZ$1048576"), MATCH(E$1, MarR!$6:$6, 0), FALSE), 0 ) + IFERROR( VLOOKUP($A11, INDIRECT("AbrR!$A$6:$ZZ$1048576"), MATCH(E$1, AbrR!$6:$6, 0), FALSE), 0 ) + IFERROR( VLOOKUP($A11, INDIRECT("MayR!$A$6:$ZZ$1048576"), MATCH(E$1, MayR!$6:$6, 0), FALSE), 0 ) + IFERROR( VLOOKUP($A11, INDIRECT("JunR!$A$6:$ZZ$1048576"), MATCH(E$1, JunR!$6:$6, 0), FALSE), 0 ) + IFERROR( VLOOKUP($A11, INDIRECT("JulR!$A$6:$ZZ$1048576"), MATCH(E$1, JulR!$6:$6, 0), FALSE), 0 ) + IFERROR( VLOOKUP($A11, INDIRECT("AgoR!$A$6:$ZZ$1048576"), MATCH(E$1, AgoR!$6:$6, 0), FALSE), 0 ) + IFERROR( VLOOKUP($A11, INDIRECT("SepR!$A$6:$ZZ$1048576"), MATCH(E$1, SepR!$6:$6, 0), FALSE), 0 ) + IFERROR( VLOOKUP($A11, INDIRECT("OctR!$A$6:$ZZ$1048576"), MATCH(E$1, OctR!$6:$6, 0), FALSE), 0 ) + IFERROR( VLOOKUP($A11, INDIRECT("NovR!$A$6:$ZZ$1048576"), MATCH(E$1, NovR!$6:$6, 0), FALSE), 0 ) + IFERROR( VLOOKUP($A11, INDIRECT("DicR!$A$6:$ZZ$1048576"), MATCH(E$1, DicR!$6:$6, 0), FALSE), 0 ) )} -> 0 | F11: {=SUM( IFERROR( VLOOKUP($A11, INDIRECT("EneR!$A$6:$ZZ$1048576"), MATCH(F$1, EneR!$6:$6, 0), FALSE), 0 ) + IFERROR( VLOOKUP($A11, INDIRECT("FebR!$A$6:$ZZ$1048576"), MATCH(F$1, FebR!$6:$6, 0), FALSE), 0 ) + IFERROR( VLOOKUP($A11, INDIRECT("MarR!$A$6:$ZZ$1048576"), MATCH(F$1, MarR!$6:$6, 0), FALSE), 0 ) + IFERROR( VLOOKUP($A11, INDIRECT("AbrR!$A$6:$ZZ$1048576"), MATCH(F$1, AbrR!$6:$6, 0), FALSE), 0 ) + IFERROR( VLOOKUP($A11, INDIRECT("MayR!$A$6:$ZZ$1048576"), MATCH(F$1, MayR!$6:$6, 0), FALSE), 0 ) + IFERROR( VLOOKUP($A11, INDIRECT("JunR!$A$6:$ZZ$1048576"), MATCH(F$1, JunR!$6:$6, 0), FALSE), 0 ) + IFERROR( VLOOKUP($A11, INDIRECT("JulR!$A$6:$ZZ$1048576"), MATCH(F$1, JulR!$6:$6, 0), FALSE), 0 ) + IFERROR( VLOOKUP($A11, INDIRECT("AgoR!$A$6:$ZZ$1048576"), MATCH(F$1, AgoR!$6:$6, 0), FALSE), 0 ) + IFERROR( VLOOKUP($A11, INDIRECT("SepR!$A$6:$ZZ$1048576"), MATCH(F$1, SepR!$6:$6, 0), FALSE), 0 ) + IFERROR( VLOOKUP($A11, INDIRECT("OctR!$A$6:$ZZ$1048576"), MATCH(F$1, OctR!$6:$6, 0), FALSE), 0 ) + IFERROR( VLOOKUP($A11, INDIRECT("NovR!$A$6:$ZZ$1048576"), MATCH(F$1, NovR!$6:$6, 0), FALSE), 0 ) + IFERROR( VLOOKUP($A11, INDIRECT("DicR!$A$6:$ZZ$1048576"), MATCH(F$1, DicR!$6:$6, 0), FALSE), 0 ) )} -> 0 | G11: {=SUM( IFERROR( VLOOKUP($A11, INDIRECT("EneR!$A$6:$ZZ$1048576"), MATCH(G$1, EneR!$6:$6, 0), FALSE), 0 ) + IFERROR( VLOOKUP($A11, INDIRECT("FebR!$A$6:$ZZ$1048576"), MATCH(G$1, FebR!$6:$6, 0), FALSE), 0 ) + IFERROR( VLOOKUP($A11, INDIRECT("MarR!$A$6:$ZZ$1048576"), MATCH(G$1, MarR!$6:$6, 0), FALSE), 0 ) + IFERROR( VLOOKUP($A11, INDIRECT("AbrR!$A$6:$ZZ$1048576"), MATCH(G$1, AbrR!$6:$6, 0), FALSE), 0 ) + IFERROR( VLOOKUP($A11, INDIRECT("MayR!$A$6:$ZZ$1048576"), MATCH(G$1, MayR!$6:$6, 0), FALSE), 0 ) + IFERROR( VLOOKUP($A11, INDIRECT("JunR!$A$6:$ZZ$1048576"), MATCH(G$1, JunR!$6:$6, 0), FALSE), 0 ) + IFERROR( VLOOKUP($A11, INDIRECT("JulR!$A$6:$ZZ$1048576"), MATCH(G$1, JulR!$6:$6, 0), FALSE), 0 ) + IFERROR( VLOOKUP($A11, INDIRECT("AgoR!$A$6:$ZZ$1048576"), MATCH(G$1, AgoR!$6:$6, 0), FALSE), 0 ) + IFERROR( VLOOKUP($A11, INDIRECT("SepR!$A$6:$ZZ$1048576"), MATCH(G$1, SepR!$6:$6, 0), FALSE), 0 ) + IFERROR( VLOOKUP($A11, INDIRECT("OctR!$A$6:$ZZ$1048576"), MATCH(G$1, OctR!$6:$6, 0), FALSE), 0 ) + IFERROR( VLOOKUP($A11, INDIRECT("NovR!$A$6:$ZZ$1048576"), MATCH(G$1, NovR!$6:$6, 0), FALSE), 0 ) + IFERROR( VLOOKUP($A11, INDIRECT("DicR!$A$6:$ZZ$1048576"), MATCH(G$1, DicR!$6:$6, 0), FALSE), 0 ) )} -> 0 | H11: {=SUM( IFERROR( VLOOKUP($A11, INDIRECT("EneR!$A$6:$ZZ$1048576"), MATCH(H$1, EneR!$6:$6, 0), FALSE), 0 ) + IFERROR( VLOOKUP($A11, INDIRECT("FebR!$A$6:$ZZ$1048576"), MATCH(H$1, FebR!$6:$6, 0), FALSE), 0 ) + IFERROR( VLOOKUP($A11, INDIRECT("MarR!$A$6:$ZZ$1048576"), MATCH(H$1, MarR!$6:$6, 0), FALSE), 0 ) + IFERROR( VLOOKUP($A11, INDIRECT("AbrR!$A$6:$ZZ$1048576"), MATCH(H$1, AbrR!$6:$6, 0), FALSE), 0 ) + IFERROR( VLOOKUP($A11, INDIRECT("MayR!$A$6:$ZZ$1048576"), MATCH(H$1, MayR!$6:$6, 0), FALSE), 0 ) + IFERROR( VLOOKUP($A11, INDIRECT("JunR!$A$6:$ZZ$1048576"), MATCH(H$1, JunR!$6:$6, 0), FALSE), 0 ) + IFERROR( VLOOKUP($A11, INDIRECT("JulR!$A$6:$ZZ$1048576"), MATCH(H$1, JulR!$6:$6, 0), FALSE), 0 ) + IFERROR( VLOOKUP($A11, INDIRECT("AgoR!$A$6:$ZZ$1048576"), MATCH(H$1, AgoR!$6:$6, 0), FALSE), 0 ) + IFERROR( VLOOKUP($A11, INDIRECT("SepR!$A$6:$ZZ$1048576"), MATCH(H$1, SepR!$6:$6, 0), FALSE), 0 ) + IFERROR( VLOOKUP($A11, INDIRECT("OctR!$A$6:$ZZ$1048576"), MATCH(H$1, OctR!$6:$6, 0), FALSE), 0 ) + IFERROR( VLOOKUP($A11, INDIRECT("NovR!$A$6:$ZZ$1048576"), MATCH(H$1, NovR!$6:$6, 0), FALSE), 0 ) + IFERROR( VLOOKUP($A11, INDIRECT("DicR!$A$6:$ZZ$1048576"), MATCH(H$1, DicR!$6:$6, 0), FALSE), 0 ) )} -> 0 | I11: {=SUM( IFERROR( VLOOKUP($A11, INDIRECT("EneR!$A$6:$ZZ$1048576"), MATCH(I$1, EneR!$6:$6, 0), FALSE), 0 ) + IFERROR( VLOOKUP($A11, INDIRECT("FebR!$A$6:$ZZ$1048576"), MATCH(I$1, FebR!$6:$6, 0), FALSE), 0 ) + IFERROR( VLOOKUP($A11, INDIRECT("MarR!$A$6:$ZZ$1048576"), MATCH(I$1, MarR!$6:$6, 0), FALSE), 0 ) + IFERROR( VLOOKUP($A11, INDIRECT("AbrR!$A$6:$ZZ$1048576"), MATCH(I$1, AbrR!$6:$6, 0), FALSE), 0 ) + IFERROR( VLOOKUP($A11, INDIRECT("MayR!$A$6:$ZZ$1048576"), MATCH(I$1, MayR!$6:$6, 0), FALSE), 0 ) + IFERROR( VLOOKUP($A11, INDIRECT("JunR!$A$6:$ZZ$1048576"), MATCH(I$1, JunR!$6:$6, 0), FALSE), 0 ) + IFERROR( VLOOKUP($A11, INDIRECT("JulR!$A$6:$ZZ$1048576"), MATCH(I$1, JulR!$6:$6, 0), FALSE), 0 ) + IFERROR( VLOOKUP($A11, INDIRECT("AgoR!$A$6:$ZZ$1048576"), MATCH(I$1, AgoR!$6:$6, 0), FALSE), 0 ) + IFERROR( VLOOKUP($A11, INDIRECT("SepR!$A$6:$ZZ$1048576"), MATCH(I$1, SepR!$6:$6, 0), FALSE), 0 ) + IFERROR( VLOOKUP($A11, INDIRECT("OctR!$A$6:$ZZ$1048576"), MATCH(I$1, OctR!$6:$6, 0), FALSE), 0 ) + IFERROR( VLOOKUP($A11, INDIRECT("NovR!$A$6:$ZZ$1048576"), MATCH(I$1, NovR!$6:$6, 0), FALSE), 0 ) + IFERROR( VLOOKUP($A11, INDIRECT("DicR!$A$6:$ZZ$1048576"), MATCH(I$1, DicR!$6:$6, 0), FALSE), 0 ) )} -> 0 | J11: {=SUM( IFERROR( VLOOKUP($A11, INDIRECT("EneR!$A$6:$ZZ$1048576"), MATCH(J$1, EneR!$6:$6, 0), FALSE), 0 ) + IFERROR( VLOOKUP($A11, INDIRECT("FebR!$A$6:$ZZ$1048576"), MATCH(J$1, FebR!$6:$6, 0), FALSE), 0 ) + IFERROR( VLOOKUP($A11, INDIRECT("MarR!$A$6:$ZZ$1048576"), MATCH(J$1, MarR!$6:$6, 0), FALSE), 0 ) + IFERROR( VLOOKUP($A11, INDIRECT("AbrR!$A$6:$ZZ$1048576"), MATCH(J$1, AbrR!$6:$6, 0), FALSE), 0 ) + IFERROR( VLOOKUP($A11, INDIRECT("MayR!$A$6:$ZZ$1048576"), MATCH(J$1, MayR!$6:$6, 0), FALSE), 0 ) + IFERROR( VLOOKUP($A11, INDIRECT("JunR!$A$6:$ZZ$1048576"), MATCH(J$1, JunR!$6:$6, 0), FALSE), 0 ) + IFERROR( VLOOKUP($A11, INDIRECT("JulR!$A$6:$ZZ$1048576"), MATCH(J$1, JulR!$6:$6, 0), FALSE), 0 ) + IFERROR( VLOOKUP($A11, INDIRECT("AgoR!$A$6:$ZZ$1048576"), MATCH(J$1, AgoR!$6:$6, 0), FALSE), 0 ) + IFERROR( VLOOKUP($A11, INDIRECT("SepR!$A$6:$ZZ$1048576"), MATCH(J$1, SepR!$6:$6, 0), FALSE), 0 ) + IFERROR( VLOOKUP($A11, INDIRECT("OctR!$A$6:$ZZ$1048576"), MATCH(J$1, OctR!$6:$6, 0), FALSE), 0 ) + IFERROR( VLOOKUP($A11, INDIRECT("NovR!$A$6:$ZZ$1048576"), MATCH(J$1, NovR!$6:$6, 0), FALSE), 0 ) + IFERROR( VLOOKUP($A11, INDIRECT("DicR!$A$6:$ZZ$1048576"), MATCH(J$1, DicR!$6:$6, 0), FALSE), 0 ) )} -> 0 | K11: {=SUM( IFERROR( VLOOKUP($A11, INDIRECT("EneR!$A$6:$ZZ$1048576"), MATCH(K$1, EneR!$6:$6, 0), FALSE), 0 ) + IFERROR( VLOOKUP($A11, INDIRECT("FebR!$A$6:$ZZ$1048576"), MATCH(K$1, FebR!$6:$6, 0), FALSE), 0 ) + IFERROR( VLOOKUP($A11, INDIRECT("MarR!$A$6:$ZZ$1048576"), MATCH(K$1, MarR!$6:$6, 0), FALSE), 0 ) + IFERROR( VLOOKUP($A11, INDIRECT("AbrR!$A$6:$ZZ$1048576"), MATCH(K$1, AbrR!$6:$6, 0), FALSE), 0 ) + IFERROR( VLOOKUP($A11, INDIRECT("MayR!$A$6:$ZZ$1048576"), MATCH(K$1, MayR!$6:$6, 0), FALSE), 0 ) + IFERROR( VLOOKUP($A11, INDIRECT("JunR!$A$6:$ZZ$1048576"), MATCH(K$1, JunR!$6:$6, 0), FALSE), 0 ) + IFERROR( VLOOKUP($A11, INDIRECT("JulR!$A$6:$ZZ$1048576"), MATCH(K$1, JulR!$6:$6, 0), FALSE), 0 ) + IFERROR( VLOOKUP($A11, INDIRECT("AgoR!$A$6:$ZZ$1048576"), MATCH(K$1, AgoR!$6:$6, 0), FALSE), 0 ) + IFERROR( VLOOKUP($A11, INDIRECT("SepR!$A$6:$ZZ$1048576"), MATCH(K$1, SepR!$6:$6, 0), FALSE), 0 ) + IFERROR( VLOOKUP($A11, INDIRECT("OctR!$A$6:$ZZ$1048576"), MATCH(K$1, OctR!$6:$6, 0), FALSE), 0 ) + IFERROR( VLOOKUP($A11, INDIRECT("NovR!$A$6:$ZZ$1048576"), MATCH(K$1, NovR!$6:$6, 0), FALSE), 0 ) + IFERROR( VLOOKUP($A11, INDIRECT("DicR!$A$6:$ZZ$1048576"), MATCH(K$1, DicR!$6:$6, 0), FALSE), 0 ) )} -> 0 | ... AY11: {=SUM( IFERROR( VLOOKUP($A11, INDIRECT("EneR!$A$6:$ZZ$1048576"), MATCH(AY$1, EneR!$6:$6, 0), FALSE), 0 ) + IFERROR( VLOOKUP($A11, INDIRECT("FebR!$A$6:$ZZ$1048576"), MATCH(AY$1, FebR!$6:$6, 0), FALSE), 0 ) + IFERROR( VLOOKUP($A11, INDIRECT("MarR!$A$6:$ZZ$1048576"), MATCH(AY$1, MarR!$6:$6, 0), FALSE), 0 ) + IFERROR( VLOOKUP($A11, INDIRECT("AbrR!$A$6:$ZZ$1048576"), MATCH(AY$1, AbrR!$6:$6, 0), FALSE), 0 ) + IFERROR( VLOOKUP($A11, INDIRECT("MayR!$A$6:$ZZ$1048576"), MATCH(AY$1, MayR!$6:$6, 0), FALSE), 0 ) + IFERROR( VLOOKUP($A11, INDIRECT("JunR!$A$6:$ZZ$1048576"), MATCH(AY$1, JunR!$6:$6, 0), FALSE), 0 ) + IFERROR( VLOOKUP($A11, INDIRECT("JulR!$A$6:$ZZ$1048576"), MATCH(AY$1, JulR!$6:$6, 0), FALSE), 0 ) + IFERROR( VLOOKUP($A11, INDIRECT("AgoR!$A$6:$ZZ$1048576"), MATCH(AY$1, AgoR!$6:$6, 0), FALSE), 0 ) + IFERROR( VLOOKUP($A11, INDIRECT("SepR!$A$6:$ZZ$1048576"), MATCH(AY$1, SepR!$6:$6, 0), FALSE), 0 ) + IFERROR( VLOOKUP($A11, INDIRECT("OctR!$A$6:$ZZ$1048576"), MATCH(AY$1, OctR!$6:$6, 0), FALSE), 0 ) + IFERROR( VLOOKUP($A11, INDIRECT("NovR!$A$6:$ZZ$1048576"), MATCH(AY$1, NovR!$6:$6, 0), FALSE), 0 ) + IFERROR( VLOOKUP($A11, INDIRECT("DicR!$A$6:$ZZ$1048576"), MATCH(AY$1, DicR!$6:$6, 0), FALSE), 0 ) )} -> 0
A12: =Menus!R4 | B12: =IFERROR(SUM(D12:AZ12),"") -> 0 | C12: =IFERROR(INDEX($D$1:$AQ129, MATCH($A12, $A$1:$A129, 0), MATCH(C$1, $D$1:AZ$1, 0)), "") | D12: {=SUM( IFERROR( VLOOKUP($A12, INDIRECT("EneR!$A$6:$ZZ$1048576"), MATCH(D$1, EneR!$6:$6, 0), FALSE), 0 ) + IFERROR( VLOOKUP($A12, INDIRECT("FebR!$A$6:$ZZ$1048576"), MATCH(D$1, FebR!$6:$6, 0), FALSE), 0 ) + IFERROR( VLOOKUP($A12, INDIRECT("MarR!$A$6:$ZZ$1048576"), MATCH(D$1, MarR!$6:$6, 0), FALSE), 0 ) + IFERROR( VLOOKUP($A12, INDIRECT("AbrR!$A$6:$ZZ$1048576"), MATCH(D$1, AbrR!$6:$6, 0), FALSE), 0 ) + IFERROR( VLOOKUP($A12, INDIRECT("MayR!$A$6:$ZZ$1048576"), MATCH(D$1, MayR!$6:$6, 0), FALSE), 0 ) + IFERROR( VLOOKUP($A12, INDIRECT("JunR!$A$6:$ZZ$1048576"), MATCH(D$1, JunR!$6:$6, 0), FALSE), 0 ) + IFERROR( VLOOKUP($A12, INDIRECT("JulR!$A$6:$ZZ$1048576"), MATCH(D$1, JulR!$6:$6, 0), FALSE), 0 ) + IFERROR( VLOOKUP($A12, INDIRECT("AgoR!$A$6:$ZZ$1048576"), MATCH(D$1, AgoR!$6:$6, 0), FALSE), 0 ) + IFERROR( VLOOKUP($A12, INDIRECT("SepR!$A$6:$ZZ$1048576"), MATCH(D$1, SepR!$6:$6, 0), FALSE), 0 ) + IFERROR( VLOOKUP($A12, INDIRECT("OctR!$A$6:$ZZ$1048576"), MATCH(D$1, OctR!$6:$6, 0), FALSE), 0 ) + IFERROR( VLOOKUP($A12, INDIRECT("NovR!$A$6:$ZZ$1048576"), MATCH(D$1, NovR!$6:$6, 0), FALSE), 0 ) + IFERROR( VLOOKUP($A12, INDIRECT("DicR!$A$6:$ZZ$1048576"), MATCH(D$1, DicR!$6:$6, 0), FALSE), 0 ) )} -> 0 | E12: {=SUM( IFERROR( VLOOKUP($A12, INDIRECT("EneR!$A$6:$ZZ$1048576"), MATCH(E$1, EneR!$6:$6, 0), FALSE), 0 ) + IFERROR( VLOOKUP($A12, INDIRECT("FebR!$A$6:$ZZ$1048576"), MATCH(E$1, FebR!$6:$6, 0), FALSE), 0 ) + IFERROR( VLOOKUP($A12, INDIRECT("MarR!$A$6:$ZZ$1048576"), MATCH(E$1, MarR!$6:$6, 0), FALSE), 0 ) + IFERROR( VLOOKUP($A12, INDIRECT("AbrR!$A$6:$ZZ$1048576"), MATCH(E$1, AbrR!$6:$6, 0), FALSE), 0 ) + IFERROR( VLOOKUP($A12, INDIRECT("MayR!$A$6:$ZZ$1048576"), MATCH(E$1, MayR!$6:$6, 0), FALSE), 0 ) + IFERROR( VLOOKUP($A12, INDIRECT("JunR!$A$6:$ZZ$1048576"), MATCH(E$1, JunR!$6:$6, 0), FALSE), 0 ) + IFERROR( VLOOKUP($A12, INDIRECT("JulR!$A$6:$ZZ$1048576"), MATCH(E$1, JulR!$6:$6, 0), FALSE), 0 ) + IFERROR( VLOOKUP($A12, INDIRECT("AgoR!$A$6:$ZZ$1048576"), MATCH(E$1, AgoR!$6:$6, 0), FALSE), 0 ) + IFERROR( VLOOKUP($A12, INDIRECT("SepR!$A$6:$ZZ$1048576"), MATCH(E$1, SepR!$6:$6, 0), FALSE), 0 ) + IFERROR( VLOOKUP($A12, INDIRECT("OctR!$A$6:$ZZ$1048576"), MATCH(E$1, OctR!$6:$6, 0), FALSE), 0 ) + IFERROR( VLOOKUP($A12, INDIRECT("NovR!$A$6:$ZZ$1048576"), MATCH(E$1, NovR!$6:$6, 0), FALSE), 0 ) + IFERROR( VLOOKUP($A12, INDIRECT("DicR!$A$6:$ZZ$1048576"), MATCH(E$1, DicR!$6:$6, 0), FALSE), 0 ) )} -> 0 | F12: {=SUM( IFERROR( VLOOKUP($A12, INDIRECT("EneR!$A$6:$ZZ$1048576"), MATCH(F$1, EneR!$6:$6, 0), FALSE), 0 ) + IFERROR( VLOOKUP($A12, INDIRECT("FebR!$A$6:$ZZ$1048576"), MATCH(F$1, FebR!$6:$6, 0), FALSE), 0 ) + IFERROR( VLOOKUP($A12, INDIRECT("MarR!$A$6:$ZZ$1048576"), MATCH(F$1, MarR!$6:$6, 0), FALSE), 0 ) + IFERROR( VLOOKUP($A12, INDIRECT("AbrR!$A$6:$ZZ$1048576"), MATCH(F$1, AbrR!$6:$6, 0), FALSE), 0 ) + IFERROR( VLOOKUP($A12, INDIRECT("MayR!$A$6:$ZZ$1048576"), MATCH(F$1, MayR!$6:$6, 0), FALSE), 0 ) + IFERROR( VLOOKUP($A12, INDIRECT("JunR!$A$6:$ZZ$1048576"), MATCH(F$1, JunR!$6:$6, 0), FALSE), 0 ) + IFERROR( VLOOKUP($A12, INDIRECT("JulR!$A$6:$ZZ$1048576"), MATCH(F$1, JulR!$6:$6, 0), FALSE), 0 ) + IFERROR( VLOOKUP($A12, INDIRECT("AgoR!$A$6:$ZZ$1048576"), MATCH(F$1, AgoR!$6:$6, 0), FALSE), 0 ) + IFERROR( VLOOKUP($A12, INDIRECT("SepR!$A$6:$ZZ$1048576"), MATCH(F$1, SepR!$6:$6, 0), FALSE), 0 ) + IFERROR( VLOOKUP($A12, INDIRECT("OctR!$A$6:$ZZ$1048576"), MATCH(F$1, OctR!$6:$6, 0), FALSE), 0 ) + IFERROR( VLOOKUP($A12, INDIRECT("NovR!$A$6:$ZZ$1048576"), MATCH(F$1, NovR!$6:$6, 0), FALSE), 0 ) + IFERROR( VLOOKUP($A12, INDIRECT("DicR!$A$6:$ZZ$1048576"), MATCH(F$1, DicR!$6:$6, 0), FALSE), 0 ) )} -> 0 | G12: {=SUM( IFERROR( VLOOKUP($A12, INDIRECT("EneR!$A$6:$ZZ$1048576"), MATCH(G$1, EneR!$6:$6, 0), FALSE), 0 ) + IFERROR( VLOOKUP($A12, INDIRECT("FebR!$A$6:$ZZ$1048576"), MATCH(G$1, FebR!$6:$6, 0), FALSE), 0 ) + IFERROR( VLOOKUP($A12, INDIRECT("MarR!$A$6:$ZZ$1048576"), MATCH(G$1, MarR!$6:$6, 0), FALSE), 0 ) + IFERROR( VLOOKUP($A12, INDIRECT("AbrR!$A$6:$ZZ$1048576"), MATCH(G$1, AbrR!$6:$6, 0), FALSE), 0 ) + IFERROR( VLOOKUP($A12, INDIRECT("MayR!$A$6:$ZZ$1048576"), MATCH(G$1, MayR!$6:$6, 0), FALSE), 0 ) + IFERROR( VLOOKUP($A12, INDIRECT("JunR!$A$6:$ZZ$1048576"), MATCH(G$1, JunR!$6:$6, 0), FALSE), 0 ) + IFERROR( VLOOKUP($A12, INDIRECT("JulR!$A$6:$ZZ$1048576"), MATCH(G$1, JulR!$6:$6, 0), FALSE), 0 ) + IFERROR( VLOOKUP($A12, INDIRECT("AgoR!$A$6:$ZZ$1048576"), MATCH(G$1, AgoR!$6:$6, 0), FALSE), 0 ) + IFERROR( VLOOKUP($A12, INDIRECT("SepR!$A$6:$ZZ$1048576"), MATCH(G$1, SepR!$6:$6, 0), FALSE), 0 ) + IFERROR( VLOOKUP($A12, INDIRECT("OctR!$A$6:$ZZ$1048576"), MATCH(G$1, OctR!$6:$6, 0), FALSE), 0 ) + IFERROR( VLOOKUP($A12, INDIRECT("NovR!$A$6:$ZZ$1048576"), MATCH(G$1, NovR!$6:$6, 0), FALSE), 0 ) + IFERROR( VLOOKUP($A12, INDIRECT("DicR!$A$6:$ZZ$1048576"), MATCH(G$1, DicR!$6:$6, 0), FALSE), 0 ) )} -> 0 | H12: {=SUM( IFERROR( VLOOKUP($A12, INDIRECT("EneR!$A$6:$ZZ$1048576"), MATCH(H$1, EneR!$6:$6, 0), FALSE), 0 ) + IFERROR( VLOOKUP($A12, INDIRECT("FebR!$A$6:$ZZ$1048576"), MATCH(H$1, FebR!$6:$6, 0), FALSE), 0 ) + IFERROR( VLOOKUP($A12, INDIRECT("MarR!$A$6:$ZZ$1048576"), MATCH(H$1, MarR!$6:$6, 0), FALSE), 0 ) + IFERROR( VLOOKUP($A12, INDIRECT("AbrR!$A$6:$ZZ$1048576"), MATCH(H$1, AbrR!$6:$6, 0), FALSE), 0 ) + IFERROR( VLOOKUP($A12, INDIRECT("MayR!$A$6:$ZZ$1048576"), MATCH(H$1, MayR!$6:$6, 0), FALSE), 0 ) + IFERROR( VLOOKUP($A12, INDIRECT("JunR!$A$6:$ZZ$1048576"), MATCH(H$1, JunR!$6:$6, 0), FALSE), 0 ) + IFERROR( VLOOKUP($A12, INDIRECT("JulR!$A$6:$ZZ$1048576"), MATCH(H$1, JulR!$6:$6, 0), FALSE), 0 ) + IFERROR( VLOOKUP($A12, INDIRECT("AgoR!$A$6:$ZZ$1048576"), MATCH(H$1, AgoR!$6:$6, 0), FALSE), 0 ) + IFERROR( VLOOKUP($A12, INDIRECT("SepR!$A$6:$ZZ$1048576"), MATCH(H$1, SepR!$6:$6, 0), FALSE), 0 ) + IFERROR( VLOOKUP($A12, INDIRECT("OctR!$A$6:$ZZ$1048576"), MATCH(H$1, OctR!$6:$6, 0), FALSE), 0 ) + IFERROR( VLOOKUP($A12, INDIRECT("NovR!$A$6:$ZZ$1048576"), MATCH(H$1, NovR!$6:$6, 0), FALSE), 0 ) + IFERROR( VLOOKUP($A12, INDIRECT("DicR!$A$6:$ZZ$1048576"), MATCH(H$1, DicR!$6:$6, 0), FALSE), 0 ) )} -> 0 | I12: {=SUM( IFERROR( VLOOKUP($A12, INDIRECT("EneR!$A$6:$ZZ$1048576"), MATCH(I$1, EneR!$6:$6, 0), FALSE), 0 ) + IFERROR( VLOOKUP($A12, INDIRECT("FebR!$A$6:$ZZ$1048576"), MATCH(I$1, FebR!$6:$6, 0), FALSE), 0 ) + IFERROR( VLOOKUP($A12, INDIRECT("MarR!$A$6:$ZZ$1048576"), MATCH(I$1, MarR!$6:$6, 0), FALSE), 0 ) + IFERROR( VLOOKUP($A12, INDIRECT("AbrR!$A$6:$ZZ$1048576"), MATCH(I$1, AbrR!$6:$6, 0), FALSE), 0 ) + IFERROR( VLOOKUP($A12, INDIRECT("MayR!$A$6:$ZZ$1048576"), MATCH(I$1, MayR!$6:$6, 0), FALSE), 0 ) + IFERROR( VLOOKUP($A12, INDIRECT("JunR!$A$6:$ZZ$1048576"), MATCH(I$1, JunR!$6:$6, 0), FALSE), 0 ) + IFERROR( VLOOKUP($A12, INDIRECT("JulR!$A$6:$ZZ$1048576"), MATCH(I$1, JulR!$6:$6, 0), FALSE), 0 ) + IFERROR( VLOOKUP($A12, INDIRECT("AgoR!$A$6:$ZZ$1048576"), MATCH(I$1, AgoR!$6:$6, 0), FALSE), 0 ) + IFERROR( VLOOKUP($A12, INDIRECT("SepR!$A$6:$ZZ$1048576"), MATCH(I$1, SepR!$6:$6, 0), FALSE), 0 ) + IFERROR( VLOOKUP($A12, INDIRECT("OctR!$A$6:$ZZ$1048576"), MATCH(I$1, OctR!$6:$6, 0), FALSE), 0 ) + IFERROR( VLOOKUP($A12, INDIRECT("NovR!$A$6:$ZZ$1048576"), MATCH(I$1, NovR!$6:$6, 0), FALSE), 0 ) + IFERROR( VLOOKUP($A12, INDIRECT("DicR!$A$6:$ZZ$1048576"), MATCH(I$1, DicR!$6:$6, 0), FALSE), 0 ) )} -> 0 | J12: {=SUM( IFERROR( VLOOKUP($A12, INDIRECT("EneR!$A$6:$ZZ$1048576"), MATCH(J$1, EneR!$6:$6, 0), FALSE), 0 ) + IFERROR( VLOOKUP($A12, INDIRECT("FebR!$A$6:$ZZ$1048576"), MATCH(J$1, FebR!$6:$6, 0), FALSE), 0 ) + IFERROR( VLOOKUP($A12, INDIRECT("MarR!$A$6:$ZZ$1048576"), MATCH(J$1, MarR!$6:$6, 0), FALSE), 0 ) + IFERROR( VLOOKUP($A12, INDIRECT("AbrR!$A$6:$ZZ$1048576"), MATCH(J$1, AbrR!$6:$6, 0), FALSE), 0 ) + IFERROR( VLOOKUP($A12, INDIRECT("MayR!$A$6:$ZZ$1048576"), MATCH(J$1, MayR!$6:$6, 0), FALSE), 0 ) + IFERROR( VLOOKUP($A12, INDIRECT("JunR!$A$6:$ZZ$1048576"), MATCH(J$1, JunR!$6:$6, 0), FALSE), 0 ) + IFERROR( VLOOKUP($A12, INDIRECT("JulR!$A$6:$ZZ$1048576"), MATCH(J$1, JulR!$6:$6, 0), FALSE), 0 ) + IFERROR( VLOOKUP($A12, INDIRECT("AgoR!$A$6:$ZZ$1048576"), MATCH(J$1, AgoR!$6:$6, 0), FALSE), 0 ) + IFERROR( VLOOKUP($A12, INDIRECT("SepR!$A$6:$ZZ$1048576"), MATCH(J$1, SepR!$6:$6, 0), FALSE), 0 ) + IFERROR( VLOOKUP($A12, INDIRECT("OctR!$A$6:$ZZ$1048576"), MATCH(J$1, OctR!$6:$6, 0), FALSE), 0 ) + IFERROR( VLOOKUP($A12, INDIRECT("NovR!$A$6:$ZZ$1048576"), MATCH(J$1, NovR!$6:$6, 0), FALSE), 0 ) + IFERROR( VLOOKUP($A12, INDIRECT("DicR!$A$6:$ZZ$1048576"), MATCH(J$1, DicR!$6:$6, 0), FALSE), 0 ) )} -> 0 | K12: {=SUM( IFERROR( VLOOKUP($A12, INDIRECT("EneR!$A$6:$ZZ$1048576"), MATCH(K$1, EneR!$6:$6, 0), FALSE), 0 ) + IFERROR( VLOOKUP($A12, INDIRECT("FebR!$A$6:$ZZ$1048576"), MATCH(K$1, FebR!$6:$6, 0), FALSE), 0 ) + IFERROR( VLOOKUP($A12, INDIRECT("MarR!$A$6:$ZZ$1048576"), MATCH(K$1, MarR!$6:$6, 0), FALSE), 0 ) + IFERROR( VLOOKUP($A12, INDIRECT("AbrR!$A$6:$ZZ$1048576"), MATCH(K$1, AbrR!$6:$6, 0), FALSE), 0 ) + IFERROR( VLOOKUP($A12, INDIRECT("MayR!$A$6:$ZZ$1048576"), MATCH(K$1, MayR!$6:$6, 0), FALSE), 0 ) + IFERROR( VLOOKUP($A12, INDIRECT("JunR!$A$6:$ZZ$1048576"), MATCH(K$1, JunR!$6:$6, 0), FALSE), 0 ) + IFERROR( VLOOKUP($A12, INDIRECT("JulR!$A$6:$ZZ$1048576"), MATCH(K$1, JulR!$6:$6, 0), FALSE), 0 ) + IFERROR( VLOOKUP($A12, INDIRECT("AgoR!$A$6:$ZZ$1048576"), MATCH(K$1, AgoR!$6:$6, 0), FALSE), 0 ) + IFERROR( VLOOKUP($A12, INDIRECT("SepR!$A$6:$ZZ$1048576"), MATCH(K$1, SepR!$6:$6, 0), FALSE), 0 ) + IFERROR( VLOOKUP($A12, INDIRECT("OctR!$A$6:$ZZ$1048576"), MATCH(K$1, OctR!$6:$6, 0), FALSE), 0 ) + IFERROR( VLOOKUP($A12, INDIRECT("NovR!$A$6:$ZZ$1048576"), MATCH(K$1, NovR!$6:$6, 0), FALSE), 0 ) + IFERROR( VLOOKUP($A12, INDIRECT("DicR!$A$6:$ZZ$1048576"), MATCH(K$1, DicR!$6:$6, 0), FALSE), 0 ) )} -> 0 | ... AY12: {=SUM( IFERROR( VLOOKUP($A12, INDIRECT("EneR!$A$6:$ZZ$1048576"), MATCH(AY$1, EneR!$6:$6, 0), FALSE), 0 ) + IFERROR( VLOOKUP($A12, INDIRECT("FebR!$A$6:$ZZ$1048576"), MATCH(AY$1, FebR!$6:$6, 0), FALSE), 0 ) + IFERROR( VLOOKUP($A12, INDIRECT("MarR!$A$6:$ZZ$1048576"), MATCH(AY$1, MarR!$6:$6, 0), FALSE), 0 ) + IFERROR( VLOOKUP($A12, INDIRECT("AbrR!$A$6:$ZZ$1048576"), MATCH(AY$1, AbrR!$6:$6, 0), FALSE), 0 ) + IFERROR( VLOOKUP($A12, INDIRECT("MayR!$A$6:$ZZ$1048576"), MATCH(AY$1, MayR!$6:$6, 0), FALSE), 0 ) + IFERROR( VLOOKUP($A12, INDIRECT("JunR!$A$6:$ZZ$1048576"), MATCH(AY$1, JunR!$6:$6, 0), FALSE), 0 ) + IFERROR( VLOOKUP($A12, INDIRECT("JulR!$A$6:$ZZ$1048576"), MATCH(AY$1, JulR!$6:$6, 0), FALSE), 0 ) + IFERROR( VLOOKUP($A12, INDIRECT("AgoR!$A$6:$ZZ$1048576"), MATCH(AY$1, AgoR!$6:$6, 0), FALSE), 0 ) + IFERROR( VLOOKUP($A12, INDIRECT("SepR!$A$6:$ZZ$1048576"), MATCH(AY$1, SepR!$6:$6, 0), FALSE), 0 ) + IFERROR( VLOOKUP($A12, INDIRECT("OctR!$A$6:$ZZ$1048576"), MATCH(AY$1, OctR!$6:$6, 0), FALSE), 0 ) + IFERROR( VLOOKUP($A12, INDIRECT("NovR!$A$6:$ZZ$1048576"), MATCH(AY$1, NovR!$6:$6, 0), FALSE), 0 ) + IFERROR( VLOOKUP($A12, INDIRECT("DicR!$A$6:$ZZ$1048576"), MATCH(AY$1, DicR!$6:$6, 0), FALSE), 0 ) )} -> 0
A13: =Menus!R5 | B13: =IFERROR(SUM(D13:AZ13),"") -> 0 | C13: =IFERROR(INDEX($D$1:$AQ130, MATCH($A13, $A$1:$A130, 0), MATCH(C$1, $D$1:AZ$1, 0)), "") | D13: {=SUM( IFERROR( VLOOKUP($A13, INDIRECT("EneR!$A$6:$ZZ$1048576"), MATCH(D$1, EneR!$6:$6, 0), FALSE), 0 ) + IFERROR( VLOOKUP($A13, INDIRECT("FebR!$A$6:$ZZ$1048576"), MATCH(D$1, FebR!$6:$6, 0), FALSE), 0 ) + IFERROR( VLOOKUP($A13, INDIRECT("MarR!$A$6:$ZZ$1048576"), MATCH(D$1, MarR!$6:$6, 0), FALSE), 0 ) + IFERROR( VLOOKUP($A13, INDIRECT("AbrR!$A$6:$ZZ$1048576"), MATCH(D$1, AbrR!$6:$6, 0), FALSE), 0 ) + IFERROR( VLOOKUP($A13, INDIRECT("MayR!$A$6:$ZZ$1048576"), MATCH(D$1, MayR!$6:$6, 0), FALSE), 0 ) + IFERROR( VLOOKUP($A13, INDIRECT("JunR!$A$6:$ZZ$1048576"), MATCH(D$1, JunR!$6:$6, 0), FALSE), 0 ) + IFERROR( VLOOKUP($A13, INDIRECT("JulR!$A$6:$ZZ$1048576"), MATCH(D$1, JulR!$6:$6, 0), FALSE), 0 ) + IFERROR( VLOOKUP($A13, INDIRECT("AgoR!$A$6:$ZZ$1048576"), MATCH(D$1, AgoR!$6:$6, 0), FALSE), 0 ) + IFERROR( VLOOKUP($A13, INDIRECT("SepR!$A$6:$ZZ$1048576"), MATCH(D$1, SepR!$6:$6, 0), FALSE), 0 ) + IFERROR( VLOOKUP($A13, INDIRECT("OctR!$A$6:$ZZ$1048576"), MATCH(D$1, OctR!$6:$6, 0), FALSE), 0 ) + IFERROR( VLOOKUP($A13, INDIRECT("NovR!$A$6:$ZZ$1048576"), MATCH(D$1, NovR!$6:$6, 0), FALSE), 0 ) + IFERROR( VLOOKUP($A13, INDIRECT("DicR!$A$6:$ZZ$1048576"), MATCH(D$1, DicR!$6:$6, 0), FALSE), 0 ) )} -> 0 | E13: {=SUM( IFERROR( VLOOKUP($A13, INDIRECT("EneR!$A$6:$ZZ$1048576"), MATCH(E$1, EneR!$6:$6, 0), FALSE), 0 ) + IFERROR( VLOOKUP($A13, INDIRECT("FebR!$A$6:$ZZ$1048576"), MATCH(E$1, FebR!$6:$6, 0), FALSE), 0 ) + IFERROR( VLOOKUP($A13, INDIRECT("MarR!$A$6:$ZZ$1048576"), MATCH(E$1, MarR!$6:$6, 0), FALSE), 0 ) + IFERROR( VLOOKUP($A13, INDIRECT("AbrR!$A$6:$ZZ$1048576"), MATCH(E$1, AbrR!$6:$6, 0), FALSE), 0 ) + IFERROR( VLOOKUP($A13, INDIRECT("MayR!$A$6:$ZZ$1048576"), MATCH(E$1, MayR!$6:$6, 0), FALSE), 0 ) + IFERROR( VLOOKUP($A13, INDIRECT("JunR!$A$6:$ZZ$1048576"), MATCH(E$1, JunR!$6:$6, 0), FALSE), 0 ) + IFERROR( VLOOKUP($A13, INDIRECT("JulR!$A$6:$ZZ$1048576"), MATCH(E$1, JulR!$6:$6, 0), FALSE), 0 ) + IFERROR( VLOOKUP($A13, INDIRECT("AgoR!$A$6:$ZZ$1048576"), MATCH(E$1, AgoR!$6:$6, 0), FALSE), 0 ) + IFERROR( VLOOKUP($A13, INDIRECT("SepR!$A$6:$ZZ$1048576"), MATCH(E$1, SepR!$6:$6, 0), FALSE), 0 ) + IFERROR( VLOOKUP($A13, INDIRECT("OctR!$A$6:$ZZ$1048576"), MATCH(E$1, OctR!$6:$6, 0), FALSE), 0 ) + IFERROR( VLOOKUP($A13, INDIRECT("NovR!$A$6:$ZZ$1048576"), MATCH(E$1, NovR!$6:$6, 0), FALSE), 0 ) + IFERROR( VLOOKUP($A13, INDIRECT("DicR!$A$6:$ZZ$1048576"), MATCH(E$1, DicR!$6:$6, 0), FALSE), 0 ) )} -> 0 | F13: {=SUM( IFERROR( VLOOKUP($A13, INDIRECT("EneR!$A$6:$ZZ$1048576"), MATCH(F$1, EneR!$6:$6, 0), FALSE), 0 ) + IFERROR( VLOOKUP($A13, INDIRECT("FebR!$A$6:$ZZ$1048576"), MATCH(F$1, FebR!$6:$6, 0), FALSE), 0 ) + IFERROR( VLOOKUP($A13, INDIRECT("MarR!$A$6:$ZZ$1048576"), MATCH(F$1, MarR!$6:$6, 0), FALSE), 0 ) + IFERROR( VLOOKUP($A13, INDIRECT("AbrR!$A$6:$ZZ$1048576"), MATCH(F$1, AbrR!$6:$6, 0), FALSE), 0 ) + IFERROR( VLOOKUP($A13, INDIRECT("MayR!$A$6:$ZZ$1048576"), MATCH(F$1, MayR!$6:$6, 0), FALSE), 0 ) + IFERROR( VLOOKUP($A13, INDIRECT("JunR!$A$6:$ZZ$1048576"), MATCH(F$1, JunR!$6:$6, 0), FALSE), 0 ) + IFERROR( VLOOKUP($A13, INDIRECT("JulR!$A$6:$ZZ$1048576"), MATCH(F$1, JulR!$6:$6, 0), FALSE), 0 ) + IFERROR( VLOOKUP($A13, INDIRECT("AgoR!$A$6:$ZZ$1048576"), MATCH(F$1, AgoR!$6:$6, 0), FALSE), 0 ) + IFERROR( VLOOKUP($A13, INDIRECT("SepR!$A$6:$ZZ$1048576"), MATCH(F$1, SepR!$6:$6, 0), FALSE), 0 ) + IFERROR( VLOOKUP($A13, INDIRECT("OctR!$A$6:$ZZ$1048576"), MATCH(F$1, OctR!$6:$6, 0), FALSE), 0 ) + IFERROR( VLOOKUP($A13, INDIRECT("NovR!$A$6:$ZZ$1048576"), MATCH(F$1, NovR!$6:$6, 0), FALSE), 0 ) + IFERROR( VLOOKUP($A13, INDIRECT("DicR!$A$6:$ZZ$1048576"), MATCH(F$1, DicR!$6:$6, 0), FALSE), 0 ) )} -> 0 | G13: {=SUM( IFERROR( VLOOKUP($A13, INDIRECT("EneR!$A$6:$ZZ$1048576"), MATCH(G$1, EneR!$6:$6, 0), FALSE), 0 ) + IFERROR( VLOOKUP($A13, INDIRECT("FebR!$A$6:$ZZ$1048576"), MATCH(G$1, FebR!$6:$6, 0), FALSE), 0 ) + IFERROR( VLOOKUP($A13, INDIRECT("MarR!$A$6:$ZZ$1048576"), MATCH(G$1, MarR!$6:$6, 0), FALSE), 0 ) + IFERROR( VLOOKUP($A13, INDIRECT("AbrR!$A$6:$ZZ$1048576"), MATCH(G$1, AbrR!$6:$6, 0), FALSE), 0 ) + IFERROR( VLOOKUP($A13, INDIRECT("MayR!$A$6:$ZZ$1048576"), MATCH(G$1, MayR!$6:$6, 0), FALSE), 0 ) + IFERROR( VLOOKUP($A13, INDIRECT("JunR!$A$6:$ZZ$1048576"), MATCH(G$1, JunR!$6:$6, 0), FALSE), 0 ) + IFERROR( VLOOKUP($A13, INDIRECT("JulR!$A$6:$ZZ$1048576"), MATCH(G$1, JulR!$6:$6, 0), FALSE), 0 ) + IFERROR( VLOOKUP($A13, INDIRECT("AgoR!$A$6:$ZZ$1048576"), MATCH(G$1, AgoR!$6:$6, 0), FALSE), 0 ) + IFERROR( VLOOKUP($A13, INDIRECT("SepR!$A$6:$ZZ$1048576"), MATCH(G$1, SepR!$6:$6, 0), FALSE), 0 ) + IFERROR( VLOOKUP($A13, INDIRECT("OctR!$A$6:$ZZ$1048576"), MATCH(G$1, OctR!$6:$6, 0), FALSE), 0 ) + IFERROR( VLOOKUP($A13, INDIRECT("NovR!$A$6:$ZZ$1048576"), MATCH(G$1, NovR!$6:$6, 0), FALSE), 0 ) + IFERROR( VLOOKUP($A13, INDIRECT("DicR!$A$6:$ZZ$1048576"), MATCH(G$1, DicR!$6:$6, 0), FALSE), 0 ) )} -> 0 | H13: {=SUM( IFERROR( VLOOKUP($A13, INDIRECT("EneR!$A$6:$ZZ$1048576"), MATCH(H$1, EneR!$6:$6, 0), FALSE), 0 ) + IFERROR( VLOOKUP($A13, INDIRECT("FebR!$A$6:$ZZ$1048576"), MATCH(H$1, FebR!$6:$6, 0), FALSE), 0 ) + IFERROR( VLOOKUP($A13, INDIRECT("MarR!$A$6:$ZZ$1048576"), MATCH(H$1, MarR!$6:$6, 0), FALSE), 0 ) + IFERROR( VLOOKUP($A13, INDIRECT("AbrR!$A$6:$ZZ$1048576"), MATCH(H$1, AbrR!$6:$6, 0), FALSE), 0 ) + IFERROR( VLOOKUP($A13, INDIRECT("MayR!$A$6:$ZZ$1048576"), MATCH(H$1, MayR!$6:$6, 0), FALSE), 0 ) + IFERROR( VLOOKUP($A13, INDIRECT("JunR!$A$6:$ZZ$1048576"), MATCH(H$1, JunR!$6:$6, 0), FALSE), 0 ) + IFERROR( VLOOKUP($A13, INDIRECT("JulR!$A$6:$ZZ$1048576"), MATCH(H$1, JulR!$6:$6, 0), FALSE), 0 ) + IFERROR( VLOOKUP($A13, INDIRECT("AgoR!$A$6:$ZZ$1048576"), MATCH(H$1, AgoR!$6:$6, 0), FALSE), 0 ) + IFERROR( VLOOKUP($A13, INDIRECT("SepR!$A$6:$ZZ$1048576"), MATCH(H$1, SepR!$6:$6, 0), FALSE), 0 ) + IFERROR( VLOOKUP($A13, INDIRECT("OctR!$A$6:$ZZ$1048576"), MATCH(H$1, OctR!$6:$6, 0), FALSE), 0 ) + IFERROR( VLOOKUP($A13, INDIRECT("NovR!$A$6:$ZZ$1048576"), MATCH(H$1, NovR!$6:$6, 0), FALSE), 0 ) + IFERROR( VLOOKUP($A13, INDIRECT("DicR!$A$6:$ZZ$1048576"), MATCH(H$1, DicR!$6:$6, 0), FALSE), 0 ) )} -> 0 | I13: {=SUM( IFERROR( VLOOKUP($A13, INDIRECT("EneR!$A$6:$ZZ$1048576"), MATCH(I$1, EneR!$6:$6, 0), FALSE), 0 ) + IFERROR( VLOOKUP($A13, INDIRECT("FebR!$A$6:$ZZ$1048576"), MATCH(I$1, FebR!$6:$6, 0), FALSE), 0 ) + IFERROR( VLOOKUP($A13, INDIRECT("MarR!$A$6:$ZZ$1048576"), MATCH(I$1, MarR!$6:$6, 0), FALSE), 0 ) + IFERROR( VLOOKUP($A13, INDIRECT("AbrR!$A$6:$ZZ$1048576"), MATCH(I$1, AbrR!$6:$6, 0), FALSE), 0 ) + IFERROR( VLOOKUP($A13, INDIRECT("MayR!$A$6:$ZZ$1048576"), MATCH(I$1, MayR!$6:$6, 0), FALSE), 0 ) + IFERROR( VLOOKUP($A13, INDIRECT("JunR!$A$6:$ZZ$1048576"), MATCH(I$1, JunR!$6:$6, 0), FALSE), 0 ) + IFERROR( VLOOKUP($A13, INDIRECT("JulR!$A$6:$ZZ$1048576"), MATCH(I$1, JulR!$6:$6, 0), FALSE), 0 ) + IFERROR( VLOOKUP($A13, INDIRECT("AgoR!$A$6:$ZZ$1048576"), MATCH(I$1, AgoR!$6:$6, 0), FALSE), 0 ) + IFERROR( VLOOKUP($A13, INDIRECT("SepR!$A$6:$ZZ$1048576"), MATCH(I$1, SepR!$6:$6, 0), FALSE), 0 ) + IFERROR( VLOOKUP($A13, INDIRECT("OctR!$A$6:$ZZ$1048576"), MATCH(I$1, OctR!$6:$6, 0), FALSE), 0 ) + IFERROR( VLOOKUP($A13, INDIRECT("NovR!$A$6:$ZZ$1048576"), MATCH(I$1, NovR!$6:$6, 0), FALSE), 0 ) + IFERROR( VLOOKUP($A13, INDIRECT("DicR!$A$6:$ZZ$1048576"), MATCH(I$1, DicR!$6:$6, 0), FALSE), 0 ) )} -> 0 | J13: {=SUM( IFERROR( VLOOKUP($A13, INDIRECT("EneR!$A$6:$ZZ$1048576"), MATCH(J$1, EneR!$6:$6, 0), FALSE), 0 ) + IFERROR( VLOOKUP($A13, INDIRECT("FebR!$A$6:$ZZ$1048576"), MATCH(J$1, FebR!$6:$6, 0), FALSE), 0 ) + IFERROR( VLOOKUP($A13, INDIRECT("MarR!$A$6:$ZZ$1048576"), MATCH(J$1, MarR!$6:$6, 0), FALSE), 0 ) + IFERROR( VLOOKUP($A13, INDIRECT("AbrR!$A$6:$ZZ$1048576"), MATCH(J$1, AbrR!$6:$6, 0), FALSE), 0 ) + IFERROR( VLOOKUP($A13, INDIRECT("MayR!$A$6:$ZZ$1048576"), MATCH(J$1, MayR!$6:$6, 0), FALSE), 0 ) + IFERROR( VLOOKUP($A13, INDIRECT("JunR!$A$6:$ZZ$1048576"), MATCH(J$1, JunR!$6:$6, 0), FALSE), 0 ) + IFERROR( VLOOKUP($A13, INDIRECT("JulR!$A$6:$ZZ$1048576"), MATCH(J$1, JulR!$6:$6, 0), FALSE), 0 ) + IFERROR( VLOOKUP($A13, INDIRECT("AgoR!$A$6:$ZZ$1048576"), MATCH(J$1, AgoR!$6:$6, 0), FALSE), 0 ) + IFERROR( VLOOKUP($A13, INDIRECT("SepR!$A$6:$ZZ$1048576"), MATCH(J$1, SepR!$6:$6, 0), FALSE), 0 ) + IFERROR( VLOOKUP($A13, INDIRECT("OctR!$A$6:$ZZ$1048576"), MATCH(J$1, OctR!$6:$6, 0), FALSE), 0 ) + IFERROR( VLOOKUP($A13, INDIRECT("NovR!$A$6:$ZZ$1048576"), MATCH(J$1, NovR!$6:$6, 0), FALSE), 0 ) + IFERROR( VLOOKUP($A13, INDIRECT("DicR!$A$6:$ZZ$1048576"), MATCH(J$1, DicR!$6:$6, 0), FALSE), 0 ) )} -> 0 | K13: {=SUM( IFERROR( VLOOKUP($A13, INDIRECT("EneR!$A$6:$ZZ$1048576"), MATCH(K$1, EneR!$6:$6, 0), FALSE), 0 ) + IFERROR( VLOOKUP($A13, INDIRECT("FebR!$A$6:$ZZ$1048576"), MATCH(K$1, FebR!$6:$6, 0), FALSE), 0 ) + IFERROR( VLOOKUP($A13, INDIRECT("MarR!$A$6:$ZZ$1048576"), MATCH(K$1, MarR!$6:$6, 0), FALSE), 0 ) + IFERROR( VLOOKUP($A13, INDIRECT("AbrR!$A$6:$ZZ$1048576"), MATCH(K$1, AbrR!$6:$6, 0), FALSE), 0 ) + IFERROR( VLOOKUP($A13, INDIRECT("MayR!$A$6:$ZZ$1048576"), MATCH(K$1, MayR!$6:$6, 0), FALSE), 0 ) + IFERROR( VLOOKUP($A13, INDIRECT("JunR!$A$6:$ZZ$1048576"), MATCH(K$1, JunR!$6:$6, 0), FALSE), 0 ) + IFERROR( VLOOKUP($A13, INDIRECT("JulR!$A$6:$ZZ$1048576"), MATCH(K$1, JulR!$6:$6, 0), FALSE), 0 ) + IFERROR( VLOOKUP($A13, INDIRECT("AgoR!$A$6:$ZZ$1048576"), MATCH(K$1, AgoR!$6:$6, 0), FALSE), 0 ) + IFERROR( VLOOKUP($A13, INDIRECT("SepR!$A$6:$ZZ$1048576"), MATCH(K$1, SepR!$6:$6, 0), FALSE), 0 ) + IFERROR( VLOOKUP($A13, INDIRECT("OctR!$A$6:$ZZ$1048576"), MATCH(K$1, OctR!$6:$6, 0), FALSE), 0 ) + IFERROR( VLOOKUP($A13, INDIRECT("NovR!$A$6:$ZZ$1048576"), MATCH(K$1, NovR!$6:$6, 0), FALSE), 0 ) + IFERROR( VLOOKUP($A13, INDIRECT("DicR!$A$6:$ZZ$1048576"), MATCH(K$1, DicR!$6:$6, 0), FALSE), 0 ) )} -> 0 | ... AY13: {=SUM( IFERROR( VLOOKUP($A13, INDIRECT("EneR!$A$6:$ZZ$1048576"), MATCH(AY$1, EneR!$6:$6, 0), FALSE), 0 ) + IFERROR( VLOOKUP($A13, INDIRECT("FebR!$A$6:$ZZ$1048576"), MATCH(AY$1, FebR!$6:$6, 0), FALSE), 0 ) + IFERROR( VLOOKUP($A13, INDIRECT("MarR!$A$6:$ZZ$1048576"), MATCH(AY$1, MarR!$6:$6, 0), FALSE), 0 ) + IFERROR( VLOOKUP($A13, INDIRECT("AbrR!$A$6:$ZZ$1048576"), MATCH(AY$1, AbrR!$6:$6, 0), FALSE), 0 ) + IFERROR( VLOOKUP($A13, INDIRECT("MayR!$A$6:$ZZ$1048576"), MATCH(AY$1, MayR!$6:$6, 0), FALSE), 0 ) + IFERROR( VLOOKUP($A13, INDIRECT("JunR!$A$6:$ZZ$1048576"), MATCH(AY$1, JunR!$6:$6, 0), FALSE), 0 ) + IFERROR( VLOOKUP($A13, INDIRECT("JulR!$A$6:$ZZ$1048576"), MATCH(AY$1, JulR!$6:$6, 0), FALSE), 0 ) + IFERROR( VLOOKUP($A13, INDIRECT("AgoR!$A$6:$ZZ$1048576"), MATCH(AY$1, AgoR!$6:$6, 0), FALSE), 0 ) + IFERROR( VLOOKUP($A13, INDIRECT("SepR!$A$6:$ZZ$1048576"), MATCH(AY$1, SepR!$6:$6, 0), FALSE), 0 ) + IFERROR( VLOOKUP($A13, INDIRECT("OctR!$A$6:$ZZ$1048576"), MATCH(AY$1, OctR!$6:$6, 0), FALSE), 0 ) + IFERROR( VLOOKUP($A13, INDIRECT("NovR!$A$6:$ZZ$1048576"), MATCH(AY$1, NovR!$6:$6, 0), FALSE), 0 ) + IFERROR( VLOOKUP($A13, INDIRECT("DicR!$A$6:$ZZ$1048576"), MATCH(AY$1, DicR!$6:$6, 0), FALSE), 0 ) )} -> 0
A14: =Menus!R6 | B14: =IFERROR(SUM(D14:AZ14),"") -> 0 | C14: =IFERROR(INDEX($D$1:$AQ131, MATCH($A14, $A$1:$A131, 0), MATCH(C$1, $D$1:AZ$1, 0)), "") | D14: {=SUM( IFERROR( VLOOKUP($A14, INDIRECT("EneR!$A$6:$ZZ$1048576"), MATCH(D$1, EneR!$6:$6, 0), FALSE), 0 ) + IFERROR( VLOOKUP($A14, INDIRECT("FebR!$A$6:$ZZ$1048576"), MATCH(D$1, FebR!$6:$6, 0), FALSE), 0 ) + IFERROR( VLOOKUP($A14, INDIRECT("MarR!$A$6:$ZZ$1048576"), MATCH(D$1, MarR!$6:$6, 0), FALSE), 0 ) + IFERROR( VLOOKUP($A14, INDIRECT("AbrR!$A$6:$ZZ$1048576"), MATCH(D$1, AbrR!$6:$6, 0), FALSE), 0 ) + IFERROR( VLOOKUP($A14, INDIRECT("MayR!$A$6:$ZZ$1048576"), MATCH(D$1, MayR!$6:$6, 0), FALSE), 0 ) + IFERROR( VLOOKUP($A14, INDIRECT("JunR!$A$6:$ZZ$1048576"), MATCH(D$1, JunR!$6:$6, 0), FALSE), 0 ) + IFERROR( VLOOKUP($A14, INDIRECT("JulR!$A$6:$ZZ$1048576"), MATCH(D$1, JulR!$6:$6, 0), FALSE), 0 ) + IFERROR( VLOOKUP($A14, INDIRECT("AgoR!$A$6:$ZZ$1048576"), MATCH(D$1, AgoR!$6:$6, 0), FALSE), 0 ) + IFERROR( VLOOKUP($A14, INDIRECT("SepR!$A$6:$ZZ$1048576"), MATCH(D$1, SepR!$6:$6, 0), FALSE), 0 ) + IFERROR( VLOOKUP($A14, INDIRECT("OctR!$A$6:$ZZ$1048576"), MATCH(D$1, OctR!$6:$6, 0), FALSE), 0 ) + IFERROR( VLOOKUP($A14, INDIRECT("NovR!$A$6:$ZZ$1048576"), MATCH(D$1, NovR!$6:$6, 0), FALSE), 0 ) + IFERROR( VLOOKUP($A14, INDIRECT("DicR!$A$6:$ZZ$1048576"), MATCH(D$1, DicR!$6:$6, 0), FALSE), 0 ) )} -> 0 | E14: {=SUM( IFERROR( VLOOKUP($A14, INDIRECT("EneR!$A$6:$ZZ$1048576"), MATCH(E$1, EneR!$6:$6, 0), FALSE), 0 ) + IFERROR( VLOOKUP($A14, INDIRECT("FebR!$A$6:$ZZ$1048576"), MATCH(E$1, FebR!$6:$6, 0), FALSE), 0 ) + IFERROR( VLOOKUP($A14, INDIRECT("MarR!$A$6:$ZZ$1048576"), MATCH(E$1, MarR!$6:$6, 0), FALSE), 0 ) + IFERROR( VLOOKUP($A14, INDIRECT("AbrR!$A$6:$ZZ$1048576"), MATCH(E$1, AbrR!$6:$6, 0), FALSE), 0 ) + IFERROR( VLOOKUP($A14, INDIRECT("MayR!$A$6:$ZZ$1048576"), MATCH(E$1, MayR!$6:$6, 0), FALSE), 0 ) + IFERROR( VLOOKUP($A14, INDIRECT("JunR!$A$6:$ZZ$1048576"), MATCH(E$1, JunR!$6:$6, 0), FALSE), 0 ) + IFERROR( VLOOKUP($A14, INDIRECT("JulR!$A$6:$ZZ$1048576"), MATCH(E$1, JulR!$6:$6, 0), FALSE), 0 ) + IFERROR( VLOOKUP($A14, INDIRECT("AgoR!$A$6:$ZZ$1048576"), MATCH(E$1, AgoR!$6:$6, 0), FALSE), 0 ) + IFERROR( VLOOKUP($A14, INDIRECT("SepR!$A$6:$ZZ$1048576"), MATCH(E$1, SepR!$6:$6, 0), FALSE), 0 ) + IFERROR( VLOOKUP($A14, INDIRECT("OctR!$A$6:$ZZ$1048576"), MATCH(E$1, OctR!$6:$6, 0), FALSE), 0 ) + IFERROR( VLOOKUP($A14, INDIRECT("NovR!$A$6:$ZZ$1048576"), MATCH(E$1, NovR!$6:$6, 0), FALSE), 0 ) + IFERROR( VLOOKUP($A14, INDIRECT("DicR!$A$6:$ZZ$1048576"), MATCH(E$1, DicR!$6:$6, 0), FALSE), 0 ) )} -> 0 | F14: {=SUM( IFERROR( VLOOKUP($A14, INDIRECT("EneR!$A$6:$ZZ$1048576"), MATCH(F$1, EneR!$6:$6, 0), FALSE), 0 ) + IFERROR( VLOOKUP($A14, INDIRECT("FebR!$A$6:$ZZ$1048576"), MATCH(F$1, FebR!$6:$6, 0), FALSE), 0 ) + IFERROR( VLOOKUP($A14, INDIRECT("MarR!$A$6:$ZZ$1048576"), MATCH(F$1, MarR!$6:$6, 0), FALSE), 0 ) + IFERROR( VLOOKUP($A14, INDIRECT("AbrR!$A$6:$ZZ$1048576"), MATCH(F$1, AbrR!$6:$6, 0), FALSE), 0 ) + IFERROR( VLOOKUP($A14, INDIRECT("MayR!$A$6:$ZZ$1048576"), MATCH(F$1, MayR!$6:$6, 0), FALSE), 0 ) + IFERROR( VLOOKUP($A14, INDIRECT("JunR!$A$6:$ZZ$1048576"), MATCH(F$1, JunR!$6:$6, 0), FALSE), 0 ) + IFERROR( VLOOKUP($A14, INDIRECT("JulR!$A$6:$ZZ$1048576"), MATCH(F$1, JulR!$6:$6, 0), FALSE), 0 ) + IFERROR( VLOOKUP($A14, INDIRECT("AgoR!$A$6:$ZZ$1048576"), MATCH(F$1, AgoR!$6:$6, 0), FALSE), 0 ) + IFERROR( VLOOKUP($A14, INDIRECT("SepR!$A$6:$ZZ$1048576"), MATCH(F$1, SepR!$6:$6, 0), FALSE), 0 ) + IFERROR( VLOOKUP($A14, INDIRECT("OctR!$A$6:$ZZ$1048576"), MATCH(F$1, OctR!$6:$6, 0), FALSE), 0 ) + IFERROR( VLOOKUP($A14, INDIRECT("NovR!$A$6:$ZZ$1048576"), MATCH(F$1, NovR!$6:$6, 0), FALSE), 0 ) + IFERROR( VLOOKUP($A14, INDIRECT("DicR!$A$6:$ZZ$1048576"), MATCH(F$1, DicR!$6:$6, 0), FALSE), 0 ) )} -> 0 | G14: {=SUM( IFERROR( VLOOKUP($A14, INDIRECT("EneR!$A$6:$ZZ$1048576"), MATCH(G$1, EneR!$6:$6, 0), FALSE), 0 ) + IFERROR( VLOOKUP($A14, INDIRECT("FebR!$A$6:$ZZ$1048576"), MATCH(G$1, FebR!$6:$6, 0), FALSE), 0 ) + IFERROR( VLOOKUP($A14, INDIRECT("MarR!$A$6:$ZZ$1048576"), MATCH(G$1, MarR!$6:$6, 0), FALSE), 0 ) + IFERROR( VLOOKUP($A14, INDIRECT("AbrR!$A$6:$ZZ$1048576"), MATCH(G$1, AbrR!$6:$6, 0), FALSE), 0 ) + IFERROR( VLOOKUP($A14, INDIRECT("MayR!$A$6:$ZZ$1048576"), MATCH(G$1, MayR!$6:$6, 0), FALSE), 0 ) + IFERROR( VLOOKUP($A14, INDIRECT("JunR!$A$6:$ZZ$1048576"), MATCH(G$1, JunR!$6:$6, 0), FALSE), 0 ) + IFERROR( VLOOKUP($A14, INDIRECT("JulR!$A$6:$ZZ$1048576"), MATCH(G$1, JulR!$6:$6, 0), FALSE), 0 ) + IFERROR( VLOOKUP($A14, INDIRECT("AgoR!$A$6:$ZZ$1048576"), MATCH(G$1, AgoR!$6:$6, 0), FALSE), 0 ) + IFERROR( VLOOKUP($A14, INDIRECT("SepR!$A$6:$ZZ$1048576"), MATCH(G$1, SepR!$6:$6, 0), FALSE), 0 ) + IFERROR( VLOOKUP($A14, INDIRECT("OctR!$A$6:$ZZ$1048576"), MATCH(G$1, OctR!$6:$6, 0), FALSE), 0 ) + IFERROR( VLOOKUP($A14, INDIRECT("NovR!$A$6:$ZZ$1048576"), MATCH(G$1, NovR!$6:$6, 0), FALSE), 0 ) + IFERROR( VLOOKUP($A14, INDIRECT("DicR!$A$6:$ZZ$1048576"), MATCH(G$1, DicR!$6:$6, 0), FALSE), 0 ) )} -> 0 | H14: {=SUM( IFERROR( VLOOKUP($A14, INDIRECT("EneR!$A$6:$ZZ$1048576"), MATCH(H$1, EneR!$6:$6, 0), FALSE), 0 ) + IFERROR( VLOOKUP($A14, INDIRECT("FebR!$A$6:$ZZ$1048576"), MATCH(H$1, FebR!$6:$6, 0), FALSE), 0 ) + IFERROR( VLOOKUP($A14, INDIRECT("MarR!$A$6:$ZZ$1048576"), MATCH(H$1, MarR!$6:$6, 0), FALSE), 0 ) + IFERROR( VLOOKUP($A14, INDIRECT("AbrR!$A$6:$ZZ$1048576"), MATCH(H$1, AbrR!$6:$6, 0), FALSE), 0 ) + IFERROR( VLOOKUP($A14, INDIRECT("MayR!$A$6:$ZZ$1048576"), MATCH(H$1, MayR!$6:$6, 0), FALSE), 0 ) + IFERROR( VLOOKUP($A14, INDIRECT("JunR!$A$6:$ZZ$1048576"), MATCH(H$1, JunR!$6:$6, 0), FALSE), 0 ) + IFERROR( VLOOKUP($A14, INDIRECT("JulR!$A$6:$ZZ$1048576"), MATCH(H$1, JulR!$6:$6, 0), FALSE), 0 ) + IFERROR( VLOOKUP($A14, INDIRECT("AgoR!$A$6:$ZZ$1048576"), MATCH(H$1, AgoR!$6:$6, 0), FALSE), 0 ) + IFERROR( VLOOKUP($A14, INDIRECT("SepR!$A$6:$ZZ$1048576"), MATCH(H$1, SepR!$6:$6, 0), FALSE), 0 ) + IFERROR( VLOOKUP($A14, INDIRECT("OctR!$A$6:$ZZ$1048576"), MATCH(H$1, OctR!$6:$6, 0), FALSE), 0 ) + IFERROR( VLOOKUP($A14, INDIRECT("NovR!$A$6:$ZZ$1048576"), MATCH(H$1, NovR!$6:$6, 0), FALSE), 0 ) + IFERROR( VLOOKUP($A14, INDIRECT("DicR!$A$6:$ZZ$1048576"), MATCH(H$1, DicR!$6:$6, 0), FALSE), 0 ) )} -> 0 | I14: {=SUM( IFERROR( VLOOKUP($A14, INDIRECT("EneR!$A$6:$ZZ$1048576"), MATCH(I$1, EneR!$6:$6, 0), FALSE), 0 ) + IFERROR( VLOOKUP($A14, INDIRECT("FebR!$A$6:$ZZ$1048576"), MATCH(I$1, FebR!$6:$6, 0), FALSE), 0 ) + IFERROR( VLOOKUP($A14, INDIRECT("MarR!$A$6:$ZZ$1048576"), MATCH(I$1, MarR!$6:$6, 0), FALSE), 0 ) + IFERROR( VLOOKUP($A14, INDIRECT("AbrR!$A$6:$ZZ$1048576"), MATCH(I$1, AbrR!$6:$6, 0), FALSE), 0 ) + IFERROR( VLOOKUP($A14, INDIRECT("MayR!$A$6:$ZZ$1048576"), MATCH(I$1, MayR!$6:$6, 0), FALSE), 0 ) + IFERROR( VLOOKUP($A14, INDIRECT("JunR!$A$6:$ZZ$1048576"), MATCH(I$1, JunR!$6:$6, 0), FALSE), 0 ) + IFERROR( VLOOKUP($A14, INDIRECT("JulR!$A$6:$ZZ$1048576"), MATCH(I$1, JulR!$6:$6, 0), FALSE), 0 ) + IFERROR( VLOOKUP($A14, INDIRECT("AgoR!$A$6:$ZZ$1048576"), MATCH(I$1, AgoR!$6:$6, 0), FALSE), 0 ) + IFERROR( VLOOKUP($A14, INDIRECT("SepR!$A$6:$ZZ$1048576"), MATCH(I$1, SepR!$6:$6, 0), FALSE), 0 ) + IFERROR( VLOOKUP($A14, INDIRECT("OctR!$A$6:$ZZ$1048576"), MATCH(I$1, OctR!$6:$6, 0), FALSE), 0 ) + IFERROR( VLOOKUP($A14, INDIRECT("NovR!$A$6:$ZZ$1048576"), MATCH(I$1, NovR!$6:$6, 0), FALSE), 0 ) + IFERROR( VLOOKUP($A14, INDIRECT("DicR!$A$6:$ZZ$1048576"), MATCH(I$1, DicR!$6:$6, 0), FALSE), 0 ) )} -> 0 | J14: {=SUM( IFERROR( VLOOKUP($A14, INDIRECT("EneR!$A$6:$ZZ$1048576"), MATCH(J$1, EneR!$6:$6, 0), FALSE), 0 ) + IFERROR( VLOOKUP($A14, INDIRECT("FebR!$A$6:$ZZ$1048576"), MATCH(J$1, FebR!$6:$6, 0), FALSE), 0 ) + IFERROR( VLOOKUP($A14, INDIRECT("MarR!$A$6:$ZZ$1048576"), MATCH(J$1, MarR!$6:$6, 0), FALSE), 0 ) + IFERROR( VLOOKUP($A14, INDIRECT("AbrR!$A$6:$ZZ$1048576"), MATCH(J$1, AbrR!$6:$6, 0), FALSE), 0 ) + IFERROR( VLOOKUP($A14, INDIRECT("MayR!$A$6:$ZZ$1048576"), MATCH(J$1, MayR!$6:$6, 0), FALSE), 0 ) + IFERROR( VLOOKUP($A14, INDIRECT("JunR!$A$6:$ZZ$1048576"), MATCH(J$1, JunR!$6:$6, 0), FALSE), 0 ) + IFERROR( VLOOKUP($A14, INDIRECT("JulR!$A$6:$ZZ$1048576"), MATCH(J$1, JulR!$6:$6, 0), FALSE), 0 ) + IFERROR( VLOOKUP($A14, INDIRECT("AgoR!$A$6:$ZZ$1048576"), MATCH(J$1, AgoR!$6:$6, 0), FALSE), 0 ) + IFERROR( VLOOKUP($A14, INDIRECT("SepR!$A$6:$ZZ$1048576"), MATCH(J$1, SepR!$6:$6, 0), FALSE), 0 ) + IFERROR( VLOOKUP($A14, INDIRECT("OctR!$A$6:$ZZ$1048576"), MATCH(J$1, OctR!$6:$6, 0), FALSE), 0 ) + IFERROR( VLOOKUP($A14, INDIRECT("NovR!$A$6:$ZZ$1048576"), MATCH(J$1, NovR!$6:$6, 0), FALSE), 0 ) + IFERROR( VLOOKUP($A14, INDIRECT("DicR!$A$6:$ZZ$1048576"), MATCH(J$1, DicR!$6:$6, 0), FALSE), 0 ) )} -> 0 | K14: {=SUM( IFERROR( VLOOKUP($A14, INDIRECT("EneR!$A$6:$ZZ$1048576"), MATCH(K$1, EneR!$6:$6, 0), FALSE), 0 ) + IFERROR( VLOOKUP($A14, INDIRECT("FebR!$A$6:$ZZ$1048576"), MATCH(K$1, FebR!$6:$6, 0), FALSE), 0 ) + IFERROR( VLOOKUP($A14, INDIRECT("MarR!$A$6:$ZZ$1048576"), MATCH(K$1, MarR!$6:$6, 0), FALSE), 0 ) + IFERROR( VLOOKUP($A14, INDIRECT("AbrR!$A$6:$ZZ$1048576"), MATCH(K$1, AbrR!$6:$6, 0), FALSE), 0 ) + IFERROR( VLOOKUP($A14, INDIRECT("MayR!$A$6:$ZZ$1048576"), MATCH(K$1, MayR!$6:$6, 0), FALSE), 0 ) + IFERROR( VLOOKUP($A14, INDIRECT("JunR!$A$6:$ZZ$1048576"), MATCH(K$1, JunR!$6:$6, 0), FALSE), 0 ) + IFERROR( VLOOKUP($A14, INDIRECT("JulR!$A$6:$ZZ$1048576"), MATCH(K$1, JulR!$6:$6, 0), FALSE), 0 ) + IFERROR( VLOOKUP($A14, INDIRECT("AgoR!$A$6:$ZZ$1048576"), MATCH(K$1, AgoR!$6:$6, 0), FALSE), 0 ) + IFERROR( VLOOKUP($A14, INDIRECT("SepR!$A$6:$ZZ$1048576"), MATCH(K$1, SepR!$6:$6, 0), FALSE), 0 ) + IFERROR( VLOOKUP($A14, INDIRECT("OctR!$A$6:$ZZ$1048576"), MATCH(K$1, OctR!$6:$6, 0), FALSE), 0 ) + IFERROR( VLOOKUP($A14, INDIRECT("NovR!$A$6:$ZZ$1048576"), MATCH(K$1, NovR!$6:$6, 0), FALSE), 0 ) + IFERROR( VLOOKUP($A14, INDIRECT("DicR!$A$6:$ZZ$1048576"), MATCH(K$1, DicR!$6:$6, 0), FALSE), 0 ) )} -> 0 | ... AY14: {=SUM( IFERROR( VLOOKUP($A14, INDIRECT("EneR!$A$6:$ZZ$1048576"), MATCH(AY$1, EneR!$6:$6, 0), FALSE), 0 ) + IFERROR( VLOOKUP($A14, INDIRECT("FebR!$A$6:$ZZ$1048576"), MATCH(AY$1, FebR!$6:$6, 0), FALSE), 0 ) + IFERROR( VLOOKUP($A14, INDIRECT("MarR!$A$6:$ZZ$1048576"), MATCH(AY$1, MarR!$6:$6, 0), FALSE), 0 ) + IFERROR( VLOOKUP($A14, INDIRECT("AbrR!$A$6:$ZZ$1048576"), MATCH(AY$1, AbrR!$6:$6, 0), FALSE), 0 ) + IFERROR( VLOOKUP($A14, INDIRECT("MayR!$A$6:$ZZ$1048576"), MATCH(AY$1, MayR!$6:$6, 0), FALSE), 0 ) + IFERROR( VLOOKUP($A14, INDIRECT("JunR!$A$6:$ZZ$1048576"), MATCH(AY$1, JunR!$6:$6, 0), FALSE), 0 ) + IFERROR( VLOOKUP($A14, INDIRECT("JulR!$A$6:$ZZ$1048576"), MATCH(AY$1, JulR!$6:$6, 0), FALSE), 0 ) + IFERROR( VLOOKUP($A14, INDIRECT("AgoR!$A$6:$ZZ$1048576"), MATCH(AY$1, AgoR!$6:$6, 0), FALSE), 0 ) + IFERROR( VLOOKUP($A14, INDIRECT("SepR!$A$6:$ZZ$1048576"), MATCH(AY$1, SepR!$6:$6, 0), FALSE), 0 ) + IFERROR( VLOOKUP($A14, INDIRECT("OctR!$A$6:$ZZ$1048576"), MATCH(AY$1, OctR!$6:$6, 0), FALSE), 0 ) + IFERROR( VLOOKUP($A14, INDIRECT("NovR!$A$6:$ZZ$1048576"), MATCH(AY$1, NovR!$6:$6, 0), FALSE), 0 ) + IFERROR( VLOOKUP($A14, INDIRECT("DicR!$A$6:$ZZ$1048576"), MATCH(AY$1, DicR!$6:$6, 0), FALSE), 0 ) )} -> 0
A15: =Menus!R7 | B15: =IFERROR(SUM(D15:AZ15),"") -> 0 | C15: =IFERROR(INDEX($D$1:$AQ132, MATCH($A15, $A$1:$A132, 0), MATCH(C$1, $D$1:AZ$1, 0)), "") | D15: {=SUM( IFERROR( VLOOKUP($A15, INDIRECT("EneR!$A$6:$ZZ$1048576"), MATCH(D$1, EneR!$6:$6, 0), FALSE), 0 ) + IFERROR( VLOOKUP($A15, INDIRECT("FebR!$A$6:$ZZ$1048576"), MATCH(D$1, FebR!$6:$6, 0), FALSE), 0 ) + IFERROR( VLOOKUP($A15, INDIRECT("MarR!$A$6:$ZZ$1048576"), MATCH(D$1, MarR!$6:$6, 0), FALSE), 0 ) + IFERROR( VLOOKUP($A15, INDIRECT("AbrR!$A$6:$ZZ$1048576"), MATCH(D$1, AbrR!$6:$6, 0), FALSE), 0 ) + IFERROR( VLOOKUP($A15, INDIRECT("MayR!$A$6:$ZZ$1048576"), MATCH(D$1, MayR!$6:$6, 0), FALSE), 0 ) + IFERROR( VLOOKUP($A15, INDIRECT("JunR!$A$6:$ZZ$1048576"), MATCH(D$1, JunR!$6:$6, 0), FALSE), 0 ) + IFERROR( VLOOKUP($A15, INDIRECT("JulR!$A$6:$ZZ$1048576"), MATCH(D$1, JulR!$6:$6, 0), FALSE), 0 ) + IFERROR( VLOOKUP($A15, INDIRECT("AgoR!$A$6:$ZZ$1048576"), MATCH(D$1, AgoR!$6:$6, 0), FALSE), 0 ) + IFERROR( VLOOKUP($A15, INDIRECT("SepR!$A$6:$ZZ$1048576"), MATCH(D$1, SepR!$6:$6, 0), FALSE), 0 ) + IFERROR( VLOOKUP($A15, INDIRECT("OctR!$A$6:$ZZ$1048576"), MATCH(D$1, OctR!$6:$6, 0), FALSE), 0 ) + IFERROR( VLOOKUP($A15, INDIRECT("NovR!$A$6:$ZZ$1048576"), MATCH(D$1, NovR!$6:$6, 0), FALSE), 0 ) + IFERROR( VLOOKUP($A15, INDIRECT("DicR!$A$6:$ZZ$1048576"), MATCH(D$1, DicR!$6:$6, 0), FALSE), 0 ) )} -> 0 | E15: {=SUM( IFERROR( VLOOKUP($A15, INDIRECT("EneR!$A$6:$ZZ$1048576"), MATCH(E$1, EneR!$6:$6, 0), FALSE), 0 ) + IFERROR( VLOOKUP($A15, INDIRECT("FebR!$A$6:$ZZ$1048576"), MATCH(E$1, FebR!$6:$6, 0), FALSE), 0 ) + IFERROR( VLOOKUP($A15, INDIRECT("MarR!$A$6:$ZZ$1048576"), MATCH(E$1, MarR!$6:$6, 0), FALSE), 0 ) + IFERROR( VLOOKUP($A15, INDIRECT("AbrR!$A$6:$ZZ$1048576"), MATCH(E$1, AbrR!$6:$6, 0), FALSE), 0 ) + IFERROR( VLOOKUP($A15, INDIRECT("MayR!$A$6:$ZZ$1048576"), MATCH(E$1, MayR!$6:$6, 0), FALSE), 0 ) + IFERROR( VLOOKUP($A15, INDIRECT("JunR!$A$6:$ZZ$1048576"), MATCH(E$1, JunR!$6:$6, 0), FALSE), 0 ) + IFERROR( VLOOKUP($A15, INDIRECT("JulR!$A$6:$ZZ$1048576"), MATCH(E$1, JulR!$6:$6, 0), FALSE), 0 ) + IFERROR( VLOOKUP($A15, INDIRECT("AgoR!$A$6:$ZZ$1048576"), MATCH(E$1, AgoR!$6:$6, 0), FALSE), 0 ) + IFERROR( VLOOKUP($A15, INDIRECT("SepR!$A$6:$ZZ$1048576"), MATCH(E$1, SepR!$6:$6, 0), FALSE), 0 ) + IFERROR( VLOOKUP($A15, INDIRECT("OctR!$A$6:$ZZ$1048576"), MATCH(E$1, OctR!$6:$6, 0), FALSE), 0 ) + IFERROR( VLOOKUP($A15, INDIRECT("NovR!$A$6:$ZZ$1048576"), MATCH(E$1, NovR!$6:$6, 0), FALSE), 0 ) + IFERROR( VLOOKUP($A15, INDIRECT("DicR!$A$6:$ZZ$1048576"), MATCH(E$1, DicR!$6:$6, 0), FALSE), 0 ) )} -> 0 | F15: {=SUM( IFERROR( VLOOKUP($A15, INDIRECT("EneR!$A$6:$ZZ$1048576"), MATCH(F$1, EneR!$6:$6, 0), FALSE), 0 ) + IFERROR( VLOOKUP($A15, INDIRECT("FebR!$A$6:$ZZ$1048576"), MATCH(F$1, FebR!$6:$6, 0), FALSE), 0 ) + IFERROR( VLOOKUP($A15, INDIRECT("MarR!$A$6:$ZZ$1048576"), MATCH(F$1, MarR!$6:$6, 0), FALSE), 0 ) + IFERROR( VLOOKUP($A15, INDIRECT("AbrR!$A$6:$ZZ$1048576"), MATCH(F$1, AbrR!$6:$6, 0), FALSE), 0 ) + IFERROR( VLOOKUP($A15, INDIRECT("MayR!$A$6:$ZZ$1048576"), MATCH(F$1, MayR!$6:$6, 0), FALSE), 0 ) + IFERROR( VLOOKUP($A15, INDIRECT("JunR!$A$6:$ZZ$1048576"), MATCH(F$1, JunR!$6:$6, 0), FALSE), 0 ) + IFERROR( VLOOKUP($A15, INDIRECT("JulR!$A$6:$ZZ$1048576"), MATCH(F$1, JulR!$6:$6, 0), FALSE), 0 ) + IFERROR( VLOOKUP($A15, INDIRECT("AgoR!$A$6:$ZZ$1048576"), MATCH(F$1, AgoR!$6:$6, 0), FALSE), 0 ) + IFERROR( VLOOKUP($A15, INDIRECT("SepR!$A$6:$ZZ$1048576"), MATCH(F$1, SepR!$6:$6, 0), FALSE), 0 ) + IFERROR( VLOOKUP($A15, INDIRECT("OctR!$A$6:$ZZ$1048576"), MATCH(F$1, OctR!$6:$6, 0), FALSE), 0 ) + IFERROR( VLOOKUP($A15, INDIRECT("NovR!$A$6:$ZZ$1048576"), MATCH(F$1, NovR!$6:$6, 0), FALSE), 0 ) + IFERROR( VLOOKUP($A15, INDIRECT("DicR!$A$6:$ZZ$1048576"), MATCH(F$1, DicR!$6:$6, 0), FALSE), 0 ) )} -> 0 | G15: {=SUM( IFERROR( VLOOKUP($A15, INDIRECT("EneR!$A$6:$ZZ$1048576"), MATCH(G$1, EneR!$6:$6, 0), FALSE), 0 ) + IFERROR( VLOOKUP($A15, INDIRECT("FebR!$A$6:$ZZ$1048576"), MATCH(G$1, FebR!$6:$6, 0), FALSE), 0 ) + IFERROR( VLOOKUP($A15, INDIRECT("MarR!$A$6:$ZZ$1048576"), MATCH(G$1, MarR!$6:$6, 0), FALSE), 0 ) + IFERROR( VLOOKUP($A15, INDIRECT("AbrR!$A$6:$ZZ$1048576"), MATCH(G$1, AbrR!$6:$6, 0), FALSE), 0 ) + IFERROR( VLOOKUP($A15, INDIRECT("MayR!$A$6:$ZZ$1048576"), MATCH(G$1, MayR!$6:$6, 0), FALSE), 0 ) + IFERROR( VLOOKUP($A15, INDIRECT("JunR!$A$6:$ZZ$1048576"), MATCH(G$1, JunR!$6:$6, 0), FALSE), 0 ) + IFERROR( VLOOKUP($A15, INDIRECT("JulR!$A$6:$ZZ$1048576"), MATCH(G$1, JulR!$6:$6, 0), FALSE), 0 ) + IFERROR( VLOOKUP($A15, INDIRECT("AgoR!$A$6:$ZZ$1048576"), MATCH(G$1, AgoR!$6:$6, 0), FALSE), 0 ) + IFERROR( VLOOKUP($A15, INDIRECT("SepR!$A$6:$ZZ$1048576"), MATCH(G$1, SepR!$6:$6, 0), FALSE), 0 ) + IFERROR( VLOOKUP($A15, INDIRECT("OctR!$A$6:$ZZ$1048576"), MATCH(G$1, OctR!$6:$6, 0), FALSE), 0 ) + IFERROR( VLOOKUP($A15, INDIRECT("NovR!$A$6:$ZZ$1048576"), MATCH(G$1, NovR!$6:$6, 0), FALSE), 0 ) + IFERROR( VLOOKUP($A15, INDIRECT("DicR!$A$6:$ZZ$1048576"), MATCH(G$1, DicR!$6:$6, 0), FALSE), 0 ) )} -> 0 | H15: {=SUM( IFERROR( VLOOKUP($A15, INDIRECT("EneR!$A$6:$ZZ$1048576"), MATCH(H$1, EneR!$6:$6, 0), FALSE), 0 ) + IFERROR( VLOOKUP($A15, INDIRECT("FebR!$A$6:$ZZ$1048576"), MATCH(H$1, FebR!$6:$6, 0), FALSE), 0 ) + IFERROR( VLOOKUP($A15, INDIRECT("MarR!$A$6:$ZZ$1048576"), MATCH(H$1, MarR!$6:$6, 0), FALSE), 0 ) + IFERROR( VLOOKUP($A15, INDIRECT("AbrR!$A$6:$ZZ$1048576"), MATCH(H$1, AbrR!$6:$6, 0), FALSE), 0 ) + IFERROR( VLOOKUP($A15, INDIRECT("MayR!$A$6:$ZZ$1048576"), MATCH(H$1, MayR!$6:$6, 0), FALSE), 0 ) + IFERROR( VLOOKUP($A15, INDIRECT("JunR!$A$6:$ZZ$1048576"), MATCH(H$1, JunR!$6:$6, 0), FALSE), 0 ) + IFERROR( VLOOKUP($A15, INDIRECT("JulR!$A$6:$ZZ$1048576"), MATCH(H$1, JulR!$6:$6, 0), FALSE), 0 ) + IFERROR( VLOOKUP($A15, INDIRECT("AgoR!$A$6:$ZZ$1048576"), MATCH(H$1, AgoR!$6:$6, 0), FALSE), 0 ) + IFERROR( VLOOKUP($A15, INDIRECT("SepR!$A$6:$ZZ$1048576"), MATCH(H$1, SepR!$6:$6, 0), FALSE), 0 ) + IFERROR( VLOOKUP($A15, INDIRECT("OctR!$A$6:$ZZ$1048576"), MATCH(H$1, OctR!$6:$6, 0), FALSE), 0 ) + IFERROR( VLOOKUP($A15, INDIRECT("NovR!$A$6:$ZZ$1048576"), MATCH(H$1, NovR!$6:$6, 0), FALSE), 0 ) + IFERROR( VLOOKUP($A15, INDIRECT("DicR!$A$6:$ZZ$1048576"), MATCH(H$1, DicR!$6:$6, 0), FALSE), 0 ) )} -> 0 | I15: {=SUM( IFERROR( VLOOKUP($A15, INDIRECT("EneR!$A$6:$ZZ$1048576"), MATCH(I$1, EneR!$6:$6, 0), FALSE), 0 ) + IFERROR( VLOOKUP($A15, INDIRECT("FebR!$A$6:$ZZ$1048576"), MATCH(I$1, FebR!$6:$6, 0), FALSE), 0 ) + IFERROR( VLOOKUP($A15, INDIRECT("MarR!$A$6:$ZZ$1048576"), MATCH(I$1, MarR!$6:$6, 0), FALSE), 0 ) + IFERROR( VLOOKUP($A15, INDIRECT("AbrR!$A$6:$ZZ$1048576"), MATCH(I$1, AbrR!$6:$6, 0), FALSE), 0 ) + IFERROR( VLOOKUP($A15, INDIRECT("MayR!$A$6:$ZZ$1048576"), MATCH(I$1, MayR!$6:$6, 0), FALSE), 0 ) + IFERROR( VLOOKUP($A15, INDIRECT("JunR!$A$6:$ZZ$1048576"), MATCH(I$1, JunR!$6:$6, 0), FALSE), 0 ) + IFERROR( VLOOKUP($A15, INDIRECT("JulR!$A$6:$ZZ$1048576"), MATCH(I$1, JulR!$6:$6, 0), FALSE), 0 ) + IFERROR( VLOOKUP($A15, INDIRECT("AgoR!$A$6:$ZZ$1048576"), MATCH(I$1, AgoR!$6:$6, 0), FALSE), 0 ) + IFERROR( VLOOKUP($A15, INDIRECT("SepR!$A$6:$ZZ$1048576"), MATCH(I$1, SepR!$6:$6, 0), FALSE), 0 ) + IFERROR( VLOOKUP($A15, INDIRECT("OctR!$A$6:$ZZ$1048576"), MATCH(I$1, OctR!$6:$6, 0), FALSE), 0 ) + IFERROR( VLOOKUP($A15, INDIRECT("NovR!$A$6:$ZZ$1048576"), MATCH(I$1, NovR!$6:$6, 0), FALSE), 0 ) + IFERROR( VLOOKUP($A15, INDIRECT("DicR!$A$6:$ZZ$1048576"), MATCH(I$1, DicR!$6:$6, 0), FALSE), 0 ) )} -> 0 | J15: {=SUM( IFERROR( VLOOKUP($A15, INDIRECT("EneR!$A$6:$ZZ$1048576"), MATCH(J$1, EneR!$6:$6, 0), FALSE), 0 ) + IFERROR( VLOOKUP($A15, INDIRECT("FebR!$A$6:$ZZ$1048576"), MATCH(J$1, FebR!$6:$6, 0), FALSE), 0 ) + IFERROR( VLOOKUP($A15, INDIRECT("MarR!$A$6:$ZZ$1048576"), MATCH(J$1, MarR!$6:$6, 0), FALSE), 0 ) + IFERROR( VLOOKUP($A15, INDIRECT("AbrR!$A$6:$ZZ$1048576"), MATCH(J$1, AbrR!$6:$6, 0), FALSE), 0 ) + IFERROR( VLOOKUP($A15, INDIRECT("MayR!$A$6:$ZZ$1048576"), MATCH(J$1, MayR!$6:$6, 0), FALSE), 0 ) + IFERROR( VLOOKUP($A15, INDIRECT("JunR!$A$6:$ZZ$1048576"), MATCH(J$1, JunR!$6:$6, 0), FALSE), 0 ) + IFERROR( VLOOKUP($A15, INDIRECT("JulR!$A$6:$ZZ$1048576"), MATCH(J$1, JulR!$6:$6, 0), FALSE), 0 ) + IFERROR( VLOOKUP($A15, INDIRECT("AgoR!$A$6:$ZZ$1048576"), MATCH(J$1, AgoR!$6:$6, 0), FALSE), 0 ) + IFERROR( VLOOKUP($A15, INDIRECT("SepR!$A$6:$ZZ$1048576"), MATCH(J$1, SepR!$6:$6, 0), FALSE), 0 ) + IFERROR( VLOOKUP($A15, INDIRECT("OctR!$A$6:$ZZ$1048576"), MATCH(J$1, OctR!$6:$6, 0), FALSE), 0 ) + IFERROR( VLOOKUP($A15, INDIRECT("NovR!$A$6:$ZZ$1048576"), MATCH(J$1, NovR!$6:$6, 0), FALSE), 0 ) + IFERROR( VLOOKUP($A15, INDIRECT("DicR!$A$6:$ZZ$1048576"), MATCH(J$1, DicR!$6:$6, 0), FALSE), 0 ) )} -> 0 | K15: {=SUM( IFERROR( VLOOKUP($A15, INDIRECT("EneR!$A$6:$ZZ$1048576"), MATCH(K$1, EneR!$6:$6, 0), FALSE), 0 ) + IFERROR( VLOOKUP($A15, INDIRECT("FebR!$A$6:$ZZ$1048576"), MATCH(K$1, FebR!$6:$6, 0), FALSE), 0 ) + IFERROR( VLOOKUP($A15, INDIRECT("MarR!$A$6:$ZZ$1048576"), MATCH(K$1, MarR!$6:$6, 0), FALSE), 0 ) + IFERROR( VLOOKUP($A15, INDIRECT("AbrR!$A$6:$ZZ$1048576"), MATCH(K$1, AbrR!$6:$6, 0), FALSE), 0 ) + IFERROR( VLOOKUP($A15, INDIRECT("MayR!$A$6:$ZZ$1048576"), MATCH(K$1, MayR!$6:$6, 0), FALSE), 0 ) + IFERROR( VLOOKUP($A15, INDIRECT("JunR!$A$6:$ZZ$1048576"), MATCH(K$1, JunR!$6:$6, 0), FALSE), 0 ) + IFERROR( VLOOKUP($A15, INDIRECT("JulR!$A$6:$ZZ$1048576"), MATCH(K$1, JulR!$6:$6, 0), FALSE), 0 ) + IFERROR( VLOOKUP($A15, INDIRECT("AgoR!$A$6:$ZZ$1048576"), MATCH(K$1, AgoR!$6:$6, 0), FALSE), 0 ) + IFERROR( VLOOKUP($A15, INDIRECT("SepR!$A$6:$ZZ$1048576"), MATCH(K$1, SepR!$6:$6, 0), FALSE), 0 ) + IFERROR( VLOOKUP($A15, INDIRECT("OctR!$A$6:$ZZ$1048576"), MATCH(K$1, OctR!$6:$6, 0), FALSE), 0 ) + IFERROR( VLOOKUP($A15, INDIRECT("NovR!$A$6:$ZZ$1048576"), MATCH(K$1, NovR!$6:$6, 0), FALSE), 0 ) + IFERROR( VLOOKUP($A15, INDIRECT("DicR!$A$6:$ZZ$1048576"), MATCH(K$1, DicR!$6:$6, 0), FALSE), 0 ) )} -> 0 | ... AY15: {=SUM( IFERROR( VLOOKUP($A15, INDIRECT("EneR!$A$6:$ZZ$1048576"), MATCH(AY$1, EneR!$6:$6, 0), FALSE), 0 ) + IFERROR( VLOOKUP($A15, INDIRECT("FebR!$A$6:$ZZ$1048576"), MATCH(AY$1, FebR!$6:$6, 0), FALSE), 0 ) + IFERROR( VLOOKUP($A15, INDIRECT("MarR!$A$6:$ZZ$1048576"), MATCH(AY$1, MarR!$6:$6, 0), FALSE), 0 ) + IFERROR( VLOOKUP($A15, INDIRECT("AbrR!$A$6:$ZZ$1048576"), MATCH(AY$1, AbrR!$6:$6, 0), FALSE), 0 ) + IFERROR( VLOOKUP($A15, INDIRECT("MayR!$A$6:$ZZ$1048576"), MATCH(AY$1, MayR!$6:$6, 0), FALSE), 0 ) + IFERROR( VLOOKUP($A15, INDIRECT("JunR!$A$6:$ZZ$1048576"), MATCH(AY$1, JunR!$6:$6, 0), FALSE), 0 ) + IFERROR( VLOOKUP($A15, INDIRECT("JulR!$A$6:$ZZ$1048576"), MATCH(AY$1, JulR!$6:$6, 0), FALSE), 0 ) + IFERROR( VLOOKUP($A15, INDIRECT("AgoR!$A$6:$ZZ$1048576"), MATCH(AY$1, AgoR!$6:$6, 0), FALSE), 0 ) + IFERROR( VLOOKUP($A15, INDIRECT("SepR!$A$6:$ZZ$1048576"), MATCH(AY$1, SepR!$6:$6, 0), FALSE), 0 ) + IFERROR( VLOOKUP($A15, INDIRECT("OctR!$A$6:$ZZ$1048576"), MATCH(AY$1, OctR!$6:$6, 0), FALSE), 0 ) + IFERROR( VLOOKUP($A15, INDIRECT("NovR!$A$6:$ZZ$1048576"), MATCH(AY$1, NovR!$6:$6, 0), FALSE), 0 ) + IFERROR( VLOOKUP($A15, INDIRECT("DicR!$A$6:$ZZ$1048576"), MATCH(AY$1, DicR!$6:$6, 0), FALSE), 0 ) )} -> 0
A16: =Menus!R8 | B16: =IFERROR(SUM(D16:AZ16),"") -> 0 | C16: =IFERROR(INDEX($D$1:$AQ133, MATCH($A16, $A$1:$A133, 0), MATCH(C$1, $D$1:AZ$1, 0)), "") | D16: {=SUM( IFERROR( VLOOKUP($A16, INDIRECT("EneR!$A$6:$ZZ$1048576"), MATCH(D$1, EneR!$6:$6, 0), FALSE), 0 ) + IFERROR( VLOOKUP($A16, INDIRECT("FebR!$A$6:$ZZ$1048576"), MATCH(D$1, FebR!$6:$6, 0), FALSE), 0 ) + IFERROR( VLOOKUP($A16, INDIRECT("MarR!$A$6:$ZZ$1048576"), MATCH(D$1, MarR!$6:$6, 0), FALSE), 0 ) + IFERROR( VLOOKUP($A16, INDIRECT("AbrR!$A$6:$ZZ$1048576"), MATCH(D$1, AbrR!$6:$6, 0), FALSE), 0 ) + IFERROR( VLOOKUP($A16, INDIRECT("MayR!$A$6:$ZZ$1048576"), MATCH(D$1, MayR!$6:$6, 0), FALSE), 0 ) + IFERROR( VLOOKUP($A16, INDIRECT("JunR!$A$6:$ZZ$1048576"), MATCH(D$1, JunR!$6:$6, 0), FALSE), 0 ) + IFERROR( VLOOKUP($A16, INDIRECT("JulR!$A$6:$ZZ$1048576"), MATCH(D$1, JulR!$6:$6, 0), FALSE), 0 ) + IFERROR( VLOOKUP($A16, INDIRECT("AgoR!$A$6:$ZZ$1048576"), MATCH(D$1, AgoR!$6:$6, 0), FALSE), 0 ) + IFERROR( VLOOKUP($A16, INDIRECT("SepR!$A$6:$ZZ$1048576"), MATCH(D$1, SepR!$6:$6, 0), FALSE), 0 ) + IFERROR( VLOOKUP($A16, INDIRECT("OctR!$A$6:$ZZ$1048576"), MATCH(D$1, OctR!$6:$6, 0), FALSE), 0 ) + IFERROR( VLOOKUP($A16, INDIRECT("NovR!$A$6:$ZZ$1048576"), MATCH(D$1, NovR!$6:$6, 0), FALSE), 0 ) + IFERROR( VLOOKUP($A16, INDIRECT("DicR!$A$6:$ZZ$1048576"), MATCH(D$1, DicR!$6:$6, 0), FALSE), 0 ) )} -> 0 | E16: {=SUM( IFERROR( VLOOKUP($A16, INDIRECT("EneR!$A$6:$ZZ$1048576"), MATCH(E$1, EneR!$6:$6, 0), FALSE), 0 ) + IFERROR( VLOOKUP($A16, INDIRECT("FebR!$A$6:$ZZ$1048576"), MATCH(E$1, FebR!$6:$6, 0), FALSE), 0 ) + IFERROR( VLOOKUP($A16, INDIRECT("MarR!$A$6:$ZZ$1048576"), MATCH(E$1, MarR!$6:$6, 0), FALSE), 0 ) + IFERROR( VLOOKUP($A16, INDIRECT("AbrR!$A$6:$ZZ$1048576"), MATCH(E$1, AbrR!$6:$6, 0), FALSE), 0 ) + IFERROR( VLOOKUP($A16, INDIRECT("MayR!$A$6:$ZZ$1048576"), MATCH(E$1, MayR!$6:$6, 0), FALSE), 0 ) + IFERROR( VLOOKUP($A16, INDIRECT("JunR!$A$6:$ZZ$1048576"), MATCH(E$1, JunR!$6:$6, 0), FALSE), 0 ) + IFERROR( VLOOKUP($A16, INDIRECT("JulR!$A$6:$ZZ$1048576"), MATCH(E$1, JulR!$6:$6, 0), FALSE), 0 ) + IFERROR( VLOOKUP($A16, INDIRECT("AgoR!$A$6:$ZZ$1048576"), MATCH(E$1, AgoR!$6:$6, 0), FALSE), 0 ) + IFERROR( VLOOKUP($A16, INDIRECT("SepR!$A$6:$ZZ$1048576"), MATCH(E$1, SepR!$6:$6, 0), FALSE), 0 ) + IFERROR( VLOOKUP($A16, INDIRECT("OctR!$A$6:$ZZ$1048576"), MATCH(E$1, OctR!$6:$6, 0), FALSE), 0 ) + IFERROR( VLOOKUP($A16, INDIRECT("NovR!$A$6:$ZZ$1048576"), MATCH(E$1, NovR!$6:$6, 0), FALSE), 0 ) + IFERROR( VLOOKUP($A16, INDIRECT("DicR!$A$6:$ZZ$1048576"), MATCH(E$1, DicR!$6:$6, 0), FALSE), 0 ) )} -> 0 | F16: {=SUM( IFERROR( VLOOKUP($A16, INDIRECT("EneR!$A$6:$ZZ$1048576"), MATCH(F$1, EneR!$6:$6, 0), FALSE), 0 ) + IFERROR( VLOOKUP($A16, INDIRECT("FebR!$A$6:$ZZ$1048576"), MATCH(F$1, FebR!$6:$6, 0), FALSE), 0 ) + IFERROR( VLOOKUP($A16, INDIRECT("MarR!$A$6:$ZZ$1048576"), MATCH(F$1, MarR!$6:$6, 0), FALSE), 0 ) + IFERROR( VLOOKUP($A16, INDIRECT("AbrR!$A$6:$ZZ$1048576"), MATCH(F$1, AbrR!$6:$6, 0), FALSE), 0 ) + IFERROR( VLOOKUP($A16, INDIRECT("MayR!$A$6:$ZZ$1048576"), MATCH(F$1, MayR!$6:$6, 0), FALSE), 0 ) + IFERROR( VLOOKUP($A16, INDIRECT("JunR!$A$6:$ZZ$1048576"), MATCH(F$1, JunR!$6:$6, 0), FALSE), 0 ) + IFERROR( VLOOKUP($A16, INDIRECT("JulR!$A$6:$ZZ$1048576"), MATCH(F$1, JulR!$6:$6, 0), FALSE), 0 ) + IFERROR( VLOOKUP($A16, INDIRECT("AgoR!$A$6:$ZZ$1048576"), MATCH(F$1, AgoR!$6:$6, 0), FALSE), 0 ) + IFERROR( VLOOKUP($A16, INDIRECT("SepR!$A$6:$ZZ$1048576"), MATCH(F$1, SepR!$6:$6, 0), FALSE), 0 ) + IFERROR( VLOOKUP($A16, INDIRECT("OctR!$A$6:$ZZ$1048576"), MATCH(F$1, OctR!$6:$6, 0), FALSE), 0 ) + IFERROR( VLOOKUP($A16, INDIRECT("NovR!$A$6:$ZZ$1048576"), MATCH(F$1, NovR!$6:$6, 0), FALSE), 0 ) + IFERROR( VLOOKUP($A16, INDIRECT("DicR!$A$6:$ZZ$1048576"), MATCH(F$1, DicR!$6:$6, 0), FALSE), 0 ) )} -> 0 | G16: {=SUM( IFERROR( VLOOKUP($A16, INDIRECT("EneR!$A$6:$ZZ$1048576"), MATCH(G$1, EneR!$6:$6, 0), FALSE), 0 ) + IFERROR( VLOOKUP($A16, INDIRECT("FebR!$A$6:$ZZ$1048576"), MATCH(G$1, FebR!$6:$6, 0), FALSE), 0 ) + IFERROR( VLOOKUP($A16, INDIRECT("MarR!$A$6:$ZZ$1048576"), MATCH(G$1, MarR!$6:$6, 0), FALSE), 0 ) + IFERROR( VLOOKUP($A16, INDIRECT("AbrR!$A$6:$ZZ$1048576"), MATCH(G$1, AbrR!$6:$6, 0), FALSE), 0 ) + IFERROR( VLOOKUP($A16, INDIRECT("MayR!$A$6:$ZZ$1048576"), MATCH(G$1, MayR!$6:$6, 0), FALSE), 0 ) + IFERROR( VLOOKUP($A16, INDIRECT("JunR!$A$6:$ZZ$1048576"), MATCH(G$1, JunR!$6:$6, 0), FALSE), 0 ) + IFERROR( VLOOKUP($A16, INDIRECT("JulR!$A$6:$ZZ$1048576"), MATCH(G$1, JulR!$6:$6, 0), FALSE), 0 ) + IFERROR( VLOOKUP($A16, INDIRECT("AgoR!$A$6:$ZZ$1048576"), MATCH(G$1, AgoR!$6:$6, 0), FALSE), 0 ) + IFERROR( VLOOKUP($A16, INDIRECT("SepR!$A$6:$ZZ$1048576"), MATCH(G$1, SepR!$6:$6, 0), FALSE), 0 ) + IFERROR( VLOOKUP($A16, INDIRECT("OctR!$A$6:$ZZ$1048576"), MATCH(G$1, OctR!$6:$6, 0), FALSE), 0 ) + IFERROR( VLOOKUP($A16, INDIRECT("NovR!$A$6:$ZZ$1048576"), MATCH(G$1, NovR!$6:$6, 0), FALSE), 0 ) + IFERROR( VLOOKUP($A16, INDIRECT("DicR!$A$6:$ZZ$1048576"), MATCH(G$1, DicR!$6:$6, 0), FALSE), 0 ) )} -> 0 | H16: {=SUM( IFERROR( VLOOKUP($A16, INDIRECT("EneR!$A$6:$ZZ$1048576"), MATCH(H$1, EneR!$6:$6, 0), FALSE), 0 ) + IFERROR( VLOOKUP($A16, INDIRECT("FebR!$A$6:$ZZ$1048576"), MATCH(H$1, FebR!$6:$6, 0), FALSE), 0 ) + IFERROR( VLOOKUP($A16, INDIRECT("MarR!$A$6:$ZZ$1048576"), MATCH(H$1, MarR!$6:$6, 0), FALSE), 0 ) + IFERROR( VLOOKUP($A16, INDIRECT("AbrR!$A$6:$ZZ$1048576"), MATCH(H$1, AbrR!$6:$6, 0), FALSE), 0 ) + IFERROR( VLOOKUP($A16, INDIRECT("MayR!$A$6:$ZZ$1048576"), MATCH(H$1, MayR!$6:$6, 0), FALSE), 0 ) + IFERROR( VLOOKUP($A16, INDIRECT("JunR!$A$6:$ZZ$1048576"), MATCH(H$1, JunR!$6:$6, 0), FALSE), 0 ) + IFERROR( VLOOKUP($A16, INDIRECT("JulR!$A$6:$ZZ$1048576"), MATCH(H$1, JulR!$6:$6, 0), FALSE), 0 ) + IFERROR( VLOOKUP($A16, INDIRECT("AgoR!$A$6:$ZZ$1048576"), MATCH(H$1, AgoR!$6:$6, 0), FALSE), 0 ) + IFERROR( VLOOKUP($A16, INDIRECT("SepR!$A$6:$ZZ$1048576"), MATCH(H$1, SepR!$6:$6, 0), FALSE), 0 ) + IFERROR( VLOOKUP($A16, INDIRECT("OctR!$A$6:$ZZ$1048576"), MATCH(H$1, OctR!$6:$6, 0), FALSE), 0 ) + IFERROR( VLOOKUP($A16, INDIRECT("NovR!$A$6:$ZZ$1048576"), MATCH(H$1, NovR!$6:$6, 0), FALSE), 0 ) + IFERROR( VLOOKUP($A16, INDIRECT("DicR!$A$6:$ZZ$1048576"), MATCH(H$1, DicR!$6:$6, 0), FALSE), 0 ) )} -> 0 | I16: {=SUM( IFERROR( VLOOKUP($A16, INDIRECT("EneR!$A$6:$ZZ$1048576"), MATCH(I$1, EneR!$6:$6, 0), FALSE), 0 ) + IFERROR( VLOOKUP($A16, INDIRECT("FebR!$A$6:$ZZ$1048576"), MATCH(I$1, FebR!$6:$6, 0), FALSE), 0 ) + IFERROR( VLOOKUP($A16, INDIRECT("MarR!$A$6:$ZZ$1048576"), MATCH(I$1, MarR!$6:$6, 0), FALSE), 0 ) + IFERROR( VLOOKUP($A16, INDIRECT("AbrR!$A$6:$ZZ$1048576"), MATCH(I$1, AbrR!$6:$6, 0), FALSE), 0 ) + IFERROR( VLOOKUP($A16, INDIRECT("MayR!$A$6:$ZZ$1048576"), MATCH(I$1, MayR!$6:$6, 0), FALSE), 0 ) + IFERROR( VLOOKUP($A16, INDIRECT("JunR!$A$6:$ZZ$1048576"), MATCH(I$1, JunR!$6:$6, 0), FALSE), 0 ) + IFERROR( VLOOKUP($A16, INDIRECT("JulR!$A$6:$ZZ$1048576"), MATCH(I$1, JulR!$6:$6, 0), FALSE), 0 ) + IFERROR( VLOOKUP($A16, INDIRECT("AgoR!$A$6:$ZZ$1048576"), MATCH(I$1, AgoR!$6:$6, 0), FALSE), 0 ) + IFERROR( VLOOKUP($A16, INDIRECT("SepR!$A$6:$ZZ$1048576"), MATCH(I$1, SepR!$6:$6, 0), FALSE), 0 ) + IFERROR( VLOOKUP($A16, INDIRECT("OctR!$A$6:$ZZ$1048576"), MATCH(I$1, OctR!$6:$6, 0), FALSE), 0 ) + IFERROR( VLOOKUP($A16, INDIRECT("NovR!$A$6:$ZZ$1048576"), MATCH(I$1, NovR!$6:$6, 0), FALSE), 0 ) + IFERROR( VLOOKUP($A16, INDIRECT("DicR!$A$6:$ZZ$1048576"), MATCH(I$1, DicR!$6:$6, 0), FALSE), 0 ) )} -> 0 | J16: {=SUM( IFERROR( VLOOKUP($A16, INDIRECT("EneR!$A$6:$ZZ$1048576"), MATCH(J$1, EneR!$6:$6, 0), FALSE), 0 ) + IFERROR( VLOOKUP($A16, INDIRECT("FebR!$A$6:$ZZ$1048576"), MATCH(J$1, FebR!$6:$6, 0), FALSE), 0 ) + IFERROR( VLOOKUP($A16, INDIRECT("MarR!$A$6:$ZZ$1048576"), MATCH(J$1, MarR!$6:$6, 0), FALSE), 0 ) + IFERROR( VLOOKUP($A16, INDIRECT("AbrR!$A$6:$ZZ$1048576"), MATCH(J$1, AbrR!$6:$6, 0), FALSE), 0 ) + IFERROR( VLOOKUP($A16, INDIRECT("MayR!$A$6:$ZZ$1048576"), MATCH(J$1, MayR!$6:$6, 0), FALSE), 0 ) + IFERROR( VLOOKUP($A16, INDIRECT("JunR!$A$6:$ZZ$1048576"), MATCH(J$1, JunR!$6:$6, 0), FALSE), 0 ) + IFERROR( VLOOKUP($A16, INDIRECT("JulR!$A$6:$ZZ$1048576"), MATCH(J$1, JulR!$6:$6, 0), FALSE), 0 ) + IFERROR( VLOOKUP($A16, INDIRECT("AgoR!$A$6:$ZZ$1048576"), MATCH(J$1, AgoR!$6:$6, 0), FALSE), 0 ) + IFERROR( VLOOKUP($A16, INDIRECT("SepR!$A$6:$ZZ$1048576"), MATCH(J$1, SepR!$6:$6, 0), FALSE), 0 ) + IFERROR( VLOOKUP($A16, INDIRECT("OctR!$A$6:$ZZ$1048576"), MATCH(J$1, OctR!$6:$6, 0), FALSE), 0 ) + IFERROR( VLOOKUP($A16, INDIRECT("NovR!$A$6:$ZZ$1048576"), MATCH(J$1, NovR!$6:$6, 0), FALSE), 0 ) + IFERROR( VLOOKUP($A16, INDIRECT("DicR!$A$6:$ZZ$1048576"), MATCH(J$1, DicR!$6:$6, 0), FALSE), 0 ) )} -> 0 | K16: {=SUM( IFERROR( VLOOKUP($A16, INDIRECT("EneR!$A$6:$ZZ$1048576"), MATCH(K$1, EneR!$6:$6, 0), FALSE), 0 ) + IFERROR( VLOOKUP($A16, INDIRECT("FebR!$A$6:$ZZ$1048576"), MATCH(K$1, FebR!$6:$6, 0), FALSE), 0 ) + IFERROR( VLOOKUP($A16, INDIRECT("MarR!$A$6:$ZZ$1048576"), MATCH(K$1, MarR!$6:$6, 0), FALSE), 0 ) + IFERROR( VLOOKUP($A16, INDIRECT("AbrR!$A$6:$ZZ$1048576"), MATCH(K$1, AbrR!$6:$6, 0), FALSE), 0 ) + IFERROR( VLOOKUP($A16, INDIRECT("MayR!$A$6:$ZZ$1048576"), MATCH(K$1, MayR!$6:$6, 0), FALSE), 0 ) + IFERROR( VLOOKUP($A16, INDIRECT("JunR!$A$6:$ZZ$1048576"), MATCH(K$1, JunR!$6:$6, 0), FALSE), 0 ) + IFERROR( VLOOKUP($A16, INDIRECT("JulR!$A$6:$ZZ$1048576"), MATCH(K$1, JulR!$6:$6, 0), FALSE), 0 ) + IFERROR( VLOOKUP($A16, INDIRECT("AgoR!$A$6:$ZZ$1048576"), MATCH(K$1, AgoR!$6:$6, 0), FALSE), 0 ) + IFERROR( VLOOKUP($A16, INDIRECT("SepR!$A$6:$ZZ$1048576"), MATCH(K$1, SepR!$6:$6, 0), FALSE), 0 ) + IFERROR( VLOOKUP($A16, INDIRECT("OctR!$A$6:$ZZ$1048576"), MATCH(K$1, OctR!$6:$6, 0), FALSE), 0 ) + IFERROR( VLOOKUP($A16, INDIRECT("NovR!$A$6:$ZZ$1048576"), MATCH(K$1, NovR!$6:$6, 0), FALSE), 0 ) + IFERROR( VLOOKUP($A16, INDIRECT("DicR!$A$6:$ZZ$1048576"), MATCH(K$1, DicR!$6:$6, 0), FALSE), 0 ) )} -> 0 | ... AY16: {=SUM( IFERROR( VLOOKUP($A16, INDIRECT("EneR!$A$6:$ZZ$1048576"), MATCH(AY$1, EneR!$6:$6, 0), FALSE), 0 ) + IFERROR( VLOOKUP($A16, INDIRECT("FebR!$A$6:$ZZ$1048576"), MATCH(AY$1, FebR!$6:$6, 0), FALSE), 0 ) + IFERROR( VLOOKUP($A16, INDIRECT("MarR!$A$6:$ZZ$1048576"), MATCH(AY$1, MarR!$6:$6, 0), FALSE), 0 ) + IFERROR( VLOOKUP($A16, INDIRECT("AbrR!$A$6:$ZZ$1048576"), MATCH(AY$1, AbrR!$6:$6, 0), FALSE), 0 ) + IFERROR( VLOOKUP($A16, INDIRECT("MayR!$A$6:$ZZ$1048576"), MATCH(AY$1, MayR!$6:$6, 0), FALSE), 0 ) + IFERROR( VLOOKUP($A16, INDIRECT("JunR!$A$6:$ZZ$1048576"), MATCH(AY$1, JunR!$6:$6, 0), FALSE), 0 ) + IFERROR( VLOOKUP($A16, INDIRECT("JulR!$A$6:$ZZ$1048576"), MATCH(AY$1, JulR!$6:$6, 0), FALSE), 0 ) + IFERROR( VLOOKUP($A16, INDIRECT("AgoR!$A$6:$ZZ$1048576"), MATCH(AY$1, AgoR!$6:$6, 0), FALSE), 0 ) + IFERROR( VLOOKUP($A16, INDIRECT("SepR!$A$6:$ZZ$1048576"), MATCH(AY$1, SepR!$6:$6, 0), FALSE), 0 ) + IFERROR( VLOOKUP($A16, INDIRECT("OctR!$A$6:$ZZ$1048576"), MATCH(AY$1, OctR!$6:$6, 0), FALSE), 0 ) + IFERROR( VLOOKUP($A16, INDIRECT("NovR!$A$6:$ZZ$1048576"), MATCH(AY$1, NovR!$6:$6, 0), FALSE), 0 ) + IFERROR( VLOOKUP($A16, INDIRECT("DicR!$A$6:$ZZ$1048576"), MATCH(AY$1, DicR!$6:$6, 0), FALSE), 0 ) )} -> 0
A17: =Menus!R9 | B17: =IFERROR(SUM(D17:AZ17),"") -> 0 | C17: =IFERROR(INDEX($D$1:$AQ134, MATCH($A17, $A$1:$A134, 0), MATCH(C$1, $D$1:AZ$1, 0)), "") | D17: {=SUM( IFERROR( VLOOKUP($A17, INDIRECT("EneR!$A$6:$ZZ$1048576"), MATCH(D$1, EneR!$6:$6, 0), FALSE), 0 ) + IFERROR( VLOOKUP($A17, INDIRECT("FebR!$A$6:$ZZ$1048576"), MATCH(D$1, FebR!$6:$6, 0), FALSE), 0 ) + IFERROR( VLOOKUP($A17, INDIRECT("MarR!$A$6:$ZZ$1048576"), MATCH(D$1, MarR!$6:$6, 0), FALSE), 0 ) + IFERROR( VLOOKUP($A17, INDIRECT("AbrR!$A$6:$ZZ$1048576"), MATCH(D$1, AbrR!$6:$6, 0), FALSE), 0 ) + IFERROR( VLOOKUP($A17, INDIRECT("MayR!$A$6:$ZZ$1048576"), MATCH(D$1, MayR!$6:$6, 0), FALSE), 0 ) + IFERROR( VLOOKUP($A17, INDIRECT("JunR!$A$6:$ZZ$1048576"), MATCH(D$1, JunR!$6:$6, 0), FALSE), 0 ) + IFERROR( VLOOKUP($A17, INDIRECT("JulR!$A$6:$ZZ$1048576"), MATCH(D$1, JulR!$6:$6, 0), FALSE), 0 ) + IFERROR( VLOOKUP($A17, INDIRECT("AgoR!$A$6:$ZZ$1048576"), MATCH(D$1, AgoR!$6:$6, 0), FALSE), 0 ) + IFERROR( VLOOKUP($A17, INDIRECT("SepR!$A$6:$ZZ$1048576"), MATCH(D$1, SepR!$6:$6, 0), FALSE), 0 ) + IFERROR( VLOOKUP($A17, INDIRECT("OctR!$A$6:$ZZ$1048576"), MATCH(D$1, OctR!$6:$6, 0), FALSE), 0 ) + IFERROR( VLOOKUP($A17, INDIRECT("NovR!$A$6:$ZZ$1048576"), MATCH(D$1, NovR!$6:$6, 0), FALSE), 0 ) + IFERROR( VLOOKUP($A17, INDIRECT("DicR!$A$6:$ZZ$1048576"), MATCH(D$1, DicR!$6:$6, 0), FALSE), 0 ) )} -> 0 | E17: {=SUM( IFERROR( VLOOKUP($A17, INDIRECT("EneR!$A$6:$ZZ$1048576"), MATCH(E$1, EneR!$6:$6, 0), FALSE), 0 ) + IFERROR( VLOOKUP($A17, INDIRECT("FebR!$A$6:$ZZ$1048576"), MATCH(E$1, FebR!$6:$6, 0), FALSE), 0 ) + IFERROR( VLOOKUP($A17, INDIRECT("MarR!$A$6:$ZZ$1048576"), MATCH(E$1, MarR!$6:$6, 0), FALSE), 0 ) + IFERROR( VLOOKUP($A17, INDIRECT("AbrR!$A$6:$ZZ$1048576"), MATCH(E$1, AbrR!$6:$6, 0), FALSE), 0 ) + IFERROR( VLOOKUP($A17, INDIRECT("MayR!$A$6:$ZZ$1048576"), MATCH(E$1, MayR!$6:$6, 0), FALSE), 0 ) + IFERROR( VLOOKUP($A17, INDIRECT("JunR!$A$6:$ZZ$1048576"), MATCH(E$1, JunR!$6:$6, 0), FALSE), 0 ) + IFERROR( VLOOKUP($A17, INDIRECT("JulR!$A$6:$ZZ$1048576"), MATCH(E$1, JulR!$6:$6, 0), FALSE), 0 ) + IFERROR( VLOOKUP($A17, INDIRECT("AgoR!$A$6:$ZZ$1048576"), MATCH(E$1, AgoR!$6:$6, 0), FALSE), 0 ) + IFERROR( VLOOKUP($A17, INDIRECT("SepR!$A$6:$ZZ$1048576"), MATCH(E$1, SepR!$6:$6, 0), FALSE), 0 ) + IFERROR( VLOOKUP($A17, INDIRECT("OctR!$A$6:$ZZ$1048576"), MATCH(E$1, OctR!$6:$6, 0), FALSE), 0 ) + IFERROR( VLOOKUP($A17, INDIRECT("NovR!$A$6:$ZZ$1048576"), MATCH(E$1, NovR!$6:$6, 0), FALSE), 0 ) + IFERROR( VLOOKUP($A17, INDIRECT("DicR!$A$6:$ZZ$1048576"), MATCH(E$1, DicR!$6:$6, 0), FALSE), 0 ) )} -> 0 | F17: {=SUM( IFERROR( VLOOKUP($A17, INDIRECT("EneR!$A$6:$ZZ$1048576"), MATCH(F$1, EneR!$6:$6, 0), FALSE), 0 ) + IFERROR( VLOOKUP($A17, INDIRECT("FebR!$A$6:$ZZ$1048576"), MATCH(F$1, FebR!$6:$6, 0), FALSE), 0 ) + IFERROR( VLOOKUP($A17, INDIRECT("MarR!$A$6:$ZZ$1048576"), MATCH(F$1, MarR!$6:$6, 0), FALSE), 0 ) + IFERROR( VLOOKUP($A17, INDIRECT("AbrR!$A$6:$ZZ$1048576"), MATCH(F$1, AbrR!$6:$6, 0), FALSE), 0 ) + IFERROR( VLOOKUP($A17, INDIRECT("MayR!$A$6:$ZZ$1048576"), MATCH(F$1, MayR!$6:$6, 0), FALSE), 0 ) + IFERROR( VLOOKUP($A17, INDIRECT("JunR!$A$6:$ZZ$1048576"), MATCH(F$1, JunR!$6:$6, 0), FALSE), 0 ) + IFERROR( VLOOKUP($A17, INDIRECT("JulR!$A$6:$ZZ$1048576"), MATCH(F$1, JulR!$6:$6, 0), FALSE), 0 ) + IFERROR( VLOOKUP($A17, INDIRECT("AgoR!$A$6:$ZZ$1048576"), MATCH(F$1, AgoR!$6:$6, 0), FALSE), 0 ) + IFERROR( VLOOKUP($A17, INDIRECT("SepR!$A$6:$ZZ$1048576"), MATCH(F$1, SepR!$6:$6, 0), FALSE), 0 ) + IFERROR( VLOOKUP($A17, INDIRECT("OctR!$A$6:$ZZ$1048576"), MATCH(F$1, OctR!$6:$6, 0), FALSE), 0 ) + IFERROR( VLOOKUP($A17, INDIRECT("NovR!$A$6:$ZZ$1048576"), MATCH(F$1, NovR!$6:$6, 0), FALSE), 0 ) + IFERROR( VLOOKUP($A17, INDIRECT("DicR!$A$6:$ZZ$1048576"), MATCH(F$1, DicR!$6:$6, 0), FALSE), 0 ) )} -> 0 | G17: {=SUM( IFERROR( VLOOKUP($A17, INDIRECT("EneR!$A$6:$ZZ$1048576"), MATCH(G$1, EneR!$6:$6, 0), FALSE), 0 ) + IFERROR( VLOOKUP($A17, INDIRECT("FebR!$A$6:$ZZ$1048576"), MATCH(G$1, FebR!$6:$6, 0), FALSE), 0 ) + IFERROR( VLOOKUP($A17, INDIRECT("MarR!$A$6:$ZZ$1048576"), MATCH(G$1, MarR!$6:$6, 0), FALSE), 0 ) + IFERROR( VLOOKUP($A17, INDIRECT("AbrR!$A$6:$ZZ$1048576"), MATCH(G$1, AbrR!$6:$6, 0), FALSE), 0 ) + IFERROR( VLOOKUP($A17, INDIRECT("MayR!$A$6:$ZZ$1048576"), MATCH(G$1, MayR!$6:$6, 0), FALSE), 0 ) + IFERROR( VLOOKUP($A17, INDIRECT("JunR!$A$6:$ZZ$1048576"), MATCH(G$1, JunR!$6:$6, 0), FALSE), 0 ) + IFERROR( VLOOKUP($A17, INDIRECT("JulR!$A$6:$ZZ$1048576"), MATCH(G$1, JulR!$6:$6, 0), FALSE), 0 ) + IFERROR( VLOOKUP($A17, INDIRECT("AgoR!$A$6:$ZZ$1048576"), MATCH(G$1, AgoR!$6:$6, 0), FALSE), 0 ) + IFERROR( VLOOKUP($A17, INDIRECT("SepR!$A$6:$ZZ$1048576"), MATCH(G$1, SepR!$6:$6, 0), FALSE), 0 ) + IFERROR( VLOOKUP($A17, INDIRECT("OctR!$A$6:$ZZ$1048576"), MATCH(G$1, OctR!$6:$6, 0), FALSE), 0 ) + IFERROR( VLOOKUP($A17, INDIRECT("NovR!$A$6:$ZZ$1048576"), MATCH(G$1, NovR!$6:$6, 0), FALSE), 0 ) + IFERROR( VLOOKUP($A17, INDIRECT("DicR!$A$6:$ZZ$1048576"), MATCH(G$1, DicR!$6:$6, 0), FALSE), 0 ) )} -> 0 | H17: {=SUM( IFERROR( VLOOKUP($A17, INDIRECT("EneR!$A$6:$ZZ$1048576"), MATCH(H$1, EneR!$6:$6, 0), FALSE), 0 ) + IFERROR( VLOOKUP($A17, INDIRECT("FebR!$A$6:$ZZ$1048576"), MATCH(H$1, FebR!$6:$6, 0), FALSE), 0 ) + IFERROR( VLOOKUP($A17, INDIRECT("MarR!$A$6:$ZZ$1048576"), MATCH(H$1, MarR!$6:$6, 0), FALSE), 0 ) + IFERROR( VLOOKUP($A17, INDIRECT("AbrR!$A$6:$ZZ$1048576"), MATCH(H$1, AbrR!$6:$6, 0), FALSE), 0 ) + IFERROR( VLOOKUP($A17, INDIRECT("MayR!$A$6:$ZZ$1048576"), MATCH(H$1, MayR!$6:$6, 0), FALSE), 0 ) + IFERROR( VLOOKUP($A17, INDIRECT("JunR!$A$6:$ZZ$1048576"), MATCH(H$1, JunR!$6:$6, 0), FALSE), 0 ) + IFERROR( VLOOKUP($A17, INDIRECT("JulR!$A$6:$ZZ$1048576"), MATCH(H$1, JulR!$6:$6, 0), FALSE), 0 ) + IFERROR( VLOOKUP($A17, INDIRECT("AgoR!$A$6:$ZZ$1048576"), MATCH(H$1, AgoR!$6:$6, 0), FALSE), 0 ) + IFERROR( VLOOKUP($A17, INDIRECT("SepR!$A$6:$ZZ$1048576"), MATCH(H$1, SepR!$6:$6, 0), FALSE), 0 ) + IFERROR( VLOOKUP($A17, INDIRECT("OctR!$A$6:$ZZ$1048576"), MATCH(H$1, OctR!$6:$6, 0), FALSE), 0 ) + IFERROR( VLOOKUP($A17, INDIRECT("NovR!$A$6:$ZZ$1048576"), MATCH(H$1, NovR!$6:$6, 0), FALSE), 0 ) + IFERROR( VLOOKUP($A17, INDIRECT("DicR!$A$6:$ZZ$1048576"), MATCH(H$1, DicR!$6:$6, 0), FALSE), 0 ) )} -> 0 | I17: {=SUM( IFERROR( VLOOKUP($A17, INDIRECT("EneR!$A$6:$ZZ$1048576"), MATCH(I$1, EneR!$6:$6, 0), FALSE), 0 ) + IFERROR( VLOOKUP($A17, INDIRECT("FebR!$A$6:$ZZ$1048576"), MATCH(I$1, FebR!$6:$6, 0), FALSE), 0 ) + IFERROR( VLOOKUP($A17, INDIRECT("MarR!$A$6:$ZZ$1048576"), MATCH(I$1, MarR!$6:$6, 0), FALSE), 0 ) + IFERROR( VLOOKUP($A17, INDIRECT("AbrR!$A$6:$ZZ$1048576"), MATCH(I$1, AbrR!$6:$6, 0), FALSE), 0 ) + IFERROR( VLOOKUP($A17, INDIRECT("MayR!$A$6:$ZZ$1048576"), MATCH(I$1, MayR!$6:$6, 0), FALSE), 0 ) + IFERROR( VLOOKUP($A17, INDIRECT("JunR!$A$6:$ZZ$1048576"), MATCH(I$1, JunR!$6:$6, 0), FALSE), 0 ) + IFERROR( VLOOKUP($A17, INDIRECT("JulR!$A$6:$ZZ$1048576"), MATCH(I$1, JulR!$6:$6, 0), FALSE), 0 ) + IFERROR( VLOOKUP($A17, INDIRECT("AgoR!$A$6:$ZZ$1048576"), MATCH(I$1, AgoR!$6:$6, 0), FALSE), 0 ) + IFERROR( VLOOKUP($A17, INDIRECT("SepR!$A$6:$ZZ$1048576"), MATCH(I$1, SepR!$6:$6, 0), FALSE), 0 ) + IFERROR( VLOOKUP($A17, INDIRECT("OctR!$A$6:$ZZ$1048576"), MATCH(I$1, OctR!$6:$6, 0), FALSE), 0 ) + IFERROR( VLOOKUP($A17, INDIRECT("NovR!$A$6:$ZZ$1048576"), MATCH(I$1, NovR!$6:$6, 0), FALSE), 0 ) + IFERROR( VLOOKUP($A17, INDIRECT("DicR!$A$6:$ZZ$1048576"), MATCH(I$1, DicR!$6:$6, 0), FALSE), 0 ) )} -> 0 | J17: {=SUM( IFERROR( VLOOKUP($A17, INDIRECT("EneR!$A$6:$ZZ$1048576"), MATCH(J$1, EneR!$6:$6, 0), FALSE), 0 ) + IFERROR( VLOOKUP($A17, INDIRECT("FebR!$A$6:$ZZ$1048576"), MATCH(J$1, FebR!$6:$6, 0), FALSE), 0 ) + IFERROR( VLOOKUP($A17, INDIRECT("MarR!$A$6:$ZZ$1048576"), MATCH(J$1, MarR!$6:$6, 0), FALSE), 0 ) + IFERROR( VLOOKUP($A17, INDIRECT("AbrR!$A$6:$ZZ$1048576"), MATCH(J$1, AbrR!$6:$6, 0), FALSE), 0 ) + IFERROR( VLOOKUP($A17, INDIRECT("MayR!$A$6:$ZZ$1048576"), MATCH(J$1, MayR!$6:$6, 0), FALSE), 0 ) + IFERROR( VLOOKUP($A17, INDIRECT("JunR!$A$6:$ZZ$1048576"), MATCH(J$1, JunR!$6:$6, 0), FALSE), 0 ) + IFERROR( VLOOKUP($A17, INDIRECT("JulR!$A$6:$ZZ$1048576"), MATCH(J$1, JulR!$6:$6, 0), FALSE), 0 ) + IFERROR( VLOOKUP($A17, INDIRECT("AgoR!$A$6:$ZZ$1048576"), MATCH(J$1, AgoR!$6:$6, 0), FALSE), 0 ) + IFERROR( VLOOKUP($A17, INDIRECT("SepR!$A$6:$ZZ$1048576"), MATCH(J$1, SepR!$6:$6, 0), FALSE), 0 ) + IFERROR( VLOOKUP($A17, INDIRECT("OctR!$A$6:$ZZ$1048576"), MATCH(J$1, OctR!$6:$6, 0), FALSE), 0 ) + IFERROR( VLOOKUP($A17, INDIRECT("NovR!$A$6:$ZZ$1048576"), MATCH(J$1, NovR!$6:$6, 0), FALSE), 0 ) + IFERROR( VLOOKUP($A17, INDIRECT("DicR!$A$6:$ZZ$1048576"), MATCH(J$1, DicR!$6:$6, 0), FALSE), 0 ) )} -> 0 | K17: {=SUM( IFERROR( VLOOKUP($A17, INDIRECT("EneR!$A$6:$ZZ$1048576"), MATCH(K$1, EneR!$6:$6, 0), FALSE), 0 ) + IFERROR( VLOOKUP($A17, INDIRECT("FebR!$A$6:$ZZ$1048576"), MATCH(K$1, FebR!$6:$6, 0), FALSE), 0 ) + IFERROR( VLOOKUP($A17, INDIRECT("MarR!$A$6:$ZZ$1048576"), MATCH(K$1, MarR!$6:$6, 0), FALSE), 0 ) + IFERROR( VLOOKUP($A17, INDIRECT("AbrR!$A$6:$ZZ$1048576"), MATCH(K$1, AbrR!$6:$6, 0), FALSE), 0 ) + IFERROR( VLOOKUP($A17, INDIRECT("MayR!$A$6:$ZZ$1048576"), MATCH(K$1, MayR!$6:$6, 0), FALSE), 0 ) + IFERROR( VLOOKUP($A17, INDIRECT("JunR!$A$6:$ZZ$1048576"), MATCH(K$1, JunR!$6:$6, 0), FALSE), 0 ) + IFERROR( VLOOKUP($A17, INDIRECT("JulR!$A$6:$ZZ$1048576"), MATCH(K$1, JulR!$6:$6, 0), FALSE), 0 ) + IFERROR( VLOOKUP($A17, INDIRECT("AgoR!$A$6:$ZZ$1048576"), MATCH(K$1, AgoR!$6:$6, 0), FALSE), 0 ) + IFERROR( VLOOKUP($A17, INDIRECT("SepR!$A$6:$ZZ$1048576"), MATCH(K$1, SepR!$6:$6, 0), FALSE), 0 ) + IFERROR( VLOOKUP($A17, INDIRECT("OctR!$A$6:$ZZ$1048576"), MATCH(K$1, OctR!$6:$6, 0), FALSE), 0 ) + IFERROR( VLOOKUP($A17, INDIRECT("NovR!$A$6:$ZZ$1048576"), MATCH(K$1, NovR!$6:$6, 0), FALSE), 0 ) + IFERROR( VLOOKUP($A17, INDIRECT("DicR!$A$6:$ZZ$1048576"), MATCH(K$1, DicR!$6:$6, 0), FALSE), 0 ) )} -> 0 | ... AY17: {=SUM( IFERROR( VLOOKUP($A17, INDIRECT("EneR!$A$6:$ZZ$1048576"), MATCH(AY$1, EneR!$6:$6, 0), FALSE), 0 ) + IFERROR( VLOOKUP($A17, INDIRECT("FebR!$A$6:$ZZ$1048576"), MATCH(AY$1, FebR!$6:$6, 0), FALSE), 0 ) + IFERROR( VLOOKUP($A17, INDIRECT("MarR!$A$6:$ZZ$1048576"), MATCH(AY$1, MarR!$6:$6, 0), FALSE), 0 ) + IFERROR( VLOOKUP($A17, INDIRECT("AbrR!$A$6:$ZZ$1048576"), MATCH(AY$1, AbrR!$6:$6, 0), FALSE), 0 ) + IFERROR( VLOOKUP($A17, INDIRECT("MayR!$A$6:$ZZ$1048576"), MATCH(AY$1, MayR!$6:$6, 0), FALSE), 0 ) + IFERROR( VLOOKUP($A17, INDIRECT("JunR!$A$6:$ZZ$1048576"), MATCH(AY$1, JunR!$6:$6, 0), FALSE), 0 ) + IFERROR( VLOOKUP($A17, INDIRECT("JulR!$A$6:$ZZ$1048576"), MATCH(AY$1, JulR!$6:$6, 0), FALSE), 0 ) + IFERROR( VLOOKUP($A17, INDIRECT("AgoR!$A$6:$ZZ$1048576"), MATCH(AY$1, AgoR!$6:$6, 0), FALSE), 0 ) + IFERROR( VLOOKUP($A17, INDIRECT("SepR!$A$6:$ZZ$1048576"), MATCH(AY$1, SepR!$6:$6, 0), FALSE), 0 ) + IFERROR( VLOOKUP($A17, INDIRECT("OctR!$A$6:$ZZ$1048576"), MATCH(AY$1, OctR!$6:$6, 0), FALSE), 0 ) + IFERROR( VLOOKUP($A17, INDIRECT("NovR!$A$6:$ZZ$1048576"), MATCH(AY$1, NovR!$6:$6, 0), FALSE), 0 ) + IFERROR( VLOOKUP($A17, INDIRECT("DicR!$A$6:$ZZ$1048576"), MATCH(AY$1, DicR!$6:$6, 0), FALSE), 0 ) )} -> 0
A18: =Menus!R10 | B18: =IFERROR(SUM(D18:AZ18),"") -> 0 | C18: =IFERROR(INDEX($D$1:$AQ135, MATCH($A18, $A$1:$A135, 0), MATCH(C$1, $D$1:AZ$1, 0)), "") | D18: {=SUM( IFERROR( VLOOKUP($A18, INDIRECT("EneR!$A$6:$ZZ$1048576"), MATCH(D$1, EneR!$6:$6, 0), FALSE), 0 ) + IFERROR( VLOOKUP($A18, INDIRECT("FebR!$A$6:$ZZ$1048576"), MATCH(D$1, FebR!$6:$6, 0), FALSE), 0 ) + IFERROR( VLOOKUP($A18, INDIRECT("MarR!$A$6:$ZZ$1048576"), MATCH(D$1, MarR!$6:$6, 0), FALSE), 0 ) + IFERROR( VLOOKUP($A18, INDIRECT("AbrR!$A$6:$ZZ$1048576"), MATCH(D$1, AbrR!$6:$6, 0), FALSE), 0 ) + IFERROR( VLOOKUP($A18, INDIRECT("MayR!$A$6:$ZZ$1048576"), MATCH(D$1, MayR!$6:$6, 0), FALSE), 0 ) + IFERROR( VLOOKUP($A18, INDIRECT("JunR!$A$6:$ZZ$1048576"), MATCH(D$1, JunR!$6:$6, 0), FALSE), 0 ) + IFERROR( VLOOKUP($A18, INDIRECT("JulR!$A$6:$ZZ$1048576"), MATCH(D$1, JulR!$6:$6, 0), FALSE), 0 ) + IFERROR( VLOOKUP($A18, INDIRECT("AgoR!$A$6:$ZZ$1048576"), MATCH(D$1, AgoR!$6:$6, 0), FALSE), 0 ) + IFERROR( VLOOKUP($A18, INDIRECT("SepR!$A$6:$ZZ$1048576"), MATCH(D$1, SepR!$6:$6, 0), FALSE), 0 ) + IFERROR( VLOOKUP($A18, INDIRECT("OctR!$A$6:$ZZ$1048576"), MATCH(D$1, OctR!$6:$6, 0), FALSE), 0 ) + IFERROR( VLOOKUP($A18, INDIRECT("NovR!$A$6:$ZZ$1048576"), MATCH(D$1, NovR!$6:$6, 0), FALSE), 0 ) + IFERROR( VLOOKUP($A18, INDIRECT("DicR!$A$6:$ZZ$1048576"), MATCH(D$1, DicR!$6:$6, 0), FALSE), 0 ) )} -> 0 | E18: {=SUM( IFERROR( VLOOKUP($A18, INDIRECT("EneR!$A$6:$ZZ$1048576"), MATCH(E$1, EneR!$6:$6, 0), FALSE), 0 ) + IFERROR( VLOOKUP($A18, INDIRECT("FebR!$A$6:$ZZ$1048576"), MATCH(E$1, FebR!$6:$6, 0), FALSE), 0 ) + IFERROR( VLOOKUP($A18, INDIRECT("MarR!$A$6:$ZZ$1048576"), MATCH(E$1, MarR!$6:$6, 0), FALSE), 0 ) + IFERROR( VLOOKUP($A18, INDIRECT("AbrR!$A$6:$ZZ$1048576"), MATCH(E$1, AbrR!$6:$6, 0), FALSE), 0 ) + IFERROR( VLOOKUP($A18, INDIRECT("MayR!$A$6:$ZZ$1048576"), MATCH(E$1, MayR!$6:$6, 0), FALSE), 0 ) + IFERROR( VLOOKUP($A18, INDIRECT("JunR!$A$6:$ZZ$1048576"), MATCH(E$1, JunR!$6:$6, 0), FALSE), 0 ) + IFERROR( VLOOKUP($A18, INDIRECT("JulR!$A$6:$ZZ$1048576"), MATCH(E$1, JulR!$6:$6, 0), FALSE), 0 ) + IFERROR( VLOOKUP($A18, INDIRECT("AgoR!$A$6:$ZZ$1048576"), MATCH(E$1, AgoR!$6:$6, 0), FALSE), 0 ) + IFERROR( VLOOKUP($A18, INDIRECT("SepR!$A$6:$ZZ$1048576"), MATCH(E$1, SepR!$6:$6, 0), FALSE), 0 ) + IFERROR( VLOOKUP($A18, INDIRECT("OctR!$A$6:$ZZ$1048576"), MATCH(E$1, OctR!$6:$6, 0), FALSE), 0 ) + IFERROR( VLOOKUP($A18, INDIRECT("NovR!$A$6:$ZZ$1048576"), MATCH(E$1, NovR!$6:$6, 0), FALSE), 0 ) + IFERROR( VLOOKUP($A18, INDIRECT("DicR!$A$6:$ZZ$1048576"), MATCH(E$1, DicR!$6:$6, 0), FALSE), 0 ) )} -> 0 | F18: {=SUM( IFERROR( VLOOKUP($A18, INDIRECT("EneR!$A$6:$ZZ$1048576"), MATCH(F$1, EneR!$6:$6, 0), FALSE), 0 ) + IFERROR( VLOOKUP($A18, INDIRECT("FebR!$A$6:$ZZ$1048576"), MATCH(F$1, FebR!$6:$6, 0), FALSE), 0 ) + IFERROR( VLOOKUP($A18, INDIRECT("MarR!$A$6:$ZZ$1048576"), MATCH(F$1, MarR!$6:$6, 0), FALSE), 0 ) + IFERROR( VLOOKUP($A18, INDIRECT("AbrR!$A$6:$ZZ$1048576"), MATCH(F$1, AbrR!$6:$6, 0), FALSE), 0 ) + IFERROR( VLOOKUP($A18, INDIRECT("MayR!$A$6:$ZZ$1048576"), MATCH(F$1, MayR!$6:$6, 0), FALSE), 0 ) + IFERROR( VLOOKUP($A18, INDIRECT("JunR!$A$6:$ZZ$1048576"), MATCH(F$1, JunR!$6:$6, 0), FALSE), 0 ) + IFERROR( VLOOKUP($A18, INDIRECT("JulR!$A$6:$ZZ$1048576"), MATCH(F$1, JulR!$6:$6, 0), FALSE), 0 ) + IFERROR( VLOOKUP($A18, INDIRECT("AgoR!$A$6:$ZZ$1048576"), MATCH(F$1, AgoR!$6:$6, 0), FALSE), 0 ) + IFERROR( VLOOKUP($A18, INDIRECT("SepR!$A$6:$ZZ$1048576"), MATCH(F$1, SepR!$6:$6, 0), FALSE), 0 ) + IFERROR( VLOOKUP($A18, INDIRECT("OctR!$A$6:$ZZ$1048576"), MATCH(F$1, OctR!$6:$6, 0), FALSE), 0 ) + IFERROR( VLOOKUP($A18, INDIRECT("NovR!$A$6:$ZZ$1048576"), MATCH(F$1, NovR!$6:$6, 0), FALSE), 0 ) + IFERROR( VLOOKUP($A18, INDIRECT("DicR!$A$6:$ZZ$1048576"), MATCH(F$1, DicR!$6:$6, 0), FALSE), 0 ) )} -> 0 | G18: {=SUM( IFERROR( VLOOKUP($A18, INDIRECT("EneR!$A$6:$ZZ$1048576"), MATCH(G$1, EneR!$6:$6, 0), FALSE), 0 ) + IFERROR( VLOOKUP($A18, INDIRECT("FebR!$A$6:$ZZ$1048576"), MATCH(G$1, FebR!$6:$6, 0), FALSE), 0 ) + IFERROR( VLOOKUP($A18, INDIRECT("MarR!$A$6:$ZZ$1048576"), MATCH(G$1, MarR!$6:$6, 0), FALSE), 0 ) + IFERROR( VLOOKUP($A18, INDIRECT("AbrR!$A$6:$ZZ$1048576"), MATCH(G$1, AbrR!$6:$6, 0), FALSE), 0 ) + IFERROR( VLOOKUP($A18, INDIRECT("MayR!$A$6:$ZZ$1048576"), MATCH(G$1, MayR!$6:$6, 0), FALSE), 0 ) + IFERROR( VLOOKUP($A18, INDIRECT("JunR!$A$6:$ZZ$1048576"), MATCH(G$1, JunR!$6:$6, 0), FALSE), 0 ) + IFERROR( VLOOKUP($A18, INDIRECT("JulR!$A$6:$ZZ$1048576"), MATCH(G$1, JulR!$6:$6, 0), FALSE), 0 ) + IFERROR( VLOOKUP($A18, INDIRECT("AgoR!$A$6:$ZZ$1048576"), MATCH(G$1, AgoR!$6:$6, 0), FALSE), 0 ) + IFERROR( VLOOKUP($A18, INDIRECT("SepR!$A$6:$ZZ$1048576"), MATCH(G$1, SepR!$6:$6, 0), FALSE), 0 ) + IFERROR( VLOOKUP($A18, INDIRECT("OctR!$A$6:$ZZ$1048576"), MATCH(G$1, OctR!$6:$6, 0), FALSE), 0 ) + IFERROR( VLOOKUP($A18, INDIRECT("NovR!$A$6:$ZZ$1048576"), MATCH(G$1, NovR!$6:$6, 0), FALSE), 0 ) + IFERROR( VLOOKUP($A18, INDIRECT("DicR!$A$6:$ZZ$1048576"), MATCH(G$1, DicR!$6:$6, 0), FALSE), 0 ) )} -> 0 | H18: {=SUM( IFERROR( VLOOKUP($A18, INDIRECT("EneR!$A$6:$ZZ$1048576"), MATCH(H$1, EneR!$6:$6, 0), FALSE), 0 ) + IFERROR( VLOOKUP($A18, INDIRECT("FebR!$A$6:$ZZ$1048576"), MATCH(H$1, FebR!$6:$6, 0), FALSE), 0 ) + IFERROR( VLOOKUP($A18, INDIRECT("MarR!$A$6:$ZZ$1048576"), MATCH(H$1, MarR!$6:$6, 0), FALSE), 0 ) + IFERROR( VLOOKUP($A18, INDIRECT("AbrR!$A$6:$ZZ$1048576"), MATCH(H$1, AbrR!$6:$6, 0), FALSE), 0 ) + IFERROR( VLOOKUP($A18, INDIRECT("MayR!$A$6:$ZZ$1048576"), MATCH(H$1, MayR!$6:$6, 0), FALSE), 0 ) + IFERROR( VLOOKUP($A18, INDIRECT("JunR!$A$6:$ZZ$1048576"), MATCH(H$1, JunR!$6:$6, 0), FALSE), 0 ) + IFERROR( VLOOKUP($A18, INDIRECT("JulR!$A$6:$ZZ$1048576"), MATCH(H$1, JulR!$6:$6, 0), FALSE), 0 ) + IFERROR( VLOOKUP($A18, INDIRECT("AgoR!$A$6:$ZZ$1048576"), MATCH(H$1, AgoR!$6:$6, 0), FALSE), 0 ) + IFERROR( VLOOKUP($A18, INDIRECT("SepR!$A$6:$ZZ$1048576"), MATCH(H$1, SepR!$6:$6, 0), FALSE), 0 ) + IFERROR( VLOOKUP($A18, INDIRECT("OctR!$A$6:$ZZ$1048576"), MATCH(H$1, OctR!$6:$6, 0), FALSE), 0 ) + IFERROR( VLOOKUP($A18, INDIRECT("NovR!$A$6:$ZZ$1048576"), MATCH(H$1, NovR!$6:$6, 0), FALSE), 0 ) + IFERROR( VLOOKUP($A18, INDIRECT("DicR!$A$6:$ZZ$1048576"), MATCH(H$1, DicR!$6:$6, 0), FALSE), 0 ) )} -> 0 | I18: {=SUM( IFERROR( VLOOKUP($A18, INDIRECT("EneR!$A$6:$ZZ$1048576"), MATCH(I$1, EneR!$6:$6, 0), FALSE), 0 ) + IFERROR( VLOOKUP($A18, INDIRECT("FebR!$A$6:$ZZ$1048576"), MATCH(I$1, FebR!$6:$6, 0), FALSE), 0 ) + IFERROR( VLOOKUP($A18, INDIRECT("MarR!$A$6:$ZZ$1048576"), MATCH(I$1, MarR!$6:$6, 0), FALSE), 0 ) + IFERROR( VLOOKUP($A18, INDIRECT("AbrR!$A$6:$ZZ$1048576"), MATCH(I$1, AbrR!$6:$6, 0), FALSE), 0 ) + IFERROR( VLOOKUP($A18, INDIRECT("MayR!$A$6:$ZZ$1048576"), MATCH(I$1, MayR!$6:$6, 0), FALSE), 0 ) + IFERROR( VLOOKUP($A18, INDIRECT("JunR!$A$6:$ZZ$1048576"), MATCH(I$1, JunR!$6:$6, 0), FALSE), 0 ) + IFERROR( VLOOKUP($A18, INDIRECT("JulR!$A$6:$ZZ$1048576"), MATCH(I$1, JulR!$6:$6, 0), FALSE), 0 ) + IFERROR( VLOOKUP($A18, INDIRECT("AgoR!$A$6:$ZZ$1048576"), MATCH(I$1, AgoR!$6:$6, 0), FALSE), 0 ) + IFERROR( VLOOKUP($A18, INDIRECT("SepR!$A$6:$ZZ$1048576"), MATCH(I$1, SepR!$6:$6, 0), FALSE), 0 ) + IFERROR( VLOOKUP($A18, INDIRECT("OctR!$A$6:$ZZ$1048576"), MATCH(I$1, OctR!$6:$6, 0), FALSE), 0 ) + IFERROR( VLOOKUP($A18, INDIRECT("NovR!$A$6:$ZZ$1048576"), MATCH(I$1, NovR!$6:$6, 0), FALSE), 0 ) + IFERROR( VLOOKUP($A18, INDIRECT("DicR!$A$6:$ZZ$1048576"), MATCH(I$1, DicR!$6:$6, 0), FALSE), 0 ) )} -> 0 | J18: {=SUM( IFERROR( VLOOKUP($A18, INDIRECT("EneR!$A$6:$ZZ$1048576"), MATCH(J$1, EneR!$6:$6, 0), FALSE), 0 ) + IFERROR( VLOOKUP($A18, INDIRECT("FebR!$A$6:$ZZ$1048576"), MATCH(J$1, FebR!$6:$6, 0), FALSE), 0 ) + IFERROR( VLOOKUP($A18, INDIRECT("MarR!$A$6:$ZZ$1048576"), MATCH(J$1, MarR!$6:$6, 0), FALSE), 0 ) + IFERROR( VLOOKUP($A18, INDIRECT("AbrR!$A$6:$ZZ$1048576"), MATCH(J$1, AbrR!$6:$6, 0), FALSE), 0 ) + IFERROR( VLOOKUP($A18, INDIRECT("MayR!$A$6:$ZZ$1048576"), MATCH(J$1, MayR!$6:$6, 0), FALSE), 0 ) + IFERROR( VLOOKUP($A18, INDIRECT("JunR!$A$6:$ZZ$1048576"), MATCH(J$1, JunR!$6:$6, 0), FALSE), 0 ) + IFERROR( VLOOKUP($A18, INDIRECT("JulR!$A$6:$ZZ$1048576"), MATCH(J$1, JulR!$6:$6, 0), FALSE), 0 ) + IFERROR( VLOOKUP($A18, INDIRECT("AgoR!$A$6:$ZZ$1048576"), MATCH(J$1, AgoR!$6:$6, 0), FALSE), 0 ) + IFERROR( VLOOKUP($A18, INDIRECT("SepR!$A$6:$ZZ$1048576"), MATCH(J$1, SepR!$6:$6, 0), FALSE), 0 ) + IFERROR( VLOOKUP($A18, INDIRECT("OctR!$A$6:$ZZ$1048576"), MATCH(J$1, OctR!$6:$6, 0), FALSE), 0 ) + IFERROR( VLOOKUP($A18, INDIRECT("NovR!$A$6:$ZZ$1048576"), MATCH(J$1, NovR!$6:$6, 0), FALSE), 0 ) + IFERROR( VLOOKUP($A18, INDIRECT("DicR!$A$6:$ZZ$1048576"), MATCH(J$1, DicR!$6:$6, 0), FALSE), 0 ) )} -> 0 | K18: {=SUM( IFERROR( VLOOKUP($A18, INDIRECT("EneR!$A$6:$ZZ$1048576"), MATCH(K$1, EneR!$6:$6, 0), FALSE), 0 ) + IFERROR( VLOOKUP($A18, INDIRECT("FebR!$A$6:$ZZ$1048576"), MATCH(K$1, FebR!$6:$6, 0), FALSE), 0 ) + IFERROR( VLOOKUP($A18, INDIRECT("MarR!$A$6:$ZZ$1048576"), MATCH(K$1, MarR!$6:$6, 0), FALSE), 0 ) + IFERROR( VLOOKUP($A18, INDIRECT("AbrR!$A$6:$ZZ$1048576"), MATCH(K$1, AbrR!$6:$6, 0), FALSE), 0 ) + IFERROR( VLOOKUP($A18, INDIRECT("MayR!$A$6:$ZZ$1048576"), MATCH(K$1, MayR!$6:$6, 0), FALSE), 0 ) + IFERROR( VLOOKUP($A18, INDIRECT("JunR!$A$6:$ZZ$1048576"), MATCH(K$1, JunR!$6:$6, 0), FALSE), 0 ) + IFERROR( VLOOKUP($A18, INDIRECT("JulR!$A$6:$ZZ$1048576"), MATCH(K$1, JulR!$6:$6, 0), FALSE), 0 ) + IFERROR( VLOOKUP($A18, INDIRECT("AgoR!$A$6:$ZZ$1048576"), MATCH(K$1, AgoR!$6:$6, 0), FALSE), 0 ) + IFERROR( VLOOKUP($A18, INDIRECT("SepR!$A$6:$ZZ$1048576"), MATCH(K$1, SepR!$6:$6, 0), FALSE), 0 ) + IFERROR( VLOOKUP($A18, INDIRECT("OctR!$A$6:$ZZ$1048576"), MATCH(K$1, OctR!$6:$6, 0), FALSE), 0 ) + IFERROR( VLOOKUP($A18, INDIRECT("NovR!$A$6:$ZZ$1048576"), MATCH(K$1, NovR!$6:$6, 0), FALSE), 0 ) + IFERROR( VLOOKUP($A18, INDIRECT("DicR!$A$6:$ZZ$1048576"), MATCH(K$1, DicR!$6:$6, 0), FALSE), 0 ) )} -> 0 | ... AY18: {=SUM( IFERROR( VLOOKUP($A18, INDIRECT("EneR!$A$6:$ZZ$1048576"), MATCH(AY$1, EneR!$6:$6, 0), FALSE), 0 ) + IFERROR( VLOOKUP($A18, INDIRECT("FebR!$A$6:$ZZ$1048576"), MATCH(AY$1, FebR!$6:$6, 0), FALSE), 0 ) + IFERROR( VLOOKUP($A18, INDIRECT("MarR!$A$6:$ZZ$1048576"), MATCH(AY$1, MarR!$6:$6, 0), FALSE), 0 ) + IFERROR( VLOOKUP($A18, INDIRECT("AbrR!$A$6:$ZZ$1048576"), MATCH(AY$1, AbrR!$6:$6, 0), FALSE), 0 ) + IFERROR( VLOOKUP($A18, INDIRECT("MayR!$A$6:$ZZ$1048576"), MATCH(AY$1, MayR!$6:$6, 0), FALSE), 0 ) + IFERROR( VLOOKUP($A18, INDIRECT("JunR!$A$6:$ZZ$1048576"), MATCH(AY$1, JunR!$6:$6, 0), FALSE), 0 ) + IFERROR( VLOOKUP($A18, INDIRECT("JulR!$A$6:$ZZ$1048576"), MATCH(AY$1, JulR!$6:$6, 0), FALSE), 0 ) + IFERROR( VLOOKUP($A18, INDIRECT("AgoR!$A$6:$ZZ$1048576"), MATCH(AY$1, AgoR!$6:$6, 0), FALSE), 0 ) + IFERROR( VLOOKUP($A18, INDIRECT("SepR!$A$6:$ZZ$1048576"), MATCH(AY$1, SepR!$6:$6, 0), FALSE), 0 ) + IFERROR( VLOOKUP($A18, INDIRECT("OctR!$A$6:$ZZ$1048576"), MATCH(AY$1, OctR!$6:$6, 0), FALSE), 0 ) + IFERROR( VLOOKUP($A18, INDIRECT("NovR!$A$6:$ZZ$1048576"), MATCH(AY$1, NovR!$6:$6, 0), FALSE), 0 ) + IFERROR( VLOOKUP($A18, INDIRECT("DicR!$A$6:$ZZ$1048576"), MATCH(AY$1, DicR!$6:$6, 0), FALSE), 0 ) )} -> 0
A19: =Menus!R11 | B19: =IFERROR(SUM(D19:AZ19),"") -> 0 | C19: =IFERROR(INDEX($D$1:$AQ136, MATCH($A19, $A$1:$A136, 0), MATCH(C$1, $D$1:AZ$1, 0)), "") | D19: {=SUM( IFERROR( VLOOKUP($A19, INDIRECT("EneR!$A$6:$ZZ$1048576"), MATCH(D$1, EneR!$6:$6, 0), FALSE), 0 ) + IFERROR( VLOOKUP($A19, INDIRECT("FebR!$A$6:$ZZ$1048576"), MATCH(D$1, FebR!$6:$6, 0), FALSE), 0 ) + IFERROR( VLOOKUP($A19, INDIRECT("MarR!$A$6:$ZZ$1048576"), MATCH(D$1, MarR!$6:$6, 0), FALSE), 0 ) + IFERROR( VLOOKUP($A19, INDIRECT("AbrR!$A$6:$ZZ$1048576"), MATCH(D$1, AbrR!$6:$6, 0), FALSE), 0 ) + IFERROR( VLOOKUP($A19, INDIRECT("MayR!$A$6:$ZZ$1048576"), MATCH(D$1, MayR!$6:$6, 0), FALSE), 0 ) + IFERROR( VLOOKUP($A19, INDIRECT("JunR!$A$6:$ZZ$1048576"), MATCH(D$1, JunR!$6:$6, 0), FALSE), 0 ) + IFERROR( VLOOKUP($A19, INDIRECT("JulR!$A$6:$ZZ$1048576"), MATCH(D$1, JulR!$6:$6, 0), FALSE), 0 ) + IFERROR( VLOOKUP($A19, INDIRECT("AgoR!$A$6:$ZZ$1048576"), MATCH(D$1, AgoR!$6:$6, 0), FALSE), 0 ) + IFERROR( VLOOKUP($A19, INDIRECT("SepR!$A$6:$ZZ$1048576"), MATCH(D$1, SepR!$6:$6, 0), FALSE), 0 ) + IFERROR( VLOOKUP($A19, INDIRECT("OctR!$A$6:$ZZ$1048576"), MATCH(D$1, OctR!$6:$6, 0), FALSE), 0 ) + IFERROR( VLOOKUP($A19, INDIRECT("NovR!$A$6:$ZZ$1048576"), MATCH(D$1, NovR!$6:$6, 0), FALSE), 0 ) + IFERROR( VLOOKUP($A19, INDIRECT("DicR!$A$6:$ZZ$1048576"), MATCH(D$1, DicR!$6:$6, 0), FALSE), 0 ) )} -> 0 | E19: {=SUM( IFERROR( VLOOKUP($A19, INDIRECT("EneR!$A$6:$ZZ$1048576"), MATCH(E$1, EneR!$6:$6, 0), FALSE), 0 ) + IFERROR( VLOOKUP($A19, INDIRECT("FebR!$A$6:$ZZ$1048576"), MATCH(E$1, FebR!$6:$6, 0), FALSE), 0 ) + IFERROR( VLOOKUP($A19, INDIRECT("MarR!$A$6:$ZZ$1048576"), MATCH(E$1, MarR!$6:$6, 0), FALSE), 0 ) + IFERROR( VLOOKUP($A19, INDIRECT("AbrR!$A$6:$ZZ$1048576"), MATCH(E$1, AbrR!$6:$6, 0), FALSE), 0 ) + IFERROR( VLOOKUP($A19, INDIRECT("MayR!$A$6:$ZZ$1048576"), MATCH(E$1, MayR!$6:$6, 0), FALSE), 0 ) + IFERROR( VLOOKUP($A19, INDIRECT("JunR!$A$6:$ZZ$1048576"), MATCH(E$1, JunR!$6:$6, 0), FALSE), 0 ) + IFERROR( VLOOKUP($A19, INDIRECT("JulR!$A$6:$ZZ$1048576"), MATCH(E$1, JulR!$6:$6, 0), FALSE), 0 ) + IFERROR( VLOOKUP($A19, INDIRECT("AgoR!$A$6:$ZZ$1048576"), MATCH(E$1, AgoR!$6:$6, 0), FALSE), 0 ) + IFERROR( VLOOKUP($A19, INDIRECT("SepR!$A$6:$ZZ$1048576"), MATCH(E$1, SepR!$6:$6, 0), FALSE), 0 ) + IFERROR( VLOOKUP($A19, INDIRECT("OctR!$A$6:$ZZ$1048576"), MATCH(E$1, OctR!$6:$6, 0), FALSE), 0 ) + IFERROR( VLOOKUP($A19, INDIRECT("NovR!$A$6:$ZZ$1048576"), MATCH(E$1, NovR!$6:$6, 0), FALSE), 0 ) + IFERROR( VLOOKUP($A19, INDIRECT("DicR!$A$6:$ZZ$1048576"), MATCH(E$1, DicR!$6:$6, 0), FALSE), 0 ) )} -> 0 | F19: {=SUM( IFERROR( VLOOKUP($A19, INDIRECT("EneR!$A$6:$ZZ$1048576"), MATCH(F$1, EneR!$6:$6, 0), FALSE), 0 ) + IFERROR( VLOOKUP($A19, INDIRECT("FebR!$A$6:$ZZ$1048576"), MATCH(F$1, FebR!$6:$6, 0), FALSE), 0 ) + IFERROR( VLOOKUP($A19, INDIRECT("MarR!$A$6:$ZZ$1048576"), MATCH(F$1, MarR!$6:$6, 0), FALSE), 0 ) + IFERROR( VLOOKUP($A19, INDIRECT("AbrR!$A$6:$ZZ$1048576"), MATCH(F$1, AbrR!$6:$6, 0), FALSE), 0 ) + IFERROR( VLOOKUP($A19, INDIRECT("MayR!$A$6:$ZZ$1048576"), MATCH(F$1, MayR!$6:$6, 0), FALSE), 0 ) + IFERROR( VLOOKUP($A19, INDIRECT("JunR!$A$6:$ZZ$1048576"), MATCH(F$1, JunR!$6:$6, 0), FALSE), 0 ) + IFERROR( VLOOKUP($A19, INDIRECT("JulR!$A$6:$ZZ$1048576"), MATCH(F$1, JulR!$6:$6, 0), FALSE), 0 ) + IFERROR( VLOOKUP($A19, INDIRECT("AgoR!$A$6:$ZZ$1048576"), MATCH(F$1, AgoR!$6:$6, 0), FALSE), 0 ) + IFERROR( VLOOKUP($A19, INDIRECT("SepR!$A$6:$ZZ$1048576"), MATCH(F$1, SepR!$6:$6, 0), FALSE), 0 ) + IFERROR( VLOOKUP($A19, INDIRECT("OctR!$A$6:$ZZ$1048576"), MATCH(F$1, OctR!$6:$6, 0), FALSE), 0 ) + IFERROR( VLOOKUP($A19, INDIRECT("NovR!$A$6:$ZZ$1048576"), MATCH(F$1, NovR!$6:$6, 0), FALSE), 0 ) + IFERROR( VLOOKUP($A19, INDIRECT("DicR!$A$6:$ZZ$1048576"), MATCH(F$1, DicR!$6:$6, 0), FALSE), 0 ) )} -> 0 | G19: {=SUM( IFERROR( VLOOKUP($A19, INDIRECT("EneR!$A$6:$ZZ$1048576"), MATCH(G$1, EneR!$6:$6, 0), FALSE), 0 ) + IFERROR( VLOOKUP($A19, INDIRECT("FebR!$A$6:$ZZ$1048576"), MATCH(G$1, FebR!$6:$6, 0), FALSE), 0 ) + IFERROR( VLOOKUP($A19, INDIRECT("MarR!$A$6:$ZZ$1048576"), MATCH(G$1, MarR!$6:$6, 0), FALSE), 0 ) + IFERROR( VLOOKUP($A19, INDIRECT("AbrR!$A$6:$ZZ$1048576"), MATCH(G$1, AbrR!$6:$6, 0), FALSE), 0 ) + IFERROR( VLOOKUP($A19, INDIRECT("MayR!$A$6:$ZZ$1048576"), MATCH(G$1, MayR!$6:$6, 0), FALSE), 0 ) + IFERROR( VLOOKUP($A19, INDIRECT("JunR!$A$6:$ZZ$1048576"), MATCH(G$1, JunR!$6:$6, 0), FALSE), 0 ) + IFERROR( VLOOKUP($A19, INDIRECT("JulR!$A$6:$ZZ$1048576"), MATCH(G$1, JulR!$6:$6, 0), FALSE), 0 ) + IFERROR( VLOOKUP($A19, INDIRECT("AgoR!$A$6:$ZZ$1048576"), MATCH(G$1, AgoR!$6:$6, 0), FALSE), 0 ) + IFERROR( VLOOKUP($A19, INDIRECT("SepR!$A$6:$ZZ$1048576"), MATCH(G$1, SepR!$6:$6, 0), FALSE), 0 ) + IFERROR( VLOOKUP($A19, INDIRECT("OctR!$A$6:$ZZ$1048576"), MATCH(G$1, OctR!$6:$6, 0), FALSE), 0 ) + IFERROR( VLOOKUP($A19, INDIRECT("NovR!$A$6:$ZZ$1048576"), MATCH(G$1, NovR!$6:$6, 0), FALSE), 0 ) + IFERROR( VLOOKUP($A19, INDIRECT("DicR!$A$6:$ZZ$1048576"), MATCH(G$1, DicR!$6:$6, 0), FALSE), 0 ) )} -> 0 | H19: {=SUM( IFERROR( VLOOKUP($A19, INDIRECT("EneR!$A$6:$ZZ$1048576"), MATCH(H$1, EneR!$6:$6, 0), FALSE), 0 ) + IFERROR( VLOOKUP($A19, INDIRECT("FebR!$A$6:$ZZ$1048576"), MATCH(H$1, FebR!$6:$6, 0), FALSE), 0 ) + IFERROR( VLOOKUP($A19, INDIRECT("MarR!$A$6:$ZZ$1048576"), MATCH(H$1, MarR!$6:$6, 0), FALSE), 0 ) + IFERROR( VLOOKUP($A19, INDIRECT("AbrR!$A$6:$ZZ$1048576"), MATCH(H$1, AbrR!$6:$6, 0), FALSE), 0 ) + IFERROR( VLOOKUP($A19, INDIRECT("MayR!$A$6:$ZZ$1048576"), MATCH(H$1, MayR!$6:$6, 0), FALSE), 0 ) + IFERROR( VLOOKUP($A19, INDIRECT("JunR!$A$6:$ZZ$1048576"), MATCH(H$1, JunR!$6:$6, 0), FALSE), 0 ) + IFERROR( VLOOKUP($A19, INDIRECT("JulR!$A$6:$ZZ$1048576"), MATCH(H$1, JulR!$6:$6, 0), FALSE), 0 ) + IFERROR( VLOOKUP($A19, INDIRECT("AgoR!$A$6:$ZZ$1048576"), MATCH(H$1, AgoR!$6:$6, 0), FALSE), 0 ) + IFERROR( VLOOKUP($A19, INDIRECT("SepR!$A$6:$ZZ$1048576"), MATCH(H$1, SepR!$6:$6, 0), FALSE), 0 ) + IFERROR( VLOOKUP($A19, INDIRECT("OctR!$A$6:$ZZ$1048576"), MATCH(H$1, OctR!$6:$6, 0), FALSE), 0 ) + IFERROR( VLOOKUP($A19, INDIRECT("NovR!$A$6:$ZZ$1048576"), MATCH(H$1, NovR!$6:$6, 0), FALSE), 0 ) + IFERROR( VLOOKUP($A19, INDIRECT("DicR!$A$6:$ZZ$1048576"), MATCH(H$1, DicR!$6:$6, 0), FALSE), 0 ) )} -> 0 | I19: {=SUM( IFERROR( VLOOKUP($A19, INDIRECT("EneR!$A$6:$ZZ$1048576"), MATCH(I$1, EneR!$6:$6, 0), FALSE), 0 ) + IFERROR( VLOOKUP($A19, INDIRECT("FebR!$A$6:$ZZ$1048576"), MATCH(I$1, FebR!$6:$6, 0), FALSE), 0 ) + IFERROR( VLOOKUP($A19, INDIRECT("MarR!$A$6:$ZZ$1048576"), MATCH(I$1, MarR!$6:$6, 0), FALSE), 0 ) + IFERROR( VLOOKUP($A19, INDIRECT("AbrR!$A$6:$ZZ$1048576"), MATCH(I$1, AbrR!$6:$6, 0), FALSE), 0 ) + IFERROR( VLOOKUP($A19, INDIRECT("MayR!$A$6:$ZZ$1048576"), MATCH(I$1, MayR!$6:$6, 0), FALSE), 0 ) + IFERROR( VLOOKUP($A19, INDIRECT("JunR!$A$6:$ZZ$1048576"), MATCH(I$1, JunR!$6:$6, 0), FALSE), 0 ) + IFERROR( VLOOKUP($A19, INDIRECT("JulR!$A$6:$ZZ$1048576"), MATCH(I$1, JulR!$6:$6, 0), FALSE), 0 ) + IFERROR( VLOOKUP($A19, INDIRECT("AgoR!$A$6:$ZZ$1048576"), MATCH(I$1, AgoR!$6:$6, 0), FALSE), 0 ) + IFERROR( VLOOKUP($A19, INDIRECT("SepR!$A$6:$ZZ$1048576"), MATCH(I$1, SepR!$6:$6, 0), FALSE), 0 ) + IFERROR( VLOOKUP($A19, INDIRECT("OctR!$A$6:$ZZ$1048576"), MATCH(I$1, OctR!$6:$6, 0), FALSE), 0 ) + IFERROR( VLOOKUP($A19, INDIRECT("NovR!$A$6:$ZZ$1048576"), MATCH(I$1, NovR!$6:$6, 0), FALSE), 0 ) + IFERROR( VLOOKUP($A19, INDIRECT("DicR!$A$6:$ZZ$1048576"), MATCH(I$1, DicR!$6:$6, 0), FALSE), 0 ) )} -> 0 | J19: {=SUM( IFERROR( VLOOKUP($A19, INDIRECT("EneR!$A$6:$ZZ$1048576"), MATCH(J$1, EneR!$6:$6, 0), FALSE), 0 ) + IFERROR( VLOOKUP($A19, INDIRECT("FebR!$A$6:$ZZ$1048576"), MATCH(J$1, FebR!$6:$6, 0), FALSE), 0 ) + IFERROR( VLOOKUP($A19, INDIRECT("MarR!$A$6:$ZZ$1048576"), MATCH(J$1, MarR!$6:$6, 0), FALSE), 0 ) + IFERROR( VLOOKUP($A19, INDIRECT("AbrR!$A$6:$ZZ$1048576"), MATCH(J$1, AbrR!$6:$6, 0), FALSE), 0 ) + IFERROR( VLOOKUP($A19, INDIRECT("MayR!$A$6:$ZZ$1048576"), MATCH(J$1, MayR!$6:$6, 0), FALSE), 0 ) + IFERROR( VLOOKUP($A19, INDIRECT("JunR!$A$6:$ZZ$1048576"), MATCH(J$1, JunR!$6:$6, 0), FALSE), 0 ) + IFERROR( VLOOKUP($A19, INDIRECT("JulR!$A$6:$ZZ$1048576"), MATCH(J$1, JulR!$6:$6, 0), FALSE), 0 ) + IFERROR( VLOOKUP($A19, INDIRECT("AgoR!$A$6:$ZZ$1048576"), MATCH(J$1, AgoR!$6:$6, 0), FALSE), 0 ) + IFERROR( VLOOKUP($A19, INDIRECT("SepR!$A$6:$ZZ$1048576"), MATCH(J$1, SepR!$6:$6, 0), FALSE), 0 ) + IFERROR( VLOOKUP($A19, INDIRECT("OctR!$A$6:$ZZ$1048576"), MATCH(J$1, OctR!$6:$6, 0), FALSE), 0 ) + IFERROR( VLOOKUP($A19, INDIRECT("NovR!$A$6:$ZZ$1048576"), MATCH(J$1, NovR!$6:$6, 0), FALSE), 0 ) + IFERROR( VLOOKUP($A19, INDIRECT("DicR!$A$6:$ZZ$1048576"), MATCH(J$1, DicR!$6:$6, 0), FALSE), 0 ) )} -> 0 | K19: {=SUM( IFERROR( VLOOKUP($A19, INDIRECT("EneR!$A$6:$ZZ$1048576"), MATCH(K$1, EneR!$6:$6, 0), FALSE), 0 ) + IFERROR( VLOOKUP($A19, INDIRECT("FebR!$A$6:$ZZ$1048576"), MATCH(K$1, FebR!$6:$6, 0), FALSE), 0 ) + IFERROR( VLOOKUP($A19, INDIRECT("MarR!$A$6:$ZZ$1048576"), MATCH(K$1, MarR!$6:$6, 0), FALSE), 0 ) + IFERROR( VLOOKUP($A19, INDIRECT("AbrR!$A$6:$ZZ$1048576"), MATCH(K$1, AbrR!$6:$6, 0), FALSE), 0 ) + IFERROR( VLOOKUP($A19, INDIRECT("MayR!$A$6:$ZZ$1048576"), MATCH(K$1, MayR!$6:$6, 0), FALSE), 0 ) + IFERROR( VLOOKUP($A19, INDIRECT("JunR!$A$6:$ZZ$1048576"), MATCH(K$1, JunR!$6:$6, 0), FALSE), 0 ) + IFERROR( VLOOKUP($A19, INDIRECT("JulR!$A$6:$ZZ$1048576"), MATCH(K$1, JulR!$6:$6, 0), FALSE), 0 ) + IFERROR( VLOOKUP($A19, INDIRECT("AgoR!$A$6:$ZZ$1048576"), MATCH(K$1, AgoR!$6:$6, 0), FALSE), 0 ) + IFERROR( VLOOKUP($A19, INDIRECT("SepR!$A$6:$ZZ$1048576"), MATCH(K$1, SepR!$6:$6, 0), FALSE), 0 ) + IFERROR( VLOOKUP($A19, INDIRECT("OctR!$A$6:$ZZ$1048576"), MATCH(K$1, OctR!$6:$6, 0), FALSE), 0 ) + IFERROR( VLOOKUP($A19, INDIRECT("NovR!$A$6:$ZZ$1048576"), MATCH(K$1, NovR!$6:$6, 0), FALSE), 0 ) + IFERROR( VLOOKUP($A19, INDIRECT("DicR!$A$6:$ZZ$1048576"), MATCH(K$1, DicR!$6:$6, 0), FALSE), 0 ) )} -> 0 | ... AY19: {=SUM( IFERROR( VLOOKUP($A19, INDIRECT("EneR!$A$6:$ZZ$1048576"), MATCH(AY$1, EneR!$6:$6, 0), FALSE), 0 ) + IFERROR( VLOOKUP($A19, INDIRECT("FebR!$A$6:$ZZ$1048576"), MATCH(AY$1, FebR!$6:$6, 0), FALSE), 0 ) + IFERROR( VLOOKUP($A19, INDIRECT("MarR!$A$6:$ZZ$1048576"), MATCH(AY$1, MarR!$6:$6, 0), FALSE), 0 ) + IFERROR( VLOOKUP($A19, INDIRECT("AbrR!$A$6:$ZZ$1048576"), MATCH(AY$1, AbrR!$6:$6, 0), FALSE), 0 ) + IFERROR( VLOOKUP($A19, INDIRECT("MayR!$A$6:$ZZ$1048576"), MATCH(AY$1, MayR!$6:$6, 0), FALSE), 0 ) + IFERROR( VLOOKUP($A19, INDIRECT("JunR!$A$6:$ZZ$1048576"), MATCH(AY$1, JunR!$6:$6, 0), FALSE), 0 ) + IFERROR( VLOOKUP($A19, INDIRECT("JulR!$A$6:$ZZ$1048576"), MATCH(AY$1, JulR!$6:$6, 0), FALSE), 0 ) + IFERROR( VLOOKUP($A19, INDIRECT("AgoR!$A$6:$ZZ$1048576"), MATCH(AY$1, AgoR!$6:$6, 0), FALSE), 0 ) + IFERROR( VLOOKUP($A19, INDIRECT("SepR!$A$6:$ZZ$1048576"), MATCH(AY$1, SepR!$6:$6, 0), FALSE), 0 ) + IFERROR( VLOOKUP($A19, INDIRECT("OctR!$A$6:$ZZ$1048576"), MATCH(AY$1, OctR!$6:$6, 0), FALSE), 0 ) + IFERROR( VLOOKUP($A19, INDIRECT("NovR!$A$6:$ZZ$1048576"), MATCH(AY$1, NovR!$6:$6, 0), FALSE), 0 ) + IFERROR( VLOOKUP($A19, INDIRECT("DicR!$A$6:$ZZ$1048576"), MATCH(AY$1, DicR!$6:$6, 0), FALSE), 0 ) )} -> 0
A20: =Menus!R12 | B20: =IFERROR(SUM(D20:AZ20),"") -> 0 | C20: =IFERROR(INDEX($D$1:$AQ137, MATCH($A20, $A$1:$A137, 0), MATCH(C$1, $D$1:AZ$1, 0)), "") | D20: {=SUM( IFERROR( VLOOKUP($A20, INDIRECT("EneR!$A$6:$ZZ$1048576"), MATCH(D$1, EneR!$6:$6, 0), FALSE), 0 ) + IFERROR( VLOOKUP($A20, INDIRECT("FebR!$A$6:$ZZ$1048576"), MATCH(D$1, FebR!$6:$6, 0), FALSE), 0 ) + IFERROR( VLOOKUP($A20, INDIRECT("MarR!$A$6:$ZZ$1048576"), MATCH(D$1, MarR!$6:$6, 0), FALSE), 0 ) + IFERROR( VLOOKUP($A20, INDIRECT("AbrR!$A$6:$ZZ$1048576"), MATCH(D$1, AbrR!$6:$6, 0), FALSE), 0 ) + IFERROR( VLOOKUP($A20, INDIRECT("MayR!$A$6:$ZZ$1048576"), MATCH(D$1, MayR!$6:$6, 0), FALSE), 0 ) + IFERROR( VLOOKUP($A20, INDIRECT("JunR!$A$6:$ZZ$1048576"), MATCH(D$1, JunR!$6:$6, 0), FALSE), 0 ) + IFERROR( VLOOKUP($A20, INDIRECT("JulR!$A$6:$ZZ$1048576"), MATCH(D$1, JulR!$6:$6, 0), FALSE), 0 ) + IFERROR( VLOOKUP($A20, INDIRECT("AgoR!$A$6:$ZZ$1048576"), MATCH(D$1, AgoR!$6:$6, 0), FALSE), 0 ) + IFERROR( VLOOKUP($A20, INDIRECT("SepR!$A$6:$ZZ$1048576"), MATCH(D$1, SepR!$6:$6, 0), FALSE), 0 ) + IFERROR( VLOOKUP($A20, INDIRECT("OctR!$A$6:$ZZ$1048576"), MATCH(D$1, OctR!$6:$6, 0), FALSE), 0 ) + IFERROR( VLOOKUP($A20, INDIRECT("NovR!$A$6:$ZZ$1048576"), MATCH(D$1, NovR!$6:$6, 0), FALSE), 0 ) + IFERROR( VLOOKUP($A20, INDIRECT("DicR!$A$6:$ZZ$1048576"), MATCH(D$1, DicR!$6:$6, 0), FALSE), 0 ) )} -> 0 | E20: {=SUM( IFERROR( VLOOKUP($A20, INDIRECT("EneR!$A$6:$ZZ$1048576"), MATCH(E$1, EneR!$6:$6, 0), FALSE), 0 ) + IFERROR( VLOOKUP($A20, INDIRECT("FebR!$A$6:$ZZ$1048576"), MATCH(E$1, FebR!$6:$6, 0), FALSE), 0 ) + IFERROR( VLOOKUP($A20, INDIRECT("MarR!$A$6:$ZZ$1048576"), MATCH(E$1, MarR!$6:$6, 0), FALSE), 0 ) + IFERROR( VLOOKUP($A20, INDIRECT("AbrR!$A$6:$ZZ$1048576"), MATCH(E$1, AbrR!$6:$6, 0), FALSE), 0 ) + IFERROR( VLOOKUP($A20, INDIRECT("MayR!$A$6:$ZZ$1048576"), MATCH(E$1, MayR!$6:$6, 0), FALSE), 0 ) + IFERROR( VLOOKUP($A20, INDIRECT("JunR!$A$6:$ZZ$1048576"), MATCH(E$1, JunR!$6:$6, 0), FALSE), 0 ) + IFERROR( VLOOKUP($A20, INDIRECT("JulR!$A$6:$ZZ$1048576"), MATCH(E$1, JulR!$6:$6, 0), FALSE), 0 ) + IFERROR( VLOOKUP($A20, INDIRECT("AgoR!$A$6:$ZZ$1048576"), MATCH(E$1, AgoR!$6:$6, 0), FALSE), 0 ) + IFERROR( VLOOKUP($A20, INDIRECT("SepR!$A$6:$ZZ$1048576"), MATCH(E$1, SepR!$6:$6, 0), FALSE), 0 ) + IFERROR( VLOOKUP($A20, INDIRECT("OctR!$A$6:$ZZ$1048576"), MATCH(E$1, OctR!$6:$6, 0), FALSE), 0 ) + IFERROR( VLOOKUP($A20, INDIRECT("NovR!$A$6:$ZZ$1048576"), MATCH(E$1, NovR!$6:$6, 0), FALSE), 0 ) + IFERROR( VLOOKUP($A20, INDIRECT("DicR!$A$6:$ZZ$1048576"), MATCH(E$1, DicR!$6:$6, 0), FALSE), 0 ) )} -> 0 | F20: {=SUM( IFERROR( VLOOKUP($A20, INDIRECT("EneR!$A$6:$ZZ$1048576"), MATCH(F$1, EneR!$6:$6, 0), FALSE), 0 ) + IFERROR( VLOOKUP($A20, INDIRECT("FebR!$A$6:$ZZ$1048576"), MATCH(F$1, FebR!$6:$6, 0), FALSE), 0 ) + IFERROR( VLOOKUP($A20, INDIRECT("MarR!$A$6:$ZZ$1048576"), MATCH(F$1, MarR!$6:$6, 0), FALSE), 0 ) + IFERROR( VLOOKUP($A20, INDIRECT("AbrR!$A$6:$ZZ$1048576"), MATCH(F$1, AbrR!$6:$6, 0), FALSE), 0 ) + IFERROR( VLOOKUP($A20, INDIRECT("MayR!$A$6:$ZZ$1048576"), MATCH(F$1, MayR!$6:$6, 0), FALSE), 0 ) + IFERROR( VLOOKUP($A20, INDIRECT("JunR!$A$6:$ZZ$1048576"), MATCH(F$1, JunR!$6:$6, 0), FALSE), 0 ) + IFERROR( VLOOKUP($A20, INDIRECT("JulR!$A$6:$ZZ$1048576"), MATCH(F$1, JulR!$6:$6, 0), FALSE), 0 ) + IFERROR( VLOOKUP($A20, INDIRECT("AgoR!$A$6:$ZZ$1048576"), MATCH(F$1, AgoR!$6:$6, 0), FALSE), 0 ) + IFERROR( VLOOKUP($A20, INDIRECT("SepR!$A$6:$ZZ$1048576"), MATCH(F$1, SepR!$6:$6, 0), FALSE), 0 ) + IFERROR( VLOOKUP($A20, INDIRECT("OctR!$A$6:$ZZ$1048576"), MATCH(F$1, OctR!$6:$6, 0), FALSE), 0 ) + IFERROR( VLOOKUP($A20, INDIRECT("NovR!$A$6:$ZZ$1048576"), MATCH(F$1, NovR!$6:$6, 0), FALSE), 0 ) + IFERROR( VLOOKUP($A20, INDIRECT("DicR!$A$6:$ZZ$1048576"), MATCH(F$1, DicR!$6:$6, 0), FALSE), 0 ) )} -> 0 | G20: {=SUM( IFERROR( VLOOKUP($A20, INDIRECT("EneR!$A$6:$ZZ$1048576"), MATCH(G$1, EneR!$6:$6, 0), FALSE), 0 ) + IFERROR( VLOOKUP($A20, INDIRECT("FebR!$A$6:$ZZ$1048576"), MATCH(G$1, FebR!$6:$6, 0), FALSE), 0 ) + IFERROR( VLOOKUP($A20, INDIRECT("MarR!$A$6:$ZZ$1048576"), MATCH(G$1, MarR!$6:$6, 0), FALSE), 0 ) + IFERROR( VLOOKUP($A20, INDIRECT("AbrR!$A$6:$ZZ$1048576"), MATCH(G$1, AbrR!$6:$6, 0), FALSE), 0 ) + IFERROR( VLOOKUP($A20, INDIRECT("MayR!$A$6:$ZZ$1048576"), MATCH(G$1, MayR!$6:$6, 0), FALSE), 0 ) + IFERROR( VLOOKUP($A20, INDIRECT("JunR!$A$6:$ZZ$1048576"), MATCH(G$1, JunR!$6:$6, 0), FALSE), 0 ) + IFERROR( VLOOKUP($A20, INDIRECT("JulR!$A$6:$ZZ$1048576"), MATCH(G$1, JulR!$6:$6, 0), FALSE), 0 ) + IFERROR( VLOOKUP($A20, INDIRECT("AgoR!$A$6:$ZZ$1048576"), MATCH(G$1, AgoR!$6:$6, 0), FALSE), 0 ) + IFERROR( VLOOKUP($A20, INDIRECT("SepR!$A$6:$ZZ$1048576"), MATCH(G$1, SepR!$6:$6, 0), FALSE), 0 ) + IFERROR( VLOOKUP($A20, INDIRECT("OctR!$A$6:$ZZ$1048576"), MATCH(G$1, OctR!$6:$6, 0), FALSE), 0 ) + IFERROR( VLOOKUP($A20, INDIRECT("NovR!$A$6:$ZZ$1048576"), MATCH(G$1, NovR!$6:$6, 0), FALSE), 0 ) + IFERROR( VLOOKUP($A20, INDIRECT("DicR!$A$6:$ZZ$1048576"), MATCH(G$1, DicR!$6:$6, 0), FALSE), 0 ) )} -> 0 | H20: {=SUM( IFERROR( VLOOKUP($A20, INDIRECT("EneR!$A$6:$ZZ$1048576"), MATCH(H$1, EneR!$6:$6, 0), FALSE), 0 ) + IFERROR( VLOOKUP($A20, INDIRECT("FebR!$A$6:$ZZ$1048576"), MATCH(H$1, FebR!$6:$6, 0), FALSE), 0 ) + IFERROR( VLOOKUP($A20, INDIRECT("MarR!$A$6:$ZZ$1048576"), MATCH(H$1, MarR!$6:$6, 0), FALSE), 0 ) + IFERROR( VLOOKUP($A20, INDIRECT("AbrR!$A$6:$ZZ$1048576"), MATCH(H$1, AbrR!$6:$6, 0), FALSE), 0 ) + IFERROR( VLOOKUP($A20, INDIRECT("MayR!$A$6:$ZZ$1048576"), MATCH(H$1, MayR!$6:$6, 0), FALSE), 0 ) + IFERROR( VLOOKUP($A20, INDIRECT("JunR!$A$6:$ZZ$1048576"), MATCH(H$1, JunR!$6:$6, 0), FALSE), 0 ) + IFERROR( VLOOKUP($A20, INDIRECT("JulR!$A$6:$ZZ$1048576"), MATCH(H$1, JulR!$6:$6, 0), FALSE), 0 ) + IFERROR( VLOOKUP($A20, INDIRECT("AgoR!$A$6:$ZZ$1048576"), MATCH(H$1, AgoR!$6:$6, 0), FALSE), 0 ) + IFERROR( VLOOKUP($A20, INDIRECT("SepR!$A$6:$ZZ$1048576"), MATCH(H$1, SepR!$6:$6, 0), FALSE), 0 ) + IFERROR( VLOOKUP($A20, INDIRECT("OctR!$A$6:$ZZ$1048576"), MATCH(H$1, OctR!$6:$6, 0), FALSE), 0 ) + IFERROR( VLOOKUP($A20, INDIRECT("NovR!$A$6:$ZZ$1048576"), MATCH(H$1, NovR!$6:$6, 0), FALSE), 0 ) + IFERROR( VLOOKUP($A20, INDIRECT("DicR!$A$6:$ZZ$1048576"), MATCH(H$1, DicR!$6:$6, 0), FALSE), 0 ) )} -> 0 | I20: {=SUM( IFERROR( VLOOKUP($A20, INDIRECT("EneR!$A$6:$ZZ$1048576"), MATCH(I$1, EneR!$6:$6, 0), FALSE), 0 ) + IFERROR( VLOOKUP($A20, INDIRECT("FebR!$A$6:$ZZ$1048576"), MATCH(I$1, FebR!$6:$6, 0), FALSE), 0 ) + IFERROR( VLOOKUP($A20, INDIRECT("MarR!$A$6:$ZZ$1048576"), MATCH(I$1, MarR!$6:$6, 0), FALSE), 0 ) + IFERROR( VLOOKUP($A20, INDIRECT("AbrR!$A$6:$ZZ$1048576"), MATCH(I$1, AbrR!$6:$6, 0), FALSE), 0 ) + IFERROR( VLOOKUP($A20, INDIRECT("MayR!$A$6:$ZZ$1048576"), MATCH(I$1, MayR!$6:$6, 0), FALSE), 0 ) + IFERROR( VLOOKUP($A20, INDIRECT("JunR!$A$6:$ZZ$1048576"), MATCH(I$1, JunR!$6:$6, 0), FALSE), 0 ) + IFERROR( VLOOKUP($A20, INDIRECT("JulR!$A$6:$ZZ$1048576"), MATCH(I$1, JulR!$6:$6, 0), FALSE), 0 ) + IFERROR( VLOOKUP($A20, INDIRECT("AgoR!$A$6:$ZZ$1048576"), MATCH(I$1, AgoR!$6:$6, 0), FALSE), 0 ) + IFERROR( VLOOKUP($A20, INDIRECT("SepR!$A$6:$ZZ$1048576"), MATCH(I$1, SepR!$6:$6, 0), FALSE), 0 ) + IFERROR( VLOOKUP($A20, INDIRECT("OctR!$A$6:$ZZ$1048576"), MATCH(I$1, OctR!$6:$6, 0), FALSE), 0 ) + IFERROR( VLOOKUP($A20, INDIRECT("NovR!$A$6:$ZZ$1048576"), MATCH(I$1, NovR!$6:$6, 0), FALSE), 0 ) + IFERROR( VLOOKUP($A20, INDIRECT("DicR!$A$6:$ZZ$1048576"), MATCH(I$1, DicR!$6:$6, 0), FALSE), 0 ) )} -> 0 | J20: {=SUM( IFERROR( VLOOKUP($A20, INDIRECT("EneR!$A$6:$ZZ$1048576"), MATCH(J$1, EneR!$6:$6, 0), FALSE), 0 ) + IFERROR( VLOOKUP($A20, INDIRECT("FebR!$A$6:$ZZ$1048576"), MATCH(J$1, FebR!$6:$6, 0), FALSE), 0 ) + IFERROR( VLOOKUP($A20, INDIRECT("MarR!$A$6:$ZZ$1048576"), MATCH(J$1, MarR!$6:$6, 0), FALSE), 0 ) + IFERROR( VLOOKUP($A20, INDIRECT("AbrR!$A$6:$ZZ$1048576"), MATCH(J$1, AbrR!$6:$6, 0), FALSE), 0 ) + IFERROR( VLOOKUP($A20, INDIRECT("MayR!$A$6:$ZZ$1048576"), MATCH(J$1, MayR!$6:$6, 0), FALSE), 0 ) + IFERROR( VLOOKUP($A20, INDIRECT("JunR!$A$6:$ZZ$1048576"), MATCH(J$1, JunR!$6:$6, 0), FALSE), 0 ) + IFERROR( VLOOKUP($A20, INDIRECT("JulR!$A$6:$ZZ$1048576"), MATCH(J$1, JulR!$6:$6, 0), FALSE), 0 ) + IFERROR( VLOOKUP($A20, INDIRECT("AgoR!$A$6:$ZZ$1048576"), MATCH(J$1, AgoR!$6:$6, 0), FALSE), 0 ) + IFERROR( VLOOKUP($A20, INDIRECT("SepR!$A$6:$ZZ$1048576"), MATCH(J$1, SepR!$6:$6, 0), FALSE), 0 ) + IFERROR( VLOOKUP($A20, INDIRECT("OctR!$A$6:$ZZ$1048576"), MATCH(J$1, OctR!$6:$6, 0), FALSE), 0 ) + IFERROR( VLOOKUP($A20, INDIRECT("NovR!$A$6:$ZZ$1048576"), MATCH(J$1, NovR!$6:$6, 0), FALSE), 0 ) + IFERROR( VLOOKUP($A20, INDIRECT("DicR!$A$6:$ZZ$1048576"), MATCH(J$1, DicR!$6:$6, 0), FALSE), 0 ) )} -> 0 | K20: {=SUM( IFERROR( VLOOKUP($A20, INDIRECT("EneR!$A$6:$ZZ$1048576"), MATCH(K$1, EneR!$6:$6, 0), FALSE), 0 ) + IFERROR( VLOOKUP($A20, INDIRECT("FebR!$A$6:$ZZ$1048576"), MATCH(K$1, FebR!$6:$6, 0), FALSE), 0 ) + IFERROR( VLOOKUP($A20, INDIRECT("MarR!$A$6:$ZZ$1048576"), MATCH(K$1, MarR!$6:$6, 0), FALSE), 0 ) + IFERROR( VLOOKUP($A20, INDIRECT("AbrR!$A$6:$ZZ$1048576"), MATCH(K$1, AbrR!$6:$6, 0), FALSE), 0 ) + IFERROR( VLOOKUP($A20, INDIRECT("MayR!$A$6:$ZZ$1048576"), MATCH(K$1, MayR!$6:$6, 0), FALSE), 0 ) + IFERROR( VLOOKUP($A20, INDIRECT("JunR!$A$6:$ZZ$1048576"), MATCH(K$1, JunR!$6:$6, 0), FALSE), 0 ) + IFERROR( VLOOKUP($A20, INDIRECT("JulR!$A$6:$ZZ$1048576"), MATCH(K$1, JulR!$6:$6, 0), FALSE), 0 ) + IFERROR( VLOOKUP($A20, INDIRECT("AgoR!$A$6:$ZZ$1048576"), MATCH(K$1, AgoR!$6:$6, 0), FALSE), 0 ) + IFERROR( VLOOKUP($A20, INDIRECT("SepR!$A$6:$ZZ$1048576"), MATCH(K$1, SepR!$6:$6, 0), FALSE), 0 ) + IFERROR( VLOOKUP($A20, INDIRECT("OctR!$A$6:$ZZ$1048576"), MATCH(K$1, OctR!$6:$6, 0), FALSE), 0 ) + IFERROR( VLOOKUP($A20, INDIRECT("NovR!$A$6:$ZZ$1048576"), MATCH(K$1, NovR!$6:$6, 0), FALSE), 0 ) + IFERROR( VLOOKUP($A20, INDIRECT("DicR!$A$6:$ZZ$1048576"), MATCH(K$1, DicR!$6:$6, 0), FALSE), 0 ) )} -> 0 | ... AY20: {=SUM( IFERROR( VLOOKUP($A20, INDIRECT("EneR!$A$6:$ZZ$1048576"), MATCH(AY$1, EneR!$6:$6, 0), FALSE), 0 ) + IFERROR( VLOOKUP($A20, INDIRECT("FebR!$A$6:$ZZ$1048576"), MATCH(AY$1, FebR!$6:$6, 0), FALSE), 0 ) + IFERROR( VLOOKUP($A20, INDIRECT("MarR!$A$6:$ZZ$1048576"), MATCH(AY$1, MarR!$6:$6, 0), FALSE), 0 ) + IFERROR( VLOOKUP($A20, INDIRECT("AbrR!$A$6:$ZZ$1048576"), MATCH(AY$1, AbrR!$6:$6, 0), FALSE), 0 ) + IFERROR( VLOOKUP($A20, INDIRECT("MayR!$A$6:$ZZ$1048576"), MATCH(AY$1, MayR!$6:$6, 0), FALSE), 0 ) + IFERROR( VLOOKUP($A20, INDIRECT("JunR!$A$6:$ZZ$1048576"), MATCH(AY$1, JunR!$6:$6, 0), FALSE), 0 ) + IFERROR( VLOOKUP($A20, INDIRECT("JulR!$A$6:$ZZ$1048576"), MATCH(AY$1, JulR!$6:$6, 0), FALSE), 0 ) + IFERROR( VLOOKUP($A20, INDIRECT("AgoR!$A$6:$ZZ$1048576"), MATCH(AY$1, AgoR!$6:$6, 0), FALSE), 0 ) + IFERROR( VLOOKUP($A20, INDIRECT("SepR!$A$6:$ZZ$1048576"), MATCH(AY$1, SepR!$6:$6, 0), FALSE), 0 ) + IFERROR( VLOOKUP($A20, INDIRECT("OctR!$A$6:$ZZ$1048576"), MATCH(AY$1, OctR!$6:$6, 0), FALSE), 0 ) + IFERROR( VLOOKUP($A20, INDIRECT("NovR!$A$6:$ZZ$1048576"), MATCH(AY$1, NovR!$6:$6, 0), FALSE), 0 ) + IFERROR( VLOOKUP($A20, INDIRECT("DicR!$A$6:$ZZ$1048576"), MATCH(AY$1, DicR!$6:$6, 0), FALSE), 0 ) )} -> 0
A21: =Menus!R13 | B21: =IFERROR(SUM(D21:AZ21),"") -> 0 | C21: =IFERROR(INDEX($D$1:$AQ138, MATCH($A21, $A$1:$A138, 0), MATCH(C$1, $D$1:AZ$1, 0)), "") | D21: {=SUM( IFERROR( VLOOKUP($A21, INDIRECT("EneR!$A$6:$ZZ$1048576"), MATCH(D$1, EneR!$6:$6, 0), FALSE), 0 ) + IFERROR( VLOOKUP($A21, INDIRECT("FebR!$A$6:$ZZ$1048576"), MATCH(D$1, FebR!$6:$6, 0), FALSE), 0 ) + IFERROR( VLOOKUP($A21, INDIRECT("MarR!$A$6:$ZZ$1048576"), MATCH(D$1, MarR!$6:$6, 0), FALSE), 0 ) + IFERROR( VLOOKUP($A21, INDIRECT("AbrR!$A$6:$ZZ$1048576"), MATCH(D$1, AbrR!$6:$6, 0), FALSE), 0 ) + IFERROR( VLOOKUP($A21, INDIRECT("MayR!$A$6:$ZZ$1048576"), MATCH(D$1, MayR!$6:$6, 0), FALSE), 0 ) + IFERROR( VLOOKUP($A21, INDIRECT("JunR!$A$6:$ZZ$1048576"), MATCH(D$1, JunR!$6:$6, 0), FALSE), 0 ) + IFERROR( VLOOKUP($A21, INDIRECT("JulR!$A$6:$ZZ$1048576"), MATCH(D$1, JulR!$6:$6, 0), FALSE), 0 ) + IFERROR( VLOOKUP($A21, INDIRECT("AgoR!$A$6:$ZZ$1048576"), MATCH(D$1, AgoR!$6:$6, 0), FALSE), 0 ) + IFERROR( VLOOKUP($A21, INDIRECT("SepR!$A$6:$ZZ$1048576"), MATCH(D$1, SepR!$6:$6, 0), FALSE), 0 ) + IFERROR( VLOOKUP($A21, INDIRECT("OctR!$A$6:$ZZ$1048576"), MATCH(D$1, OctR!$6:$6, 0), FALSE), 0 ) + IFERROR( VLOOKUP($A21, INDIRECT("NovR!$A$6:$ZZ$1048576"), MATCH(D$1, NovR!$6:$6, 0), FALSE), 0 ) + IFERROR( VLOOKUP($A21, INDIRECT("DicR!$A$6:$ZZ$1048576"), MATCH(D$1, DicR!$6:$6, 0), FALSE), 0 ) )} -> 0 | E21: {=SUM( IFERROR( VLOOKUP($A21, INDIRECT("EneR!$A$6:$ZZ$1048576"), MATCH(E$1, EneR!$6:$6, 0), FALSE), 0 ) + IFERROR( VLOOKUP($A21, INDIRECT("FebR!$A$6:$ZZ$1048576"), MATCH(E$1, FebR!$6:$6, 0), FALSE), 0 ) + IFERROR( VLOOKUP($A21, INDIRECT("MarR!$A$6:$ZZ$1048576"), MATCH(E$1, MarR!$6:$6, 0), FALSE), 0 ) + IFERROR( VLOOKUP($A21, INDIRECT("AbrR!$A$6:$ZZ$1048576"), MATCH(E$1, AbrR!$6:$6, 0), FALSE), 0 ) + IFERROR( VLOOKUP($A21, INDIRECT("MayR!$A$6:$ZZ$1048576"), MATCH(E$1, MayR!$6:$6, 0), FALSE), 0 ) + IFERROR( VLOOKUP($A21, INDIRECT("JunR!$A$6:$ZZ$1048576"), MATCH(E$1, JunR!$6:$6, 0), FALSE), 0 ) + IFERROR( VLOOKUP($A21, INDIRECT("JulR!$A$6:$ZZ$1048576"), MATCH(E$1, JulR!$6:$6, 0), FALSE), 0 ) + IFERROR( VLOOKUP($A21, INDIRECT("AgoR!$A$6:$ZZ$1048576"), MATCH(E$1, AgoR!$6:$6, 0), FALSE), 0 ) + IFERROR( VLOOKUP($A21, INDIRECT("SepR!$A$6:$ZZ$1048576"), MATCH(E$1, SepR!$6:$6, 0), FALSE), 0 ) + IFERROR( VLOOKUP($A21, INDIRECT("OctR!$A$6:$ZZ$1048576"), MATCH(E$1, OctR!$6:$6, 0), FALSE), 0 ) + IFERROR( VLOOKUP($A21, INDIRECT("NovR!$A$6:$ZZ$1048576"), MATCH(E$1, NovR!$6:$6, 0), FALSE), 0 ) + IFERROR( VLOOKUP($A21, INDIRECT("DicR!$A$6:$ZZ$1048576"), MATCH(E$1, DicR!$6:$6, 0), FALSE), 0 ) )} -> 0 | F21: {=SUM( IFERROR( VLOOKUP($A21, INDIRECT("EneR!$A$6:$ZZ$1048576"), MATCH(F$1, EneR!$6:$6, 0), FALSE), 0 ) + IFERROR( VLOOKUP($A21, INDIRECT("FebR!$A$6:$ZZ$1048576"), MATCH(F$1, FebR!$6:$6, 0), FALSE), 0 ) + IFERROR( VLOOKUP($A21, INDIRECT("MarR!$A$6:$ZZ$1048576"), MATCH(F$1, MarR!$6:$6, 0), FALSE), 0 ) + IFERROR( VLOOKUP($A21, INDIRECT("AbrR!$A$6:$ZZ$1048576"), MATCH(F$1, AbrR!$6:$6, 0), FALSE), 0 ) + IFERROR( VLOOKUP($A21, INDIRECT("MayR!$A$6:$ZZ$1048576"), MATCH(F$1, MayR!$6:$6, 0), FALSE), 0 ) + IFERROR( VLOOKUP($A21, INDIRECT("JunR!$A$6:$ZZ$1048576"), MATCH(F$1, JunR!$6:$6, 0), FALSE), 0 ) + IFERROR( VLOOKUP($A21, INDIRECT("JulR!$A$6:$ZZ$1048576"), MATCH(F$1, JulR!$6:$6, 0), FALSE), 0 ) + IFERROR( VLOOKUP($A21, INDIRECT("AgoR!$A$6:$ZZ$1048576"), MATCH(F$1, AgoR!$6:$6, 0), FALSE), 0 ) + IFERROR( VLOOKUP($A21, INDIRECT("SepR!$A$6:$ZZ$1048576"), MATCH(F$1, SepR!$6:$6, 0), FALSE), 0 ) + IFERROR( VLOOKUP($A21, INDIRECT("OctR!$A$6:$ZZ$1048576"), MATCH(F$1, OctR!$6:$6, 0), FALSE), 0 ) + IFERROR( VLOOKUP($A21, INDIRECT("NovR!$A$6:$ZZ$1048576"), MATCH(F$1, NovR!$6:$6, 0), FALSE), 0 ) + IFERROR( VLOOKUP($A21, INDIRECT("DicR!$A$6:$ZZ$1048576"), MATCH(F$1, DicR!$6:$6, 0), FALSE), 0 ) )} -> 0 | G21: {=SUM( IFERROR( VLOOKUP($A21, INDIRECT("EneR!$A$6:$ZZ$1048576"), MATCH(G$1, EneR!$6:$6, 0), FALSE), 0 ) + IFERROR( VLOOKUP($A21, INDIRECT("FebR!$A$6:$ZZ$1048576"), MATCH(G$1, FebR!$6:$6, 0), FALSE), 0 ) + IFERROR( VLOOKUP($A21, INDIRECT("MarR!$A$6:$ZZ$1048576"), MATCH(G$1, MarR!$6:$6, 0), FALSE), 0 ) + IFERROR( VLOOKUP($A21, INDIRECT("AbrR!$A$6:$ZZ$1048576"), MATCH(G$1, AbrR!$6:$6, 0), FALSE), 0 ) + IFERROR( VLOOKUP($A21, INDIRECT("MayR!$A$6:$ZZ$1048576"), MATCH(G$1, MayR!$6:$6, 0), FALSE), 0 ) + IFERROR( VLOOKUP($A21, INDIRECT("JunR!$A$6:$ZZ$1048576"), MATCH(G$1, JunR!$6:$6, 0), FALSE), 0 ) + IFERROR( VLOOKUP($A21, INDIRECT("JulR!$A$6:$ZZ$1048576"), MATCH(G$1, JulR!$6:$6, 0), FALSE), 0 ) + IFERROR( VLOOKUP($A21, INDIRECT("AgoR!$A$6:$ZZ$1048576"), MATCH(G$1, AgoR!$6:$6, 0), FALSE), 0 ) + IFERROR( VLOOKUP($A21, INDIRECT("SepR!$A$6:$ZZ$1048576"), MATCH(G$1, SepR!$6:$6, 0), FALSE), 0 ) + IFERROR( VLOOKUP($A21, INDIRECT("OctR!$A$6:$ZZ$1048576"), MATCH(G$1, OctR!$6:$6, 0), FALSE), 0 ) + IFERROR( VLOOKUP($A21, INDIRECT("NovR!$A$6:$ZZ$1048576"), MATCH(G$1, NovR!$6:$6, 0), FALSE), 0 ) + IFERROR( VLOOKUP($A21, INDIRECT("DicR!$A$6:$ZZ$1048576"), MATCH(G$1, DicR!$6:$6, 0), FALSE), 0 ) )} -> 0 | H21: {=SUM( IFERROR( VLOOKUP($A21, INDIRECT("EneR!$A$6:$ZZ$1048576"), MATCH(H$1, EneR!$6:$6, 0), FALSE), 0 ) + IFERROR( VLOOKUP($A21, INDIRECT("FebR!$A$6:$ZZ$1048576"), MATCH(H$1, FebR!$6:$6, 0), FALSE), 0 ) + IFERROR( VLOOKUP($A21, INDIRECT("MarR!$A$6:$ZZ$1048576"), MATCH(H$1, MarR!$6:$6, 0), FALSE), 0 ) + IFERROR( VLOOKUP($A21, INDIRECT("AbrR!$A$6:$ZZ$1048576"), MATCH(H$1, AbrR!$6:$6, 0), FALSE), 0 ) + IFERROR( VLOOKUP($A21, INDIRECT("MayR!$A$6:$ZZ$1048576"), MATCH(H$1, MayR!$6:$6, 0), FALSE), 0 ) + IFERROR( VLOOKUP($A21, INDIRECT("JunR!$A$6:$ZZ$1048576"), MATCH(H$1, JunR!$6:$6, 0), FALSE), 0 ) + IFERROR( VLOOKUP($A21, INDIRECT("JulR!$A$6:$ZZ$1048576"), MATCH(H$1, JulR!$6:$6, 0), FALSE), 0 ) + IFERROR( VLOOKUP($A21, INDIRECT("AgoR!$A$6:$ZZ$1048576"), MATCH(H$1, AgoR!$6:$6, 0), FALSE), 0 ) + IFERROR( VLOOKUP($A21, INDIRECT("SepR!$A$6:$ZZ$1048576"), MATCH(H$1, SepR!$6:$6, 0), FALSE), 0 ) + IFERROR( VLOOKUP($A21, INDIRECT("OctR!$A$6:$ZZ$1048576"), MATCH(H$1, OctR!$6:$6, 0), FALSE), 0 ) + IFERROR( VLOOKUP($A21, INDIRECT("NovR!$A$6:$ZZ$1048576"), MATCH(H$1, NovR!$6:$6, 0), FALSE), 0 ) + IFERROR( VLOOKUP($A21, INDIRECT("DicR!$A$6:$ZZ$1048576"), MATCH(H$1, DicR!$6:$6, 0), FALSE), 0 ) )} -> 0 | I21: {=SUM( IFERROR( VLOOKUP($A21, INDIRECT("EneR!$A$6:$ZZ$1048576"), MATCH(I$1, EneR!$6:$6, 0), FALSE), 0 ) + IFERROR( VLOOKUP($A21, INDIRECT("FebR!$A$6:$ZZ$1048576"), MATCH(I$1, FebR!$6:$6, 0), FALSE), 0 ) + IFERROR( VLOOKUP($A21, INDIRECT("MarR!$A$6:$ZZ$1048576"), MATCH(I$1, MarR!$6:$6, 0), FALSE), 0 ) + IFERROR( VLOOKUP($A21, INDIRECT("AbrR!$A$6:$ZZ$1048576"), MATCH(I$1, AbrR!$6:$6, 0), FALSE), 0 ) + IFERROR( VLOOKUP($A21, INDIRECT("MayR!$A$6:$ZZ$1048576"), MATCH(I$1, MayR!$6:$6, 0), FALSE), 0 ) + IFERROR( VLOOKUP($A21, INDIRECT("JunR!$A$6:$ZZ$1048576"), MATCH(I$1, JunR!$6:$6, 0), FALSE), 0 ) + IFERROR( VLOOKUP($A21, INDIRECT("JulR!$A$6:$ZZ$1048576"), MATCH(I$1, JulR!$6:$6, 0), FALSE), 0 ) + IFERROR( VLOOKUP($A21, INDIRECT("AgoR!$A$6:$ZZ$1048576"), MATCH(I$1, AgoR!$6:$6, 0), FALSE), 0 ) + IFERROR( VLOOKUP($A21, INDIRECT("SepR!$A$6:$ZZ$1048576"), MATCH(I$1, SepR!$6:$6, 0), FALSE), 0 ) + IFERROR( VLOOKUP($A21, INDIRECT("OctR!$A$6:$ZZ$1048576"), MATCH(I$1, OctR!$6:$6, 0), FALSE), 0 ) + IFERROR( VLOOKUP($A21, INDIRECT("NovR!$A$6:$ZZ$1048576"), MATCH(I$1, NovR!$6:$6, 0), FALSE), 0 ) + IFERROR( VLOOKUP($A21, INDIRECT("DicR!$A$6:$ZZ$1048576"), MATCH(I$1, DicR!$6:$6, 0), FALSE), 0 ) )} -> 0 | J21: {=SUM( IFERROR( VLOOKUP($A21, INDIRECT("EneR!$A$6:$ZZ$1048576"), MATCH(J$1, EneR!$6:$6, 0), FALSE), 0 ) + IFERROR( VLOOKUP($A21, INDIRECT("FebR!$A$6:$ZZ$1048576"), MATCH(J$1, FebR!$6:$6, 0), FALSE), 0 ) + IFERROR( VLOOKUP($A21, INDIRECT("MarR!$A$6:$ZZ$1048576"), MATCH(J$1, MarR!$6:$6, 0), FALSE), 0 ) + IFERROR( VLOOKUP($A21, INDIRECT("AbrR!$A$6:$ZZ$1048576"), MATCH(J$1, AbrR!$6:$6, 0), FALSE), 0 ) + IFERROR( VLOOKUP($A21, INDIRECT("MayR!$A$6:$ZZ$1048576"), MATCH(J$1, MayR!$6:$6, 0), FALSE), 0 ) + IFERROR( VLOOKUP($A21, INDIRECT("JunR!$A$6:$ZZ$1048576"), MATCH(J$1, JunR!$6:$6, 0), FALSE), 0 ) + IFERROR( VLOOKUP($A21, INDIRECT("JulR!$A$6:$ZZ$1048576"), MATCH(J$1, JulR!$6:$6, 0), FALSE), 0 ) + IFERROR( VLOOKUP($A21, INDIRECT("AgoR!$A$6:$ZZ$1048576"), MATCH(J$1, AgoR!$6:$6, 0), FALSE), 0 ) + IFERROR( VLOOKUP($A21, INDIRECT("SepR!$A$6:$ZZ$1048576"), MATCH(J$1, SepR!$6:$6, 0), FALSE), 0 ) + IFERROR( VLOOKUP($A21, INDIRECT("OctR!$A$6:$ZZ$1048576"), MATCH(J$1, OctR!$6:$6, 0), FALSE), 0 ) + IFERROR( VLOOKUP($A21, INDIRECT("NovR!$A$6:$ZZ$1048576"), MATCH(J$1, NovR!$6:$6, 0), FALSE), 0 ) + IFERROR( VLOOKUP($A21, INDIRECT("DicR!$A$6:$ZZ$1048576"), MATCH(J$1, DicR!$6:$6, 0), FALSE), 0 ) )} -> 0 | K21: {=SUM( IFERROR( VLOOKUP($A21, INDIRECT("EneR!$A$6:$ZZ$1048576"), MATCH(K$1, EneR!$6:$6, 0), FALSE), 0 ) + IFERROR( VLOOKUP($A21, INDIRECT("FebR!$A$6:$ZZ$1048576"), MATCH(K$1, FebR!$6:$6, 0), FALSE), 0 ) + IFERROR( VLOOKUP($A21, INDIRECT("MarR!$A$6:$ZZ$1048576"), MATCH(K$1, MarR!$6:$6, 0), FALSE), 0 ) + IFERROR( VLOOKUP($A21, INDIRECT("AbrR!$A$6:$ZZ$1048576"), MATCH(K$1, AbrR!$6:$6, 0), FALSE), 0 ) + IFERROR( VLOOKUP($A21, INDIRECT("MayR!$A$6:$ZZ$1048576"), MATCH(K$1, MayR!$6:$6, 0), FALSE), 0 ) + IFERROR( VLOOKUP($A21, INDIRECT("JunR!$A$6:$ZZ$1048576"), MATCH(K$1, JunR!$6:$6, 0), FALSE), 0 ) + IFERROR( VLOOKUP($A21, INDIRECT("JulR!$A$6:$ZZ$1048576"), MATCH(K$1, JulR!$6:$6, 0), FALSE), 0 ) + IFERROR( VLOOKUP($A21, INDIRECT("AgoR!$A$6:$ZZ$1048576"), MATCH(K$1, AgoR!$6:$6, 0), FALSE), 0 ) + IFERROR( VLOOKUP($A21, INDIRECT("SepR!$A$6:$ZZ$1048576"), MATCH(K$1, SepR!$6:$6, 0), FALSE), 0 ) + IFERROR( VLOOKUP($A21, INDIRECT("OctR!$A$6:$ZZ$1048576"), MATCH(K$1, OctR!$6:$6, 0), FALSE), 0 ) + IFERROR( VLOOKUP($A21, INDIRECT("NovR!$A$6:$ZZ$1048576"), MATCH(K$1, NovR!$6:$6, 0), FALSE), 0 ) + IFERROR( VLOOKUP($A21, INDIRECT("DicR!$A$6:$ZZ$1048576"), MATCH(K$1, DicR!$6:$6, 0), FALSE), 0 ) )} -> 0 | ... AY21: {=SUM( IFERROR( VLOOKUP($A21, INDIRECT("EneR!$A$6:$ZZ$1048576"), MATCH(AY$1, EneR!$6:$6, 0), FALSE), 0 ) + IFERROR( VLOOKUP($A21, INDIRECT("FebR!$A$6:$ZZ$1048576"), MATCH(AY$1, FebR!$6:$6, 0), FALSE), 0 ) + IFERROR( VLOOKUP($A21, INDIRECT("MarR!$A$6:$ZZ$1048576"), MATCH(AY$1, MarR!$6:$6, 0), FALSE), 0 ) + IFERROR( VLOOKUP($A21, INDIRECT("AbrR!$A$6:$ZZ$1048576"), MATCH(AY$1, AbrR!$6:$6, 0), FALSE), 0 ) + IFERROR( VLOOKUP($A21, INDIRECT("MayR!$A$6:$ZZ$1048576"), MATCH(AY$1, MayR!$6:$6, 0), FALSE), 0 ) + IFERROR( VLOOKUP($A21, INDIRECT("JunR!$A$6:$ZZ$1048576"), MATCH(AY$1, JunR!$6:$6, 0), FALSE), 0 ) + IFERROR( VLOOKUP($A21, INDIRECT("JulR!$A$6:$ZZ$1048576"), MATCH(AY$1, JulR!$6:$6, 0), FALSE), 0 ) + IFERROR( VLOOKUP($A21, INDIRECT("AgoR!$A$6:$ZZ$1048576"), MATCH(AY$1, AgoR!$6:$6, 0), FALSE), 0 ) + IFERROR( VLOOKUP($A21, INDIRECT("SepR!$A$6:$ZZ$1048576"), MATCH(AY$1, SepR!$6:$6, 0), FALSE), 0 ) + IFERROR( VLOOKUP($A21, INDIRECT("OctR!$A$6:$ZZ$1048576"), MATCH(AY$1, OctR!$6:$6, 0), FALSE), 0 ) + IFERROR( VLOOKUP($A21, INDIRECT("NovR!$A$6:$ZZ$1048576"), MATCH(AY$1, NovR!$6:$6, 0), FALSE), 0 ) + IFERROR( VLOOKUP($A21, INDIRECT("DicR!$A$6:$ZZ$1048576"), MATCH(AY$1, DicR!$6:$6, 0), FALSE), 0 ) )} -> 0
... A28: =Menus!R20 | B28: =IFERROR(SUM(D28:AZ28),"") -> 0 | C28: =IFERROR(INDEX($D$1:$AQ145, MATCH($A28, $A$1:$A145, 0), MATCH(C$1, $D$1:AZ$1, 0)), "") | D28: {=SUM( IFERROR( VLOOKUP($A28, INDIRECT("EneR!$A$6:$ZZ$1048576"), MATCH(D$1, EneR!$6:$6, 0), FALSE), 0 ) + IFERROR( VLOOKUP($A28, INDIRECT("FebR!$A$6:$ZZ$1048576"), MATCH(D$1, FebR!$6:$6, 0), FALSE), 0 ) + IFERROR( VLOOKUP($A28, INDIRECT("MarR!$A$6:$ZZ$1048576"), MATCH(D$1, MarR!$6:$6, 0), FALSE), 0 ) + IFERROR( VLOOKUP($A28, INDIRECT("AbrR!$A$6:$ZZ$1048576"), MATCH(D$1, AbrR!$6:$6, 0), FALSE), 0 ) + IFERROR( VLOOKUP($A28, INDIRECT("MayR!$A$6:$ZZ$1048576"), MATCH(D$1, MayR!$6:$6, 0), FALSE), 0 ) + IFERROR( VLOOKUP($A28, INDIRECT("JunR!$A$6:$ZZ$1048576"), MATCH(D$1, JunR!$6:$6, 0), FALSE), 0 ) + IFERROR( VLOOKUP($A28, INDIRECT("JulR!$A$6:$ZZ$1048576"), MATCH(D$1, JulR!$6:$6, 0), FALSE), 0 ) + IFERROR( VLOOKUP($A28, INDIRECT("AgoR!$A$6:$ZZ$1048576"), MATCH(D$1, AgoR!$6:$6, 0), FALSE), 0 ) + IFERROR( VLOOKUP($A28, INDIRECT("SepR!$A$6:$ZZ$1048576"), MATCH(D$1, SepR!$6:$6, 0), FALSE), 0 ) + IFERROR( VLOOKUP($A28, INDIRECT("OctR!$A$6:$ZZ$1048576"), MATCH(D$1, OctR!$6:$6, 0), FALSE), 0 ) + IFERROR( VLOOKUP($A28, INDIRECT("NovR!$A$6:$ZZ$1048576"), MATCH(D$1, NovR!$6:$6, 0), FALSE), 0 ) + IFERROR( VLOOKUP($A28, INDIRECT("DicR!$A$6:$ZZ$1048576"), MATCH(D$1, DicR!$6:$6, 0), FALSE), 0 ) )} -> 0 | E28: {=SUM( IFERROR( VLOOKUP($A28, INDIRECT("EneR!$A$6:$ZZ$1048576"), MATCH(E$1, EneR!$6:$6, 0), FALSE), 0 ) + IFERROR( VLOOKUP($A28, INDIRECT("FebR!$A$6:$ZZ$1048576"), MATCH(E$1, FebR!$6:$6, 0), FALSE), 0 ) + IFERROR( VLOOKUP($A28, INDIRECT("MarR!$A$6:$ZZ$1048576"), MATCH(E$1, MarR!$6:$6, 0), FALSE), 0 ) + IFERROR( VLOOKUP($A28, INDIRECT("AbrR!$A$6:$ZZ$1048576"), MATCH(E$1, AbrR!$6:$6, 0), FALSE), 0 ) + IFERROR( VLOOKUP($A28, INDIRECT("MayR!$A$6:$ZZ$1048576"), MATCH(E$1, MayR!$6:$6, 0), FALSE), 0 ) + IFERROR( VLOOKUP($A28, INDIRECT("JunR!$A$6:$ZZ$1048576"), MATCH(E$1, JunR!$6:$6, 0), FALSE), 0 ) + IFERROR( VLOOKUP($A28, INDIRECT("JulR!$A$6:$ZZ$1048576"), MATCH(E$1, JulR!$6:$6, 0), FALSE), 0 ) + IFERROR( VLOOKUP($A28, INDIRECT("AgoR!$A$6:$ZZ$1048576"), MATCH(E$1, AgoR!$6:$6, 0), FALSE), 0 ) + IFERROR( VLOOKUP($A28, INDIRECT("SepR!$A$6:$ZZ$1048576"), MATCH(E$1, SepR!$6:$6, 0), FALSE), 0 ) + IFERROR( VLOOKUP($A28, INDIRECT("OctR!$A$6:$ZZ$1048576"), MATCH(E$1, OctR!$6:$6, 0), FALSE), 0 ) + IFERROR( VLOOKUP($A28, INDIRECT("NovR!$A$6:$ZZ$1048576"), MATCH(E$1, NovR!$6:$6, 0), FALSE), 0 ) + IFERROR( VLOOKUP($A28, INDIRECT("DicR!$A$6:$ZZ$1048576"), MATCH(E$1, DicR!$6:$6, 0), FALSE), 0 ) )} -> 0 | F28: {=SUM( IFERROR( VLOOKUP($A28, INDIRECT("EneR!$A$6:$ZZ$1048576"), MATCH(F$1, EneR!$6:$6, 0), FALSE), 0 ) + IFERROR( VLOOKUP($A28, INDIRECT("FebR!$A$6:$ZZ$1048576"), MATCH(F$1, FebR!$6:$6, 0), FALSE), 0 ) + IFERROR( VLOOKUP($A28, INDIRECT("MarR!$A$6:$ZZ$1048576"), MATCH(F$1, MarR!$6:$6, 0), FALSE), 0 ) + IFERROR( VLOOKUP($A28, INDIRECT("AbrR!$A$6:$ZZ$1048576"), MATCH(F$1, AbrR!$6:$6, 0), FALSE), 0 ) + IFERROR( VLOOKUP($A28, INDIRECT("MayR!$A$6:$ZZ$1048576"), MATCH(F$1, MayR!$6:$6, 0), FALSE), 0 ) + IFERROR( VLOOKUP($A28, INDIRECT("JunR!$A$6:$ZZ$1048576"), MATCH(F$1, JunR!$6:$6, 0), FALSE), 0 ) + IFERROR( VLOOKUP($A28, INDIRECT("JulR!$A$6:$ZZ$1048576"), MATCH(F$1, JulR!$6:$6, 0), FALSE), 0 ) + IFERROR( VLOOKUP($A28, INDIRECT("AgoR!$A$6:$ZZ$1048576"), MATCH(F$1, AgoR!$6:$6, 0), FALSE), 0 ) + IFERROR( VLOOKUP($A28, INDIRECT("SepR!$A$6:$ZZ$1048576"), MATCH(F$1, SepR!$6:$6, 0), FALSE), 0 ) + IFERROR( VLOOKUP($A28, INDIRECT("OctR!$A$6:$ZZ$1048576"), MATCH(F$1, OctR!$6:$6, 0), FALSE), 0 ) + IFERROR( VLOOKUP($A28, INDIRECT("NovR!$A$6:$ZZ$1048576"), MATCH(F$1, NovR!$6:$6, 0), FALSE), 0 ) + IFERROR( VLOOKUP($A28, INDIRECT("DicR!$A$6:$ZZ$1048576"), MATCH(F$1, DicR!$6:$6, 0), FALSE), 0 ) )} -> 0 | G28: {=SUM( IFERROR( VLOOKUP($A28, INDIRECT("EneR!$A$6:$ZZ$1048576"), MATCH(G$1, EneR!$6:$6, 0), FALSE), 0 ) + IFERROR( VLOOKUP($A28, INDIRECT("FebR!$A$6:$ZZ$1048576"), MATCH(G$1, FebR!$6:$6, 0), FALSE), 0 ) + IFERROR( VLOOKUP($A28, INDIRECT("MarR!$A$6:$ZZ$1048576"), MATCH(G$1, MarR!$6:$6, 0), FALSE), 0 ) + IFERROR( VLOOKUP($A28, INDIRECT("AbrR!$A$6:$ZZ$1048576"), MATCH(G$1, AbrR!$6:$6, 0), FALSE), 0 ) + IFERROR( VLOOKUP($A28, INDIRECT("MayR!$A$6:$ZZ$1048576"), MATCH(G$1, MayR!$6:$6, 0), FALSE), 0 ) + IFERROR( VLOOKUP($A28, INDIRECT("JunR!$A$6:$ZZ$1048576"), MATCH(G$1, JunR!$6:$6, 0), FALSE), 0 ) + IFERROR( VLOOKUP($A28, INDIRECT("JulR!$A$6:$ZZ$1048576"), MATCH(G$1, JulR!$6:$6, 0), FALSE), 0 ) + IFERROR( VLOOKUP($A28, INDIRECT("AgoR!$A$6:$ZZ$1048576"), MATCH(G$1, AgoR!$6:$6, 0), FALSE), 0 ) + IFERROR( VLOOKUP($A28, INDIRECT("SepR!$A$6:$ZZ$1048576"), MATCH(G$1, SepR!$6:$6, 0), FALSE), 0 ) + IFERROR( VLOOKUP($A28, INDIRECT("OctR!$A$6:$ZZ$1048576"), MATCH(G$1, OctR!$6:$6, 0), FALSE), 0 ) + IFERROR( VLOOKUP($A28, INDIRECT("NovR!$A$6:$ZZ$1048576"), MATCH(G$1, NovR!$6:$6, 0), FALSE), 0 ) + IFERROR( VLOOKUP($A28, INDIRECT("DicR!$A$6:$ZZ$1048576"), MATCH(G$1, DicR!$6:$6, 0), FALSE), 0 ) )} -> 0 | H28: {=SUM( IFERROR( VLOOKUP($A28, INDIRECT("EneR!$A$6:$ZZ$1048576"), MATCH(H$1, EneR!$6:$6, 0), FALSE), 0 ) + IFERROR( VLOOKUP($A28, INDIRECT("FebR!$A$6:$ZZ$1048576"), MATCH(H$1, FebR!$6:$6, 0), FALSE), 0 ) + IFERROR( VLOOKUP($A28, INDIRECT("MarR!$A$6:$ZZ$1048576"), MATCH(H$1, MarR!$6:$6, 0), FALSE), 0 ) + IFERROR( VLOOKUP($A28, INDIRECT("AbrR!$A$6:$ZZ$1048576"), MATCH(H$1, AbrR!$6:$6, 0), FALSE), 0 ) + IFERROR( VLOOKUP($A28, INDIRECT("MayR!$A$6:$ZZ$1048576"), MATCH(H$1, MayR!$6:$6, 0), FALSE), 0 ) + IFERROR( VLOOKUP($A28, INDIRECT("JunR!$A$6:$ZZ$1048576"), MATCH(H$1, JunR!$6:$6, 0), FALSE), 0 ) + IFERROR( VLOOKUP($A28, INDIRECT("JulR!$A$6:$ZZ$1048576"), MATCH(H$1, JulR!$6:$6, 0), FALSE), 0 ) + IFERROR( VLOOKUP($A28, INDIRECT("AgoR!$A$6:$ZZ$1048576"), MATCH(H$1, AgoR!$6:$6, 0), FALSE), 0 ) + IFERROR( VLOOKUP($A28, INDIRECT("SepR!$A$6:$ZZ$1048576"), MATCH(H$1, SepR!$6:$6, 0), FALSE), 0 ) + IFERROR( VLOOKUP($A28, INDIRECT("OctR!$A$6:$ZZ$1048576"), MATCH(H$1, OctR!$6:$6, 0), FALSE), 0 ) + IFERROR( VLOOKUP($A28, INDIRECT("NovR!$A$6:$ZZ$1048576"), MATCH(H$1, NovR!$6:$6, 0), FALSE), 0 ) + IFERROR( VLOOKUP($A28, INDIRECT("DicR!$A$6:$ZZ$1048576"), MATCH(H$1, DicR!$6:$6, 0), FALSE), 0 ) )} -> 0 | I28: {=SUM( IFERROR( VLOOKUP($A28, INDIRECT("EneR!$A$6:$ZZ$1048576"), MATCH(I$1, EneR!$6:$6, 0), FALSE), 0 ) + IFERROR( VLOOKUP($A28, INDIRECT("FebR!$A$6:$ZZ$1048576"), MATCH(I$1, FebR!$6:$6, 0), FALSE), 0 ) + IFERROR( VLOOKUP($A28, INDIRECT("MarR!$A$6:$ZZ$1048576"), MATCH(I$1, MarR!$6:$6, 0), FALSE), 0 ) + IFERROR( VLOOKUP($A28, INDIRECT("AbrR!$A$6:$ZZ$1048576"), MATCH(I$1, AbrR!$6:$6, 0), FALSE), 0 ) + IFERROR( VLOOKUP($A28, INDIRECT("MayR!$A$6:$ZZ$1048576"), MATCH(I$1, MayR!$6:$6, 0), FALSE), 0 ) + IFERROR( VLOOKUP($A28, INDIRECT("JunR!$A$6:$ZZ$1048576"), MATCH(I$1, JunR!$6:$6, 0), FALSE), 0 ) + IFERROR( VLOOKUP($A28, INDIRECT("JulR!$A$6:$ZZ$1048576"), MATCH(I$1, JulR!$6:$6, 0), FALSE), 0 ) + IFERROR( VLOOKUP($A28, INDIRECT("AgoR!$A$6:$ZZ$1048576"), MATCH(I$1, AgoR!$6:$6, 0), FALSE), 0 ) + IFERROR( VLOOKUP($A28, INDIRECT("SepR!$A$6:$ZZ$1048576"), MATCH(I$1, SepR!$6:$6, 0), FALSE), 0 ) + IFERROR( VLOOKUP($A28, INDIRECT("OctR!$A$6:$ZZ$1048576"), MATCH(I$1, OctR!$6:$6, 0), FALSE), 0 ) + IFERROR( VLOOKUP($A28, INDIRECT("NovR!$A$6:$ZZ$1048576"), MATCH(I$1, NovR!$6:$6, 0), FALSE), 0 ) + IFERROR( VLOOKUP($A28, INDIRECT("DicR!$A$6:$ZZ$1048576"), MATCH(I$1, DicR!$6:$6, 0), FALSE), 0 ) )} -> 0 | J28: {=SUM( IFERROR( VLOOKUP($A28, INDIRECT("EneR!$A$6:$ZZ$1048576"), MATCH(J$1, EneR!$6:$6, 0), FALSE), 0 ) + IFERROR( VLOOKUP($A28, INDIRECT("FebR!$A$6:$ZZ$1048576"), MATCH(J$1, FebR!$6:$6, 0), FALSE), 0 ) + IFERROR( VLOOKUP($A28, INDIRECT("MarR!$A$6:$ZZ$1048576"), MATCH(J$1, MarR!$6:$6, 0), FALSE), 0 ) + IFERROR( VLOOKUP($A28, INDIRECT("AbrR!$A$6:$ZZ$1048576"), MATCH(J$1, AbrR!$6:$6, 0), FALSE), 0 ) + IFERROR( VLOOKUP($A28, INDIRECT("MayR!$A$6:$ZZ$1048576"), MATCH(J$1, MayR!$6:$6, 0), FALSE), 0 ) + IFERROR( VLOOKUP($A28, INDIRECT("JunR!$A$6:$ZZ$1048576"), MATCH(J$1, JunR!$6:$6, 0), FALSE), 0 ) + IFERROR( VLOOKUP($A28, INDIRECT("JulR!$A$6:$ZZ$1048576"), MATCH(J$1, JulR!$6:$6, 0), FALSE), 0 ) + IFERROR( VLOOKUP($A28, INDIRECT("AgoR!$A$6:$ZZ$1048576"), MATCH(J$1, AgoR!$6:$6, 0), FALSE), 0 ) + IFERROR( VLOOKUP($A28, INDIRECT("SepR!$A$6:$ZZ$1048576"), MATCH(J$1, SepR!$6:$6, 0), FALSE), 0 ) + IFERROR( VLOOKUP($A28, INDIRECT("OctR!$A$6:$ZZ$1048576"), MATCH(J$1, OctR!$6:$6, 0), FALSE), 0 ) + IFERROR( VLOOKUP($A28, INDIRECT("NovR!$A$6:$ZZ$1048576"), MATCH(J$1, NovR!$6:$6, 0), FALSE), 0 ) + IFERROR( VLOOKUP($A28, INDIRECT("DicR!$A$6:$ZZ$1048576"), MATCH(J$1, DicR!$6:$6, 0), FALSE), 0 ) )} -> 0 | K28: {=SUM( IFERROR( VLOOKUP($A28, INDIRECT("EneR!$A$6:$ZZ$1048576"), MATCH(K$1, EneR!$6:$6, 0), FALSE), 0 ) + IFERROR( VLOOKUP($A28, INDIRECT("FebR!$A$6:$ZZ$1048576"), MATCH(K$1, FebR!$6:$6, 0), FALSE), 0 ) + IFERROR( VLOOKUP($A28, INDIRECT("MarR!$A$6:$ZZ$1048576"), MATCH(K$1, MarR!$6:$6, 0), FALSE), 0 ) + IFERROR( VLOOKUP($A28, INDIRECT("AbrR!$A$6:$ZZ$1048576"), MATCH(K$1, AbrR!$6:$6, 0), FALSE), 0 ) + IFERROR( VLOOKUP($A28, INDIRECT("MayR!$A$6:$ZZ$1048576"), MATCH(K$1, MayR!$6:$6, 0), FALSE), 0 ) + IFERROR( VLOOKUP($A28, INDIRECT("JunR!$A$6:$ZZ$1048576"), MATCH(K$1, JunR!$6:$6, 0), FALSE), 0 ) + IFERROR( VLOOKUP($A28, INDIRECT("JulR!$A$6:$ZZ$1048576"), MATCH(K$1, JulR!$6:$6, 0), FALSE), 0 ) + IFERROR( VLOOKUP($A28, INDIRECT("AgoR!$A$6:$ZZ$1048576"), MATCH(K$1, AgoR!$6:$6, 0), FALSE), 0 ) + IFERROR( VLOOKUP($A28, INDIRECT("SepR!$A$6:$ZZ$1048576"), MATCH(K$1, SepR!$6:$6, 0), FALSE), 0 ) + IFERROR( VLOOKUP($A28, INDIRECT("OctR!$A$6:$ZZ$1048576"), MATCH(K$1, OctR!$6:$6, 0), FALSE), 0 ) + IFERROR( VLOOKUP($A28, INDIRECT("NovR!$A$6:$ZZ$1048576"), MATCH(K$1, NovR!$6:$6, 0), FALSE), 0 ) + IFERROR( VLOOKUP($A28, INDIRECT("DicR!$A$6:$ZZ$1048576"), MATCH(K$1, DicR!$6:$6, 0), FALSE), 0 ) )} -> 0 | ... AY28: {=SUM( IFERROR( VLOOKUP($A28, INDIRECT("EneR!$A$6:$ZZ$1048576"), MATCH(AY$1, EneR!$6:$6, 0), FALSE), 0 ) + IFERROR( VLOOKUP($A28, INDIRECT("FebR!$A$6:$ZZ$1048576"), MATCH(AY$1, FebR!$6:$6, 0), FALSE), 0 ) + IFERROR( VLOOKUP($A28, INDIRECT("MarR!$A$6:$ZZ$1048576"), MATCH(AY$1, MarR!$6:$6, 0), FALSE), 0 ) + IFERROR( VLOOKUP($A28, INDIRECT("AbrR!$A$6:$ZZ$1048576"), MATCH(AY$1, AbrR!$6:$6, 0), FALSE), 0 ) + IFERROR( VLOOKUP($A28, INDIRECT("MayR!$A$6:$ZZ$1048576"), MATCH(AY$1, MayR!$6:$6, 0), FALSE), 0 ) + IFERROR( VLOOKUP($A28, INDIRECT("JunR!$A$6:$ZZ$1048576"), MATCH(AY$1, JunR!$6:$6, 0), FALSE), 0 ) + IFERROR( VLOOKUP($A28, INDIRECT("JulR!$A$6:$ZZ$1048576"), MATCH(AY$1, JulR!$6:$6, 0), FALSE), 0 ) + IFERROR( VLOOKUP($A28, INDIRECT("AgoR!$A$6:$ZZ$1048576"), MATCH(AY$1, AgoR!$6:$6, 0), FALSE), 0 ) + IFERROR( VLOOKUP($A28, INDIRECT("SepR!$A$6:$ZZ$1048576"), MATCH(AY$1, SepR!$6:$6, 0), FALSE), 0 ) + IFERROR( VLOOKUP($A28, INDIRECT("OctR!$A$6:$ZZ$1048576"), MATCH(AY$1, OctR!$6:$6, 0), FALSE), 0 ) + IFERROR( VLOOKUP($A28, INDIRECT("NovR!$A$6:$ZZ$1048576"), MATCH(AY$1, NovR!$6:$6, 0), FALSE), 0 ) + IFERROR( VLOOKUP($A28, INDIRECT("DicR!$A$6:$ZZ$1048576"), MATCH(AY$1, DicR!$6:$6, 0), FALSE), 0 ) )} -> 0
A29: =Menus!R21 | B29: =IFERROR(SUM(D29:AR29),"") -> 0 | C29: =IFERROR(INDEX($D$1:$AQ$69, MATCH($A29, $A$1:$A$109, 0), MATCH(C$1, $D$1:AZ$1, 0)), "") | D29: {=SUM( IFERROR( VLOOKUP($A29, INDIRECT("EneR!$A$6:$ZZ$1048576"), MATCH(D$1, EneR!$6:$6, 0), FALSE), 0 ) + IFERROR( VLOOKUP($A29, INDIRECT("FebR!$A$6:$ZZ$1048576"), MATCH(D$1, FebR!$6:$6, 0), FALSE), 0 ) + IFERROR( VLOOKUP($A29, INDIRECT("MarR!$A$6:$ZZ$1048576"), MATCH(D$1, MarR!$6:$6, 0), FALSE), 0 ) + IFERROR( VLOOKUP($A29, INDIRECT("AbrR!$A$6:$ZZ$1048576"), MATCH(D$1, AbrR!$6:$6, 0), FALSE), 0 ) + IFERROR( VLOOKUP($A29, INDIRECT("MayR!$A$6:$ZZ$1048576"), MATCH(D$1, MayR!$6:$6, 0), FALSE), 0 ) + IFERROR( VLOOKUP($A29, INDIRECT("JunR!$A$6:$ZZ$1048576"), MATCH(D$1, JunR!$6:$6, 0), FALSE), 0 ) + IFERROR( VLOOKUP($A29, INDIRECT("JulR!$A$6:$ZZ$1048576"), MATCH(D$1, JulR!$6:$6, 0), FALSE), 0 ) + IFERROR( VLOOKUP($A29, INDIRECT("AgoR!$A$6:$ZZ$1048576"), MATCH(D$1, AgoR!$6:$6, 0), FALSE), 0 ) + IFERROR( VLOOKUP($A29, INDIRECT("SepR!$A$6:$ZZ$1048576"), MATCH(D$1, SepR!$6:$6, 0), FALSE), 0 ) + IFERROR( VLOOKUP($A29, INDIRECT("OctR!$A$6:$ZZ$1048576"), MATCH(D$1, OctR!$6:$6, 0), FALSE), 0 ) + IFERROR( VLOOKUP($A29, INDIRECT("NovR!$A$6:$ZZ$1048576"), MATCH(D$1, NovR!$6:$6, 0), FALSE), 0 ) + IFERROR( VLOOKUP($A29, INDIRECT("DicR!$A$6:$ZZ$1048576"), MATCH(D$1, DicR!$6:$6, 0), FALSE), 0 ) )} -> 0 | E29: {=SUM( IFERROR( VLOOKUP($A29, INDIRECT("EneR!$A$6:$ZZ$1048576"), MATCH(E$1, EneR!$6:$6, 0), FALSE), 0 ) + IFERROR( VLOOKUP($A29, INDIRECT("FebR!$A$6:$ZZ$1048576"), MATCH(E$1, FebR!$6:$6, 0), FALSE), 0 ) + IFERROR( VLOOKUP($A29, INDIRECT("MarR!$A$6:$ZZ$1048576"), MATCH(E$1, MarR!$6:$6, 0), FALSE), 0 ) + IFERROR( VLOOKUP($A29, INDIRECT("AbrR!$A$6:$ZZ$1048576"), MATCH(E$1, AbrR!$6:$6, 0), FALSE), 0 ) + IFERROR( VLOOKUP($A29, INDIRECT("MayR!$A$6:$ZZ$1048576"), MATCH(E$1, MayR!$6:$6, 0), FALSE), 0 ) + IFERROR( VLOOKUP($A29, INDIRECT("JunR!$A$6:$ZZ$1048576"), MATCH(E$1, JunR!$6:$6, 0), FALSE), 0 ) + IFERROR( VLOOKUP($A29, INDIRECT("JulR!$A$6:$ZZ$1048576"), MATCH(E$1, JulR!$6:$6, 0), FALSE), 0 ) + IFERROR( VLOOKUP($A29, INDIRECT("AgoR!$A$6:$ZZ$1048576"), MATCH(E$1, AgoR!$6:$6, 0), FALSE), 0 ) + IFERROR( VLOOKUP($A29, INDIRECT("SepR!$A$6:$ZZ$1048576"), MATCH(E$1, SepR!$6:$6, 0), FALSE), 0 ) + IFERROR( VLOOKUP($A29, INDIRECT("OctR!$A$6:$ZZ$1048576"), MATCH(E$1, OctR!$6:$6, 0), FALSE), 0 ) + IFERROR( VLOOKUP($A29, INDIRECT("NovR!$A$6:$ZZ$1048576"), MATCH(E$1, NovR!$6:$6, 0), FALSE), 0 ) + IFERROR( VLOOKUP($A29, INDIRECT("DicR!$A$6:$ZZ$1048576"), MATCH(E$1, DicR!$6:$6, 0), FALSE), 0 ) )} -> 0 | F29: {=SUM( IFERROR( VLOOKUP($A29, INDIRECT("EneR!$A$6:$ZZ$1048576"), MATCH(F$1, EneR!$6:$6, 0), FALSE), 0 ) + IFERROR( VLOOKUP($A29, INDIRECT("FebR!$A$6:$ZZ$1048576"), MATCH(F$1, FebR!$6:$6, 0), FALSE), 0 ) + IFERROR( VLOOKUP($A29, INDIRECT("MarR!$A$6:$ZZ$1048576"), MATCH(F$1, MarR!$6:$6, 0), FALSE), 0 ) + IFERROR( VLOOKUP($A29, INDIRECT("AbrR!$A$6:$ZZ$1048576"), MATCH(F$1, AbrR!$6:$6, 0), FALSE), 0 ) + IFERROR( VLOOKUP($A29, INDIRECT("MayR!$A$6:$ZZ$1048576"), MATCH(F$1, MayR!$6:$6, 0), FALSE), 0 ) + IFERROR( VLOOKUP($A29, INDIRECT("JunR!$A$6:$ZZ$1048576"), MATCH(F$1, JunR!$6:$6, 0), FALSE), 0 ) + IFERROR( VLOOKUP($A29, INDIRECT("JulR!$A$6:$ZZ$1048576"), MATCH(F$1, JulR!$6:$6, 0), FALSE), 0 ) + IFERROR( VLOOKUP($A29, INDIRECT("AgoR!$A$6:$ZZ$1048576"), MATCH(F$1, AgoR!$6:$6, 0), FALSE), 0 ) + IFERROR( VLOOKUP($A29, INDIRECT("SepR!$A$6:$ZZ$1048576"), MATCH(F$1, SepR!$6:$6, 0), FALSE), 0 ) + IFERROR( VLOOKUP($A29, INDIRECT("OctR!$A$6:$ZZ$1048576"), MATCH(F$1, OctR!$6:$6, 0), FALSE), 0 ) + IFERROR( VLOOKUP($A29, INDIRECT("NovR!$A$6:$ZZ$1048576"), MATCH(F$1, NovR!$6:$6, 0), FALSE), 0 ) + IFERROR( VLOOKUP($A29, INDIRECT("DicR!$A$6:$ZZ$1048576"), MATCH(F$1, DicR!$6:$6, 0), FALSE), 0 ) )} -> 0 | G29: {=SUM( IFERROR( VLOOKUP($A29, INDIRECT("EneR!$A$6:$ZZ$1048576"), MATCH(G$1, EneR!$6:$6, 0), FALSE), 0 ) + IFERROR( VLOOKUP($A29, INDIRECT("FebR!$A$6:$ZZ$1048576"), MATCH(G$1, FebR!$6:$6, 0), FALSE), 0 ) + IFERROR( VLOOKUP($A29, INDIRECT("MarR!$A$6:$ZZ$1048576"), MATCH(G$1, MarR!$6:$6, 0), FALSE), 0 ) + IFERROR( VLOOKUP($A29, INDIRECT("AbrR!$A$6:$ZZ$1048576"), MATCH(G$1, AbrR!$6:$6, 0), FALSE), 0 ) + IFERROR( VLOOKUP($A29, INDIRECT("MayR!$A$6:$ZZ$1048576"), MATCH(G$1, MayR!$6:$6, 0), FALSE), 0 ) + IFERROR( VLOOKUP($A29, INDIRECT("JunR!$A$6:$ZZ$1048576"), MATCH(G$1, JunR!$6:$6, 0), FALSE), 0 ) + IFERROR( VLOOKUP($A29, INDIRECT("JulR!$A$6:$ZZ$1048576"), MATCH(G$1, JulR!$6:$6, 0), FALSE), 0 ) + IFERROR( VLOOKUP($A29, INDIRECT("AgoR!$A$6:$ZZ$1048576"), MATCH(G$1, AgoR!$6:$6, 0), FALSE), 0 ) + IFERROR( VLOOKUP($A29, INDIRECT("SepR!$A$6:$ZZ$1048576"), MATCH(G$1, SepR!$6:$6, 0), FALSE), 0 ) + IFERROR( VLOOKUP($A29, INDIRECT("OctR!$A$6:$ZZ$1048576"), MATCH(G$1, OctR!$6:$6, 0), FALSE), 0 ) + IFERROR( VLOOKUP($A29, INDIRECT("NovR!$A$6:$ZZ$1048576"), MATCH(G$1, NovR!$6:$6, 0), FALSE), 0 ) + IFERROR( VLOOKUP($A29, INDIRECT("DicR!$A$6:$ZZ$1048576"), MATCH(G$1, DicR!$6:$6, 0), FALSE), 0 ) )} -> 0 | H29: {=SUM( IFERROR( VLOOKUP($A29, INDIRECT("EneR!$A$6:$ZZ$1048576"), MATCH(H$1, EneR!$6:$6, 0), FALSE), 0 ) + IFERROR( VLOOKUP($A29, INDIRECT("FebR!$A$6:$ZZ$1048576"), MATCH(H$1, FebR!$6:$6, 0), FALSE), 0 ) + IFERROR( VLOOKUP($A29, INDIRECT("MarR!$A$6:$ZZ$1048576"), MATCH(H$1, MarR!$6:$6, 0), FALSE), 0 ) + IFERROR( VLOOKUP($A29, INDIRECT("AbrR!$A$6:$ZZ$1048576"), MATCH(H$1, AbrR!$6:$6, 0), FALSE), 0 ) + IFERROR( VLOOKUP($A29, INDIRECT("MayR!$A$6:$ZZ$1048576"), MATCH(H$1, MayR!$6:$6, 0), FALSE), 0 ) + IFERROR( VLOOKUP($A29, INDIRECT("JunR!$A$6:$ZZ$1048576"), MATCH(H$1, JunR!$6:$6, 0), FALSE), 0 ) + IFERROR( VLOOKUP($A29, INDIRECT("JulR!$A$6:$ZZ$1048576"), MATCH(H$1, JulR!$6:$6, 0), FALSE), 0 ) + IFERROR( VLOOKUP($A29, INDIRECT("AgoR!$A$6:$ZZ$1048576"), MATCH(H$1, AgoR!$6:$6, 0), FALSE), 0 ) + IFERROR( VLOOKUP($A29, INDIRECT("SepR!$A$6:$ZZ$1048576"), MATCH(H$1, SepR!$6:$6, 0), FALSE), 0 ) + IFERROR( VLOOKUP($A29, INDIRECT("OctR!$A$6:$ZZ$1048576"), MATCH(H$1, OctR!$6:$6, 0), FALSE), 0 ) + IFERROR( VLOOKUP($A29, INDIRECT("NovR!$A$6:$ZZ$1048576"), MATCH(H$1, NovR!$6:$6, 0), FALSE), 0 ) + IFERROR( VLOOKUP($A29, INDIRECT("DicR!$A$6:$ZZ$1048576"), MATCH(H$1, DicR!$6:$6, 0), FALSE), 0 ) )} -> 0 | I29: {=SUM( IFERROR( VLOOKUP($A29, INDIRECT("EneR!$A$6:$ZZ$1048576"), MATCH(I$1, EneR!$6:$6, 0), FALSE), 0 ) + IFERROR( VLOOKUP($A29, INDIRECT("FebR!$A$6:$ZZ$1048576"), MATCH(I$1, FebR!$6:$6, 0), FALSE), 0 ) + IFERROR( VLOOKUP($A29, INDIRECT("MarR!$A$6:$ZZ$1048576"), MATCH(I$1, MarR!$6:$6, 0), FALSE), 0 ) + IFERROR( VLOOKUP($A29, INDIRECT("AbrR!$A$6:$ZZ$1048576"), MATCH(I$1, AbrR!$6:$6, 0), FALSE), 0 ) + IFERROR( VLOOKUP($A29, INDIRECT("MayR!$A$6:$ZZ$1048576"), MATCH(I$1, MayR!$6:$6, 0), FALSE), 0 ) + IFERROR( VLOOKUP($A29, INDIRECT("JunR!$A$6:$ZZ$1048576"), MATCH(I$1, JunR!$6:$6, 0), FALSE), 0 ) + IFERROR( VLOOKUP($A29, INDIRECT("JulR!$A$6:$ZZ$1048576"), MATCH(I$1, JulR!$6:$6, 0), FALSE), 0 ) + IFERROR( VLOOKUP($A29, INDIRECT("AgoR!$A$6:$ZZ$1048576"), MATCH(I$1, AgoR!$6:$6, 0), FALSE), 0 ) + IFERROR( VLOOKUP($A29, INDIRECT("SepR!$A$6:$ZZ$1048576"), MATCH(I$1, SepR!$6:$6, 0), FALSE), 0 ) + IFERROR( VLOOKUP($A29, INDIRECT("OctR!$A$6:$ZZ$1048576"), MATCH(I$1, OctR!$6:$6, 0), FALSE), 0 ) + IFERROR( VLOOKUP($A29, INDIRECT("NovR!$A$6:$ZZ$1048576"), MATCH(I$1, NovR!$6:$6, 0), FALSE), 0 ) + IFERROR( VLOOKUP($A29, INDIRECT("DicR!$A$6:$ZZ$1048576"), MATCH(I$1, DicR!$6:$6, 0), FALSE), 0 ) )} -> 0 | J29: {=SUM( IFERROR( VLOOKUP($A29, INDIRECT("EneR!$A$6:$ZZ$1048576"), MATCH(J$1, EneR!$6:$6, 0), FALSE), 0 ) + IFERROR( VLOOKUP($A29, INDIRECT("FebR!$A$6:$ZZ$1048576"), MATCH(J$1, FebR!$6:$6, 0), FALSE), 0 ) + IFERROR( VLOOKUP($A29, INDIRECT("MarR!$A$6:$ZZ$1048576"), MATCH(J$1, MarR!$6:$6, 0), FALSE), 0 ) + IFERROR( VLOOKUP($A29, INDIRECT("AbrR!$A$6:$ZZ$1048576"), MATCH(J$1, AbrR!$6:$6, 0), FALSE), 0 ) + IFERROR( VLOOKUP($A29, INDIRECT("MayR!$A$6:$ZZ$1048576"), MATCH(J$1, MayR!$6:$6, 0), FALSE), 0 ) + IFERROR( VLOOKUP($A29, INDIRECT("JunR!$A$6:$ZZ$1048576"), MATCH(J$1, JunR!$6:$6, 0), FALSE), 0 ) + IFERROR( VLOOKUP($A29, INDIRECT("JulR!$A$6:$ZZ$1048576"), MATCH(J$1, JulR!$6:$6, 0), FALSE), 0 ) + IFERROR( VLOOKUP($A29, INDIRECT("AgoR!$A$6:$ZZ$1048576"), MATCH(J$1, AgoR!$6:$6, 0), FALSE), 0 ) + IFERROR( VLOOKUP($A29, INDIRECT("SepR!$A$6:$ZZ$1048576"), MATCH(J$1, SepR!$6:$6, 0), FALSE), 0 ) + IFERROR( VLOOKUP($A29, INDIRECT("OctR!$A$6:$ZZ$1048576"), MATCH(J$1, OctR!$6:$6, 0), FALSE), 0 ) + IFERROR( VLOOKUP($A29, INDIRECT("NovR!$A$6:$ZZ$1048576"), MATCH(J$1, NovR!$6:$6, 0), FALSE), 0 ) + IFERROR( VLOOKUP($A29, INDIRECT("DicR!$A$6:$ZZ$1048576"), MATCH(J$1, DicR!$6:$6, 0), FALSE), 0 ) )} -> 0 | K29: {=SUM( IFERROR( VLOOKUP($A29, INDIRECT("EneR!$A$6:$ZZ$1048576"), MATCH(K$1, EneR!$6:$6, 0), FALSE), 0 ) + IFERROR( VLOOKUP($A29, INDIRECT("FebR!$A$6:$ZZ$1048576"), MATCH(K$1, FebR!$6:$6, 0), FALSE), 0 ) + IFERROR( VLOOKUP($A29, INDIRECT("MarR!$A$6:$ZZ$1048576"), MATCH(K$1, MarR!$6:$6, 0), FALSE), 0 ) + IFERROR( VLOOKUP($A29, INDIRECT("AbrR!$A$6:$ZZ$1048576"), MATCH(K$1, AbrR!$6:$6, 0), FALSE), 0 ) + IFERROR( VLOOKUP($A29, INDIRECT("MayR!$A$6:$ZZ$1048576"), MATCH(K$1, MayR!$6:$6, 0), FALSE), 0 ) + IFERROR( VLOOKUP($A29, INDIRECT("JunR!$A$6:$ZZ$1048576"), MATCH(K$1, JunR!$6:$6, 0), FALSE), 0 ) + IFERROR( VLOOKUP($A29, INDIRECT("JulR!$A$6:$ZZ$1048576"), MATCH(K$1, JulR!$6:$6, 0), FALSE), 0 ) + IFERROR( VLOOKUP($A29, INDIRECT("AgoR!$A$6:$ZZ$1048576"), MATCH(K$1, AgoR!$6:$6, 0), FALSE), 0 ) + IFERROR( VLOOKUP($A29, INDIRECT("SepR!$A$6:$ZZ$1048576"), MATCH(K$1, SepR!$6:$6, 0), FALSE), 0 ) + IFERROR( VLOOKUP($A29, INDIRECT("OctR!$A$6:$ZZ$1048576"), MATCH(K$1, OctR!$6:$6, 0), FALSE), 0 ) + IFERROR( VLOOKUP($A29, INDIRECT("NovR!$A$6:$ZZ$1048576"), MATCH(K$1, NovR!$6:$6, 0), FALSE), 0 ) + IFERROR( VLOOKUP($A29, INDIRECT("DicR!$A$6:$ZZ$1048576"), MATCH(K$1, DicR!$6:$6, 0), FALSE), 0 ) )} -> 0 | ... AY29: {=SUM( IFERROR( VLOOKUP($A29, INDIRECT("EneR!$A$6:$ZZ$1048576"), MATCH(AY$1, EneR!$6:$6, 0), FALSE), 0 ) + IFERROR( VLOOKUP($A29, INDIRECT("FebR!$A$6:$ZZ$1048576"), MATCH(AY$1, FebR!$6:$6, 0), FALSE), 0 ) + IFERROR( VLOOKUP($A29, INDIRECT("MarR!$A$6:$ZZ$1048576"), MATCH(AY$1, MarR!$6:$6, 0), FALSE), 0 ) + IFERROR( VLOOKUP($A29, INDIRECT("AbrR!$A$6:$ZZ$1048576"), MATCH(AY$1, AbrR!$6:$6, 0), FALSE), 0 ) + IFERROR( VLOOKUP($A29, INDIRECT("MayR!$A$6:$ZZ$1048576"), MATCH(AY$1, MayR!$6:$6, 0), FALSE), 0 ) + IFERROR( VLOOKUP($A29, INDIRECT("JunR!$A$6:$ZZ$1048576"), MATCH(AY$1, JunR!$6:$6, 0), FALSE), 0 ) + IFERROR( VLOOKUP($A29, INDIRECT("JulR!$A$6:$ZZ$1048576"), MATCH(AY$1, JulR!$6:$6, 0), FALSE), 0 ) + IFERROR( VLOOKUP($A29, INDIRECT("AgoR!$A$6:$ZZ$1048576"), MATCH(AY$1, AgoR!$6:$6, 0), FALSE), 0 ) + IFERROR( VLOOKUP($A29, INDIRECT("SepR!$A$6:$ZZ$1048576"), MATCH(AY$1, SepR!$6:$6, 0), FALSE), 0 ) + IFERROR( VLOOKUP($A29, INDIRECT("OctR!$A$6:$ZZ$1048576"), MATCH(AY$1, OctR!$6:$6, 0), FALSE), 0 ) + IFERROR( VLOOKUP($A29, INDIRECT("NovR!$A$6:$ZZ$1048576"), MATCH(AY$1, NovR!$6:$6, 0), FALSE), 0 ) + IFERROR( VLOOKUP($A29, INDIRECT("DicR!$A$6:$ZZ$1048576"), MATCH(AY$1, DicR!$6:$6, 0), FALSE), 0 ) )} -> 0
A30: =Menus!R22 | B30: =IFERROR(SUM(D30:AR30),"") -> 0 | C30: =IFERROR(INDEX($D$1:$AQ$69, MATCH($A30, $A$1:$A$109, 0), MATCH(C$1, $D$1:AZ$1, 0)), "") | D30: {=SUM( IFERROR( VLOOKUP($A30, INDIRECT("EneR!$A$6:$ZZ$1048576"), MATCH(D$1, EneR!$6:$6, 0), FALSE), 0 ) + IFERROR( VLOOKUP($A30, INDIRECT("FebR!$A$6:$ZZ$1048576"), MATCH(D$1, FebR!$6:$6, 0), FALSE), 0 ) + IFERROR( VLOOKUP($A30, INDIRECT("MarR!$A$6:$ZZ$1048576"), MATCH(D$1, MarR!$6:$6, 0), FALSE), 0 ) + IFERROR( VLOOKUP($A30, INDIRECT("AbrR!$A$6:$ZZ$1048576"), MATCH(D$1, AbrR!$6:$6, 0), FALSE), 0 ) + IFERROR( VLOOKUP($A30, INDIRECT("MayR!$A$6:$ZZ$1048576"), MATCH(D$1, MayR!$6:$6, 0), FALSE), 0 ) + IFERROR( VLOOKUP($A30, INDIRECT("JunR!$A$6:$ZZ$1048576"), MATCH(D$1, JunR!$6:$6, 0), FALSE), 0 ) + IFERROR( VLOOKUP($A30, INDIRECT("JulR!$A$6:$ZZ$1048576"), MATCH(D$1, JulR!$6:$6, 0), FALSE), 0 ) + IFERROR( VLOOKUP($A30, INDIRECT("AgoR!$A$6:$ZZ$1048576"), MATCH(D$1, AgoR!$6:$6, 0), FALSE), 0 ) + IFERROR( VLOOKUP($A30, INDIRECT("SepR!$A$6:$ZZ$1048576"), MATCH(D$1, SepR!$6:$6, 0), FALSE), 0 ) + IFERROR( VLOOKUP($A30, INDIRECT("OctR!$A$6:$ZZ$1048576"), MATCH(D$1, OctR!$6:$6, 0), FALSE), 0 ) + IFERROR( VLOOKUP($A30, INDIRECT("NovR!$A$6:$ZZ$1048576"), MATCH(D$1, NovR!$6:$6, 0), FALSE), 0 ) + IFERROR( VLOOKUP($A30, INDIRECT("DicR!$A$6:$ZZ$1048576"), MATCH(D$1, DicR!$6:$6, 0), FALSE), 0 ) )} -> 0 | E30: {=SUM( IFERROR( VLOOKUP($A30, INDIRECT("EneR!$A$6:$ZZ$1048576"), MATCH(E$1, EneR!$6:$6, 0), FALSE), 0 ) + IFERROR( VLOOKUP($A30, INDIRECT("FebR!$A$6:$ZZ$1048576"), MATCH(E$1, FebR!$6:$6, 0), FALSE), 0 ) + IFERROR( VLOOKUP($A30, INDIRECT("MarR!$A$6:$ZZ$1048576"), MATCH(E$1, MarR!$6:$6, 0), FALSE), 0 ) + IFERROR( VLOOKUP($A30, INDIRECT("AbrR!$A$6:$ZZ$1048576"), MATCH(E$1, AbrR!$6:$6, 0), FALSE), 0 ) + IFERROR( VLOOKUP($A30, INDIRECT("MayR!$A$6:$ZZ$1048576"), MATCH(E$1, MayR!$6:$6, 0), FALSE), 0 ) + IFERROR( VLOOKUP($A30, INDIRECT("JunR!$A$6:$ZZ$1048576"), MATCH(E$1, JunR!$6:$6, 0), FALSE), 0 ) + IFERROR( VLOOKUP($A30, INDIRECT("JulR!$A$6:$ZZ$1048576"), MATCH(E$1, JulR!$6:$6, 0), FALSE), 0 ) + IFERROR( VLOOKUP($A30, INDIRECT("AgoR!$A$6:$ZZ$1048576"), MATCH(E$1, AgoR!$6:$6, 0), FALSE), 0 ) + IFERROR( VLOOKUP($A30, INDIRECT("SepR!$A$6:$ZZ$1048576"), MATCH(E$1, SepR!$6:$6, 0), FALSE), 0 ) + IFERROR( VLOOKUP($A30, INDIRECT("OctR!$A$6:$ZZ$1048576"), MATCH(E$1, OctR!$6:$6, 0), FALSE), 0 ) + IFERROR( VLOOKUP($A30, INDIRECT("NovR!$A$6:$ZZ$1048576"), MATCH(E$1, NovR!$6:$6, 0), FALSE), 0 ) + IFERROR( VLOOKUP($A30, INDIRECT("DicR!$A$6:$ZZ$1048576"), MATCH(E$1, DicR!$6:$6, 0), FALSE), 0 ) )} -> 0 | F30: {=SUM( IFERROR( VLOOKUP($A30, INDIRECT("EneR!$A$6:$ZZ$1048576"), MATCH(F$1, EneR!$6:$6, 0), FALSE), 0 ) + IFERROR( VLOOKUP($A30, INDIRECT("FebR!$A$6:$ZZ$1048576"), MATCH(F$1, FebR!$6:$6, 0), FALSE), 0 ) + IFERROR( VLOOKUP($A30, INDIRECT("MarR!$A$6:$ZZ$1048576"), MATCH(F$1, MarR!$6:$6, 0), FALSE), 0 ) + IFERROR( VLOOKUP($A30, INDIRECT("AbrR!$A$6:$ZZ$1048576"), MATCH(F$1, AbrR!$6:$6, 0), FALSE), 0 ) + IFERROR( VLOOKUP($A30, INDIRECT("MayR!$A$6:$ZZ$1048576"), MATCH(F$1, MayR!$6:$6, 0), FALSE), 0 ) + IFERROR( VLOOKUP($A30, INDIRECT("JunR!$A$6:$ZZ$1048576"), MATCH(F$1, JunR!$6:$6, 0), FALSE), 0 ) + IFERROR( VLOOKUP($A30, INDIRECT("JulR!$A$6:$ZZ$1048576"), MATCH(F$1, JulR!$6:$6, 0), FALSE), 0 ) + IFERROR( VLOOKUP($A30, INDIRECT("AgoR!$A$6:$ZZ$1048576"), MATCH(F$1, AgoR!$6:$6, 0), FALSE), 0 ) + IFERROR( VLOOKUP($A30, INDIRECT("SepR!$A$6:$ZZ$1048576"), MATCH(F$1, SepR!$6:$6, 0), FALSE), 0 ) + IFERROR( VLOOKUP($A30, INDIRECT("OctR!$A$6:$ZZ$1048576"), MATCH(F$1, OctR!$6:$6, 0), FALSE), 0 ) + IFERROR( VLOOKUP($A30, INDIRECT("NovR!$A$6:$ZZ$1048576"), MATCH(F$1, NovR!$6:$6, 0), FALSE), 0 ) + IFERROR( VLOOKUP($A30, INDIRECT("DicR!$A$6:$ZZ$1048576"), MATCH(F$1, DicR!$6:$6, 0), FALSE), 0 ) )} -> 0 | G30: {=SUM( IFERROR( VLOOKUP($A30, INDIRECT("EneR!$A$6:$ZZ$1048576"), MATCH(G$1, EneR!$6:$6, 0), FALSE), 0 ) + IFERROR( VLOOKUP($A30, INDIRECT("FebR!$A$6:$ZZ$1048576"), MATCH(G$1, FebR!$6:$6, 0), FALSE), 0 ) + IFERROR( VLOOKUP($A30, INDIRECT("MarR!$A$6:$ZZ$1048576"), MATCH(G$1, MarR!$6:$6, 0), FALSE), 0 ) + IFERROR( VLOOKUP($A30, INDIRECT("AbrR!$A$6:$ZZ$1048576"), MATCH(G$1, AbrR!$6:$6, 0), FALSE), 0 ) + IFERROR( VLOOKUP($A30, INDIRECT("MayR!$A$6:$ZZ$1048576"), MATCH(G$1, MayR!$6:$6, 0), FALSE), 0 ) + IFERROR( VLOOKUP($A30, INDIRECT("JunR!$A$6:$ZZ$1048576"), MATCH(G$1, JunR!$6:$6, 0), FALSE), 0 ) + IFERROR( VLOOKUP($A30, INDIRECT("JulR!$A$6:$ZZ$1048576"), MATCH(G$1, JulR!$6:$6, 0), FALSE), 0 ) + IFERROR( VLOOKUP($A30, INDIRECT("AgoR!$A$6:$ZZ$1048576"), MATCH(G$1, AgoR!$6:$6, 0), FALSE), 0 ) + IFERROR( VLOOKUP($A30, INDIRECT("SepR!$A$6:$ZZ$1048576"), MATCH(G$1, SepR!$6:$6, 0), FALSE), 0 ) + IFERROR( VLOOKUP($A30, INDIRECT("OctR!$A$6:$ZZ$1048576"), MATCH(G$1, OctR!$6:$6, 0), FALSE), 0 ) + IFERROR( VLOOKUP($A30, INDIRECT("NovR!$A$6:$ZZ$1048576"), MATCH(G$1, NovR!$6:$6, 0), FALSE), 0 ) + IFERROR( VLOOKUP($A30, INDIRECT("DicR!$A$6:$ZZ$1048576"), MATCH(G$1, DicR!$6:$6, 0), FALSE), 0 ) )} -> 0 | H30: {=SUM( IFERROR( VLOOKUP($A30, INDIRECT("EneR!$A$6:$ZZ$1048576"), MATCH(H$1, EneR!$6:$6, 0), FALSE), 0 ) + IFERROR( VLOOKUP($A30, INDIRECT("FebR!$A$6:$ZZ$1048576"), MATCH(H$1, FebR!$6:$6, 0), FALSE), 0 ) + IFERROR( VLOOKUP($A30, INDIRECT("MarR!$A$6:$ZZ$1048576"), MATCH(H$1, MarR!$6:$6, 0), FALSE), 0 ) + IFERROR( VLOOKUP($A30, INDIRECT("AbrR!$A$6:$ZZ$1048576"), MATCH(H$1, AbrR!$6:$6, 0), FALSE), 0 ) + IFERROR( VLOOKUP($A30, INDIRECT("MayR!$A$6:$ZZ$1048576"), MATCH(H$1, MayR!$6:$6, 0), FALSE), 0 ) + IFERROR( VLOOKUP($A30, INDIRECT("JunR!$A$6:$ZZ$1048576"), MATCH(H$1, JunR!$6:$6, 0), FALSE), 0 ) + IFERROR( VLOOKUP($A30, INDIRECT("JulR!$A$6:$ZZ$1048576"), MATCH(H$1, JulR!$6:$6, 0), FALSE), 0 ) + IFERROR( VLOOKUP($A30, INDIRECT("AgoR!$A$6:$ZZ$1048576"), MATCH(H$1, AgoR!$6:$6, 0), FALSE), 0 ) + IFERROR( VLOOKUP($A30, INDIRECT("SepR!$A$6:$ZZ$1048576"), MATCH(H$1, SepR!$6:$6, 0), FALSE), 0 ) + IFERROR( VLOOKUP($A30, INDIRECT("OctR!$A$6:$ZZ$1048576"), MATCH(H$1, OctR!$6:$6, 0), FALSE), 0 ) + IFERROR( VLOOKUP($A30, INDIRECT("NovR!$A$6:$ZZ$1048576"), MATCH(H$1, NovR!$6:$6, 0), FALSE), 0 ) + IFERROR( VLOOKUP($A30, INDIRECT("DicR!$A$6:$ZZ$1048576"), MATCH(H$1, DicR!$6:$6, 0), FALSE), 0 ) )} -> 0 | I30: {=SUM( IFERROR( VLOOKUP($A30, INDIRECT("EneR!$A$6:$ZZ$1048576"), MATCH(I$1, EneR!$6:$6, 0), FALSE), 0 ) + IFERROR( VLOOKUP($A30, INDIRECT("FebR!$A$6:$ZZ$1048576"), MATCH(I$1, FebR!$6:$6, 0), FALSE), 0 ) + IFERROR( VLOOKUP($A30, INDIRECT("MarR!$A$6:$ZZ$1048576"), MATCH(I$1, MarR!$6:$6, 0), FALSE), 0 ) + IFERROR( VLOOKUP($A30, INDIRECT("AbrR!$A$6:$ZZ$1048576"), MATCH(I$1, AbrR!$6:$6, 0), FALSE), 0 ) + IFERROR( VLOOKUP($A30, INDIRECT("MayR!$A$6:$ZZ$1048576"), MATCH(I$1, MayR!$6:$6, 0), FALSE), 0 ) + IFERROR( VLOOKUP($A30, INDIRECT("JunR!$A$6:$ZZ$1048576"), MATCH(I$1, JunR!$6:$6, 0), FALSE), 0 ) + IFERROR( VLOOKUP($A30, INDIRECT("JulR!$A$6:$ZZ$1048576"), MATCH(I$1, JulR!$6:$6, 0), FALSE), 0 ) + IFERROR( VLOOKUP($A30, INDIRECT("AgoR!$A$6:$ZZ$1048576"), MATCH(I$1, AgoR!$6:$6, 0), FALSE), 0 ) + IFERROR( VLOOKUP($A30, INDIRECT("SepR!$A$6:$ZZ$1048576"), MATCH(I$1, SepR!$6:$6, 0), FALSE), 0 ) + IFERROR( VLOOKUP($A30, INDIRECT("OctR!$A$6:$ZZ$1048576"), MATCH(I$1, OctR!$6:$6, 0), FALSE), 0 ) + IFERROR( VLOOKUP($A30, INDIRECT("NovR!$A$6:$ZZ$1048576"), MATCH(I$1, NovR!$6:$6, 0), FALSE), 0 ) + IFERROR( VLOOKUP($A30, INDIRECT("DicR!$A$6:$ZZ$1048576"), MATCH(I$1, DicR!$6:$6, 0), FALSE), 0 ) )} -> 0 | J30: {=SUM( IFERROR( VLOOKUP($A30, INDIRECT("EneR!$A$6:$ZZ$1048576"), MATCH(J$1, EneR!$6:$6, 0), FALSE), 0 ) + IFERROR( VLOOKUP($A30, INDIRECT("FebR!$A$6:$ZZ$1048576"), MATCH(J$1, FebR!$6:$6, 0), FALSE), 0 ) + IFERROR( VLOOKUP($A30, INDIRECT("MarR!$A$6:$ZZ$1048576"), MATCH(J$1, MarR!$6:$6, 0), FALSE), 0 ) + IFERROR( VLOOKUP($A30, INDIRECT("AbrR!$A$6:$ZZ$1048576"), MATCH(J$1, AbrR!$6:$6, 0), FALSE), 0 ) + IFERROR( VLOOKUP($A30, INDIRECT("MayR!$A$6:$ZZ$1048576"), MATCH(J$1, MayR!$6:$6, 0), FALSE), 0 ) + IFERROR( VLOOKUP($A30, INDIRECT("JunR!$A$6:$ZZ$1048576"), MATCH(J$1, JunR!$6:$6, 0), FALSE), 0 ) + IFERROR( VLOOKUP($A30, INDIRECT("JulR!$A$6:$ZZ$1048576"), MATCH(J$1, JulR!$6:$6, 0), FALSE), 0 ) + IFERROR( VLOOKUP($A30, INDIRECT("AgoR!$A$6:$ZZ$1048576"), MATCH(J$1, AgoR!$6:$6, 0), FALSE), 0 ) + IFERROR( VLOOKUP($A30, INDIRECT("SepR!$A$6:$ZZ$1048576"), MATCH(J$1, SepR!$6:$6, 0), FALSE), 0 ) + IFERROR( VLOOKUP($A30, INDIRECT("OctR!$A$6:$ZZ$1048576"), MATCH(J$1, OctR!$6:$6, 0), FALSE), 0 ) + IFERROR( VLOOKUP($A30, INDIRECT("NovR!$A$6:$ZZ$1048576"), MATCH(J$1, NovR!$6:$6, 0), FALSE), 0 ) + IFERROR( VLOOKUP($A30, INDIRECT("DicR!$A$6:$ZZ$1048576"), MATCH(J$1, DicR!$6:$6, 0), FALSE), 0 ) )} -> 0 | K30: {=SUM( IFERROR( VLOOKUP($A30, INDIRECT("EneR!$A$6:$ZZ$1048576"), MATCH(K$1, EneR!$6:$6, 0), FALSE), 0 ) + IFERROR( VLOOKUP($A30, INDIRECT("FebR!$A$6:$ZZ$1048576"), MATCH(K$1, FebR!$6:$6, 0), FALSE), 0 ) + IFERROR( VLOOKUP($A30, INDIRECT("MarR!$A$6:$ZZ$1048576"), MATCH(K$1, MarR!$6:$6, 0), FALSE), 0 ) + IFERROR( VLOOKUP($A30, INDIRECT("AbrR!$A$6:$ZZ$1048576"), MATCH(K$1, AbrR!$6:$6, 0), FALSE), 0 ) + IFERROR( VLOOKUP($A30, INDIRECT("MayR!$A$6:$ZZ$1048576"), MATCH(K$1, MayR!$6:$6, 0), FALSE), 0 ) + IFERROR( VLOOKUP($A30, INDIRECT("JunR!$A$6:$ZZ$1048576"), MATCH(K$1, JunR!$6:$6, 0), FALSE), 0 ) + IFERROR( VLOOKUP($A30, INDIRECT("JulR!$A$6:$ZZ$1048576"), MATCH(K$1, JulR!$6:$6, 0), FALSE), 0 ) + IFERROR( VLOOKUP($A30, INDIRECT("AgoR!$A$6:$ZZ$1048576"), MATCH(K$1, AgoR!$6:$6, 0), FALSE), 0 ) + IFERROR( VLOOKUP($A30, INDIRECT("SepR!$A$6:$ZZ$1048576"), MATCH(K$1, SepR!$6:$6, 0), FALSE), 0 ) + IFERROR( VLOOKUP($A30, INDIRECT("OctR!$A$6:$ZZ$1048576"), MATCH(K$1, OctR!$6:$6, 0), FALSE), 0 ) + IFERROR( VLOOKUP($A30, INDIRECT("NovR!$A$6:$ZZ$1048576"), MATCH(K$1, NovR!$6:$6, 0), FALSE), 0 ) + IFERROR( VLOOKUP($A30, INDIRECT("DicR!$A$6:$ZZ$1048576"), MATCH(K$1, DicR!$6:$6, 0), FALSE), 0 ) )} -> 0 | ... AY30: {=SUM( IFERROR( VLOOKUP($A30, INDIRECT("EneR!$A$6:$ZZ$1048576"), MATCH(AY$1, EneR!$6:$6, 0), FALSE), 0 ) + IFERROR( VLOOKUP($A30, INDIRECT("FebR!$A$6:$ZZ$1048576"), MATCH(AY$1, FebR!$6:$6, 0), FALSE), 0 ) + IFERROR( VLOOKUP($A30, INDIRECT("MarR!$A$6:$ZZ$1048576"), MATCH(AY$1, MarR!$6:$6, 0), FALSE), 0 ) + IFERROR( VLOOKUP($A30, INDIRECT("AbrR!$A$6:$ZZ$1048576"), MATCH(AY$1, AbrR!$6:$6, 0), FALSE), 0 ) + IFERROR( VLOOKUP($A30, INDIRECT("MayR!$A$6:$ZZ$1048576"), MATCH(AY$1, MayR!$6:$6, 0), FALSE), 0 ) + IFERROR( VLOOKUP($A30, INDIRECT("JunR!$A$6:$ZZ$1048576"), MATCH(AY$1, JunR!$6:$6, 0), FALSE), 0 ) + IFERROR( VLOOKUP($A30, INDIRECT("JulR!$A$6:$ZZ$1048576"), MATCH(AY$1, JulR!$6:$6, 0), FALSE), 0 ) + IFERROR( VLOOKUP($A30, INDIRECT("AgoR!$A$6:$ZZ$1048576"), MATCH(AY$1, AgoR!$6:$6, 0), FALSE), 0 ) + IFERROR( VLOOKUP($A30, INDIRECT("SepR!$A$6:$ZZ$1048576"), MATCH(AY$1, SepR!$6:$6, 0), FALSE), 0 ) + IFERROR( VLOOKUP($A30, INDIRECT("OctR!$A$6:$ZZ$1048576"), MATCH(AY$1, OctR!$6:$6, 0), FALSE), 0 ) + IFERROR( VLOOKUP($A30, INDIRECT("NovR!$A$6:$ZZ$1048576"), MATCH(AY$1, NovR!$6:$6, 0), FALSE), 0 ) + IFERROR( VLOOKUP($A30, INDIRECT("DicR!$A$6:$ZZ$1048576"), MATCH(AY$1, DicR!$6:$6, 0), FALSE), 0 ) )} -> 0
A31: =Menus!R23 | B31: =IFERROR(SUM(D31:AR31),"") -> 0 | C31: =IFERROR(INDEX($D$1:$AQ$69, MATCH($A31, $A$1:$A$109, 0), MATCH(C$1, $D$1:AZ$1, 0)), "") | D31: {=SUM( IFERROR( VLOOKUP($A31, INDIRECT("EneR!$A$6:$ZZ$1048576"), MATCH(D$1, EneR!$6:$6, 0), FALSE), 0 ) + IFERROR( VLOOKUP($A31, INDIRECT("FebR!$A$6:$ZZ$1048576"), MATCH(D$1, FebR!$6:$6, 0), FALSE), 0 ) + IFERROR( VLOOKUP($A31, INDIRECT("MarR!$A$6:$ZZ$1048576"), MATCH(D$1, MarR!$6:$6, 0), FALSE), 0 ) + IFERROR( VLOOKUP($A31, INDIRECT("AbrR!$A$6:$ZZ$1048576"), MATCH(D$1, AbrR!$6:$6, 0), FALSE), 0 ) + IFERROR( VLOOKUP($A31, INDIRECT("MayR!$A$6:$ZZ$1048576"), MATCH(D$1, MayR!$6:$6, 0), FALSE), 0 ) + IFERROR( VLOOKUP($A31, INDIRECT("JunR!$A$6:$ZZ$1048576"), MATCH(D$1, JunR!$6:$6, 0), FALSE), 0 ) + IFERROR( VLOOKUP($A31, INDIRECT("JulR!$A$6:$ZZ$1048576"), MATCH(D$1, JulR!$6:$6, 0), FALSE), 0 ) + IFERROR( VLOOKUP($A31, INDIRECT("AgoR!$A$6:$ZZ$1048576"), MATCH(D$1, AgoR!$6:$6, 0), FALSE), 0 ) + IFERROR( VLOOKUP($A31, INDIRECT("SepR!$A$6:$ZZ$1048576"), MATCH(D$1, SepR!$6:$6, 0), FALSE), 0 ) + IFERROR( VLOOKUP($A31, INDIRECT("OctR!$A$6:$ZZ$1048576"), MATCH(D$1, OctR!$6:$6, 0), FALSE), 0 ) + IFERROR( VLOOKUP($A31, INDIRECT("NovR!$A$6:$ZZ$1048576"), MATCH(D$1, NovR!$6:$6, 0), FALSE), 0 ) + IFERROR( VLOOKUP($A31, INDIRECT("DicR!$A$6:$ZZ$1048576"), MATCH(D$1, DicR!$6:$6, 0), FALSE), 0 ) )} -> 0 | E31: {=SUM( IFERROR( VLOOKUP($A31, INDIRECT("EneR!$A$6:$ZZ$1048576"), MATCH(E$1, EneR!$6:$6, 0), FALSE), 0 ) + IFERROR( VLOOKUP($A31, INDIRECT("FebR!$A$6:$ZZ$1048576"), MATCH(E$1, FebR!$6:$6, 0), FALSE), 0 ) + IFERROR( VLOOKUP($A31, INDIRECT("MarR!$A$6:$ZZ$1048576"), MATCH(E$1, MarR!$6:$6, 0), FALSE), 0 ) + IFERROR( VLOOKUP($A31, INDIRECT("AbrR!$A$6:$ZZ$1048576"), MATCH(E$1, AbrR!$6:$6, 0), FALSE), 0 ) + IFERROR( VLOOKUP($A31, INDIRECT("MayR!$A$6:$ZZ$1048576"), MATCH(E$1, MayR!$6:$6, 0), FALSE), 0 ) + IFERROR( VLOOKUP($A31, INDIRECT("JunR!$A$6:$ZZ$1048576"), MATCH(E$1, JunR!$6:$6, 0), FALSE), 0 ) + IFERROR( VLOOKUP($A31, INDIRECT("JulR!$A$6:$ZZ$1048576"), MATCH(E$1, JulR!$6:$6, 0), FALSE), 0 ) + IFERROR( VLOOKUP($A31, INDIRECT("AgoR!$A$6:$ZZ$1048576"), MATCH(E$1, AgoR!$6:$6, 0), FALSE), 0 ) + IFERROR( VLOOKUP($A31, INDIRECT("SepR!$A$6:$ZZ$1048576"), MATCH(E$1, SepR!$6:$6, 0), FALSE), 0 ) + IFERROR( VLOOKUP($A31, INDIRECT("OctR!$A$6:$ZZ$1048576"), MATCH(E$1, OctR!$6:$6, 0), FALSE), 0 ) + IFERROR( VLOOKUP($A31, INDIRECT("NovR!$A$6:$ZZ$1048576"), MATCH(E$1, NovR!$6:$6, 0), FALSE), 0 ) + IFERROR( VLOOKUP($A31, INDIRECT("DicR!$A$6:$ZZ$1048576"), MATCH(E$1, DicR!$6:$6, 0), FALSE), 0 ) )} -> 0 | F31: {=SUM( IFERROR( VLOOKUP($A31, INDIRECT("EneR!$A$6:$ZZ$1048576"), MATCH(F$1, EneR!$6:$6, 0), FALSE), 0 ) + IFERROR( VLOOKUP($A31, INDIRECT("FebR!$A$6:$ZZ$1048576"), MATCH(F$1, FebR!$6:$6, 0), FALSE), 0 ) + IFERROR( VLOOKUP($A31, INDIRECT("MarR!$A$6:$ZZ$1048576"), MATCH(F$1, MarR!$6:$6, 0), FALSE), 0 ) + IFERROR( VLOOKUP($A31, INDIRECT("AbrR!$A$6:$ZZ$1048576"), MATCH(F$1, AbrR!$6:$6, 0), FALSE), 0 ) + IFERROR( VLOOKUP($A31, INDIRECT("MayR!$A$6:$ZZ$1048576"), MATCH(F$1, MayR!$6:$6, 0), FALSE), 0 ) + IFERROR( VLOOKUP($A31, INDIRECT("JunR!$A$6:$ZZ$1048576"), MATCH(F$1, JunR!$6:$6, 0), FALSE), 0 ) + IFERROR( VLOOKUP($A31, INDIRECT("JulR!$A$6:$ZZ$1048576"), MATCH(F$1, JulR!$6:$6, 0), FALSE), 0 ) + IFERROR( VLOOKUP($A31, INDIRECT("AgoR!$A$6:$ZZ$1048576"), MATCH(F$1, AgoR!$6:$6, 0), FALSE), 0 ) + IFERROR( VLOOKUP($A31, INDIRECT("SepR!$A$6:$ZZ$1048576"), MATCH(F$1, SepR!$6:$6, 0), FALSE), 0 ) + IFERROR( VLOOKUP($A31, INDIRECT("OctR!$A$6:$ZZ$1048576"), MATCH(F$1, OctR!$6:$6, 0), FALSE), 0 ) + IFERROR( VLOOKUP($A31, INDIRECT("NovR!$A$6:$ZZ$1048576"), MATCH(F$1, NovR!$6:$6, 0), FALSE), 0 ) + IFERROR( VLOOKUP($A31, INDIRECT("DicR!$A$6:$ZZ$1048576"), MATCH(F$1, DicR!$6:$6, 0), FALSE), 0 ) )} -> 0 | G31: {=SUM( IFERROR( VLOOKUP($A31, INDIRECT("EneR!$A$6:$ZZ$1048576"), MATCH(G$1, EneR!$6:$6, 0), FALSE), 0 ) + IFERROR( VLOOKUP($A31, INDIRECT("FebR!$A$6:$ZZ$1048576"), MATCH(G$1, FebR!$6:$6, 0), FALSE), 0 ) + IFERROR( VLOOKUP($A31, INDIRECT("MarR!$A$6:$ZZ$1048576"), MATCH(G$1, MarR!$6:$6, 0), FALSE), 0 ) + IFERROR( VLOOKUP($A31, INDIRECT("AbrR!$A$6:$ZZ$1048576"), MATCH(G$1, AbrR!$6:$6, 0), FALSE), 0 ) + IFERROR( VLOOKUP($A31, INDIRECT("MayR!$A$6:$ZZ$1048576"), MATCH(G$1, MayR!$6:$6, 0), FALSE), 0 ) + IFERROR( VLOOKUP($A31, INDIRECT("JunR!$A$6:$ZZ$1048576"), MATCH(G$1, JunR!$6:$6, 0), FALSE), 0 ) + IFERROR( VLOOKUP($A31, INDIRECT("JulR!$A$6:$ZZ$1048576"), MATCH(G$1, JulR!$6:$6, 0), FALSE), 0 ) + IFERROR( VLOOKUP($A31, INDIRECT("AgoR!$A$6:$ZZ$1048576"), MATCH(G$1, AgoR!$6:$6, 0), FALSE), 0 ) + IFERROR( VLOOKUP($A31, INDIRECT("SepR!$A$6:$ZZ$1048576"), MATCH(G$1, SepR!$6:$6, 0), FALSE), 0 ) + IFERROR( VLOOKUP($A31, INDIRECT("OctR!$A$6:$ZZ$1048576"), MATCH(G$1, OctR!$6:$6, 0), FALSE), 0 ) + IFERROR( VLOOKUP($A31, INDIRECT("NovR!$A$6:$ZZ$1048576"), MATCH(G$1, NovR!$6:$6, 0), FALSE), 0 ) + IFERROR( VLOOKUP($A31, INDIRECT("DicR!$A$6:$ZZ$1048576"), MATCH(G$1, DicR!$6:$6, 0), FALSE), 0 ) )} -> 0 | H31: {=SUM( IFERROR( VLOOKUP($A31, INDIRECT("EneR!$A$6:$ZZ$1048576"), MATCH(H$1, EneR!$6:$6, 0), FALSE), 0 ) + IFERROR( VLOOKUP($A31, INDIRECT("FebR!$A$6:$ZZ$1048576"), MATCH(H$1, FebR!$6:$6, 0), FALSE), 0 ) + IFERROR( VLOOKUP($A31, INDIRECT("MarR!$A$6:$ZZ$1048576"), MATCH(H$1, MarR!$6:$6, 0), FALSE), 0 ) + IFERROR( VLOOKUP($A31, INDIRECT("AbrR!$A$6:$ZZ$1048576"), MATCH(H$1, AbrR!$6:$6, 0), FALSE), 0 ) + IFERROR( VLOOKUP($A31, INDIRECT("MayR!$A$6:$ZZ$1048576"), MATCH(H$1, MayR!$6:$6, 0), FALSE), 0 ) + IFERROR( VLOOKUP($A31, INDIRECT("JunR!$A$6:$ZZ$1048576"), MATCH(H$1, JunR!$6:$6, 0), FALSE), 0 ) + IFERROR( VLOOKUP($A31, INDIRECT("JulR!$A$6:$ZZ$1048576"), MATCH(H$1, JulR!$6:$6, 0), FALSE), 0 ) + IFERROR( VLOOKUP($A31, INDIRECT("AgoR!$A$6:$ZZ$1048576"), MATCH(H$1, AgoR!$6:$6, 0), FALSE), 0 ) + IFERROR( VLOOKUP($A31, INDIRECT("SepR!$A$6:$ZZ$1048576"), MATCH(H$1, SepR!$6:$6, 0), FALSE), 0 ) + IFERROR( VLOOKUP($A31, INDIRECT("OctR!$A$6:$ZZ$1048576"), MATCH(H$1, OctR!$6:$6, 0), FALSE), 0 ) + IFERROR( VLOOKUP($A31, INDIRECT("NovR!$A$6:$ZZ$1048576"), MATCH(H$1, NovR!$6:$6, 0), FALSE), 0 ) + IFERROR( VLOOKUP($A31, INDIRECT("DicR!$A$6:$ZZ$1048576"), MATCH(H$1, DicR!$6:$6, 0), FALSE), 0 ) )} -> 0 | I31: {=SUM( IFERROR( VLOOKUP($A31, INDIRECT("EneR!$A$6:$ZZ$1048576"), MATCH(I$1, EneR!$6:$6, 0), FALSE), 0 ) + IFERROR( VLOOKUP($A31, INDIRECT("FebR!$A$6:$ZZ$1048576"), MATCH(I$1, FebR!$6:$6, 0), FALSE), 0 ) + IFERROR( VLOOKUP($A31, INDIRECT("MarR!$A$6:$ZZ$1048576"), MATCH(I$1, MarR!$6:$6, 0), FALSE), 0 ) + IFERROR( VLOOKUP($A31, INDIRECT("AbrR!$A$6:$ZZ$1048576"), MATCH(I$1, AbrR!$6:$6, 0), FALSE), 0 ) + IFERROR( VLOOKUP($A31, INDIRECT("MayR!$A$6:$ZZ$1048576"), MATCH(I$1, MayR!$6:$6, 0), FALSE), 0 ) + IFERROR( VLOOKUP($A31, INDIRECT("JunR!$A$6:$ZZ$1048576"), MATCH(I$1, JunR!$6:$6, 0), FALSE), 0 ) + IFERROR( VLOOKUP($A31, INDIRECT("JulR!$A$6:$ZZ$1048576"), MATCH(I$1, JulR!$6:$6, 0), FALSE), 0 ) + IFERROR( VLOOKUP($A31, INDIRECT("AgoR!$A$6:$ZZ$1048576"), MATCH(I$1, AgoR!$6:$6, 0), FALSE), 0 ) + IFERROR( VLOOKUP($A31, INDIRECT("SepR!$A$6:$ZZ$1048576"), MATCH(I$1, SepR!$6:$6, 0), FALSE), 0 ) + IFERROR( VLOOKUP($A31, INDIRECT("OctR!$A$6:$ZZ$1048576"), MATCH(I$1, OctR!$6:$6, 0), FALSE), 0 ) + IFERROR( VLOOKUP($A31, INDIRECT("NovR!$A$6:$ZZ$1048576"), MATCH(I$1, NovR!$6:$6, 0), FALSE), 0 ) + IFERROR( VLOOKUP($A31, INDIRECT("DicR!$A$6:$ZZ$1048576"), MATCH(I$1, DicR!$6:$6, 0), FALSE), 0 ) )} -> 0 | J31: {=SUM( IFERROR( VLOOKUP($A31, INDIRECT("EneR!$A$6:$ZZ$1048576"), MATCH(J$1, EneR!$6:$6, 0), FALSE), 0 ) + IFERROR( VLOOKUP($A31, INDIRECT("FebR!$A$6:$ZZ$1048576"), MATCH(J$1, FebR!$6:$6, 0), FALSE), 0 ) + IFERROR( VLOOKUP($A31, INDIRECT("MarR!$A$6:$ZZ$1048576"), MATCH(J$1, MarR!$6:$6, 0), FALSE), 0 ) + IFERROR( VLOOKUP($A31, INDIRECT("AbrR!$A$6:$ZZ$1048576"), MATCH(J$1, AbrR!$6:$6, 0), FALSE), 0 ) + IFERROR( VLOOKUP($A31, INDIRECT("MayR!$A$6:$ZZ$1048576"), MATCH(J$1, MayR!$6:$6, 0), FALSE), 0 ) + IFERROR( VLOOKUP($A31, INDIRECT("JunR!$A$6:$ZZ$1048576"), MATCH(J$1, JunR!$6:$6, 0), FALSE), 0 ) + IFERROR( VLOOKUP($A31, INDIRECT("JulR!$A$6:$ZZ$1048576"), MATCH(J$1, JulR!$6:$6, 0), FALSE), 0 ) + IFERROR( VLOOKUP($A31, INDIRECT("AgoR!$A$6:$ZZ$1048576"), MATCH(J$1, AgoR!$6:$6, 0), FALSE), 0 ) + IFERROR( VLOOKUP($A31, INDIRECT("SepR!$A$6:$ZZ$1048576"), MATCH(J$1, SepR!$6:$6, 0), FALSE), 0 ) + IFERROR( VLOOKUP($A31, INDIRECT("OctR!$A$6:$ZZ$1048576"), MATCH(J$1, OctR!$6:$6, 0), FALSE), 0 ) + IFERROR( VLOOKUP($A31, INDIRECT("NovR!$A$6:$ZZ$1048576"), MATCH(J$1, NovR!$6:$6, 0), FALSE), 0 ) + IFERROR( VLOOKUP($A31, INDIRECT("DicR!$A$6:$ZZ$1048576"), MATCH(J$1, DicR!$6:$6, 0), FALSE), 0 ) )} -> 0 | K31: {=SUM( IFERROR( VLOOKUP($A31, INDIRECT("EneR!$A$6:$ZZ$1048576"), MATCH(K$1, EneR!$6:$6, 0), FALSE), 0 ) + IFERROR( VLOOKUP($A31, INDIRECT("FebR!$A$6:$ZZ$1048576"), MATCH(K$1, FebR!$6:$6, 0), FALSE), 0 ) + IFERROR( VLOOKUP($A31, INDIRECT("MarR!$A$6:$ZZ$1048576"), MATCH(K$1, MarR!$6:$6, 0), FALSE), 0 ) + IFERROR( VLOOKUP($A31, INDIRECT("AbrR!$A$6:$ZZ$1048576"), MATCH(K$1, AbrR!$6:$6, 0), FALSE), 0 ) + IFERROR( VLOOKUP($A31, INDIRECT("MayR!$A$6:$ZZ$1048576"), MATCH(K$1, MayR!$6:$6, 0), FALSE), 0 ) + IFERROR( VLOOKUP($A31, INDIRECT("JunR!$A$6:$ZZ$1048576"), MATCH(K$1, JunR!$6:$6, 0), FALSE), 0 ) + IFERROR( VLOOKUP($A31, INDIRECT("JulR!$A$6:$ZZ$1048576"), MATCH(K$1, JulR!$6:$6, 0), FALSE), 0 ) + IFERROR( VLOOKUP($A31, INDIRECT("AgoR!$A$6:$ZZ$1048576"), MATCH(K$1, AgoR!$6:$6, 0), FALSE), 0 ) + IFERROR( VLOOKUP($A31, INDIRECT("SepR!$A$6:$ZZ$1048576"), MATCH(K$1, SepR!$6:$6, 0), FALSE), 0 ) + IFERROR( VLOOKUP($A31, INDIRECT("OctR!$A$6:$ZZ$1048576"), MATCH(K$1, OctR!$6:$6, 0), FALSE), 0 ) + IFERROR( VLOOKUP($A31, INDIRECT("NovR!$A$6:$ZZ$1048576"), MATCH(K$1, NovR!$6:$6, 0), FALSE), 0 ) + IFERROR( VLOOKUP($A31, INDIRECT("DicR!$A$6:$ZZ$1048576"), MATCH(K$1, DicR!$6:$6, 0), FALSE), 0 ) )} -> 0 | ... AY31: {=SUM( IFERROR( VLOOKUP($A31, INDIRECT("EneR!$A$6:$ZZ$1048576"), MATCH(AY$1, EneR!$6:$6, 0), FALSE), 0 ) + IFERROR( VLOOKUP($A31, INDIRECT("FebR!$A$6:$ZZ$1048576"), MATCH(AY$1, FebR!$6:$6, 0), FALSE), 0 ) + IFERROR( VLOOKUP($A31, INDIRECT("MarR!$A$6:$ZZ$1048576"), MATCH(AY$1, MarR!$6:$6, 0), FALSE), 0 ) + IFERROR( VLOOKUP($A31, INDIRECT("AbrR!$A$6:$ZZ$1048576"), MATCH(AY$1, AbrR!$6:$6, 0), FALSE), 0 ) + IFERROR( VLOOKUP($A31, INDIRECT("MayR!$A$6:$ZZ$1048576"), MATCH(AY$1, MayR!$6:$6, 0), FALSE), 0 ) + IFERROR( VLOOKUP($A31, INDIRECT("JunR!$A$6:$ZZ$1048576"), MATCH(AY$1, JunR!$6:$6, 0), FALSE), 0 ) + IFERROR( VLOOKUP($A31, INDIRECT("JulR!$A$6:$ZZ$1048576"), MATCH(AY$1, JulR!$6:$6, 0), FALSE), 0 ) + IFERROR( VLOOKUP($A31, INDIRECT("AgoR!$A$6:$ZZ$1048576"), MATCH(AY$1, AgoR!$6:$6, 0), FALSE), 0 ) + IFERROR( VLOOKUP($A31, INDIRECT("SepR!$A$6:$ZZ$1048576"), MATCH(AY$1, SepR!$6:$6, 0), FALSE), 0 ) + IFERROR( VLOOKUP($A31, INDIRECT("OctR!$A$6:$ZZ$1048576"), MATCH(AY$1, OctR!$6:$6, 0), FALSE), 0 ) + IFERROR( VLOOKUP($A31, INDIRECT("NovR!$A$6:$ZZ$1048576"), MATCH(AY$1, NovR!$6:$6, 0), FALSE), 0 ) + IFERROR( VLOOKUP($A31, INDIRECT("DicR!$A$6:$ZZ$1048576"), MATCH(AY$1, DicR!$6:$6, 0), FALSE), 0 ) )} -> 0
A32: =Menus!R24 | B32: =IFERROR(SUM(D32:AR32),"") -> 0 | C32: =IFERROR(INDEX($D$1:$AQ$69, MATCH($A32, $A$1:$A$109, 0), MATCH(C$1, $D$1:AZ$1, 0)), "") | D32: {=SUM( IFERROR( VLOOKUP($A32, INDIRECT("EneR!$A$6:$ZZ$1048576"), MATCH(D$1, EneR!$6:$6, 0), FALSE), 0 ) + IFERROR( VLOOKUP($A32, INDIRECT("FebR!$A$6:$ZZ$1048576"), MATCH(D$1, FebR!$6:$6, 0), FALSE), 0 ) + IFERROR( VLOOKUP($A32, INDIRECT("MarR!$A$6:$ZZ$1048576"), MATCH(D$1, MarR!$6:$6, 0), FALSE), 0 ) + IFERROR( VLOOKUP($A32, INDIRECT("AbrR!$A$6:$ZZ$1048576"), MATCH(D$1, AbrR!$6:$6, 0), FALSE), 0 ) + IFERROR( VLOOKUP($A32, INDIRECT("MayR!$A$6:$ZZ$1048576"), MATCH(D$1, MayR!$6:$6, 0), FALSE), 0 ) + IFERROR( VLOOKUP($A32, INDIRECT("JunR!$A$6:$ZZ$1048576"), MATCH(D$1, JunR!$6:$6, 0), FALSE), 0 ) + IFERROR( VLOOKUP($A32, INDIRECT("JulR!$A$6:$ZZ$1048576"), MATCH(D$1, JulR!$6:$6, 0), FALSE), 0 ) + IFERROR( VLOOKUP($A32, INDIRECT("AgoR!$A$6:$ZZ$1048576"), MATCH(D$1, AgoR!$6:$6, 0), FALSE), 0 ) + IFERROR( VLOOKUP($A32, INDIRECT("SepR!$A$6:$ZZ$1048576"), MATCH(D$1, SepR!$6:$6, 0), FALSE), 0 ) + IFERROR( VLOOKUP($A32, INDIRECT("OctR!$A$6:$ZZ$1048576"), MATCH(D$1, OctR!$6:$6, 0), FALSE), 0 ) + IFERROR( VLOOKUP($A32, INDIRECT("NovR!$A$6:$ZZ$1048576"), MATCH(D$1, NovR!$6:$6, 0), FALSE), 0 ) + IFERROR( VLOOKUP($A32, INDIRECT("DicR!$A$6:$ZZ$1048576"), MATCH(D$1, DicR!$6:$6, 0), FALSE), 0 ) )} -> 0 | E32: {=SUM( IFERROR( VLOOKUP($A32, INDIRECT("EneR!$A$6:$ZZ$1048576"), MATCH(E$1, EneR!$6:$6, 0), FALSE), 0 ) + IFERROR( VLOOKUP($A32, INDIRECT("FebR!$A$6:$ZZ$1048576"), MATCH(E$1, FebR!$6:$6, 0), FALSE), 0 ) + IFERROR( VLOOKUP($A32, INDIRECT("MarR!$A$6:$ZZ$1048576"), MATCH(E$1, MarR!$6:$6, 0), FALSE), 0 ) + IFERROR( VLOOKUP($A32, INDIRECT("AbrR!$A$6:$ZZ$1048576"), MATCH(E$1, AbrR!$6:$6, 0), FALSE), 0 ) + IFERROR( VLOOKUP($A32, INDIRECT("MayR!$A$6:$ZZ$1048576"), MATCH(E$1, MayR!$6:$6, 0), FALSE), 0 ) + IFERROR( VLOOKUP($A32, INDIRECT("JunR!$A$6:$ZZ$1048576"), MATCH(E$1, JunR!$6:$6, 0), FALSE), 0 ) + IFERROR( VLOOKUP($A32, INDIRECT("JulR!$A$6:$ZZ$1048576"), MATCH(E$1, JulR!$6:$6, 0), FALSE), 0 ) + IFERROR( VLOOKUP($A32, INDIRECT("AgoR!$A$6:$ZZ$1048576"), MATCH(E$1, AgoR!$6:$6, 0), FALSE), 0 ) + IFERROR( VLOOKUP($A32, INDIRECT("SepR!$A$6:$ZZ$1048576"), MATCH(E$1, SepR!$6:$6, 0), FALSE), 0 ) + IFERROR( VLOOKUP($A32, INDIRECT("OctR!$A$6:$ZZ$1048576"), MATCH(E$1, OctR!$6:$6, 0), FALSE), 0 ) + IFERROR( VLOOKUP($A32, INDIRECT("NovR!$A$6:$ZZ$1048576"), MATCH(E$1, NovR!$6:$6, 0), FALSE), 0 ) + IFERROR( VLOOKUP($A32, INDIRECT("DicR!$A$6:$ZZ$1048576"), MATCH(E$1, DicR!$6:$6, 0), FALSE), 0 ) )} -> 0 | F32: {=SUM( IFERROR( VLOOKUP($A32, INDIRECT("EneR!$A$6:$ZZ$1048576"), MATCH(F$1, EneR!$6:$6, 0), FALSE), 0 ) + IFERROR( VLOOKUP($A32, INDIRECT("FebR!$A$6:$ZZ$1048576"), MATCH(F$1, FebR!$6:$6, 0), FALSE), 0 ) + IFERROR( VLOOKUP($A32, INDIRECT("MarR!$A$6:$ZZ$1048576"), MATCH(F$1, MarR!$6:$6, 0), FALSE), 0 ) + IFERROR( VLOOKUP($A32, INDIRECT("AbrR!$A$6:$ZZ$1048576"), MATCH(F$1, AbrR!$6:$6, 0), FALSE), 0 ) + IFERROR( VLOOKUP($A32, INDIRECT("MayR!$A$6:$ZZ$1048576"), MATCH(F$1, MayR!$6:$6, 0), FALSE), 0 ) + IFERROR( VLOOKUP($A32, INDIRECT("JunR!$A$6:$ZZ$1048576"), MATCH(F$1, JunR!$6:$6, 0), FALSE), 0 ) + IFERROR( VLOOKUP($A32, INDIRECT("JulR!$A$6:$ZZ$1048576"), MATCH(F$1, JulR!$6:$6, 0), FALSE), 0 ) + IFERROR( VLOOKUP($A32, INDIRECT("AgoR!$A$6:$ZZ$1048576"), MATCH(F$1, AgoR!$6:$6, 0), FALSE), 0 ) + IFERROR( VLOOKUP($A32, INDIRECT("SepR!$A$6:$ZZ$1048576"), MATCH(F$1, SepR!$6:$6, 0), FALSE), 0 ) + IFERROR( VLOOKUP($A32, INDIRECT("OctR!$A$6:$ZZ$1048576"), MATCH(F$1, OctR!$6:$6, 0), FALSE), 0 ) + IFERROR( VLOOKUP($A32, INDIRECT("NovR!$A$6:$ZZ$1048576"), MATCH(F$1, NovR!$6:$6, 0), FALSE), 0 ) + IFERROR( VLOOKUP($A32, INDIRECT("DicR!$A$6:$ZZ$1048576"), MATCH(F$1, DicR!$6:$6, 0), FALSE), 0 ) )} -> 0 | G32: {=SUM( IFERROR( VLOOKUP($A32, INDIRECT("EneR!$A$6:$ZZ$1048576"), MATCH(G$1, EneR!$6:$6, 0), FALSE), 0 ) + IFERROR( VLOOKUP($A32, INDIRECT("FebR!$A$6:$ZZ$1048576"), MATCH(G$1, FebR!$6:$6, 0), FALSE), 0 ) + IFERROR( VLOOKUP($A32, INDIRECT("MarR!$A$6:$ZZ$1048576"), MATCH(G$1, MarR!$6:$6, 0), FALSE), 0 ) + IFERROR( VLOOKUP($A32, INDIRECT("AbrR!$A$6:$ZZ$1048576"), MATCH(G$1, AbrR!$6:$6, 0), FALSE), 0 ) + IFERROR( VLOOKUP($A32, INDIRECT("MayR!$A$6:$ZZ$1048576"), MATCH(G$1, MayR!$6:$6, 0), FALSE), 0 ) + IFERROR( VLOOKUP($A32, INDIRECT("JunR!$A$6:$ZZ$1048576"), MATCH(G$1, JunR!$6:$6, 0), FALSE), 0 ) + IFERROR( VLOOKUP($A32, INDIRECT("JulR!$A$6:$ZZ$1048576"), MATCH(G$1, JulR!$6:$6, 0), FALSE), 0 ) + IFERROR( VLOOKUP($A32, INDIRECT("AgoR!$A$6:$ZZ$1048576"), MATCH(G$1, AgoR!$6:$6, 0), FALSE), 0 ) + IFERROR( VLOOKUP($A32, INDIRECT("SepR!$A$6:$ZZ$1048576"), MATCH(G$1, SepR!$6:$6, 0), FALSE), 0 ) + IFERROR( VLOOKUP($A32, INDIRECT("OctR!$A$6:$ZZ$1048576"), MATCH(G$1, OctR!$6:$6, 0), FALSE), 0 ) + IFERROR( VLOOKUP($A32, INDIRECT("NovR!$A$6:$ZZ$1048576"), MATCH(G$1, NovR!$6:$6, 0), FALSE), 0 ) + IFERROR( VLOOKUP($A32, INDIRECT("DicR!$A$6:$ZZ$1048576"), MATCH(G$1, DicR!$6:$6, 0), FALSE), 0 ) )} -> 0 | H32: {=SUM( IFERROR( VLOOKUP($A32, INDIRECT("EneR!$A$6:$ZZ$1048576"), MATCH(H$1, EneR!$6:$6, 0), FALSE), 0 ) + IFERROR( VLOOKUP($A32, INDIRECT("FebR!$A$6:$ZZ$1048576"), MATCH(H$1, FebR!$6:$6, 0), FALSE), 0 ) + IFERROR( VLOOKUP($A32, INDIRECT("MarR!$A$6:$ZZ$1048576"), MATCH(H$1, MarR!$6:$6, 0), FALSE), 0 ) + IFERROR( VLOOKUP($A32, INDIRECT("AbrR!$A$6:$ZZ$1048576"), MATCH(H$1, AbrR!$6:$6, 0), FALSE), 0 ) + IFERROR( VLOOKUP($A32, INDIRECT("MayR!$A$6:$ZZ$1048576"), MATCH(H$1, MayR!$6:$6, 0), FALSE), 0 ) + IFERROR( VLOOKUP($A32, INDIRECT("JunR!$A$6:$ZZ$1048576"), MATCH(H$1, JunR!$6:$6, 0), FALSE), 0 ) + IFERROR( VLOOKUP($A32, INDIRECT("JulR!$A$6:$ZZ$1048576"), MATCH(H$1, JulR!$6:$6, 0), FALSE), 0 ) + IFERROR( VLOOKUP($A32, INDIRECT("AgoR!$A$6:$ZZ$1048576"), MATCH(H$1, AgoR!$6:$6, 0), FALSE), 0 ) + IFERROR( VLOOKUP($A32, INDIRECT("SepR!$A$6:$ZZ$1048576"), MATCH(H$1, SepR!$6:$6, 0), FALSE), 0 ) + IFERROR( VLOOKUP($A32, INDIRECT("OctR!$A$6:$ZZ$1048576"), MATCH(H$1, OctR!$6:$6, 0), FALSE), 0 ) + IFERROR( VLOOKUP($A32, INDIRECT("NovR!$A$6:$ZZ$1048576"), MATCH(H$1, NovR!$6:$6, 0), FALSE), 0 ) + IFERROR( VLOOKUP($A32, INDIRECT("DicR!$A$6:$ZZ$1048576"), MATCH(H$1, DicR!$6:$6, 0), FALSE), 0 ) )} -> 0 | I32: {=SUM( IFERROR( VLOOKUP($A32, INDIRECT("EneR!$A$6:$ZZ$1048576"), MATCH(I$1, EneR!$6:$6, 0), FALSE), 0 ) + IFERROR( VLOOKUP($A32, INDIRECT("FebR!$A$6:$ZZ$1048576"), MATCH(I$1, FebR!$6:$6, 0), FALSE), 0 ) + IFERROR( VLOOKUP($A32, INDIRECT("MarR!$A$6:$ZZ$1048576"), MATCH(I$1, MarR!$6:$6, 0), FALSE), 0 ) + IFERROR( VLOOKUP($A32, INDIRECT("AbrR!$A$6:$ZZ$1048576"), MATCH(I$1, AbrR!$6:$6, 0), FALSE), 0 ) + IFERROR( VLOOKUP($A32, INDIRECT("MayR!$A$6:$ZZ$1048576"), MATCH(I$1, MayR!$6:$6, 0), FALSE), 0 ) + IFERROR( VLOOKUP($A32, INDIRECT("JunR!$A$6:$ZZ$1048576"), MATCH(I$1, JunR!$6:$6, 0), FALSE), 0 ) + IFERROR( VLOOKUP($A32, INDIRECT("JulR!$A$6:$ZZ$1048576"), MATCH(I$1, JulR!$6:$6, 0), FALSE), 0 ) + IFERROR( VLOOKUP($A32, INDIRECT("AgoR!$A$6:$ZZ$1048576"), MATCH(I$1, AgoR!$6:$6, 0), FALSE), 0 ) + IFERROR( VLOOKUP($A32, INDIRECT("SepR!$A$6:$ZZ$1048576"), MATCH(I$1, SepR!$6:$6, 0), FALSE), 0 ) + IFERROR( VLOOKUP($A32, INDIRECT("OctR!$A$6:$ZZ$1048576"), MATCH(I$1, OctR!$6:$6, 0), FALSE), 0 ) + IFERROR( VLOOKUP($A32, INDIRECT("NovR!$A$6:$ZZ$1048576"), MATCH(I$1, NovR!$6:$6, 0), FALSE), 0 ) + IFERROR( VLOOKUP($A32, INDIRECT("DicR!$A$6:$ZZ$1048576"), MATCH(I$1, DicR!$6:$6, 0), FALSE), 0 ) )} -> 0 | J32: {=SUM( IFERROR( VLOOKUP($A32, INDIRECT("EneR!$A$6:$ZZ$1048576"), MATCH(J$1, EneR!$6:$6, 0), FALSE), 0 ) + IFERROR( VLOOKUP($A32, INDIRECT("FebR!$A$6:$ZZ$1048576"), MATCH(J$1, FebR!$6:$6, 0), FALSE), 0 ) + IFERROR( VLOOKUP($A32, INDIRECT("MarR!$A$6:$ZZ$1048576"), MATCH(J$1, MarR!$6:$6, 0), FALSE), 0 ) + IFERROR( VLOOKUP($A32, INDIRECT("AbrR!$A$6:$ZZ$1048576"), MATCH(J$1, AbrR!$6:$6, 0), FALSE), 0 ) + IFERROR( VLOOKUP($A32, INDIRECT("MayR!$A$6:$ZZ$1048576"), MATCH(J$1, MayR!$6:$6, 0), FALSE), 0 ) + IFERROR( VLOOKUP($A32, INDIRECT("JunR!$A$6:$ZZ$1048576"), MATCH(J$1, JunR!$6:$6, 0), FALSE), 0 ) + IFERROR( VLOOKUP($A32, INDIRECT("JulR!$A$6:$ZZ$1048576"), MATCH(J$1, JulR!$6:$6, 0), FALSE), 0 ) + IFERROR( VLOOKUP($A32, INDIRECT("AgoR!$A$6:$ZZ$1048576"), MATCH(J$1, AgoR!$6:$6, 0), FALSE), 0 ) + IFERROR( VLOOKUP($A32, INDIRECT("SepR!$A$6:$ZZ$1048576"), MATCH(J$1, SepR!$6:$6, 0), FALSE), 0 ) + IFERROR( VLOOKUP($A32, INDIRECT("OctR!$A$6:$ZZ$1048576"), MATCH(J$1, OctR!$6:$6, 0), FALSE), 0 ) + IFERROR( VLOOKUP($A32, INDIRECT("NovR!$A$6:$ZZ$1048576"), MATCH(J$1, NovR!$6:$6, 0), FALSE), 0 ) + IFERROR( VLOOKUP($A32, INDIRECT("DicR!$A$6:$ZZ$1048576"), MATCH(J$1, DicR!$6:$6, 0), FALSE), 0 ) )} -> 0 | K32: {=SUM( IFERROR( VLOOKUP($A32, INDIRECT("EneR!$A$6:$ZZ$1048576"), MATCH(K$1, EneR!$6:$6, 0), FALSE), 0 ) + IFERROR( VLOOKUP($A32, INDIRECT("FebR!$A$6:$ZZ$1048576"), MATCH(K$1, FebR!$6:$6, 0), FALSE), 0 ) + IFERROR( VLOOKUP($A32, INDIRECT("MarR!$A$6:$ZZ$1048576"), MATCH(K$1, MarR!$6:$6, 0), FALSE), 0 ) + IFERROR( VLOOKUP($A32, INDIRECT("AbrR!$A$6:$ZZ$1048576"), MATCH(K$1, AbrR!$6:$6, 0), FALSE), 0 ) + IFERROR( VLOOKUP($A32, INDIRECT("MayR!$A$6:$ZZ$1048576"), MATCH(K$1, MayR!$6:$6, 0), FALSE), 0 ) + IFERROR( VLOOKUP($A32, INDIRECT("JunR!$A$6:$ZZ$1048576"), MATCH(K$1, JunR!$6:$6, 0), FALSE), 0 ) + IFERROR( VLOOKUP($A32, INDIRECT("JulR!$A$6:$ZZ$1048576"), MATCH(K$1, JulR!$6:$6, 0), FALSE), 0 ) + IFERROR( VLOOKUP($A32, INDIRECT("AgoR!$A$6:$ZZ$1048576"), MATCH(K$1, AgoR!$6:$6, 0), FALSE), 0 ) + IFERROR( VLOOKUP($A32, INDIRECT("SepR!$A$6:$ZZ$1048576"), MATCH(K$1, SepR!$6:$6, 0), FALSE), 0 ) + IFERROR( VLOOKUP($A32, INDIRECT("OctR!$A$6:$ZZ$1048576"), MATCH(K$1, OctR!$6:$6, 0), FALSE), 0 ) + IFERROR( VLOOKUP($A32, INDIRECT("NovR!$A$6:$ZZ$1048576"), MATCH(K$1, NovR!$6:$6, 0), FALSE), 0 ) + IFERROR( VLOOKUP($A32, INDIRECT("DicR!$A$6:$ZZ$1048576"), MATCH(K$1, DicR!$6:$6, 0), FALSE), 0 ) )} -> 0 | ... AY32: {=SUM( IFERROR( VLOOKUP($A32, INDIRECT("EneR!$A$6:$ZZ$1048576"), MATCH(AY$1, EneR!$6:$6, 0), FALSE), 0 ) + IFERROR( VLOOKUP($A32, INDIRECT("FebR!$A$6:$ZZ$1048576"), MATCH(AY$1, FebR!$6:$6, 0), FALSE), 0 ) + IFERROR( VLOOKUP($A32, INDIRECT("MarR!$A$6:$ZZ$1048576"), MATCH(AY$1, MarR!$6:$6, 0), FALSE), 0 ) + IFERROR( VLOOKUP($A32, INDIRECT("AbrR!$A$6:$ZZ$1048576"), MATCH(AY$1, AbrR!$6:$6, 0), FALSE), 0 ) + IFERROR( VLOOKUP($A32, INDIRECT("MayR!$A$6:$ZZ$1048576"), MATCH(AY$1, MayR!$6:$6, 0), FALSE), 0 ) + IFERROR( VLOOKUP($A32, INDIRECT("JunR!$A$6:$ZZ$1048576"), MATCH(AY$1, JunR!$6:$6, 0), FALSE), 0 ) + IFERROR( VLOOKUP($A32, INDIRECT("JulR!$A$6:$ZZ$1048576"), MATCH(AY$1, JulR!$6:$6, 0), FALSE), 0 ) + IFERROR( VLOOKUP($A32, INDIRECT("AgoR!$A$6:$ZZ$1048576"), MATCH(AY$1, AgoR!$6:$6, 0), FALSE), 0 ) + IFERROR( VLOOKUP($A32, INDIRECT("SepR!$A$6:$ZZ$1048576"), MATCH(AY$1, SepR!$6:$6, 0), FALSE), 0 ) + IFERROR( VLOOKUP($A32, INDIRECT("OctR!$A$6:$ZZ$1048576"), MATCH(AY$1, OctR!$6:$6, 0), FALSE), 0 ) + IFERROR( VLOOKUP($A32, INDIRECT("NovR!$A$6:$ZZ$1048576"), MATCH(AY$1, NovR!$6:$6, 0), FALSE), 0 ) + IFERROR( VLOOKUP($A32, INDIRECT("DicR!$A$6:$ZZ$1048576"), MATCH(AY$1, DicR!$6:$6, 0), FALSE), 0 ) )} -> 0
